Workbook

Sheet MRA - Cassiterite - Tin
A1: Mineral accounts: Flow accounts: Cassiterite
B2: Physical accounts | L2: Monetary accounts | T2: Exchange rate | U2: ='Basic data - source records'!AF5 -> 614.29514 | V2: ='Basic data - source records'!AG5 -> 646.63597 | W2: ='Basic data - source records'!AH5 -> 681.86172 | X2: ='Basic data - source records'!AI5 -> 720.97511 | Y2: ='Basic data - source records'!AJ5 -> 788
C3: Source | D3: Units | E3: 2012 | F3: 2013 | G3: 2014 | H3: 2015 | I3: 2016 | J3: Notes | M3: Source | N3: Units | O3: 2012 | P3: 2013 | Q3: 2014 | R3: 2015 | S3: 2016 | T3: Units | U3: 2012 | V3: 2013 | W3: 2014 | X3: 2015 | Y3: 2016 | Z3: Notes
B4: Mining operations | L4: Mining operations | T4: Mining operations
B5: Tagged production | C5: ITRI | D5: tons | E5: ='Basic data - source records'!C5 -> 3670.5237 | F5: ='Basic data - source records'!D5 -> 6112.1432 | G5: ='Basic data - source records'!E5 -> 7137.4683 | H5: ='Basic data - source records'!F5 -> 4714.1224 | I5: ='Basic data - source records'!G5 -> 2024 | J5: Data verified by RMB | L5: Production | M5: ITRI | N5: tons | O5: =E5 -> 3670.5237 | P5: =F5 -> 6112.1432 | Q5: =G5 -> 7137.4683 | R5: =H5 -> 4714.1224 | S5: =I5 -> 2024 | T5: tons | U5: =O5 -> 3670.5237 | V5: =P5 -> 6112.1432 | W5: =Q5 -> 7137.4683 | X5: =R5 -> 4714.1224 | Y5: =S5 -> 2024 | Z5: From physical accounts
B6: Employment (part time) | C6: NISR: LFS | D6: people | L6: Average price | M6: Calc | N6: USD/ton | O6: ='Mining price data'!BO40 -> 9213.9125 | P6: ='Mining price data'!BP40 -> 10196.272 | Q6: ='Mining price data'!BQ40 -> 10101.396 | R6: ='Mining price data'!BR40 -> 7003.4075 | S6: ='Mining price data'!BS40 -> 7573.3436 | T6: Frw/ton | U6: =O6*U2 -> 5660061.7 | V6: =P6*V2 -> 6593276.1 | W6: =Q6*W2 -> 6887755.1 | X6: =R6*X2 -> 5049282.5 | Y6: =S6*Y2 -> 5967794.7 | Z6: Based on avg. of 5 transactions/month per major trader
B7: Employment (full time) | C7: NISR: IBES | D7: people | L7: Sales | M7: Calc | N7: USD | O7: =O6*O5 -> 33819884 | P7: =P6*P5 -> 62321073 | Q7: =Q6*Q5 -> 72098392 | R7: =R6*R5 -> 33014920 | S7: =S6*S5 -> 15328447 | T7: Frw: billion | U7: =O7*U$2/1000000000 -> 20.775391 | V7: =P7*V$2/1000000000 -> 40.299048 | W7: =Q7*W$2/1000000000 -> 49.161134 | X7: =R7*X$2/1000000000 -> 23.802936 | Y7: =S7*Y$2/1000000000 -> 12.078817 | Z7: Calculated
L8: Less: Intermediate consumption (payments to sub-contractors & direct costs to production) | M8: IBES | N8: USD | O8: =O$7*'IBES data'!$U7 -> 28602849 | P8: =P$7*'IBES data'!$U7 -> 52707461 | Q8: =Q$7*'IBES data'!$U7 -> 60976537 | R8: =R$7*'IBES data'!$U7 -> 27922058 | S8: =S$7*'IBES data'!$U7 -> 12963890 | T8: Frw: billion | U8: =O8*U$2/1000000000 -> 17.570591 | V8: =P8*V$2/1000000000 -> 34.08254 | W8: =Q8*W$2/1000000000 -> 41.577566 | X8: =R8*X$2/1000000000 -> 20.131109 | Y8: =S8*Y$2/1000000000 -> 10.215545 | Z8: Derived from IBES structure
B9: Change in inventory | C9: Calc | D9: tons | E9: =E5-E12 -> 0 | F9: =F5-F12 -> 0 | G9: =G5-G12 -> 0 | H9: =H5-H12 -> 0 | I9: =I5-I12 -> 0 | L9: Less: Other operating and overhead costs | M9: IBES | N9: USD | O9: =O$7*'IBES data'!$U8 -> 5224160.7 | P9: =P$7*'IBES data'!$U8 -> 9626741.9 | Q9: =Q$7*'IBES data'!$U8 -> 11137045 | R9: =R$7*'IBES data'!$U8 -> 5099817.8 | S9: =S$7*'IBES data'!$U8 -> 2367786.7 | T9: Frw: billion | U9: =O9*U$2/1000000000 -> 3.2091765 | V9: =P9*V$2/1000000000 -> 6.2249977 | W9: =Q9*W$2/1000000000 -> 7.5939249 | X9: =R9*X$2/1000000000 -> 3.6768417 | Y9: =S9*Y$2/1000000000 -> 1.8658159 | Z9: Derived from IBES structure
L10: Less: Consumption of capital (Deprc) | M10: IBES | N10: USD | O10: =O$7*'IBES data'!$U9 -> 575397.56 | P10: =P$7*'IBES data'!$U9 -> 1060305 | Q10: =Q$7*'IBES data'!$U9 -> 1226652.3 | R10: =R$7*'IBES data'!$U9 -> 561702.23 | S10: =S$7*'IBES data'!$U9 -> 260791.88 | T10: Frw: billion | U10: =O10*U$2/1000000000 -> 0.35346393 | V10: =P10*V$2/1000000000 -> 0.68563137 | W10: =Q10*W$2/1000000000 -> 0.83640725 | X10: =R10*X$2/1000000000 -> 0.40497333 | Y10: =S10*Y$2/1000000000 -> 0.205504 | Z10: Derived from IBES structure
B11: Trading operations | L11: Less: Opportunity cost of capital ("normal profit") | M11: Calc | N11: USD | O11: =O10*'Basic data - source records'!Y5*'Basic data - source records'!$AR$2 -> 650199.24 | P11: =P10*'Basic data - source records'!Z5*'Basic data - source records'!$AR$2 -> 1113320.3 | Q11: =Q10*'Basic data - source records'!AA5*'Basic data - source records'!$AR$2 -> 1312518 | R11: =R10*'Basic data - source records'!AB5*'Basic data - source records'!$AR$2 -> 589787.35 | S11: =S10*'Basic data - source records'!AC5*'Basic data - source records'!$AR$2 -> 273831.48 | T11: Frw: billion | U11: =O11*U$2/1000000000 -> 0.39941424 | V11: =P11*V$2/1000000000 -> 0.71991294 | W11: =Q11*W$2/1000000000 -> 0.89495576 | X11: =R11*X$2/1000000000 -> 0.425222 | Y11: =S11*Y$2/1000000000 -> 0.2157792 | Z11: Derived from IBES structure
B12: Tagged purchases | C12: ITRI | D12: tons | E12: ='Basic data - source records'!C5 -> 3670.5237 | F12: ='Basic data - source records'!D5 -> 6112.1432 | G12: ='Basic data - source records'!E5 -> 7137.4683 | H12: ='Basic data - source records'!F5 -> 4714.1224 | I12: ='Basic data - source records'!G5 -> 2024 | J12: Data verified by RMB
L13: Equal: Resource rent | M13: Calc | N13: USD | O13: =O7-(O8+O9+O10+O11) -> -1232722.2 | P13: =P7-(P8+P9+P10+P11) -> -2186755.5 | Q13: =Q7-(Q8+Q9+Q10+Q11) -> -2554360.4 | R13: =R7-(R8+R9+R10+R11) -> -1158445.4 | S13: =S7-(S8+S9+S10+S11) -> -537852.85 | T13: Frw: billion | U13: =O13*U$2/1000000000 -> -0.75725525 | V13: =P13*V$2/1000000000 -> -1.4140348 | W13: =Q13*W$2/1000000000 -> -1.7417206 | X13: =R13*X$2/1000000000 -> -0.83521028 | Y13: =S13*Y$2/1000000000 -> -0.42382805 | Z13: Calculated
B14: Less: Waste or losses during processing by traders | C14: Calc | D14: tons | E14: =E12-E16 -> -910.02411 | F14: =F12-F16 -> 1317.596 | G14: =G12-G16 -> 1232.2722 | H14: =H12-H16 -> 1508.9454 | I14: =I12-I16 -> -1264 | L14: Unit rent | M14: Calc | N14: USD/ton | O14: =O13/O5 -> -335.84368 | P14: =P13/P5 -> -357.77229 | Q14: =Q13/Q5 -> -357.88046 | R14: =R13/R5 -> -245.73935 | S14: =S13/S5 -> -265.73758 | T14: Frw/ton | U14: =O14*U2 -> -206307.14 | V14: =P14*V2 -> -231348.44 | W14: =Q14*W2 -> -244024.99 | X14: =R14*X2 -> -177171.96 | Y14: =S14*Y2 -> -209401.21 | Z14: Calculated
L15: Inventory or sundry changes (residual change) | M15: Calc | N15: USD | O15: =O20-O7 -> 11388016 | P15: =P20-P7 -> -10124278 | Q15: =Q20-Q7 -> -10610670 | R15: =R20-R7 -> -3732124.1 | S15: =S20-S7 -> 14419838 | T15: Frw: billion | U15: =O15*U$2/1000000000 -> 6.995603 | V15: =P15*V$2/1000000000 -> -6.5467223 | W15: =Q15*W$2/1000000000 -> -7.2350096 | X15: =R15*X$2/1000000000 -> -2.6907686 | Y15: =S15*Y$2/1000000000 -> 11.362832 | Z15: Calculated
B16: Equal: Processed and tagged production | C16: ITRI | D16: tons | E16: ='Basic data - source records'!C6 -> 4580.5478 | F16: ='Basic data - source records'!D6 -> 4794.5472 | G16: ='Basic data - source records'!E6 -> 5905.1961 | H16: ='Basic data - source records'!F6 -> 3205.177 | I16: ='Basic data - source records'!G6 -> 3288 | J16: Data verified by RMB | L16: Trading operations | T16: Trading operations
L17: Production (exports) | M17: RMB | N17: tons | O17: =E20 -> 4636.6403 | P17: =F20 -> 4895.2675 | Q17: =G20 -> 5953.7963 | R17: =H20 -> 3845.6561 | S17: =I20 -> 3549.915 | T17: tons | U17: =O17 -> 4636.6403 | V17: =P17 -> 4895.2675 | W17: =Q17 -> 5953.7963 | X17: =R17 -> 3845.6561 | Y17: =S17 -> 3549.915 | Z17: From physical accounts
B18: Change in inventory | C18: Calc | D18: tons | E18: =E16-E20 -> -56.09248 | F18: =F16-F20 -> -100.72027 | G18: =G16-G20 -> -48.60026 | H18: =H16-H20 -> -640.47913 | I18: =I16-I20 -> -261.91505 | L18: Average price | M18: Calc | N18: USD/ton | O18: =O19/O17 -> 11408.456 | P18: =P19/P17 -> 12476.229 | Q18: =Q19/Q17 -> 12083.99 | R18: =R19/R17 -> 8909.5964 | S18: =S19/S17 -> 9805.278 | T18: Frw/ton | U18: =O18*U2 -> 7008159 | V18: =P18*V2 -> 8067578.6 | W18: =Q18*W2 -> 8239610.4 | X18: =R18*X2 -> 6423597.3 | Y18: =S18*Y2 -> 7726559.1 | Z18: Calculated
L19: Sales (exports) | M19: RMB | N19: USD | O19: ='Basic data - source records'!R5 -> 52896906 | P19: ='Basic data - source records'!S5 -> 61074479 | Q19: ='Basic data - source records'!T5 -> 71945617 | R19: ='Basic data - source records'!U5 -> 34263244 | S19: ='Basic data - source records'!V5 -> 34807904 | T19: Frw: billion | U19: =O19*U$2/1000000000 -> 32.494313 | V19: =P19*V$2/1000000000 -> 39.492955 | W19: =Q19*W$2/1000000000 -> 49.056962 | X19: =R19*X$2/1000000000 -> 24.702946 | Y19: =S19*Y$2/1000000000 -> 27.428628 | Z19: Published data
B20: Equal: Marketed production (exports) | C20: RMB | D20: tons | E20: ='Basic data - source records'!J5 -> 4636.6403 | F20: ='Basic data - source records'!K5 -> 4895.2675 | G20: ='Basic data - source records'!L5 -> 5953.7963 | H20: ='Basic data - source records'!M5 -> 3845.6561 | I20: ='Basic data - source records'!N5 -> 3549.915 | J20: RMB & RNB | L20: Less: Purchase of raw material | M20: IBES | N20: USD | O20: =O$19*'IBES data'!$U31 -> 45207900 | P20: =P$19*'IBES data'!$U31 -> 52196795 | Q20: =Q$19*'IBES data'!$U31 -> 61487723 | R20: =R$19*'IBES data'!$U31 -> 29282796 | S20: =S$19*'IBES data'!$U31 -> 29748285 | T20: Frw: billion | U20: =O20*U$2/1000000000 -> 27.770994 | V20: =P20*V$2/1000000000 -> 33.752325 | W20: =Q20*W$2/1000000000 -> 41.926124 | X20: =R20*X$2/1000000000 -> 21.112167 | Y20: =S20*Y$2/1000000000 -> 23.441649 | Z20: Derived from IBES structure
L21: Less: Intermediate consumption | M21: IBES | N21: USD | O21: =O$19*'IBES data'!$U32 -> 0 | P21: =P$19*'IBES data'!$U32 -> 0 | Q21: =Q$19*'IBES data'!$U32 -> 0 | R21: =R$19*'IBES data'!$U32 -> 0 | S21: =S$19*'IBES data'!$U32 -> 0 | T21: Frw: billion | U21: =O21*U$2/1000000000 -> 0 | V21: =P21*V$2/1000000000 -> 0 | W21: =Q21*W$2/1000000000 -> 0 | X21: =R21*X$2/1000000000 -> 0 | Y21: =S21*Y$2/1000000000 -> 0 | Z21: Derived from IBES structure
L22: Less: Other operating and overhead costs | M22: IBES | N22: USD | O22: =O$19*'IBES data'!$U33 -> 8582741.2 | P22: =P$19*'IBES data'!$U33 -> 9909586.1 | Q22: =Q$19*'IBES data'!$U33 -> 11673473 | R22: =R$19*'IBES data'!$U33 -> 5559352.6 | S22: =S$19*'IBES data'!$U33 -> 5647725.9 | T22: Frw: billion | U22: =O22*U$2/1000000000 -> 5.2723362 | V22: =P22*V$2/1000000000 -> 6.4078948 | W22: =Q22*W$2/1000000000 -> 7.9596944 | X22: =R22*X$2/1000000000 -> 4.0081548 | Y22: =S22*Y$2/1000000000 -> 4.450408 | Z22: Derived from IBES structure
B23: Key to colour coding: | L23: Less: Consumption of capital (Deprc) | M23: IBES | N23: USD | O23: =O$19*'IBES data'!$U34 -> 484941.81 | P23: =P$19*'IBES data'!$U34 -> 559911.17 | Q23: =Q$19*'IBES data'!$U34 -> 659574.27 | R23: =R$19*'IBES data'!$U34 -> 314114.39 | S23: =S$19*'IBES data'!$U34 -> 319107.66 | T23: Frw: billion | U23: =O23*U$2/1000000000 -> 0.2978974 | V23: =P23*V$2/1000000000 -> 0.3620587 | W23: =Q23*W$2/1000000000 -> 0.44973844 | X23: =R23*X$2/1000000000 -> 0.22646866 | Y23: =S23*Y$2/1000000000 -> 0.25145684 | Z23: Derived from IBES structure
B24: High quality data - published | L24: Less: Opportunity cost of capital ("normal profit") | M24: Calc | N24: USD | O24: =O23*'Basic data - source records'!Y5*'Basic data - source records'!$AR$2 -> 547984.25 | P24: =P23*'Basic data - source records'!Z5*'Basic data - source records'!$AR$2 -> 587906.73 | Q24: =Q23*'Basic data - source records'!AA5*'Basic data - source records'!$AR$2 -> 705744.46 | R24: =R23*'Basic data - source records'!AB5*'Basic data - source records'!$AR$2 -> 329820.11 | S24: =S23*'Basic data - source records'!AC5*'Basic data - source records'!$AR$2 -> 335063.04 | T24: Frw: billion | U24: =O24*U$2/1000000000 -> 0.33662406 | V24: =P24*V$2/1000000000 -> 0.38016164 | W24: =Q24*W$2/1000000000 -> 0.48122013 | X24: =R24*X$2/1000000000 -> 0.23779209 | Y24: =S24*Y$2/1000000000 -> 0.26402968 | Z24: Derived from IBES structure
B25: High quality input - derived from IBES structure
B26: Good quality data - derived from hard data | L26: Equal: Resource rent | M26: Calc | N26: USD | O26: =O19-(O20+O21+O22+O23+O24) -> -1926661.3 | P26: =P19-(P20+P21+P22+P23+P24) -> -2179719.7 | Q26: =Q19-(Q20+Q21+Q22+Q23+Q24) -> -2580897.1 | R26: =R19-(R20+R21+R22+R23+R24) -> -1222839.2 | S26: =S19-(S20+S21+S22+S23+S24) -> -1242277.9 | T26: Frw: billion | U26: =O26*U$2/1000000000 -> -1.1835387 | V26: =P26*V$2/1000000000 -> -1.4094852 | W26: =Q26*W$2/1000000000 -> -1.7598149 | X26: =R26*X$2/1000000000 -> -0.88163665 | Y26: =S26*Y$2/1000000000 -> -0.97891498 | Z26: Calculated
B27: Results/outcomes - based on formulas | L27: Unit rent | M27: Calc | N27: USD/ton | O27: =O26/O17 -> -415.52961 | P27: =P26/P17 -> -445.27081 | Q27: =Q26/Q17 -> -433.48764 | R27: =R26/R17 -> -317.97935 | S27: =S26/S17 -> -349.94581 | T27: Frw/ton | U27: =O27*U2 -> -255257.82 | V27: =P27*V2 -> -287928.13 | W27: =Q27*W2 -> -295578.62 | X27: =R27*X2 -> -229255.2 | Y27: =S27*Y2 -> -275757.3 | Z27: Calculated
L28: Royalty payments | M28: Calc | N28: USD | O28: =0*O19 -> 0 | P28: =0.02*P19 -> 1221489.6 | Q28: =0.04*Q19 -> 2877824.7 | R28: =0.04*R19 -> 1370529.8 | S28: =0.04*S19 -> 1392316.2 | T28: Frw: billion | U28: =O28*U2/1000000000 -> 0 | V28: =P28*V2/1000000000 -> 0.7898591 | W28: =Q28*W2/1000000000 -> 1.9622785 | X28: =R28*X2/1000000000 -> 0.98811784 | Y28: =S28*Y2/1000000000 -> 1.0971451 | Z28: Calculated as 4% of sales
L30: operators
L31: vol | O31: =O5 -> 3670.5237 | P31: =P5 -> 6112.1432 | Q31: =Q5 -> 7137.4683 | R31: =R5 -> 4714.1224 | S31: =S5 -> 2024
L32: price | O32: 9549.7561 | P32: 10554.044 | Q32: 10459.276 | R32: 7249.1469 | S32: 7839.0812 | T32: =AVERAGE(O32:S32) -> 9130.2609 | W32: =S19+'MRA - Coltan - Tantalum'!S19+'MRA - Wolfram - Tungsten'!S19 -> 86424093
L33: sales | O33: =O31*O32 -> 35052606 | P33: =P31*P32 -> 64507828 | Q33: =Q31*Q32 -> 74652753 | R33: =R31*R32 -> 34173365 | S33: =S31*S32 -> 15866300
L34: cost | O34: =SUM(O8:O11) -> 35052606 | P34: =SUM(P8:P11) -> 64507828 | Q34: =SUM(Q8:Q11) -> 74652753 | R34: =SUM(R8:R11) -> 34173365 | S34: =SUM(S8:S11) -> 15866300
L35: rent | O35: =O33-O34 -> 0 | P35: =P33-P34 -> 0 | Q35: =Q33-Q34 -> 0 | R35: =R33-R34 -> 0 | S35: =S33-S34 -> 0
L37: new price | O37: =O32 -> 9549.7561 | P37: =P32 -> 10554.044 | Q37: =Q32 -> 10459.276 | R37: =R32 -> 7249.1469 | S37: =S32 -> 7839.0812
L38: old price | O38: =O6 -> 9213.9125 | P38: =P6 -> 10196.272 | Q38: =Q6 -> 10101.396 | R38: =R6 -> 7003.4075 | S38: =S6 -> 7573.3436
O39: =(O37-O38)/O38 -> 0.036449628 | P39: =(P37-P38)/P38 -> 0.035088541 | Q39: =(Q37-Q38)/Q38 -> 0.035428813 | R39: =(R37-R38)/R38 -> 0.035088541 | S39: =(S37-S38)/S38 -> 0.035088541 | T39: =AVERAGE(O39:S39) -> 0.035428813
L42: traders
L43: vol | O43: =O17 -> 4636.6403 | P43: =P17 -> 4895.2675 | Q43: =Q17 -> 5953.7963 | R43: =R17 -> 3845.6561 | S43: =S17 -> 3549.915
L44: price | O44: 11823.985 | P44: 12921.5 | Q44: 12517.478 | R44: 9227.5758 | S44: 10155.224 | T44: =AVERAGE(O44:S44) -> 11329.153
L45: sales | O45: =O43*O44 -> 54823568 | P45: =P43*P44 -> 63254199 | Q45: =Q43*Q44 -> 74526514 | R45: =R43*R44 -> 35486083 | S45: =S43*S44 -> 36050182
L46: cost | O46: =SUM(O20:O24) -> 54823568 | P46: =SUM(P20:P24) -> 63254199 | Q46: =SUM(Q20:Q24) -> 74526514 | R46: =SUM(R20:R24) -> 35486083 | S46: =SUM(S20:S24) -> 36050182
L47: rent | O47: =O45-O46 -> 0 | P47: =P45-P46 -> 0 | Q47: =Q45-Q46 -> 0 | R47: =R45-R46 -> 0 | S47: =S45-S46 -> 0
L49: new price | O49: =O44 -> 11823.985 | P49: =P44 -> 12921.5 | Q49: =Q44 -> 12517.478 | R49: =R44 -> 9227.5758 | S49: =S44 -> 10155.224
L50: old price | O50: =O18 -> 11408.456 | P50: =P18 -> 12476.229 | Q50: =Q18 -> 12083.99 | R50: =R18 -> 8909.5964 | S50: =S18 -> 9805.278
O51: =(O49-O50)/O50 -> 0.036422949 | P51: =(P49-P50)/P50 -> 0.035689535 | Q51: =(Q49-Q50)/Q50 -> 0.035872888 | R51: =(R49-R50)/R50 -> 0.035689535 | S51: =(S49-S50)/S50 -> 0.035689535 | T51: =AVERAGE(O51:S51) -> 0.035872888

Sheet MRA - Coltan - Tantalum
A1: Mineral accounts: Flow accounts: Coltan
B2: Physical accounts | L2: Monetary accounts | T2: Exchange rate | U2: ='Basic data - source records'!AF5 -> 614.29514 | V2: ='Basic data - source records'!AG5 -> 646.63597 | W2: ='Basic data - source records'!AH5 -> 681.86172 | X2: ='Basic data - source records'!AI5 -> 720.97511 | Y2: ='Basic data - source records'!AJ5 -> 788
C3: Source | D3: Units | E3: 2012 | F3: 2013 | G3: 2014 | H3: 2015 | I3: 2016 | J3: Notes | M3: Source | N3: Units | O3: 2012 | P3: 2013 | Q3: 2014 | R3: 2015 | S3: 2016 | T3: Units | U3: 2012 | V3: 2013 | W3: 2014 | X3: 2015 | Y3: 2016 | Z3: Notes
B4: Mining operations | L4: Mining operations | T4: Mining operations
B5: Tagged production | C5: ITRI | D5: tons | E5: ='Basic data - source records'!C7 -> 967.88761 | F5: ='Basic data - source records'!D7 -> 1924.3862 | G5: ='Basic data - source records'!E7 -> 2097.5135 | H5: ='Basic data - source records'!F7 -> 1332 | I5: ='Basic data - source records'!G7 -> 2553.6 | J5: Data verified by RMB | L5: Production | M5: ITRI | N5: tons | O5: =E5 -> 967.88761 | P5: =F5 -> 1924.3862 | Q5: =G5 -> 2097.5135 | R5: =H5 -> 1332 | S5: =I5 -> 2553.6 | T5: tons | U5: =O5 -> 967.88761 | V5: =P5 -> 1924.3862 | W5: =Q5 -> 2097.5135 | X5: =R5 -> 1332 | Y5: =S5 -> 2553.6 | Z5: From physical accounts
B6: Employment | C6: NISR: LFS | D6: people | L6: Average price | M6: Calc | N6: USD/ton | O6: ='Mining price data'!BO47 -> 49840 | P6: ='Mining price data'!BP47 -> 56141 | Q6: ='Mining price data'!BQ47 -> 44661.636 | R6: ='Mining price data'!BR47 -> 42300.37 | S6: ='Mining price data'!BS47 -> 35080.727 | T6: Frw/ton | U6: =O6*U2 -> 30616470 | V6: =P6*V2 -> 36302790 | W6: =Q6*W2 -> 30453060 | X6: =R6*X2 -> 30497514 | Y6: =S6*Y2 -> 27643613 | Z6: Based on avg. of 5 transactions/month per major trader
B7: Employment | C7: NISR: IBES | D7: people | L7: Sales | M7: Calc | N7: USD | O7: =O6*O5 -> 48239518 | P7: =P6*P5 -> 1.0803697e+08 | Q7: =Q6*Q5 -> 93678385 | R7: =R6*R5 -> 56344093 | S7: =S6*S5 -> 89582145 | T7: Frw: billion | U7: =O7*U$2/1000000000 -> 29.633302 | V7: =P7*V$2/1000000000 -> 69.860589 | W7: =Q7*W$2/1000000000 -> 63.875704 | X7: =R7*X$2/1000000000 -> 40.622689 | Y7: =S7*Y$2/1000000000 -> 70.59073 | Z7: Calculated
L8: Less: Intermediate consumption (payments to sub-contractors & direct costs to production) | M8: IBES | N8: USD | O8: =O$7*'IBES data'!$U7 -> 40798119 | P8: =P$7*'IBES data'!$U7 -> 91371247 | Q8: =Q$7*'IBES data'!$U7 -> 79227613 | R8: =R$7*'IBES data'!$U7 -> 47652487 | S8: =S$7*'IBES data'!$U7 -> 75763257 | T8: Frw: billion | U8: =O8*U$2/1000000000 -> 25.062086 | V8: =P8*V$2/1000000000 -> 59.083936 | W8: =Q8*W$2/1000000000 -> 54.022276 | X8: =R8*X$2/1000000000 -> 34.356257 | Y8: =S8*Y$2/1000000000 -> 59.701446 | Z8: Derived from IBES structure
B9: Change in inventory | C9: Calc | D9: tons | E9: =E5-E12 -> 0 | F9: =F5-F12 -> 0 | G9: =G5-G12 -> 0 | H9: =H5-H12 -> 0 | I9: =I5-I12 -> 0 | L9: Less: Other operating and overhead costs | M9: IBES | N9: USD | O9: =O$7*'IBES data'!$U8 -> 7451562.9 | P9: =P$7*'IBES data'!$U8 -> 16688480 | Q9: =Q$7*'IBES data'!$U8 -> 14470509 | R9: =R$7*'IBES data'!$U8 -> 8703477.4 | S9: =S$7*'IBES data'!$U8 -> 13837762 | T9: Frw: billion | U9: =O9*U$2/1000000000 -> 4.5774589 | V9: =P9*V$2/1000000000 -> 10.791372 | W9: =Q9*W$2/1000000000 -> 9.8668861 | X9: =R9*X$2/1000000000 -> 6.2749906 | Y9: =S9*Y$2/1000000000 -> 10.904157 | Z9: Derived from IBES structure
L10: Less: Consumption of capital (Deprc) | M10: IBES | N10: USD | O10: =O$7*'IBES data'!$U9 -> 820727.27 | P10: =P$7*'IBES data'!$U9 -> 1838096.4 | Q10: =Q$7*'IBES data'!$U9 -> 1593805.4 | R10: =R$7*'IBES data'!$U9 -> 958615.16 | S10: =S$7*'IBES data'!$U9 -> 1524113.7 | T10: Frw: billion | U10: =O10*U$2/1000000000 -> 0.50416877 | V10: =P10*V$2/1000000000 -> 1.1885792 | W10: =Q10*W$2/1000000000 -> 1.0867549 | X10: =R10*X$2/1000000000 -> 0.69113767 | Y10: =S10*Y$2/1000000000 -> 1.2010016 | Z10: Derived from IBES structure
B11: Trading operations | L11: Less: Opportunity cost of capital ("normal profit") | M11: Calc | N11: USD | O11: =O10*'Basic data - source records'!Y5*'Basic data - source records'!$AR$2 -> 927421.81 | P11: =P10*'Basic data - source records'!Z5*'Basic data - source records'!$AR$2 -> 1930001.2 | Q11: =Q10*'Basic data - source records'!AA5*'Basic data - source records'!$AR$2 -> 1705371.8 | R11: =R10*'Basic data - source records'!AB5*'Basic data - source records'!$AR$2 -> 1006545.9 | S11: =S10*'Basic data - source records'!AC5*'Basic data - source records'!$AR$2 -> 1600319.4 | T11: Frw: billion | U11: =O11*U$2/1000000000 -> 0.56971071 | V11: =P11*V$2/1000000000 -> 1.2480082 | W11: =Q11*W$2/1000000000 -> 1.1628277 | X11: =R11*X$2/1000000000 -> 0.72569456 | Y11: =S11*Y$2/1000000000 -> 1.2610517 | Z11: Derived from IBES structure
B12: Tagged purchases | C12: ITRI | D12: tons | E12: ='Basic data - source records'!C7 -> 967.88761 | F12: ='Basic data - source records'!D7 -> 1924.3862 | G12: ='Basic data - source records'!E7 -> 2097.5135 | H12: ='Basic data - source records'!F7 -> 1332 | I12: ='Basic data - source records'!G7 -> 2553.6 | J12: Data verified by RMB
L13: Equal: Resource rent | M13: Calc | N13: USD | O13: =O7-(O8+O9+O10+O11) -> -1758312.5 | P13: =P7-(P8+P9+P10+P11) -> -3790859.5 | Q13: =Q7-(Q8+Q9+Q10+Q11) -> -3318913.9 | R13: =R7-(R8+R9+R10+R11) -> -1977032 | S13: =S7-(S8+S9+S10+S11) -> -3143306.8 | T13: Frw: billion | U13: =O13*U$2/1000000000 -> -1.0801228 | V13: =P13*V$2/1000000000 -> -2.4513061 | W13: =Q13*W$2/1000000000 -> -2.2630404 | X13: =R13*X$2/1000000000 -> -1.4253909 | Y13: =S13*Y$2/1000000000 -> -2.4769257 | Z13: Calculated
B14: Less: Waste or losses during processing by traders | C14: Calc | D14: tons | E14: =E12-E16 -> 25.639905 | F14: =F12-F16 -> -122.37527 | G14: =G12-G16 -> -187.39354 | H14: =H12-H16 -> -258 | I14: =I12-I16 -> 1377.6 | L14: Unit rent | M14: Calc | N14: USD/ton | O14: =O13/O5 -> -1816.6495 | P14: =P13/P5 -> -1969.9058 | Q14: =Q13/Q5 -> -1582.3087 | R14: =R13/R5 -> -1484.2583 | S14: =S13/S5 -> -1230.9315 | T14: Frw/ton | U14: =O14*U2 -> -1115958.9 | V14: =P14*V2 -> -1273811.9 | W14: =Q14*W2 -> -1078915.8 | X14: =R14*X2 -> -1070113.3 | Y14: =S14*Y2 -> -969974.05 | Z14: Calculated
L15: Inventory or sundry changes (residual change) | M15: Calc | N15: USD | O15: =O20-O7 -> 399510.88 | P15: =P20-P7 -> 6973543.1 | Q15: =Q20-Q7 -> -4128747.9 | R15: =R20-R7 -> 233461.36 | S15: =S20-S7 -> -55616543 | T15: Frw: billion | U15: =O15*U$2/1000000000 -> 0.24541759 | V15: =P15*V$2/1000000000 -> 4.5093439 | W15: =Q15*W$2/1000000000 -> -2.8152351 | X15: =R15*X$2/1000000000 -> 0.16831983 | Y15: =S15*Y$2/1000000000 -> -43.825836 | Z15: Calculated
B16: Equal: Processed and tagged production | C16: ITRI | D16: tons | E16: ='Basic data - source records'!C8 -> 942.2477 | F16: ='Basic data - source records'!D8 -> 2046.7615 | G16: ='Basic data - source records'!E8 -> 2284.907 | H16: ='Basic data - source records'!F8 -> 1590 | I16: ='Basic data - source records'!G8 -> 1176 | J16: Data verified by RMB | L16: Trading operations | T16: Trading operations
L17: Production (exports) | M17: RMB | N17: tons | O17: =E20 -> 1144.6847 | P17: =F20 -> 2466.0237 | Q17: =G20 -> 2302.5189 | R17: =H20 -> 1651.7113 | S17: =I20 -> 1269.9392 | T17: tons | U17: =O17 -> 1144.6847 | V17: =P17 -> 2466.0237 | W17: =Q17 -> 2302.5189 | X17: =R17 -> 1651.7113 | Y17: =S17 -> 1269.9392 | Z17: From physical accounts
B18: Change in inventory | C18: Calc | D18: tons | E18: =E16-E20 -> -202.437 | F18: =F16-F20 -> -419.2622 | G18: =G16-G20 -> -17.61184 | H18: =H16-H20 -> -61.71126 | I18: =I16-I20 -> -93.9392 | L18: Average price | M18: Calc | N18: USD/ton | O18: =O19/O17 -> 49718.149 | P18: =P19/P17 -> 54570.285 | Q18: =Q19/Q17 -> 45506.828 | R18: =R19/R17 -> 40079.84 | S18: =S19/S17 -> 31294.811 | T18: Frw/ton | U18: =O18*U2 -> 30541618 | V18: =P18*V2 -> 35287109 | W18: =Q18*W2 -> 31029364 | X18: =R18*X2 -> 28896567 | Y18: =S18*Y2 -> 24660311 | Z18: Calculated
L19: Sales (exports) | M19: RMB | N19: USD | O19: ='Basic data - source records'!R6 -> 56911605 | P19: ='Basic data - source records'!S6 -> 1.3457161e+08 | Q19: ='Basic data - source records'!T6 -> 1.0478033e+08 | R19: ='Basic data - source records'!U6 -> 66200323 | S19: ='Basic data - source records'!V6 -> 39742507 | T19: Frw: billion | U19: =O19*U$2/1000000000 -> 34.960522 | V19: =P19*V$2/1000000000 -> 87.018847 | W19: =Q19*W$2/1000000000 -> 71.445696 | X19: =R19*X$2/1000000000 -> 47.728785 | Y19: =S19*Y$2/1000000000 -> 31.317095 | Z19: Published data
B20: Equal: Marketed production (exports) | C20: RMB | D20: tons | E20: ='Basic data - source records'!J6 -> 1144.6847 | F20: ='Basic data - source records'!K6 -> 2466.0237 | G20: ='Basic data - source records'!L6 -> 2302.5189 | H20: ='Basic data - source records'!M6 -> 1651.7113 | I20: ='Basic data - source records'!N6 -> 1269.9392 | J20: RMB & RNB | L20: Less: Purchase of raw material | M20: IBES | N20: USD | O20: =O$19*'IBES data'!$U31 -> 48639029 | P20: =P$19*'IBES data'!$U31 -> 1.1501051e+08 | Q20: =Q$19*'IBES data'!$U31 -> 89549637 | R20: =R$19*'IBES data'!$U31 -> 56577555 | S20: =S$19*'IBES data'!$U31 -> 33965602 | T20: Frw: billion | U20: =O20*U$2/1000000000 -> 29.878719 | V20: =P20*V$2/1000000000 -> 74.369932 | W20: =Q20*W$2/1000000000 -> 61.060469 | X20: =R20*X$2/1000000000 -> 40.791009 | Y20: =S20*Y$2/1000000000 -> 26.764895 | Z20: Derived from IBES structure
L21: Less: Intermediate consumption | M21: IBES | N21: USD | O21: =O$19*'IBES data'!$U32 -> 0 | P21: =P$19*'IBES data'!$U32 -> 0 | Q21: =Q$19*'IBES data'!$U32 -> 0 | R21: =R$19*'IBES data'!$U32 -> 0 | S21: =S$19*'IBES data'!$U32 -> 0 | T21: Frw: billion | U21: =O21*U$2/1000000000 -> 0 | V21: =P21*V$2/1000000000 -> 0 | W21: =Q21*W$2/1000000000 -> 0 | X21: =R21*X$2/1000000000 -> 0 | Y21: =S21*Y$2/1000000000 -> 0 | Z21: Derived from IBES structure
L22: Less: Other operating and overhead costs | M22: IBES | N22: USD | O22: =O$19*'IBES data'!$U33 -> 9234142.6 | P22: =P$19*'IBES data'!$U33 -> 21834799 | Q22: =Q$19*'IBES data'!$U33 -> 17001041 | R22: =R$19*'IBES data'!$U33 -> 10741275 | S22: =S$19*'IBES data'!$U33 -> 6448385.6 | T22: Frw: billion | U22: =O22*U$2/1000000000 -> 5.6724889 | V22: =P22*V$2/1000000000 -> 14.119167 | W22: =Q22*W$2/1000000000 -> 11.592359 | X22: =R22*X$2/1000000000 -> 7.7441922 | Y22: =S22*Y$2/1000000000 -> 5.0813279 | Z22: Derived from IBES structure
B23: Key to colour coding: | L23: Less: Consumption of capital (Deprc) | M23: IBES | N23: USD | O23: =O$19*'IBES data'!$U34 -> 521747.28 | P23: =P$19*'IBES data'!$U34 -> 1233709.2 | Q23: =Q$19*'IBES data'!$U34 -> 960592.35 | R23: =R$19*'IBES data'!$U34 -> 606903.26 | S23: =S$19*'IBES data'!$U34 -> 364346.51 | T23: Frw: billion | U23: =O23*U$2/1000000000 -> 0.32050682 | V23: =P23*V$2/1000000000 -> 0.79776078 | W23: =Q23*W$2/1000000000 -> 0.65499115 | X23: =R23*X$2/1000000000 -> 0.43756214 | Y23: =S23*Y$2/1000000000 -> 0.28710505 | Z23: Derived from IBES structure
B24: High quality data - published | L24: Less: Opportunity cost of capital ("normal profit") | M24: Calc | N24: USD | O24: =O23*'Basic data - source records'!Y5*'Basic data - source records'!$AR$2 -> 589574.42 | P24: =P23*'Basic data - source records'!Z5*'Basic data - source records'!$AR$2 -> 1295394.7 | Q24: =Q23*'Basic data - source records'!AA5*'Basic data - source records'!$AR$2 -> 1027833.8 | R24: =R23*'Basic data - source records'!AB5*'Basic data - source records'!$AR$2 -> 637248.42 | S24: =S23*'Basic data - source records'!AC5*'Basic data - source records'!$AR$2 -> 382563.84 | T24: Frw: billion | U24: =O24*U$2/1000000000 -> 0.36217271 | V24: =P24*V$2/1000000000 -> 0.83764882 | W24: =Q24*W$2/1000000000 -> 0.70084053 | X24: =R24*X$2/1000000000 -> 0.45944025 | Y24: =S24*Y$2/1000000000 -> 0.3014603 | Z24: Derived from IBES structure
B25: High quality input - derived from IBES structure
B26: Good quality data - derived from hard data | L26: Equal: Resource rent | M26: Calc | N26: USD | O26: =O19-(O20+O21+O22+O23+O24) -> -2072888.5 | P26: =P19-(P20+P21+P22+P23+P24) -> -4802798.3 | Q26: =Q19-(Q20+Q21+Q22+Q23+Q24) -> -3758773.1 | R26: =R19-(R20+R21+R22+R23+R24) -> -2362658.7 | S26: =S19-(S20+S21+S22+S23+S24) -> -1418391.6 | T26: Frw: billion | U26: =O26*U$2/1000000000 -> -1.2733653 | V26: =P26*V$2/1000000000 -> -3.1056621 | W26: =Q26*W$2/1000000000 -> -2.5629635 | X26: =R26*X$2/1000000000 -> -1.7034181 | Y26: =S26*Y$2/1000000000 -> -1.1176926 | Z26: Calculated
B27: Results/outcomes - based on formulas | L27: Unit rent | M27: Calc | N27: USD/ton | O27: =O26/O17 -> -1810.8816 | P27: =P26/P17 -> -1947.5881 | Q27: =Q26/Q17 -> -1632.4614 | R27: =R26/R17 -> -1430.4308 | S27: =S26/S17 -> -1116.8972 | T27: Frw/ton | U27: =O27*U2 -> -1112415.8 | V27: =P27*V2 -> -1259380.5 | W27: =Q27*W2 -> -1113112.9 | X27: =R27*X2 -> -1031305 | Y27: =S27*Y2 -> -880115.02 | Z27: Calculated
L28: Royalty payments | M28: Calc | N28: USD | O28: =0*O19 -> 0 | P28: =0.02*P19 -> 2691432.3 | Q28: =0.04*Q19 -> 4191213.2 | R28: =0.04*R19 -> 2648012.9 | S28: =0.04*S19 -> 1589700.3 | T28: Frw: billion | U28: =O28*U2/1000000000 -> 0 | V28: =P28*V2/1000000000 -> 1.7403769 | W28: =Q28*W2/1000000000 -> 2.8578279 | X28: =R28*X2/1000000000 -> 1.9091514 | Y28: =S28*Y2/1000000000 -> 1.2526838 | Z28: Calculated as 4% of sales

Sheet MRA - Wolfram - Tungsten
A1: Mineral accounts: Flow accounts: Wolfram
B2: Physical accounts | L2: Monetary accounts | T2: Exchange rate | U2: ='Basic data - source records'!AF5 -> 614.29514 | V2: ='Basic data - source records'!AG5 -> 646.63597 | W2: ='Basic data - source records'!AH5 -> 681.86172 | X2: ='Basic data - source records'!AI5 -> 720.97511 | Y2: ='Basic data - source records'!AJ5 -> 788
C3: Source | D3: Units | E3: 2012 | F3: 2013 | G3: 2014 | H3: 2015 | I3: 2016 | J3: Notes | M3: Source | N3: Units | O3: 2012 | P3: 2013 | Q3: 2014 | R3: 2015 | S3: 2016 | T3: Units | U3: 2012 | V3: 2013 | W3: 2014 | X3: 2015 | Y3: 2016 | Z3: Notes
B4: Mining operations | L4: Mining operations | T4: Mining operations
B5: Tagged production | C5: ITRI | D5: tons | E5: ='Basic data - source records'!C9 -> 1771.2722 | F5: ='Basic data - source records'!D9 -> 2264.212 | G5: ='Basic data - source records'!E9 -> 2534.869 | H5: ='Basic data - source records'!F9 -> 2169.4109 | I5: ='Basic data - source records'!G9 -> 1498 | J5: Data verified by RMB | L5: Production | M5: ITRI | N5: tons | O5: =E5 -> 1771.2722 | P5: =F5 -> 2264.212 | Q5: =G5 -> 2534.869 | R5: =H5 -> 2169.4109 | S5: =I5 -> 1498 | T5: tons | U5: =O5 -> 1771.2722 | V5: =P5 -> 2264.212 | W5: =Q5 -> 2534.869 | X5: =R5 -> 2169.4109 | Y5: =S5 -> 1498 | Z5: From physical accounts
B6: Employment | C6: NISR: LFS | D6: people | L6: Average price | M6: Calc | N6: USD/ton | O6: ='Mining price data'!BO60 -> 12737.778 | P6: ='Mining price data'!BP60 -> 11327.25 | Q6: ='Mining price data'!BQ60 -> 10091.2 | R6: ='Mining price data'!BR60 -> 7377.5 | S6: ='Mining price data'!BS60 -> 5573.1053 | T6: Frw/ton | U6: =O6*U2 -> 7824755 | V6: =P6*V2 -> 7324607.3 | W6: =Q6*W2 -> 6880803 | X6: =R6*X2 -> 5318993.9 | Y6: =S6*Y2 -> 4391607 | Z6: Based on avg. of 5 transactions/month per major trader
B7: Employment | C7: NISR: IBES | D7: people | L7: Sales | M7: Calc | N7: USD | O7: =O6*O5 -> 22562072 | P7: =P6*P5 -> 25647295 | Q7: =Q6*Q5 -> 25579870 | R7: =R6*R5 -> 16004829 | S7: =S6*S5 -> 8348511.8 | T7: Frw: billion | U7: =O7*U$2/1000000000 -> 13.859771 | V7: =P7*V$2/1000000000 -> 16.584464 | W7: =Q7*W$2/1000000000 -> 17.441934 | X7: =R7*X$2/1000000000 -> 11.539083 | Y7: =S7*Y$2/1000000000 -> 6.5786273 | Z7: Calculated
L8: Less: Intermediate consumption (payments to sub-contractors & direct costs to production) | M8: IBES | N8: USD | O8: =O$7*'IBES data'!$U7 -> 19081660 | P8: =P$7*'IBES data'!$U7 -> 21690959 | Q8: =Q$7*'IBES data'!$U7 -> 21633934 | R8: =R$7*'IBES data'!$U7 -> 13535934 | S8: =S$7*'IBES data'!$U7 -> 7060675.3 | T8: Frw: billion | U8: =O8*U$2/1000000000 -> 11.721771 | V8: =P8*V$2/1000000000 -> 14.026154 | W8: =Q8*W$2/1000000000 -> 14.751352 | X8: =R8*X$2/1000000000 -> 9.7590713 | Y8: =S8*Y$2/1000000000 -> 5.5638122 | Z8: Derived from IBES structure
B9: Change in inventory | C9: Calc | D9: tons | E9: =E5-E12 -> 0 | F9: =F5-F12 -> 0 | G9: =G5-G12 -> 0 | H9: =H5-H12 -> 0 | I9: =I5-I12 -> 0 | L9: Less: Other operating and overhead costs | M9: IBES | N9: USD | O9: =O$7*'IBES data'!$U8 -> 3485165.3 | P9: =P$7*'IBES data'!$U8 -> 3961740.1 | Q9: =Q$7*'IBES data'!$U8 -> 3951324.9 | R9: =R$7*'IBES data'!$U8 -> 2472267.5 | S9: =S$7*'IBES data'!$U8 -> 1289595.4 | T9: Frw: billion | U9: =O9*U$2/1000000000 -> 2.1409201 | V9: =P9*V$2/1000000000 -> 2.5618037 | W9: =Q9*W$2/1000000000 -> 2.6942572 | X9: =R9*X$2/1000000000 -> 1.7824433 | Y9: =S9*Y$2/1000000000 -> 1.0162012 | Z9: Derived from IBES structure
L10: Less: Consumption of capital (Deprc) | M10: IBES | N10: USD | O10: =O$7*'IBES data'!$U9 -> 383861.78 | P10: =P$7*'IBES data'!$U9 -> 436352.51 | Q10: =Q$7*'IBES data'!$U9 -> 435205.36 | R10: =R$7*'IBES data'!$U9 -> 272299.56 | S10: =S$7*'IBES data'!$U9 -> 142038.14 | T10: Frw: billion | U10: =O10*U$2/1000000000 -> 0.23580443 | V10: =P10*V$2/1000000000 -> 0.28216123 | W10: =Q10*W$2/1000000000 -> 0.29674987 | X10: =R10*X$2/1000000000 -> 0.19632121 | Y10: =S10*Y$2/1000000000 -> 0.11192605 | Z10: Derived from IBES structure
B11: Trading operations | L11: Less: Opportunity cost of capital ("normal profit") | M11: Calc | N11: USD | O11: =O10*'Basic data - source records'!Y5*'Basic data - source records'!$AR$2 -> 433763.81 | P11: =P10*'Basic data - source records'!Z5*'Basic data - source records'!$AR$2 -> 458170.13 | Q11: =Q10*'Basic data - source records'!AA5*'Basic data - source records'!$AR$2 -> 465669.73 | R11: =R10*'Basic data - source records'!AB5*'Basic data - source records'!$AR$2 -> 285914.54 | S11: =S10*'Basic data - source records'!AC5*'Basic data - source records'!$AR$2 -> 149140.04 | T11: Frw: billion | U11: =O11*U$2/1000000000 -> 0.266459 | V11: =P11*V$2/1000000000 -> 0.29626929 | W11: =Q11*W$2/1000000000 -> 0.31752236 | X11: =R11*X$2/1000000000 -> 0.20613727 | Y11: =S11*Y$2/1000000000 -> 0.11752235 | Z11: Derived from IBES structure
B12: Tagged purchases | C12: ITRI | D12: tons | E12: ='Basic data - source records'!C9 -> 1771.2722 | F12: ='Basic data - source records'!D9 -> 2264.212 | G12: ='Basic data - source records'!E9 -> 2534.869 | H12: ='Basic data - source records'!F9 -> 2169.4109 | I12: ='Basic data - source records'!G9 -> 1498 | J12: Data verified by RMB
L13: Equal: Resource rent | M13: Calc | N13: USD | O13: =O7-(O8+O9+O10+O11) -> -822379.12 | P13: =P7-(P8+P9+P10+P11) -> -899926.17 | Q13: =Q7-(Q8+Q9+Q10+Q11) -> -906264.41 | R13: =R7-(R8+R9+R10+R11) -> -561586.1 | S13: =S7-(S8+S9+S10+S11) -> -292937.1 | T13: Frw: billion | U13: =O13*U$2/1000000000 -> -0.5051835 | V13: =P13*V$2/1000000000 -> -0.58192464 | W13: =Q13*W$2/1000000000 -> -0.61794701 | X13: =R13*X$2/1000000000 -> -0.4048896 | Y13: =S13*Y$2/1000000000 -> -0.23083443 | Z13: Calculated
B14: Less: Waste or losses during processing by traders | C14: Calc | D14: tons | E14: =E12-E16 -> 186.51019 | F14: =F12-F16 -> -5.75276 | G14: =G12-G16 -> 475.9909 | H14: =H12-H16 -> 846.41094 | I14: =I12-I16 -> -141 | L14: Unit rent | M14: Calc | N14: USD/ton | O14: =O13/O5 -> -464.28726 | P14: =P13/P5 -> -397.45667 | Q14: =Q13/Q5 -> -357.51923 | R14: =R13/R5 -> -258.86571 | S14: =S13/S5 -> -195.55213 | T14: Frw/ton | U14: =O14*U2 -> -285209.41 | V14: =P14*V2 -> -257009.78 | W14: =Q14*W2 -> -243778.68 | X14: =R14*X2 -> -186635.73 | Y14: =S14*Y2 -> -154095.08 | Z14: Calculated
L15: Inventory or sundry changes (residual change) | M15: Calc | N15: USD | O15: =O20-O7 -> -117077.29 | P15: =P20-P7 -> 37919.316 | Q15: =Q20-Q7 -> -2852967 | R15: =R20-R7 -> -1182668.7 | S15: =S20-S7 -> 1799232.1 | T15: Frw: billion | U15: =O15*U$2/1000000000 -> -0.071920012 | V15: =P15*V$2/1000000000 -> 0.024519994 | W15: =Q15*W$2/1000000000 -> -1.945329 | X15: =R15*X$2/1000000000 -> -0.85267471 | Y15: =S15*Y$2/1000000000 -> 1.4177949 | Z15: Calculated
B16: Equal: Processed and tagged production | C16: ITRI | D16: tons | E16: ='Basic data - source records'!C10 -> 1584.762 | F16: ='Basic data - source records'!D10 -> 2269.9648 | G16: ='Basic data - source records'!E10 -> 2058.8781 | H16: ='Basic data - source records'!F10 -> 1323 | I16: ='Basic data - source records'!G10 -> 1639 | J16: Data verified by RMB | L16: Trading operations | T16: Trading operations
L17: Production (exports) | M17: RMB | N17: tons | O17: =E20 -> 1750.5665 | P17: =F20 -> 2217.928 | Q17: =G20 -> 2214.4937 | R17: =H20 -> 1784.4011 | S17: =I20 -> 1715.9599 | T17: tons | U17: =O17 -> 1750.5665 | V17: =P17 -> 2217.928 | W17: =Q17 -> 2214.4937 | X17: =R17 -> 1784.4011 | Y17: =S17 -> 1715.9599 | Z17: From physical accounts
B18: Change in inventory | C18: Calc | D18: tons | E18: =E16-E20 -> -165.80449 | F18: =F16-F20 -> 52.03672 | G18: =G16-G20 -> -155.61557 | H18: =H16-H20 -> -461.40112 | I18: =I16-I20 -> -76.95995 | L18: Average price | M18: Calc | N18: USD/ton | O18: =O19/O17 -> 15002.265 | P18: =P19/P17 -> 13550.387 | Q18: =Q19/Q17 -> 12008.306 | R18: =R19/R17 -> 9719.2994 | S18: =S19/S17 -> 6919.5569 | T18: Frw/ton | U18: =O18*U2 -> 9215818.3 | V18: =P18*V2 -> 8762167.4 | W18: =Q18*W2 -> 8188004.3 | X18: =R18*X2 -> 7007372.9 | Y18: =S18*Y2 -> 5452610.9 | Z18: Calculated
L19: Sales (exports) | M19: RMB | N19: USD | O19: ='Basic data - source records'!R7 -> 26262462 | P19: ='Basic data - source records'!S7 -> 30053782 | Q19: ='Basic data - source records'!T7 -> 26592318 | R19: ='Basic data - source records'!U7 -> 17343129 | S19: ='Basic data - source records'!V7 -> 11873683 | T19: Frw: billion | U19: =O19*U$2/1000000000 -> 16.132903 | V19: =P19*V$2/1000000000 -> 19.433857 | W19: =Q19*W$2/1000000000 -> 18.132283 | X19: =R19*X$2/1000000000 -> 12.503964 | Y19: =S19*Y$2/1000000000 -> 9.3564619 | Z19: Published data
B20: Equal: Marketed production (exports) | C20: RMB | D20: tons | E20: ='Basic data - source records'!J7 -> 1750.5665 | F20: ='Basic data - source records'!K7 -> 2217.928 | G20: ='Basic data - source records'!L7 -> 2214.4937 | H20: ='Basic data - source records'!M7 -> 1784.4011 | I20: ='Basic data - source records'!N7 -> 1715.9599 | J20: RMB & RNB | L20: Less: Purchase of raw material | M20: IBES | N20: USD | O20: =O$19*'IBES data'!$U31 -> 22444994 | P20: =P$19*'IBES data'!$U31 -> 25685215 | Q20: =Q$19*'IBES data'!$U31 -> 22726903 | R20: =R$19*'IBES data'!$U31 -> 14822160 | S20: =S$19*'IBES data'!$U31 -> 10147744 | T20: Frw: billion | U20: =O20*U$2/1000000000 -> 13.787851 | V20: =P20*V$2/1000000000 -> 16.608984 | W20: =Q20*W$2/1000000000 -> 15.496605 | X20: =R20*X$2/1000000000 -> 10.686409 | Y20: =S20*Y$2/1000000000 -> 7.9964222 | Z20: Derived from IBES structure
L21: Less: Intermediate consumption | M21: IBES | N21: USD | O21: =O$19*'IBES data'!$U32 -> 0 | P21: =P$19*'IBES data'!$U32 -> 0 | Q21: =Q$19*'IBES data'!$U32 -> 0 | R21: =R$19*'IBES data'!$U32 -> 0 | S21: =S$19*'IBES data'!$U32 -> 0 | T21: Frw: billion | U21: =O21*U$2/1000000000 -> 0 | V21: =P21*V$2/1000000000 -> 0 | W21: =Q21*W$2/1000000000 -> 0 | X21: =R21*X$2/1000000000 -> 0 | Y21: =S21*Y$2/1000000000 -> 0 | Z21: Derived from IBES structure
L22: Less: Other operating and overhead costs | M22: IBES | N22: USD | O22: =O$19*'IBES data'!$U33 -> 4261192.7 | P22: =P$19*'IBES data'!$U33 -> 4876350.1 | Q22: =Q$19*'IBES data'!$U33 -> 4314713.2 | R22: =R$19*'IBES data'!$U33 -> 2813994.1 | S22: =S$19*'IBES data'!$U33 -> 1926554 | T22: Frw: billion | U22: =O22*U$2/1000000000 -> 2.61763 | V22: =P22*V$2/1000000000 -> 3.1532234 | W22: =Q22*W$2/1000000000 -> 2.9420378 | X22: =R22*X$2/1000000000 -> 2.0288197 | Y22: =S22*Y$2/1000000000 -> 1.5181245 | Z22: Derived from IBES structure
B23: Key to colour coding: | L23: Less: Consumption of capital (Deprc) | M23: IBES | N23: USD | O23: =O$19*'IBES data'!$U34 -> 240765.8 | P23: =P$19*'IBES data'!$U34 -> 275523.4 | Q23: =Q$19*'IBES data'!$U34 -> 243789.81 | R23: =R$19*'IBES data'!$U34 -> 158996.22 | S23: =S$19*'IBES data'!$U34 -> 108854.1 | T23: Frw: billion | U23: =O23*U$2/1000000000 -> 0.14790126 | V23: =P23*V$2/1000000000 -> 0.17816334 | W23: =Q23*W$2/1000000000 -> 0.16623094 | X23: =R23*X$2/1000000000 -> 0.11463232 | Y23: =S23*Y$2/1000000000 -> 0.085777031 | Z23: Derived from IBES structure
B24: High quality data - published | L24: Less: Opportunity cost of capital ("normal profit") | M24: Calc | N24: USD | O24: =O23*'Basic data - source records'!Y5*'Basic data - source records'!$AR$2 -> 272065.35 | P24: =P23*'Basic data - source records'!Z5*'Basic data - source records'!$AR$2 -> 289299.57 | Q24: =Q23*'Basic data - source records'!AA5*'Basic data - source records'!$AR$2 -> 260855.1 | R24: =R23*'Basic data - source records'!AB5*'Basic data - source records'!$AR$2 -> 166946.03 | S24: =S23*'Basic data - source records'!AC5*'Basic data - source records'!$AR$2 -> 114296.81 | T24: Frw: billion | U24: =O24*U$2/1000000000 -> 0.16712843 | V24: =P24*V$2/1000000000 -> 0.18707151 | W24: =Q24*W$2/1000000000 -> 0.17786711 | X24: =R24*X$2/1000000000 -> 0.12036393 | Y24: =S24*Y$2/1000000000 -> 0.090065883 | Z24: Derived from IBES structure
B25: High quality input - derived from IBES structure
B26: Good quality data - derived from hard data | L26: Equal: Resource rent | M26: Calc | N26: USD | O26: =O19-(O20+O21+O22+O23+O24) -> -956556.31 | P26: =P19-(P20+P21+P22+P23+P24) -> -1072605.5 | Q26: =Q19-(Q20+Q21+Q22+Q23+Q24) -> -953943.24 | R26: =R19-(R20+R21+R22+R23+R24) -> -618968.19 | S26: =S19-(S20+S21+S22+S23+S24) -> -423766.21 | T26: Frw: billion | U26: =O26*U$2/1000000000 -> -0.5876079 | V26: =P26*V$2/1000000000 -> -0.69358531 | W26: =Q26*W$2/1000000000 -> -0.65045738 | X26: =R26*X$2/1000000000 -> -0.44626066 | Y26: =S26*Y$2/1000000000 -> -0.33392777 | Z26: Calculated
B27: Results/outcomes - based on formulas | L27: Unit rent | M27: Calc | N27: USD/ton | O27: =O26/O17 -> -546.42672 | P27: =P26/P17 -> -483.60699 | Q27: =Q26/Q17 -> -430.77263 | R27: =R26/R17 -> -346.87727 | S27: =S26/S17 -> -246.95577 | T27: Frw/ton | U27: =O27*U2 -> -335667.28 | V27: =P27*V2 -> -312717.68 | W27: =Q27*W2 -> -293727.36 | X27: =R27*X2 -> -250089.88 | Y27: =S27*Y2 -> -194601.15 | Z27: Calculated
L28: Royalty payments | M28: Calc | N28: USD | O28: =0*O19 -> 0 | P28: =0.02*P19 -> 601075.65 | Q28: =0.04*Q19 -> 1063692.7 | R28: =0.04*R19 -> 693725.15 | S28: =0.04*S19 -> 474947.3 | T28: Frw: billion | U28: =O28*U2/1000000000 -> 0 | V28: =P28*V2/1000000000 -> 0.38867714 | W28: =Q28*W2/1000000000 -> 0.72529134 | X28: =R28*X2/1000000000 -> 0.50015856 | Y28: =S28*Y2/1000000000 -> 0.37425847 | Z28: Calculated as 4% of sales

Sheet Graphs
AO1: R_GDP National Accounts 2018_r | AW1: Year | AX1: GDP in current prices | AY1: Mining GDP in current prices | AZ1: Mining GDP as % of GDP | BA1: Population (millions) | BB1: GDP/cap ('000RwF) | BC1: GDP/capita (US$) | BE1: Exchange rate (RwF:US$)
C2: Production and exports of minerals | W2: Rwanda: Export prices and volumes of minerals | AO2: GDP in RwF billions (current prices) | AP2: GDP in RwF billions (constant prices) | AQ2: mining GDP in RwF billions (current p) | AS2: Goods export (fob) US$ | AT2: FOB exports in current prices (US$ million) | AU2: Exchange rate | AV2: 3T export | AX2: (million US$) | AY2: (million US$)
D3: 2012 | E3: 2013 | F3: 2014 | G3: 2015 | H3: 2016 | W3: =D3 -> 2012 | X3: =E3 -> 2013 | Y3: =F3 -> 2014 | Z3: =G3 -> 2015 | AA3: =H3 -> 2016 | AO3: 607 | AP3: 1760 | AQ3: 1 | AR3: 1999 | AS3: 62874251 | AT3: 62.874251 | AU3: 334 | AW3: 1999 | AX3: =(AO3*1000000000)/(BE3*1000000) -> 1817.3653 | AY3: =(AQ3*1000000000)/(BE3*1000000) -> 2.994012 | AZ3: =AY3/AX3 -> 0.0016474465 | BA3: =AO3/BB3 -> 7.4938272 | BB3: 81 | BC3: 242 | BE3: 334
C4: Cassiterite production | D4: ='MRA - Cassiterite - Tin'!E5 -> 3670.5237 | E4: ='MRA - Cassiterite - Tin'!F5 -> 6112.1432 | F4: ='MRA - Cassiterite - Tin'!G5 -> 7137.4683 | G4: ='MRA - Cassiterite - Tin'!H5 -> 4714.1224 | H4: ='MRA - Cassiterite - Tin'!I5 -> 2024 | V4: =C5 -> Cassiterite exports | W4: =D5 -> 4636.6403 | X4: =E5 -> 4895.2675 | Y4: =F5 -> 5953.7963 | Z4: =G5 -> 3845.6561 | AA4: =H5 -> 3549.915 | AO4: 676 | AP4: 1907 | AQ4: 1 | AR4: 2000 | AS4: 69230769 | AT4: 69.230769 | AU4: 390 | AW4: 2000 | AX4: =(AO4*1000000000)/(BE4*1000000) -> 1733.3333 | AY4: =(AQ4*1000000000)/(BE4*1000000) -> 2.5641026 | AZ4: =AY4/AX4 -> 0.0014792899 | BA4: =AO4/BB4 -> 7.6818182 | BB4: 88 | BC4: 225 | BE4: 390
C5: Cassiterite exports | D5: ='MRA - Cassiterite - Tin'!E20 -> 4636.6403 | E5: ='MRA - Cassiterite - Tin'!F20 -> 4895.2675 | F5: ='MRA - Cassiterite - Tin'!G20 -> 5953.7963 | G5: ='MRA - Cassiterite - Tin'!H20 -> 3845.6561 | H5: ='MRA - Cassiterite - Tin'!I20 -> 3549.915 | V5: =C7 -> Coltan exports | W5: =D7 -> 1144.6847 | X5: =E7 -> 2466.0237 | Y5: =F7 -> 2302.5189 | Z5: =G7 -> 1651.7113 | AA5: =H7 -> 1269.9392 | AO5: 742 | AP5: 2069 | AQ5: 6 | AR5: 2001 | AS5: 92550790 | AT5: 92.55079 | AU5: 443 | AW5: 2001 | AX5: =(AO5*1000000000)/(BE5*1000000) -> 1674.9436 | AY5: =(AQ5*1000000000)/(BE5*1000000) -> 13.544018 | AZ5: =AY5/AX5 -> 0.0080862534 | BA5: =AO5/BB5 -> 7.893617 | BB5: 94 | BC5: 211 | BE5: 443
C6: Coltan production | D6: ='MRA - Coltan - Tantalum'!E5 -> 967.88761 | E6: ='MRA - Coltan - Tantalum'!F5 -> 1924.3862 | F6: ='MRA - Coltan - Tantalum'!G5 -> 2097.5135 | G6: ='MRA - Coltan - Tantalum'!H5 -> 1332 | H6: ='MRA - Coltan - Tantalum'!I5 -> 2553.6 | V6: =C9 -> Wolfram exports | W6: =D9 -> 1750.5665 | X6: =E9 -> 2217.928 | Y6: =F9 -> 2214.4937 | Z6: =G9 -> 1784.4011 | AA6: =H9 -> 1715.9599 | AO6: 797 | AP6: 2342 | AQ6: 2 | AR6: 2002 | AS6: 67368421 | AT6: 67.368421 | AU6: 475 | AW6: 2002 | AX6: =(AO6*1000000000)/(BE6*1000000) -> 1677.8947 | AY6: =(AQ6*1000000000)/(BE6*1000000) -> 4.2105263 | AZ6: =AY6/AX6 -> 0.0025094103 | BA6: =AO6/BB6 -> 8.1326531 | BB6: 98 | BC6: 206 | BE6: 475
C7: Coltan exports | D7: ='MRA - Coltan - Tantalum'!E20 -> 1144.6847 | E7: ='MRA - Coltan - Tantalum'!F20 -> 2466.0237 | F7: ='MRA - Coltan - Tantalum'!G20 -> 2302.5189 | G7: ='MRA - Coltan - Tantalum'!H20 -> 1651.7113 | H7: ='MRA - Coltan - Tantalum'!I20 -> 1269.9392 | V7: =C20 -> Cassiterite export prices | W7: =D20 -> 11408.456 | X7: =E20 -> 12476.229 | Y7: =F20 -> 12083.99 | Z7: =G20 -> 8909.5964 | AA7: =H20 -> 9805.278 | AO7: 993 | AP7: 2393 | AQ7: 3 | AR7: 2003 | AS7: 61338290 | AT7: 61.33829 | AU7: 538 | AW7: 2003 | AX7: =(AO7*1000000000)/(BE7*1000000) -> 1845.7249 | AY7: =(AQ7*1000000000)/(BE7*1000000) -> 5.5762082 | AZ7: =AY7/AX7 -> 0.003021148 | BA7: =AO7/BB7 -> 8.3445378 | BB7: 119 | BC7: 221 | BE7: 538
C8: Wolfram production | D8: ='MRA - Wolfram - Tungsten'!E5 -> 1771.2722 | E8: ='MRA - Wolfram - Tungsten'!F5 -> 2264.212 | F8: ='MRA - Wolfram - Tungsten'!G5 -> 2534.869 | G8: ='MRA - Wolfram - Tungsten'!H5 -> 2169.4109 | H8: ='MRA - Wolfram - Tungsten'!I5 -> 1498 | V8: =C22 -> Coltan export prices | W8: =D22 -> 49718.149 | X8: =E22 -> 54570.285 | Y8: =F22 -> 45506.828 | Z8: =G22 -> 40079.84 | AA8: =H22 -> 31294.811 | AO8: 1206 | AP8: 2572 | AQ8: 8 | AR8: 2004 | AS8: 95652174 | AT8: 95.652174 | AU8: 575 | AW8: 2004 | AX8: =(AO8*1000000000)/(BE8*1000000) -> 2097.3913 | AY8: =(AQ8*1000000000)/(BE8*1000000) -> 13.913043 | AZ8: =AY8/AX8 -> 0.0066334992 | BA8: =AO8/BB8 -> 8.5531915 | BB8: 141 | BC8: 245 | BE8: 575
C9: Wolfram exports | D9: ='MRA - Wolfram - Tungsten'!E20 -> 1750.5665 | E9: ='MRA - Wolfram - Tungsten'!F20 -> 2217.928 | F9: ='MRA - Wolfram - Tungsten'!G20 -> 2214.4937 | G9: ='MRA - Wolfram - Tungsten'!H20 -> 1784.4011 | H9: ='MRA - Wolfram - Tungsten'!I20 -> 1715.9599 | V9: =C24 -> Wolfram export prices | W9: =D24 -> 15002.265 | X9: =E24 -> 13550.387 | Y9: =F24 -> 12008.306 | Z9: =G24 -> 9719.2994 | AA9: =H24 -> 6919.5569 | AO9: 1440 | AP9: 2813 | AQ9: 10 | AR9: 2005 | AS9: 1.2028725e+08 | AT9: 120.28725 | AU9: 557 | AW9: 2005 | AX9: =(AO9*1000000000)/(BE9*1000000) -> 2585.2783 | AY9: =(AQ9*1000000000)/(BE9*1000000) -> 17.953321 | AZ9: =AY9/AX9 -> 0.0069444444 | BA9: =AO9/BB9 -> 8.7804878 | BB9: 164 | BC9: 295 | BE9: 557
AO10: 1762 | AP10: 3072 | AQ10: 23 | AR10: 2006 | AS10: 1.4311594e+08 | AT10: 143.11594 | AU10: 552 | AW10: 2006 | AX10: =(AO10*1000000000)/(BE10*1000000) -> 3192.029 | AY10: =(AQ10*1000000000)/(BE10*1000000) -> 41.666667 | AZ10: =AY10/AX10 -> 0.013053348 | BA10: =AO10/BB10 -> 8.9897959 | BB10: 196 | BC10: 355 | BE10: 552
AO11: 2120 | AP11: 3307 | AQ11: 43 | AR11: 2007 | AS11: 1.7915905e+08 | AT11: 179.15905 | AU11: 547 | AW11: 2007 | AX11: =(AO11*1000000000)/(BE11*1000000) -> 3875.6856 | AY11: =(AQ11*1000000000)/(BE11*1000000) -> 78.610603 | AZ11: =AY11/AX11 -> 0.020283019 | BA11: =AO11/BB11 -> 9.2173913 | BB11: 230 | BC11: 420 | BE11: 547
AO12: 2693 | AP12: 3676 | AQ12: 51 | AR12: 2008 | AS12: 2.6873857e+08 | AT12: 268.73857 | AU12: 547 | AW12: 2008 | AX12: =(AO12*1000000000)/(BE12*1000000) -> 4923.2176 | AY12: =(AQ12*1000000000)/(BE12*1000000) -> 93.235832 | AZ12: =AY12/AX12 -> 0.018937987 | BA12: =AO12/BB12 -> 9.4823944 | BB12: 284 | BC12: 520 | BE12: 547
AO13: 3097 | AP13: 3906 | AQ13: 33 | AR13: 2009 | AS13: 2.0070423e+08 | AT13: 200.70423 | AU13: 568 | AW13: 2009 | AX13: =(AO13*1000000000)/(BE13*1000000) -> 5452.4648 | AY13: =(AQ13*1000000000)/(BE13*1000000) -> 58.098592 | AZ13: =AY13/AX13 -> 0.010655473 | BA13: =AO13/BB13 -> 9.7084639 | BB13: 319 | BC13: 561 | BE13: 568
AA14: 532.40152 | AO14: 3411 | AP14: 4192 | AQ14: 45 | AR14: 2010 | AS14: 2.6929674e+08 | AT14: 269.29674 | AU14: 583 | AW14: 2010 | AX14: =(AO14*1000000000)/(BE14*1000000) -> 5850.7719 | AY14: =(AQ14*1000000000)/(BE14*1000000) -> 77.186964 | AZ14: =AY14/AX14 -> 0.013192612 | BA14: =AO14/BB14 -> 9.9736842 | BB14: 342 | BC14: 587 | BE14: 583
AO15: 3990 | AP15: 4526 | AQ15: 102 | AR15: 2011 | AS15: 465000000 | AT15: 465 | AU15: 600 | AW15: 2011 | AX15: =(AO15*1000000000)/(BE15*1000000) -> 6650 | AY15: =(AQ15*1000000000)/(BE15*1000000) -> 170 | AZ15: =AY15/AX15 -> 0.02556391 | BA15: =AO15/BB15 -> 10.230769 | BB15: 390 | BC15: 650 | BE15: 600
V16: US$ | AO16: 4564 | AP16: 4917 | AQ16: 97 | AR16: 2012 | AS16: 5.1302932e+08 | AT16: 513.02932 | AU16: 614 | AW16: 2012 | AX16: =(AO16*1000000000)/(BE16*1000000) -> 7433.2248 | AY16: =(AQ16*1000000000)/(BE16*1000000) -> 157.98046 | AZ16: =AY16/AX16 -> 0.021253287 | BA16: =AO16/BB16 -> 10.491954 | BB16: 435 | BC16: 709 | BE16: 614
C17: Producer and export prices of minerals | V17: Cassiterite exports | W17: ='MRA - Cassiterite - Tin'!O19/1000000 -> 52.896906 | X17: ='MRA - Cassiterite - Tin'!P19/1000000 -> 61.074479 | Y17: ='MRA - Cassiterite - Tin'!Q19/1000000 -> 71.945617 | Z17: ='MRA - Cassiterite - Tin'!R19/1000000 -> 34.263244 | AA17: ='MRA - Cassiterite - Tin'!S19/1000000 -> 34.807904 | AB17: ='Basic data - source records'!W5/1000000 -> 50.154998 | AO17: 4929 | AP17: 5149 | AQ17: 124 | AR17: 2013 | AS17: 6.0587326e+08 | AT17: 605.87326 | AU17: 647 | AW17: 2013 | AX17: =(AO17*1000000000)/(BE17*1000000) -> 7618.238 | AY17: =(AQ17*1000000000)/(BE17*1000000) -> 191.65379 | AZ17: =AY17/AX17 -> 0.025157233 | BA17: =AO17/BB17 -> 10.738562 | BB17: 459 | BC17: 710 | BE17: 647
D18: 2012 | E18: 2013 | F18: 2014 | G18: 2015 | H18: 2016 | V18: Coltan exports | W18: ='MRA - Coltan - Tantalum'!O19/1000000 -> 56.911605 | X18: ='MRA - Coltan - Tantalum'!P19/1000000 -> 134.57161 | Y18: ='MRA - Coltan - Tantalum'!Q19/1000000 -> 104.78033 | Z18: ='MRA - Coltan - Tantalum'!R19/1000000 -> 66.200323 | AA18: ='MRA - Coltan - Tantalum'!S19/1000000 -> 39.742507 | AB18: ='Basic data - source records'!W6/1000000 -> 62.209186 | AO18: 5466 | AP18: 5466 | AQ18: 147 | AR18: 2014 | AS18: 5.8565154e+08 | AT18: 585.65154 | AU18: 683 | AW18: 2014 | AX18: =(AO18*1000000000)/(BE18*1000000) -> 8002.9283 | AY18: =(AQ18*1000000000)/(BE18*1000000) -> 215.22694 | AZ18: =AY18/AX18 -> 0.026893524 | BA18: =AO18/BB18 -> 10.997988 | BB18: 497 | BC18: 728 | BE18: 683
C19: Cassiterite producer prices | D19: ='MRA - Cassiterite - Tin'!O6 -> 9213.9125 | E19: ='MRA - Cassiterite - Tin'!P6 -> 10196.272 | F19: ='MRA - Cassiterite - Tin'!Q6 -> 10101.396 | G19: ='MRA - Cassiterite - Tin'!R6 -> 7003.4075 | H19: ='MRA - Cassiterite - Tin'!S6 -> 7573.3436 | V19: Wolfram exports | W19: ='MRA - Wolfram - Tungsten'!O19/1000000 -> 26.262462 | X19: ='MRA - Wolfram - Tungsten'!P19/1000000 -> 30.053782 | Y19: ='MRA - Wolfram - Tungsten'!Q19/1000000 -> 26.592318 | Z19: ='MRA - Wolfram - Tungsten'!R19/1000000 -> 17.343129 | AA19: ='MRA - Wolfram - Tungsten'!S19/1000000 -> 11.873683 | AB19: ='Basic data - source records'!W7/1000000 -> 12.604563 | AO19: 5968 | AP19: 5951 | AQ19: 132 | AR19: 2015 | AS19: 5.2222222e+08 | AT19: 522.22222 | AU19: 720 | AW19: 2015 | AX19: =(AO19*1000000000)/(BE19*1000000) -> 8288.8889 | AY19: =(AQ19*1000000000)/(BE19*1000000) -> 183.33333 | AZ19: =AY19/AX19 -> 0.022117962 | BA19: =AO19/BB19 -> 11.260377 | BB19: 530 | BC19: 736 | BE19: 720
C20: Cassiterite export prices | D20: ='MRA - Cassiterite - Tin'!O18 -> 11408.456 | E20: ='MRA - Cassiterite - Tin'!P18 -> 12476.229 | F20: ='MRA - Cassiterite - Tin'!Q18 -> 12083.99 | G20: ='MRA - Cassiterite - Tin'!R18 -> 8909.5964 | H20: ='MRA - Cassiterite - Tin'!S18 -> 9805.278 | W20: =SUM(W17:W19) -> 136.07097 | X20: =SUM(X17:X19) -> 225.69987 | Y20: =SUM(Y17:Y19) -> 203.31827 | Z20: =SUM(Z17:Z19) -> 117.8067 | AA20: =SUM(AA17:AA19) -> 86.424093 | AB20: =SUM(AB17:AB19) -> 124.96875 | AO20: 6672 | AP20: 6307 | AQ20: 137 | AR20: 2016 | AS20: 5.3240152e+08 | AT20: 532.40152 | AU20: 787 | AW20: 2016 | AX20: =(AO20*1000000000)/(BE20*1000000) -> 8477.7637 | AY20: =(AQ20*1000000000)/(BE20*1000000) -> 174.07878 | AZ20: =AY20/AX20 -> 0.020533573 | BA20: =AO20/BB20 -> 11.523316 | BB20: 579 | BC20: 735 | BE20: 787
C21: Coltan producer prices | D21: ='MRA - Coltan - Tantalum'!O6 -> 49840 | E21: ='MRA - Coltan - Tantalum'!P6 -> 56141 | F21: ='MRA - Coltan - Tantalum'!Q6 -> 44661.636 | G21: ='MRA - Coltan - Tantalum'!R6 -> 42300.37 | H21: ='MRA - Coltan - Tantalum'!S6 -> 35080.727 | V21: Total exports | W21: =AT16 -> 513.02932 | X21: =AT17 -> 605.87326 | Y21: =AT18 -> 585.65154 | Z21: =AT19 -> 522.22222 | AA21: =AT20 -> 532.40152 | AB21: =AT21 -> 855.76923 | AO21: 7600 | AP21: 6693 | AQ21: 182 | AR21: 2017 | AS21: 8.5576923e+08 | AT21: 855.76923 | AU21: 832 | AW21: 2017 | AX21: =(AO21*1000000000)/(BE21*1000000) -> 9134.6154 | AY21: =(AQ21*1000000000)/(BE21*1000000) -> 218.75 | AZ21: =AY21/AX21 -> 0.023947368 | BA21: =AO21/BB21 -> 11.801242 | BB21: 644 | BC21: 774 | BE21: 832
C22: Coltan export prices | D22: ='MRA - Coltan - Tantalum'!O18 -> 49718.149 | E22: ='MRA - Coltan - Tantalum'!P18 -> 54570.285 | F22: ='MRA - Coltan - Tantalum'!Q18 -> 45506.828 | G22: ='MRA - Coltan - Tantalum'!R18 -> 40079.84 | H22: ='MRA - Coltan - Tantalum'!S18 -> 31294.811 | V22: 3T to total exports | W22: =W20/W21 -> 0.2652304 | X22: =X20/X21 -> 0.37251995 | Y22: =Y20/Y21 -> 0.34716594 | Z22: =Z20/Z21 -> 0.22558729 | AA22: =AA20/AA21 -> 0.16232879 | AO22: 8189 | AP22: 7269 | AQ22: 204 | AR22: 2018 | AW22: 2018 | AX22: =(AO22*1000000000)/(BE22*1000000) -> 9511.0337 | AY22: =(AQ22*1000000000)/(BE22*1000000) -> 236.9338 | AZ22: =AY22/AX22 -> 0.024911467 | BA22: =AO22/BB22 -> 12.096012 | BB22: 677 | BC22: 787 | BE22: 861
C23: Wolfram production prices | D23: ='MRA - Wolfram - Tungsten'!O6 -> 12737.778 | E23: ='MRA - Wolfram - Tungsten'!P6 -> 11327.25 | F23: ='MRA - Wolfram - Tungsten'!Q6 -> 10091.2 | G23: ='MRA - Wolfram - Tungsten'!R6 -> 7377.5 | H23: ='MRA - Wolfram - Tungsten'!S6 -> 5573.1053
C24: Wolfram export prices | D24: ='MRA - Wolfram - Tungsten'!O18 -> 15002.265 | E24: ='MRA - Wolfram - Tungsten'!P18 -> 13550.387 | F24: ='MRA - Wolfram - Tungsten'!Q18 -> 12008.306 | G24: ='MRA - Wolfram - Tungsten'!R18 -> 9719.2994 | H24: ='MRA - Wolfram - Tungsten'!S18 -> 6919.5569 | W24: 2012 | X24: 2013 | Y24: 2014 | Z24: 2015 | AA24: 2016 | AB24: 2017
V25: Cassiterite | W25: =W17/W$21 -> 0.10310699 | X25: =X17/X$21 -> 0.10080405 | Y25: =Y17/Y$21 -> 0.12284714 | Z25: =Z17/Z$21 -> 0.065610467 | AA25: =AA17/AA$21 -> 0.065379046 | AB25: =AB17/AB$21 -> 0.058608087
V26: Coltan | W26: =W18/W$21 -> 0.11093246 | X26: =X18/X$21 -> 0.22211182 | Y26: =Y18/Y$21 -> 0.17891241 | Z26: =Z18/Z$21 -> 0.12676658 | AA26: =AA18/AA$21 -> 0.07464762 | AB26: =AB18/AB$21 -> 0.072693881
V27: Wolfram | W27: =W19/W$21 -> 0.051190958 | X27: =X19/X$21 -> 0.049604074 | Y27: =Y19/Y$21 -> 0.045406383 | Z27: =Z19/Z$21 -> 0.033210246 | AA27: =AA19/AA$21 -> 0.02230212 | AB27: =AB19/AB$21 -> 0.014728928
V28: Mining GDP as % to total GDP | W28: =AZ16 -> 0.021253287 | X28: =AZ17 -> 0.025157233 | Y28: =AZ18 -> 0.026893524 | Z28: =AZ19 -> 0.022117962 | AA28: =AZ20 -> 0.020533573 | AB28: =AZ21 -> 0.023947368
W29: =W20/W$21 -> 0.2652304 | X29: =X20/X$21 -> 0.37251995 | Y29: =Y20/Y$21 -> 0.34716594 | Z29: =Z20/Z$21 -> 0.22558729 | AA29: =AA20/AA$21 -> 0.16232879 | AB29: =AB20/AB$21 -> 0.1460309 | AQ29: 1999 | AR29: 2000 | AS29: 2001 | AT29: 2002 | AU29: 2003 | AV29: 2004 | AW29: 2005 | AX29: 2006 | AY29: 2007 | AZ29: 2008 | BA29: 2009 | BB29: 2010 | BC29: 2011 | BD29: 2012 | BE29: 2013 | BF29: 2014 | BG29: 2015 | BH29: 2016 | BI29: 2017
AP30: Mining GDP as % of GDP | AQ30: 0.001 | AR30: 0.002 | AS30: 0.008 | AT30: 0.003 | AU30: 0.003 | AV30: 0.007 | AW30: 0.007 | AX30: 0.013 | AY30: 0.021 | AZ30: 0.019 | BA30: 0.011 | BB30: 0.014 | BC30: 0.026 | BD30: 0.021 | BE30: 0.025 | BF30: 0.027 | BG30: 0.022 | BH30: 0.021 | BI30: 0.023 | BJ30: 0.023
C35: Resource rents
D36: 2012 | E36: 2013 | F36: 2014 | G36: 2015 | H36: 2016
C37: Cassiterite resource rent: producers | D37: ='MRA - Cassiterite - Tin'!O13/1000000 -> -1.2327222 | E37: ='MRA - Cassiterite - Tin'!P13/1000000 -> -2.1867555 | F37: ='MRA - Cassiterite - Tin'!Q13/1000000 -> -2.5543604 | G37: ='MRA - Cassiterite - Tin'!R13/1000000 -> -1.1584454 | H37: ='MRA - Cassiterite - Tin'!S13/1000000 -> -0.53785285
C38: Cassiterite resource rent: traders | D38: ='MRA - Cassiterite - Tin'!O26/1000000 -> -1.9266613 | E38: ='MRA - Cassiterite - Tin'!P26/1000000 -> -2.1797197 | F38: ='MRA - Cassiterite - Tin'!Q26/1000000 -> -2.5808971 | G38: ='MRA - Cassiterite - Tin'!R26/1000000 -> -1.2228392 | H38: ='MRA - Cassiterite - Tin'!S26/1000000 -> -1.2422779
C39: Coltan resource rent: producers | D39: ='MRA - Coltan - Tantalum'!O13/1000000 -> -1.7583125 | E39: ='MRA - Coltan - Tantalum'!P13/1000000 -> -3.7908595 | F39: ='MRA - Coltan - Tantalum'!Q13/1000000 -> -3.3189139 | G39: ='MRA - Coltan - Tantalum'!R13/1000000 -> -1.977032 | H39: ='MRA - Coltan - Tantalum'!S13/1000000 -> -3.1433068
C40: Coltan resource rent: traders | D40: ='MRA - Coltan - Tantalum'!O26/1000000 -> -2.0728885 | E40: ='MRA - Coltan - Tantalum'!P26/1000000 -> -4.8027983 | F40: ='MRA - Coltan - Tantalum'!Q26/1000000 -> -3.7587731 | G40: ='MRA - Coltan - Tantalum'!R26/1000000 -> -2.3626587 | H40: ='MRA - Coltan - Tantalum'!S26/1000000 -> -1.4183916
C41: Wolfram resource rent: producers | D41: ='MRA - Wolfram - Tungsten'!O13/1000000 -> -0.82237912 | E41: ='MRA - Wolfram - Tungsten'!P13/1000000 -> -0.89992617 | F41: ='MRA - Wolfram - Tungsten'!Q13/1000000 -> -0.90626441 | G41: ='MRA - Wolfram - Tungsten'!R13/1000000 -> -0.5615861 | H41: ='MRA - Wolfram - Tungsten'!S13/1000000 -> -0.2929371 | AD41: GROSS DOMESTIC PRODUCT (GDP) | AE41: =GDP!AY7 -> 8189
C42: Wolfram resource rent: traders | D42: ='MRA - Wolfram - Tungsten'!O26/1000000 -> -0.95655631 | E42: ='MRA - Wolfram - Tungsten'!P26/1000000 -> -1.0726055 | F42: ='MRA - Wolfram - Tungsten'!Q26/1000000 -> -0.95394324 | G42: ='MRA - Wolfram - Tungsten'!R26/1000000 -> -0.61896819 | H42: ='MRA - Wolfram - Tungsten'!S26/1000000 -> -0.42376621 | AD42: AGRICULTURE, FORESTRY & FISHING | AE42: =GDP!AY9 -> 2378 | AF42: Agriculture | AG42: =AE42/$AE$41 -> 0.29038955
AD43: Mining & quarrying | AE43: =GDP!AY16 -> 204 | AF43: Mining & quarrying | AG43: =AE43/$AE$41 -> 0.024911467
AD44: TOTAL MANUFACTURING | AE44: =GDP!AY17 -> 482 | AF44: Manufacturng | AG44: =AE44/$AE$41 -> 0.058859446
AD45: Electricity | AE45: =GDP!AY26 -> 96 | AF45: Electricity | AG45: =AE45/$AE$41 -> 0.011723043
AD46: Water & waste management | AE46: =GDP!AY27 -> 39 | AF46: Water & waste management | AG46: =AE46/$AE$41 -> 0.0047624863
AD47: Construction | AE47: =GDP!AY28 -> 508 | AF47: Construction | AG47: =AE47/$AE$41 -> 0.062034436
AD48: TRADE &TRANSPORT | AE48: =GDP!AY30 -> 963 | AF48: Trade and transport | AG48: =AE48/$AE$41 -> 0.11759678
AD49: OTHER SERVICES | AE49: =GDP!AY34 -> 2952 | AF49: Other services | AG49: =AE49/$AE$41 -> 0.36048358
AD50: TAXES LESS SUBSIDIES ON PRODUCTS | AE50: =GDP!AY46 -> 568 | AF50: Taxes less subsidies | AG50: =AE50/$AE$41 -> 0.069361338
AF53: Agriculture | AG53: =AG42 -> 0.29038955
C54: Resource rent and royalties | AF54: Mining & quarrying | AG54: =AG43 -> 0.024911467
D55: 2012 | E55: 2013 | F55: 2014 | G55: 2015 | H55: 2016 | AF55: Manufacturing | AG55: =AG44 -> 0.058859446
C56: Cassiterite: total resource rent | D56: =('MRA - Cassiterite - Tin'!O13+'MRA - Cassiterite - Tin'!O26)/1000000 -> -3.1593835 | E56: =('MRA - Cassiterite - Tin'!P13+'MRA - Cassiterite - Tin'!P26)/1000000 -> -4.3664752 | F56: =('MRA - Cassiterite - Tin'!Q13+'MRA - Cassiterite - Tin'!Q26)/1000000 -> -5.1352575 | G56: =('MRA - Cassiterite - Tin'!R13+'MRA - Cassiterite - Tin'!R26)/1000000 -> -2.3812846 | H56: =('MRA - Cassiterite - Tin'!S13+'MRA - Cassiterite - Tin'!S26)/1000000 -> -1.7801308 | AF56: Other services | AG56: =AG49 -> 0.36048358
C57: Cassiterite: royalties | D57: =('MRA - Cassiterite - Tin'!O28)/1000000 -> 0 | E57: =('MRA - Cassiterite - Tin'!P28)/1000000 -> 1.2214896 | F57: =('MRA - Cassiterite - Tin'!Q28)/1000000 -> 2.8778247 | G57: =('MRA - Cassiterite - Tin'!R28)/1000000 -> 1.3705298 | H57: =('MRA - Cassiterite - Tin'!S28)/1000000 -> 1.3923162 | AF57: Taxes less subsidies | AG57: =AG50 -> 0.069361338
C58: Coltan: total resource rent | D58: =('MRA - Coltan - Tantalum'!O13+'MRA - Coltan - Tantalum'!O26)/1000000 -> -3.831201 | E58: =('MRA - Coltan - Tantalum'!P13+'MRA - Coltan - Tantalum'!P26)/1000000 -> -8.5936578 | F58: =('MRA - Coltan - Tantalum'!Q13+'MRA - Coltan - Tantalum'!Q26)/1000000 -> -7.077687 | G58: =('MRA - Coltan - Tantalum'!R13+'MRA - Coltan - Tantalum'!R26)/1000000 -> -4.3396907 | H58: =('MRA - Coltan - Tantalum'!S13+'MRA - Coltan - Tantalum'!S26)/1000000 -> -4.5616983 | AF58: Trade and transport | AG58: =AG48 -> 0.11759678
C59: Coltan: royalties | D59: =('MRA - Coltan - Tantalum'!O28)/1000000 -> 0 | E59: =('MRA - Coltan - Tantalum'!P28)/1000000 -> 2.6914323 | F59: =('MRA - Coltan - Tantalum'!Q28)/1000000 -> 4.1912132 | G59: =('MRA - Coltan - Tantalum'!R28)/1000000 -> 2.6480129 | H59: =('MRA - Coltan - Tantalum'!S28)/1000000 -> 1.5897003 | AF59: Electricity | AG59: =AG45 -> 0.011723043
C60: Wolfram: total resource rent | D60: =('MRA - Wolfram - Tungsten'!O13+'MRA - Wolfram - Tungsten'!O26)/1000000 -> -1.7789354 | E60: =('MRA - Wolfram - Tungsten'!P13+'MRA - Wolfram - Tungsten'!P26)/1000000 -> -1.9725317 | F60: =('MRA - Wolfram - Tungsten'!Q13+'MRA - Wolfram - Tungsten'!Q26)/1000000 -> -1.8602077 | G60: =('MRA - Wolfram - Tungsten'!R13+'MRA - Wolfram - Tungsten'!R26)/1000000 -> -1.1805543 | H60: =('MRA - Wolfram - Tungsten'!S13+'MRA - Wolfram - Tungsten'!S26)/1000000 -> -0.7167033 | AF60: Water & waste manmnt | AG60: =AG46 -> 0.0047624863
C61: Wolfram: royalties | D61: =('MRA - Wolfram - Tungsten'!O28)/1000000 -> 0 | E61: =('MRA - Wolfram - Tungsten'!P28)/1000000 -> 0.60107565 | F61: =('MRA - Wolfram - Tungsten'!Q28)/1000000 -> 1.0636927 | G61: =('MRA - Wolfram - Tungsten'!R28)/1000000 -> 0.69372515 | H61: =('MRA - Wolfram - Tungsten'!S28)/1000000 -> 0.4749473 | AF61: Construction | AG61: =AG47 -> 0.062034436
C64: Resource rent and royalties
D65: 2012-2016
C66: Total resource rent | D66: =(SUM('MRA - Cassiterite - Tin'!O26:S26)+SUM('MRA - Cassiterite - Tin'!O13:S13)+SUM('MRA - Coltan - Tantalum'!O26:S26)+SUM('MRA - Coltan - Tantalum'!O13:S13)+SUM('MRA - Wolfram - Tungsten'!O13:S13)+SUM('MRA - Wolfram - Tungsten'!O26:S26))/1000000 -> -52.735399
C67: Total royalties | D67: =(SUM('MRA - Wolfram - Tungsten'!O28:S28)+SUM('MRA - Coltan - Tantalum'!O28:S28)+SUM('MRA - Cassiterite - Tin'!O28:S28))/1000000 -> 20.81596
C74: Distribution of costs:
D75: Traders of 3Ts: 2016 | F75: Miners of 3Ts: 2016
C76: Purchases of raw material | D76: ='MRA - Wolfram - Tungsten'!S20+'MRA - Coltan - Tantalum'!S20+'MRA - Cassiterite - Tin'!S20 -> 73861631 | E76: Purchases of raw material | F76: =G76*'IBES data'!U10 -> 64666848 | G76: ='MRA - Cassiterite - Tin'!S8+'MRA - Coltan - Tantalum'!S8+'MRA - Wolfram - Tungsten'!S8 -> 95787822
C77: Intermediate consumption | D77: ='MRA - Wolfram - Tungsten'!S21+'MRA - Coltan - Tantalum'!S21+'MRA - Cassiterite - Tin'!S21 -> 0 | E77: Interm. consump. excl. purchases or material | F77: =G76-F76 -> 31120974
C78: Other operating and overhead costs | D78: ='MRA - Wolfram - Tungsten'!S22+'MRA - Coltan - Tantalum'!S22+'MRA - Cassiterite - Tin'!S22 -> 14022666 | E78: Other operating and overhead costs | F78: ='MRA - Cassiterite - Tin'!S9+'MRA - Coltan - Tantalum'!S9+'MRA - Wolfram - Tungsten'!S9 -> 17495144
C79: Consumption of capital | D79: ='MRA - Wolfram - Tungsten'!S23+'MRA - Coltan - Tantalum'!S23+'MRA - Cassiterite - Tin'!S23 -> 792308.27 | E79: Consumption of capital | F79: ='MRA - Cassiterite - Tin'!S10+'MRA - Coltan - Tantalum'!S10+'MRA - Wolfram - Tungsten'!S10 -> 1926943.7
C80: Opportunity cost of capital | D80: ='MRA - Wolfram - Tungsten'!S24+'MRA - Coltan - Tantalum'!S24+'MRA - Cassiterite - Tin'!S24 -> 831923.69 | E80: Opportunity cost of capital | F80: ='MRA - Cassiterite - Tin'!S11+'MRA - Coltan - Tantalum'!S11+'MRA - Wolfram - Tungsten'!S11 -> 2023290.9
D83: Miners of 3Ts: 2016 | E83: Traders of 3Ts: 2016
C84: =C76 -> Purchases of raw material | D84: =F76/SUM(F$76:F$80) -> 0.55160865 | E84: =D76/SUM(D$76:D$80) -> 0.82519099
C85: =C77 -> Intermediate consumption | D85: =F77/SUM(F$76:F$80) -> 0.26546212 | E85: =D77/SUM(D$76:D$80) -> 0
C86: =C78 -> Other operating and overhead costs | D86: =F78/SUM(F$76:F$80) -> 0.1492337 | E86: =D78/SUM(D$76:D$80) -> 0.1566629
C87: =C79 -> Consumption of capital | D87: =F79/SUM(F$76:F$80) -> 0.016436843 | E87: =D79/SUM(D$76:D$80) -> 0.0088517629
C88: =C80 -> Opportunity cost of capital | D88: =F80/SUM(F$76:F$80) -> 0.017258685 | E88: =D80/SUM(D$76:D$80) -> 0.009294351
AK92: 2012 | AL92: 2013 | AM92: 2014 | AN92: 2015 | AO92: 2016
AI93: US$/t | AJ93: Cassiteriate | AK93: ='MRA - Cassiterite - Tin'!O18 -> 11408.456 | AL93: ='MRA - Cassiterite - Tin'!P18 -> 12476.229 | AM93: ='MRA - Cassiterite - Tin'!Q18 -> 12083.99 | AN93: ='MRA - Cassiterite - Tin'!R18 -> 8909.5964 | AO93: ='MRA - Cassiterite - Tin'!S18 -> 9805.278 | AP93: Table
AI94: US$/t | AJ94: Tin | AK94: 21109 | AL94: 22281 | AM94: 21898 | AN94: 16066 | AO94: 17933 | AP94: https://www.metalary.com/tin-price/
D95: 2012 | E95: 2013 | F95: 2014 | G95: 2015 | H95: 2016 | AI95: US$/t | AJ95: Coltan | AK95: ='MRA - Coltan - Tantalum'!O18 -> 49718.149 | AL95: ='MRA - Coltan - Tantalum'!P18 -> 54570.285 | AM95: ='MRA - Coltan - Tantalum'!Q18 -> 45506.828 | AN95: ='MRA - Coltan - Tantalum'!R18 -> 40079.84 | AO95: ='MRA - Coltan - Tantalum'!S18 -> 31294.811 | AP95: Table
C96: Value of sales: Cassiterite mining operators | D96: ='MRA - Cassiterite - Tin'!O7/1000000 -> 33.819884 | E96: ='MRA - Cassiterite - Tin'!P7/1000000 -> 62.321073 | F96: ='MRA - Cassiterite - Tin'!Q7/1000000 -> 72.098392 | G96: ='MRA - Cassiterite - Tin'!R7/1000000 -> 33.01492 | H96: ='MRA - Cassiterite - Tin'!S7/1000000 -> 15.328447 | AI96: US$/t | AJ96: Tantalum | AK96: 292000 | AL96: 317000 | AM96: 152000 | AN96: 174000 | AO96: 134000 | AP96: https://www.metalary.com/tantalum-price/
C97: Value of exports: Cassiterite exports | D97: ='MRA - Cassiterite - Tin'!O19/1000000 -> 52.896906 | E97: ='MRA - Cassiterite - Tin'!P19/1000000 -> 61.074479 | F97: ='MRA - Cassiterite - Tin'!Q19/1000000 -> 71.945617 | G97: ='MRA - Cassiterite - Tin'!R19/1000000 -> 34.263244 | H97: ='MRA - Cassiterite - Tin'!S19/1000000 -> 34.807904 | AI97: US$/t | AJ97: Wolfram | AK97: ='MRA - Wolfram - Tungsten'!O18 -> 15002.265 | AL97: ='MRA - Wolfram - Tungsten'!P18 -> 13550.387 | AM97: ='MRA - Wolfram - Tungsten'!Q18 -> 12008.306 | AN97: ='MRA - Wolfram - Tungsten'!R18 -> 9719.2994 | AO97: ='MRA - Wolfram - Tungsten'!S18 -> 6919.5569 | AP97: Table
C98: Value of sales: Coltan mining operators | D98: ='MRA - Coltan - Tantalum'!O7/1000000 -> 48.239518 | E98: ='MRA - Coltan - Tantalum'!P7/1000000 -> 108.03697 | F98: ='MRA - Coltan - Tantalum'!Q7/1000000 -> 93.678385 | G98: ='MRA - Coltan - Tantalum'!R7/1000000 -> 56.344093 | H98: ='MRA - Coltan - Tantalum'!S7/1000000 -> 89.582145 | AI98: US$/t | AJ98: Tungsten | AK98: 56700 | AL98: 46600 | AM98: 43840 | AN98: 40320 | AO98: 38150 | AP98: https://www.metalary.com/tungsten-price/
C99: Value of exports: Coltan exports | D99: ='MRA - Coltan - Tantalum'!O19/1000000 -> 56.911605 | E99: ='MRA - Coltan - Tantalum'!P19/1000000 -> 134.57161 | F99: ='MRA - Coltan - Tantalum'!Q19/1000000 -> 104.78033 | G99: ='MRA - Coltan - Tantalum'!R19/1000000 -> 66.200323 | H99: ='MRA - Coltan - Tantalum'!S19/1000000 -> 39.742507
C100: Value of sales: Wolfram mining operators | D100: ='MRA - Wolfram - Tungsten'!O7/1000000 -> 22.562072 | E100: ='MRA - Wolfram - Tungsten'!P7/1000000 -> 25.647295 | F100: ='MRA - Wolfram - Tungsten'!Q7/1000000 -> 25.57987 | G100: ='MRA - Wolfram - Tungsten'!R7/1000000 -> 16.004829 | H100: ='MRA - Wolfram - Tungsten'!S7/1000000 -> 8.3485118
C101: Value of exports: Wolfram exports | D101: ='MRA - Wolfram - Tungsten'!O19/1000000 -> 26.262462 | E101: ='MRA - Wolfram - Tungsten'!P19/1000000 -> 30.053782 | F101: ='MRA - Wolfram - Tungsten'!Q19/1000000 -> 26.592318 | G101: ='MRA - Wolfram - Tungsten'!R19/1000000 -> 17.343129 | H101: ='MRA - Wolfram - Tungsten'!S19/1000000 -> 11.873683 | AK101: 2012 | AL101: 2013 | AM101: 2014 | AN101: 2015 | AO101: 2016
AJ102: Cassiterite as % of Tin | AK102: =AK93/AK94 -> 0.54045459 | AL102: =AL93/AL94 -> 0.55994925 | AM102: =AM93/AM94 -> 0.55183078 | AN102: =AN93/AN94 -> 0.55456221 | AO102: =AO93/AO94 -> 0.54677288
AJ103: Coltan as % of Tantalum | AK103: =AK95/AK96 -> 0.17026763 | AL103: =AL95/AL96 -> 0.17214601 | AM103: =AM95/AM96 -> 0.29938703 | AN103: =AN95/AN96 -> 0.23034391 | AO103: =AO95/AO96 -> 0.23354336
AJ104: Wolfram as % of Tungsten | AK104: =AK97/AK98 -> 0.26459021 | AL104: =AL97/AL98 -> 0.29078083 | AM104: =AM97/AM98 -> 0.27391209 | AN104: =AN97/AN98 -> 0.24105405 | AO104: =AO97/AO98 -> 0.18137764
D114: 2016 | N114: 0.035 | O114: 0.06 | P114: 0.09 | Q114: 0.12
C115: Total sales by operators | D115: ='MRA - Cassiterite - Tin'!S7+'MRA - Coltan - Tantalum'!S7+'MRA - Wolfram - Tungsten'!S7 -> 1.132591e+08 | K115: 2016
C116: Number of people | D116: 53369 | K116: Sales | L116: Production cost | M116: Resource rent | N116: Average unit price: +3,5% | O116: Average unit price: +6% | P116: Average unit price: +9% | Q116: Average unit price: +12%
C117: Income | D117: =D115/D116 -> 2122.189 | J117: Cassiterite: Operators | K117: ='MRA - Cassiterite - Tin'!S7 -> 15328447 | L117: =SUM('MRA - Cassiterite - Tin'!S8:S11) -> 15866300 | M117: =K117-L117 -> -537852.85 | N117: =($K117*(1+N$114))-$L117 -> -1357.1934 | O117: =($K117*(1+O$114))-$L117 -> 381853.99 | P117: =($K117*(1+P$114))-$L117 -> 841707.41 | Q117: =($K117*(1+Q$114))-$L117 -> 1301560.8
C118: days | D118: 260 | J118: Cassiterite: Traders | K118: ='MRA - Cassiterite - Tin'!S19 -> 34807904 | L118: =SUM('MRA - Cassiterite - Tin'!S20:S24) -> 36050182 | M118: =K118-L118 -> -1242277.9 | N118: =($K118*(1+N$114))-$L118 -> -24001.259 | O118: =($K118*(1+O$114))-$L118 -> 846196.34 | P118: =($K118*(1+P$114))-$L118 -> 1890433.5 | Q118: =($K118*(1+Q$114))-$L118 -> 2934670.6
D119: =D117/D118 -> 8.1622654 | J119: Coltan: Operators | K119: ='MRA - Coltan - Tantalum'!S7 -> 89582145 | L119: =SUM('MRA - Coltan - Tantalum'!S8:S11) -> 92725452 | M119: =K119-L119 -> -3143306.8 | N119: =($K119*(1+N$114))-$L119 -> -7931.677 | O119: =($K119*(1+O$114))-$L119 -> 2231622 | P119: =($K119*(1+P$114))-$L119 -> 4919086.3 | Q119: =($K119*(1+Q$114))-$L119 -> 7606550.7
J120: Coltan: Traders | K120: ='MRA - Coltan - Tantalum'!S19 -> 39742507 | L120: =SUM('MRA - Coltan - Tantalum'!S20:S24) -> 41160898 | M120: =K120-L120 -> -1418391.6 | N120: =($K120*(1+N$114))-$L120 -> -27403.84 | O120: =($K120*(1+O$114))-$L120 -> 966158.83 | P120: =($K120*(1+P$114))-$L120 -> 2158434 | Q120: =($K120*(1+Q$114))-$L120 -> 3350709.2
J121: Wolfram: Operators | K121: ='MRA - Wolfram - Tungsten'!S7 -> 8348511.8 | L121: =SUM('MRA - Wolfram - Tungsten'!S8:S11) -> 8641448.9 | M121: =K121-L121 -> -292937.1 | N121: =($K121*(1+N$114))-$L121 -> -739.18412 | O121: =($K121*(1+O$114))-$L121 -> 207973.61 | P121: =($K121*(1+P$114))-$L121 -> 458428.97 | Q121: =($K121*(1+Q$114))-$L121 -> 708884.32
J122: Wolfram: Traders | K122: ='MRA - Wolfram - Tungsten'!S19 -> 11873683 | L122: =SUM('MRA - Wolfram - Tungsten'!S20:S24) -> 12297449 | M122: =K122-L122 -> -423766.21 | N122: =($K122*(1+N$114))-$L122 -> -8187.3168 | O122: =($K122*(1+O$114))-$L122 -> 288654.75 | P122: =($K122*(1+P$114))-$L122 -> 644865.22 | Q122: =($K122*(1+Q$114))-$L122 -> 1001075.7
J123: Total | K123: =SUM(K117:K122) -> 1.996832e+08 | L123: =SUM(L117:L122) -> 2.0674173e+08 | M123: =SUM(M117:M122) -> -7058532.4 | N123: =SUM(N117:N122) -> -69620.47 | O123: =SUM(O117:O122) -> 4922459.5 | P123: =SUM(P117:P122) -> 10912955 | Q123: =SUM(Q117:Q122) -> 16903451

Sheet GDP
D1: Table 2 | AC1: Table 1
D2: Gross Domestic product by Kind of Activity | AC2: Gross Domestic product by Kind of Activity
D3: at constant 2014 prices | AC3: at current prices
D4: ( in billion Rwf) | AC4: ( in billion Rwf)
D5: Activity description | E5: ISIC4 | G5: 1999 | H5: 2000 | I5: 2001 | J5: 2002 | K5: 2003 | L5: 2004 | M5: 2005 | N5: 2006 | O5: 2007 | P5: 2008 | Q5: 2009 | R5: 2010 | S5: 2011 | T5: 2012 | U5: 2013 | V5: 2014 | W5: 2015 | X5: 2016 | Y5: 2017 | Z5: 2018 | AC5: Activity description | AD5: ISIC4 | AF5: 1999 | AG5: 2000 | AH5: 2001 | AI5: 2002 | AJ5: 2003 | AK5: 2004 | AL5: 2005 | AM5: 2006 | AN5: 2007 | AO5: 2008 | AP5: 2009 | AQ5: 2010 | AR5: 2011 | AS5: 2012 | AT5: 2013 | AU5: 2014 | AV5: 2015 | AW5: 2016 | AX5: 2017 | AY5: 2018
D7: GROSS DOMESTIC PRODUCT (GDP) | F7: 0 | G7: 1760 | H7: 1907 | I7: 2069 | J7: 2342 | K7: 2393 | L7: 2572 | M7: 2813 | N7: 3072 | O7: 3307 | P7: 3676 | Q7: 3906 | R7: 4192 | S7: 4526 | T7: 4917 | U7: 5149 | V7: 5466 | W7: 5951 | X7: 6307 | Y7: 6693 | Z7: 7269 | AC7: GROSS DOMESTIC PRODUCT (GDP) | AF7: 607 | AG7: 676 | AH7: 742 | AI7: 797 | AJ7: 993 | AK7: 1206 | AL7: 1440 | AM7: 1762 | AN7: 2120 | AO7: 2693 | AP7: 3097 | AQ7: 3411 | AR7: 3990 | AS7: 4564 | AT7: 4929 | AU7: 5466 | AV7: 5968 | AW7: 6672 | AX7: 7600 | AY7: 8189
D9: AGRICULTURE, FORESTRY & FISHING | E9: A | F9: 0 | G9: 702 | H9: 754 | I9: 821 | J9: 960 | K9: 930 | L9: 947 | M9: 1008 | N9: 1036 | O9: 1063 | P9: 1132 | Q9: 1219 | R9: 1280 | S9: 1336 | T9: 1427 | U9: 1474 | V9: 1572 | W9: 1650 | X9: 1714 | Y9: 1827 | Z9: 1934 | AC9: AGRICULTURE, FORESTRY & FISHING | AD9: A | AF9: 227 | AG9: 251 | AH9: 277 | AI9: 282 | AJ9: 380 | AK9: 465 | AL9: 553 | AM9: 592 | AN9: 635 | AO9: 753 | AP9: 896 | AQ9: 949 | AR9: 1112 | AS9: 1317 | AT9: 1424 | AU9: 1572 | AV9: 1671 | AW9: 1956 | AX9: 2352 | AY9: 2378
D10: Food crops | E10: AA | F10: 0 | G10: 398 | H10: 428 | I10: 466 | J10: 553 | K10: 533 | L10: 531 | M10: 573 | N10: 581 | O10: 604 | P10: 642 | Q10: 702 | R10: 737 | S10: 764 | T10: 827 | U10: 859 | V10: 934 | W10: 968 | X10: 998 | Y10: 1071 | Z10: 1118 | AC10: Food crops | AD10: AA | AF10: 194 | AG10: 217 | AH10: 238 | AI10: 238 | AJ10: 332 | AK10: 396 | AL10: 467 | AM10: 309 | AN10: 353 | AO10: 397 | AP10: 496 | AQ10: 519 | AR10: 606 | AS10: 740 | AT10: 839 | AU10: 934 | AV10: 992 | AW10: 1208 | AX10: 1504 | AY10: 1342
D11: Export crops | E11: AB | F11: 0 | G11: 60 | H11: 69 | I11: 79 | J11: 83 | K11: 69 | L11: 112 | M11: 87 | N11: 115 | O11: 82 | P11: 106 | Q11: 90 | R11: 102 | S11: 105 | T11: 114 | U11: 109 | V11: 107 | W11: 122 | X11: 125 | Y11: 128 | Z11: 140 | AC11: Export crops | AD11: AB | AF11: 6 | AG11: 7 | AH11: 8 | AI11: 7 | AJ11: 7 | AK11: 13 | AL11: 18 | AM11: 70 | AN11: 50 | AO11: 67 | AP11: 64 | AQ11: 79 | AR11: 82 | AS11: 106 | AT11: 83 | AU11: 107 | AV11: 109 | AW11: 129 | AX11: 172 | AY11: 185
D12: Livestock & livestock products | E12: AC | F12: 0 | G12: 88 | H12: 92 | I12: 98 | J12: 102 | K12: 107 | L12: 111 | M12: 116 | N12: 121 | O12: 124 | P12: 128 | Q12: 132 | R12: 138 | S12: 142 | T12: 151 | U12: 160 | V12: 174 | W12: 189 | X12: 208 | Y12: 231 | Z12: 262 | AC12: Livestock & livestock products | AD12: AC | AF12: 16 | AG12: 16 | AH12: 18 | AI12: 21 | AJ12: 22 | AK12: 26 | AL12: 27 | AM12: 68 | AN12: 71 | AO12: 91 | AP12: 108 | AQ12: 113 | AR12: 127 | AS12: 143 | AT12: 158 | AU12: 174 | AV12: 195 | AW12: 223 | AX12: 260 | AY12: 301
D13: Forestry | E13: AD | F13: 0 | G13: 153 | H13: 161 | I13: 173 | J13: 190 | K13: 207 | L13: 225 | M13: 244 | N13: 264 | O13: 272 | P13: 282 | Q13: 289 | R13: 298 | S13: 306 | T13: 317 | U13: 326 | V13: 337 | W13: 350 | X13: 362 | Y13: 374 | Z13: 390 | AC13: Forestry | AD13: AD | AF13: 8 | AG13: 8 | AH13: 10 | AI13: 13 | AJ13: 15 | AK13: 26 | AL13: 35 | AM13: 169 | AN13: 174 | AO13: 227 | AP13: 244 | AQ13: 258 | AR13: 283 | AS13: 312 | AT13: 325 | AU13: 337 | AV13: 354 | AW13: 372 | AX13: 391 | AY13: 520
D14: Fishing | E14: AE | F14: 0 | G14: 13 | H14: 13 | I14: 14 | J14: 15 | K14: 15 | L14: 16 | M14: 16 | N14: 16 | O14: 17 | P14: 17 | Q14: 18 | R14: 18 | S14: 19 | T14: 18 | U14: 19 | V14: 20 | W14: 21 | X14: 21 | Y14: 22 | Z14: 23 | AC14: Fishing | AD14: AE | AF14: 3 | AG14: 3 | AH14: 3 | AI14: 3 | AJ14: 4 | AK14: 5 | AL14: 5 | AM14: 6 | AN14: 7 | AO14: 9 | AP14: 10 | AQ14: 12 | AR14: 14 | AS14: 16 | AT14: 19 | AU14: 20 | AV14: 22 | AW14: 23 | AX14: 26 | AY14: 29
D15: INDUSTRY | E15: B-F | F15: 0 | G15: 263 | H15: 267 | I15: 301 | J15: 323 | K15: 338 | L15: 390 | M15: 426 | N15: 476 | O15: 519 | P15: 598 | Q15: 606 | R15: 656 | S15: 773 | T15: 838 | U15: 916 | V15: 939 | W15: 1023 | X15: 1092 | Y15: 1141 | Z15: 1259 | AC15: INDUSTRY | AD15: B-F | AF15: 93 | AG15: 97 | AH15: 111 | AI15: 117 | AJ15: 135 | AK15: 177 | AL15: 214 | AM15: 249 | AN15: 323 | AO15: 418 | AP15: 470 | AQ15: 539 | AR15: 699 | AS15: 804 | AT15: 848 | AU15: 939 | AV15: 1013 | AW15: 1092 | AX15: 1201 | AY15: 1329
D16: Mining & quarrying | E16: B | F16: 0 | G16: 21 | H16: 29 | I16: 79 | J16: 60 | K16: 48 | L16: 71 | M16: 93 | N16: 80 | O16: 114 | P16: 96 | Q16: 79 | R16: 71 | S16: 106 | T16: 98 | U16: 118 | V16: 147 | W16: 140 | X16: 154 | Y16: 189 | Z16: 193 | AC16: Mining & quarrying | AD16: B | AF16: 1 | AG16: 1 | AH16: 6 | AI16: 2 | AJ16: 3 | AK16: 8 | AL16: 10 | AM16: 23 | AN16: 43 | AO16: 51 | AP16: 33 | AQ16: 45 | AR16: 102 | AS16: 97 | AT16: 124 | AU16: 147 | AV16: 132 | AW16: 137 | AX16: 182 | AY16: 204
D17: TOTAL MANUFACTURING | E17: C | F17: 0 | G17: 141 | H17: 141 | I17: 155 | J17: 178 | K17: 186 | L17: 209 | M17: 227 | N17: 257 | O17: 259 | P17: 273 | Q17: 281 | R17: 307 | S17: 333 | T17: 352 | U17: 369 | V17: 322 | W17: 349 | X17: 372 | Y17: 396 | Z17: 439 | AC17: TOTAL MANUFACTURING | AD17: C | AF17: 63 | AG17: 66 | AH17: 68 | AI17: 78 | AJ17: 88 | AK17: 106 | AL17: 126 | AM17: 129 | AN17: 141 | AO17: 181 | AP17: 225 | AQ17: 255 | AR17: 288 | AS17: 331 | AT17: 291 | AU17: 322 | AV17: 352 | AW17: 388 | AX17: 450 | AY17: 482
D18: Of which: Food | E18: CA | F18: 0 | G18: 25 | H18: 26 | I18: 32 | J18: 36 | K18: 40 | L18: 54 | M18: 61 | N18: 71 | O18: 67 | P18: 73 | Q18: 77 | R18: 84 | S18: 88 | T18: 89 | U18: 96 | V18: 101 | W18: 102 | X18: 110 | Y18: 126 | Z18: 137 | AC18: Of which: Food | AD18: CA | AF18: 7 | AG18: 8 | AH18: 9 | AI18: 10 | AJ18: 13 | AK18: 21 | AL18: 28 | AM18: 34 | AN18: 35 | AO18: 46 | AP18: 57 | AQ18: 66 | AR18: 79 | AS18: 87 | AT18: 92 | AU18: 101 | AV18: 104 | AW18: 119 | AX18: 161 | AY18: 157
D19: Beverages & tobacco | E19: CB | F19: 0 | G19: 58 | H19: 53 | I19: 53 | J19: 64 | K19: 58 | L19: 59 | M19: 66 | N19: 71 | O19: 70 | P19: 72 | Q19: 75 | R19: 76 | S19: 82 | T19: 86 | U19: 89 | V19: 95 | W19: 101 | X19: 104 | Y19: 96 | Z19: 104 | AC19: Beverages & tobacco | AD19: CB | AF19: 19 | AG19: 18 | AH19: 18 | AI19: 23 | AJ19: 22 | AK19: 23 | AL19: 27 | AM19: 28 | AN19: 31 | AO19: 41 | AP19: 56 | AQ19: 61 | AR19: 66 | AS19: 76 | AT19: 85 | AU19: 95 | AV19: 102 | AW19: 109 | AX19: 112 | AY19: 121
D20: Textiles, clothing & leather goods | E20: CC | F20: 0 | G20: 32 | H20: 37 | I20: 39 | J20: 45 | K20: 50 | L20: 59 | M20: 65 | N20: 75 | O20: 82 | P20: 81 | Q20: 79 | R20: 81 | S20: 79 | T20: 86 | U20: 19 | V20: 20 | W20: 21 | X20: 23 | Y20: 28 | Z20: 34 | AC20: Textiles, clothing & leather goods | AD20: CC | AF20: 18 | AG20: 22 | AH20: 20 | AI20: 24 | AJ20: 28 | AK20: 34 | AL20: 40 | AM20: 46 | AN20: 51 | AO20: 59 | AP20: 58 | AQ20: 63 | AR20: 76 | AS20: 82 | AT20: 19 | AU20: 20 | AV20: 21 | AW20: 23 | AX20: 28 | AY20: 34
... D44: Cultural, domestic & other services | E44: R-T | F44: 0 | G44: 9 | H44: 48 | I44: 51 | J44: 64 | K44: 82 | L44: 95 | M44: 127 | N44: 152 | O44: 173 | P44: 177 | Q44: 167 | R44: 179 | S44: 178 | T44: 197 | U44: 221 | V44: 257 | W44: 306 | X44: 328 | Y44: 356 | Z44: 400 | AC44: Cultural, domestic & other services | AD44: R-T | AF44: 5 | AG44: 27 | AH44: 28 | AI44: 34 | AJ44: 47 | AK44: 58 | AL44: 83 | AM44: 105 | AN44: 123 | AO44: 138 | AP44: 141 | AQ44: 153 | AR44: 161 | AS44: 185 | AT44: 214 | AU44: 257 | AV44: 313 | AW44: 342 | AX44: 382 | AY44: 441
D46: TAXES LESS SUBSIDIES ON PRODUCTS | F46: 0 | G46: 168 | H46: 182 | I46: 197 | J46: 217 | K46: 216 | L46: 226 | M46: 240 | N46: 261 | O46: 272 | P46: 304 | Q46: 333 | R46: 349 | S46: 354 | T46: 361 | U46: 349 | V46: 377 | W46: 430 | X46: 449 | Y46: 431 | Z46: 492 | AC46: TAXES LESS SUBSIDIES ON PRODUCTS | AF46: 47 | AG46: 49 | AH46: 57 | AI46: 66 | AJ46: 81 | AK46: 98 | AL46: 112 | AM46: 129 | AN46: 157 | AO46: 215 | AP46: 239 | AQ46: 266 | AR46: 328 | AS46: 301 | AT46: 304 | AU46: 377 | AV46: 427 | AW46: 469 | AX46: 524 | AY46: 568
D48: Source: National Institute of Statistics of Rwanda | AC48: Source: National Institute of Statistics of Rwanda
D49: 43174 | AC49: =TODAY() -> 43965
D55: Agriculture, forestry and fishing | G55: =G9 -> 702 | H55: =H9 -> 754 | I55: =I9 -> 821 | J55: =J9 -> 960 | K55: =K9 -> 930 | L55: =L9 -> 947 | M55: =M9 -> 1008 | N55: =N9 -> 1036 | ... Z55: =Z9 -> 1934
D56: Mining & quarrying | G56: =G16 -> 21 | H56: =H16 -> 29 | I56: =I16 -> 79 | J56: =J16 -> 60 | K56: =K16 -> 48 | L56: =L16 -> 71 | M56: =M16 -> 93 | N56: =N16 -> 80 | ... Z56: =Z16 -> 193
D57: Manufacturing | G57: =G17 -> 141 | H57: =H17 -> 141 | I57: =I17 -> 155 | J57: =J17 -> 178 | K57: =K17 -> 186 | L57: =L17 -> 209 | M57: =M17 -> 227 | N57: =N17 -> 257 | ... Z57: =Z17 -> 439
D58: Electricity | G58: =G26 -> 49 | H58: =H26 -> 43 | I58: =I26 -> 39 | J58: =J26 -> 39 | K58: =K26 -> 35 | L58: =L26 -> 24 | M58: =M26 -> 21 | N58: =N26 -> 18 | ... Z58: =Z26 -> 68
D59: Water & waste management | G59: =G27 -> 37 | H59: =H27 -> 33 | I59: =I27 -> 30 | J59: =J27 -> 29 | K59: =K27 -> 27 | L59: =L27 -> 18 | M59: =M27 -> 16 | N59: =N27 -> 14 | ... Z59: =Z27 -> 34
D60: Construction | G60: =G28 -> 75 | H60: =H28 -> 77 | I60: =I28 -> 85 | J60: =J28 -> 87 | K60: =K28 -> 95 | L60: =L28 -> 114 | M60: =M28 -> 124 | N60: =N28 -> 140 | ... Z60: =Z28 -> 525
D61: Trade and transport | G61: =G30 -> 126 | H61: =H30 -> 144 | I61: =I30 -> 156 | J61: =J30 -> 179 | K61: =K30 -> 184 | L61: =L30 -> 210 | M61: =M30 -> 240 | N61: =N30 -> 290 | ... Z61: =Z30 -> 917
D62: Other services | G62: =G34 -> 607 | H62: =H34 -> 681 | I62: =I34 -> 714 | J62: =J34 -> 773 | K62: =K34 -> 847 | L62: =L34 -> 904 | M62: =M34 -> 1005 | N62: =N34 -> 1016 | ... Z62: =Z34 -> 2667
D63: Taxes less subsidies | G63: =G46 -> 168 | H63: =H46 -> 182 | I63: =I46 -> 197 | J63: =J46 -> 217 | K63: =K46 -> 216 | L63: =L46 -> 226 | M63: =M46 -> 240 | N63: =N46 -> 261 | ... Z63: =Z46 -> 492
G64: =SUM(G55:G63)-G7 -> 166 | H64: =SUM(H55:H63)-H7 -> 177 | I64: =SUM(I55:I63)-I7 -> 207 | J64: =SUM(J55:J63)-J7 -> 180 | K64: =SUM(K55:K63)-K7 -> 175 | L64: =SUM(L55:L63)-L7 -> 151 | M64: =SUM(M55:M63)-M7 -> 161 | N64: =SUM(N55:N63)-N7 -> 40 | ... Z64: =SUM(Z55:Z63)-Z7 -> 0
G67: =G5 -> 1999 | H67: =H5 -> 2000 | I67: =I5 -> 2001 | J67: =J5 -> 2002 | K67: =K5 -> 2003 | L67: =L5 -> 2004 | M67: =M5 -> 2005 | N67: =N5 -> 2006 | ... Z67: =Z5 -> 2018
F68: Agriculture, forestry and fishing | G68: =G55/G$7 -> 0.39886364 | H68: =H55/H$7 -> 0.39538542 | I68: =I55/I$7 -> 0.39681005 | J68: =J55/J$7 -> 0.40990606 | K68: =K55/K$7 -> 0.38863351 | L68: =L55/L$7 -> 0.36819596 | M68: =M55/M$7 -> 0.3583363 | N68: =N55/N$7 -> 0.33723958 | ... Z68: =Z55/Z$7 -> 0.26606136
F69: Mining & quarrying | G69: =G56/G$7 -> 0.011931818 | H69: =H56/H$7 -> 0.015207132 | I69: =I56/I$7 -> 0.038182697 | J69: =J56/J$7 -> 0.025619129 | K69: =K56/K$7 -> 0.020058504 | L69: =L56/L$7 -> 0.027604977 | M69: =M56/M$7 -> 0.033060789 | N69: =N56/N$7 -> 0.026041667 | ... Z69: =Z56/Z$7 -> 0.026551107
F70: Manufacturing | G70: =G57/G$7 -> 0.080113636 | H70: =H57/H$7 -> 0.073938123 | I70: =I57/I$7 -> 0.074915418 | J70: =J57/J$7 -> 0.076003416 | K70: =K57/K$7 -> 0.077726703 | L70: =L57/L$7 -> 0.08125972 | M70: =M57/M$7 -> 0.080696765 | N70: =N57/N$7 -> 0.083658854 | ... Z70: =Z57/Z$7 -> 0.060393452
F71: Electricity | G71: =G58/G$7 -> 0.027840909 | H71: =H58/H$7 -> 0.022548506 | I71: =I58/I$7 -> 0.018849686 | J71: =J58/J$7 -> 0.016652434 | K71: =K58/K$7 -> 0.014625992 | L71: =L58/L$7 -> 0.0093312597 | M71: =M58/M$7 -> 0.0074653395 | N71: =N58/N$7 -> 0.005859375 | ... Z71: =Z58/Z$7 -> 0.0093547943
F72: Water & waste management | G72: =G59/G$7 -> 0.021022727 | H72: =H59/H$7 -> 0.017304667 | I72: =I59/I$7 -> 0.014499758 | J72: =J59/J$7 -> 0.012382579 | K72: =K59/K$7 -> 0.011282908 | L72: =L59/L$7 -> 0.0069984448 | M72: =M59/M$7 -> 0.0056878777 | N72: =N59/N$7 -> 0.0045572917 | ... Z72: =Z59/Z$7 -> 0.0046773972
F73: Construction | G73: =G60/G$7 -> 0.042613636 | H73: =H60/H$7 -> 0.040377556 | I73: =I60/I$7 -> 0.041082649 | J73: =J60/J$7 -> 0.037147737 | K73: =K60/K$7 -> 0.039699122 | L73: =L60/L$7 -> 0.044323484 | M73: =M60/M$7 -> 0.044081052 | N73: =N60/N$7 -> 0.045572917 | ... Z73: =Z60/Z$7 -> 0.072224515
F74: Trade and transport | G74: =G61/G$7 -> 0.071590909 | H74: =H61/H$7 -> 0.075511274 | I74: =I61/I$7 -> 0.075398743 | J74: =J61/J$7 -> 0.076430401 | K74: =K61/K$7 -> 0.076890932 | L74: =L61/L$7 -> 0.081648523 | M74: =M61/M$7 -> 0.085318166 | N74: =N61/N$7 -> 0.094401042 | ... Z74: =Z61/Z$7 -> 0.12615215
F75: Other services | G75: =G62/G$7 -> 0.34488636 | H75: =H62/H$7 -> 0.3571054 | I75: =I62/I$7 -> 0.34509425 | J75: =J62/J$7 -> 0.33005978 | K75: =K62/K$7 -> 0.35394902 | L75: =L62/L$7 -> 0.35147745 | M75: =M62/M$7 -> 0.35726982 | N75: =N62/N$7 -> 0.33072917 | ... Z75: =Z62/Z$7 -> 0.36690054
F76: Taxes less subsidies | G76: =G63/G$7 -> 0.095454545 | H76: =H63/H$7 -> 0.095437861 | I76: =I63/I$7 -> 0.09521508 | J76: =J63/J$7 -> 0.09265585 | K76: =K63/K$7 -> 0.090263268 | L76: =L63/L$7 -> 0.087869362 | M76: =M63/M$7 -> 0.085318166 | N76: =N63/N$7 -> 0.084960938 | ... Z76: =Z63/Z$7 -> 0.067684688

Sheet Basic data - source records
AR1: Avg years:
AN2: # | AO2: Asset Category | AP2: Depreciation Rate | AR2: =ROUNDUP(1/AR8,0) -> 10
A3: Mineral produced and processed volumes (Tonnes) | I3: Mineral export volumes (Tonnes) | Q3: Mineral export values (USD) | Y3: Social discount rate (%) | AF3: Exchange rate Frw:USD | AN3: 1 | AO3: Land, fine arts, antiquities, jewellery and any other assets that are not subject to wear and tear or obsolescence | AP3: 0 | AQ3: 0 | AR3: 0
C4: 2012 | D4: 2013 | E4: 2014 | F4: 2015 | G4: 2016 | J4: 2012 | K4: 2013 | L4: 2014 | M4: 2015 | N4: 2016 | O4: 2017 | Q4: Mineral | R4: 2012 | S4: 2013 | T4: 2014 | U4: 2015 | V4: 2016 | W4: 2017 | Y4: 2012 | Z4: 2013 | AA4: 2014 | AB4: 2015 | AC4: 2016 | AD4: 2017 | AF4: 2012 | AG4: 2013 | AH4: 2014 | AI4: 2015 | AJ4: 2016 | AK4: 2017 | AN4: 2 | AO4: cost of acquisition or construction and the cost of refining, rehabilitation, reconstruction of buildings, equipment and heavy machinery fixed in walls | AP4: 5 % (of cost price) | AQ4: 0.05 | AR4: 0.55 | AS4: =SUM(AR4:AR7) -> 1
A5: Cassiteritte | B5: Production | C5: 3670.5237 | D5: 6112.1432 | E5: 7137.4683 | F5: 4714.1224 | G5: 2024 | I5: Cassiterite | J5: 4636.6403 | K5: 4895.2675 | L5: 5953.7963 | M5: 3845.6561 | N5: 3549.915 | O5: 4759.6213 | Q5: Cassiterite | R5: 52896906 | S5: 61074479 | T5: 71945617 | U5: 34263244 | V5: 34807904 | W5: 50154998 | Y5: 0.113 | Z5: =AB5 -> 0.105 | AA5: 0.107 | AB5: 0.105 | AC5: 0.105 | AD5: 0.101 | AF5: 614.29514 | AG5: 646.63597 | AH5: 681.86172 | AI5: 720.97511 | AJ5: 788 | AK5: 832 | AN5: 3 | AO5: The cost of acquisition or development and the cost of improvement, rehabilitation, and reconstruction of intangible assets including goodwill | AP5: 10% of the cost price | AQ5: 0.1 | AR5: 0.35
B6: Processed | C6: 4580.5478 | D6: 4794.5472 | E6: 5905.1961 | F6: 3205.177 | G6: 3288 | I6: Coltan | J6: 1144.6847 | K6: 2466.0237 | L6: 2302.5189 | M6: 1651.7113 | N6: 1269.9392 | O6: 1725.182 | Q6: Coltan | R6: 56911605 | S6: 1.3457161e+08 | T6: 1.0478033e+08 | U6: 66200323 | V6: 39742507 | W6: 62209186 | Y6: Source: BNR | AF6: www.statistics.gov.rw/file/5257/download?token=Dk0FmVmU | AN6: 4 | AO6: computers and accessories, information and communication systems, software | AP6: 0.5 | AQ6: 0.5 | AR6: 0.05
A7: Coltan | B7: Production | C7: 967.88761 | D7: 1924.3862 | E7: 2097.5135 | F7: 1332 | G7: 2553.6 | I7: Wolfram | J7: 1750.5665 | K7: 2217.928 | L7: 2214.4937 | M7: 1784.4011 | N7: 1715.9599 | O7: 1523.6765 | Q7: Wolfram | R7: 26262462 | S7: 30053782 | T7: 26592318 | U7: 17343129 | V7: 11873683 | W7: 12604563 | Y7: https://www.bnr.rw/index.php?id=88 | AN7: 5 | AO7: all other business assets | AP7: 0.25 | AQ7: 0.25 | AR7: 0.05
B8: Processed | C8: 942.2477 | D8: 2046.7615 | E8: 2284.907 | F8: 1590 | G8: 1176 | I8: Sources: RMB: Data provided by J.Butera & RNB | Q8: TOTAL | R8: =SUM(R5:R7) -> 1.3607097e+08 | S8: =SUM(S5:S7) -> 2.2569987e+08 | T8: =SUM(T5:T7) -> 2.0331827e+08 | U8: =SUM(U5:U7) -> 1.178067e+08 | V8: =SUM(V5:V7) -> 86424093 | W8: =SUM(W5:W7) -> 1.2496875e+08 | AR8: =SUMPRODUCT(AQ3:AQ7,AR3:AR7) -> 0.1
A9: Wolfram | B9: Production | C9: 1771.2722 | D9: 2264.212 | E9: 2534.869 | F9: 2169.4109 | G9: 1498 | Q9: Sources: RMB: Data provided by J.Butera & RNB
B10: Processed | C10: 1584.762 | D10: 2269.9648 | E10: 2058.8781 | F10: 1323 | G10: 1639 | AO10: INVESTMENT ALLOWANCES
A11: SOURCE: ITRI/iTSCi/PACT RWANDA | AO11: A registered investor shall be entitled to a flat accelerated depreciation rate of fifty per cent (50%) for the first year for new or used assets if he/she meets the following criteria :
AO13: Criteria | AP13: Rate
AO14: Investor operate in export projects - invest in business assets worth at least fifty thousand US dollars (USD 50,000) each; | AP14: 0.5
AO15: construction projects worth at least one million eight hundred thousand United States dollars (USD 1,800,000); | AP15: 0.5
AO16: Any other sectors provided the investment is worth at least one hundred thousand United States dollars (USD 100,000) | AP16: 0.5
AO18: Rwanda Investment Code, 2015

Sheet IBES data
A1: Integrated Business Enterprise Survey: 2015 (to be used for 2012 - 2015 eventually when IBES for other years are avialable, but for now for entire period)
A2: 2015Operators
B3: Mining operators
B4: Table III.2.2.1 | H4: Table III.2.2.2 | O4: Table III.2.2.4:
B5: Income statement for service sector, Frw billion | H5: Expenditure statement for services sector, Frw billion | O5: Summary assets of the services sector, Frw billion | W5: Asset structure | AB5: Opportunity cost of capital
B6: Income components | C6: Mining and Quarrying | D6: Mining Operators | E6: Mining Operators (US$:Mill) | F6: Structure | H6: Expenditure components | I6: Mining and Quarrying | J6: Mining Operators | K6: Mining Operators (US$:Mill) | L6: Structure | M6: Structure to use | O6: Assets | P6: Mining and Quarrying | Q6: Mining Operators | R6: Mining Operators (US$:Mill) | S6: Structure | U6: % of sales | W6: 2015 | AB6: 2012 | AC6: 2013 | AD6: 2014 | AE6: 2015 | AF6: 2016
B7: Sales of goods in the same condition as purchased | C7: 55.4 | D7: 51.741567 | E7: =D7*1000/'Basic data - source records'!$AI$5 -> 71.766093 | F7: =D7/$D$21 -> 0.59645928 | H7: Purchases of goods for resale | I7: 52.5 | J7: 49.529887 | K7: =J7*1000/'Basic data - source records'!$AI$5 -> 68.698471 | L7: =J7/$J$21 -> 0.5593356 | M7: =J7/$D$21 -> 0.57096379 | O7: Non-current assets | P7: 224 | Q7: 221.04983 | R7: =Q7*1000/'Basic data - source records'!$AI$5 -> 306.59843 | S7: =Q7/$Q$21 -> 0.24523724 | T7: Intermediate consumption | U7: =M7+M8+M9+M10+M11 -> 0.84574059 | W7: Value Cassiterite | X7: ='MRA - Cassiterite - Tin'!R7 -> 33014920 | Y7: =X7/$X$10 -> 0.31334203 | Z7: Non-current assets: Cassiterite | AA7: =Y7*R7 -> 96.070173 | AB7: =$AA7*'Basic data - source records'!Y$5*1000000 -> 10855930 | AC7: =$AA7*'Basic data - source records'!Z$5*1000000 -> 10087368 | AD7: =$AA7*'Basic data - source records'!AA$5*1000000 -> 10279508 | AE7: =$AA7*'Basic data - source records'!AB$5*1000000 -> 10087368 | AF7: =$AA7*'Basic data - source records'!AC$5*1000000 -> 10087368
B8: Sales of manufactured, mined or quarried products | C8: 49 | D8: 33.041979 | E8: =D8*1000/'Basic data - source records'!$AI$5 -> 45.829569 | F8: =D8/$D$21 -> 0.38089675 | H8: Purchases of raw materials, etc., used in manufacturing | I8: 21.9 | J8: 21.934295 | K8: =J8*1000/'Basic data - source records'!$AI$5 -> 30.423096 | L8: =J8/$J$21 -> 0.24770159 | M8: =J8/$D$21 -> 0.25285113 | O8: Fixed assets | P8: 222.4 | Q8: 219.50579 | R8: =Q8*1000/'Basic data - source records'!$AI$5 -> 304.45682 | S8: =Q8/$Q$21 -> 0.24352425 | T8: Other operating and overhead costs | U8: =SUM(L12:L17)+L19 -> 0.15447009 | W8: Value Coltan | X8: ='MRA - Coltan - Tantalum'!R7 -> 56344093 | Y8: =X8/$X$10 -> 0.53475739 | Z8: Non-current assets: Coltan | AA8: =Y8*R7 -> 163.95577 | AB8: =$AA8*'Basic data - source records'!Y$5*1000000 -> 18527002 | AC8: =$AA8*'Basic data - source records'!Z$5*1000000 -> 17215356 | AD8: =$AA8*'Basic data - source records'!AA$5*1000000 -> 17543268 | AE8: =$AA8*'Basic data - source records'!AB$5*1000000 -> 17215356 | AF8: =$AA8*'Basic data - source records'!AC$5*1000000 -> 17215356
B9: Sales of electricity | D9: 0 | E9: =D9*1000/'Basic data - source records'!$AI$5 -> 0 | F9: =D9/$D$21 -> 0 | H9: Fuel purchased for mining and quarrying | I9: 11.1 | J9: 1.9020047 | K9: =J9*1000/'Basic data - source records'!$AI$5 -> 2.6381004 | L9: =J9/$J$21 -> 0.021479131 | M9: =J9/$D$21 -> 0.021925667 | O9: Land | P9: 2.5 | Q9: 0.92147253 | R9: =Q9*1000/'Basic data - source records'!$AI$5 -> 1.278092 | S9: =Q9/$Q$21 -> 0.0010223006 | T9: Consumption of capital | U9: =L18 -> 0.017013588 | W9: Value Wolfram | X9: ='MRA - Wolfram - Tungsten'!R7 -> 16004829 | Y9: =X9/$X$10 -> 0.15190058 | Z9: Non-current assets: Wolfram | AA9: =Y9*R7 -> 46.57248 | AB9: =$AA9*'Basic data - source records'!Y$5*1000000 -> 5262690.2 | AC9: =$AA9*'Basic data - source records'!Z$5*1000000 -> 4890110.4 | AD9: =$AA9*'Basic data - source records'!AA$5*1000000 -> 4983255.4 | AE9: =$AA9*'Basic data - source records'!AB$5*1000000 -> 4890110.4 | AF9: =$AA9*'Basic data - source records'!AC$5*1000000 -> 4890110.4
B10: Sales of water by pipe or bouser | D10: 0 | E10: =D10*1000/'Basic data - source records'!$AI$5 -> 0 | F10: =D10/$D$21 -> 0 | H10: Construction sub-contracts, equipment hire, fuel, materials | J10: 0 | K10: =J10*1000/'Basic data - source records'!$AI$5 -> 0 | L10: =J10/$J$21 -> 0 | M10: =J10/$D$21 -> 0 | O10: Buildings and structures | P10: 3.7 | Q10: 3.281885 | R10: =Q10*1000/'Basic data - source records'!$AI$5 -> 4.5520088 | S10: =Q10/$Q$21 -> 0.0036409909 | T10: Contractors' income | U10: =M7/U7 -> 0.6751051 | X10: =SUM(X7:X9) -> 1.0536384e+08 | Y10: =SUM(Y7:Y9) -> 1 | AA10: =SUM(AA7:AA9) -> 306.59843 | AB10: =SUM(AB7:AB9) -> 34645622 | AC10: =SUM(AC7:AC9) -> 32192835 | AD10: =SUM(AD7:AD9) -> 32806032 | AE10: =SUM(AE7:AE9) -> 32192835 | AF10: =SUM(AF7:AF9) -> 32192835
B11: Construction work done | D11: 0 | E11: =D11*1000/'Basic data - source records'!$AI$5 -> 0 | F11: =D11/$D$21 -> 0 | H11: Purchases of food and drinks for catering & bar services | J11: 0 | K11: =J11*1000/'Basic data - source records'!$AI$5 -> 0 | L11: =J11/$J$21 -> 0 | M11: =J11/$D$21 -> 0 | O11: Vehicles&Machines | P11: 215.2 | Q11: 214.54443 | R11: =Q11*1000/'Basic data - source records'!$AI$5 -> 297.57537 | S11: =Q11/$Q$21 -> 0.23802002
B12: Charges for delivery of goods sold, if invoiced separately | D12: 0 | E12: =D12*1000/'Basic data - source records'!$AI$5 -> 0 | F12: =D12/$D$21 -> 0 | H12: Rent of land paid / payable | I12: 0.04 | J12: 0 | K12: =J12*1000/'Basic data - source records'!$AI$5 -> 0 | L12: =J12/$J$21 -> 0 | M12: =J12/$D$21 -> 0 | O12: Others | P12: 1 | Q12: 0.75800684 | R12: =Q12*1000/'Basic data - source records'!$AI$5 -> 1.0513634 | S12: =Q12/$Q$21 -> 0.00084094841 | AA12: =AA10-R7 -> 0
B13: Transport, storage and travel services rendered | D13: 0 | E13: =D13*1000/'Basic data - source records'!$AI$5 -> 0 | F13: =D13/$D$21 -> 0 | H13: Rent of buildings paid / payable | I13: 0.2 | J13: 0.15731336 | K13: =J13*1000/'Basic data - source records'!$AI$5 -> 0.21819527 | L13: =J13/$J$21 -> 0.0017765225 | M13: =J13/$D$21 -> 0.0018134552 | O13: Capital work in progress | P13: 0.1 | Q13: 0.12786336 | R13: =Q13*1000/'Basic data - source records'!$AI$5 -> 0.17734782 | S13: =Q13/$Q$21 -> 0.00014185425
B14: Hotel & catering services | D14: 0 | E14: =D14*1000/'Basic data - source records'!$AI$5 -> 0 | F14: =D14/$D$21 -> 0 | H14: Other goods and services purchased (not interest,etc see below) | I14: 5.5 | J14: 3.2708771 | K14: =J14*1000/'Basic data - source records'!$AI$5 -> 4.5367407 | L14: =J14/$J$21 -> 0.036937657 | M14: =J14/$D$21 -> 0.037705565 | O14: Other investments | P14: 1.5 | Q14: 1.4161802 | R14: =Q14*1000/'Basic data - source records'!$AI$5 -> 1.9642567 | S14: =Q14/$Q$21 -> 0.0015711395
B15: Telecommmunication & internet connections | D15: 0 | E15: =D15*1000/'Basic data - source records'!$AI$5 -> 0 | F15: =D15/$D$21 -> 0 | H15: Wages & salaries paid (Social security & other benefits included) | I15: 7.9 | J15: 4.5679972 | K15: =J15*1000/'Basic data - source records'!$AI$5 -> 6.3358598 | L15: =J15/$J$21 -> 0.051585892 | M15: =J15/$D$21 -> 0.052658327
B16: Sales of professional & scientific services | D16: 0 | E16: =D16*1000/'Basic data - source records'!$AI$5 -> 0 | F16: =D16/$D$21 -> 0 | H16: Interests paid / payable (excluding other bank charges) | I16: 0.4 | J16: 0.33007173 | K16: =J16*1000/'Basic data - source records'!$AI$5 -> 0.45781293 | L16: =J16/$J$21 -> 0.0037274639 | M16: =J16/$D$21 -> 0.0038049552 | O16: Current assets | P16: 686.5 | Q16: 680.32155 | R16: =Q16*1000/'Basic data - source records'!$AI$5 -> 943.61309 | S16: =Q16/$Q$21 -> 0.75476276
B17: Rent of land receivable | D17: 0 | E17: =D17*1000/'Basic data - source records'!$AI$5 -> 0 | F17: =D17/$D$21 -> 0 | H17: Business licenses, rates and fees payable to government | I17: 1.24 | J17: 0.5315719 | K17: =J17*1000/'Basic data - source records'!$AI$5 -> 0.73729577 | L17: =J17/$J$21 -> 0.0060029832 | M17: =J17/$D$21 -> 0.0061277811 | O17: Inventories | P17: 407.5 | Q17: 404.52808 | R17: =Q17*1000/'Basic data - source records'!$AI$5 -> 561.08467 | S17: =Q17/$Q$21 -> 0.44879179
B18: Rent of buildings received / receivable | C18: 0.01 | D18: 0.041725366 | E18: =D18*1000/'Basic data - source records'!$AI$5 -> 0.057873517 | F18: =D18/$D$21 -> 0.0004809959 | H18: Depreciation charges for the year on fixed assets | I18: 1.8 | J18: 1.5065751 | K18: =J18*1000/'Basic data - source records'!$AI$5 -> 2.0896354 | L18: =J18/$J$21 -> 0.017013588 | M18: =J18/$D$21 -> 0.017367288 | O18: Debtors & other receivables | P18: 109.8 | Q18: 106.82738 | R18: =Q18*1000/'Basic data - source records'!$AI$5 -> 148.17069 | S18: =Q18/$Q$21 -> 0.1185165
B19: Dividends or other profits realised | C19: 0.7 | D19: 0.70322523 | E19: =D19*1000/'Basic data - source records'!$AI$5 -> 0.97538073 | F19: =D19/$D$21 -> 0.0081065426 | H19: All other costs, losses, provisions, etc | I19: 5.6 | J19: 4.8206945 | K19: =J19*1000/'Basic data - source records'!$AI$5 -> 6.6863536 | L19: =J19/$J$21 -> 0.054439575 | M19: =J19/$D$21 -> 0.055571336 | O19: Cash and cash equivalents | P19: 169.2 | Q19: 168.9661 | R19: =Q19*1000/'Basic data - source records'!$AI$5 -> 234.35775 | S19: =Q19/$Q$21 -> 0.18745448
B20: All other income | C20: 1.3 | D20: 1.2193647 | E20: =D20*1000/'Basic data - source records'!$AI$5 -> 1.6912715 | F20: =D20/$D$21 -> 0.014056424 | K20: =J20*1000/'Basic data - source records'!$AI$5 -> 0
B21: TOTAL INCOME FOR THE YEAR 2015 | C21: =SUM(C7:C20) -> 106.41 | D21: =SUM(D7:D20) -> 86.747861 | E21: =SUM(E7:E20) -> 120.32019 | F21: =D21/$D$21 -> 1 | H21: TOTAL EXPENSES FOR THE YEAR 2015 | I21: =SUM(I7:I19) -> 108.18 | J21: =SUM(J7:J19) -> 88.551288 | K21: =SUM(K7:K19) -> 122.82156 | L21: =J21/$J$21 -> 1 | M21: =J21/$D$21 -> 1.0207893 | O21: Total assets | P21: =P16+P7 -> 910.5 | Q21: =Q16+Q7 -> 901.37139 | R21: =R16+R7 -> 1250.2115 | S21: =Q21/$Q$21 -> 1
B22: Source: NISR, IBES 2015 Survey | H22: Source: NISR, IBES 2015 Survey | O22: Source: NISR, IBES 2015 Survey
B23: NOTE: in this scenario we took off Quarrying activities in our calculations and remained with only Mining Activities
B24: Data prodiced by: Ivan Patrick KAYITARE
A26: 2015Traders
B27: Mining traders
B28: Table III.2.2.1: | H28: Table III.2.2.2: | O28: Table III.2.2.4:
B29: Income statement for service sector, Frw billion | H29: Expenditure statement for services sector, Frw billion | O29: Summary assets of the services sector, Frw billion | W29: Asset structure | AB29: Opportunity cost of capital
B30: Income components | C30: Wholesale and retail trade; repair of motor vehicles | D30: Wholesale of metals and metal ores | E30: Wholesale of metals and metal ores (US$:Mill) | F30: Structure | H30: Expenditure components | I30: Wholesale and retail trade; repair of motor vehicles | J30: Wholesale of metals and metal ores | K30: Mining Operators (US$:Mill) | L30: Structure | M30: Structure to use | O30: Assets | P30: Wholesale and retail trade; repair of motor vehicles | Q30: Wholesale of metals and metal ores | R30: Wholesale of metals and metal ores (US$:Mill) | S30: Structure | U30: % of sales | X30: 2015 | AB30: 2012 | AC30: 2013 | AD30: 2014 | AE30: 2015 | AF30: 2016
B31: Sales of goods in the same condition as purchased | C31: 1828.4 | D31: 4.1450488 | E31: =D31*1000/'Basic data - source records'!$AI$5 -> 5.7492259 | F31: =D31/$D$45 -> 1 | H31: Purchases of goods for resale | I31: 1600.6 | J31: 3.5425314 | K31: =J31*1000/'Basic data - source records'!$AI$5 -> 4.9135281 | L31: =J31/$J$45 -> 0.8285782 | M31: =J31/$D$45 -> 0.85464167 | O31: Non-current assets | P31: 766 | Q31: 0.10629211 | R31: =Q31*1000/'Basic data - source records'!$AI$5 -> 0.14742826 | S31: =Q31/$Q$45 -> 0.14311392 | T31: Purchace of raw material | U31: =M31 -> 0.85464167 | W31: Value Cassiterite | X31: ='MRA - Cassiterite - Tin'!R19 -> 34263244 | Y31: =X31/$X$34 -> 0.29084292 | Z31: Non-current assets: Cassiterite | AA31: =Y31*R31 -> 0.042878467 | AB31: =$AA31*'Basic data - source records'!Y$5*1000000 -> 4845.2667 | AC31: =$AA31*'Basic data - source records'!Z$5*1000000 -> 4502.239 | AD31: =$AA31*'Basic data - source records'!AA$5*1000000 -> 4587.9959 | AE31: =$AA31*'Basic data - source records'!AB$5*1000000 -> 4502.239 | AF31: =$AA31*'Basic data - source records'!AC$5*1000000 -> 4502.239
B32: Sales of manufactured, mined or quarried products | C32: 4.8 | D32: 0 | E32: =D32*1000/'Basic data - source records'!$AI$5 -> 0 | F32: =D32/$D$45 -> 0 | H32: Purchases of raw materials, etc., used in manufacturing | I32: 3.5 | J32: 0 | K32: =J32*1000/'Basic data - source records'!$AI$5 -> 0 | L32: =J32/$J$45 -> 0 | M32: =J32/$D$45 -> 0 | O32: Fixed assets | P32: 739.9 | Q32: 0.10629211 | R32: =Q32*1000/'Basic data - source records'!$AI$5 -> 0.14742826 | S32: =Q32/$Q$45 -> 0.14311392 | T32: Intermediate consumption | U32: =M32+M33+M34+M35 -> 0 | W32: Value Coltan | X32: ='MRA - Coltan - Tantalum'!R19 -> 66200323 | Y32: =X32/$X$34 -> 0.56194024 | Z32: Non-current assets: Coltan | AA32: =Y32*R31 -> 0.082845873 | AB32: =$AA32*'Basic data - source records'!Y$5*1000000 -> 9361.5836 | AC32: =$AA32*'Basic data - source records'!Z$5*1000000 -> 8698.8166 | AD32: =$AA32*'Basic data - source records'!AA$5*1000000 -> 8864.5084 | AE32: =$AA32*'Basic data - source records'!AB$5*1000000 -> 8698.8166 | AF32: =$AA32*'Basic data - source records'!AC$5*1000000 -> 8698.8166
B33: Sales of electricity | C33: 0.8 | D33: 0 | E33: =D33*1000/'Basic data - source records'!$AI$5 -> 0 | F33: =D33/$D$45 -> 0 | H33: Fuel purchased for mining and quarrying | I33: 0 | J33: 0 | K33: =J33*1000/'Basic data - source records'!$AI$5 -> 0 | L33: =J33/$J$45 -> 0 | M33: =J33/$D$45 -> 0 | O33: Land | P33: 369.6 | Q33: 0 | R33: =Q33*1000/'Basic data - source records'!$AI$5 -> 0 | S33: =Q33/$Q$45 -> 0 | T33: Other operating and overhead costs | U33: =SUM(L36:L41)+L43 -> 0.16225412 | W33: Value Wolfram | X33: ='MRA - Wolfram - Tungsten'!R19 -> 17343129 | Y33: =X33/$X$34 -> 0.14721683 | Z33: Non-current assets: Wolfram | AA33: =Y33*R31 -> 0.021703922 | AB33: =$AA33*'Basic data - source records'!Y$5*1000000 -> 2452.5432 | AC33: =$AA33*'Basic data - source records'!Z$5*1000000 -> 2278.9118 | AD33: =$AA33*'Basic data - source records'!AA$5*1000000 -> 2322.3196 | AE33: =$AA33*'Basic data - source records'!AB$5*1000000 -> 2278.9118 | AF33: =$AA33*'Basic data - source records'!AC$5*1000000 -> 2278.9118
B34: Sales of water by pipe or bouser | C34: 0 | D34: 0 | E34: =D34*1000/'Basic data - source records'!$AI$5 -> 0 | F34: =D34/$D$45 -> 0 | H34: Construction sub-contracts, equipment hire, fuel, materials | I34: 3.8 | J34: 0 | K34: =J34*1000/'Basic data - source records'!$AI$5 -> 0 | L34: =J34/$J$45 -> 0 | M34: =J34/$D$45 -> 0 | O34: Buildings and structures | P34: 102.5 | Q34: 0 | R34: =Q34*1000/'Basic data - source records'!$AI$5 -> 0 | S34: =Q34/$Q$45 -> 0 | T34: Consumption of capital | U34: =L42 -> 0.0091676782 | X34: =SUM(X31:X33) -> 1.178067e+08 | Y34: =SUM(Y31:Y33) -> 1 | AA34: =SUM(AA31:AA33) -> 0.14742826 | AB34: =SUM(AB31:AB33) -> 16659.394 | AC34: =SUM(AC31:AC33) -> 15479.967 | AD34: =SUM(AD31:AD33) -> 15774.824 | AE34: =SUM(AE31:AE33) -> 15479.967 | AF34: =SUM(AF31:AF33) -> 15479.967
B35: Construction work done | C35: 4.7 | D35: 0 | E35: =D35*1000/'Basic data - source records'!$AI$5 -> 0 | F35: =D35/$D$45 -> 0 | H35: Purchases of food and drinks for catering & bar services | I35: 0.2 | J35: 0 | K35: =J35*1000/'Basic data - source records'!$AI$5 -> 0 | L35: =J35/$J$45 -> 0 | M35: =J35/$D$45 -> 0 | O35: Vehicles&Machines | P35: 255 | Q35: 0.10186213 | R35: =Q35*1000/'Basic data - source records'!$AI$5 -> 0.14128383 | S35: =Q35/$Q$45 -> 0.1371493
B36: Charges for delivery of goods sold, if invoiced separately | C36: 0.01 | D36: 0 | E36: =D36*1000/'Basic data - source records'!$AI$5 -> 0 | F36: =D36/$D$45 -> 0 | H36: Rent of land paid / payable | I36: 0.4 | J36: 0 | K36: =J36*1000/'Basic data - source records'!$AI$5 -> 0 | L36: =J36/$J$45 -> 0 | M36: =J36/$D$45 -> 0 | O36: Others | P36: 12.8 | Q36: 0.0044299822 | R36: =Q36*1000/'Basic data - source records'!$AI$5 -> 0.0061444316 | S36: =Q36/$Q$45 -> 0.0059646207 | AA36: =AA34-R31 -> 0
B37: Transport, storage and travel services rendered | C37: 4.2 | D37: 0 | E37: =D37*1000/'Basic data - source records'!$AI$5 -> 0 | F37: =D37/$D$45 -> 0 | H37: Rent of buildings paid / payable | I37: 14.3 | J37: 0.041414799 | K37: =J37*1000/'Basic data - source records'!$AI$5 -> 0.057442758 | L37: =J37/$J$45 -> 0.0096866888 | M37: =J37/$D$45 -> 0.0099913899 | O37: Capital work in progress | P37: 11.3 | Q37: 0 | R37: =Q37*1000/'Basic data - source records'!$AI$5 -> 0 | S37: =Q37/$Q$45 -> 0
B38: Hotel & catering services | C38: 0.3 | D38: 0 | E38: =D38*1000/'Basic data - source records'!$AI$5 -> 0 | F38: =D38/$D$45 -> 0 | H38: Other goods and services purchased (not interest,etc see below) | I38: 94.4 | J38: 0.25337192 | K38: =J38*1000/'Basic data - source records'!$AI$5 -> 0.3514295 | L38: =J38/$J$45 -> 0.059262269 | M38: =J38/$D$45 -> 0.061126403 | O38: Other investments | P38: 14.8 | Q38: 0 | R38: =Q38*1000/'Basic data - source records'!$AI$5 -> 0 | S38: =Q38/$Q$45 -> 0
B39: Telecommmunication & internet connections | C39: 0.1 | D39: 0 | E39: =D39*1000/'Basic data - source records'!$AI$5 -> 0 | F39: =D39/$D$45 -> 0 | H39: Wages & salaries paid (Social security & other benefits included) | I39: 32.7 | J39: 0.1295866 | L39: =J39/$J$45 -> 0.030309579 | M39: =J39/$D$45 -> 0.031262986
B40: Sales of professional & scientific services | C40: 0.04 | D40: 0 | E40: =D40*1000/'Basic data - source records'!$AI$5 -> 0 | F40: =D40/$D$45 -> 0 | H40: Interests paid / payable (excluding other bank charges) | I40: 15.8 | J40: 0 | K40: =J40*1000/'Basic data - source records'!$AI$5 -> 0 | L40: =J40/$J$45 -> 0 | M40: =J40/$D$45 -> 0 | O40: Current assets | P40: 5391.3 | Q40: 0.63641769 | R40: =Q40*1000/'Basic data - source records'!$AI$5 -> 0.88271798 | S40: =Q40/$Q$45 -> 0.85688608
B41: Rent of land receivable | C41: 0.2 | D41: 0 | E41: =D41*1000/'Basic data - source records'!$AI$5 -> 0 | F41: =D41/$D$45 -> 0 | H41: Business licenses, rates and fees payable to government | I41: 4.4 | J41: 0.18852928 | K41: =J41*1000/'Basic data - source records'!$AI$5 -> 0.26149208 | L41: =J41/$J$45 -> 0.044095939 | M41: =J41/$D$45 -> 0.045483006 | O41: Inventories | P41: 4635.6 | Q41: 0.0902106 | R41: =Q41*1000/'Basic data - source records'!$AI$5 -> 0.12512304 | S41: =Q41/$Q$45 -> 0.12146144
B42: Rent of buildings received / receivable | C42: 2.2 | D42: 0 | E42: =D42*1000/'Basic data - source records'!$AI$5 -> 0 | F42: =D42/$D$45 -> 0 | H42: Depreciation charges for the year on fixed assets | I42: 12.3 | J42: 0.039195803 | K42: =J42*1000/'Basic data - source records'!$AI$5 -> 0.054364988 | L42: =J42/$J$45 -> 0.0091676782 | M42: =J42/$D$45 -> 0.0094560535 | O42: Debtors & other receivables | P42: 564.2 | Q42: 0.53239052 | R42: =Q42*1000/'Basic data - source records'!$AI$5 -> 0.73843121 | S42: =Q42/$Q$45 -> 0.71682173
B43: Dividends or other profits realised | C43: 0.4 | D43: 0 | E43: =D43*1000/'Basic data - source records'!$AI$5 -> 0 | F43: =D43/$D$45 -> 0 | H43: All other costs, losses, provisions, etc | I43: 25.3 | J43: 0.080804196 | K43: =J43*1000/'Basic data - source records'!$AI$5 -> 0.11207626 | L43: =J43/$J$45 -> 0.018899648 | M43: =J43/$D$45 -> 0.019494148 | O43: Cash and cash equivalents | P43: 191.5 | Q43: 0.013816585 | R43: =Q43*1000/'Basic data - source records'!$AI$5 -> 0.019163747 | S43: =Q43/$Q$45 -> 0.018602939
B44: All other income | C44: 20.5 | D44: 0 | E44: =D44*1000/'Basic data - source records'!$AI$5 -> 0 | F44: =D44/$D$45 -> 0
B45: TOTAL INCOME FOR THE YEAR 2015 | C45: =SUM(C31:C44) -> 1866.65 | D45: =SUM(D31:D44) -> 4.1450488 | E45: =SUM(E31:E44) -> 5.7492259 | F45: =D45/$D$45 -> 1 | H45: TOTAL EXPENSES FOR THE YEAR 2015 | I45: =SUM(I31:I43) -> 1807.7 | J45: =SUM(J31:J43) -> 4.275434 | K45: =SUM(K31:K43) -> 5.7503337 | L45: =J45/$J$45 -> 1 | M45: =J45/$D$45 -> 1.0314557 | O45: Total assets | P45: =P40+P31 -> 6157.3 | Q45: =Q40+Q31 -> 0.7427098 | R45: =R40+R31 -> 1.0301462 | S45: =Q45/$Q$45 -> 1
B46: Source: NISR, IBES 2015 Survey | H46: Source: NISR, IBES 2015 Survey | O46: Source: NISR, IBES 2015 Survey
B47: Data prodiced by: Ivan Patrick KAYITARE
A60: Integrated Business Enterprise Survey: 2016 (to be used for 2016)
A61: 2016Operators
A62: 2016Operators | B62: Mining operators
B63: Table III.2.2.1 | H63: Table III.2.2.2 | O63: Table III.2.2.4:
B64: Income statement for service sector, Frw billion | H64: Expenditure statement for services sector, Frw billion | O64: Summary assets of the services sector, Frw billion | W64: Asset structure | AB64: Opportunity cost of capital
B65: Income components | C65: Mining and Quarrying | D65: Mining Operators | E65: Mining Operators (US$:Mill) | F65: Structure | H65: Expenditure components | I65: Mining and Quarrying | J65: Mining Operators | K65: Mining Operators (US$:Mill) | L65: Structure | M65: Structure to use | O65: Assets | P65: Mining and Quarrying | Q65: Mining Operators | R65: Mining Operators (US$:Mill) | S65: Structure | U65: % of sales | W65: 2016 | AB65: 2016
B66: Sales of goods in the same condition as purchased | E66: =D66*1000/'Basic data - source records'!$AJ$5 -> 0 | F66: =D66/$D$80 -> #DIV/0! | H66: Purchases of goods for resale | K66: =J66*1000/'Basic data - source records'!$AJ$5 -> 0 | L66: =J66/$J$80 -> #DIV/0! | M66: =J66/$D$80 -> #DIV/0! | O66: Non-current assets | R66: =Q66*1000/'Basic data - source records'!$AJ$5 -> 0 | S66: =Q66/$Q$45 -> 0 | T66: Intermediate consumption | U66: =M66+M67+M68+M69+M70 -> #DIV/0! | W66: Value Cassiterite | X66: ='MRA - Cassiterite - Tin'!R66 -> 0 | Y66: =X66/$X$10 -> 0 | Z66: Non-current assets: Cassiterite | AA66: =Y66*R66 -> 0 | AB66: =$AA66*'Basic data - source records'!AC$5*1000000 -> 0
B67: Sales of manufactured, mined or quarried products | E67: =D67*1000/'Basic data - source records'!$AJ$5 -> 0 | F67: =D67/$D$80 -> #DIV/0! | H67: Purchases of raw materials, etc., used in manufacturing | K67: =J67*1000/'Basic data - source records'!$AJ$5 -> 0 | L67: =J67/$J$80 -> #DIV/0! | M67: =J67/$D$80 -> #DIV/0! | O67: Fixed assets | R67: =Q67*1000/'Basic data - source records'!$AJ$5 -> 0 | S67: =Q67/$Q$45 -> 0 | T67: Other operating and overhead costs | U67: =SUM(L71:L76)+L78 -> #DIV/0! | W67: Value Coltan | X67: ='MRA - Coltan - Tantalum'!R66 -> 0 | Y67: =X67/$X$10 -> 0 | Z67: Non-current assets: Coltan | AA67: =Y67*R66 -> 0 | AB67: =$AA67*'Basic data - source records'!AC$5*1000000 -> 0
B68: Sales of electricity | E68: =D68*1000/'Basic data - source records'!$AJ$5 -> 0 | F68: =D68/$D$80 -> #DIV/0! | H68: Fuel purchased for mining and quarrying | K68: =J68*1000/'Basic data - source records'!$AJ$5 -> 0 | L68: =J68/$J$80 -> #DIV/0! | M68: =J68/$D$80 -> #DIV/0! | O68: Land | R68: =Q68*1000/'Basic data - source records'!$AJ$5 -> 0 | S68: =Q68/$Q$45 -> 0 | T68: Consumption of capital | U68: =L77 -> #DIV/0! | W68: Value Wolfram | X68: ='MRA - Wolfram - Tungsten'!R66 -> 0 | Y68: =X68/$X$10 -> 0 | Z68: Non-current assets: Wolfram | AA68: =Y68*R66 -> 0 | AB68: =$AA68*'Basic data - source records'!AC$5*1000000 -> 0
B69: Sales of water by pipe or bouser | E69: =D69*1000/'Basic data - source records'!$AJ$5 -> 0 | F69: =D69/$D$80 -> #DIV/0! | H69: Construction sub-contracts, equipment hire, fuel, materials | K69: =J69*1000/'Basic data - source records'!$AJ$5 -> 0 | L69: =J69/$J$80 -> #DIV/0! | M69: =J69/$D$80 -> #DIV/0! | O69: Buildings and structures | R69: =Q69*1000/'Basic data - source records'!$AJ$5 -> 0 | S69: =Q69/$Q$45 -> 0 | X69: =SUM(X66:X68) -> 0 | AA69: =SUM(AA66:AA68) -> 0 | AB69: =SUM(AB66:AB68) -> 0
B70: Construction work done | E70: =D70*1000/'Basic data - source records'!$AJ$5 -> 0 | F70: =D70/$D$80 -> #DIV/0! | H70: Purchases of food and drinks for catering & bar services | K70: =J70*1000/'Basic data - source records'!$AJ$5 -> 0 | L70: =J70/$J$80 -> #DIV/0! | M70: =J70/$D$80 -> #DIV/0! | O70: Vehicles&Machines | R70: =Q70*1000/'Basic data - source records'!$AJ$5 -> 0 | S70: =Q70/$Q$45 -> 0
B71: Charges for delivery of goods sold, if invoiced separately | E71: =D71*1000/'Basic data - source records'!$AJ$5 -> 0 | F71: =D71/$D$80 -> #DIV/0! | H71: Rent of land paid / payable | K71: =J71*1000/'Basic data - source records'!$AJ$5 -> 0 | L71: =J71/$J$80 -> #DIV/0! | M71: =J71/$D$80 -> #DIV/0! | O71: Others | R71: =Q71*1000/'Basic data - source records'!$AJ$5 -> 0 | S71: =Q71/$Q$45 -> 0
B72: Transport, storage and travel services rendered | E72: =D72*1000/'Basic data - source records'!$AJ$5 -> 0 | F72: =D72/$D$80 -> #DIV/0! | H72: Rent of buildings paid / payable | K72: =J72*1000/'Basic data - source records'!$AJ$5 -> 0 | L72: =J72/$J$80 -> #DIV/0! | M72: =J72/$D$80 -> #DIV/0! | O72: Capital work in progress | R72: =Q72*1000/'Basic data - source records'!$AJ$5 -> 0 | S72: =Q72/$Q$45 -> 0
B73: Hotel & catering services | E73: =D73*1000/'Basic data - source records'!$AJ$5 -> 0 | F73: =D73/$D$80 -> #DIV/0! | H73: Other goods and services purchased (not interest,etc see below) | K73: =J73*1000/'Basic data - source records'!$AJ$5 -> 0 | L73: =J73/$J$80 -> #DIV/0! | M73: =J73/$D$80 -> #DIV/0! | O73: Other investments | R73: =Q73*1000/'Basic data - source records'!$AJ$5 -> 0 | S73: =Q73/$Q$45 -> 0
B74: Telecommmunication & internet connections | E74: =D74*1000/'Basic data - source records'!$AJ$5 -> 0 | F74: =D74/$D$80 -> #DIV/0! | H74: Wages & salaries paid (Social security & other benefits included) | K74: =J74*1000/'Basic data - source records'!$AJ$5 -> 0 | L74: =J74/$J$80 -> #DIV/0! | M74: =J74/$D$80 -> #DIV/0!
B75: Sales of professional & scientific services | E75: =D75*1000/'Basic data - source records'!$AJ$5 -> 0 | F75: =D75/$D$80 -> #DIV/0! | H75: Interests paid / payable (excluding other bank charges) | K75: =J75*1000/'Basic data - source records'!$AJ$5 -> 0 | L75: =J75/$J$80 -> #DIV/0! | M75: =J75/$D$80 -> #DIV/0! | O75: Current assets | R75: =Q75*1000/'Basic data - source records'!$AJ$5 -> 0 | S75: =Q75/$Q$45 -> 0
B76: Rent of land receivable | E76: =D76*1000/'Basic data - source records'!$AJ$5 -> 0 | F76: =D76/$D$80 -> #DIV/0! | H76: Business licenses, rates and fees payable to government | K76: =J76*1000/'Basic data - source records'!$AJ$5 -> 0 | L76: =J76/$J$80 -> #DIV/0! | M76: =J76/$D$80 -> #DIV/0! | O76: Inventories | R76: =Q76*1000/'Basic data - source records'!$AJ$5 -> 0 | S76: =Q76/$Q$45 -> 0
B77: Rent of buildings received / receivable | E77: =D77*1000/'Basic data - source records'!$AJ$5 -> 0 | F77: =D77/$D$80 -> #DIV/0! | H77: Depreciation charges for the year on fixed assets | K77: =J77*1000/'Basic data - source records'!$AJ$5 -> 0 | L77: =J77/$J$80 -> #DIV/0! | M77: =J77/$D$80 -> #DIV/0! | O77: Debtors & other receivables | R77: =Q77*1000/'Basic data - source records'!$AJ$5 -> 0 | S77: =Q77/$Q$45 -> 0
B78: Dividends or other profits realised | E78: =D78*1000/'Basic data - source records'!$AJ$5 -> 0 | F78: =D78/$D$80 -> #DIV/0! | H78: All other costs, losses, provisions, etc | K78: =J78*1000/'Basic data - source records'!$AJ$5 -> 0 | L78: =J78/$J$80 -> #DIV/0! | M78: =J78/$D$80 -> #DIV/0! | O78: Cash and cash equivalents | R78: =Q78*1000/'Basic data - source records'!$AJ$5 -> 0 | S78: =Q78/$Q$45 -> 0
B79: All other income | E79: =D79*1000/'Basic data - source records'!$AJ$5 -> 0 | F79: =D79/$D$80 -> #DIV/0!
B80: TOTAL INCOME FOR THE YEAR 2016 | E80: =D80*1000/'Basic data - source records'!$AJ$5 -> 0 | F80: =D80/$D$80 -> #DIV/0! | H80: TOTAL EXPENSES FOR THE YEAR 2016 | K80: =J80*1000/'Basic data - source records'!$AJ$5 -> 0 | L80: =J80/$J$80 -> #DIV/0! | M80: =J80/$D$80 -> #DIV/0! | O80: Total assets | R80: =Q80*1000/'Basic data - source records'!$AJ$5 -> 0 | S80: =Q80/$Q$45 -> 0
B81: Source: NISR, IBES 2016 Survey | H81: Source: NISR, IBES 2016 Survey | O81: Source: NISR, IBES 2016 Survey
B82: NOTE: in this scenario we took off Quarrying activities in our calculations and remained with only Mining Activities
B83: Data prodiced by: Ivan Patrick KAYITARE
A85: 2016Traders
B86: Mining traders
B87: Table III.2.2.1: | H87: Table III.2.2.2: | O87: Table III.2.2.4:
B88: Income statement for service sector, Frw billion | H88: Expenditure statement for services sector, Frw billion | O88: Summary assets of the services sector, Frw billion | W88: Asset structure | AB88: Opportunity cost of capital
B89: Income components | C89: Wholesale and retail trade; repair of motor vehicles | D89: Wholesale of metals and metal ores | E89: Wholesale of metals and metal ores (US$:Mill) | F89: Structure | H89: Expenditure components | I89: Wholesale and retail trade; repair of motor vehicles | J89: Wholesale of metals and metal ores | K89: Mining Operators (US$:Mill) | L89: Structure | M89: Structure to use | O89: Assets | P89: Wholesale and retail trade; repair of motor vehicles | Q89: Wholesale of metals and metal ores | R89: Wholesale of metals and metal ores (US$:Mill) | S89: Structure | U89: % of sales | X89: 2015 | AB89: 2016
B90: Sales of goods in the same condition as purchased | E90: =D90*1000/'Basic data - source records'!$AJ$5 -> 0 | F90: =D90/$D$104 -> #DIV/0! | H90: Purchases of goods for resale | K90: =J90*1000/'Basic data - source records'!$AJ$5 -> 0 | L90: =J90/$J$104 -> #DIV/0! | M90: =J90/$D$104 -> #DIV/0! | O90: Non-current assets | R90: =Q90*1000/'Basic data - source records'!$AJ$5 -> 0 | S90: =Q90/$Q$45 -> 0 | T90: Purchace of raw material | U90: =M90 -> #DIV/0! | W90: Value Cassiterite | X90: ='MRA - Cassiterite - Tin'!R78 -> 0 | Y90: =X90/$X$10 -> 0 | Z90: Non-current assets: Cassiterite | AA90: =Y90*R90 -> 0 | AB90: =$AA90*'Basic data - source records'!AC$5*1000000 -> 0
B91: Sales of manufactured, mined or quarried products | E91: =D91*1000/'Basic data - source records'!$AJ$5 -> 0 | F91: =D91/$D$104 -> #DIV/0! | H91: Purchases of raw materials, etc., used in manufacturing | K91: =J91*1000/'Basic data - source records'!$AJ$5 -> 0 | L91: =J91/$J$104 -> #DIV/0! | M91: =J91/$D$104 -> #DIV/0! | O91: Fixed assets | R91: =Q91*1000/'Basic data - source records'!$AJ$5 -> 0 | S91: =Q91/$Q$45 -> 0 | T91: Intermediate consumption | U91: =M91+M92+M93+M94 -> #DIV/0! | W91: Value Coltan | X91: ='MRA - Coltan - Tantalum'!R78 -> 0 | Y91: =X91/$X$10 -> 0 | Z91: Non-current assets: Coltan | AA91: =Y91*R90 -> 0 | AB91: =$AA91*'Basic data - source records'!AC$5*1000000 -> 0
B92: Sales of electricity | E92: =D92*1000/'Basic data - source records'!$AJ$5 -> 0 | F92: =D92/$D$104 -> #DIV/0! | H92: Fuel purchased for mining and quarrying | K92: =J92*1000/'Basic data - source records'!$AJ$5 -> 0 | L92: =J92/$J$104 -> #DIV/0! | M92: =J92/$D$104 -> #DIV/0! | O92: Land | R92: =Q92*1000/'Basic data - source records'!$AJ$5 -> 0 | S92: =Q92/$Q$45 -> 0 | T92: Other operating and overhead costs | U92: =SUM(L95:L100)+L102 -> #DIV/0! | W92: Value Wolfram | X92: ='MRA - Wolfram - Tungsten'!R78 -> 0 | Y92: =X92/$X$10 -> 0 | Z92: Non-current assets: Wolfram | AA92: =Y92*R90 -> 0 | AB92: =$AA92*'Basic data - source records'!AC$5*1000000 -> 0
B93: Sales of water by pipe or bouser | E93: =D93*1000/'Basic data - source records'!$AJ$5 -> 0 | F93: =D93/$D$104 -> #DIV/0! | H93: Construction sub-contracts, equipment hire, fuel, materials | K93: =J93*1000/'Basic data - source records'!$AJ$5 -> 0 | L93: =J93/$J$104 -> #DIV/0! | M93: =J93/$D$104 -> #DIV/0! | O93: Buildings and structures | R93: =Q93*1000/'Basic data - source records'!$AJ$5 -> 0 | S93: =Q93/$Q$45 -> 0 | T93: Consumption of capital | U93: =L101 -> #DIV/0! | X93: =SUM(X90:X92) -> 0 | AA93: =SUM(AA90:AA92) -> 0 | AB93: =SUM(AB90:AB92) -> 0
B94: Construction work done | E94: =D94*1000/'Basic data - source records'!$AJ$5 -> 0 | F94: =D94/$D$104 -> #DIV/0! | H94: Purchases of food and drinks for catering & bar services | K94: =J94*1000/'Basic data - source records'!$AJ$5 -> 0 | L94: =J94/$J$104 -> #DIV/0! | M94: =J94/$D$104 -> #DIV/0! | O94: Vehicles&Machines | R94: =Q94*1000/'Basic data - source records'!$AJ$5 -> 0 | S94: =Q94/$Q$45 -> 0
B95: Charges for delivery of goods sold, if invoiced separately | E95: =D95*1000/'Basic data - source records'!$AJ$5 -> 0 | F95: =D95/$D$104 -> #DIV/0! | H95: Rent of land paid / payable | K95: =J95*1000/'Basic data - source records'!$AJ$5 -> 0 | L95: =J95/$J$104 -> #DIV/0! | M95: =J95/$D$104 -> #DIV/0! | O95: Others | R95: =Q95*1000/'Basic data - source records'!$AJ$5 -> 0 | S95: =Q95/$Q$45 -> 0
B96: Transport, storage and travel services rendered | E96: =D96*1000/'Basic data - source records'!$AJ$5 -> 0 | F96: =D96/$D$104 -> #DIV/0! | H96: Rent of buildings paid / payable | K96: =J96*1000/'Basic data - source records'!$AJ$5 -> 0 | L96: =J96/$J$104 -> #DIV/0! | M96: =J96/$D$104 -> #DIV/0! | O96: Capital work in progress | R96: =Q96*1000/'Basic data - source records'!$AJ$5 -> 0 | S96: =Q96/$Q$45 -> 0
B97: Hotel & catering services | E97: =D97*1000/'Basic data - source records'!$AJ$5 -> 0 | F97: =D97/$D$104 -> #DIV/0! | H97: Other goods and services purchased (not interest,etc see below) | K97: =J97*1000/'Basic data - source records'!$AJ$5 -> 0 | L97: =J97/$J$104 -> #DIV/0! | M97: =J97/$D$104 -> #DIV/0! | O97: Other investments | R97: =Q97*1000/'Basic data - source records'!$AJ$5 -> 0 | S97: =Q97/$Q$45 -> 0
B98: Telecommmunication & internet connections | E98: =D98*1000/'Basic data - source records'!$AJ$5 -> 0 | F98: =D98/$D$104 -> #DIV/0! | H98: Wages & salaries paid (Social security & other benefits included) | K98: =J98*1000/'Basic data - source records'!$AJ$5 -> 0 | L98: =J98/$J$104 -> #DIV/0! | M98: =J98/$D$104 -> #DIV/0!
B99: Sales of professional & scientific services | E99: =D99*1000/'Basic data - source records'!$AJ$5 -> 0 | F99: =D99/$D$104 -> #DIV/0! | H99: Interests paid / payable (excluding other bank charges) | K99: =J99*1000/'Basic data - source records'!$AJ$5 -> 0 | L99: =J99/$J$104 -> #DIV/0! | M99: =J99/$D$104 -> #DIV/0! | O99: Current assets | R99: =Q99*1000/'Basic data - source records'!$AJ$5 -> 0 | S99: =Q99/$Q$45 -> 0
B100: Rent of land receivable | E100: =D100*1000/'Basic data - source records'!$AJ$5 -> 0 | F100: =D100/$D$104 -> #DIV/0! | H100: Business licenses, rates and fees payable to government | K100: =J100*1000/'Basic data - source records'!$AJ$5 -> 0 | L100: =J100/$J$104 -> #DIV/0! | M100: =J100/$D$104 -> #DIV/0! | O100: Inventories | R100: =Q100*1000/'Basic data - source records'!$AJ$5 -> 0 | S100: =Q100/$Q$45 -> 0
B101: Rent of buildings received / receivable | E101: =D101*1000/'Basic data - source records'!$AJ$5 -> 0 | F101: =D101/$D$104 -> #DIV/0! | H101: Depreciation charges for the year on fixed assets | K101: =J101*1000/'Basic data - source records'!$AJ$5 -> 0 | L101: =J101/$J$104 -> #DIV/0! | M101: =J101/$D$104 -> #DIV/0! | O101: Debtors & other receivables | R101: =Q101*1000/'Basic data - source records'!$AJ$5 -> 0 | S101: =Q101/$Q$45 -> 0
B102: Dividends or other profits realised | E102: =D102*1000/'Basic data - source records'!$AJ$5 -> 0 | F102: =D102/$D$104 -> #DIV/0! | H102: All other costs, losses, provisions, etc | K102: =J102*1000/'Basic data - source records'!$AJ$5 -> 0 | L102: =J102/$J$104 -> #DIV/0! | M102: =J102/$D$104 -> #DIV/0! | O102: Cash and cash equivalents | R102: =Q102*1000/'Basic data - source records'!$AJ$5 -> 0 | S102: =Q102/$Q$45 -> 0
B103: All other income | E103: =D103*1000/'Basic data - source records'!$AJ$5 -> 0 | F103: =D103/$D$104 -> #DIV/0!
B104: TOTAL INCOME FOR THE YEAR 2016 | E104: =D104*1000/'Basic data - source records'!$AJ$5 -> 0 | F104: =D104/$D$104 -> #DIV/0! | H104: TOTAL EXPENSES FOR THE YEAR 2016 | K104: =J104*1000/'Basic data - source records'!$AJ$5 -> 0 | L104: =J104/$J$104 -> #DIV/0! | M104: =J104/$D$104 -> #DIV/0! | O104: Total assets | R104: =Q104*1000/'Basic data - source records'!$AJ$5 -> 0 | S104: =Q104/$Q$45 -> 0
B105: Source: NISR, IBES 2016 Survey | H105: Source: NISR, IBES 2016 Survey | O105: Source: NISR, IBES 2016 Survey
B106: Data prodiced by: Ivan Patrick KAYITARE
A118: Integrated Business Enterprise Survey: 2017 (to be used for 2017)
B120: Mining operators
B121: Table III.2.2.1 | H121: Table III.2.2.2 | O121: Table III.2.2.4:
B122: Income statement for service sector, Frw billion | H122: Expenditure statement for services sector, Frw billion | O122: Summary assets of the services sector, Frw billion | W122: Asset structure | AB122: Opportunity cost of capital
B123: Income components | C123: Mining and Quarrying | D123: Mining Operators | E123: Mining Operators (US$:Mill) | F123: Structure | H123: Expenditure components | I123: Mining and Quarrying | J123: Mining Operators | K123: Mining Operators (US$:Mill) | L123: Structure | M123: Structure to use | O123: Assets | P123: Mining and Quarrying | Q123: Mining Operators | R123: Mining Operators (US$:Mill) | S123: Structure | U123: % of sales | W123: 2017 | AB123: 2017
B124: Sales of goods in the same condition as purchased | E124: =D124*1000/'Basic data - source records'!$AI$5 -> 0 | F124: =D124/$D$21 -> 0 | H124: Purchases of goods for resale | K124: =J124*1000/'Basic data - source records'!$AI$5 -> 0 | L124: =J124/$J$21 -> 0 | M124: =J124/$D$21 -> 0 | O124: Non-current assets | R124: =Q124*1000/'Basic data - source records'!$AI$5 -> 0 | S124: =Q124/$Q$45 -> 0 | T124: Intermediate consumption | U124: =M124+M125+M126+M127+M128 -> 0 | W124: Value Cassiterite | X124: ='MRA - Cassiterite - Tin'!R124 -> 0 | Y124: =X124/$X$10 -> 0 | Z124: Non-current assets: Cassiterite | AA124: =Y124*R124 -> 0 | AB124: =$AA124*'Basic data - source records'!AD$5*1000000 -> 0
B125: Sales of manufactured, mined or quarried products | E125: =D125*1000/'Basic data - source records'!$AI$5 -> 0 | F125: =D125/$D$21 -> 0 | H125: Purchases of raw materials, etc., used in manufacturing | K125: =J125*1000/'Basic data - source records'!$AI$5 -> 0 | L125: =J125/$J$21 -> 0 | M125: =J125/$D$21 -> 0 | O125: Fixed assets | R125: =Q125*1000/'Basic data - source records'!$AI$5 -> 0 | S125: =Q125/$Q$45 -> 0 | T125: Other operating and overhead costs | U125: =SUM(L129:L134)+L136 -> 0 | W125: Value Coltan | X125: ='MRA - Coltan - Tantalum'!R124 -> 0 | Y125: =X125/$X$10 -> 0 | Z125: Non-current assets: Coltan | AA125: =Y125*R124 -> 0 | AB125: =$AA125*'Basic data - source records'!AD$5*1000000 -> 0
B126: Sales of electricity | E126: =D126*1000/'Basic data - source records'!$AI$5 -> 0 | F126: =D126/$D$21 -> 0 | H126: Fuel purchased for mining and quarrying | K126: =J126*1000/'Basic data - source records'!$AI$5 -> 0 | L126: =J126/$J$21 -> 0 | M126: =J126/$D$21 -> 0 | O126: Land | R126: =Q126*1000/'Basic data - source records'!$AI$5 -> 0 | S126: =Q126/$Q$45 -> 0 | T126: Consumption of capital | U126: =L135 -> 0 | W126: Value Wolfram | X126: ='MRA - Wolfram - Tungsten'!R124 -> 0 | Y126: =X126/$X$10 -> 0 | Z126: Non-current assets: Wolfram | AA126: =Y126*R124 -> 0 | AB126: =$AA126*'Basic data - source records'!AD$5*1000000 -> 0
...

Sheet Mining price data
A1: Prices a selection of traders are paying miners - a sample of monthly trades
A2: Source: ITRI logbooks
A3: Cassiterite
B4: Trader | D4: Jan | I4: Feb | N4: March | S4: April | X4: May | AC4: Jun | AH4: July | AM4: Aug | AR4: Sept | AW4: Oct | BB4: Nov | BG4: Dec | BM4: Average
B5: MSA | C5: 2012 | D5: 8.15 | E5: 8.27 | F5: 9.94 | G5: 9.9 | H5: 7.41 | I5: 9.15 | J5: 11.24 | K5: 10.35 | L5: 11.89 | M5: 11 | N5: 11.35 | O5: 11.45 | P5: 11.03 | Q5: 7.5 | R5: 12.12 | S5: 10.5 | T5: 8.9 | U5: 9.6 | V5: 9.94 | W5: 9.15 | X5: 10.05 | Y5: 9.55 | Z5: 7.15 | AA5: 8.125 | AB5: 8.4 | AC5: 9.1 | AD5: 8.92 | AE5: 8.75 | AF5: 9.5 | AG5: 9.22 | AH5: 7.55 | AI5: 8.3 | AJ5: 8.25 | AK5: 8.99 | AL5: 7.65 | AM5: 8.35 | AN5: 8.2 | AO5: 6.15 | AP5: 8.25 | AQ5: 7.75 | AR5: 8.1 | AS5: 6.55 | AT5: 9.75 | AU5: 8.85 | AV5: 10.56 | AW5: 10.8 | AX5: 12.2 | AY5: 11.02 | AZ5: 9 | BA5: 10.17 | BB5: 6.45 | BC5: 8.95 | BD5: 10.35 | BE5: 8.5 | BF5: 9.53 | BG5: 11.22 | BH5: 10.05 | BI5: 10.55 | BJ5: 11.5 | BK5: 10.85 | BM5: =AVERAGE(D5:BK5) -> 9.3665833
C6: 2013 | D6: 11.54 | E6: 13.91 | F6: 12.2 | G6: 11.75 | H6: 8.95 | I6: 12.34 | J6: 12.66 | K6: 11.35 | L6: 12.47 | M6: 8.19 | N6: 8.1 | O6: 10.18 | P6: 11.52 | Q6: 11.7 | R6: 9.38 | S6: 11.8 | T6: 11.45 | U6: 11.46 | V6: 11.99 | W6: 9.16 | X6: 9.05 | Y6: 10.09 | Z6: 10.93 | AA6: 10.07 | AB6: 10.91 | AC6: 8.38 | AD6: 9.65 | AE6: 9.77 | AF6: 9.6 | AG6: 10.38 | AH6: 8.2 | AI6: 9.41 | AJ6: 6.62 | AK6: 7.83 | AL6: 9.13 | AM6: 10.45 | AN6: 10.74 | AO6: 11.52 | AP6: 11.11 | AQ6: 9.45 | AR6: 10.74 | AS6: 11.66 | AT6: 10.45 | AU6: 11.5 | AV6: 12.13 | AW6: 10.19 | AX6: 9.45 | AY6: 10.45 | AZ6: 8.2 | BA6: 10.94 | BB6: 10.9 | BC6: 10.55 | BD6: 10 | BE6: 12.04 | BF6: 11.5 | BG6: 11.52 | BH6: 12.79 | BI6: 10.25 | BJ6: 9.4 | BK6: 10.5 | BM6: =AVERAGE(D6:BK6) -> 10.509167
C7: 2014 | D7: 11.73 | E7: 8.05 | F7: 10.23 | G7: 10.61 | H7: 9.06 | I7: 10.63 | J7: 10.63 | K7: 9.5 | L7: 13.32 | M7: 11.53 | N7: 10.55 | O7: 10.35 | P7: 8.65 | Q7: 11.97 | R7: 10.05 | S7: 14.12 | T7: 13.6 | U7: 13.91 | V7: 11.03 | W7: 12.04 | X7: 9.35 | Y7: 11.2 | Z7: 11.59 | AA7: 9.04 | AB7: 10.07 | AC7: 12.27 | AD7: 9.3 | AE7: 12.35 | AF7: 12.2 | AG7: 12.1 | AH7: 12.72 | AI7: 9.95 | AJ7: 11.25 | AK7: 10.96 | AL7: 10.77 | AM7: 11.09 | AN7: 10.92 | AO7: 11 | AP7: 13.1 | AQ7: 14.2 | AR7: 12.63 | AS7: 9.63 | AT7: 9.5 | AU7: 13.045 | AV7: 10.37 | AW7: 12.75 | AX7: 9.45 | AY7: 10.7 | AZ7: 10.89 | BA7: 10.6 | BB7: 10.75 | BC7: 7.53 | BD7: 8.54 | BE7: 10.8 | BF7: 10.17 | BG7: 7.71 | BH7: 10.7 | BI7: 7.87 | BJ7: 10.19 | BK7: 10.8 | BM7: =AVERAGE(D7:BK7) -> 10.86025
C8: 2015 | D8: 11 | E8: 10.46 | F8: 8.95 | G8: 8.23 | H8: 10.4 | I8: 11 | J8: 7.43 | K8: 10.53 | L8: 9.62 | M8: 9.34 | N8: 9.96 | O8: 9.51 | P8: 6.83 | Q8: 8.75 | R8: 8.53 | S8: 8.27 | T8: 8.57 | U8: 8.14 | V8: 5.83 | W8: 9.27 | X8: 7.32 | Y8: 8.65 | Z8: 8.87 | AA8: 8.7 | AB8: 8.01 | AC8: 8.3 | AD8: 8.7 | AE8: 7.38 | AF8: 7.33 | AG8: 7.6 | AH8: 9 | AI8: 7.67 | AJ8: 7.97 | AK8: 6.44 | AL8: 7.9 | AM8: 7.88 | AN8: 7.21 | AO8: 7.47 | AP8: 7 | AQ8: 5.9 | AR8: 7.5 | AS8: 8.5 | AT8: 6.7 | AU8: 7.3 | AV8: 5.4 | AW8: 5.06 | AX8: 6.8 | AY8: 7.3 | AZ8: 7.7 | BA8: 8.5 | BB8: 5.8 | BC8: 5.4 | BD8: 5.1 | BE8: 6.9 | BF8: 7.9 | BG8: 7.4 | BH8: 7.5 | BI8: 7.2 | BJ8: 7.9 | BK8: 7.47 | BM8: =AVERAGE(D8:BK8) -> 7.9208333
C9: 2016 | D9: 6.4 | E9: 7.03 | F9: 6.5 | G9: 5.6 | H9: 5.7 | I9: 6.4 | J9: 6.4 | K9: 7.5 | L9: 5.5 | M9: 8.4 | N9: 8.5 | O9: 7.7 | P9: 9.7 | Q9: 9.3 | R9: 8.6 | S9: 9.3 | T9: 8.6 | U9: 8.7 | V9: 9 | W9: 8.8 | X9: 7.7 | Y9: 9.3 | Z9: 8.4 | AA9: 9.3 | AB9: 9.4 | AC9: 8.8 | AD9: 8.4 | AE9: 12.8 | AF9: 8.2 | AG9: 11 | AH9: 9.3 | AI9: 13.52 | AJ9: 8.1 | AK9: 9 | AL9: 8.2 | AM9: 10.7 | AN9: 10.5 | AO9: 10.5 | AP9: 9.4 | AQ9: 9 | AR9: 8.6 | AS9: 10.4 | AT9: 10.4 | AU9: 5.9 | AV9: 4.5 | AW9: 10.4 | AX9: 6.4 | AY9: 9.9 | AZ9: 10.3 | BA9: 10.3 | BB9: 10.9 | BC9: 10.7 | BD9: 11.5 | BE9: 10.9 | BF9: 10.9 | BM9: =AVERAGE(D9:BK9) -> 8.8572727
B12: Trader | D12: Jan | I12: Feb | N12: March | S12: April | X12: May | AC12: Jun | AH12: July | AM12: Aug | AR12: Sept | AW12: Oct | BB12: Nov | BG12: Dec
B13: FECOMIRWA | C13: 2012 | D13: 10 | E13: 8.8 | F13: 8 | G13: 9 | H13: 8.5 | I13: 8 | J13: 6.5 | N13: 9 | O13: 8 | S13: 8 | T13: 8.5 | U13: 7 | V13: 7 | W13: 9 | X13: 9 | Y13: 10 | Z13: 8.5 | AA13: 10 | AB13: 9.5 | AC13: 12 | AD13: 8.5 | AE13: 7.6 | AF13: 8 | AG13: 9 | AH13: 8.9 | AI13: 7.5 | AJ13: 10 | AK13: 8 | AL13: 9 | AM13: 7 | AN13: 7.5 | AO13: 4 | AP13: 5 | AR13: 8.5 | AS13: 8.5 | AT13: 8.5 | AU13: 8.5 | BB13: 7.5 | BC13: 5.5 | BD13: 6 | BE13: 4 | BF13: 7 | BG13: 10 | BH13: 6 | BM13: =AVERAGE(D13:BK13) -> 8.0522727
C14: 2013 | D14: 9 | E14: 4 | F14: 9 | G14: 6.5 | H14: 8.5 | I14: 7 | J14: 7.5 | K14: 9 | N14: 9 | O14: 6 | P14: 7 | Q14: 7 | R14: 9.5 | S14: 12 | T14: 10.5 | U14: 7 | V14: 10 | W14: 10 | X14: 9 | Y14: 10.5 | Z14: 10 | AA14: 6 | AB14: 7 | AC14: 9.5 | AD14: 10.5 | AE14: 6 | AF14: 7 | AG14: 10.5 | AH14: 5.6 | AI14: 6 | AJ14: 10 | AK14: 8.3 | AL14: 10.5 | AM14: 12 | AN14: 12 | AO14: 10 | AP14: 5.5 | AQ14: 10 | AR14: 12 | AS14: 10.5 | AT14: 10 | AU14: 10 | AV14: 10.5 | AW14: 9.5 | AX14: 12 | AY14: 10.5 | AZ14: 10 | BA14: 10 | BB14: 10.5 | BC14: 10.6 | BD14: 12 | BE14: 10 | BF14: 8.8 | BG14: 10 | BH14: 10.5 | BI14: 9.5 | BJ14: 10.5 | BK14: 8.8 | BM14: =AVERAGE(D14:BK14) -> 9.1482759
C15: 2014 | D15: 10 | E15: 8 | F15: 8 | G15: 9 | H15: 10 | I15: 10 | J15: 10.5 | K15: 10 | L15: 10 | M15: 9.5 | N15: 10 | O15: 8 | P15: 9.9 | S15: 8.5 | T15: 10 | U15: 10 | V15: 8.5 | W15: 10 | X15: 11.5 | Y15: 10 | Z15: 10.2 | AA15: 10.2 | AB15: 6 | AC15: 8 | AD15: 10 | AE15: 10 | AF15: 8.2 | AG15: 10 | AH15: 10 | AI15: 10.5 | AJ15: 12 | AK15: 10.5 | AL15: 9.8 | AM15: 10.5 | AN15: 10.2 | AO15: 8 | AP15: 9.4 | AQ15: 10 | AR15: 10 | AS15: 10 | AT15: 10.5 | AU15: 10.2 | AV15: 12 | AW15: 10 | AX15: 8.5 | AY15: 10 | AZ15: 10.5 | BA15: 10 | BM15: =AVERAGE(D15:BK15) -> 9.7208333
C16: 2015 | N16: 6.97 | O16: 7.2 | P16: 8.21 | Q16: 4.63 | R16: 7.7 | S16: 8.35 | T16: 7.8 | U16: 6.4 | V16: 5.43 | W16: 7.3 | X16: 6.2 | Y16: 8.75 | AC16: 5.3 | AH16: 6.7 | AI16: 6.5 | AJ16: 4.5 | AK16: 6.2 | AL16: 7.2 | AM16: 7.58 | AN16: 7.51 | AO16: 5 | AP16: 6.71 | AQ16: 6.89 | AR16: 4.24 | AS16: 7.01 | AT16: 5.8 | AU16: 6 | AW16: 5.67 | AX16: 7.2 | AY16: 7.21 | AZ16: 5.99 | BB16: 6.25 | BC16: 6.13 | BD16: 4.13 | BE16: 7.51 | BF16: 5.81 | BG16: 5.68 | BH16: 6.44 | BI16: 6.55 | BJ16: 5.81 | BK16: 4.41 | BM16: =AVERAGE(D16:BK16) -> 6.4114634
C17: 2016 | D17: 7.02 | I17: 3.68 | J17: 4.61 | K17: 5.31 | L17: 6.22 | N17: 7 | O17: 7 | P17: 5.54 | Q17: 4.92 | R17: 7 | S17: 6.2 | T17: 7 | U17: 8 | V17: 6.47 | W17: 7 | X17: 7 | Y17: 5.46 | Z17: 7.26 | AA17: 5.46 | AC17: 7.5 | AD17: 7.72 | AE17: 8 | AF17: 4.46 | AG17: 7 | AH17: 7 | AI17: 6 | AJ17: 8.5 | AK17: 8 | AL17: 5.6 | AW17: 8.41 | AX17: 9.12 | AY17: 9.12 | AZ17: 8.31 | BA17: 8.4 | BM17: =AVERAGE(D17:BK17) -> 6.8026471
B20: Trader | D20: Jan | I20: Feb | N20: March | S20: April | X20: May | AC20: Jun | AH20: July | AM20: Aug | AR20: Sept | AW20: Oct | BB20: Nov | BG20: Dec
B21: MUNSAD | C21: 2012 | D21: 12.3 | E21: 11 | F21: 11 | G21: 12 | H21: 12 | I21: 12 | J21: 12.5 | K21: 10.75 | L21: 14 | M21: 12 | N21: 13.5 | O21: 11.4 | P21: 11 | Q21: 9.3 | R21: 12.5 | S21: 9 | T21: 10 | U21: 10.6 | V21: 10 | W21: 12 | X21: 8.7 | Y21: 9.7 | Z21: 11 | AA21: 9.8 | AB21: 8.7 | AC21: 10 | AD21: 9.6 | AE21: 8.4 | AF21: 9.26 | AG21: 8.27 | AH21: 8.28 | AI21: 9 | AJ21: 8.5 | AK21: 9 | AL21: 7 | AM21: 8.4 | AN21: 8.21 | AO21: 8.6 | AP21: 8.6 | AQ21: 7 | AR21: 9.5 | AS21: 8.2 | AT21: 13 | AU21: 9.5 | AV21: 9.5 | AW21: 10.5 | AX21: 9.5 | AY21: 9.3 | AZ21: 8.5 | BA21: 11.2 | BB21: 10.7 | BC21: 10.5 | BD21: 10.8 | BE21: 10.5 | BF21: 9.1 | BG21: 13.05 | BH21: 12 | BI21: 11 | BJ21: 12.8 | BM21: =AVERAGE(D21:BK21) -> 10.237627
C22: 2013 | D22: 12.65 | E22: 12.6 | F22: 11 | G22: 13 | H22: 12 | I22: 11.5 | J22: 13 | K22: 12.8 | L22: 11.7 | M22: 13.25 | N22: 12 | O22: 12 | P22: 12.3 | Q22: 12.3 | R22: 11 | S22: 12 | T22: 10.5 | U22: 9 | V22: 10 | W22: 10.5 | X22: 9.7 | Y22: 10.5 | Z22: 10.2 | AA22: 9.1 | AB22: 8.9 | AC22: 8.5 | AD22: 9.7 | AE22: 8.6 | AF22: 8.6 | AH22: 11 | AI22: 8.5 | AJ22: 7.2 | AK22: 10.38 | AL22: 7.4 | AM22: 9.7 | AN22: 10.3 | AO22: 9.8 | AP22: 9.7 | AQ22: 8.9 | AR22: 10 | AS22: 11 | AT22: 11 | AU22: 12 | AV22: 12 | AW22: 11 | AX22: 11.34 | AY22: 9 | AZ22: 9.2 | BA22: 10.5 | BB22: 11.7 | BC22: 11.2 | BD22: 10.8 | BE22: 10.9 | BF22: 10.8 | BG22: 10.7 | BH22: 10.7 | BI22: 10.7 | BJ22: 8.82 | BK22: 10.18 | BM22: =AVERAGE(D22:BK22) -> 10.598644
C23: 2014 | AR23: 9.6 | AS23: 9 | BG23: 8.32 | BH23: 8.28 | BI23: 9.26 | BM23: =AVERAGE(D23:BK23) -> 8.892
C24: 2015 | N24: 6 | O24: 6 | BM24: =AVERAGE(D24:BK24) -> 6
C25: 2016 | AM25: 5.8 | AR25: 5.8 | AS25: 5.8 | AW25: 5.8 | AX25: 5.8 | BM25: =AVERAGE(D25:BK25) -> 5.8
B28: Trader | D28: Jan | I28: Feb | N28: March | S28: April | X28: May | AC28: Jun | AH28: July | AM28: Aug | AR28: Sept | AW28: Oct | BB28: Nov | BG28: Dec
B29: PHOENIX METAL | C29: 2012 | D29: 9 | E29: 8.74 | F29: 9.3 | G29: 8.8 | H29: 9.79 | I29: 11.56 | J29: 3.8 | K29: 11.7 | L29: 11.66 | M29: 10.6 | N29: 11 | O29: 6.61 | P29: 8.43 | Q29: 10.33 | R29: 8.6 | S29: 9.6 | T29: 12 | U29: 8.8 | V29: 9.37 | W29: 10.47 | X29: 10.64 | Y29: 11.12 | Z29: 9.5 | AA29: 10.7 | AB29: 10.3 | AC29: 9 | AD29: 9.8 | AE29: 8.35 | AF29: 7.8 | AG29: 9.32 | AH29: 8.4 | AI29: 6.05 | AJ29: 6.34 | AK29: 8.92 | AL29: 8.87 | AM29: 8.1 | AN29: 7.78 | AO29: 7.86 | AP29: 7.7 | AQ29: 8.18 | AR29: 10 | AS29: 8 | AT29: 9.37 | AU29: 8.32 | AV29: 8.25 | AW29: 9.65 | AX29: 8.8 | AY29: 10.8 | AZ29: 10.33 | BA29: 9.5 | BB29: 9.06 | BC29: 8.86 | BD29: 8.73 | BE29: 9.8 | BF29: 9.3 | BG29: 9 | BH29: 8.13 | BI29: 10.3 | BJ29: 8.76 | BK29: 12.1 | BM29: =AVERAGE(D29:BK29) -> 9.1991667
C30: 2013 | D30: 11.5 | E30: 10.35 | F30: 12.3 | G30: 12.65 | H30: 12.15 | I30: 12.48 | J30: 12.55 | K30: 10.75 | L30: 10.55 | M30: 12.12 | N30: 11 | O30: 13.71 | P30: 11.45 | Q30: 6.9 | R30: 11.45 | S30: 12.1 | T30: 9.4 | U30: 9.6 | V30: 9.96 | W30: 9.74 | X30: 6.9 | Y30: 10.31 | Z30: 9.6 | AA30: 6.15 | AB30: 11 | AC30: 7.68 | AD30: 7.4 | AE30: 10.43 | AF30: 11.5 | AG30: 11.63 | AH30: 10.83 | AI30: 8 | AJ30: 10.25 | AK30: 9.66 | AL30: 9 | AM30: 10.58 | AN30: 9 | AO30: 11.53 | AP30: 8.26 | AQ30: 10 | AR30: 10.28 | AS30: 12.69 | AT30: 13.38 | AU30: 11.47 | AV30: 9.2 | AW30: 10.22 | AX30: 8.09 | AY30: 7.64 | AZ30: 10.6 | BA30: 12.8 | BB30: 12.5 | BC30: 9.7 | BD30: 9.9 | BE30: 12.1 | BF30: 12 | BG30: 10.15 | BH30: 13 | BI30: 12.5 | BJ30: 10.9 | BK30: 10.2 | BM30: =AVERAGE(D30:BK30) -> 10.529
C31: 2014 | D31: 12.7 | E31: 9.4 | F31: 12 | G31: 9.2 | H31: 10.8 | I31: 10.5 | J31: 11 | K31: 9.8 | L31: 8.95 | M31: 12.4 | N31: 10.5 | O31: 13 | P31: 13 | Q31: 12 | R31: 11.69 | S31: 10.5 | T31: 11.2 | U31: 10.3 | V31: 12.2 | W31: 12 | X31: 12.4 | Y31: 12.3 | Z31: 12.7 | AA31: 11.4 | AB31: 11.1 | AC31: 11 | AD31: 13.7 | AE31: 11 | AF31: 13 | AG31: 9.2 | AH31: 12.2 | AI31: 12.8 | AJ31: 9.7 | AK31: 11.8 | AL31: 11.5 | AM31: 12.25 | AN31: 9.3 | AO31: 10.7 | AP31: 12 | AQ31: 13.17 | AR31: 10.9 | AS31: 11.1 | AT31: 12.51 | AU31: 11.8 | AV31: 8.8 | AW31: 9.55 | AX31: 8.7 | AY31: 9.8 | AZ31: 9.4 | BA31: 9.8 | BB31: 10.8 | BC31: 9.9 | BD31: 9.5 | BE31: 10 | BF31: 9.5 | BG31: 7 | BH31: 8.77 | BI31: 10.48 | BJ31: 10.15 | BK31: 11.13 | BM31: =AVERAGE(D31:BK31) -> 10.9325
C32: 2015 | D32: 10.64 | E32: 9.25 | F32: 9.8 | G32: 9.71 | H32: 10.11 | I32: 5 | J32: 9.1 | K32: 9.6 | L32: 5.6 | M32: 8.28 | N32: 8.5 | O32: 9.14 | P32: 9.42 | Q32: 7.5 | R32: 7.8 | S32: 6.24 | T32: 6.79 | U32: 8.65 | V32: 8.23 | W32: 8 | X32: 8.64 | Y32: 7.7 | Z32: 8.12 | AA32: 6.5 | AB32: 6.9 | AC32: 7.3 | AD32: 8.74 | AE32: 8.47 | AF32: 7.82 | AG32: 6.81 | AH32: 7.65 | AI32: 7.61 | AJ32: 7.06 | AK32: 7.65 | AL32: 7.58 | AM32: 6.31 | AN32: 6.56 | AO32: 6.64 | AP32: 5.63 | AQ32: 4.8 | AR32: 7.96 | AS32: 6.93 | AT32: 8.28 | AU32: 8.86 | AV32: 7 | AW32: 7.22 | AX32: 7.62 | AY32: 6.7 | AZ32: 8 | BA32: 8.88 | BB32: 6.94 | BC32: 6.16 | BD32: 7.44 | BE32: 7.13 | BF32: 7.25 | BG32: 7.88 | BH32: 7.66 | BI32: 7.87 | BJ32: 5.4 | BK32: 7.85 | BM32: =AVERAGE(D32:BK32) -> 7.6813333
C33: 2016 | D33: 7.32 | E33: 10.5 | F33: 5.75 | G33: 7 | H33: 7.13 | I33: 7.65 | J33: 8.38 | K33: 8.64 | L33: 7.81 | M33: 7.65 | N33: 7.4 | O33: 8.31 | P33: 8.74 | Q33: 9.69 | R33: 7.93 | S33: 7.58 | T33: 7.6 | U33: 7.93 | V33: 7.57 | W33: 8.05 | X33: 5.37 | Y33: 9.16 | Z33: 8.73 | AA33: 8.6 | AB33: 7.68 | AC33: 8.81 | AD33: 8.32 | AE33: 8.78 | AF33: 8.85 | AG33: 8.71 | AH33: 7.76 | AI33: 8.38 | AJ33: 10.74 | AK33: 9.61 | AL33: 6.2 | AM33: 10.71 | AN33: 9.48 | AO33: 9.19 | AP33: 10.02 | AQ33: 11.02 | AR33: 11.31 | AS33: 11.92 | AT33: 9.8 | AU33: 10.5 | AV33: 9.95 | AW33: 8.13 | AX33: 10.21 | AY33: 10.42 | AZ33: 9.85 | BA33: 10.77 | BB33: 9.19 | BC33: 11.61 | BD33: 9.84 | BE33: 9.84 | BF33: 7.75 | BM33: =AVERAGE(D33:BK33) -> 8.8334545
BO34: 2012 | BP34: =(BM5+BM13+BM21+BM29)/4 -> 9.2139125
BO35: 2013 | BP35: =(BM6+BM14+BM22+BM30)/4 -> 10.196272
BO36: 2014 | BP36: =(BM7+BM15+BM23+BM31)/4 -> 10.101396
BO37: 2015 | BP37: =(BM8+BM16+BM24+BM32)/4 -> 7.0034075
BO38: 2016 | BP38: =(BM9+BM17+BM25+BM33)/4 -> 7.5733436
BO39: 2012 | BP39: 2013 | BQ39: 2014 | BR39: 2015 | BS39: 2016
BN40: USD/ton | BO40: =BP34*1000 -> 9213.9125 | BP40: =BP35*1000 -> 10196.272 | BQ40: =BP36*1000 -> 10101.396 | BR40: =BP37*1000 -> 7003.4075 | BS40: =BP38*1000 -> 7573.3436
A45: Coltan
B46: Trader | D46: Jan | I46: Feb | N46: March | S46: April | X46: May | AC46: Jun | AH46: July | AM46: Aug | AR46: Sept | AW46: Oct | BB46: Nov | BG46: Dec | BO46: 2012 | BP46: 2013 | BQ46: 2014 | BR46: 2015 | BS46: 2016
B47: MSA | C47: 2012 | AF47: 67.44 | AG47: 35.36 | AH47: 73.1 | AI47: 29.92 | AJ47: 80.73 | AK47: 46.8 | AL47: 40.65 | AM47: 44.72 | AN47: 40.65 | AO47: 35.12 | AP47: 69.1 | AQ47: 44.88 | AR47: 40.65 | AS47: 38.5 | AT47: 60.16 | AU47: 42.58 | AV47: 24.84 | AW47: 31.53 | AX47: 56.42 | AY47: 40.65 | AZ47: 83.63 | BA47: 33.66 | BB47: 49 | BC47: 58.54 | BD47: 43.3 | BE47: 26.2 | BF47: 49.8 | BG47: 41.68 | BH47: 68 | BI47: 70.76 | BJ47: 86.19 | BK47: 40.32 | BM47: =AVERAGE(D47:BK47) -> 49.84 | BN47: USD/ton | BO47: =BM47*1000 -> 49840 | BP47: =BM48*1000 -> 56141 | BQ47: =BM49*1000 -> 44661.636 | BR47: =BM50*1000 -> 42300.37 | BS47: =BM51*1000 -> 35080.727
C48: 2013 | D48: 108.68 | E48: 112.61 | F48: 100.3 | G48: 108.16 | H48: 120.39 | I48: 109.12 | J48: 69.05 | K48: 60.79 | L48: 44.69 | M48: 60.74 | N48: 47.68 | O48: 59.3 | P48: 49.29 | Q48: 48.3 | R48: 59.78 | S48: 88.94 | T48: 63.56 | U48: 57.39 | V48: 49.64 | W48: 58.39 | X48: 38.43 | Y48: 67.74 | Z48: 70.3 | AA48: 66.95 | AB48: 40.56 | AC48: 65.9 | AD48: 70.9 | AE48: 48.14 | AF48: 73.11 | AG48: 62.56 | AH48: 38.17 | AI48: 25.95 | AJ48: 32.79 | AK48: 77.12 | AL48: 48.96 | AM48: 58.7 | AN48: 66.14 | AO48: 54.8 | AP48: 61.72 | AQ48: 62.45 | AR48: 60.32 | AS48: 29.08 | AT48: 59.93 | AU48: 70.65 | AV48: 51.41 | AW48: 46.53 | AX48: 50.47 | AY48: 31.82 | AZ48: 31.82 | BA48: 30.31 | BB48: 31.05 | BC48: 30.26 | BD48: 21.91 | BE48: 25.28 | BF48: 28.61 | BG48: 40.39 | BH48: 17.29 | BI48: 31.1 | BJ48: 37.97 | BK48: 34.07 | BM48: =AVERAGE(D48:BK48) -> 56.141
C49: 2014 | D49: 42.3 | E49: 25.88 | F49: 25.88 | G49: 37.91 | H49: 26.71 | N49: 20.29 | O49: 38.9 | P49: 37.97 | Q49: 31.39 | R49: 19.8 | S49: 33.67 | T49: 50.64 | U49: 32.9 | V49: 35.1 | W49: 39.55 | X49: 36.4 | Y49: 43.79 | Z49: 34.06 | AA49: 41.66 | AB49: 59.27 | AC49: 43.55 | AD49: 43.97 | AE49: 72.8 | AF49: 47.81 | AG49: 68.93 | AH49: 45.82 | AI49: 41.62 | AJ49: 65.78 | AK49: 40.27 | AL49: 84.21 | AM49: 47.68 | AN49: 47.3 | AO49: 50.53 | AP49: 51.3 | AQ49: 50.34 | AR49: 46.8 | AS49: 51.72 | AT49: 51.21 | AU49: 48.7 | AV49: 36.33 | AW49: 43.93 | AX49: 43.93 | AY49: 56.52 | AZ49: 35.59 | BA49: 47.45 | BB49: 47.12 | BC49: 43.14 | BD49: 87.61 | BE49: 56.86 | BF49: 45.85 | BG49: 21.63 | BH49: 27.46 | BI49: 26.4 | BJ49: 83.5 | BK49: 38.66 | BM49: =AVERAGE(D49:BK49) -> 44.661636
C50: 2015 | D50: 43.91 | E50: 33.34 | F50: 41.01 | G50: 49.25 | H50: 52.18 | I50: 62.76 | J50: 36.7 | K50: 36.7 | L50: 36.67 | M50: 36.67 | N50: 53.86 | O50: 53.86 | P50: 51.86 | Q50: 49.84 | R50: 63 | S50: 25.37 | T50: 34.06 | U50: 47.11 | V50: 81.39 | W50: 46.15 | AC50: 37.1 | AD50: 24 | AE50: 33.2 | AF50: 50.7 | AH50: 53.64 | AI50: 53.27 | AJ50: 40.4 | AK50: 29.7 | AL50: 47.5 | AM50: 59.2 | AN50: 45.1 | AO50: 49.02 | AP50: 39.8 | AQ50: 60.7 | AR50: 53 | AS50: 40 | AT50: 43.5 | AU50: 32.7 | AV50: 32.2 | AW50: 29.1 | AX50: 38.3 | AY50: 40.2 | AZ50: 35.9 | BA50: 38.8 | BB50: 38.2 | BC50: 34.6 | BD50: 34.7 | BE50: 35.7 | BF50: 34.6 | BG50: 36.1 | BH50: 35.2 | BI50: 21.1 | BJ50: 35 | BK50: 36.3 | BM50: =AVERAGE(D50:BK50) -> 42.30037
C51: 2016 | D51: 21.7 | E51: 36.2 | F51: 27.6 | G51: 34.2 | H51: 34.2 | I51: 31.1 | J51: 54 | K51: 53.8 | L51: 53.8 | M51: 40.7 | N51: 15.9 | O51: 36 | P51: 20.61 | Q51: 39.5 | R51: 37.15 | S51: 38.1 | T51: 34.1 | U51: 47.7 | V51: 44.5 | W51: 45.7 | X51: 35.6 | Y51: 40 | Z51: 48.5 | AA51: 51.8 | AB51: 52.9 | AC51: 37.7 | AD51: 33.1 | AE51: 35.6 | AF51: 30.3 | AG51: 34.1 | AH51: 37.38 | AI51: 34.7 | AJ51: 34.1 | AK51: 18.2 | AL51: 36.2 | AM51: 44 | AN51: 15.5 | AO51: 50.9 | AP51: 45.9 | AQ51: 51.2 | AR51: 30.4 | AS51: 29.4 | AT51: 24.8 | AU51: 33.1 | AV51: 35.8 | AW51: 24.2 | AX51: 23.4 | AY51: 24.5 | AZ51: 21 | BA51: 27.6 | BB51: 31.3 | BC51: 33.3 | BD51: 29.4 | BE51: 22.5 | BF51: 24.5 | BM51: =AVERAGE(D51:BK51) -> 35.080727
A58: Wolfram
B59: Trader | D59: Jan | I59: Feb | N59: March | S59: April | X59: May | AC59: Jun | AH59: July | AM59: Aug | AR59: Sept | AW59: Oct | BB59: Nov | BG59: Dec | BO59: 2012 | BP59: 2013 | BQ59: 2014 | BR59: 2015 | BS59: 2016
B60: MSA | C60: 2012 | N60: 13.43 | O60: 13.35 | AC60: 17.67 | AD60: 17.67 | AE60: 14 | AF60: 12.35 | AH60: 13.75 | AI60: 9.9 | AJ60: 11.71 | AK60: 14.41 | AL60: 14.41 | AM60: 8.15 | AN60: 9.75 | AO60: 9.75 | AP60: 11.95 | AQ60: 14.76 | AR60: 11.57 | AS60: 9.45 | AT60: 19.88 | AU60: 12.08 | AV60: 20.21 | AW60: 10.5 | AX60: 12.03 | AY60: 11.83 | AZ60: 13.05 | BA60: 20.06 | BB60: 9.35 | BC60: 11.36 | BD60: 11.49 | BE60: 11.45 | BF60: 9.48 | BG60: 10.95 | BH60: 12.31 | BI60: 12.25 | BJ60: 12 | BK60: 10.25 | BM60: =AVERAGE(D60:BK60) -> 12.737778 | BN60: USD/ton | BO60: =BM60*1000 -> 12737.778 | BP60: =BM61*1000 -> 11327.25 | BQ60: =BM62*1000 -> 10091.2 | BR60: =BM63*1000 -> 7377.5 | BS60: =((BM64*1000)+(BM72*1000))/2 -> 5573.1053
C61: 2013 | D61: 12.95 | E61: 8.66 | F61: 10.44 | G61: 8.59 | H61: 10.45 | I61: 10.75 | J61: 10.7 | K61: 10.25 | L61: 9.55 | M61: 8.45 | N61: 11.32 | O61: 10.45 | P61: 8.5 | Q61: 8.7 | R61: 8.62 | S61: 7.8 | T61: 8.87 | U61: 5.2 | V61: 11.86 | W61: 10.1 | X61: 17.75 | Y61: 9.85 | Z61: 9.89 | AA61: 9.125 | AB61: 12.15 | AC61: 13.41 | AD61: 11.55 | AE61: 12.45 | AF61: 12.6 | AG61: 12.05 | AH61: 11.26 | AI61: 11.26 | AJ61: 11.45 | AK61: 14.64 | AL61: 12.71 | AM61: 11.44 | AN61: 10.75 | AO61: 15.25 | AP61: 11.2 | AQ61: 12.6 | AR61: 14.45 | AS61: 15.5 | AT61: 11.08 | AU61: 11.36 | AV61: 16.52 | AW61: 10.91 | AX61: 11.84 | AY61: 11.84 | AZ61: 11.84 | BA61: 9.82 | BB61: 12.12 | BC61: 12.04 | BD61: 12.95 | BE61: 12.2 | BF61: 9.62 | BG61: 11.59 | BH61: 11.6 | BI61: 9.69 | BJ61: 11.05 | BK61: 16.02 | BM61: =AVERAGE(D61:BK61) -> 11.32725
C62: 2014 | D62: 14.55 | E62: 8.6 | F62: 12.88 | G62: 11.6 | H62: 9.9 | I62: 19.77 | J62: 12.45 | K62: 13.31 | L62: 12.29 | M62: 6.5 | N62: 11.07 | O62: 10.25 | P62: 11 | Q62: 10.25 | R62: 8.58 | X62: 9.73 | Y62: 10.1 | Z62: 7.57 | AA62: 9.24 | AB62: 9.03 | AC62: 10.55 | AD62: 8.91 | AE62: 9.43 | AF62: 9.68 | AG62: 10.22 | AH62: 10.69 | AI62: 10.69 | AJ62: 9.12 | AK62: 9.12 | AL62: 9.64 | AM62: 11.31 | AN62: 10.11 | AO62: 10.11 | AP62: 7.5 | AQ62: 10.11 | AR62: 11.31 | AS62: 9.1 | AT62: 8.52 | AU62: 10.13 | AV62: 9.78 | AW62: 9.65 | AX62: 9.54 | AY62: 8.3 | AZ62: 12 | BA62: 8.9 | BB62: 8.1 | BC62: 8.1 | BD62: 8.1 | BE62: 9.07 | BF62: 8.1 | BM62: =AVERAGE(D62:BK62) -> 10.0912
C63: 2015 | I63: 6.9 | J63: 7.18 | K63: 7.32 | L63: 7.51 | M63: 6.83 | S63: 7.16 | T63: 7.16 | U63: 7.71 | V63: 7.8 | W63: 6.45 | X63: 8.28 | Y63: 8.01 | Z63: 7.33 | AA63: 8.2 | AB63: 8.2 | AC63: 6.91 | AD63: 6.91 | AE63: 7.79 | AF63: 6.95 | AG63: 6.95 | BM63: =AVERAGE(D63:BK63) -> 7.3775
C64: 2016 | I64: 4.3 | J64: 3.3 | K64: 4.5 | L64: 4.5 | M64: 4.5 | N64: 4.6 | X64: 3 | Y64: 4.3 | AC64: 6.91 | AH64: 6.25 | AI64: 6.25 | AJ64: 6.25 | AK64: 6.25 | AL64: 6.25 | AR64: 5.8 | AW64: 6.7 | AX64: 6.7 | AY64: 6.7 | AZ64: 6.7 | BB64: 6.4 | BC64: 6.4 | BD64: 6.2 | BE64: 5.5 | BF64: 5.8 | BM64: =AVERAGE(D64:BK64) -> 5.5858333
B67: Trader | D67: Jan | I67: Feb | N67: March | S67: April | X67: May | AC67: Jun | AH67: July | AM67: Aug | AR67: Sept | AW67: Oct | BB67: Nov | BG67: Dec
B68: Phoenix | C68: 2012 | BM68: =AVERAGE(D68:BK68) -> #DIV/0!
C69: 2013 | BM69: =AVERAGE(D69:BK69) -> #DIV/0!
C70: 2014 | BM70: =AVERAGE(D70:BK70) -> #DIV/0!
C71: 2015 | BM71: =AVERAGE(D71:BK71) -> #DIV/0!
C72: 2016 | D72: 3.82 | E72: 5.66 | F72: 5.66 | G72: 5.66 | H72: 5.66 | I72: 4.45 | J72: 4.45 | K72: 4.45 | L72: 4.45 | M72: 4.45 | N72: 4.82 | O72: 4.82 | P72: 4.82 | Q72: 5.95 | R72: 5.95 | S72: 3.87 | T72: 3.87 | U72: 3.87 | V72: 5.11 | W72: 5.31 | X72: 5.31 | Y72: 5.31 | Z72: 5.31 | AA72: 6.14 | AB72: 6.14 | AC72: 5.69 | AD72: 5.69 | AE72: 5.69 | AF72: 5.69 | AG72: 5.69 | AH72: 5.26 | AI72: 5.3 | AJ72: 5.3 | AK72: 5.3 | AL72: 5.3 | AM72: 5.88 | AN72: 5.88 | AO72: 5.88 | AP72: 5.63 | AQ72: 5.63 | AR72: 5.61 | AS72: 5.61 | AT72: 5.61 | AU72: 5.61 | AV72: 5.65 | AW72: 8.27 | AX72: 8.27 | AY72: 6.51 | BB72: 7.96 | BC72: 6.62 | BD72: 6.62 | BE72: 6.62 | BF72: 6.62 | BM72: =AVERAGE(D72:BK72) -> 5.5603774
A75: Source: ITRI/iTSCi Logbook

Sheet Metal prices
C2: Tin | D2: Tantulam | E2: Tungsten
C3: US$/ton | D3: US$/ton | E3: US$/ton
B4: 1980 | C4: 16777 | E4: 18500
B5: 1981 | C5: 14168 | E5: 17600
B6: 1982 | C6: 12829 | E6: 14000
B7: 1983 | C7: 12987 | E7: 10400
B8: 1984 | C8: 12230 | E8: 11400
B9: 1985 | C9: 11539 | E9: 9310
B10: 1986 | C10: 6161 | E10: 7070
B11: 1987 | C11: 6689 | E11: 6350
B12: 1988 | C12: 7051 | E12: 7500
B13: 1989 | C13: 8534 | E13: 10600
B14: 1990 | C14: 6085 | E14: 8480
B15: 1991 | C15: 5595 | E15: 9870
... B23: 1999 | C23: 5391 | E23: 7070
B24: 2000 | C24: 5435 | D24: 591000 | E24: 8290
C25: Tin (LH axis) | D25: Tantalum (RH axis) | E25: Tungsten (LH axis)
B26: 2001 | C26: 4889 | D26: 99500 | E26: 12500
B27: 2002 | C27: 4061 | D27: 80500 | E27: 9080
B28: 2003 | C28: 4889 | D28: 80200 | E28: 8710
B29: 2004 | C29: 8480 | D29: 80000 | E29: 11600
B30: 2005 | C30: 7385 | D30: 94000 | E30: 29900
B31: 2006 | C31: 8754 | D31: 87500 | E31: 37000
B32: 2007 | C32: 14495 | D32: 100000 | E32: 35900
B33: 2008 | C33: 18466 | D33: 118000 | E33: 35100
B34: 2009 | C34: 13602 | D34: 108000 | E34: 25700
B35: 2010 | C35: 20367 | D35: 146000 | E35: 27000
B36: 2011 | C36: 26051 | D36: 336000 | E36: 46700
B37: 2012 | C37: 21109 | D37: 292000 | E37: 56700
... B43: 2018 | C43: 21825 | D43: 151800 | E43: 30300
