Workbook
Name ADDITIVE: #REF!
Name AGRICULT: #REF!
Name ANTCOAL: #REF!
Name AUTOCHP: #REF!
Name AUTOELEC: #REF!
Name AUTOHEAT: #REF!
Name AVBUNK: #REF!
Name AVGAS: #REF!
Name BIODIESEL: #REF!
Name BIOGASES: #REF!
Name BIOGASOL: #REF!
Name BIOJETKERO: #REF!
Name BITCOAL: #REF!
Name BITUMEN: #REF!
Name BKB: #REF!
Name BLFURGS: #REF!
Name BOILER: #REF!
Name CFHeadings: #REF!
Name CHARCOAL: #REF!
Name CHEMHEAT: #REF!
Name CHEMICAL: #REF!
Name COALTAR: #REF!
Name COKCOAL: #REF!
Name COKEOVGS: #REF!
Name COMMPUB: #REF!
Name CONSTRUC: #REF!
Name ConversionFactors: OFFSET(#REF!,0,0,100,16)
Name Countries: #REF!
Name CountryName: #REF!
Name CRUDEOIL: #REF!
Name DataYear: #REF!
Name DBDef1: #REF!
Name DBDef2: #REF!
Name DBDef2a: #REF!
Name DBDef3: #REF!
Name DBLinks: #REF!
Name dbsourcefiles: #REF!
Name DISTLOSS: #REF!
Name DOMESAIR: #REF!
Name DOMESNAV: #REF!
Name DOMSUP: #REF!
Name EBIOGAS: #REF!
Name EBKB: #REF!
Name EBLASTFUR: #REF!
Name ECHARCOAL: #REF!
Name ECOALLIQ: #REF!
Name ECOKEOVS: #REF!
Name EGASWKS: #REF!
Name EGTL: #REF!
Name ELECTR: #REF!
Name ELNG: #REF!
Name ELOUTPUT: #REF!
Name EMINES: #REF!
Name ENONSPEC: #REF!
Name ENUC: #REF!
Name EOILGASEX: #REF!
Name EPATFUEL: #REF!
Name EPOWERPLT: #REF!
Name EPUMPST: #REF!
Name EREFINER: #REF!

Sheet HS Code
A1: PCT CODE | D1: DESCRIPTION | E1: CD (%) | F1: chrome-extension://efaidnbmnnnibpcajpcglclefindmkaj/https://download1.fbr.gov.pk/Docs/2017112112112348253CustomsTariff2017-18Ch1-99.pdf
A2: Heading / | B2: Statistical | K2: Lookup Table
A3: Sub- | B3: suffix | L3: HS Code | M3: Category | N3: Product Name
A4: heading | L4: 27149000 | M4: Coal and Coke | N4: Coal; briquettes, ovoids and similar solid fuels manufactured from coal. | O4: Other of (Bitumen and asphalt, natural; bituminous or oil shale and tar sands; asphaltites and asphaltic rocks.
A5: -1 | B5: -2 | D5: -3 | E5: -4 | L5: 27011100 | M5: Coal and Coke | N5: Coal; briquettes, ovoids and similar solid fuels manufactured from coal. | O5: Anthracite
A6: 101 | C6: Live horses, asses, mules and hinnies. | L6: 27011200 | M6: Coal and Coke | N6: Coal; briquettes, ovoids and similar solid fuels manufactured from coal. | O6: Bituminous coal
C7: - Horses: | L7: 27011900 | M7: Coal and Coke | N7: Coal; briquettes, ovoids and similar solid fuels manufactured from coal. | O7: Other coal
A8: 1012100 | C8: - - Pure-bred breeding animals | E8: 3 | L8: 27012000 | M8: Coal and Coke | N8: Coal; briquettes, ovoids and similar solid fuels manufactured from coal. | O8: Briquettes, ovoids and similar soild fuels manufactured from coal
A9: 10129 | C9: - - Other | E9: 3 | L9: 27030000 | M9: Coal and Coke | N9: Peat (including peat litter), whether or not agglomerated. | O9: Peat (including peat litter), whether or not agglomerated.
A10: 1013 | C10: - Asses | E10: 3 | L10: 27040000 | M10: Coal and Coke | N10: Coke and semi- coke of coal, of lignite or of peat, whether or not agglomerated; retort carbon. | O10: Coke and semi- coke of coal, of lignite or of peat, whether or not agglomerated; retort carbon.
A11: 1019 | C11: - Other | E11: 3 | L11: 27060000 | M11: Coal and Coke | N11: Tar distilled from coal, from lignite or from peat, and other mineral tars, whether or not dehydrated or partially distilled, including reconstituted tars. | O11: Tar distilled from coal, from lignite or from peat, and other mineral tars, whether or not dehydrated or partially distilled, including reconstituted tars.
A12: 102 | C12: Live bovine animals. | L12: 27072000 | M12: Oils | N12: Oils and other products of the distillation of high temperature coal tar; similar products in which the weight of the aromatic constituents exceeds that of the non- aromatic constituents. | O12: Toluol (toluene)
C13: - Cattle: | L13: 27073000 | M13: Oils | N13: Oils and other products of the distillation of high temperature coal tar; similar products in which the weight of the aromatic constituents exceeds that of the non- aromatic constituents. | O13: Xylol (xylenes)
C14: - - Pure-bred breeding animals: | L14: 27074000 | M14: Oils | N14: Oils and other products of the distillation of high temperature coal tar; similar products in which the weight of the aromatic constituents exceeds that of the non- aromatic constituents. | O14: Naphthalene
A15: 1022110 | C15: - - - Bulls | E15: 3 | L15: 27075000 | M15: Oils | N15: Oils and other products of the distillation of high temperature coal tar; similar products in which the weight of the aromatic constituents exceeds that of the non- aromatic constituents. | O15: Other aromatic hydrocarbon mixtures of which 65 % or more by volume (including losses) distils at 250oC by the ISO 3405 method (equivalent to the ASTM D 86 method)
A16: 102212 | C16: - - - Cows | E16: 3 | L16: 27079100 | M16: Oils | N16: Oils and other products of the distillation of high temperature coal tar; similar products in which the weight of the aromatic constituents exceeds that of the non- aromatic constituents. | O16: Creosote oils
A17: 102213 | C17: - - - Oxen | E17: 3 | L17: 27079900 | M17: Oils | N17: Oils and other products of the distillation of high temperature coal tar; similar products in which the weight of the aromatic constituents exceeds that of the non- aromatic constituents. | O17: Carbon black oil (carbon black feedstock)
A18: 102219 | C18: - - - Other | E18: 3 | L18: 27082000 | M18: Oils | N18: Pitch and pitch coke, obtained from coal tar or from other mineral tars. | O18: Pitch coke
C19: - - | D19: Other: | L19: 27090000 | M19: Petroleum | N19: Petroleum oils and oils obtained from bituminous minerals, crude | O19: Petroleum oils and oils obtained from bituminous minerals, crude
A20: 102291 | C20: - - - Bulls | E20: 3 | L20: 27101210 | M20: Petroleum | N20: Petroleum oils and oils obtained from bituminous minerals, other than crude; preparations not elsewhere specified or included, containing by weight 70 % or more of petroleum oils or of oils obtained from bituminous minerals, these oils being the basic constituents of the preparations; waste oils. | O20: Motor spirit
A21: 102292 | C21: - - - Cows | E21: 3 | L21: 27101220 | M21: Petroleum | N21: Petroleum oils and oils obtained from bituminous minerals, other than crude; preparations not elsewhere specified or included, containing by weight 70 % or more of petroleum oils or of oils obtained from bituminous minerals, these oils being the basic constituents of the preparations; waste oils. | O21: Aviation spirit
A22: 102293 | C22: - - - Oxen | E22: 3 | L22: 27101230 | M22: Petroleum | N22: Petroleum oils and oils obtained from bituminous minerals, other than crude; preparations not elsewhere specified or included, containing by weight 70 % or more of petroleum oils or of oils obtained from bituminous minerals, these oils being the basic constituents of the preparations; waste oils. | O22: Spirit type jet fuel
A23: 102299 | C23: - - - Other | E23: 3 | L23: 27101240 | M23: White spirit and special boiling point industrial spirits | N23: Petroleum oils and oils obtained from bituminous minerals, other than crude; preparations not elsewhere specified or included, containing by weight 70 % or more of petroleum oils or of oils obtained from bituminous minerals, these oils being the basic constituents of the preparations; waste oils. | O23: White spirit
C24: - Buffalo: | L24: 27101250 | M24: Petroleum | N24: Petroleum oils and oils obtained from bituminous minerals, other than crude; preparations not elsewhere specified or included, containing by weight 70 % or more of petroleum oils or of oils obtained from bituminous minerals, these oils being the basic constituents of the preparations; waste oils. | O24: Solvent oil (non-composite)
A25: 1023100 | C25: - - Pure-bred breeding animals | E25: 3 | L25: 27101290 | M25: Petroleum | N25: Petroleum oils and oils obtained from bituminous minerals, other than crude; preparations not elsewhere specified or included, containing by weight 70 % or more of petroleum oils or of oils obtained from bituminous minerals, these oils being the basic constituents of the preparations; waste oils. | O25: Other
A26: 10239 | C26: - - Other | E26: 3 | L26: 27101910 | M26: Petroleum | N26: Kerosene, including kerosene type jet fuel: | O26: Kerosene
L27: 27101921 | M27: Petroleum | N27: Kerosene, including kerosene type jet fuel: | O27: Light diesel oil
A28: PCT CODE | D28: DESCRIPTION | E28: CD (%) | L28: 27101922 | M28: Petroleum | N28: Kerosene, including kerosene type jet fuel:
A29: Heading / | B29: Statistical | L29: 27101929 | M29: Petroleum | N29: Kerosene, including kerosene type jet fuel:
A30: Sub- | B30: suffix | L30: 27101931 | M30: Petroleum | N30: Kerosene, including kerosene type jet fuel:
A31: heading | L31: 27101932 | M31: Petroleum | N31: Kerosene, including kerosene type jet fuel:
A32: -1 | B32: -2 | D32: -3 | E32: -4 | L32: 27101939 | M32: Petroleum | N32: Kerosene, including kerosene type jet fuel:
A33: 1029 | C33: - Other | E33: 3 | L33: 27101941 | M33: Petroleum | N33: Kerosene, including kerosene type jet fuel:
A34: 103 | C34: Live swine. | L34: 27101942 | M34: Petroleum | N34: Kerosene, including kerosene type jet fuel:
A35: 1031 | C35: - Pure- bred breeding animals | E35: 20 | L35: 27101943 | M35: Petroleum | N35: Kerosene, including kerosene type jet fuel:
C36: - Other: | L36: 27101949 | M36: Petroleum | N36: Kerosene, including kerosene type jet fuel:
A37: 1039100 | C37: - - Weighing less than 50 kg | E37: 20 | L37: 27101951 | M37: Petroleum | N37: Kerosene, including kerosene type jet fuel:
A38: 10392 | C38: - - Weighing 50 kg or more | E38: 20 | L38: 27101952 | M38: Petroleum | N38: Kerosene, including kerosene type jet fuel:
A39: 104 | C39: Live sheep and goats. | L39: 27101953 | M39: Petroleum | N39: Kerosene, including kerosene type jet fuel:
A40: 1041 | C40: - Sheep | E40: 3 | L40: 27101954 | M40: Petroleum | N40: Kerosene, including kerosene type jet fuel:
A41: 1042 | C41: - Goats | E41: 3 | L41: 27101955 | M41: Petroleum | N41: Kerosene, including kerosene type jet fuel:
A42: 105 | C42: Live poultry, that is to say, fowls of the | L42: 27101956 | M42: Petroleum | N42: Kerosene, including kerosene type jet fuel:
C43: species Gallus domesticus, ducks, geese, | L43: 27101957 | M43: Petroleum | N43: Kerosene, including kerosene type jet fuel:
C44: turkeys and guinea fowls. | L44: 27101959 | M44: Petroleum | N44: Kerosene, including kerosene type jet fuel:
C45: - Weighing not more than 185 g: | L45: 27102000 | M45: Petroleum | N45: - Petroleum oils and oils obtained from bituminous minerals (other than crude) and preparations not elsewhere specified or included, containing by weight 70 % or more of petroleum oils or of oils obtained from bituminous minerals, these oils being the basic constituents of the preparations, containing biodiesel and other than waste oils
A46: 1051100 | C46: - - Fowls of the species Gallus domesticus | E46: 3 | L46: 27109100 | M46: Petroleum | N46: Containing polychlorinated biphenyls (PCBs), polychlorinated terphenyls (PCTs) or polybrominated biphenyls (PBBs)
C47: (chicken) | L47: 27109900 | M47: Petroleum | N47: Other
A48: 10512 | C48: - - Turkeys | E48: 3 | L48: 27111100 | M48: Natural Gas | N48: Natural gas Liquefied | O48: Natural gas Liquefied
A49: 10513 | C49: - - Ducks | E49: 3 | L49: 27111200 | N49: Propane | O49: Propane
A50: 10514 | C50: - - Geese | E50: 3 | L50: 27111300 | N50: Butanes | O50: Butanes
A51: 10515 | C51: - - Guinea fowls | E51: 3 | L51: 27111400 | N51: Ethylene, propylene, butylene and butadiene | O51: Ethylene, propylene, butylene and butadiene
C52: - Other: | L52: 27111900 | N52: L.P.G. | O52: L.P.G.
A53: 1059400 | C53: - - Fowls of the species Gallus domesticus | E53: 3 | L53: 27112100 | N53: Petroleum jelly; paraffin wax, micro- | O53: Natural gas
C54: (chicken) | L54: 27112900 | N54: Other | O54: Other
A55: 10599 | C55: - - | D55: Other | E55: 3 | L55: 27121000 | N55: Petroleum jelly | O55: Petroleum jelly
A56: 106 | C56: Other live animals. | L56: 27122000 | N56: Paraffin wax containing by weight less than 0.75 % of oil | O56: Paraffin wax containing by weight less than 0.75 % of oil
C57: - Mammals: | L57: 27129000 | N57: Slack wax | O57: Slack wax
A58: 1061100 | C58: - - Primates | E58: 3 | L58: 27131100 | N58: Petroleum coke, petroleum bitumen and other residues of petroleum oils or of oils obtained from bituminous minerals. | O58: Not calcined
A59: 10612 | C59: - - Whales, dolphins and porpoises (mammals of | E59: 3 | L59: 27131200 | N59: Petroleum coke, petroleum bitumen and other residues of petroleum oils or of oils obtained from bituminous minerals. | O59: Calcined
C60: the order Cetacea); manatees and dugongs | L60: 27132000 | N60: Petroleum coke, petroleum bitumen and other residues of petroleum oils or of oils obtained from bituminous minerals. | O60: Petroleum bitumen
C61: (mammals of the order Sirenia); seals,sea lions | L61: 27139000 | N61: Petroleum coke, petroleum bitumen and other residues of petroleum oils or of oils obtained from bituminous minerals. | O61: Carbon black oil (carbon black feed stock)
C62: and walruses (mammals of the suborder | L62: 27141000 | N62: Bitumen and asphalt, natural; bituminous or oil shale and tar sands; asphaltites and asphaltic rocks. | O62: Bituminous or oil shale and tar sands
C63: Pinnipedia) | L63: 27149000 | N63: Bitumen and asphalt, natural; bituminous or oil shale and tar sands; asphaltites and asphaltic rocks. | O63: Other
A64: 10613 | C64: - - Camels and other camelids (Camelidae) | E64: 3 | L64: 27150000 | N64: Bituminous mixtures based on natural asphalt, on natural bitumen, on petroleum bitumen, on mineral tar or on mineral tar pitch (for example, bituminous mastics, cut-backs).
A65: 10614 | C65: - - Rabbits and hares | E65: 3 | L65: 27160000 | N65: Electrical energy. (optional heading) | O65: Electrical energy. (optional heading)
A66: 10619 | C66: - - Other | E66: 3
A67: 1062 | C67: - Reptiles (including snakes and turtles) | E67: 3
C68: - Birds:
C69: - - Birds of prey:
A70: 1063110 | C70: - - - Falcons | E70: 3
A71: 106319 | C71: - - - Other | E71: 3
A72: 10632 | C72: - - Psittaciformes (including parrots, parakeets, | E72: 3
C73: macaws and cockatoos)
A74: 10633 | C74: - - Ostriches; emus (Dromaius novaehollandiae) | E74: 3
A75: 10639 | C75: - - Other | E75: 3
C76: - Insects:
A77: 1064100 | C77: - - Bees | E77: 3
A78: 10649 | C78: - - Other | E78: 3
A79: 1069 | C79: - Other | E79: 3
A82: 201 | C82: Meat of bovine animals, fresh or chilled.
A84: 2011 | C84: - Carcasses and half- carcasses | D84: 3
A86: 2012 | C86: - Other cuts with bone in | D86: 3
A88: 2013 | C88: - Boneless | D88: 3
A90: 202 | C90: Meat of bovine animals, frozen.
A92: 2021 | C92: - Carcasses and half- carcasses | D92: 3
A94: 2022 | C94: - Other cuts with bone in | D94: 3
A96: 2023 | C96: - Boneless | D96: 3
A98: 203 | C98: Meat of swine, fresh, chilled or frozen.
C100: - Fresh or chilled:
A102: 2031100 | C102: - - Carcasses and half-carcasses | D102: 20
A104: 20312 | C104: - - Hams, shoulders and cuts thereof, with bone | D104: 20
C105: in
A106: 20319 | C106: - - Other | D106: 20
C108: - Frozen:
A110: 2032100 | C110: - - Carcasses and half-carcasses | D110: 20
A112: 20322 | C112: - - Hams, shoulders and cuts thereof, with bone | D112: 20
C113: in
A114: 20329 | C114: - - Other | D114: 20
A116: 204 | C116: Meat of sheep or goats, fresh, chilled or
C117: frozen.
...

Sheet Cover Page
F4: Kenya Energy Accounts
J9: Draft V 1.1 | M9: 45814
J11: Prepared For:
J24: Prepared By:
J35: Contact Person: Jackie Crafford j.crafford@primeafrica.net

Sheet Colour coding
B2: Data Cell Colour Codes within Water Accounts
B3: White | C3: Expected empty cells
B4: Green | C4: Official statistics from KNBS and other government departments
B5: Light Green | C5: Data estimates by KNBS based on official statistics
B6: Orange | C6: Data derived from Green and Light Green statistics
B7: Red | C7: Literature estimates
B9: Data Text Colour Codes within Water Accounts
B10: Black Text | C10: Calculations
B11: Blue Text | C11: Data entered from data input sources
B12: Red Text | C12: Work in progress

Sheet Conversions
B2: GWh | C2: 1 | D2: GWh | E2: 3.6 | F2: TJ
B3: Gasoline | C3: 1 | D3: MT | E3: 44.4 | F3: GJ
C4: 1 | D4: GJ | E4: =1/1000 -> 0.001 | F4: TJ
B5: 1 litre of Motor Gasoline Premium ≈ 0.00003256 TJ | C5: 1 | D5: Litre | E5: 3.2e-05 | F5: TJ
B6: AGO (Automotive Gas Oil or Light Diesel Oil) 1 MT of AGO ≈ 0.043 to 0.0455 TJ | C6: 1 | D6: MT | E6: 0.043 | F6: TJ
C7: 1 | D7: Lite | E7: 3.58e-05 | F7: TJ
B8: Jet fuel | C8: 1 | D8: MT | E8: 0.0431 | F8: TJ
C9: 1 | D9: Litre | E9: 3.5e-05 | F9: TJ
B10: Iluminating kerosene | C10: 1 | D10: MT | E10: 0.0438 | F10: TJ
B11: Iluminating kerosene ( kerosene ≈ 0.0000344 TJ) | C11: 1 | D11: Litre | E11: 3.44e-05 | F11: TJ
C12: 1 | D12: Litre | E12: 3.74e-05 | F12: TJ
B13: LPG (Liquefied Petroleum Gas) 1 MT ≈ 0.0461 to 0.0500 TJ | C13: 1 | D13: MT | E13: 0.0461 | F13: TJ
B14: LPG 13 kg of LPG ≈ 0.00065 TJ. | C14: 13 | D14: Kg | E14: 0.00065 | F14: TJ
B15: White spirit (1 Litre of White Spirit ≈ 0.000033 to 0.0000345 TJ | C15: 1 | D15: Litre | E15: 3.3e-05 | F15: TJ
B16: Motor spirit | C16: 1 | D16: Lite | E16: 3.42e-05 | F16: TJ
B17: Coal and coke | C17: 1 | D17: Kg | E17: 2.6e-05 | F17: TJ
B18: Avaition spirit | C18: 1 | D18: Litre | E18: 3.35e-05 | F18: TJ
B19: Volume in MT | C19: 1000 | D19: MT | E19: 4.184 | F19: TJ
B20: Charcoal 1 kg of charcoal ≈ 0.00003 TJ | C20: 1 | D20: kg | E20: 3e-05 | F20: TJ
B21: Firewood | C21: 1 | D21: Tonne | E21: 0.016 | F21: TJ
B22: Electricity 1 kWh=0.0000036 TJ | C22: 1 | D22: Kwh | E22: 3.6e-06 | F22: TJ
B23: 1 litre of Light Diesel Oil ≈ 0.0000358 TJ | C23: 1 | D23: l | E23: 3.58e-05 | F23: TJ

Sheet Kenya Monetary Energy Accou
Q1: red text | T1: additional rows added to SEEA
A2: Core Account 2: Monetary Supply and Use Table for Energy | T2: TJ, needs prices to be KSH, later
B4: MONETARY SUPPLY AND USE TABLE (UNIT: KSH ) | D4: Industries (by ISIC) | P4: Final consumption and other | T4: Taxes less subsidies on products | U4: Trade and transport margins | V4: TOTAL | W4: Residuals
D5: Agriculture Forestry & Fishery | E5: Mining & Quarrying | F5: Manufacturing | G5: Electricity, gas, steam & air conditioning supply | H5: Construction | I5: Transportation & Storage | J5: Accommodation and Food Service Activities | K5: Other Commercial Sectors | L5: Public Administration and Defense | M5: Undefined | N5: Total Industry | P5: Households | Q5: Accumulation/Stock | R5: Rest of the world | S5: Flows from/to the environment (and other economic sectors)
B6: Supply of energy products (unit: KSH)
B7: NATURAL AND OTHER INPUTS:
B8: Solar | N8: =SUM(D8:M8) -> 0 | S8: ='Table 9.13(a)'!E5*'Price Summary'!G11 -> 7.4600856e+09 | U8: =V49-SUM(N8:T8) -> 0 | V8: =SUM(N8:U8) -> 7.4600856e+09 | W8: =V8-V49 -> 0
B9: Wind | N9: =SUM(D9:M9) -> 0 | S9: ='Table 9.13(a)'!E6*'Price Summary'!G9 -> 2.615142e+10 | U9: =V50-SUM(N9:T9) -> 0 | V9: =SUM(N9:U9) -> 2.615142e+10 | W9: =V9-V50 -> 0
B10: Hydro | N10: =SUM(D10:M10) -> 0 | S10: ='Table 9.13(a)'!E7*'Price Summary'!G5 -> 1.227942e+10 | U10: =V51-SUM(N10:T10) -> 0 | V10: =SUM(N10:U10) -> 1.227942e+10 | W10: =V10-V51 -> 0
B11: Geo-Thermal | N11: =SUM(D11:M11) -> 0 | S11: ='Table 9.13(a)'!E8*'Price Summary'!G7 -> 5.5179978e+10 | U11: =V52-SUM(N11:T11) -> 0 | V11: =SUM(N11:U11) -> 5.5179978e+10 | W11: =V11-V52 -> 0
B12: Biofuel: Bagasse | D12: ='Table 9.13(a)'!E9*'Price Summary'!G15 -> 255454.55 | N12: =SUM(D12:M12) -> 255454.55 | U12: =V53-SUM(N12:T12) -> 0 | V12: =SUM(N12:U12) -> 255454.55 | W12: =V12-V53 -> 0
B13: Biofuel: Biomass Wood | N13: =SUM(D13:M13) -> 0 | S13: ='Table 9.13(a)'!E10*'Price Summary'!$J$27 -> 754606293750 | U13: 0 | V13: =SUM(N13:U13) -> 754606293750 | W13: =V13-V54 -> 133706250
B14: Sub-Total (All Inputs) | D14: =SUM(D8:D13) -> 255454.55 | E14: =SUM(E8:E13) -> 0 | F14: =SUM(F8:F13) -> 0 | G14: =SUM(G8:G13) -> 0 | H14: =SUM(H8:H13) -> 0 | I14: =SUM(I8:I13) -> 0 | J14: =SUM(J8:J13) -> 0 | K14: =SUM(K8:K13) -> 0 | ... M14: =SUM(M8:M13) -> 0 | P14: =SUM(P8:P13) -> 0 | R14: =SUM(R8:R13) -> 0 | S14: =SUM(S8:S13) -> 8.556772e+11 | U14: =SUM(U8:U13) -> 0 | V14: =SUM(V8:V13) -> 8.5567745e+11 | W14: =SUM(W8:W13) -> 133706250
B15: ='Table 9.13(a)'!A12 -> IMPORTS: | U15: =V56-SUM(N15:T15) -> 0 | V15: =SUM(N15:U15) -> 0 | W15: =V15-V56 -> 0
B16: Coal and Coke | N16: =SUM(D16:M16) -> 0 | R16: ='Table 9.13(a)'!D14*'Price Summary'!H19 -> 2.2921498e+10 | U16: =(V58+('Table 9.13(a)'!I14*'Price Summary'!J19))-SUM(N16:T16) -> 2.0211738e+10 | V16: =SUM(N16:U16) -> 4.3133236e+10 | W16: =V16-V58 -> -42494423
B17: Motor Spirit Premium | N17: =SUM(D17:M17) -> 0 | R17: ='Table 9.13(a)'!D15*'Price Summary'!H29 -> 2.8554392e+10 | U17: =V59-SUM(N17:T17) -> 2.5053325e+09 | V17: =SUM(N17:U17) -> 3.1059725e+10 | W17: =V17-V59 -> 0
B18: Aviation gasoline | N18: =SUM(D18:M18) -> 0 | R18: ='Table 9.13(a)'!D16*'Price Summary'!H21 -> 18692696 | U18: =V60-SUM(N18:T18) -> 2211304.1 | V18: =SUM(N18:U18) -> 20904000 | W18: =V18-V60 -> 0
B19: Jet fuel | N19: =SUM(D19:M19) -> 0 | R19: ='Table 9.13(a)'!D17*'Price Summary'!H23 -> 2.9437082e+10 | U19: =V61-SUM(N19:T19) -> 4.3528255e+10 | V19: =SUM(N19:U19) -> 7.2965337e+10 | W19: =V19-V61 -> 0
B20: Illuminating Kerosene | N20: =SUM(D20:M20) -> 0 | R20: ='Table 9.13(a)'!D18*'Price Summary'!H37 -> 23033227 | U20: =V62-SUM(N20:T20) -> 13659933 | V20: =SUM(N20:U20) -> 36693160 | W20: =V20-V62 -> 0
B21: White spirit and special boiling point industrial spirits | N21: =SUM(D21:M21) -> 0 | R21: ='Table 9.13(a)'!D19*'Price Summary'!H25 -> 1.376021e+08 | U21: =V63-SUM(N21:T21) -> 1.2037345e+08 | V21: =SUM(N21:U21) -> 2.5797555e+08 | W21: =V21-V63 -> 0
B22: Oil shale / oil sands | N22: =SUM(D22:M22) -> 0 | U22: =V64-SUM(N22:T22) -> 0 | V22: =SUM(N22:U22) -> 0 | W22: =V22-V64 -> 0
B23: Fuel oils n.e.c. | N23: =SUM(D23:M23) -> 0 | R23: ='Table 9.13(a)'!D22*'Price Summary'!H35 -> 6.2469631e+08 | U23: =V65-SUM(N23:T23) -> 5.8517761e+09 | V23: =SUM(N23:U23) -> 6.4764724e+09 | W23: =V23-V65 -> 0
B24: Lubricating Oils | N24: =SUM(D24:M24) -> 0 | R24: ='Table 9.13(a)'!D23*'Price Summary'!H53 -> 1.6364382e+09 | U24: =V66-SUM(N24:T24) -> 6.4791287e+08 | V24: =SUM(N24:U24) -> 2.2843511e+09 | W24: =V24-V66 -> 0
B25: Lubricating Greases | N25: =SUM(D25:M25) -> 0 | R25: ='Table 9.13(a)'!D24*'Price Summary'!H55 -> 6.2526851e+08 | U25: =V67-SUM(N25:T25) -> 4.7926423e+08 | V25: =SUM(N25:U25) -> 1.1045327e+09 | W25: =V25-V67 -> 0
B26: Liquified Petroleum Gas (L.P.G) | N26: =SUM(D26:M26) -> 0 | R26: ='Table 9.13(a)'!D25*'Price Summary'!H39 -> 9.2953851e+09 | U26: =V68-SUM(N26:T26) -> 1895.03 | V26: =SUM(N26:U26) -> 9.295387e+09 | W26: =V26-V68 -> 0
B27: Natural gas | N27: =SUM(D27:M27) -> 0 | U27: =V69-SUM(N27:T27) -> 0 | V27: =SUM(N27:U27) -> 0 | W27: =V27-V69 -> 0
B28: Oil: Light Diesel Oil | N28: =SUM(D28:M28) -> 0 | R28: ='Table 9.13(a)'!D20*'Price Summary'!H31 -> 1.1583804e+10 | U28: =(V70+('Table 9.13(a)'!I20*'Price Summary'!J31))-SUM(N28:T28) -> 3.8124307e+10 | V28: =SUM(N28:U28) -> 4.9708111e+10 | W28: =V28-V70 -> -249049.12
B29: Oil: Heavy Diesel Oil | N29: =SUM(D29:M29) -> 0 | R29: ='Table 9.13(a)'!D21*'Price Summary'!H33 -> 116075.42 | U29: =V71-SUM(N29:T29) -> 531452.28 | V29: =SUM(N29:U29) -> 647527.7 | W29: =V29-V71 -> 0
B30: Electricity | N30: =SUM(D30:M30) -> 0 | R30: ='Table 9.13(a)'!D13*'Price Summary'!J51 -> 1.6225927e+10 | V30: =SUM(N30:U30) -> 1.6225927e+10
B31: Sub-Total (All Imports) | D31: =SUM(D16:D30) -> 0 | E31: =SUM(E16:E30) -> 0 | F31: =SUM(F16:F30) -> 0 | G31: =SUM(G16:G30) -> 0 | H31: =SUM(H16:H30) -> 0 | I31: =SUM(I16:I30) -> 0 | J31: =SUM(J16:J30) -> 0 | K31: =SUM(K16:K30) -> 0 | ... M31: =SUM(M16:M30) -> 0 | N31: =SUM(D31:M31) -> 0 | P31: =SUM(P16:P30) -> 0 | R31: =SUM(R16:R30) -> 1.2108394e+11 | S31: =SUM(S24:S30) -> 0 | U31: =SUM(U16:U29) -> 1.1148536e+11 | V31: =SUM(V16:V30) -> 2.325693e+11 | W31: =SUM(W16:W30) -> -42743472
B32: ='Table 9.13(a)'!A27 -> ENERGY PRODUCTS: | V32: =SUM(N32:U32) -> 0
B33: Electricity plants (Kengen) | G33: ='Table 9.13(a)'!B28*(SUM($S$8:$S$11)/SUM('Table 9.13(a)'!$B$28:$B$31)) -> 6.8141974e+10 | N33: =SUM(D33:M33) -> 6.8141974e+10 | V33: =SUM(N33:U33) -> 6.8141974e+10
B34: Electricity plants (Independent Power Producers (IPPs)) | G34: ='Table 9.13(a)'!B29*(SUM($S$8:$S$11)/SUM('Table 9.13(a)'!$B$28:$B$31)) -> 3.1539607e+10 | N34: =SUM(D34:M34) -> 3.1539607e+10 | V34: =SUM(N34:U34) -> 3.1539607e+10 | W34: =W37 -> 3.4375655e+08
B35: Electricity plants (REREC) | G35: ='Table 9.13(a)'!B30*(SUM($S$8:$S$11)/SUM('Table 9.13(a)'!$B$28:$B$31)) -> 6.6026274e+08 | N35: =SUM(D35:M35) -> 6.6026274e+08 | V35: =SUM(N35:U35) -> 6.6026274e+08
B36: Electricity plants (Off-grid)) | G36: ='Table 9.13(a)'!B31*'Price Summary'!J65 -> 7.2850883e+08 | N36: =SUM(D36:M36) -> 7.2850883e+08 | V36: =SUM(N36:U36) -> 7.2850883e+08
B37: Sub-Total (All Electricity) | D37: =SUM(D30:D36) -> 0 | E37: =SUM(E30:E36) -> 0 | F37: =SUM(F30:F36) -> 0 | G37: =SUM(G30:G36) -> 1.0107035e+11 | H37: =SUM(H30:H36) -> 0 | I37: =SUM(I30:I36) -> 0 | J37: =SUM(J30:J36) -> 0 | K37: =SUM(K30:K36) -> 0 | ... M37: =SUM(M30:M36) -> 0 | N37: =SUM(N32:N36,N30) -> 1.0107035e+11 | P37: =SUM(P30:P36) -> 0 | R37: =SUM(R32:R36,R30) -> 1.6225927e+10 | S37: =SUM(S30:S36) -> 0 | T37: =SUM(T30:T36) -> 0 | U37: =(V80+('Table 9.13(a)'!I29*(SUM($S$8:$S$11)/SUM('Table 9.13(a)'!$B$28:$B$31))))-SUM(N37:T37) -> 1.222512e+11 | V37: =SUM(N37:U37) -> 2.3954748e+11 | W37: =V37-V80 -> 3.4375655e+08
B38: BIOMASS PRODUCTS:
B39: Charcoal | D39: ='Table 9.13(a)'!B32*'Price Summary'!G17 -> 3.6023365e+08 | N39: =SUM(D39:M39) -> 3.6023365e+08 | P39: ='Table 9.13(a)'!C32*'Price Summary'!G17 -> 4.434663e+10 | U39: =V82-SUM(N39:T39) -> 2.3906665e+11 | V39: =SUM(N39:U39) -> 2.8377351e+11 | W39: =V39-V82 -> 0
B40: Firewood | D40: ='Table 9.13(a)'!B33*'Price Summary'!G27 -> 3.2239471e+09 | N40: =SUM(D40:M40) -> 3.2239471e+09 | P40: ='Table 9.13(a)'!C33*'Price Summary'!G27 -> 5.139979e+11 | U40: =V83-SUM(N40:T40) -> 155166553125 | V40: =SUM(N40:U40) -> 672388396875 | W40: =V40-V83 -> 0
B41: Sun-Total (All Biomass) | D41: =SUM(D39:D40) -> 3.5841808e+09 | E41: =SUM(E39:E40) -> 0 | F41: =SUM(F39:F40) -> 0 | G41: =SUM(G39:G40) -> 0 | H41: =SUM(H39:H40) -> 0 | I41: =SUM(I39:I40) -> 0 | J41: =SUM(J39:J40) -> 0 | K41: =SUM(K39:K40) -> 0 | ... N41: =SUM(N39:N40) -> 3.5841808e+09 | P41: =SUM(P39:P40) -> 5.5834453e+11 | R41: =SUM(R39:R40) -> 0 | U41: =SUM(U39:U40) -> 3.942332e+11 | V41: =SUM(V39:V40) -> 9.5616191e+11 | W41: =SUM(W39:W40) -> 0
B42: Residuals: | N42: =SUM(D42:M42) -> 0
B43: Other | N43: =SUM(D43:M43) -> 0 | U43: =V90-SUM(N43:T43) -> 0 | V43: =SUM(N43:U43) -> 0 | W43: =V43-V90 -> 0
B44: Total supply: | D44: =D43+D41+D37+D31+D14 -> 3.5844362e+09 | E44: =E43+E41+E37+E31+E14 -> 0 | F44: =F43+F41+F37+F31+F14 -> 0 | G44: =G43+G41+G37+G31+G14 -> 1.0107035e+11 | H44: =H43+H41+H37+H31+H14 -> 0 | I44: =I43+I41+I37+I31+I14 -> 0 | J44: =J43+J41+J37+J31+J14 -> 0 | K44: =K43+K41+K37+K31+K14 -> 0 | ... W44: =W43+W41+W37+W31+W14 -> 4.3471933e+08
B46: Use of energy products (unit: KSH)
B47: Intermediate consumption and final use (unit: KSH)
B48: ='Kenya Monetary Energy Accou'!B7 -> NATURAL AND OTHER INPUTS:
B49: Solar | D49: ='Table 9.13 (b)'!C5*'Price Summary'!D11 -> 0 | E49: ='Table 9.13 (b)'!D5*'Price Summary'!E11 -> 0 | G49: ='Table 9.13 (b)'!F5*'Price Summary'!G11 -> 7.4600856e+09 | H49: ='Table 9.13 (b)'!G5*'Price Summary'!H11 -> 0 | I49: ='Table 9.13 (b)'!H5*'Price Summary'!I11 -> 0 | J49: ='Table 9.13 (b)'!I5*'Price Summary'!J11 -> 0 | K49: ='Table 9.13 (b)'!J5*'Price Summary'!K11 -> 0 | L49: ='Table 9.13 (b)'!K5*'Price Summary'!L11 -> 0 | M49: ='Table 9.13 (b)'!L5*'Price Summary'!M11 -> 0 | N49: =SUM(D49:M49) -> 7.4600856e+09 | P49: ='Table 9.13 (b)'!M5*'Price.Data.Inputs'!$F$103 -> 0 | Q49: ='Table 9.13 (b)'!N5*'Price.Data.Inputs'!$F$103 -> 0 | R49: ='Table 9.13 (b)'!O5*'Price.Data.Inputs'!$F$103 -> 0 | S49: ='Table 9.13 (b)'!P5*'Price.Data.Inputs'!$F$103 -> 0 | V49: =SUM(N49:T49) -> 7.4600856e+09
B50: Wind | D50: ='Table 9.13 (b)'!C6*'Price Summary'!$G$9 -> 0 | E50: ='Table 9.13 (b)'!D6*'Price Summary'!$G$9 -> 0 | F50: ='Table 9.13 (b)'!E6*'Price Summary'!$G$9 -> 0 | G50: ='Table 9.13 (b)'!F6*'Price Summary'!$G$9 -> 2.615142e+10 | H50: ='Table 9.13 (b)'!G6*'Price Summary'!$G$9 -> 0 | I50: ='Table 9.13 (b)'!H6*'Price Summary'!$G$9 -> 0 | J50: ='Table 9.13 (b)'!I6*'Price Summary'!$G$9 -> 0 | K50: ='Table 9.13 (b)'!J6*'Price Summary'!$G$9 -> 0 | ... M50: ='Table 9.13 (b)'!L6*'Price Summary'!$G$9 -> 0 | N50: =SUM(D50:M50) -> 2.615142e+10 | P50: ='Table 9.13 (b)'!M6*'Price.Data.Inputs'!$F$101 -> 0 | Q50: ='Table 9.13 (b)'!N6*'Price.Data.Inputs'!$F$101 -> 0 | R50: ='Table 9.13 (b)'!O6*'Price.Data.Inputs'!$F$101 -> 0 | S50: ='Table 9.13 (b)'!P6*'Price.Data.Inputs'!$F$101 -> 0 | V50: =SUM(N50:T50) -> 2.615142e+10
B51: Hydro | D51: ='Table 9.13 (b)'!C7*'Price Summary'!$G$5 -> 0 | E51: ='Table 9.13 (b)'!D7*'Price Summary'!$G$5 -> 0 | F51: ='Table 9.13 (b)'!E7*'Price Summary'!$G$5 -> 0 | G51: ='Table 9.13 (b)'!F7*'Price Summary'!$G$5 -> 1.227942e+10 | H51: ='Table 9.13 (b)'!G7*'Price Summary'!$G$5 -> 0 | I51: ='Table 9.13 (b)'!H7*'Price Summary'!$G$5 -> 0 | J51: ='Table 9.13 (b)'!I7*'Price Summary'!$G$5 -> 0 | K51: ='Table 9.13 (b)'!J7*'Price Summary'!$G$5 -> 0 | ... M51: ='Table 9.13 (b)'!L7*'Price Summary'!$G$5 -> 0 | N51: =SUM(D51:M51) -> 1.227942e+10 | P51: ='Table 9.13 (b)'!M7*'Price.Data.Inputs'!$F$97 -> 0 | Q51: ='Table 9.13 (b)'!N7*'Price.Data.Inputs'!$F$97 -> 0 | R51: ='Table 9.13 (b)'!O7*'Price.Data.Inputs'!$F$97 -> 0 | S51: ='Table 9.13 (b)'!P7*'Price.Data.Inputs'!$F$97 -> 0 | V51: =SUM(N51:T51) -> 1.227942e+10
B52: Geo-Thermal | D52: ='Table 9.13 (b)'!C8*'Price Summary'!$G$7 -> 0 | E52: ='Table 9.13 (b)'!D8*'Price Summary'!$G$7 -> 0 | F52: ='Table 9.13 (b)'!E8*'Price Summary'!$G$7 -> 0 | G52: ='Table 9.13 (b)'!F8*'Price Summary'!$G$7 -> 5.5179978e+10 | H52: ='Table 9.13 (b)'!G8*'Price Summary'!$G$7 -> 0 | I52: ='Table 9.13 (b)'!H8*'Price Summary'!$G$7 -> 0 | J52: ='Table 9.13 (b)'!I8*'Price Summary'!$G$7 -> 0 | K52: ='Table 9.13 (b)'!J8*'Price Summary'!$G$7 -> 0 | ... M52: ='Table 9.13 (b)'!L8*'Price Summary'!$G$7 -> 0 | N52: =SUM(D52:M52) -> 5.5179978e+10 | P52: ='Table 9.13 (b)'!M8*'Price.Data.Inputs'!$F$99 -> 0 | Q52: ='Table 9.13 (b)'!N8*'Price.Data.Inputs'!$F$99 -> 0 | R52: ='Table 9.13 (b)'!O8*'Price.Data.Inputs'!$F$99 -> 0 | S52: ='Table 9.13 (b)'!P8*'Price.Data.Inputs'!$F$99 -> 0 | V52: =SUM(N52:T52) -> 5.5179978e+10
B53: Co-Generation | D53: ='Table 9.13 (b)'!C9*'Price Summary'!$G$13 -> 0 | E53: ='Table 9.13 (b)'!D9*'Price Summary'!$G$13 -> 0 | F53: ='Table 9.13 (b)'!E9*'Price Summary'!$G$13 -> 0 | G53: ='Table 9.13 (b)'!F9*'Price Summary'!$G$13 -> 255454.55 | H53: ='Table 9.13 (b)'!G9*'Price Summary'!$G$13 -> 0 | I53: ='Table 9.13 (b)'!H9*'Price Summary'!$G$13 -> 0 | J53: ='Table 9.13 (b)'!I9*'Price Summary'!$G$13 -> 0 | K53: ='Table 9.13 (b)'!J9*'Price Summary'!$G$13 -> 0 | ... M53: ='Table 9.13 (b)'!L9*'Price Summary'!$G$13 -> 0 | N53: =SUM(D53:M53) -> 255454.55 | P53: ='Table 9.13 (b)'!M9*'Price.Data.Inputs'!$F$106 -> 0 | Q53: ='Table 9.13 (b)'!N9*'Price.Data.Inputs'!$F$106 -> 0 | R53: ='Table 9.13 (b)'!O9*'Price.Data.Inputs'!$F$106 -> 0 | S53: ='Table 9.13 (b)'!P9*'Price.Data.Inputs'!$F$106 -> 0 | V53: =SUM(N53:T53) -> 255454.55
B54: Biomass Wood | D54: ='Table 9.13 (b)'!C10*'Price Summary'!$J$27 -> 0 | E54: ='Table 9.13 (b)'!D10*'Price Summary'!$J$27 -> 0 | F54: ='Table 9.13 (b)'!E10*'Price Summary'!$J$27 -> 4659412500 | G54: ='Table 9.13 (b)'!F10*'Price Summary'!$J$27 -> 0 | H54: ='Table 9.13 (b)'!G10*'Price Summary'!$J$27 -> 0 | I54: ='Table 9.13 (b)'!H10*'Price Summary'!$J$27 -> 0 | J54: ='Table 9.13 (b)'!I10*'Price Summary'!$J$27 -> 0 | K54: ='Table 9.13 (b)'!J10*'Price Summary'!$J$27 -> 0 | ... M54: ='Table 9.13 (b)'!L10*'Price Summary'!$J$27 -> 0 | N54: =SUM(D54:M54) -> 4659412500 | P54: ='Table 9.13 (b)'!M10*'Price Summary'!$J$27 -> 749813175000 | Q54: ='Table 9.13 (b)'!N10*'Price Summary'!$J$27 -> 0 | R54: ='Table 9.13 (b)'!O10*'Price Summary'!$J$27 -> 0 | S54: ='Table 9.13 (b)'!P10*'Price Summary'!$J$27 -> 0 | V54: =SUM(N54:T54) -> 754472587500
B55: Sub-Total (All Inputs) | D55: =SUM(D49:D54) -> 0 | E55: =SUM(E49:E54) -> 0 | F55: =SUM(F49:F54) -> 4659412500 | G55: =SUM(G49:G54) -> 1.0107116e+11 | H55: =SUM(H49:H54) -> 0 | I55: =SUM(I49:I54) -> 0 | J55: =SUM(J49:J54) -> 0 | K55: =SUM(K49:K54) -> 0 | ... S55: =SUM(S49:S54) -> 0 | V55: =SUM(V49:V54) -> 8.5554375e+11
B56: =B32 -> ENERGY PRODUCTS: | N56: =SUM(D56:M56) -> 0 | V56: =SUM(N56:T56) -> 0
B57: ='Table 9.13 (b)'!A12 -> Petroleum: | N57: =SUM(D57:M57) -> 0 | V57: =SUM(N57:T57) -> 0
B58: Coal and Coke | D58: ='Table 9.13 (b)'!C24*'Price.Data.Inputs'!$G$192 -> 0 | E58: ='Table 9.13 (b)'!D24*'Price.Data.Inputs'!$G$192 -> 0 | F58: ='Table 9.13 (b)'!E24*'Price Summary'!J19 -> 2.6802804e+10 | G58: ='Table 9.13 (b)'!F24*'Price.Data.Inputs'!$G$192 -> 0 | H58: ='Table 9.13 (b)'!G24*'Price.Data.Inputs'!$G$192 -> 0 | I58: ='Table 9.13 (b)'!H24*'Price.Data.Inputs'!$G$192 -> 0 | J58: ='Table 9.13 (b)'!I24*'Price.Data.Inputs'!$G$192 -> 0 | K58: ='Table 9.13 (b)'!J24*'Price.Data.Inputs'!$G$192 -> 0 | L58: ='Table 9.13 (b)'!K24*'Price.Data.Inputs'!$G$192 -> 0 | M58: ='Table 9.13 (b)'!L24*'Price Summary'!J19 -> 1.6329966e+10 | N58: =SUM(D58:M58) -> 4.3132771e+10 | P58: ='Table 9.13 (b)'!M24*'Price Summary'!$J$19 -> 0 | Q58: ='Table 9.13 (b)'!N24*'Price Summary'!$J$19 -> 0 | R58: ='Table 9.13 (b)'!O24*'Price Summary'!$J$19 -> 42960115 | S58: ='Table 9.13 (b)'!P24*'Price Summary'!$J$19 -> 0 | V58: =SUM(N58:T58) -> 4.3175731e+10
B59: Motor Spirit Premium | D59: ='Table 9.13 (b)'!C13*'Price Summary'!$J$29 -> 30669986 | E59: ='Table 9.13 (b)'!D13*'Price Summary'!$J$29 -> 2.7490849e+08 | F59: ='Table 9.13 (b)'!E13*'Price Summary'!$J$29 -> 4.6851628e+08 | G59: ='Table 9.13 (b)'!F13*'Price Summary'!$J$29 -> 5719083.3 | H59: ='Table 9.13 (b)'!G13*'Price Summary'!$J$29 -> 2.2842692e+08 | I59: ='Table 9.13 (b)'!H13*'Price Summary'!$J$29 -> 2.3006302e+10 | J59: ='Table 9.13 (b)'!I13*'Price Summary'!$J$29 -> 2186708.3 | K59: ='Table 9.13 (b)'!J13*'Price Summary'!$J$29 -> 1.093085e+10 | ... M59: ='Table 9.13 (b)'!L13*'Price Summary'!$J$29 -> 0 | N59: =SUM(D59:M59) -> 3.5016041e+10 | P59: ='Table 9.13 (b)'!M13*'Price Summary'!$J$29 -> 0 | Q59: ='Table 9.13 (b)'!N13*'Price Summary'!$J$29 -> -3.9762768e+09 | R59: ='Table 9.13 (b)'!O13*'Price Summary'!$J$29 -> 19960722 | S59: ='Table 9.13 (b)'!P13*'Price Summary'!$J$29 -> 0 | V59: =SUM(N59:T59) -> 3.1059725e+10
B60: Aviation gasoline | D60: ='Table 9.13 (b)'!C14*'Price Summary'!$J$21 -> 0 | E60: ='Table 9.13 (b)'!D14*'Price Summary'!$J$21 -> 0 | F60: ='Table 9.13 (b)'!E14*'Price Summary'!$J$21 -> 0 | G60: ='Table 9.13 (b)'!F14*'Price Summary'!$J$21 -> 0 | H60: ='Table 9.13 (b)'!G14*'Price Summary'!$J$21 -> 0 | I60: ='Table 9.13 (b)'!H14*'Price Summary'!$J$21 -> 34652400 | J60: ='Table 9.13 (b)'!I14*'Price Summary'!$J$21 -> 0 | K60: ='Table 9.13 (b)'!J14*'Price Summary'!$J$21 -> 0 | ... M60: ='Table 9.13 (b)'!L14*'Price Summary'!$J$21 -> 0 | N60: =SUM(D60:M60) -> 36381000 | P60: ='Table 9.13 (b)'!M14*'Price Summary'!$J$21 -> 0 | Q60: ='Table 9.13 (b)'!N14*'Price Summary'!$J$21 -> -16482000 | R60: ='Table 9.13 (b)'!O14*'Price Summary'!$J$21 -> 1005000 | S60: ='Table 9.13 (b)'!P14*'Price Summary'!$J$21 -> 0 | V60: =SUM(N60:T60) -> 20904000
B61: Jet fuel | D61: ='Table 9.13 (b)'!C15*'Price Summary'!$J$23 -> 0 | E61: ='Table 9.13 (b)'!D15*'Price Summary'!$J$23 -> 0 | F61: ='Table 9.13 (b)'!E15*'Price Summary'!$J$23 -> 0 | G61: ='Table 9.13 (b)'!F15*'Price Summary'!$J$23 -> 0 | H61: ='Table 9.13 (b)'!G15*'Price Summary'!$J$23 -> 0 | I61: ='Table 9.13 (b)'!H15*'Price Summary'!$J$23 -> 7.0643133e+10 | J61: ='Table 9.13 (b)'!I15*'Price Summary'!$J$23 -> 0 | K61: ='Table 9.13 (b)'!J15*'Price Summary'!$J$23 -> 0 | ... M61: ='Table 9.13 (b)'!L15*'Price Summary'!$J$23 -> 0 | N61: =SUM(D61:M61) -> 7.1125279e+10 | P61: ='Table 9.13 (b)'!M15*'Price Summary'!$J$23 -> 0 | Q61: ='Table 9.13 (b)'!N15*'Price Summary'!$J$23 -> -8.690804e+10 | R61: ='Table 9.13 (b)'!O15*'Price Summary'!$J$23 -> 8.8748098e+10 | S61: ='Table 9.13 (b)'!P15*'Price Summary'!$J$23 -> 0 | V61: =SUM(N61:T61) -> 7.2965337e+10
B62: Illuminating Kerosene | D62: ='Table 9.13 (b)'!C16*'Price Summary'!$J$37 -> 45022.282 | E62: ='Table 9.13 (b)'!D16*'Price Summary'!$J$37 -> 6708320 | F62: ='Table 9.13 (b)'!E16*'Price Summary'!$J$37 -> 3.4518583e+08 | G62: ='Table 9.13 (b)'!F16*'Price Summary'!$J$37 -> 0 | H62: ='Table 9.13 (b)'!G16*'Price Summary'!$J$37 -> 6573253.1 | I62: ='Table 9.13 (b)'!H16*'Price Summary'!$J$37 -> 495245.1 | J62: ='Table 9.13 (b)'!I16*'Price Summary'!$J$37 -> 0 | K62: ='Table 9.13 (b)'!J16*'Price Summary'!$J$37 -> 2.4203979e+08 | ... M62: ='Table 9.13 (b)'!L16*'Price Summary'!$J$37 -> 0 | N62: =SUM(D62:M62) -> 6.0104746e+08 | P62: ='Table 9.13 (b)'!M16*'Price Summary'!$J$37 -> 90899987 | Q62: ='Table 9.13 (b)'!N16*'Price Summary'!$J$37 -> -6.5525429e+08 | R62: ='Table 9.13 (b)'!O16*'Price Summary'!$J$37 -> 0 | S62: ='Table 9.13 (b)'!P16*'Price Summary'!$J$37 -> 0 | V62: =SUM(N62:T62) -> 36693160
B63: White spirit and special boiling point industrial spirits | D63: ='Table 9.13 (b)'!C17*'Price Summary'!$J$25 -> 0 | E63: ='Table 9.13 (b)'!D17*'Price Summary'!$J$25 -> 0 | F63: ='Table 9.13 (b)'!E17*'Price Summary'!$J$25 -> 0 | G63: ='Table 9.13 (b)'!F17*'Price Summary'!$J$25 -> 0 | H63: ='Table 9.13 (b)'!G17*'Price Summary'!$J$25 -> 0 | I63: ='Table 9.13 (b)'!H17*'Price Summary'!$J$25 -> 0 | J63: ='Table 9.13 (b)'!I17*'Price Summary'!$J$25 -> 0 | K63: ='Table 9.13 (b)'!J17*'Price Summary'!$J$25 -> 0 | ... M63: ='Table 9.13 (b)'!L17*'Price Summary'!$J$25 -> 0 | N63: =SUM(D63:M63) -> 0 | P63: ='Table 9.13 (b)'!M17*'Price Summary'!$J$25 -> 0 | Q63: ='Table 9.13 (b)'!N17*'Price Summary'!$J$25 -> 2.5387478e+08 | R63: ='Table 9.13 (b)'!O17*'Price Summary'!$J$25 -> 4100767.4 | S63: ='Table 9.13 (b)'!P17*'Price Summary'!$J$25 -> 0 | V63: =SUM(N63:T63) -> 2.5797555e+08
B64: Oil shale / oil sands | N64: =SUM(D64:M64) -> 0 | V64: =SUM(N64:T64) -> 0
B65: Fuel oils n.e.c. | D65: ='Table 9.13 (b)'!C20*'Price Summary'!$J$31 -> 9214817.3 | E65: ='Table 9.13 (b)'!D20*'Price Summary'!$J$31 -> 2.0910164e+08 | F65: ='Table 9.13 (b)'!E20*'Price Summary'!$J$31 -> 3.9025996e+08 | G65: ='Table 9.13 (b)'!F20*'Price Summary'!$J$31 -> 1.2557056e+09 | H65: ='Table 9.13 (b)'!G20*'Price Summary'!$J$31 -> 23360807 | I65: ='Table 9.13 (b)'!H20*'Price Summary'!$J$31 -> 4.2821007e+09 | J65: ='Table 9.13 (b)'!I20*'Price Summary'!$J$31 -> 0 | K65: ='Table 9.13 (b)'!J20*'Price Summary'!$J$31 -> 2.7385441e+08 | ... M65: ='Table 9.13 (b)'!L20*'Price Summary'!$J$31 -> 0 | N65: =SUM(D65:M65) -> 6.443598e+09 | P65: ='Table 9.13 (b)'!M20*'Price Summary'!$J$31 -> 0 | Q65: ='Table 9.13 (b)'!N20*'Price Summary'!$J$31 -> -3.7516759e+08 | R65: ='Table 9.13 (b)'!O20*'Price Summary'!$J$31 -> 4.0804207e+08 | S65: ='Table 9.13 (b)'!P20*'Price Summary'!$J$31 -> 0 | V65: =SUM(N65:T65) -> 6.4764724e+09
B66: Lubricating Oils | D66: ='Table 9.13 (b)'!C21*'Table 9.1'!$Q$16 -> 0 | E66: ='Table 9.13 (b)'!D21*'Table 9.1'!$Q$16 -> 0 | F66: ='Table 9.13 (b)'!E21*'Table 9.1'!$Q$16 -> 0 | G66: ='Table 9.13 (b)'!F21*'Table 9.1'!$Q$16 -> 0 | H66: ='Table 9.13 (b)'!G21*'Price Summary'!$J$53 -> 0 | I66: ='Table 9.13 (b)'!H21*'Price Summary'!$J$53 -> 0 | J66: ='Table 9.13 (b)'!I21*'Price Summary'!$J$53 -> 0 | K66: ='Table 9.13 (b)'!J21*'Price Summary'!$J$53 -> 0 | L66: ='Table 9.13 (b)'!K21*'Price Summary'!$J$53 -> 0 | M66: ='Table 9.13 (b)'!L21*'Price Summary'!$J$53 -> 0 | N66: =SUM(D66:M66) -> 0 | P66: ='Table 9.13 (b)'!M21*'Price Summary'!$J$53 -> 0 | Q66: ='Table 9.13 (b)'!N21*'Price Summary'!$J$53 -> -1.3927838e+10 | R66: ='Table 9.13 (b)'!O21*'Price Summary'!$J$53 -> 1.6212189e+10 | S66: ='Table 9.13 (b)'!P21*'Price Summary'!$J$53 -> 0 | V66: =SUM(N66:T66) -> 2.2843511e+09
B67: Lubricating Greases | D67: ='Table 9.13 (b)'!C22*'Table 9.1'!$Q$16 -> 0 | E67: ='Table 9.13 (b)'!D22*'Table 9.1'!$Q$16 -> 0 | F67: ='Table 9.13 (b)'!E22*'Table 9.1'!$Q$16 -> 0 | G67: ='Table 9.13 (b)'!F22*'Table 9.1'!$Q$16 -> 0 | H67: ='Table 9.13 (b)'!G22*'Price Summary'!$J$53 -> 0 | I67: ='Table 9.13 (b)'!H22*'Price Summary'!$J$53 -> 0 | J67: ='Table 9.13 (b)'!I22*'Price Summary'!$J$53 -> 0 | K67: ='Table 9.13 (b)'!J22*'Price Summary'!$J$53 -> 0 | L67: ='Table 9.13 (b)'!K22*'Price Summary'!$J$53 -> 0 | M67: ='Table 9.13 (b)'!L22*'Price Summary'!$J$53 -> 0 | N67: =SUM(D67:M67) -> 0 | P67: ='Table 9.13 (b)'!M22*'Price Summary'!$J$53 -> 0 | Q67: ='Table 9.13 (b)'!N22*'Price Summary'!$J$53 -> 1.0591551e+09 | R67: ='Table 9.13 (b)'!O22*'Price Summary'!$J$53 -> 45377629 | S67: ='Table 9.13 (b)'!P22*'Price Summary'!$J$53 -> 0 | V67: =SUM(N67:T67) -> 1.1045327e+09
B68: Liquified Petroleum Gas (L.P.G) | D68: ='Table 9.13 (b)'!C23*'Price Summary'!$J$39 -> 0 | E68: ='Table 9.13 (b)'!D23*'Price Summary'!$J$39 -> 26683960 | F68: ='Table 9.13 (b)'!E23*'Price Summary'!$J$39 -> 1.0444514e+09 | G68: ='Table 9.13 (b)'!F23*'Price Summary'!$J$39 -> 0 | H68: ='Table 9.13 (b)'!G23*'Price Summary'!$J$39 -> 4512728.6 | I68: ='Table 9.13 (b)'!H23*'Price Summary'!$J$39 -> 27812142 | J68: ='Table 9.13 (b)'!I23*'Price Summary'!$J$39 -> 74656227 | K68: ='Table 9.13 (b)'!J23*'Price Summary'!$J$39 -> 5.1036507e+09 | ... M68: ='Table 9.13 (b)'!L23*'Price Summary'!$J$39 -> 0 | N68: =SUM(D68:M68) -> 6.2817672e+09 | P68: ='Table 9.13 (b)'!M23*'Price Summary'!$J$39 -> 2.2324272e+09 | Q68: ='Table 9.13 (b)'!N23*'Price Summary'!$J$39 -> 7.5436144e+08 | R68: ='Table 9.13 (b)'!O23*'Price Summary'!$J$39 -> 26831114 | S68: ='Table 9.13 (b)'!P23*'Price Summary'!$J$39 -> 0 | V68: =SUM(N68:T68) -> 9.295387e+09
B69: Natural gas | N69: =SUM(D69:M69) -> 0 | V69: =SUM(N69:T69) -> 0
B70: Oil: Light Diesel Oil | D70: ='Table 9.13 (b)'!C18*'Price Summary'!$J$31 -> 4.2298502e+08 | E70: ='Table 9.13 (b)'!D18*'Price Summary'!$J$31 -> 1.5182034e+09 | F70: ='Table 9.13 (b)'!E18*'Price Summary'!$J$31 -> 4.4051808e+09 | G70: ='Table 9.13 (b)'!F18*'Price Summary'!$J$31 -> 2.6294606e+08 | H70: ='Table 9.13 (b)'!G18*'Price Summary'!$J$31 -> 2.8057873e+09 | I70: ='Table 9.13 (b)'!H18*'Price Summary'!$J$31 -> 1.7581871e+10 | J70: ='Table 9.13 (b)'!I18*'Price Summary'!$J$31 -> 9214817.3 | K70: ='Table 9.13 (b)'!J18*'Price Summary'!$J$31 -> 1.8757234e+10 | ... M70: ='Table 9.13 (b)'!L18*'Price Summary'!$J$31 -> 0 | N70: =SUM(D70:M70) -> 4.6023231e+10 | P70: ='Table 9.13 (b)'!M18*'Price Summary'!$J$31 -> 0 | Q70: ='Table 9.13 (b)'!N18*'Price Summary'!$J$31 -> 3.3075217e+09 | R70: ='Table 9.13 (b)'!O18*'Price Summary'!$J$31 -> 3.7760827e+08 | S70: ='Table 9.13 (b)'!P18*'Price Summary'!$J$31 -> 0 | V70: =SUM(N70:T70) -> 4.970836e+10
B71: Oil: Heavy Diesel Oil | D71: ='Table 9.13 (b)'!C19*'Price Summary'!$J$33 -> 0 | E71: ='Table 9.13 (b)'!D19*'Price Summary'!$J$33 -> 0 | F71: ='Table 9.13 (b)'!E19*'Price Summary'!$J$33 -> 0 | G71: ='Table 9.13 (b)'!F19*'Price Summary'!$J$33 -> 0 | H71: ='Table 9.13 (b)'!G19*'Price Summary'!$J$33 -> 0 | I71: ='Table 9.13 (b)'!H19*'Price Summary'!$J$33 -> 0 | J71: ='Table 9.13 (b)'!I19*'Price Summary'!$J$33 -> 0 | K71: ='Table 9.13 (b)'!J19*'Price Summary'!$J$33 -> 0 | ... M71: ='Table 9.13 (b)'!L19*'Price Summary'!$J$33 -> 0 | N71: =SUM(D71:M71) -> 0 | P71: ='Table 9.13 (b)'!M19*'Price Summary'!$J$33 -> 0 | Q71: ='Table 9.13 (b)'!N19*'Price Summary'!$J$33 -> 597717.88 | R71: ='Table 9.13 (b)'!O19*'Price Summary'!$J$33 -> 49809.823 | S71: ='Table 9.13 (b)'!P19*'Price Summary'!$J$33 -> 0 | V71: =SUM(N71:T71) -> 647527.7
B72: Sub-Total (All Petroleum) | D72: =SUM(D58:D71) -> 4.6291484e+08 | E72: =SUM(E58:E71) -> 2.0356058e+09 | F72: =SUM(F58:F71) -> 3.3456399e+10 | G72: =SUM(G58:G71) -> 1.5243708e+09 | H72: =SUM(H58:H71) -> 3.068661e+09 | I72: =SUM(I58:I71) -> 1.1557637e+11 | J72: =SUM(J58:J71) -> 86057753 | K72: =SUM(K58:K71) -> 3.5307629e+10 | ... S72: =SUM(S58:S71) -> 0 | V72: =SUM(V58:V71) -> 2.1638612e+11
B73: ='Table 9.13 (b)'!A25 -> Electricity | N73: =SUM(D73:M73) -> 0 | V73: =SUM(N73:T73) -> 0
B74: Domestic and Small Commercial | D74: ='Table 9.13 (b)'!C26*'Price Summary'!$J$41 -> 0 | E74: ='Table 9.13 (b)'!D26*'Price Summary'!$J$41 -> 0 | F74: ='Table 9.13 (b)'!E26*'Price Summary'!$J$41 -> 0 | G74: ='Table 9.13 (b)'!F26*'Price Summary'!$J$41 -> 0 | H74: ='Table 9.13 (b)'!G26*'Price Summary'!$J$41 -> 0 | I74: ='Table 9.13 (b)'!H26*'Price Summary'!$J$41 -> 0 | J74: ='Table 9.13 (b)'!I26*'Price Summary'!$J$41 -> 0 | K74: ='Table 9.13 (b)'!J26*'Price Summary'!$J$41 -> 0 | ... M74: ='Table 9.13 (b)'!L26*'Price Summary'!$J$41 -> 3.9597495e+10 | N74: =SUM(D74:M74) -> 3.9597495e+10 | P74: ='Table 9.13 (b)'!M26*'Price Summary'!$J$41 -> 7.1746232e+10 | Q74: ='Table 9.13 (b)'!N26*'Price Summary'!$J$41 -> 0 | R74: ='Table 9.13 (b)'!O26*'Price Summary'!$J$41 -> 0 | S74: ='Table 9.13 (b)'!P26*'Price Summary'!$J$41 -> 0 | V74: =SUM(N74:T74) -> 1.1134373e+11
B75: Large and Medium | D75: ='Table 9.13 (b)'!C27*'Price Summary'!$J$45 -> 0 | E75: ='Table 9.13 (b)'!D27*'Price Summary'!$J$45 -> 0 | F75: ='Table 9.13 (b)'!E27*'Price Summary'!$J$45 -> 0 | G75: ='Table 9.13 (b)'!F27*'Price Summary'!$J$45 -> 0 | H75: ='Table 9.13 (b)'!G27*'Price Summary'!$J$45 -> 0 | I75: ='Table 9.13 (b)'!H27*'Price Summary'!$J$45 -> 0 | J75: ='Table 9.13 (b)'!I27*'Price Summary'!$J$45 -> 0 | K75: ='Table 9.13 (b)'!J27*'Price Summary'!$J$45 -> 0 | ... M75: ='Table 9.13 (b)'!L27*'Price Summary'!$J$45 -> 1.1984439e+11 | N75: =SUM(D75:M75) -> 1.1984439e+11 | P75: ='Table 9.13 (b)'!M27*'Price Summary'!$J$45 -> 0 | Q75: ='Table 9.13 (b)'!N27*'Price Summary'!$J$45 -> 0 | R75: ='Table 9.13 (b)'!O27*'Price Summary'!$J$45 -> 0 | S75: ='Table 9.13 (b)'!P27*'Price Summary'!$J$45 -> 0 | V75: =SUM(N75:T75) -> 1.1984439e+11
B76: Street Lighting | D76: ='Table 9.13 (b)'!C28*'Price Summary'!$J$47 -> 0 | E76: ='Table 9.13 (b)'!D28*'Price Summary'!$J$47 -> 0 | F76: ='Table 9.13 (b)'!E28*'Price Summary'!$J$47 -> 0 | G76: ='Table 9.13 (b)'!F28*'Price Summary'!$J$47 -> 0 | H76: ='Table 9.13 (b)'!G28*'Price Summary'!$J$47 -> 0 | I76: ='Table 9.13 (b)'!H28*'Price Summary'!$J$47 -> 0 | J76: ='Table 9.13 (b)'!I28*'Price Summary'!$J$47 -> 0 | K76: ='Table 9.13 (b)'!J28*'Price Summary'!$J$47 -> 0 | ... M76: ='Table 9.13 (b)'!L28*'Price Summary'!$J$47 -> 1.1608979e+09 | N76: =SUM(D76:M76) -> 1.1608979e+09 | P76: ='Table 9.13 (b)'!M28*'Price Summary'!$J$47 -> 0 | Q76: ='Table 9.13 (b)'!N28*'Price Summary'!$J$47 -> 0 | R76: ='Table 9.13 (b)'!O28*'Price Summary'!$J$47 -> 0 | S76: ='Table 9.13 (b)'!P28*'Price Summary'!$J$47 -> 0 | V76: =SUM(N76:T76) -> 1.1608979e+09
B77: E-mobility | D77: ='Table 9.13 (b)'!C29*'Price Summary'!$J$49 -> 0 | E77: ='Table 9.13 (b)'!D29*'Price Summary'!$J$49 -> 0 | F77: ='Table 9.13 (b)'!E29*'Price Summary'!$J$49 -> 0 | G77: ='Table 9.13 (b)'!F29*'Price Summary'!$J$49 -> 0 | H77: ='Table 9.13 (b)'!G29*'Price Summary'!$J$49 -> 0 | I77: ='Table 9.13 (b)'!H29*'Price Summary'!$J$49 -> 0 | J77: ='Table 9.13 (b)'!I29*'Price Summary'!$J$49 -> 0 | K77: ='Table 9.13 (b)'!J29*'Price Summary'!$J$49 -> 0 | ... M77: ='Table 9.13 (b)'!L29*'Price Summary'!$J$49 -> 54663750 | N77: =SUM(D77:M77) -> 54663750 | P77: ='Table 9.13 (b)'!M29*'Price Summary'!$J$49 -> 0 | Q77: ='Table 9.13 (b)'!N29*'Price Summary'!$J$49 -> 0 | R77: ='Table 9.13 (b)'!O29*'Price Summary'!$J$49 -> 0 | S77: ='Table 9.13 (b)'!P29*'Price Summary'!$J$49 -> 0 | V77: =SUM(N77:T77) -> 54663750
B78: Rural electrification | D78: ='Table 9.13 (b)'!C30*'Price Summary'!$J$57 -> 0 | E78: ='Table 9.13 (b)'!D30*'Price Summary'!$J$57 -> 0 | F78: ='Table 9.13 (b)'!E30*'Price Summary'!$J$57 -> 0 | G78: ='Table 9.13 (b)'!F30*'Price Summary'!$J$57 -> 0 | H78: ='Table 9.13 (b)'!G30*'Price Summary'!$J$57 -> 0 | I78: ='Table 9.13 (b)'!H30*'Price Summary'!$J$57 -> 0 | J78: ='Table 9.13 (b)'!I30*'Price Summary'!$J$57 -> 0 | K78: ='Table 9.13 (b)'!J30*'Price Summary'!$J$57 -> 0 | ... M78: ='Table 9.13 (b)'!L30*'Price Summary'!$J$57 -> 1.807446e+09 | N78: =SUM(D78:M78) -> 1.807446e+09 | P78: ='Table 9.13 (b)'!M30*'Price Summary'!$J$57 -> 4.1571136e+09 | Q78: ='Table 9.13 (b)'!N30*'Price Summary'!$J$57 -> 0 | R78: ='Table 9.13 (b)'!O30*'Price Summary'!$J$57 -> 0 | S78: ='Table 9.13 (b)'!P30*'Price Summary'!$J$57 -> 0 | V78: =SUM(N78:T78) -> 5.9645596e+09
B79: Other | N79: =SUM(D79:M79) -> 0 | R79: ='Table 9.13 (b)'!O31*'Price Summary'!L43 -> 8.354826e+08 | V79: =SUM(N79:T79) -> 8.354826e+08
B80: Sub-Total (All electricity) | D80: =SUM(D74:D79) -> 0 | E80: =SUM(E74:E79) -> 0 | F80: =SUM(F74:F79) -> 0 | G80: =SUM(G74:G79) -> 0 | H80: =SUM(H74:H79) -> 0 | I80: =SUM(I74:I79) -> 0 | J80: =SUM(J74:J79) -> 0 | K80: =SUM(K74:K79) -> 0 | ... S80: =SUM(S74:S79) -> 0 | V80: =SUM(V74:V79) -> 2.3920372e+11
B81: ='Table 9.13 (b)'!A32 -> Biomass: | N81: =SUM(D81:M81) -> 0 | V81: =SUM(N81:T81) -> 0
B82: Charcoal | D82: ='Table 9.13 (b)'!C34*'Price Summary'!$J$17 -> 0 | E82: ='Table 9.13 (b)'!D34*'Price Summary'!$J$17 -> 0 | F82: ='Table 9.13 (b)'!E34*'Price Summary'!$J$17 -> 2.2865565e+09 | G82: ='Table 9.13 (b)'!F34*'Price Summary'!$J$17 -> 0 | H82: ='Table 9.13 (b)'!G34*'Price Summary'!$J$17 -> 0 | I82: ='Table 9.13 (b)'!H34*'Price Summary'!$J$17 -> 0 | J82: ='Table 9.13 (b)'!I34*'Price Summary'!$J$17 -> 0 | K82: ='Table 9.13 (b)'!J34*'Price Summary'!$J$17 -> 0 | ... M82: ='Table 9.13 (b)'!L34*'Price Summary'!$J$17 -> 0 | N82: =SUM(D82:M82) -> 2.2865565e+09 | P82: ='Table 9.13 (b)'!M34*'Price Summary'!$J$17 -> 2.8148696e+11 | Q82: ='Table 9.13 (b)'!N34*'Price Summary'!$J$17 -> 0 | R82: ='Table 9.13 (b)'!O34*'Price Summary'!$J$17 -> 0 | S82: ='Table 9.13 (b)'!P34*'Price Summary'!$J$17 -> 0 | V82: =SUM(N82:T82) -> 2.8377351e+11
B83: Firewood | D83: ='Table 9.13 (b)'!C33*'Price Summary'!$J$27 -> 0 | E83: ='Table 9.13 (b)'!D33*'Price Summary'!$J$27 -> 0 | F83: ='Table 9.13 (b)'!E33*'Price Summary'!$J$27 -> 4191131250 | G83: ='Table 9.13 (b)'!F33*'Price Summary'!$J$27 -> 0 | H83: ='Table 9.13 (b)'!G33*'Price Summary'!$J$27 -> 0 | I83: ='Table 9.13 (b)'!H33*'Price Summary'!$J$27 -> 0 | J83: ='Table 9.13 (b)'!I33*'Price Summary'!$J$27 -> 0 | K83: ='Table 9.13 (b)'!J33*'Price Summary'!$J$27 -> 0 | ... M83: ='Table 9.13 (b)'!L33*'Price Summary'!$J$27 -> 0 | N83: =SUM(D83:M83) -> 4191131250 | P83: ='Table 9.13 (b)'!M33*'Price Summary'!$J$27 -> 668197265625 | Q83: ='Table 9.13 (b)'!N33*'Price Summary'!$J$27 -> 0 | R83: ='Table 9.13 (b)'!O33*'Price Summary'!$J$27 -> 0 | S83: ='Table 9.13 (b)'!P33*'Price Summary'!$J$27 -> 0 | V83: =SUM(N83:T83) -> 672388396875
B84: Sub-Total (all Biomass) | D84: =SUM(D82:D83) -> 0 | E84: =SUM(E82:E83) -> 0 | F84: =SUM(F82:F83) -> 6.4776877e+09 | G84: =SUM(G82:G83) -> 0 | H84: =SUM(H82:H83) -> 0 | I84: =SUM(I82:I83) -> 0 | J84: =SUM(J82:J83) -> 0 | K84: =SUM(K82:K83) -> 0 | ... S84: =SUM(S82:S83) -> 0 | V84: =SUM(V82:V83) -> 9.5616191e+11
B85: Residuals: | N85: =SUM(D85:M85) -> 0
B86: Extraction | D86: ='Table 9.13 (b)'!C38*'Price Summary'!$J$51 -> 0 | E86: ='Table 9.13 (b)'!D38*'Price Summary'!$J$51 -> 0 | F86: ='Table 9.13 (b)'!E38*'Price Summary'!$J$51 -> 0 | G86: ='Table 9.13 (b)'!F38*'Price Summary'!$J$51 -> 0 | H86: ='Table 9.13 (b)'!G38*'Price Summary'!$J$51 -> 0 | I86: ='Table 9.13 (b)'!H38*'Price Summary'!$J$51 -> 0 | J86: ='Table 9.13 (b)'!I38*'Price Summary'!$J$51 -> 0 | K86: ='Table 9.13 (b)'!J38*'Price Summary'!$J$51 -> 0 | ... M86: ='Table 9.13 (b)'!L38*'Price Summary'!$J$51 -> 0 | N86: =SUM(D86:M86) -> 0 | P86: ='Table 9.13 (b)'!M38*'Price.Data.Inputs'!$E$224 -> 0 | Q86: ='Table 9.13 (b)'!N38*'Price.Data.Inputs'!$E$224 -> 0 | R86: ='Table 9.13 (b)'!O38*'Price.Data.Inputs'!$E$224 -> 0 | V86: =SUM(N86:T86) -> 0
B87: Transformation | N87: =SUM(D87:M87) -> 0 | V87: =SUM(N87:T87) -> 0
B88: Losses | D88: ='Table 9.13 (b)'!C40*'Price Summary'!$J$51 -> 0 | E88: ='Table 9.13 (b)'!D40*'Price Summary'!$J$51 -> 0 | F88: ='Table 9.13 (b)'!E40*'Price Summary'!$J$51 -> 0 | G88: ='Table 9.13 (b)'!F40*'Price Summary'!$J$51 -> 0 | H88: ='Table 9.13 (b)'!G40*'Price Summary'!$J$51 -> 0 | I88: ='Table 9.13 (b)'!H40*'Price Summary'!$J$51 -> 0 | J88: ='Table 9.13 (b)'!I40*'Price Summary'!$J$51 -> 0 | K88: ='Table 9.13 (b)'!J40*'Price Summary'!$J$51 -> 0 | ... M88: ='Table 9.13 (b)'!L40*'Price Summary'!$J$51 -> 0 | N88: =SUM(D88:M88) -> 0 | P88: ='Table 9.13 (b)'!M40*'Price.Data.Inputs'!$E$224 -> 0 | Q88: ='Table 9.13 (b)'!N40*'Price.Data.Inputs'!$E$224 -> 0 | R88: ='Table 9.13 (b)'!O40*'Price.Data.Inputs'!$E$224 -> 0 | V88: =SUM(N88:T88) -> 0
B89: Other | N89: =SUM(D89:M89) -> 0 | V89: =SUM(N89:T89) -> 0
B90: Sub-Total (All Residuals) | D90: =SUM(D86:D89) -> 0 | E90: =SUM(E86:E89) -> 0 | F90: =SUM(F86:F89) -> 0 | G90: =SUM(G86:G89) -> 0 | H90: =SUM(H86:H89) -> 0 | I90: =SUM(I86:I89) -> 0 | J90: =SUM(J86:J89) -> 0 | K90: =SUM(K86:K89) -> 0 | ... W90: =SUM(W86:W89) -> 0
B92: Note: Dark grey cells are null by definition. Data for industries should be presented in basic prices; last column contains information on purchaser prices.
B94: Other notes
B95: Monetary supply and use tables for energy provide information on the energy sector and the level of activity in this sector. They also provide detailed information on the industries within the economy that are using these energy products. Monetary supply and use tables for energy can readily be linked with PSUT for energy to create a powerful analytical tool, for example to do price analyses.
B96: The monetary supply table for energy products shows the value of domestic production for various energy products and the value of imports at basic prices. The table also presents, for each type of energy product and the sum of taxes less subsidies, and trade and transport margins. The final column shows the total purchasers price.
B97: The bottom part of core account 2 shows the monetary use table for energy in purchasers’ prices. It records the amounts paid by users for the various energy products used. As in the physical
B98: use table for energy, the use includes intermediate consumption by industries and other uses including household consumption, exports and accumulation.8
B99: Energy residuals in physical terms comprise energy losses and other energy residuals. Particular examples of energy losses include flaring and venting of natural gas and losses during transformation in the production of primary energy products from natural inputs and in the production of secondary energy products. Energy losses during distribution may arise from the evaporation and leakages of liquid fuels, loss of heat during transport of steam, and losses during gas distribution, electricity transmission and pipeline transport. Energy residuals also include other energy residuals particularly heat generated when end users (either households or enterprises) use energy products for energy purposes (e.g. household lighting).

Sheet Price Summary
B2: 2024 Energy Pricing
C3: Energy commodity | D3: Notes | E3: Source | F3: Unit | G3: Primary price | H3: Import price | I3: Wholesale price | J3: Retail price
B4: 1 | C4: Hydro | D4: Average price Kenya Power pays to purchase electricity from hydro sources | E4: Kenya Power Integrated Report | F4: KSh/GWh | G4: ='Price.Data.Inputs'!F96 -> 3382118.4
F5: Ksh/TJ | G5: ='Price.Data.Inputs'!F97 -> 939477.33
B6: 2 | C6: Geothermal | D6: Average price Kenya Power pays to purchase electricity from geothermal sources | E6: Kenya Power Integrated Report | F6: KSh/GWh | G6: ='Price.Data.Inputs'!F98 -> 9940532.3
F7: Ksh/TJ | G7: ='Price.Data.Inputs'!F99 -> 2761259
B8: 3 | C8: Wind | D8: Average price Kenya Power pays to purchase electricity from wind sources | E8: Kenya Power Integrated Report | F8: KSh/GWh | G8: ='Price.Data.Inputs'!F100 -> 14547379
F9: Ksh/TJ | G9: ='Price.Data.Inputs'!F101 -> 4040938.7
B10: 4 | C10: Solar | D10: Average price Kenya Power pays to purchase electricity from solar sources | E10: Kenya Power Integrated Report | F10: KSh/GWh | G10: ='Price.Data.Inputs'!F102 -> 16202021
F11: Ksh/TJ | G11: ='Price.Data.Inputs'!F103 -> 4500561.4
B12: 5 | C12: Co-generation | D12: Average price Kenya Power pays to purchase electricity from co-generation | E12: Kenya Power Integrated Report | F12: KSh/GWh | G12: ='Price.Data.Inputs'!F105 -> 15327273
F13: Ksh/TJ | G13: ='Price.Data.Inputs'!F106 -> 4257575.8
C14: Biofuel: Bagasse | D14: Average price Kenya Power pays to purchase electricity from co-generation | E14: Kenya Power Integrated Report | F14: KSh/GWh | G14: ='Price.Data.Inputs'!F105 -> 15327273
F15: Ksh/TJ | G15: ='Price.Data.Inputs'!F106 -> 4257575.8
C16: Charcoal | D16: Average price Kenya Power pays to purchase electricity from co-generation | E16: Kenya Power Integrated Report | F16: KSh/GWh
F17: Ksh/TJ | G17: =G27 -> 432692.31 | J17: ='Price.Data.Inputs'!I17 -> 2746482.4
B18: 6 | C18: Coal and coke | E18: Customs data | F18: Ksh/kg | H18: 80.43 | J18: 151.35
F19: Ksh/TJ | H19: =H18/Conversions!$E$17 -> 3093461.5 | J19: =J18/Conversions!$E$17 -> 5821153.8
B20: 7 | C20: Aviation spirit | E20: Customs data | F20: Ksh/litre | H20: 120.4241 | J20: 134.67
F21: Ksh/TJ | H21: =H20/Conversions!$E$18 -> 3594749.2 | J21: =J20/Conversions!$E$18 -> 4020000
B22: 8 | C22: Spirit type jet fuel | E22: Customs data | F22: Ksh/litre | H22: 326.37 | J22: 808.96935
F23: Ksh/TJ | H23: =H22/Conversions!$E$9 -> 9324857.1 | J23: =J22/Conversions!$E$9 -> 23113410
B24: 9 | C24: White spirit and special boiling point industrial spirits | E24: Customs data | F24: Ksh/litre | H24: 328.0975 | J24: 615.11511
F25: Ksh/TJ | H25: =H24/Conversions!$E$15 -> 9942348.5 | J25: =J24/Conversions!$E$15 -> 18639852
B26: 10 | C26: Firewood | E26: https://www.pigiame.co.ke/listings/dry-firewood-6045399#:~:text=We%20sell%20dry%20firewood%20price,free%20transport%20within%20Nairobi%20county%20. | F26: Ksh/tonne | J26: 9000
F27: Ksh/TJ | G27: =J27/1.3 -> 432692.31 | J27: =J26/Conversions!$E$21 -> 562500
B28: 11 | C28: Motor spirit premium | D28: 12 month average | E28: KNBS | F28: Ksh/litre | H28: 176.29 | J28: ='Table 9.6'!C41 -> 191.76
E29: Table 9.6 converted to TJ | F29: Ksh/TJ | H29: =H28/Conversions!E16 -> 5154678.4 | J29: ='Table 9.6'!K41 -> 5606944.4
B30: 12 | C30: Light Diesel Oil | D30: 12 month average | E30: KNBS | F30: Ksh/litre | H30: ='Price.Data.Inputs'!N316 -> 41.555 | J30: ='Table 9.6'!D41 -> 178.32
E31: Table 9.6 converted to TJ | F31: Ksh/TJ | H31: =H30/Conversions!E23 -> 1160754.2 | J31: ='Table 9.6'!L41 -> 4980982.3
C32: Heavy Diesel Oil | D32: 12 month average | E32: KNBS | F32: Ksh/litre | H32: =H30 -> 41.555 | J32: =J30 -> 178.32
E33: Table 9.6 converted to TJ | F33: Ksh/TJ | H33: =H31 -> 1160754.2 | J33: =J31 -> 4980982.3
C34: Fuel Oils | E34: Customs data | F34: Ksh/litre | H34: ='Price.Data.Inputs'!N341 -> 17.2 | J34: =J32 -> 178.32
F35: Ksh/TJ | H35: =H34/Conversions!E23 -> 480446.93 | J35: =J33 -> 4980982.3
B36: 13 | C36: Illuminating Kerosene | D36: 12 month average | E36: KNBS | F36: Ksh/litre | H36: 97.22 | J36: ='Table 9.6'!E41 -> 168.38
E37: Table 9.6 converted to TJ | F37: Ksh/TJ | H37: =H36/Conversions!E11 -> 2826162.8 | J37: ='Table 9.6'!M41 -> 4502228.2
B38: 14 | C38: Liqufied Petroleum Gas (LPG) | D38: 12 month average | E38: KNBS | F38: Ksh/13 kg cylinder | H38: =J38 -> 3188.34 | J38: ='Table 9.6'!F41 -> 3188.34
E39: Table 9.6 converted to TJ | F39: Ksh/TJ | H39: =J39-1 -> 4905138.7 | J39: ='Table 9.6'!N41 -> 4905139.7
B40: 15 | C40: Domestic | E40: KNBS | F40: KSh/kWh | J40: ='Table 9.11'!F4 -> 24.97
E41: Table 9.11 converted to TJ | F41: Ksh/TJ | J41: ='Table 9.11'!H4 -> 6936111.1 | L41: Average
B42: 16 | C42: Small Commercial | E42: KNBS | F42: KSh/kWh | J42: ='Table 9.11'!F5 -> 27.52 | L42: Goal seek | M42: Calculated
E43: Table 9.11 converted to TJ | F43: Ksh/TJ | J43: ='Table 9.11'!H5 -> 7644444.4 | L43: 5422043 | M43: =AVERAGE(J41,J43,J45,J47,J49) -> 5916111.1
B44: 17 | C44: Commercial Industrial | E44: KNBS | F44: KSh/kWh | J44: ='Table 9.11'!F6 -> 21.73
E45: Table 9.11 converted to TJ | F45: Ksh/TJ | J45: ='Table 9.11'!H6 -> 6036111.1
B46: 18 | C46: Street Lighting | E46: KNBS | F46: KSh/kWh | J46: ='Table 9.11'!F7 -> 12.92
E47: Table 9.11 converted to TJ | F47: Ksh/TJ | J47: ='Table 9.11'!H7 -> 3588888.9
B48: 19 | C48: E-Mobility | E48: KNBS | F48: KSh/kWh | J48: ='Table 9.11'!F8 -> 19.35
E49: Table 9.11 converted to TJ | F49: Ksh/TJ | J49: ='Table 9.11'!H8 -> 5375000
C50: Average electricity price | E50: KNBS | F50: KSh/kWh | J50: ='Price.Data.Inputs'!D224 -> 10.587036
E51: Table 9.11 converted to TJ | F51: Ksh/TJ | J51: ='Price.Data.Inputs'!E224 -> 2940843.4
C52: Lubricating Oils | E52: KNBS | F52: KSh/kWh
E53: Table 9.1 converted to TJ | F53: Ksh/TJ | H53: ='Table 9.1'!Q6 -> 73879830 | J53: ='Table 9.1'!Q16 -> 1.0313098e+08
C54: Lubricating Greases | E54: KNBS | F54: KSh/kWh
E55: Table 9.1 converted to TJ | F55: Ksh/TJ | H55: ='Table 9.1'!Q7 -> 58381747 | J55: =J53 -> 1.0313098e+08
C56: Rural electrification | F56: KSh/kWh | J56: 8.71
E57: Kenya power | F57: Ksh/TJ | J57: =J56/Conversions!$E$22 -> 2419444.4
C58: Electricity plants (Kengen) | F58: KSh/kWh | J58: ='Price.Data.Inputs'!D208 -> 6.142348
E59: Price Kenya Power pays for electricity | F59: Ksh/TJ | J59: =J58/Conversions!$E$22 -> 1706207.8
C60: Electricity plants (Independent Power Producers (IPPs)) | F60: KSh/kWh | J60: ='Price.Data.Inputs'!D209 -> 15.934203
E61: Price Kenya Power pays for electricity | F61: Ksh/TJ | J61: =J60/Conversions!$E$22 -> 4426167.4
C62: Electricity plants (REREC) | F62: KSh/kWh | J62: ='Price.Data.Inputs'!D210 -> 8.0350238
E63: Price Kenya Power pays for electricity | F63: Ksh/TJ | J63: =J62/Conversions!$E$22 -> 2231951.1
C64: Electricity plants (Off-grid)) | F64: KSh/kWh | J64: ='Price.Data.Inputs'!D212 -> 8.0350238
E65: Price Kenya Power pays for electricity | F65: Ksh/TJ | J65: =J64/Conversions!$E$22 -> 2231951.1
C66: Petroleum Fuels
F67: Ksh/TJ | J67: ='Table 9.1'!Q5 -> 26194025

Sheet Price.Data.Inputs
B2: Source: Kenya National Bureau of Statistics (KNBS) via email from Christine Mukami Magu on 25 Apr 2025
B3: Descriptions/ Period | C3: Motor Gasoline Premium (KSh per Litre) | D3: Light Diesel Oil (KSh per Litre) | E3: Illuminating Kerosene (KSh per Litre) | F3: L.P.G (KSh per 13 Kg) | G3: Charcoal (KSh per Kg ) | I3: Charcoal (Ksh/TJ)
B4: CPI, 2024
B5: January | C5: 207.9728 | D5: 197.2056 | E5: 194.957 | F5: 3055.511 | G5: 76.893715 | I5: =G5/Conversions!$E$20 -> 2563123.8
B6: February | C6: 206.9728 | D6: 196.2056 | E6: 193.957 | F6: 3187.0987 | G6: 77.461246 | I6: =G6/Conversions!$E$20 -> 2582041.5
B7: March | C7: 199.7666 | D7: 191.1128 | E7: 189.4826 | F7: 3231.8376 | G7: 78.639919 | I7: =G7/Conversions!$E$20 -> 2621330.6
B8: April | C8: 194.4566 | D8: 181.1128 | E8: 171.18 | F8: 3242.1143 | G8: 79.502414 | I8: =G8/Conversions!$E$20 -> 2650080.5
B9: May | C9: 193.4566 | D9: 179.9128 | E9: 169.5182 | F9: 3221.285 | G9: 82.323685 | I9: =G9/Conversions!$E$20 -> 2744122.8
B10: June | C10: 190.4566 | D10: 173.8328 | E10: 163.8224 | F10: 3213.9658 | G10: 83.802682 | I10: =G10/Conversions!$E$20 -> 2793422.7
B11: July | C11: 189.4566 | D11: 172.3328 | E11: 162.5226 | F11: 3219.5847 | G11: 84.407368 | I11: =G11/Conversions!$E$20 -> 2813578.9
B12: August | C12: 189.4566 | D12: 172.3328 | E12: 162.5226 | F12: 3217.8521 | G12: 84.169763 | I12: =G12/Conversions!$E$20 -> 2805658.8
B13: September | C13: 189.4566 | D13: 172.3328 | E13: 159.099 | F13: 3196.0417 | G13: 85.324763 | I13: =G13/Conversions!$E$20 -> 2844158.8
B14: October | C14: 181.3276 | D14: 168.818 | E14: 152.1794 | F14: 3183.2891 | G14: 85.255107 | I14: =G14/Conversions!$E$20 -> 2841836.9
B15: November | C15: 181.3276 | D15: 168.818 | E15: 152.1794 | F15: 3147.6603 | G15: 85.291648 | I15: =G15/Conversions!$E$20 -> 2843054.9
B16: December | C16: 176.9606 | D16: 165.818 | E16: 149.1794 | F16: 3143.8466 | G16: 85.661364 | I16: =G16/Conversions!$E$20 -> 2855378.8
B17: Average | I17: =AVERAGE(I5:I16) -> 2746482.4
B21: Source: Kenya National Bureau of Statistics (KNBS) via email from Christine Mukami Magu on 25 Apr 2025
B22: Domestic and Small Commercial | C22: Ksh/TJ | D22: =AVERAGE(I33:I40) -> 4444444.4
B23: Large and Medium | C23: Ksh/TJ | D23: =AVERAGE(I44,I47:I48,I50,I53:I54,I56,I59:I60,I62,I65:I66,I68,I71:I72,I74,I77) -> 2912908.5
B24: Street Lighting | C24: Ksh/TJ | D24: =I84 -> 2566666.7
B25: E-mobility | C25: Ksh/TJ | D25: =AVERAGE(I41,I43) -> 3333333.3
B26: Rural electrification | C26: Ksh/TJ | D26: =AVERAGE(I79,I82) -> 2419444.4
B27: Other | C27: Ksh/TJ
B30: Source: Kenya National Bureau of Statistics (KNBS) via email from Christine Mukami Magu on 25 Apr 2025
B31: Existing Code | C31: Proposed Code | D31: Customer | E31: Energy Limit kWh/month | F31: Charge Method | G31: Unit | H31: July 2023 - June 2024 | I31: Ksh/TJ
D32: Type (Code Name)
B33: DC | C33: DC-1 | D33: Domestic Lifeline | E33: 0-30 | F33: Energy | G33: KSh/kWh | H33: 12.24 | I33: =H33/Conversions!$E$22 -> 3400000
C34: DC-2 | D34: Domestic Ordinary | E34: >30-100 | F34: Energy | G34: KSh/kWh | H34: 16.58 | I34: =H34/Conversions!$E$22 -> 4605555.6
C35: DC-3 | D35: Domestic Ordinary | E35: >100 | F35: Energy | G35: KSh/kWh | H35: 20.58 | I35: =H35/Conversions!$E$22 -> 5716666.7
B36: SC | C36: SC-1 | D36: Small Commercial | E36: 0-30 | F36: Energy | G36: KSh/ kWh | H36: 12.24 | I36: =H36/Conversions!$E$22 -> 3400000
C37: SC-2 | D37: Small Commercial | E37: >30-100 | F37: Energy | G37: KSh/kWh | H37: 16.36 | I37: =H37/Conversions!$E$22 -> 4544444.4
C38: SC-3 | D38: Small Commercial | E38: >100 | F38: Energy | G38: KSh/kWh | H38: 20 | I38: =H38/Conversions!$E$22 -> 5555555.6
C39: TOU | D39: Time of Use for SC | E39: >100 | F39: Energy | G39: KSh/kWh | H39: 10 | I39: =H39/Conversions!$E$22 -> 2777777.8
C40: BULK TARIFF | D40: Bulk Tariff for SC | E40: 1,000-15,000 | F40: Energy | G40: KSh/kWh | H40: 20 | I40: =H40/Conversions!$E$22 -> 5555555.6
B41: EM | C41: E-mobility | D41: Electric Mobility | E41: 0 – 15,000 | F41: Energy | G41: KSh/kWh | H41: 16 | I41: =H41/Conversions!$E$22 -> 4444444.4
I42: =H42/Conversions!$E$22 -> 0
D43: Electric Mobility (TOU) | F43: Energy | G43: KSh/kWh | H43: 8 | I43: =H43/Conversions!$E$22 -> 2222222.2
B44: CI1 | C44: CI1 | D44: Comm./industrial | E44: >15,000 | F44: Energy | G44: KSh/kWh | H44: 14.5 | I44: =H44/Conversions!$E$22 -> 4027777.8
I45: =H45/Conversions!$E$22 -> 0
I46: =H46/Conversions!$E$22 -> 0
F47: TOU | G47: Ksh/kWh | H47: 7.25 | I47: =H47/Conversions!$E$22 -> 2013888.9
F48: Bulk Tariff | G48: Ksh/kWh | H48: 14.5 | I48: =H48/Conversions!$E$22 -> 4027777.8
F49: Demand | G49: KSh/kVA | H49: 1100
B50: CI2 | C50: CI2 | D50: Comm./industrial | E50: No Limit | F50: Energy | G50: KSh/kWh | H50: 13.08 | I50: =H50/Conversions!$E$22 -> 3633333.3
I51: =H51/Conversions!$E$22 -> 0
I52: =H52/Conversions!$E$22 -> 0
F53: TOU | G53: Ksh/kWh | H53: 6.54 | I53: =H53/Conversions!$E$22 -> 1816666.7
F54: Bulk Tariff | G54: Ksh/kWh | H54: 13.08 | I54: =H54/Conversions!$E$22 -> 3633333.3
F55: Demand | G55: KSh/kVA | H55: 700
B56: CI3 | C56: CI3 | D56: Comm./industrial | E56: No Limit | F56: Energy | G56: KSh/kWh | H56: 12.52 | I56: =H56/Conversions!$E$22 -> 3477777.8
F59: TOU | G59: Ksh/kWh | H59: 6.26 | I59: =H59/Conversions!$E$22 -> 1738888.9
F60: Bulk Tariff | G60: Ksh/kWh | H60: 12.52 | I60: =H60/Conversions!$E$22 -> 3477777.8
F61: Demand | G61: KSh/kVA | H61: 370
B62: CI4 | C62: CI4 | D62: Comm./industrial | E62: No Limit | F62: Energy | G62: KSh/kWh | H62: 12.26 | I62: =H62/Conversions!$E$22 -> 3405555.6
F65: TOU | G65: Ksh/kWh | H65: 6.13 | I65: =H65/Conversions!$E$22 -> 1702777.8
F66: Bulk Tariff | G66: Ksh/kWh | H66: 12.26 | I66: =H66/Conversions!$E$22 -> 3405555.6
F67: Demand | G67: KSh/kVA | H67: 300
B68: CI5 | C68: CI5 | D68: Comm./industrial | E68: No Limit | F68: Energy | G68: KSh/kWh | H68: 11.98 | I68: =H68/Conversions!$E$22 -> 3327777.8
F71: TOU | G71: Ksh/kWh | H71: 5.99 | I71: =H71/Conversions!$E$22 -> 1663888.9
F72: Bulk Tariff | G72: Ksh/kWh | H72: 11.98 | I72: =H72/Conversions!$E$22 -> 3327777.8
F73: Demand | G73: KSh/kVA | H73: 300
B74: CI6 | C74: CI6 | D74: Comm./industrial | E74: No Limit | F74: Energy | G74: KSh/kWh | H74: 10 | I74: =H74/Conversions!$E$22 -> 2777777.8
F77: TOU | G77: Ksh/kWh | H77: 7.42 | I77: =H77/Conversions!$E$22 -> 2061111.1
F78: Demand | G78: KSh/kVA | H78: 200
B79: CI7 | C79: CI7 | D79: Special Economic Zone | E79: No Limit | F79: Energy | G79: KSh/kWh | H79: 10 | I79: =H79/Conversions!$E$22 -> 2777777.8
F82: TOU | G82: Ksh/kWh | H82: 7.42 | I82: =H82/Conversions!$E$22 -> 2061111.1
F83: Demand | G83: KSh/kVA | H83: 200
B84: SL | C84: SL | D84: Street Lighting | E84: No Limit | F84: Energy | G84: KSh/kWh | H84: 9.24 | I84: =H84/Conversions!$E$22 -> 2566666.7
B92: Price Kenya Power Pays to purchase electricity from various sources
B93: Source: Kenya Power Integrated Annual Report 2024 (https://www.kplc.co.ke/storage/01JDRPZS8NZ473CWE2XCSQ1REJ.pdf)
B95: Data extracted from Kenya Power IAR 2024 tables pasted below
B96: Hydro purchase cost per GWh | E96: KSh/GWh | F96: =11485674000/3396 -> 3382118.4
E97: Ksh/TJ | F97: =F96/Conversions!$E$2 -> 939477.33
B98: Geothermal purchase cost per GWh | E98: KSh/GWh | F98: =56730618000/5707 -> 9940532.3
E99: Ksh/TJ | F99: =F98/Conversions!$E$2 -> 2761259
B100: Wind purchase cost per GWh | E100: KSh/GWh | F100: =25894335000/1780 -> 14547379
E101: Ksh/TJ | F101: =F100/Conversions!$E$2 -> 4040938.7
B102: Solar purchase cost per GWh | E102: KSh/GWh | F102: =7663556000/473 -> 16202021
E103: Ksh/TJ | F103: =F102/Conversions!$E$2 -> 4500561.4
E104: Ksh/kWh | F104: =F102/1000000 -> 16.202021
B105: Cogeneration purchase cost per GWh | E105: KSh/GWh | F105: =1686000/0.11 -> 15327273
E106: Ksh/TJ | F106: =F105/Conversions!$E$2 -> 4257575.8
B188: Source: KBNS Customs data
B189: Source: https://www.pigiame.co.ke/listings/dry-firewood-6045399#:~:text=We%20sell%20dry%20firewood%20price,free%20transport%20within%20Nairobi%20county%20.
B191: Domestic exports | C191: Coal and coke | D191: Source: Customs data | F191: Ksh/kg | G191: 151.35
F192: Ksh/TJ | G192: =G191/Conversions!$E$17 -> 5821153.8
B193: Domestic exports | C193: Aviation spirit | D193: Source: Customs data | F193: Ksh/litre | G193: 134.67
F194: Ksh/TJ | G194: =G193/Conversions!$E$18 -> 4020000
B195: Domestic exports | C195: Spirit type jet fuel | D195: Source: Customs data | F195: Ksh/litre | G195: 808.96935
F196: Ksh/TJ | G196: =G195/Conversions!$E$9 -> 23113410
B197: Domestic exports | C197: White spirit and special boiling point industrial spirits | D197: Source: Customs data | F197: Ksh/litre | G197: 615.11511
F198: Ksh/TJ | G198: =G197/Conversions!$E$15 -> 18639852
B199: Firewood retail price | D199: Source: https://www.pigiame.co.ke/listings/dry-firewood-6045399#:~:text=We%20sell%20dry%20firewood%20price,free%20transport%20within%20Nairobi%20county%20. | F199: Ksh/tonne | G199: 9000
F200: Ksh/TJ | G200: =G199/Conversions!$E$21 -> 562500
B205: Source: Data extracted from Kenya Power IAR 2024 tables
C206: KSh/GWh | D206: KSh/kWh | E206: Ksh/TJ
B207: Price Kenya Power pays for electricity
B208: Electricity plants (Kengen) | C208: =(10636869000+38172401000+440076000)/(3335+4633+50) -> 6142348 | D208: =C208/1000000 -> 6.142348
B209: Electricity plants (Independent Power Producers (IPPs)) | C209: =(848805000+18558217000+25454259000+6988614000)/(61+1074+1730+389) -> 15934203 | D209: =C209/1000000 -> 15.934203
B210: Electricity plants (REREC) | C210: =(674942000)/84 -> 8035023.8 | D210: =C210/1000000 -> 8.0350238
...

Sheet Customs_Energy Products
A1: Back
A3: Year | B3: Month | C3: Country_Code | D3: Country | E3: HS_C | F3: HS product name | G3: SITC_C | H3: BEC | I3: Unit | J3: Quantity | K3: Net weight | L3: Value in KSh | M3: Trade Flow | N3: Source | P3: Pricing
A4: 2024 | B4: 1 | D4: CHINA | E4: 27149000 | F4: =VLOOKUP(E4,'HS Code'!$L$4:$O$65,2,0) -> Coal and Coke | G4: 27897000 | H4: 21 | I4: kg | J4: 522650 | K4: 522650 | L4: 37658839 | M4: Imports | N4: Customs | P4: =L4/J4 -> 72.053648
A5: 2024 | B5: 1 | D5: ITALY | E5: 27131200 | F5: =VLOOKUP(E5,'HS Code'!$L$4:$O$65,2,0) -> 0 | G5: 33542900 | H5: 22 | I5: kg | J5: 2837 | K5: 2837 | L5: 11820720 | M5: Imports | N5: Customs | P5: =L5/J5 -> 4166.6268
A6: 2024 | B6: 1 | D6: UNITED ARAB EMIRATES | E6: 27101951 | F6: =VLOOKUP(E6,'HS Code'!$L$4:$O$65,2,0) -> Petroleum | G6: 33450910 | H6: 322 | I6: l | J6: 379006.08 | K6: 378526.08 | L6: 71152087 | M6: Imports | N6: Customs | P6: =L6/J6 -> 187.73337
A7: 2024 | B7: 1 | D7: UNITED ARAB EMIRATES | E7: 27101952 | F7: =VLOOKUP(E7,'HS Code'!$L$4:$O$65,2,0) -> Petroleum | G7: 33450920 | H7: 322 | I7: kg | J7: 1944 | K7: 1944 | L7: 350155.93 | M7: Imports | N7: Customs | P7: =L7/J7 -> 180.12136
A8: 2024 | B8: 1 | D8: UNITED ARAB EMIRATES | E8: 27101956 | F8: =VLOOKUP(E8,'HS Code'!$L$4:$O$65,2,0) -> Petroleum | G8: 33450960 | H8: 322 | I8: l | J8: 70260 | K8: 70260 | L8: 23643528 | M8: Imports | N8: Customs | P8: =L8/J8 -> 336.51477
A9: 2024 | B9: 1 | D9: UNITED ARAB EMIRATES | E9: 27101957 | F9: =VLOOKUP(E9,'HS Code'!$L$4:$O$65,2,0) -> Petroleum | G9: 33450970 | H9: 322 | I9: l | J9: 134006 | K9: 134006 | L9: 23419323 | M9: Imports | N9: Customs | P9: =L9/J9 -> 174.76324
A10: 2024 | B10: 1 | D10: UNITED ARAB EMIRATES | E10: 27101959 | F10: =VLOOKUP(E10,'HS Code'!$L$4:$O$65,2,0) -> Petroleum | G10: 33450990 | H10: 322 | I10: l | J10: 176280 | K10: 176280 | L10: 26818811 | M10: Imports | N10: Customs | P10: =L10/J10 -> 152.13757
A11: 2024 | B11: 1 | D11: UNITED ARAB EMIRATES | E11: 27129000 | F11: =VLOOKUP(E11,'HS Code'!$L$4:$O$65,2,0) -> 0 | G11: 33512900 | H11: 22 | I11: kg | J11: 83250 | K11: 83250 | L11: 16042525 | M11: Imports | N11: Customs | P11: =L11/J11 -> 192.703
A12: 2024 | B12: 1 | D12: UNITED ARAB EMIRATES | E12: 27132000 | F12: =VLOOKUP(E12,'HS Code'!$L$4:$O$65,2,0) -> 0 | G12: 33541100 | H12: 22 | I12: kg | J12: 599550 | K12: 599550 | L12: 42575805 | M12: Imports | N12: Customs | P12: =L12/J12 -> 71.012935
A13: 2024 | B13: 1 | D13: ARGENTINA | E13: 27101951 | F13: =VLOOKUP(E13,'HS Code'!$L$4:$O$65,2,0) -> Petroleum | G13: 33450910 | H13: 322 | I13: l | J13: 10368 | K13: 10368 | L13: 10364597 | M13: Imports | N13: Customs | P13: =L13/J13 -> 999.67179
A14: 2024 | B14: 1 | D14: ARGENTINA | E14: 27101952 | F14: =VLOOKUP(E14,'HS Code'!$L$4:$O$65,2,0) -> Petroleum | G14: 33450920 | H14: 322 | I14: kg | J14: 3860 | K14: 3860 | L14: 7067052.5 | M14: Imports | N14: Customs | P14: =L14/J14 -> 1830.8426
A15: 2024 | B15: 1 | D15: BELGIUM | E15: 27101951 | F15: =VLOOKUP(E15,'HS Code'!$L$4:$O$65,2,0) -> Petroleum | G15: 33450910 | H15: 322 | I15: l | J15: 7331 | K15: 7331 | L15: 4310070.8 | M15: Imports | N15: Customs | P15: =L15/J15 -> 587.924
A16: 2024 | B16: 1 | D16: SWITZERLAND | E16: 27101952 | F16: =VLOOKUP(E16,'HS Code'!$L$4:$O$65,2,0) -> Petroleum | G16: 33450920 | H16: 322 | I16: kg | J16: 26 | K16: 26 | L16: 451917.04 | M16: Imports | N16: Customs | P16: =L16/J16 -> 17381.425
... A152: 2024 | B152: 1 | D152: OMAN | E152: 27101931 | F152: =VLOOKUP(E152,'HS Code'!$L$4:$O$65,2,0) -> Petroleum | G152: 33430100 | H152: 322 | I152: l | J152: 52668115 | K152: 52668115 | L152: 7.3543567e+09 | M152: Imports | N152: Customs | P152: =L152/J152 -> 139.63584
A153: 2024 | B153: 1 | D153: SOUTH SUDAN | E153: 27150000 | F153: =VLOOKUP(E153,'HS Code'!$L$4:$O$65,2,0) -> 0 | G153: 33543000 | H153: 22 | I153: kg | J153: 548380 | K153: 548380 | L153: 24067371 | M153: Re-Exports | N153: Customs
A154: 2024 | B154: 1 | D154: AIRCRAFT & SHIPSTORES | E154: 27101921 | F154: =VLOOKUP(E154,'HS Code'!$L$4:$O$65,2,0) -> Petroleum | G154: 33421100 | H154: 322 | I154: l | J154: 29658659 | K154: 27982298 | L154: 3.4833844e+09 | M154: Re-Exports | N154: Customs
A155: 2024 | B155: 1 | D155: AIRCRAFT & SHIPSTORES | E155: 27101921 | F155: =VLOOKUP(E155,'HS Code'!$L$4:$O$65,2,0) -> Petroleum | G155: 33421100 | H155: 322 | I155: l | J155: 32418500 | K155: 32418500 | L155: 4.0096465e+09 | M155: Re-Exports | N155: Customs
A156: 2024 | B156: 1 | D156: AIRCRAFT & SHIPSTORES | E156: 27101931 | F156: =VLOOKUP(E156,'HS Code'!$L$4:$O$65,2,0) -> Petroleum | G156: 33430100 | H156: 322 | I156: l | J156: 527125 | K156: 440203 | L156: 61585690 | M156: Re-Exports | N156: Customs
A157: 2024 | B157: 1 | D157: AIRCRAFT & SHIPSTORES | E157: 27101942 | F157: =VLOOKUP(E157,'HS Code'!$L$4:$O$65,2,0) -> Petroleum | G157: 33450200 | H157: 322 | I157: l | J157: 1531115 | K157: 1498605 | L157: 2.1897038e+08 | M157: Re-Exports | N157: Customs
A158: 2024 | B158: 1 | D158: OTHER COUNTRIES N.E.S | E158: 27101931 | F158: =VLOOKUP(E158,'HS Code'!$L$4:$O$65,2,0) -> Petroleum | G158: 33430100 | H158: 322 | I158: l | J158: 735579 | K158: 735579 | L158: 1.0680589e+08 | M158: Re-Exports | N158: Customs
A159: 2024 | B159: 1 | D159: AIRCRAFT & SHIPSTORES | E159: 27101921 | F159: =VLOOKUP(E159,'HS Code'!$L$4:$O$65,2,0) -> Petroleum | G159: 33421100 | H159: 322 | I159: l | J159: 5420104 | K159: 4281881 | L159: 524423887 | M159: Re-Exports | N159: Customs
A160: 2024 | B160: 1 | D160: RWANDA | E160: 27101951 | F160: =VLOOKUP(E160,'HS Code'!$L$4:$O$65,2,0) -> Petroleum | G160: 33450910 | H160: 322 | I160: l | J160: 57428 | K160: 56691 | L160: 20832031 | M160: Re-Exports | N160: Customs
A161: 2024 | B161: 1 | D161: UGANDA | E161: 27101951 | F161: =VLOOKUP(E161,'HS Code'!$L$4:$O$65,2,0) -> Petroleum | G161: 33450910 | H161: 322 | I161: l | J161: 79002 | K161: 70434 | L161: 27109645 | M161: Re-Exports | N161: Customs
A162: 2024 | B162: 1 | D162: UGANDA | E162: 27150000 | F162: =VLOOKUP(E162,'HS Code'!$L$4:$O$65,2,0) -> 0 | G162: 33543000 | H162: 22 | I162: kg | J162: 42750 | K162: 42750 | L162: 7446253.5 | M162: Re-Exports | N162: Customs
A163: 2024 | B163: 1 | D163: UGANDA | E163: 27101230 | F163: =VLOOKUP(E163,'HS Code'!$L$4:$O$65,2,0) -> Petroleum | G163: 33411230 | H163: 321 | I163: l | J163: 19607 | K163: 19607 | L163: 6457203 | M163: Re-Exports | N163: Customs | P163: =L163/J163 -> 329.33151
A164: 2024 | B164: 1 | D164: BURUNDI | E164: 27101959 | F164: =VLOOKUP(E164,'HS Code'!$L$4:$O$65,2,0) -> Petroleum | G164: 33450990 | H164: 322 | I164: l | J164: 250 | K164: 250 | L164: 268258.86 | M164: Domestic Exports | N164: Customs
A165: 2024 | B165: 1 | D165: RWANDA | E165: 27030000 | F165: =VLOOKUP(E165,'HS Code'!$L$4:$O$65,2,0) -> Coal and Coke | G165: 32230000 | H165: 31 | I165: kg | J165: 600 | K165: 600 | L165: 75705.13 | M165: Domestic Exports | N165: Customs | P165: =L165/J165 -> 126.17522
A166: 2024 | B166: 1 | D166: RWANDA | E166: 27073000 | F166: =VLOOKUP(E166,'HS Code'!$L$4:$O$65,2,0) -> Oils | G166: 33524000 | H166: 22 | I166: kg | J166: 170 | K166: 170 | L166: 42244.666 | M166: Domestic Exports | N166: Customs
A167: 2024 | B167: 1 | D167: RWANDA | E167: 27101250 | F167: =VLOOKUP(E167,'HS Code'!$L$4:$O$65,2,0) -> Petroleum | G167: 33411250 | H167: 322 | I167: l | J167: 360 | K167: 360 | L167: 68252.8 | M167: Domestic Exports | N167: Customs
A168: 2024 | B168: 1 | D168: RWANDA | E168: 27101951 | F168: =VLOOKUP(E168,'HS Code'!$L$4:$O$65,2,0) -> Petroleum | G168: 33450910 | H168: 322 | I168: l | J168: 23349 | K168: 23349 | L168: 9366332.6 | M168: Domestic Exports | N168: Customs
A169: 2024 | B169: 1 | D169: RWANDA | E169: 27122000 | F169: =VLOOKUP(E169,'HS Code'!$L$4:$O$65,2,0) -> 0 | G169: 33512100 | H169: 22 | I169: kg | J169: 500 | K169: 500 | L169: 85785.11 | M169: Domestic Exports | N169: Customs
A170: 2024 | B170: 1 | D170: RWANDA | E170: 27150000 | F170: =VLOOKUP(E170,'HS Code'!$L$4:$O$65,2,0) -> 0 | G170: 33543000 | H170: 22 | I170: kg | J170: 900 | K170: 900 | L170: 206846.34 | M170: Domestic Exports | N170: Customs
A171: 2024 | B171: 1 | D171: TANZANIA | E171: 27101951 | F171: =VLOOKUP(E171,'HS Code'!$L$4:$O$65,2,0) -> Petroleum | G171: 33450910 | H171: 322 | I171: l | J171: 275835 | K171: 275835 | L171: 88345939 | M171: Domestic Exports | N171: Customs
A172: 2024 | B172: 1 | D172: UGANDA | E172: 27101240 | F172: =VLOOKUP(E172,'HS Code'!$L$4:$O$65,2,0) -> White spirit and special boiling point industrial spirits | G172: 33411240 | H172: 321 | I172: l | J172: 27723 | K172: 20440 | L172: 11033136 | M172: Domestic Exports | N172: Customs | P172: =L172/J172 -> 397.97771
A173: 2024 | B173: 1 | D173: UGANDA | E173: 27101951 | F173: =VLOOKUP(E173,'HS Code'!$L$4:$O$65,2,0) -> Petroleum | G173: 33450910 | H173: 322 | I173: l | J173: 1343153 | K173: 1219997.2 | L173: 4.8780497e+08 | M173: Domestic Exports | N173: Customs
A174: 2024 | B174: 1 | D174: UGANDA | E174: 27101956 | F174: =VLOOKUP(E174,'HS Code'!$L$4:$O$65,2,0) -> Petroleum | G174: 33450960 | H174: 322 | I174: l | J174: 12800 | K174: 12800 | L174: 6329411.5 | M174: Domestic Exports | N174: Customs
A175: 2024 | B175: 1 | D175: UGANDA | E175: 27150000 | F175: =VLOOKUP(E175,'HS Code'!$L$4:$O$65,2,0) -> 0 | G175: 33543000 | H175: 22 | I175: kg | J175: 6045 | K175: 6045 | L175: 576150 | M175: Domestic Exports | N175: Customs
A176: 2024 | B176: 1 | D176: RWANDA | E176: 27101951 | F176: =VLOOKUP(E176,'HS Code'!$L$4:$O$65,2,0) -> Petroleum | G176: 33450910 | H176: 322 | I176: l | J176: 84116 | K176: 79297 | L176: 26307934 | M176: Domestic Exports | N176: Customs
A177: 2024 | B177: 1 | D177: UGANDA | E177: 27101951 | F177: =VLOOKUP(E177,'HS Code'!$L$4:$O$65,2,0) -> Petroleum | G177: 33450910 | H177: 322 | I177: l | J177: 131670 | K177: 117366 | L177: 41947580 | M177: Domestic Exports | N177: Customs
A178: 2024 | B178: 1 | D178: UGANDA | E178: 27129000 | F178: =VLOOKUP(E178,'HS Code'!$L$4:$O$65,2,0) -> 0 | G178: 33512900 | H178: 22 | I178: kg | J178: 120 | K178: 120 | L178: 82738.536 | M178: Domestic Exports | N178: Customs
A179: 2024 | B179: 1 | D179: AUSTRALIA | E179: 27121000 | F179: =VLOOKUP(E179,'HS Code'!$L$4:$O$65,2,0) -> 0 | G179: 33511000 | H179: 22 | I179: kg | J179: 2090 | K179: 2090 | L179: 2056809.1 | M179: Domestic Exports | N179: Customs
A180: 2024 | B180: 1 | D180: OTHER COUNTRIES N.E.S | E180: 27121000 | F180: =VLOOKUP(E180,'HS Code'!$L$4:$O$65,2,0) -> 0 | G180: 33511000 | H180: 22 | I180: kg | J180: 600 | K180: 600 | L180: 543590 | M180: Domestic Exports | N180: Customs
A181: 2024 | B181: 1 | D181: SIERRA LEONE | E181: 27030000 | F181: =VLOOKUP(E181,'HS Code'!$L$4:$O$65,2,0) -> Coal and Coke | G181: 32230000 | H181: 31 | I181: kg | J181: 27 | K181: 27 | L181: 8000 | M181: Domestic Exports | N181: Customs | P181: =L181/J181 -> 296.2963
A182: 2024 | B182: 1 | D182: SOUTH SUDAN | E182: 27101951 | F182: =VLOOKUP(E182,'HS Code'!$L$4:$O$65,2,0) -> Petroleum | G182: 33450910 | H182: 322 | I182: l | J182: 83538 | K182: 83538 | L182: 43959190 | M182: Domestic Exports | N182: Customs
A183: 2024 | B183: 1 | D183: SOUTH SUDAN | E183: 27101956 | F183: =VLOOKUP(E183,'HS Code'!$L$4:$O$65,2,0) -> Petroleum | G183: 33450960 | H183: 322 | I183: l | J183: 1400 | K183: 1400 | L183: 585904.99 | M183: Domestic Exports | N183: Customs
A184: 2024 | B184: 1 | D184: GERMANY | E184: 27101959 | F184: =VLOOKUP(E184,'HS Code'!$L$4:$O$65,2,0) -> Petroleum | G184: 33450990 | H184: 322 | I184: l | J184: 50 | K184: 50 | L184: 99109.6 | M184: Domestic Exports | N184: Customs
A185: 2024 | B185: 1 | D185: CONGO, BRAZZAVILLE | E185: 27101951 | F185: =VLOOKUP(E185,'HS Code'!$L$4:$O$65,2,0) -> Petroleum | G185: 33450910 | H185: 322 | I185: l | J185: 29995 | K185: 29995 | L185: 11836697 | M185: Domestic Exports | N185: Customs
A186: 2024 | B186: 1 | D186: DEMOCRATIC REP OF CONGO | E186: 27101939 | F186: =VLOOKUP(E186,'HS Code'!$L$4:$O$65,2,0) -> Petroleum | G186: 33440900 | H186: 322 | I186: l | J186: 2000 | K186: 2000 | L186: 135876.06 | M186: Domestic Exports | N186: Customs
A187: 2024 | B187: 1 | D187: DEMOCRATIC REP OF CONGO | E187: 27101951 | F187: =VLOOKUP(E187,'HS Code'!$L$4:$O$65,2,0) -> Petroleum | G187: 33450910 | H187: 322 | I187: l | J187: 31378 | K187: 31378 | L187: 13115928 | M187: Domestic Exports | N187: Customs
A188: 2024 | B188: 1 | D188: DEMOCRATIC REP OF CONGO | E188: 27109900 | F188: =VLOOKUP(E188,'HS Code'!$L$4:$O$65,2,0) -> Petroleum | G188: 33499000 | H188: 322 | I188: l | J188: 22600 | K188: 22600 | L188: 10146000 | M188: Domestic Exports | N188: Customs
A189: 2024 | B189: 1 | D189: DEMOCRATIC REP OF CONGO | E189: 27121000 | F189: =VLOOKUP(E189,'HS Code'!$L$4:$O$65,2,0) -> 0 | G189: 33511000 | H189: 22 | I189: kg | J189: 27983 | K189: 27983 | L189: 9361836.6 | M189: Domestic Exports | N189: Customs
A190: 2024 | B190: 1 | D190: ETHIOPIA | E190: 27101951 | F190: =VLOOKUP(E190,'HS Code'!$L$4:$O$65,2,0) -> Petroleum | G190: 33450910 | H190: 322 | I190: l | J190: 92400 | K190: 92400 | L190: 36455282 | M190: Domestic Exports | N190: Customs
A191: 2024 | B191: 1 | D191: GERMANY | E191: 27101220 | F191: =VLOOKUP(E191,'HS Code'!$L$4:$O$65,2,0) -> Petroleum | G191: 33411220 | H191: 321 | I191: l | J191: 12 | K191: 12 | L191: 1084.85 | M191: Domestic Exports | N191: Customs | P191: =L191/J191 -> 90.404167
A192: 2024 | B192: 1 | D192: GERMANY | E192: 27101939 | F192: =VLOOKUP(E192,'HS Code'!$L$4:$O$65,2,0) -> Petroleum | G192: 33440900 | H192: 322 | I192: l | J192: 10 | K192: 10 | L192: 1049.86 | M192: Domestic Exports | N192: Customs
A193: 2024 | B193: 1 | D193: GHANA | E193: 27101951 | F193: =VLOOKUP(E193,'HS Code'!$L$4:$O$65,2,0) -> Petroleum | G193: 33450910 | H193: 322 | I193: l | J193: 25059 | K193: 25059 | L193: 8962678.8 | M193: Domestic Exports | N193: Customs
A194: 2024 | B194: 1 | D194: MADAGASCAR | E194: 27101951 | F194: =VLOOKUP(E194,'HS Code'!$L$4:$O$65,2,0) -> Petroleum | G194: 33450910 | H194: 322 | I194: l | J194: 5 | K194: 5 | L194: 3197.08 | M194: Domestic Exports | N194: Customs
A195: 2024 | B195: 1 | D195: MALAWI | E195: 27101951 | F195: =VLOOKUP(E195,'HS Code'!$L$4:$O$65,2,0) -> Petroleum | G195: 33450910 | H195: 322 | I195: l | J195: 46474.05 | K195: 46474.05 | L195: 17433125 | M195: Domestic Exports | N195: Customs
A196: 2024 | B196: 1 | D196: MALI | E196: 27101951 | F196: =VLOOKUP(E196,'HS Code'!$L$4:$O$65,2,0) -> Petroleum | G196: 33450910 | H196: 322 | I196: l | J196: 4 | K196: 4 | L196: 6413.85 | M196: Domestic Exports | N196: Customs
A197: 2024 | B197: 1 | D197: MALI | E197: 27101952 | F197: =VLOOKUP(E197,'HS Code'!$L$4:$O$65,2,0) -> Petroleum | G197: 33450920 | H197: 322 | I197: kg | J197: 5 | K197: 5 | L197: 8017.31 | M197: Domestic Exports | N197: Customs
A198: 2024 | B198: 1 | D198: RWANDA | E198: 27101240 | F198: =VLOOKUP(E198,'HS Code'!$L$4:$O$65,2,0) -> White spirit and special boiling point industrial spirits | G198: 33411240 | H198: 321 | I198: l | J198: 270 | K198: 270 | L198: 277274.35 | M198: Domestic Exports | N198: Customs | P198: =L198/J198 -> 1026.942
A199: 2024 | B199: 1 | D199: SOMALIA | E199: 27101951 | F199: =VLOOKUP(E199,'HS Code'!$L$4:$O$65,2,0) -> Petroleum | G199: 33450910 | H199: 322 | I199: l | J199: 44028 | K199: 44028 | L199: 23555538 | M199: Domestic Exports | N199: Customs
A200: 2024 | B200: 1 | D200: SOMALIA | E200: 27101956 | F200: =VLOOKUP(E200,'HS Code'!$L$4:$O$65,2,0) -> Petroleum | G200: 33450960 | H200: 322 | I200: l | J200: 660 | K200: 660 | L200: 793519.31 | M200: Domestic Exports | N200: Customs
A201: 2024 | B201: 1 | D201: SOUTH SUDAN | E201: 27101951 | F201: =VLOOKUP(E201,'HS Code'!$L$4:$O$65,2,0) -> Petroleum | G201: 33450910 | H201: 322 | I201: l | J201: 161087.5 | K201: 161087.5 | L201: 75614938 | M201: Domestic Exports | N201: Customs
A202: 2024 | B202: 1 | D202: SOUTH SUDAN | E202: 27101952 | F202: =VLOOKUP(E202,'HS Code'!$L$4:$O$65,2,0) -> Petroleum | G202: 33450920 | H202: 322 | I202: kg | J202: 690 | K202: 690 | L202: 915206.14 | M202: Domestic Exports | N202: Customs
A203: 2024 | B203: 1 | D203: SOUTH SUDAN | E203: 27121000 | F203: =VLOOKUP(E203,'HS Code'!$L$4:$O$65,2,0) -> 0 | G203: 33511000 | H203: 22 | I203: kg | J203: 1010 | K203: 1010 | L203: 125000 | M203: Domestic Exports | N203: Customs
A204: 2024 | B204: 1 | D204: UNITED KINGDOM | E204: 27129000 | F204: =VLOOKUP(E204,'HS Code'!$L$4:$O$65,2,0) -> 0 | G204: 33512900 | H204: 22 | I204: kg | J204: 237 | K204: 237 | L204: 50490.37 | M204: Domestic Exports | N204: Customs
A205: 2024 | B205: 1 | D205: ZAMBIA | E205: 27101951 | F205: =VLOOKUP(E205,'HS Code'!$L$4:$O$65,2,0) -> Petroleum | G205: 33450910 | H205: 322 | I205: l | J205: 69634 | K205: 69634 | L205: 22916155 | M205: Domestic Exports | N205: Customs
A206: 2024 | B206: 1 | D206: ZIMBABWE | E206: 27101951 | F206: =VLOOKUP(E206,'HS Code'!$L$4:$O$65,2,0) -> Petroleum | G206: 33450910 | H206: 322 | I206: l | J206: 22040 | K206: 22040 | L206: 8564697.7 | M206: Domestic Exports | N206: Customs
A207: 2024 | B207: 1 | D207: MAURITIUS | E207: 27101951 | F207: =VLOOKUP(E207,'HS Code'!$L$4:$O$65,2,0) -> Petroleum | G207: 33450910 | H207: 322 | I207: l | J207: 6902 | K207: 6902 | L207: 2850244.1 | M207: Domestic Exports | N207: Customs
A208: 2024 | B208: 1 | D208: OTHER COUNTRIES N.E.S | E208: 27101951 | F208: =VLOOKUP(E208,'HS Code'!$L$4:$O$65,2,0) -> Petroleum | G208: 33450910 | H208: 322 | I208: l | J208: 3770.778 | K208: 3770.778 | L208: 2193774.9 | M208: Domestic Exports | N208: Customs
A209: 2024 | B209: 1 | D209: TANZANIA | E209: 27101951 | F209: =VLOOKUP(E209,'HS Code'!$L$4:$O$65,2,0) -> Petroleum | G209: 33450910 | H209: 322 | I209: l | J209: 1827 | K209: 1827 | L209: 850661.79 | M209: Domestic Exports | N209: Customs
A210: 2024 | B210: 1 | D210: AIRCRAFT & SHIPSTORES | E210: 27101921 | F210: =VLOOKUP(E210,'HS Code'!$L$4:$O$65,2,0) -> Petroleum | G210: 33421100 | H210: 322 | I210: l | J210: 4716 | K210: 4716 | L210: 773416.74 | M210: Re-Exports | N210: Customs
... A212: 2024 | B212: 1 | D212: RWANDA | E212: 27090000 | F212: =VLOOKUP(E212,'HS Code'!$L$4:$O$65,2,0) -> Petroleum | G212: 33300000 | H212: 31 | I212: kg | J212: 810 | K212: 810 | L212: 196020 | M212: Re-Exports | N212: Customs
A213: 2024 | B213: 1 | D213: CHINA | E213: 27101951 | F213: =VLOOKUP(E213,'HS Code'!$L$4:$O$65,2,0) -> Petroleum | G213: 33450910 | H213: 322 | I213: l | J213: 200 | K213: 200 | L213: 78532.11 | M213: Imports | N213: Customs | P213: =L213/J213 -> 392.66055
A214: 2024 | B214: 2 | D214: UNITED ARAB EMIRATES | E214: 27132000 | F214: =VLOOKUP(E214,'HS Code'!$L$4:$O$65,2,0) -> 0 | G214: 33541100 | H214: 22 | I214: kg | J214: 676952 | K214: 676952 | L214: 59224604 | M214: Imports | N214: Customs | P214: =L214/J214 -> 87.487154
A215: 2024 | B215: 2 | D215: UNITED ARAB EMIRATES | E215: 27150000 | F215: =VLOOKUP(E215,'HS Code'!$L$4:$O$65,2,0) -> 0 | G215: 33543000 | H215: 22 | I215: kg | J215: 17272 | K215: 17272 | L215: 3287891 | M215: Imports | N215: Customs | P215: =L215/J215 -> 190.3596
A216: 2024 | B216: 2 | D216: IRAN | E216: 27132000 | F216: =VLOOKUP(E216,'HS Code'!$L$4:$O$65,2,0) -> 0 | G216: 33541100 | H216: 22 | I216: kg | J216: 1193670 | K216: 1193670 | L216: 91553714 | M216: Imports | N216: Customs | P216: =L216/J216 -> 76.699351
A217: 2024 | B217: 2 | D217: UNITED ARAB EMIRATES | E217: 27101951 | F217: =VLOOKUP(E217,'HS Code'!$L$4:$O$65,2,0) -> Petroleum | G217: 33450910 | H217: 322 | I217: l | J217: 113815.5 | K217: 127351.78 | L217: 37230032 | M217: Imports | N217: Customs | P217: =L217/J217 -> 327.10862
A218: 2024 | B218: 2 | D218: UNITED ARAB EMIRATES | E218: 27101952 | F218: =VLOOKUP(E218,'HS Code'!$L$4:$O$65,2,0) -> Petroleum | G218: 33450920 | H218: 322 | I218: kg | J218: 22377 | K218: 22377 | L218: 10358721 | M218: Imports | N218: Customs | P218: =L218/J218 -> 462.91821
A219: 2024 | B219: 2 | D219: UNITED ARAB EMIRATES | E219: 27101955 | F219: =VLOOKUP(E219,'HS Code'!$L$4:$O$65,2,0) -> Petroleum | G219: 33450950 | H219: 322 | I219: l | J219: 72000 | K219: 60408 | L219: 10019378 | M219: Imports | N219: Customs | P219: =L219/J219 -> 139.15803
A220: 2024 | B220: 2 | D220: UNITED ARAB EMIRATES | E220: 27101956 | F220: =VLOOKUP(E220,'HS Code'!$L$4:$O$65,2,0) -> Petroleum | G220: 33450960 | H220: 322 | I220: l | J220: 59215 | K220: 65216 | L220: 15514936 | M220: Imports | N220: Customs | P220: =L220/J220 -> 262.01024
A221: 2024 | B221: 2 | D221: UNITED ARAB EMIRATES | E221: 27101957 | F221: =VLOOKUP(E221,'HS Code'!$L$4:$O$65,2,0) -> Petroleum | G221: 33450970 | H221: 322 | I221: l | J221: 275352 | K221: 259628 | L221: 44587867 | M221: Imports | N221: Customs | P221: =L221/J221 -> 161.93043
A222: 2024 | B222: 2 | D222: UNITED ARAB EMIRATES | E222: 27101959 | F222: =VLOOKUP(E222,'HS Code'!$L$4:$O$65,2,0) -> Petroleum | G222: 33450990 | H222: 322 | I222: l | J222: 95820 | K222: 90650 | L222: 17679579 | M222: Imports | N222: Customs | P222: =L222/J222 -> 184.50823
A223: 2024 | B223: 2 | D223: UNITED ARAB EMIRATES | E223: 27129000 | F223: =VLOOKUP(E223,'HS Code'!$L$4:$O$65,2,0) -> 0 | G223: 33512900 | H223: 22 | I223: kg | J223: 19661 | K223: 19661 | L223: 3801323.1 | M223: Imports | N223: Customs | P223: =L223/J223 -> 193.34332
A224: 2024 | B224: 2 | D224: UNITED ARAB EMIRATES | E224: 27132000 | F224: =VLOOKUP(E224,'HS Code'!$L$4:$O$65,2,0) -> 0 | G224: 33541100 | H224: 22 | I224: kg | J224: 991908 | K224: 991908 | L224: 63672320 | M224: Imports | N224: Customs | P224: =L224/J224 -> 64.19176
... A394: 2024 | B394: 2 | D394: TURKEY | E394: 27101942 | F394: =VLOOKUP(E394,'HS Code'!$L$4:$O$65,2,0) -> Petroleum | G394: 33450200 | H394: 322 | I394: l | J394: 12386800 | K394: 11562640 | L394: 1.0811075e+09 | M394: Imports | N394: Customs | P394: =L394/J394 -> 87.279
A395: 2024 | B395: 2 | D395: DEMOCRATIC REP OF CONGO | E395: 27150000 | F395: =VLOOKUP(E395,'HS Code'!$L$4:$O$65,2,0) -> 0 | G395: 33543000 | H395: 22 | I395: kg | J395: 43440 | K395: 43440 | L395: 1906499.9 | M395: Re-Exports | N395: Customs
A396: 2024 | B396: 2 | D396: SOUTH SUDAN | E396: 27150000 | F396: =VLOOKUP(E396,'HS Code'!$L$4:$O$65,2,0) -> 0 | G396: 33543000 | H396: 22 | I396: kg | J396: 677920 | K396: 677920 | L396: 29752634 | M396: Re-Exports | N396: Customs
A397: 2024 | B397: 2 | D397: AIRCRAFT & SHIPSTORES | E397: 27101921 | F397: =VLOOKUP(E397,'HS Code'!$L$4:$O$65,2,0) -> Petroleum | G397: 33421100 | H397: 322 | I397: l | J397: 80382253 | K397: 63757465 | L397: 8.2214048e+09 | M397: Re-Exports | N397: Customs
A398: 2024 | B398: 2 | D398: AIRCRAFT & SHIPSTORES | E398: 27101931 | F398: =VLOOKUP(E398,'HS Code'!$L$4:$O$65,2,0) -> Petroleum | G398: 33430100 | H398: 322 | I398: l | J398: 560819 | K398: 462000 | L398: 57715350 | M398: Re-Exports | N398: Customs
A399: 2024 | B399: 2 | D399: AIRCRAFT & SHIPSTORES | E399: 27101931 | F399: =VLOOKUP(E399,'HS Code'!$L$4:$O$65,2,0) -> Petroleum | G399: 33430100 | H399: 322 | I399: l | J399: 526471 | K399: 441000 | L399: 58836630 | M399: Re-Exports | N399: Customs
A400: 2024 | B400: 2 | D400: AIRCRAFT & SHIPSTORES | E400: 27101921 | F400: =VLOOKUP(E400,'HS Code'!$L$4:$O$65,2,0) -> Petroleum | G400: 33421100 | H400: 322 | I400: l | J400: 34982934 | K400: 27214257 | L400: 3.3355447e+09 | M400: Re-Exports | N400: Customs
A401: 2024 | B401: 2 | D401: OTHER COUNTRIES N.E.S | E401: 27101931 | F401: =VLOOKUP(E401,'HS Code'!$L$4:$O$65,2,0) -> Petroleum | G401: 33430100 | H401: 322 | I401: l | J401: 616906 | K401: 516468 | L401: 67991534 | M401: Re-Exports | N401: Customs
A402: 2024 | B402: 2 | D402: AIRCRAFT & SHIPSTORES | E402: 27101921 | F402: =VLOOKUP(E402,'HS Code'!$L$4:$O$65,2,0) -> Petroleum | G402: 33421100 | H402: 322 | I402: l | J402: 7264479 | K402: 5675317 | L402: 6.9328555e+08 | M402: Re-Exports | N402: Customs
A403: 2024 | B403: 2 | D403: RWANDA | E403: 27101951 | F403: =VLOOKUP(E403,'HS Code'!$L$4:$O$65,2,0) -> Petroleum | G403: 33450910 | H403: 322 | I403: l | J403: 10 | K403: 12 | L403: 7870.3114 | M403: Re-Exports | N403: Customs
A404: 2024 | B404: 2 | D404: BURUNDI | E404: 27101951 | F404: =VLOOKUP(E404,'HS Code'!$L$4:$O$65,2,0) -> Petroleum | G404: 33450910 | H404: 322 | I404: l | J404: 40 | K404: 40 | L404: 11668.407 | M404: Domestic Exports | N404: Customs
A405: 2024 | B405: 2 | D405: BURUNDI | E405: 27101959 | F405: =VLOOKUP(E405,'HS Code'!$L$4:$O$65,2,0) -> Petroleum | G405: 33450990 | H405: 322 | I405: l | J405: 441 | K405: 441 | L405: 8030.93 | M405: Domestic Exports | N405: Customs
A406: 2024 | B406: 2 | D406: RWANDA | E406: 27030000 | F406: =VLOOKUP(E406,'HS Code'!$L$4:$O$65,2,0) -> Coal and Coke | G406: 32230000 | H406: 31 | I406: kg | J406: 600 | K406: 600 | L406: 68750.255 | M406: Domestic Exports | N406: Customs | P406: =L406/J406 -> 114.58376
...

Sheet Table 9.1
A1: Table 9.1 Quantity and Value of Imports, Exports and Re-exports of Petroleum Products, 2020-2024
A2: Petroleum Products | B2: Quantity ('000 Tonnes) | G2: Value (KSh Million) | M2: Unit value (KSh/TJ)
B3: 2020 | C3: 2021 | D3: 2022 | E3: 2023 | F3: 2024* | G3: 2020 | H3: 2021 | I3: 2022 | J3: 2023 | K3: 2024* | M3: 2020 | N3: 2021 | O3: 2022 | P3: 2023 | Q3: 2024
A4: IMPORTS
A5: Petroleum Fuels 1 ……………. | B5: 5723 | C5: 6409.3 | D5: 5924.8 | E5: 4287.4 | F5: 5230.6 | G5: 206826 | H5: 345447.2 | I5: 625585.6 | J5: 623335.1 | K5: 573251.8 | M5: =(G5*1000000)/(B5*1000*(Conversions!$E$19/1000)) -> 8637532.8 | N5: =(H5*1000000)/(C5*1000*(Conversions!$E$19/1000)) -> 12881885 | O5: =(I5*1000000)/(D5*1000*(Conversions!$E$19/1000)) -> 25236050 | P5: =(J5*1000000)/(E5*1000*(Conversions!$E$19/1000)) -> 34748487 | Q5: =(K5*1000000)/(F5*1000*(Conversions!$E$19/1000)) -> 26194025
A6: Lubricating Oils ……….. | B6: 9.4 | C6: 9.2 | D6: 6 | E6: 5.6 | F6: 5.3 | G6: 1796.3 | H6: 2046.9 | I6: 1976.2 | J6: 2372.5 | K6: 1638.3 | M6: =(G6*1000000)/(B6*1000*(Conversions!$E$19/1000)) -> 45672979 | N6: =(H6*1000000)/(C6*1000*(Conversions!$E$19/1000)) -> 53176178 | O6: =(I6*1000000)/(D6*1000*(Conversions!$E$19/1000)) -> 78720523 | P6: =(J6*1000000)/(E6*1000*(Conversions!$E$19/1000)) -> 1.0125734e+08 | Q6: =(K6*1000000)/(F6*1000*(Conversions!$E$19/1000)) -> 73879830
A7: Lubricating Greases ……… | B7: 2.7 | C7: 3.4 | D7: 2.7 | E7: 2.3 | F7: 2.6 | G7: 510 | H7: 812.9 | I7: 823.6 | J7: 689.1 | K7: 635.1 | M7: =(G7*1000000)/(B7*1000*(Conversions!$E$19/1000)) -> 45145528 | N7: =(H7*1000000)/(C7*1000*(Conversions!$E$19/1000)) -> 57143460 | O7: =(I7*1000000)/(D7*1000*(Conversions!$E$19/1000)) -> 72905602 | P7: =(J7*1000000)/(E7*1000*(Conversions!$E$19/1000)) -> 71608197 | Q7: =(K7*1000000)/(F7*1000*(Conversions!$E$19/1000)) -> 58381747
A8: TOTAL | B8: 5735.1 | C8: 6421.9 | D8: 5933.5 | E8: 4295.3 | F8: 5238.5 | G8: 209132.3 | H8: 348307 | I8: 628385.5 | J8: 626396.7 | K8: 575525.3
A9: DOMESTIC EXPORTS
A10: Petroleum Fuels 1 ……………. | B10: 2.3 | C10: 0.4 | D10: 8 | E10: 9.5 | F10: 7.7 | G10: 169.5 | H10: 35.8 | I10: 297.5 | J10: 976.5 | K10: 831.4
A11: Lubricating Oils ……… | B11: 25.8 | C11: 22.4 | D11: 24.2 | E11: 29.1 | F11: 37.4 | G11: 5001.3 | H11: 5210.9 | I11: 7817.7 | J11: 11224.6 | K11: 12962.7
A12: Lubricating Greases ……… | B12: 0.1 | C12: 0.1 | D12: 0 | E12: 0.1 | F12: 0.1 | G12: 19 | H12: 16.6 | I12: 22.3 | J12: 37.1 | K12: 38
A13: TOTAL……………….. | B13: 28.2 | C13: 22.9 | D13: 32.3 | E13: 38.7 | F13: 45.2 | G13: 5189.8 | H13: 5263.3 | I13: 8137.6 | J13: 12238.2 | K13: 13832
A14: RE-EXPORTS
A15: Petroleum Fuels 1 ……………. | B15: 802.7 | C15: 581.7 | D15: 471.2 | E15: 271.2 | F15: 950 | G15: 37145.8 | H15: 22848.9 | I15: 41635.2 | J15: 37397.8 | K15: 128338.9 | M15: =(G15*1000000)/(B15*1000*(Conversions!$E$19/1000)) -> 11060246 | N15: =(H15*1000000)/(C15*1000*(Conversions!$E$19/1000)) -> 9388031.9 | O15: =(I15*1000000)/(D15*1000*(Conversions!$E$19/1000)) -> 21118531 | P15: =(J15*1000000)/(E15*1000*(Conversions!$E$19/1000)) -> 32958292 | Q15: =(K15*1000000)/(F15*1000*(Conversions!$E$19/1000)) -> 32288140
A16: Lubricating Oils ……… | B16: 1.3 | C16: 6.3 | D16: 0.7 | E16: 0.3 | F16: 0.2 | G16: 241.4 | H16: 1430.4 | I16: 212.2 | J16: 117 | K16: 86.3 | M16: =(G16*1000000)/(B16*1000*(Conversions!$E$19/1000)) -> 44381527 | N16: =(H16*1000000)/(C16*1000*(Conversions!$E$19/1000)) -> 54265683 | O16: =(I16*1000000)/(D16*1000*(Conversions!$E$19/1000)) -> 72452882 | P16: =(J16*1000000)/(E16*1000*(Conversions!$E$19/1000)) -> 93212237 | Q16: =(K16*1000000)/(F16*1000*(Conversions!$E$19/1000)) -> 1.0313098e+08
A17: Lubricating Greases …….. | B17: 0 | C17: 0 | D17: 0 | E17: 0 | F17: 0 | G17: 3.5 | H17: 0 | I17: 1.1 | J17: 1.9 | K17: 0.2 | M17: =(G17*1000000)/(B17*1000*(Conversions!$E$19/1000)) -> #DIV/0! | N17: =(H17*1000000)/(C17*1000*(Conversions!$E$19/1000)) -> #DIV/0! | O17: =(I17*1000000)/(D17*1000*(Conversions!$E$19/1000)) -> #DIV/0! | P17: =(J17*1000000)/(E17*1000*(Conversions!$E$19/1000)) -> #DIV/0! | Q17: =(K17*1000000)/(F17*1000*(Conversions!$E$19/1000)) -> #DIV/0!
A18: TOTAL……………….. | B18: 803.9 | C18: 587.9 | D18: 472 | E18: 271.5 | F18: 950.2 | G18: 37390.7 | H18: 24279.3 | I18: 41848.4 | J18: 37516.6 | K18: 128425.4
A19: TOTAL EXPORTS…… | B19: 832.1 | C19: 610.8 | D19: 504.2 | E19: 310.2 | F19: 995.4 | G19: 42580.5 | H19: 29542.6 | I19: 49986 | J19: 49754.8 | K19: 142257.4
A20: NET BALANCE2…… | G20: -166551.9 | H20: -318764.4 | I20: -578399.4 | J20: -576642 | K20: -433267.8
A21: *Provisional
A22: 1 Petroleum fuels refer to liquified petroleum gas, motor spirit premium, aviation spirit, jet fuel, illuminating kerosene, light and heavy diesel oils, and fuel oils.
A23: 2 Net balance refers to the difference in monetary value of a nation's exports and imports over a certain period.

Sheet Table 9.2
A1: Table 9.2 Petroleum Supply and Demand, 2020-2024
E2: ‘000 Tonnes
A3: Petroleum Fuels | B3: 2020 | C3: 2021 | D3: 2022 | E3: 2023 | F3: 2024*
A4: DEMAND -
A5: Liquefied Petroleum Gas …………...……………………. | B5: 326.2 | C5: 371.4 | D5: 333.8 | E5: 365.3 | F5: 414.9
A6: Motor gasoline (premium) ………………………………. | B6: 1395.3 | C6: 1554.4 | D6: 1561.3 | E6: 1446.6 | F6: 1492.6
A7: Aviation spirit …………………..…………………………………... | B7: 1.9 | C7: 1.4 | D7: 0.9 | E7: 1.3 | F7: 2.2
A8: Jet/turbo fuel ………………………..…………………………………. | B8: 394.8 | C8: 506.8 | D8: 592.3 | E8: 669 | F8: 735.5
A9: Illuminating kerosene ……………………………………………. | B9: 127 | C9: 111.3 | D9: 89 | E9: 55 | F9: 36.7
A10: Light diesel oil ……………………..………………………………. | B10: 2157.6 | C10: 2305.7 | D10: 2219.7 | E10: 2186.9 | F10: 2208.4
A11: Heavy diesel oil …………………..……………………………….. | B11: 1.8 | C11: 0.8 | D11: 0 | E11: 1.3 | F11: 0
A12: Fuel oil ………………………………………...………………………………. | B12: 273.9 | C12: 340.3 | D12: 337.1 | E12: 377 | F12: 309.2
A13: TOTAL DOMESTIC DEMAND…………………… | B13: 4678.5 | C13: 5192.1 | D13: 5134.1 | E13: 5102.4 | F13: 5199.4
A14: Exports of petroleum fuels ……………………………………………….… | B14: 2.3 | C14: 0.4 | D14: 8 | E14: 9.5 | F14: 7.7
A15: TOTAL DEMAND………………………………………………… | B15: 4680.8 | C15: 5192.5 | D15: 5142.1 | E15: 5111.9 | F15: 5207.1
A16: SUPPLY -
A17: Net imports of petroleum fuels …………………..………………………………… | B17: 4920.4 | C17: 5827.6 | D17: 5453.6 | E17: 4016.2 | F17: 4280.6
A18: Adjustment1 ……………………………………………………………………..…. | B18: 239.5 | C18: 635.1 | D18: 311.5 | E18: -1095.7 | F18: -926.5
A19: TOTAL SUPPLY…………………………………………………… | B19: 4680.8 | C19: 5192.5 | D19: 5142.1 | E19: 5111.9 | F19: 5207.1
A20: Source: Ministry of Energy and Petroleum; and Energy & Petroleum Regulatory Authority
A21: * Provisional.
A22: 1 Adjustment for inventory changes and losses

Sheet Table 9.3
A1: Chapter 3 Employment, Earnings and Consumer Price Indices Tables
F2: ‘000 Tonnes
A3: Category | B3: 2020 | C3: 2021 | D3: 2022 | E3: 2023 | F3: 2024*
A4: Agriculture .. .. .. .. .. .. .. .. ……... .. | B4: 24.8 | C4: 26.6 | D4: 29 | E4: 35.1 | F4: 42.8
A5: Retail pump outlets and road transport.. … … .. .. | B5: 3650.5 | C5: 3937.8 | D5: 3849.3 | E5: 3665.6 | F5: 3777.7
A6: Rail transport .. .. .. .. .. .. .. …….. .. .. .. .. | B6: 11.4 | C6: 19.4 | D6: 19 | E6: 15.1 | F6: 20
A7: Tourism1 .. .. .. .. .. .. …... .. .. .. .. .. .. | B7: 6.5 | C7: 6 | D7: 4.9 | E7: 4 | F7: 4.7
A8: Marine (excl. Naval Forces) .. .... .. .. .. .. | B8: 1.1 | C8: 2.1 | D8: 1.5 | E8: 8.5 | F8: 9.9
A9: Aviation (excl. Government) .. ... .. .. .. .. | B9: 392.7 | C9: 499.4 | D9: 570.3 | E9: 668.9 | F9: 722.9
A10: Power Generation .. .. .. .. .. .. .. ……. .. | B10: 75.8 | C10: 147.5 | D10: 189.9 | E10: 228.8 | F10: 129.6
A11: Industrial, Commercial and Other .. .. .. .. | B11: 494.4 | C11: 530.5 | D11: 446.3 | E11: 445.2 | F11: 457.1
A12: Government .. .. .. .. .. .. .. .. .. .. ….. .. .. | B12: 21.5 | C12: 22.8 | D12: 23.8 | E12: 31.2 | F12: 34.7
A13: TOTAL .. .. .. .. .. .. .. ………... .. | B13: 4678.5 | C13: 5192.1 | D13: 5134.1 | E13: 5102.4 | F13: 5199.4
A14: Source: Ministry of Petroleum and Mining; Energy & Petroleum Regulatory Authority
A15: * Provisional
A16: 1 Comprises sales to tour operators

Sheet Table 9.4
A1: Table 9.4 Wholesale Prices of Petroleum Fuels in Mombasa, December, 2020-2024
F2: KSh per Tonne
A3: Product | B3: 2020 | C3: 2021 | D3: 20222 | E3: 20232 | F3: 20242
A4: Motor spirit (premium).. .. .. .. .. .. | B4: 95000 | C4: 113166 | D4: 146068 | E4: 165788 | F4: 165378
A5: Illuminating kerosene.. .. ….. .. .. .. .. | B5: 71740 | C5: 87543 | D5: 115692 | E5: 153407 | F5: 152818
A6: Light diesel oil .. .. .. .. .. .. .. ……... | B6: 80010 | C6: 95925 | D6: 128362 | E6: 172390 | F6: 143031
A7: Source: Energy and Petroleum Regulatory Authority
A8: 1Prices include duties and VAT.
A9: 2 Applicable maximum wholesale prices not published. EPRA did not cap the wholesale price in 2022 as a result of the stabilisation of the retail pump prices. Assumed wholesale price is pump price less KSh 8.19 per litre

Sheet Table 9.5
A1: Table 9.5 Average Murban ADNOC_OPEC Reference Basket Prices, 2020-2024
F2: US$/BBL
A3: Month/Year | B3: 2020 | C3: 2021 | D3: 2022 | E3: 2023 | F3: 2024
A4: January………………. | B4: 66.09 | C4: 54.38 | D4: 85.41 | E4: 81.62 | F4: 80.04
A5: February…………….. | B5: 55.53 | C5: 61.05 | D5: 93.95 | E5: 81.88 | F5: 81.23
A6: March……………..… | B6: 33.92 | C6: 64.56 | D6: 113.48 | E6: 78.45 | F6: 84.22
A7: April…………………. | B7: 17.66 | C7: 63.24 | D7: 105.64 | E7: 84.13 | F7: 89.12
A8: May…………...…….. | B8: 25.17 | C8: 66.91 | D8: 113.87 | E8: 75.82 | F8: 83.59
A9: June…………...……. | B9: 37.05 | C9: 71.89 | D9: 117.72 | E9: 75.19 | F9: 83.22
A10: July…………….……. | B10: 43.42 | C10: 73.53 | D10: 108.55 | E10: 81.06 | F10: 84.43
A11: August…………...….. | B11: 45.19 | C11: 70.33 | D11: 101.9 | E11: 87.33 | F11: 78.41
A12: September……..……. | B12: 41.54 | C12: 73.88 | D12: 95.32 | E12: 94.6 | F12: 73.59
A13: October……..……..… | B13: 40.08 | C13: 82.11 | D13: 93.62 | E13: 91.78 | F13: 74.45
A14: November………..….. | B14: 42.61 | C14: 80.37 | D14: 89.73 | E14: 84.92 | F14: 72.98
... A16: Annual average | B16: 41.45 | C16: 69.719167 | D16: 99.9 | E16: 82.981667 | F16: 79.8625
A17: Source : OPEC Monthly Oil Market Report
A18: US$/ BBL: US Dollar per Barrel
A19: 1 Abu Dhabi free on board (fob) Prices
A20: ADNOC: Abu Dhabi National Oil Company

Sheet Table 9.6
A1: Table 9.6 Average1 Retail Prices of Selected Petroleum Fuels, 2020-2024
A2: Year | B2: Month | C2: KSh per Litre | F2: KSh per 13 Kg cylinder | I2: Year | J2: Month | K2: KSh per TJ | N2: KSh per TJ
C3: Motor Spirit Premium | E3: Illuminating Kerosene | F3: Liqufied Petroleum Gas (LPG) | K3: Motor Spirit Premium | M3: Illuminating Kerosene | N3: Liqufied Petroleum Gas (LPG)
D4: Light Diesel Oil | L4: Light Diesel Oil
A5: 2020 | B5: January | C5: 110.61 | D5: 102.81 | E5: 104.46 | F5: 2144.81 | I5: 2020 | J5: January
B6: March | C6: 112.07 | D6: 102.93 | E6: 96.72 | F6: 2065.98 | J6: March
B7: June | C7: 90.34 | D7: 75.88 | E7: 63.79 | F7: 2078.5 | J7: June
B8: September | C8: 106.3 | D8: 95.45 | E8: 84.09 | F8: 2033.57 | J8: September
B9: December | C9: 107.69 | D9: 92.75 | E9: 84.5 | F9: 1977.36 | J9: December
B10: Annual Average | C10: 103.28 | D10: 93.96 | E10: 84.6 | F10: 2056.84 | J10: Annual Average
A11: 2021 | B11: January | C11: 107.86 | D11: 97.33 | E11: 88.07 | F11: 2018.93 | I11: 2021 | J11: January
B12: March | C12: 123.66 | D12: 108.58 | E12: 98.78 | F12: 2074.23 | J12: March
B13: June | C13: 127.98 | D13: 108.58 | E13: 98.78 | F13: 2074.23 | J13: June
B14: September | C14: 135.54 | D14: 116.51 | E14: 111.74 | F14: 2445.23 | J14: September
B15: December | C15: 130.54 | D15: 111.51 | E15: 106.46 | F15: 2638.83 | J15: December
B16: Annual Average | C16: 125.79 | D16: 108.56 | E16: 100.19 | F16: 2280.91 | J16: Annual Average
A17: 2022 | B17: January | C17: 130.54 | D17: 111.51 | E17: 106.46 | F17: 2659.24 | I17: 2022 | J17: January
B18: March | C18: 135.54 | D18: 116.51 | E18: 104.46 | F18: 2866.2 | J18: March
B19: June | C19: 159.94 | D19: 140.91 | E19: 128.86 | F19: 3218.22 | J19: June
B20: September | C20: 180.05 | D20: 165.91 | E20: 148.86 | F20: 3106.66 | J20: September
B21: December | C21: 178.05 | D21: 162.91 | E21: 146.86 | F21: 2980.8 | J21: December
B22: Annual Average | C22: 157.34 | D22: 139.69 | E22: 127.38 | F22: 2990.41 | J22: Annual Average
A23: 2023 | B23: January | C23: 178.05 | D23: 162.91 | E23: 146.86 | F23: 2961.93 | I23: 2023 | J23: January
B24: March | C24: 180.05 | D24: 162.91 | E24: 146.86 | F24: 3137.7 | J24: March
B25: June | C25: 182.63 | D25: 167.98 | E25: 162.19 | F25: 3069.01 | J25: June
B26: September | C26: 212.25 | D26: 201.73 | E26: 203.34 | F26: 2795.69 | J26: September
B27: December | C27: 212.97 | D27: 202.21 | E27: 199.78 | F27: 3032.62 | J27: December
B28: Annual Average | C28: 194.5 | D28: 180.33 | E28: 172.05 | F28: 2990.7 | J28: Annual Average
A29: 2024 | B29: January | C29: 207.97 | D29: 197.21 | E29: 194.96 | F29: 3055.51 | I29: 2024 | J29: January | K29: =C29/Conversions!$E$16 -> 6080994.2 | L29: =D29/Conversions!$E$7 -> 5508659.2 | M29: =E29/Conversions!$E$12 -> 5212834.2 | N29: =F29/Conversions!$E$14 -> 4700784.6
B30: February | C30: 206.97 | D30: 196.21 | E30: 193.96 | F30: 3187.1 | J30: February | K30: =C30/Conversions!$E$16 -> 6051754.4 | L30: =D30/Conversions!$E$7 -> 5480726.3 | M30: =E30/Conversions!$E$12 -> 5186096.3 | N30: =F30/Conversions!$E$14 -> 4903230.8
B31: March | C31: 199.77 | D31: 191.11 | E31: 189.48 | F31: 3231.84 | J31: March | K31: =C31/Conversions!$E$16 -> 5841228.1 | L31: =D31/Conversions!$E$7 -> 5338268.2 | M31: =E31/Conversions!$E$12 -> 5066310.2 | N31: =F31/Conversions!$E$14 -> 4972061.5
B32: April | C32: 194.46 | D32: 181.11 | E32: 171.18 | F32: 3242.11 | J32: April | K32: =C32/Conversions!$E$16 -> 5685964.9 | L32: =D32/Conversions!$E$7 -> 5058938.5 | M32: =E32/Conversions!$E$12 -> 4577005.3 | N32: =F32/Conversions!$E$14 -> 4987861.5
B33: May | C33: 193.46 | D33: 179.91 | E33: 169.52 | F33: 3221.29 | J33: May | K33: =C33/Conversions!$E$16 -> 5656725.1 | L33: =D33/Conversions!$E$7 -> 5025419 | M33: =E33/Conversions!$E$12 -> 4532620.3 | N33: =F33/Conversions!$E$14 -> 4955830.8
B34: June | C34: 190.46 | D34: 173.83 | E34: 163.82 | F34: 3213.97 | J34: June | K34: =C34/Conversions!$E$16 -> 5569005.8 | L34: =D34/Conversions!$E$7 -> 4855586.6 | M34: =E34/Conversions!$E$12 -> 4380213.9 | N34: =F34/Conversions!$E$14 -> 4944569.2
B35: July | C35: 189.46 | D35: 172.33 | E35: 162.52 | F35: 3219.58 | J35: July | K35: =C35/Conversions!$E$16 -> 5539766.1 | L35: =D35/Conversions!$E$7 -> 4813687.2 | M35: =E35/Conversions!$E$12 -> 4345454.5 | N35: =F35/Conversions!$E$14 -> 4953200
B36: August | C36: 189.46 | D36: 172.33 | E36: 162.52 | F36: 3217.85 | J36: August | K36: =C36/Conversions!$E$16 -> 5539766.1 | L36: =D36/Conversions!$E$7 -> 4813687.2 | M36: =E36/Conversions!$E$12 -> 4345454.5 | N36: =F36/Conversions!$E$14 -> 4950538.5
B37: September | C37: 189.46 | D37: 172.33 | E37: 159.1 | F37: 3196.04 | J37: September | K37: =C37/Conversions!$E$16 -> 5539766.1 | L37: =D37/Conversions!$E$7 -> 4813687.2 | M37: =E37/Conversions!$E$12 -> 4254010.7 | N37: =F37/Conversions!$E$14 -> 4916984.6
B38: October | C38: 181.33 | D38: 168.82 | E38: 152.18 | F38: 3183.29 | J38: October | K38: =C38/Conversions!$E$16 -> 5302046.8 | L38: =D38/Conversions!$E$7 -> 4715642.5 | M38: =E38/Conversions!$E$12 -> 4068984 | N38: =F38/Conversions!$E$14 -> 4897369.2
B39: November | C39: 181.33 | D39: 168.82 | E39: 152.18 | F39: 3147.66 | J39: November | K39: =C39/Conversions!$E$16 -> 5302046.8 | L39: =D39/Conversions!$E$7 -> 4715642.5 | M39: =E39/Conversions!$E$12 -> 4068984 | N39: =F39/Conversions!$E$14 -> 4842553.8
B40: December | C40: 176.96 | D40: 165.82 | E40: 149.18 | F40: 3143.85 | J40: December | K40: =C40/Conversions!$E$16 -> 5174269 | L40: =D40/Conversions!$E$7 -> 4631843.6 | M40: =E40/Conversions!$E$12 -> 3988770.1 | N40: =F40/Conversions!$E$14 -> 4836692.3
B41: Annual Average | C41: 191.76 | D41: 178.32 | E41: 168.38 | F41: 3188.34 | J41: Annual Average | K41: =AVERAGE(K29:K40) -> 5606944.4 | L41: =AVERAGE(L29:L40) -> 4980982.3 | M41: =AVERAGE(M29:M40) -> 4502228.2 | N41: =AVERAGE(N29:N40) -> 4905139.7
A42: 1 Twelve month average | I42: 1 Twelve month average

Sheet Table 9.7
A1: Table 9.7 Installed and Effective Capacity of Electricity by Source as at 31st December, 2020-2024
Q2: MW
B3: INSTALLED CAPACITY | J3: EFFECTIVE CAPACITY
B4: Hydro | C4: Thermal Oil | D4: Geo thermal | F4: Co- gene- ration | G4: Solar | H4: Ethiopia HVDC | I4: Total | J4: Hydro | K4: Thermal Oil | L4: Geo thermal | N4: Co- gene- ration | O4: Solar | P4: Ethiopia HVDC | Q4: Total
A5: Year | E5: Wind | M5: Wind
A6: 2020 | B6: 834 | C6: 749.1 | D6: 863.1 | E6: 336.1 | F6: 2 | G6: 52.5 | I6: 2836.7 | J6: 805 | K6: 715.5 | L6: 805.1 | M6: 325.5 | N6: 2 | O6: 52.2 | Q6: 2705.3
A7: 2021 | B7: 838.1 | C7: 677.8 | D7: 863.1 | E7: 436.1 | F7: 2 | G7: 172.5 | I7: 2989.6 | J7: 809.1 | K7: 643.7 | L7: 805.1 | M7: 425.5 | N7: 2 | O7: 172.2 | Q7: 2857.6
A8: 2022 | B8: 838.9 | C8: 681.9 | D8: 950 | E8: 436.1 | F8: 2 | G8: 212.5 | H8: 200 | I8: 3321.3 | J8: 809.9 | K8: 645.5 | L8: 871.1 | M8: 425.5 | N8: 2 | O8: 212.2 | P8: 200 | Q8: 3166.2
A9: 2023 | B9: 839.3 | C9: 613.8 | D9: 940 | E9: 436.1 | F9: 2 | G9: 212.5 | H9: 200 | I9: 3243.6 | J9: 810.4 | K9: 586.6 | L9: 876.1 | M9: 425.5 | N9: 2 | O9: 212.2 | P9: 200 | Q9: 3112.7
A10: 2024* | B10: 839.2 | C10: 605.8 | D10: 940 | E10: 436.1 | F10: 2 | G10: 212.5 | H10: 200 | I10: 3235.5 | J10: 809.7 | K10: 582.6 | L10: 876.1 | M10: 425.5 | N10: 2 | O10: 211.9 | P10: 200 | Q10: 3107.8
A11: Source: Kenya Power & Lighting Company Ltd and Kenya Electricity Generation Company Ltd
A12: * Provisional
A13: Notes:
A14: 1. 1 Megawatt = 1,000 kilowatts = 1,000,000 watts
A15: 2. Installed capacity refers to the maximum theoretical electric output a power station could produce when operating at 100 per cent
A16: 3. Effective capacity refers to the maximum electric output a power station is expected to achieve given current operating constraints
A17: 4. HVDC: High Voltage Direct Current
A18: 5. HVDC commenced in 2022

Sheet Table 9.8
A1: Table 9.8 Generation and Imports of Electricity, 2020-2024
K2: GWh
C3: GENERATION | J3: IMPORTS | K3: TOTAL
B4: Hydro | C4: Thermal oil | F4: Geo thermal | G4: Co- gene- ration | H4: Wind | I4: Solar
A5: Year | C5: KenGen | D5: IPPs and Off-Grid | E5: Total
A6: 2020 | B6: 4232.6603 | C6: 120.58344 | D6: 633.91755 | E6: 754.50099 | F6: 5059.7817 | G6: 0.181606 | H6: 1331.3607 | I6: 88.418894 | J6: 136.67957 | K6: =B6+E6+F6+G6+H6+I6+J6 -> 11603.584
A7: 2021 | B7: 3674.9899 | C7: 434.32539 | D7: 760.0221 | E7: 1262.0171 | F7: 5037.0477 | G7: 0.464559 | H7: 1984.7964 | I7: 167.41781 | J7: 287.96138 | K7: =B7+E7+F7+G7+H7+I7+J7 -> 12414.695
A8: 2022 | B8: 3039.8756 | C8: 494.9 | D8: 1090.0216 | E8: 1584.9216 | F8: 5517.5492 | G8: 0.268151 | H8: 2143.0313 | I8: 383.72196 | J8: 316.00193 | K8: =B8+E8+F8+G8+H8+I8+J8 -> 12985.37
A9: 2023 | B9: 2666.6819 | C9: 353.46234 | D9: 952.19557 | E9: 1305.6579 | F9: 6032.0808 | G9: 0.2044591 | H9: 2008.1385 | I9: 491.4648 | J9: 919.32733 | K9: =B9+E9+F9+G9+H9+I9+J9 -> 13423.556
A10: 2024* | B10: 3630.6884 | C10: 411.18557 | D10: 718.29272 | E10: 1129.4783 | F10: 5551.0081 | G10: 0.0169487 | H10: 1797.6717 | I10: 460.44289 | J10: 1532.6243 | K10: =B10+E10+F10+G10+H10+I10+J10 -> 14101.931
A11: Source: Kenya Power & Lighting Company Ltd and Kenya Electricity Generation Company Ltd
A12: * Provisional
A13: Notes:
A14: IPP: Independent Power Producers
A15: 1 Gigawatt hour = 1,000,000 kilowatt hours

Sheet Table 9.9
A1: Table 9.9 Licensed Captive Power Capacities1 by Type of Technology, 2020-2024
F2: MW
A3: Type of Technology | B3: 2020 | C3: 2021 | D3: 2022 | E3: 2023 | F3: 2024*
A4: Hydro | B4: 26 | C4: 28.3 | D4: 32.4 | E4: 30.2 | F4: 30.2
A5: Coal | B5: 30 | C5: 30 | D5: 30 | E5: 30 | F5: 30
A6: Cogeneration | B6: 32 | C6: 32 | D6: 32 | E6: 32 | F6: 32
A7: Waste Heat Recovery | B7: 0 | C7: 28.5 | D7: 83.5 | E7: 83.5 | F7: 83.5
A8: Bagasse | B8: 15.7 | C8: 60.2 | D8: 60.2 | E8: 60.2 | F8: 60.2
A9: Solar | B9: 35 | C9: 35 | D9: 46.3 | E9: 88.2 | F9: 88.2
A10: Biomass | B10: 1.5 | C10: 2.9 | D10: 2.9 | E10: 19.5 | F10: 19.5
A11: Thermal | B11: 18.5 | C11: 46.1 | D11: 53.9 | E11: 42.9 | F11: 42.9
A12: Biogas | B12: 2.6 | C12: 2.8 | D12: 2.8 | E12: 0.2 | F12: 0.2
A13: Biothermal | B13: - | C13: - | D13: 2.1 | E13: 0 | F13: 0
A14: Geothermal | B14: 3.7 | C14: 3.7 | D14: 3.7 | E14: 3.7 | F14: 3.7
A15: Total | B15: 165 | C15: 269.5 | D15: 349.8 | E15: 390.4 | F15: 390.4
A16: * Provisional
A17: 1 These are the stock of available capacities in the country which are cumulative in nature
A18: Note: Captive power capacities is the capacity of an autoproducer to generate electricity exceeding 1MW, within their facility which is then used and managed by the autoproducer for their own energy consumption.

Sheet Table 9.10
A1: Table 9.10 Electricity Demand and Supply, 2020-2024
F2: GWh
A3: Category | B3: 2020 | C3: 2021 | D3: 2022 | E3: 2023 | F3: 2024*
A4: Domestic and Small Commercial .. .. .. .. .. .. ……….. | B4: 3829.1 | C4: 4088.6 | D4: 4291.5 | E4: 4252.4 | F4: 4459.1
A5: Large & Medium (Commercial and Industrial).. ….. | B5: 4281 | C5: 4728.4 | D5: 4958.2 | E5: 5299.8 | F5: 5515.2
A6: E-mobility ................................................... | F6: 2.8
A7: Street Lighting .. .. .. .. .. .. ……………………… | B7: 74.5 | C7: 99.6 | D7: 94.2 | E7: 109.1 | F7: 89.9
A8: Rural Electrification .. .. .. .. .. ………………….. .. .. | B8: 611.9 | C8: 648.8 | D8: 664.47 | E8: 659.36 | F8: 684.79
A9: TOTAL DOMESTIC DEMAND……………….. | B9: 8796.4 | C9: 9565.4 | D9: 10008.4 | E9: 10320.6 | F9: 10751.7
A10: Exports to Uganda & Tanzania……………….. | B10: 16.5 | C10: 18.2 | D10: 21.3 | E10: 33.8 | F10: 42.8
A11: Transmission1 and Distribution losses | B11: 2790.7 | C11: 2831 | D11: 2955.7 | E11: 3069.2 | F11: 3307.4
A12: TOTAL DEMAND = TOTAL SUPPLY2……………… | B12: 11603.6 | C12: 12414.7 | D12: 12985.4 | E12: 13423.6 | F12: 14101.9
A13: Less imports from Uganda and Ethiopia ……. | B13: 136.7 | C13: 288 | D13: 316 | E13: 919.3 | F13: 1532.6
A14: Local generation .. …………………………… | B14: 11466.9 | C14: 12126.7 | D14: 12669.4 | E14: 12504.3 | F14: 12569.3
A15: Source: Kenya Power and Lighting Company Ltd
A16: *Provisional
A17: 1Voltage losses in power transmission lines
A18: 2Total supply equals Total generation and Imports
A19: Note
A20: 1. E-Mobility refers to the use of electric-powered vehicles and related technologies for transportation
A21: 2. E-mobility started in 2024

Sheet Table 9.11
A1: Table 9.11 Average electricity yield1 by Customer Category, 2019_20-2023_24 Financial Years
F2: KSh/Unit | H2: KSh/TJ
A3: Category | B3: 2019/20 | C3: 2020/21 | D3: 2021/22 | E3: 2022/23 | F3: 2023/24* | H3: 2023/24*
A4: Domestic...................... | B4: 17.51 | C4: 16.43 | D4: 16.9 | E4: 20.39 | F4: 24.97 | H4: =F4/Conversions!$E$22 -> 6936111.1
A5: Small Commercial ......... | B5: 20.25 | C5: 19.58 | D5: 20.22 | E5: 23.14 | F5: 27.52 | H5: =F5/Conversions!$E$22 -> 7644444.4
A6: Commercial Industrial .... | B6: 14.58 | C6: 16.37 | D6: 16.55 | E6: 19 | F6: 21.73 | H6: =F6/Conversions!$E$22 -> 6036111.1
A7: Street Lighting ............. | B7: 10.1 | C7: 9.83 | D7: 9.73 | E7: 9.56 | F7: 12.92 | H7: =F7/Conversions!$E$22 -> 3588888.9
A8: E-Mobility | F8: 19.35 | H8: =F8/Conversions!$E$22 -> 5375000
A9: Exports........................ | B9: 11.63 | C9: 14.34 | D9: 16.76 | E9: 20.88 | F9: 21.77 | H9: =F9/Conversions!$E$22 -> 6047222.2
A10: * Provisional
A11: Source: Kenya Power and Lighting Company Ltd
A12: 1 Electricity yield is defined as the average revenue received per unit of electricity sold
A13: Note
A14: 1. E-Mobility refers to the use of electric-powered vehicles and related technologies for transportation
A15: 2. E-mobility started in 2024

Sheet Table 9.12(a)
A1: Table 9.12(a) Energy Balance, 2024-Supply and Demand of Coal and Coke, and Renewable Feedstocks
F2: TJ
A3: Energy Products | B3: Coal and Coke | C3: Renewable feedstocks | F3: Sub-Total
C4: Wood charcoal | D4: Fuel wood, in logs, in billets, in twigs, in faggots or in similar forms | E4: Wastes or scraps
A5: Domestic Production | C5: 103322.53 | D5: 1195357.1 | E5: 42842.67 | F5: 1341522.4
A6: Imports | B6: 7409.66 | F6: 7409.66
A7: Domestic Exports | B7: 6.87 | F7: 6.87
A8: Re-Exports | B8: 0.52 | F8: 0.52
A9: Stock changes
A10: Sub-total: Supply | B10: 7402.27 | C10: 103322.53 | D10: 1195357.1 | E10: 42842.67 | F10: 1348924.6
A12: Statistical differences | B12: 3644.29 | C12: - | D12: - | E12: - | F12: 3644.29
A14: Sub-total: Demand | B14: 3757.98 | C14: 103322.53 | D14: 1195357.1 | E14: 42842.67 | F14: 1345280.3
A15: Industry | B15: 3757.98 | C15: 832.54 | D15: 7450.9 | E15: - | F15: 12041.42
A16: Households | B16: .. | C16: 102489.99 | D16: 1187906.2 | E16: 42842.67 | F16: 1333238.9
A17: 1 Terajoule (TJ)=10^12 Joules
A18: 1000 Tonnes=4.184 TJ
A19: 1 GWh=3.6 TJ
A20: ..Data not available

Sheet Table 9.12 (b)
A1: Table 9.12(b) Energy Balance, 2023-Supply and Demand of Electricity
H2: TJ
A3: Energy Products | B3: Power Generation | H3: Electicial energy distribution
B4: Hydro | C4: Geothermal | D4: Solar | E4: Wind | F4: Thermal | G4: Co-Generation
A5: Domestic Production | B5: 13070.48 | C5: 19983.63 | D5: 1657.59 | E5: 6471.62 | F5: 4066.13 | G5: 0.06 | H5: 45249.51
A6: Imports | H6: 5517.44
A7: Domestic Exports | H7: 154.09
A8: Sub-total: Supply | H8: 50612.86
A9: Statistical differences | H9: 11906.64
A10: Sub-total: Demand | H10: 38706.22
A12: Sub-total: Energy transformation | B12: 13070.48 | C12: 19983.63 | D12: 1657.59 | E12: 6471.62 | F12: 4066.13 | G12: 0.06 | H12: 45249.51
A13: Electricity plants (Kengen) | B13: 12838.45 | C13: 16032.19 | E13: 156.24 | F13: 1480.27 | H13: 30507.15
A14: Electricity plants (Independent Power Producers (IPPs) | B14: 232.03 | C14: 3951.44 | D14: 1360.98 | E14: 6315.37 | F14: 2260.44 | G14: 0.06 | H14: 14120.32
A15: Electricity plants (REREC) | D15: 295.62 | H15: 295.62
A16: Electricity plants (Off-grid)) | D16: 1 | F16: 325.42 | H16: 326.42
A17: Sub-total: Energy demand | H17: 38706.22
A18: Electricity by Category:
A19: Domestic | H19: 10343.87
A20: Small Commercial | H20: 5708.89
A21: Large and Medium Commercial | H21: 19854.57
A22: Street Lighting | H22: 323.47
A23: E-Mobility | H23: 10.17
A24: Rural Electrification | H24: 2465.26
A25: 1 Terajoule (TJ)=10^12 Joules
A26: 1000 Tonnes=4.184 TJ
A27: 1 GWh=3.6 TJ

Sheet Table 9.12(c)
A1: Table 9.12 (c) Energy Balance, 2024-Supply and Demand of Petroleum Fuels
M2: TJ
A3: Energy Products | B3: Liquid fuels | L3: Gas | M3: Sub-Total
B4: Motor Spirit (Premium) | C4: Aviation gasoline | D4: Jet fuel | E4: Illuminating Kerosene | F4: White spirit and special boiling point industrial spirits | G4: Light Diesel Oil | H4: Heavy Diesel Oil | I4: Fuel oils n.e.c. | J4: Lubricating Oils | K4: Lubricating Greases | L4: Liquified Petroleum Gas (L.P.G)
A5: Imports | B5: 5539.51 | C5: 5.21 | D5: 3156.84 | E5: 8.15 | F5: 13.84 | G5: 9979.63 | H5: 0.13 | I5: 1300.24 | J5: 22.16 | K5: 10.71 | L5: 1895.03 | M5: 21931.45
A6: Domestic Exports | B6: 2.2 | C6: 0.01 | D6: 1.66 | E6: - | F6: 0.22 | G6: 0.02 | H6: 0.01 | I6: 26.29 | J6: 156.41 | K6: 0.44 | L6: 1.82 | M6: 189.08
A7: Re-Exports | B7: 1.36 | C7: 0.25 | D7: 3838.02 | E7: - | G7: 75.79 | H7: - | I7: 55.64 | J7: 0.79 | K7: - | L7: 3.65 | M7: 3975.49
A8: Stock changes
A9: Sub-total: Supply | B9: 5535.95 | C9: 4.95 | D9: -682.84 | E9: 8.15 | F9: 13.62 | G9: 9903.82 | H9: 0.12 | I9: 1218.32 | J9: -135.05 | K9: 10.27 | L9: 1889.56 | M9: 17766.88
A11: Statistical differences | B11: -709.17 | C11: -4.1 | D11: -3760.07 | E11: -145.54 | F11: 13.62 | G11: 664.03 | H11: 0.12 | I11: -75.31 | J11: -135.05 | K11: 10.27 | L11: 153.79 | M11: -3987.42
A13: Sub-total: Energy demand | B13: 6245.13 | C13: 9.05 | D13: 3077.23 | E13: 153.69 | F13: - | G13: 9239.79 | H13: - | I13: 1293.63 | J13: - | K13: - | L13: 1735.78 | M13: 21754.31
A14: Agriculture | B14: 5.47 | C14: - | D14: - | E14: 0.01 | G14: 84.92 | I14: 1.85 | M14: 92.25
A15: Mining & Quarying | B15: 49.03 | C15: - | D15: - | E15: 1.49 | G15: 304.8 | I15: 41.98 | L15: 5.44 | M15: 402.75
A16: Manufacturing | B16: 83.56 | C16: - | D16: - | E16: 76.67 | G16: 884.4 | I16: 78.35 | L16: 212.93 | M16: 1335.9
A17: Electricity, Gas, Steam and Air Conditioning Supply | B17: 1.02 | C17: - | D17: - | E17: - | G17: 52.79 | I17: 252.1 | M17: 305.91
A18: Construction | B18: 40.74 | C18: - | D18: - | E18: 1.46 | G18: 563.3 | I18: 4.69 | L18: 0.92 | M18: 611.11
A19: Transport and Storage | B19: 4103.18 | C19: 8.62 | D19: 3056.37 | E19: 0.12 | F19: - | G19: 3529.8 | H19: - | I19: 859.69 | J19: - | K19: - | L19: 5.67 | M19: 11563.46
A20: Road Transport | B20: 2491.21 | C20: 4.97 | D20: 13.42 | E20: - | G20: 3110.07 | I20: 339.12 | M20: 5958.79
A21: Rail Transport | B21: 0.87 | C21: - | D21: - | E21: - | G21: 7.6 | I21: - | M21: 8.47
A22: Air Transport | B22: 0.13 | C22: 3.65 | D22: 3042.95 | E22: - | G22: 1.64 | I22: - | M22: 3048.38
A23: Other Transport | B23: 1610.96 | C23: - | D23: - | E23: 0.12 | G23: 410.49 | I23: 520.57 | L23: 5.67 | M23: 2547.81
A24: Accommodation and Food Service Activities | B24: 0.39 | C24: - | D24: - | E24: - | G24: 1.85 | I24: - | L24: 15.22 | M24: 17.46
A25: Other Commercial Sectors | B25: 1949.52 | C25: - | D25: - | E25: 53.76 | G25: 3765.77 | I25: 54.98 | L25: 1040.47 | M25: 6864.5
A26: Public Administration and Defense | B26: 12.21 | C26: 0.43 | D26: 20.86 | E26: - | G26: 52.16 | I26: - | M26: 85.66
A27: Households | B27: - | C27: - | D27: - | E27: 20.19 | G27: - | I27: - | L27: 455.12 | M27: 475.32
A28: 1 Terajoule (TJ)=10^12 Joules
A29: 1000 Tonnes=4.184 TJ

Sheet Table 9.13(a)
A1: Table 9.13(a) Physical Energy Supply Table, 2024
F2: TJ | G2: Use | I2: Statistical difference
A3: INDUSTRIES | B3: Industries | C3: Households | D3: Rest of the World | E3: Flows from the environment | F3: Total
A4: NATURAL INPUTS:
A5: Solar | E5: 1657.59 | F5: 1657.6 | G5: ='Table 9.13 (b)'!Q5 -> 1657.6 | I5: =F5-G5 -> 0
A6: Wind | E6: 6471.62 | F6: 6471.6 | G6: ='Table 9.13 (b)'!Q6 -> 6471.6 | I6: =F6-G6 -> 0
A7: Hydro | E7: 13070.48 | F7: 13070.5 | G7: ='Table 9.13 (b)'!Q7 -> 13070.5 | I7: =F7-G7 -> 0
A8: Geo-Thermal | E8: 19983.63 | F8: 19983.6 | G8: ='Table 9.13 (b)'!Q8 -> 19983.6 | I8: =F8-G8 -> 0
A9: Bagasse | E9: 0.06 | F9: 0.1 | G9: ='Table 9.13 (b)'!Q9 -> 0.1 | I9: =F9-G9 -> 0
A10: Biomass Wood | E10: 1341522.3 | F10: 1341522.3 | G10: ='Table 9.13 (b)'!E10+'Table 9.13 (b)'!M10 -> 1341284.6 | I10: =F10-G10 -> 237.7
A11: Sub-total | B11: - | C11: - | D11: - | E11: 1382705.7 | F11: 1382705.7
A12: IMPORTS: | F12: -
A13: Electricity | D13: 5517.44 | F13: 5517.4
A14: Coal and Coke | D14: 7409.66 | F14: 7409.7 | G14: ='Table 9.13 (b)'!Q24 -> 7417 | I14: =F14-G14 -> -7.3
A15: Motor Spirit Premium | D15: 5539.51 | F15: 5539.5 | G15: ='Table 9.13 (b)'!Q13 -> 5539.5 | I15: =F15-G15 -> 0
A16: Aviation gasoline | D16: 5.2 | F16: 5.2 | G16: ='Table 9.13 (b)'!Q14 -> 5.2 | I16: =F16-G16 -> 0
A17: Jet fuel | D17: 3156.84 | F17: 3156.8 | G17: ='Table 9.13 (b)'!Q15 -> 3156.8 | I17: =F17-G17 -> 0
A18: Illuminating Kerosene | D18: 8.15 | F18: 8.2 | G18: ='Table 9.13 (b)'!Q16 -> 8.2 | I18: =F18-G18 -> 0
A19: White spirit and special boiling point industrial spirits | D19: 13.84 | F19: 13.8 | G19: ='Table 9.13 (b)'!Q17 -> 13.8 | I19: =F19-G19 -> 0
A20: Light Diesel Oil | D20: 9979.55 | F20: 9979.5 | G20: ='Table 9.13 (b)'!Q18 -> 9979.6 | I20: =D20-G20 -> -0.05
A21: Heavy Diesel Oil | D21: 0.1 | F21: 0.1 | G21: ='Table 9.13 (b)'!Q19 -> 0.1 | I21: =F21-G21 -> 0
A22: Fuel oils n.e.c. | D22: 1300.24 | F22: 1300.2 | G22: ='Table 9.13 (b)'!Q20 -> 1300.2 | I22: =F22-G22 -> 0
A23: Lubricating Oils | D23: 22.15 | F23: 22.2 | G23: ='Table 9.13 (b)'!Q21 -> 22.2 | I23: =F23-G23 -> 0
A24: Lubricating Greases | D24: 10.71 | F24: 10.7 | G24: ='Table 9.13 (b)'!Q22 -> 10.7 | I24: =F24-G24 -> 0
A25: Liquified Petroleum Gas (L.P.G) | D25: 1895.03 | F25: 1895 | G25: ='Table 9.13 (b)'!Q23 -> 1895 | I25: =F25-G25 -> 0
A26: Sub-total | B26: - | C26: - | D26: 34858.55 | E26: - | F26: 34858.55
A27: ENERGY PRODUCTS: | F27: -
A28: Electricity plants (Kengen) | B28: 30507.2 | F28: 30507.2
A29: Electricity plants (Independent Power Producers (IPPs)) | B29: 14120.3 | F29: 14120.3 | G29: =SUM(F28:F31)+F13 -> 50766.9 | H29: =SUM('Table 9.13 (b)'!Q26:Q31)+'Table 9.13 (b)'!Q40 -> 50613 | I29: =G29-H29 -> 153.9
A30: Electricity plants (REREC) | B30: 295.6 | F30: 295.6
A31: Electricity plants (Off-grid)) | B31: 326.4 | F31: 326.4
A32: Charcoal | B32: 832.54 | C32: 102489.99 | F32: 103322.5
A33: Firewood | B33: 7450.9 | C33: 1187906.2 | F33: 1195357.2
A34: Sub-total | B34: 53532.95 | C34: 1290396.2 | D34: - | E34: - | F34: 1343929.2
A35: RESIDUALS: | F35: -
A36: Other | C36: 42842.67 | F36: 42842.7 | G36: ='Table 9.13 (b)'!Q38 -> 42842.7 | I36: =F36-G36 -> 0
A37: TOTAL SUPPLY | B37: 53533 | C37: 1290396.2 | D37: 34858.6 | E37: 1382705.7 | F37: 2804336.1 | G37: =F11+F26+F34+F36 -> 2804336.1
A38: 1 Terajoule (TJ)=10^12 Joules | I38: =SUM(I3:I36) -> 384.25
A39: 1000 Tonnes=4.184 TJ
A40: 1 GWh=3.6 TJ

Sheet Table 9.13 (b)
A1: Table 9.13(b) Physical Energy Use Table, 2024
Q2: TJ
A3: INDUSTRIES | B3: SIEC | C3: Agriculture | D3: Mining & Quarrying | E3: Manufacturing | F3: Electricity, Gas, Steam and Air Conditioning Supply | G3: Construction | H3: Transport and Storage | I3: Accommodation and Food Service Activities | J3: Other Commercial Sectors | K3: Public Administration and Defense | L3: Undefined | M3: Households | N3: Accumulation/Stock | O3: Rest of the World | P3: Flows to the environment | Q3: Total
A4: NATURAL INPUTS: | C4: 0 | D4: 0 | E4: 8283.4 | F4: 41183.4 | G4: 0 | H4: - | I4: - | J4: - | K4: - | L4: - | M4: 1333001.2 | N4: - | O4: - | P4: - | Q4: 1382468.1
A5: Solar | B5: 7000 | F5: 1657.59 | Q5: 1657.6
A6: Wind | B6: 7000 | F6: 6471.62 | Q6: 6471.6
A7: Hydro | B7: 7000 | F7: 13070.48 | Q7: 13070.5
A8: Geo-Thermal | B8: 7000 | F8: 19983.63 | Q8: 19983.6
A9: Co-Generation | B9: 7000 | F9: 0.06 | Q9: 0.1
A10: Biomass Wood | E10: 8283.4 | M10: 1333001.2 | Q10: 1341284.7
A11: ENERGY PRODUCTS CONSUMPTION:
A12: Petroleum: | C12: 92.2 | D12: 402.7 | E12: 5940.3 | F12: 305.9 | G12: 611.1 | H12: 11563.5 | I12: 17.5 | J12: 6864.5 | K12: 85.7 | L12: 2805.3 | M12: 475.3 | N12: -3987.4 | O12: 4172 | P12: 0 | Q12: 29348.5
A13: Motor Spirit Premium | B13: 4651 | C13: 5.47 | D13: 49.03 | E13: 83.56 | F13: 1.02 | G13: 40.74 | H13: 4103.18 | I13: 0.39 | J13: 1949.52 | K13: 12.21 | M13: 0 | N13: -709.17 | O13: 3.56 | Q13: 5539.5
A14: Aviation gasoline | B14: 4652 | C14: 0 | D14: 0 | E14: 0 | F14: 0 | G14: 0 | H14: 8.62 | I14: 0 | J14: 0 | K14: 0.43 | M14: 0 | N14: -4.1 | O14: 0.25 | Q14: 5.2
A15: Jet fuel | B15: 4653 | C15: 0 | D15: 0 | E15: 0 | F15: 0 | G15: 0 | H15: 3056.37 | I15: 0 | J15: 0 | K15: 20.86 | M15: 0 | N15: -3760.07 | O15: 3839.68 | Q15: 3156.8
A16: Illuminating Kerosene | B16: 4669 | C16: 0.01 | D16: 1.49 | E16: 76.67 | F16: 0 | G16: 1.46 | H16: 0.11 | I16: 0 | J16: 53.76 | K16: 0 | M16: 20.19 | N16: -145.54 | O16: 0 | Q16: 8.2
A17: White spirit and special boiling point industrial spirits | B17: 4691 | H17: 0 | N17: 13.62 | O17: 0.22 | Q17: 13.8
A18: Light Diesel Oil | B18: 4671 | C18: 84.92 | D18: 304.8 | E18: 884.4 | F18: 52.79 | G18: 563.3 | H18: 3529.8 | I18: 1.85 | J18: 3765.77 | K18: 52.16 | M18: 0 | N18: 664.03 | O18: 75.81 | Q18: 9979.6
A19: Heavy Diesel Oil | B19: 4672 | N19: 0.12 | O19: 0.01 | Q19: 0.1
A20: Fuel oils n.e.c. | B20: 4680 | C20: 1.85 | D20: 41.98 | E20: 78.35 | F20: 252.1 | G20: 4.69 | H20: 859.69 | I20: 0 | J20: 54.98 | K20: 0 | M20: 0 | N20: -75.32 | O20: 81.92 | Q20: 1300.2
A21: Lubricating Oils | B21: 4692 | N21: -135.05 | O21: 157.2 | Q21: 22.2
A22: Lubricating Greases | B22: 4692 | H22: 0 | N22: 10.27 | O22: 0.44 | Q22: 10.7
A23: Liquified Petroleum Gas (L.P.G) | B23: 4630 | D23: 5.44 | E23: 212.93 | G23: 0.92 | H23: 5.67 | I23: 15.22 | J23: 1040.47 | M23: 455.12 | N23: 153.79 | O23: 5.47 | Q23: 1895
A24: Coal and Coke | E24: 4604.38 | L24: 2805.28 | O24: 7.38 | Q24: 7417
A25: Electricity | B25: 7000 | C25: 0 | D25: 0 | E25: 0 | F25: 0 | G25: 0 | H25: 0 | I25: 0 | J25: 0 | K25: 0 | L25: 26644 | M25: 12062 | N25: 0 | O25: 154 | P25: 0 | Q25: =SUM(Q26:Q31) -> 38706.4
A26: Domestic and Small Commercial | L26: 5708.89 | M26: 10343.87 | Q26: 16052.8
A27: Large and Medium | L27: 19854.57 | Q27: 19854.6
A28: Street Lighting | L28: 323.47 | Q28: 323.5
A29: E-mobility | L29: 10.17 | Q29: 10.2
A30: Rural electrification | L30: 747.05 | M30: 1718.21 | Q30: 2465.3
A31: Other | O31: 154.09
A32: Biomass: | C32: 0 | D32: 0 | E32: 8283.4 | F32: 0 | G32: 0 | H32: 0 | I32: 0 | J32: 0 | K32: 0 | L32: 0 | M32: 1290396.2 | N32: 0 | O32: 0 | P32: 0 | Q32: 1298679.7
A33: Firewood | E33: 7450.9 | M33: 1187906.2 | Q33: 1195357.2
A34: Charcoal | E34: 832.54 | M34: 102489.99 | Q34: 103322.5
A35: Wood/Process Waste | B35: 5119 | Q35: -
A36: Farm residue/Animal crop residue | B36: 5130 | Q36: -
A37: RESIDUALS: | C37: 0 | D37: 0 | E37: 0 | F37: 0 | G37: 0 | H37: 0 | I37: 0 | J37: 0 | K37: 0 | L37: 0 | M37: 0 | N37: 0 | O37: 0 | P37: 54749.3 | Q37: 55133.7
A38: Extraction | P38: 42842.67 | Q38: 42842.7
A39: Transformation | Q39: -
A40: Losses | P40: 11906.64 | Q40: 11906.6
A41: Other | P41: 384.4 | Q41: 384.4
A42: TOTAL USE | C42: 92.2 | D42: 402.7 | E42: 22507.2 | F42: 41489.3 | G42: 611.1 | H42: 11563.5 | I42: 17.5 | J42: 6864.5 | K42: 85.7 | L42: 2805.3 | M42: 2623872.8 | N42: -3987.4 | O42: 4172 | P42: 54749.3 | Q42: 2804336.1
A43: 1 Terajoule (TJ)=10^12 Joules | Q43: =Q4+Q12+Q25+Q32+Q37 -> 2804336.4
A44: 1000 Tonnes=4.184 TJ
A45: 1 GWh=3.6 TJ
