Workbook
Name DBDef1: #REF!
Name DBDef2: #REF!
Name DBDef2a: #REF!
Name DBDef3: #REF!
Name DBLinks: #REF!
Name dbsourcefiles: #REF!
Name FinalUse: #REF!
Name Input_A: #REF!
Name Output: #REF!
Name Prod_acc: #REF!
Name Supply: #REF!
Name TabDef1: #REF!
Name TabDef2: #REF!
Name TabDef3: #REF!
Name TabDef4: #REF!

Sheet RiftValley_Subbasin_Monthly
A1: system:index | B1: Year | C1: Month | D1: Subbasin_ID | E1: area_m2 | F1: mean_rf_mm | G1: .geo
A2: 0 | B2: 2018 | C2: 1 | D2: 2CC | E2: 1.1471729e+10 | F2: 1.6203466 | G2: {"type":"MultiPoint","coordinates":[]} | J2: Year | K2: Year | L2: Year | M2: Year | N2: Year | O2: Year | P2: Year
A3: 1 | B3: 2018 | C3: 1 | D3: 2BC | E3: 3.6876892e+09 | F3: 3.2524273 | G3: {"type":"MultiPoint","coordinates":[]} | I3: Month | J3: 2018 | K3: 2019 | L3: 2020 | M3: 2021 | N3: 2022 | O3: 2023 | P3: 2024
A4: 2 | B4: 2018 | C4: 1 | D4: 2BA | E4: 1.328346e+09 | F4: 7.4607196 | G4: {"type":"MultiPoint","coordinates":[]} | I4: 1 | J4: =AVERAGEIFS($F:$F,$B:$B,J$3,$C:$C,$I4) -> 21.859691 | K4: =AVERAGEIFS($F:$F,$B:$B,K$3,$C:$C,$I4) -> 14.297515 | L4: =AVERAGEIFS($F:$F,$B:$B,L$3,$C:$C,$I4) -> 59.2462 | M4: =AVERAGEIFS($F:$F,$B:$B,M$3,$C:$C,$I4) -> 38.606003 | N4: =AVERAGEIFS($F:$F,$B:$B,N$3,$C:$C,$I4) -> 32.898476 | O4: =AVERAGEIFS($F:$F,$B:$B,O$3,$C:$C,$I4) -> 11.768009 | P4: =AVERAGEIFS($F:$F,$B:$B,P$3,$C:$C,$I4) -> 80.549755
A5: 3 | B5: 2018 | C5: 1 | D5: 2CB | E5: 2.3869168e+09 | F5: 11.624084 | G5: {"type":"MultiPoint","coordinates":[]} | I5: 2 | J5: =AVERAGEIFS($F:$F,$B:$B,J$3,$C:$C,$I5) -> 16.669364 | K5: =AVERAGEIFS($F:$F,$B:$B,K$3,$C:$C,$I5) -> 12.940036 | L5: =AVERAGEIFS($F:$F,$B:$B,L$3,$C:$C,$I5) -> 36.766511 | M5: =AVERAGEIFS($F:$F,$B:$B,M$3,$C:$C,$I5) -> 36.270469 | N5: =AVERAGEIFS($F:$F,$B:$B,N$3,$C:$C,$I5) -> 45.422258 | O5: =AVERAGEIFS($F:$F,$B:$B,O$3,$C:$C,$I5) -> 4.543465 | P5: =AVERAGEIFS($F:$F,$B:$B,P$3,$C:$C,$I5) -> 43.802893
A6: 4 | B6: 2018 | C6: 1 | D6: 2EG2 | E6: 1.2676252e+09 | F6: 9.3202006 | G6: {"type":"MultiPoint","coordinates":[]} | I6: 3 | J6: =AVERAGEIFS($F:$F,$B:$B,J$3,$C:$C,$I6) -> 167.5725 | K6: =AVERAGEIFS($F:$F,$B:$B,K$3,$C:$C,$I6) -> 30.085817 | L6: =AVERAGEIFS($F:$F,$B:$B,L$3,$C:$C,$I6) -> 160.17506 | M6: =AVERAGEIFS($F:$F,$B:$B,M$3,$C:$C,$I6) -> 36.605287 | N6: =AVERAGEIFS($F:$F,$B:$B,N$3,$C:$C,$I6) -> 36.561251 | O6: =AVERAGEIFS($F:$F,$B:$B,O$3,$C:$C,$I6) -> 104.57488 | P6: =AVERAGEIFS($F:$F,$B:$B,P$3,$C:$C,$I6) -> 61.563138
A7: 5 | B7: 2018 | C7: 1 | D7: 2EF | E7: 3.9105834e+08 | F7: 10.287612 | G7: {"type":"MultiPoint","coordinates":[]} | I7: 4 | J7: =AVERAGEIFS($F:$F,$B:$B,J$3,$C:$C,$I7) -> 303.32268 | K7: =AVERAGEIFS($F:$F,$B:$B,K$3,$C:$C,$I7) -> 102.34294 | L7: =AVERAGEIFS($F:$F,$B:$B,L$3,$C:$C,$I7) -> 236.71626 | M7: =AVERAGEIFS($F:$F,$B:$B,M$3,$C:$C,$I7) -> 91.500688 | N7: =AVERAGEIFS($F:$F,$B:$B,N$3,$C:$C,$I7) -> 113.69134 | O7: =AVERAGEIFS($F:$F,$B:$B,O$3,$C:$C,$I7) -> 157.56115 | P7: =AVERAGEIFS($F:$F,$B:$B,P$3,$C:$C,$I7) -> 261.75326
A8: 6 | B8: 2018 | C8: 1 | D8: 2ED | E8: 4.2208576e+08 | F8: 16.599725 | G8: {"type":"MultiPoint","coordinates":[]} | I8: 5 | J8: =AVERAGEIFS($F:$F,$B:$B,J$3,$C:$C,$I8) -> 221.24155 | K8: =AVERAGEIFS($F:$F,$B:$B,K$3,$C:$C,$I8) -> 64.771971 | L8: =AVERAGEIFS($F:$F,$B:$B,L$3,$C:$C,$I8) -> 115.52796 | M8: =AVERAGEIFS($F:$F,$B:$B,M$3,$C:$C,$I8) -> 173.16863 | N8: =AVERAGEIFS($F:$F,$B:$B,N$3,$C:$C,$I8) -> 84.4881 | O8: =AVERAGEIFS($F:$F,$B:$B,O$3,$C:$C,$I8) -> 78.324768 | P8: =AVERAGEIFS($F:$F,$B:$B,P$3,$C:$C,$I8) -> 202.12392
A9: 7 | B9: 2018 | C9: 1 | D9: 2EG1 | E9: 3.9769475e+08 | F9: 15.01732 | G9: {"type":"MultiPoint","coordinates":[]} | I9: 6 | J9: =AVERAGEIFS($F:$F,$B:$B,J$3,$C:$C,$I9) -> 161.528 | K9: =AVERAGEIFS($F:$F,$B:$B,K$3,$C:$C,$I9) -> 114.81653 | L9: =AVERAGEIFS($F:$F,$B:$B,L$3,$C:$C,$I9) -> 111.67158 | M9: =AVERAGEIFS($F:$F,$B:$B,M$3,$C:$C,$I9) -> 41.652293 | N9: =AVERAGEIFS($F:$F,$B:$B,N$3,$C:$C,$I9) -> 41.668222 | O9: =AVERAGEIFS($F:$F,$B:$B,O$3,$C:$C,$I9) -> 58.351639 | P9: =AVERAGEIFS($F:$F,$B:$B,P$3,$C:$C,$I9) -> 39.050899
A10: 8 | B10: 2018 | C10: 1 | D10: 2FC | E10: 1.5173549e+09 | F10: 28.544382 | G10: {"type":"MultiPoint","coordinates":[]} | I10: 7 | J10: =AVERAGEIFS($F:$F,$B:$B,J$3,$C:$C,$I10) -> 69.252752 | K10: =AVERAGEIFS($F:$F,$B:$B,K$3,$C:$C,$I10) -> 94.007435 | L10: =AVERAGEIFS($F:$F,$B:$B,L$3,$C:$C,$I10) -> 117.02844 | M10: =AVERAGEIFS($F:$F,$B:$B,M$3,$C:$C,$I10) -> 75.470816 | N10: =AVERAGEIFS($F:$F,$B:$B,N$3,$C:$C,$I10) -> 45.556247 | O10: =AVERAGEIFS($F:$F,$B:$B,O$3,$C:$C,$I10) -> 41.874304 | P10: =AVERAGEIFS($F:$F,$B:$B,P$3,$C:$C,$I10) -> 112.60966
A11: 9 | B11: 2018 | C11: 1 | D11: 2KA | E11: 5.1064914e+09 | F11: 72.205398 | G11: {"type":"MultiPoint","coordinates":[]} | I11: 8 | J11: =AVERAGEIFS($F:$F,$B:$B,J$3,$C:$C,$I11) -> 71.941013 | K11: =AVERAGEIFS($F:$F,$B:$B,K$3,$C:$C,$I11) -> 100.89376 | L11: =AVERAGEIFS($F:$F,$B:$B,L$3,$C:$C,$I11) -> 121.83942 | M11: =AVERAGEIFS($F:$F,$B:$B,M$3,$C:$C,$I11) -> 67.770147 | N11: =AVERAGEIFS($F:$F,$B:$B,N$3,$C:$C,$I11) -> 94.632327 | O11: =AVERAGEIFS($F:$F,$B:$B,O$3,$C:$C,$I11) -> 41.244459 | P11: =AVERAGEIFS($F:$F,$B:$B,P$3,$C:$C,$I11) -> 86.816223
A12: 10 | B12: 2018 | C12: 1 | D12: 2KB | E12: 1.6403244e+09 | F12: 66.117834 | G12: {"type":"MultiPoint","coordinates":[]} | I12: 9 | J12: =AVERAGEIFS($F:$F,$B:$B,J$3,$C:$C,$I12) -> 31.04461 | K12: =AVERAGEIFS($F:$F,$B:$B,K$3,$C:$C,$I12) -> 58.267881 | L12: =AVERAGEIFS($F:$F,$B:$B,L$3,$C:$C,$I12) -> 70.812841 | M12: =AVERAGEIFS($F:$F,$B:$B,M$3,$C:$C,$I12) -> 73.475875 | N12: =AVERAGEIFS($F:$F,$B:$B,N$3,$C:$C,$I12) -> 71.742297 | O12: =AVERAGEIFS($F:$F,$B:$B,O$3,$C:$C,$I12) -> 73.582851 | P12: =AVERAGEIFS($F:$F,$B:$B,P$3,$C:$C,$I12) -> 40.103428
A13: 11 | B13: 2018 | C13: 1 | D13: 2KC | E13: 1.9961974e+09 | F13: 102.11902 | G13: {"type":"MultiPoint","coordinates":[]} | I13: 10 | J13: =AVERAGEIFS($F:$F,$B:$B,J$3,$C:$C,$I13) -> 50.474487 | K13: =AVERAGEIFS($F:$F,$B:$B,K$3,$C:$C,$I13) -> 135.92471 | L13: =AVERAGEIFS($F:$F,$B:$B,L$3,$C:$C,$I13) -> 98.162708 | M13: =AVERAGEIFS($F:$F,$B:$B,M$3,$C:$C,$I13) -> 62.81794 | N13: =AVERAGEIFS($F:$F,$B:$B,N$3,$C:$C,$I13) -> 47.307848 | O13: =AVERAGEIFS($F:$F,$B:$B,O$3,$C:$C,$I13) -> 88.415097 | P13: =AVERAGEIFS($F:$F,$B:$B,P$3,$C:$C,$I13) -> 74.185622
A14: 12 | B14: 2018 | C14: 1 | D14: 2EC | E14: 8.2788451e+08 | F14: 11.242805 | G14: {"type":"MultiPoint","coordinates":[]} | I14: 11 | J14: =AVERAGEIFS($F:$F,$B:$B,J$3,$C:$C,$I14) -> 39.575555 | K14: =AVERAGEIFS($F:$F,$B:$B,K$3,$C:$C,$I14) -> 122.84125 | L14: =AVERAGEIFS($F:$F,$B:$B,L$3,$C:$C,$I14) -> 99.608536 | M14: =AVERAGEIFS($F:$F,$B:$B,M$3,$C:$C,$I14) -> 36.742754 | N14: =AVERAGEIFS($F:$F,$B:$B,N$3,$C:$C,$I14) -> 107.31512 | O14: =AVERAGEIFS($F:$F,$B:$B,O$3,$C:$C,$I14) -> 132.92189 | P14: =AVERAGEIFS($F:$F,$B:$B,P$3,$C:$C,$I14) -> 127.3144
A15: 13 | B15: 2018 | C15: 1 | D15: 2J | E15: 2.7925067e+10 | F15: 0.075005581 | G15: {"type":"MultiPoint","coordinates":[]} | I15: 12 | J15: =AVERAGEIFS($F:$F,$B:$B,J$3,$C:$C,$I15) -> 76.954583 | K15: =AVERAGEIFS($F:$F,$B:$B,K$3,$C:$C,$I15) -> 134.42385 | L15: =AVERAGEIFS($F:$F,$B:$B,L$3,$C:$C,$I15) -> 25.103619 | M15: =AVERAGEIFS($F:$F,$B:$B,M$3,$C:$C,$I15) -> 35.858952 | N15: =AVERAGEIFS($F:$F,$B:$B,N$3,$C:$C,$I15) -> 41.007349 | O15: =AVERAGEIFS($F:$F,$B:$B,O$3,$C:$C,$I15) -> 30.266499 | P15: =AVERAGEIFS($F:$F,$B:$B,P$3,$C:$C,$I15) -> 28.65843
A16: 14 | B16: 2018 | C16: 1 | D16: 2AB | E16: 9.9916307e+09 | F16: 0.0056829504 | G16: {"type":"MultiPoint","coordinates":[]}
A17: 15 | B17: 2018 | C17: 1 | E17: 7.2926614e+09 | F17: 2.8131334 | G17: {"type":"MultiPoint","coordinates":[]} | I17: TotalAnnual Rf from Monthly Avg | J17: =SUM(J4:J15) -> 1231.4368 | K17: =SUM(K4:K15) -> 985.61369 | L17: =SUM(L4:L15) -> 1252.6591 | M17: =SUM(M4:M15) -> 769.93985 | N17: =SUM(N4:N15) -> 762.29084 | O17: =SUM(O4:O15) -> 823.42901 | P17: =SUM(P4:P15) -> 1158.5316
A18: 16 | B18: 2018 | C18: 1 | D18: 2BD | E18: 1.325639e+10 | F18: 0.081960801 | G18: {"type":"MultiPoint","coordinates":[]}
A19: 17 | B19: 2018 | C19: 1 | D19: 2CA | E19: 3.5811966e+09 | F19: 0.6972395 | G19: {"type":"MultiPoint","coordinates":[]} | I19: Lake Area | J19: ='Lakes Area'!$D$7/1000000 -> 7854.5441 | K19: ='Lakes Area'!$D$7/1000000 -> 7854.5441 | L19: ='Lakes Area'!$D$7/1000000 -> 7854.5441 | M19: ='Lakes Area'!$D$7/1000000 -> 7854.5441 | N19: ='Lakes Area'!$D$7/1000000 -> 7854.5441 | O19: ='Lakes Area'!$D$7/1000000 -> 7854.5441 | P19: ='Lakes Area'!$D$7/1000000 -> 7854.5441
A20: 18 | B20: 2018 | C20: 1 | E20: 37247153 | F20: 6.6883787 | G20: {"type":"MultiPoint","coordinates":[]} | I20: Basin_Area_sqkm | J20: 131423 | K20: 131423 | L20: 131423 | M20: 131423 | N20: 131423 | O20: 131423 | P20: 131423
A21: 19 | B21: 2018 | C21: 1 | E21: 25322285 | F21: 0 | G21: {"type":"MultiPoint","coordinates":[]} | I21: proportion(WB/BA)
A22: 20 | B22: 2018 | C22: 1 | D22: 2BB | E22: 2.0410183e+09 | F22: 2.6888181 | G22: {"type":"MultiPoint","coordinates":[]} | I22: TotalRf_mm | J22: =J17 -> 1231.4368 | K22: =K17 -> 985.61369 | L22: =L17 -> 1252.6591 | M22: =M17 -> 769.93985 | N22: =N17 -> 762.29084 | O22: =O17 -> 823.42901 | P22: =P17 -> 1158.5316
A23: 21 | B23: 2018 | C23: 1 | D23: 2EH | E23: 6.0593036e+08 | F23: 10.995113 | G23: {"type":"MultiPoint","coordinates":[]} | I23: Rainfall_MCM_on_Lake | J23: =(J22*100*J19*10)/1000000 -> 9672.3746 | K23: =(K22*100*K19*10)/1000000 -> 7741.5463 | L23: =(L22*100*L19*10)/1000000 -> 9839.0665 | M23: =(M22*100*M19*10)/1000000 -> 6047.5266 | N23: =(N22*100*N19*10)/1000000 -> 5987.447 | O23: =(O22*100*O19*10)/1000000 -> 6467.6595 | P23: =(P22*100*P19*10)/1000000 -> 9099.7378
A24: 22 | B24: 2018 | C24: 1 | E24: 1.3103515e+08 | F24: 8.788273 | G24: {"type":"MultiPoint","coordinates":[]} | I24: BASIN_MAR
A25: 23 | B25: 2018 | C25: 1 | D25: 2EE | E25: 6.1143635e+08 | F25: 11.326632 | G25: {"type":"MultiPoint","coordinates":[]}
A26: 24 | B26: 2018 | C26: 1 | E26: 35239045 | F26: 8.9521121 | G26: {"type":"MultiPoint","coordinates":[]} | I26: Estimated ET_mm | M26: 2335
A27: 25 | B27: 2018 | C27: 1 | D27: 2EA | E27: 4.1157222e+08 | F27: 9.7967795 | G27: {"type":"MultiPoint","coordinates":[]} | I27: MCM | M27: =(M26*100*M19*10)/1000000 -> 18340.361
A28: 26 | B28: 2018 | C28: 1 | D28: 2FB | E28: 1.4260991e+08 | F28: 12.639265 | G28: {"type":"MultiPoint","coordinates":[]}
A29: 27 | B29: 2018 | C29: 1 | D29: 2GA | E29: 3.2524186e+08 | F29: 32.539953 | G29: {"type":"MultiPoint","coordinates":[]}
A30: 28 | B30: 2018 | C30: 1 | D30: 2FA | E30: 5.4986672e+08 | F30: 28.759558 | G30: {"type":"MultiPoint","coordinates":[]}
A31: 29 | B31: 2018 | C31: 1 | E31: 51177524 | F31: 22.382852 | G31: {"type":"MultiPoint","coordinates":[]}
A32: 30 | B32: 2018 | C32: 1 | E32: 18918004 | F32: 29.532958 | G32: {"type":"MultiPoint","coordinates":[]}
A33: 31 | B33: 2018 | C33: 1 | E33: 1.6796886e+08 | F33: 50.150468 | G33: {"type":"MultiPoint","coordinates":[]}
A34: 32 | B34: 2018 | C34: 1 | E34: 81433392 | F34: 82.904693 | G34: {"type":"MultiPoint","coordinates":[]}
A35: 33 | B35: 2018 | C35: 1 | D35: 2AA | E35: 1.1550168e+10 | F35: 1.4830465 | G35: {"type":"MultiPoint","coordinates":[]}
A36: 34 | B36: 2018 | C36: 1 | D36: 2D | E36: 1.3014403e+10 | F36: 2.6929251 | G36: {"type":"MultiPoint","coordinates":[]}
A37: 35 | B37: 2018 | C37: 1 | D37: 2EJ | E37: 1.4230694e+09 | F37: 8.3253827 | G37: {"type":"MultiPoint","coordinates":[]}
A38: 36 | B38: 2018 | C38: 1 | D38: 2EK | E38: 6.0435638e+08 | F38: 10.572256 | G38: {"type":"MultiPoint","coordinates":[]}
A39: 37 | B39: 2018 | C39: 1 | D39: 2EB | E39: 7.2885378e+08 | F39: 10.958256 | G39: {"type":"MultiPoint","coordinates":[]}
A40: 38 | B40: 2018 | C40: 1 | D40: 2GD | E40: 1.1569536e+09 | F40: 54.220483 | G40: {"type":"MultiPoint","coordinates":[]}
A41: 39 | B41: 2018 | C41: 1 | D41: 2H | E41: 8.2427992e+09 | F41: 70.938791 | G41: {"type":"MultiPoint","coordinates":[]}
A42: 40 | B42: 2018 | C42: 1 | D42: 2GB | E42: 9.6807693e+08 | F42: 31.412632 | G42: {"type":"MultiPoint","coordinates":[]}
A43: 41 | B43: 2018 | C43: 1 | D43: 2GC | E43: 7.5581907e+08 | F43: 50.272491 | G43: {"type":"MultiPoint","coordinates":[]}
A44: 42 | B44: 2018 | C44: 2 | D44: 2CC | E44: 1.1471729e+10 | F44: 5.3110139 | G44: {"type":"MultiPoint","coordinates":[]}
A45: 43 | B45: 2018 | C45: 2 | D45: 2BC | E45: 3.6876892e+09 | F45: 10.357946 | G45: {"type":"MultiPoint","coordinates":[]}
A46: 44 | B46: 2018 | C46: 2 | D46: 2BA | E46: 1.328346e+09 | F46: 13.313924 | G46: {"type":"MultiPoint","coordinates":[]}
... A58: 56 | B58: 2018 | C58: 2 | D58: 2AB | E58: 9.9916307e+09 | F58: 21.763776 | G58: {"type":"MultiPoint","coordinates":[]}
A59: 57 | B59: 2018 | C59: 2 | E59: 7.2926614e+09 | F59: 9.8261032 | G59: {"type":"MultiPoint","coordinates":[]}
A60: 58 | B60: 2018 | C60: 2 | D60: 2BD | E60: 1.325639e+10 | F60: 3.3904251 | G60: {"type":"MultiPoint","coordinates":[]}
A61: 59 | B61: 2018 | C61: 2 | D61: 2CA | E61: 3.5811966e+09 | F61: 4.8053874 | G61: {"type":"MultiPoint","coordinates":[]}
A62: 60 | B62: 2018 | C62: 2 | E62: 37247153 | F62: 9.2984802 | G62: {"type":"MultiPoint","coordinates":[]}
A63: 61 | B63: 2018 | C63: 2 | E63: 25322285 | F63: 0 | G63: {"type":"MultiPoint","coordinates":[]}
A64: 62 | B64: 2018 | C64: 2 | D64: 2BB | E64: 2.0410183e+09 | F64: 7.4031329 | G64: {"type":"MultiPoint","coordinates":[]}
A65: 63 | B65: 2018 | C65: 2 | D65: 2EH | E65: 6.0593036e+08 | F65: 7.6346985 | G65: {"type":"MultiPoint","coordinates":[]}
A66: 64 | B66: 2018 | C66: 2 | E66: 1.3103515e+08 | F66: 7.293068 | G66: {"type":"MultiPoint","coordinates":[]}
A67: 65 | B67: 2018 | C67: 2 | D67: 2EE | E67: 6.1143635e+08 | F67: 8.9235164 | G67: {"type":"MultiPoint","coordinates":[]}
A68: 66 | B68: 2018 | C68: 2 | E68: 35239045 | F68: 9.0154429 | G68: {"type":"MultiPoint","coordinates":[]}
A69: 67 | B69: 2018 | C69: 2 | D69: 2EA | E69: 4.1157222e+08 | F69: 10.129294 | G69: {"type":"MultiPoint","coordinates":[]}
A70: 68 | B70: 2018 | C70: 2 | D70: 2FB | E70: 1.4260991e+08 | F70: 16.043423 | G70: {"type":"MultiPoint","coordinates":[]}
A71: 69 | B71: 2018 | C71: 2 | D71: 2GA | E71: 3.2524186e+08 | F71: 20.373644 | G71: {"type":"MultiPoint","coordinates":[]}
A72: 70 | B72: 2018 | C72: 2 | D72: 2FA | E72: 5.4986672e+08 | F72: 19.203682 | G72: {"type":"MultiPoint","coordinates":[]}
A73: 71 | B73: 2018 | C73: 2 | E73: 51177524 | F73: 16.340508 | G73: {"type":"MultiPoint","coordinates":[]}
A74: 72 | B74: 2018 | C74: 2 | E74: 18918004 | F74: 18.670547 | G74: {"type":"MultiPoint","coordinates":[]}
A75: 73 | B75: 2018 | C75: 2 | E75: 1.6796886e+08 | F75: 31.072321 | G75: {"type":"MultiPoint","coordinates":[]}
A76: 74 | B76: 2018 | C76: 2 | E76: 81433392 | F76: 29.393696 | G76: {"type":"MultiPoint","coordinates":[]}
A77: 75 | B77: 2018 | C77: 2 | D77: 2AA | E77: 1.1550168e+10 | F77: 21.132422 | G77: {"type":"MultiPoint","coordinates":[]}
A78: 76 | B78: 2018 | C78: 2 | D78: 2D | E78: 1.3014403e+10 | F78: 5.7803944 | G78: {"type":"MultiPoint","coordinates":[]}
A79: 77 | B79: 2018 | C79: 2 | D79: 2EJ | E79: 1.4230694e+09 | F79: 9.4450371 | G79: {"type":"MultiPoint","coordinates":[]}
A80: 78 | B80: 2018 | C80: 2 | D80: 2EK | E80: 6.0435638e+08 | F80: 7.9517993 | G80: {"type":"MultiPoint","coordinates":[]}
A81: 79 | B81: 2018 | C81: 2 | D81: 2EB | E81: 7.2885378e+08 | F81: 9.9519917 | G81: {"type":"MultiPoint","coordinates":[]}
A82: 80 | B82: 2018 | C82: 2 | D82: 2GD | E82: 1.1569536e+09 | F82: 34.083838 | G82: {"type":"MultiPoint","coordinates":[]}
A83: 81 | B83: 2018 | C83: 2 | D83: 2H | E83: 8.2427992e+09 | F83: 27.320887 | G83: {"type":"MultiPoint","coordinates":[]}
A84: 82 | B84: 2018 | C84: 2 | D84: 2GB | E84: 9.6807693e+08 | F84: 21.578829 | G84: {"type":"MultiPoint","coordinates":[]}
A85: 83 | B85: 2018 | C85: 2 | D85: 2GC | E85: 7.5581907e+08 | F85: 37.178155 | G85: {"type":"MultiPoint","coordinates":[]}
A86: 84 | B86: 2018 | C86: 3 | D86: 2CC | E86: 1.1471729e+10 | F86: 119.48893 | G86: {"type":"MultiPoint","coordinates":[]}
A87: 85 | B87: 2018 | C87: 3 | D87: 2BC | E87: 3.6876892e+09 | F87: 132.62413 | G87: {"type":"MultiPoint","coordinates":[]}
A88: 86 | B88: 2018 | C88: 3 | D88: 2BA | E88: 1.328346e+09 | F88: 152.66803 | G88: {"type":"MultiPoint","coordinates":[]}
... A100: 98 | B100: 2018 | C100: 3 | D100: 2AB | E100: 9.9916307e+09 | F100: 87.52342 | G100: {"type":"MultiPoint","coordinates":[]}
A101: 99 | B101: 2018 | C101: 3 | E101: 7.2926614e+09 | F101: 58.967552 | G101: {"type":"MultiPoint","coordinates":[]}
A102: 100 | B102: 2018 | C102: 3 | D102: 2BD | E102: 1.325639e+10 | F102: 90.076675 | G102: {"type":"MultiPoint","coordinates":[]}
A103: 101 | B103: 2018 | C103: 3 | D103: 2CA | E103: 3.5811966e+09 | F103: 78.563286 | G103: {"type":"MultiPoint","coordinates":[]}
A104: 102 | B104: 2018 | C104: 3 | E104: 37247153 | F104: 76.461555 | G104: {"type":"MultiPoint","coordinates":[]}
A105: 103 | B105: 2018 | C105: 3 | E105: 25322285 | F105: 83.552175 | G105: {"type":"MultiPoint","coordinates":[]}
A106: 104 | B106: 2018 | C106: 3 | D106: 2BB | E106: 2.0410183e+09 | F106: 125.54824 | G106: {"type":"MultiPoint","coordinates":[]}
A107: 105 | B107: 2018 | C107: 3 | D107: 2EH | E107: 6.0593036e+08 | F107: 163.94018 | G107: {"type":"MultiPoint","coordinates":[]}
A108: 106 | B108: 2018 | C108: 3 | E108: 1.3103515e+08 | F108: 144.38907 | G108: {"type":"MultiPoint","coordinates":[]}
A109: 107 | B109: 2018 | C109: 3 | D109: 2EE | E109: 6.1143635e+08 | F109: 166.69883 | G109: {"type":"MultiPoint","coordinates":[]}
A110: 108 | B110: 2018 | C110: 3 | E110: 35239045 | F110: 170.43899 | G110: {"type":"MultiPoint","coordinates":[]}
A111: 109 | B111: 2018 | C111: 3 | D111: 2EA | E111: 4.1157222e+08 | F111: 148.36848 | G111: {"type":"MultiPoint","coordinates":[]}
A112: 110 | B112: 2018 | C112: 3 | D112: 2FB | E112: 1.4260991e+08 | F112: 163.44374 | G112: {"type":"MultiPoint","coordinates":[]}
A113: 111 | B113: 2018 | C113: 3 | D113: 2GA | E113: 3.2524186e+08 | F113: 179.93376 | G113: {"type":"MultiPoint","coordinates":[]}
A114: 112 | B114: 2018 | C114: 3 | D114: 2FA | E114: 5.4986672e+08 | F114: 175.07307 | G114: {"type":"MultiPoint","coordinates":[]}
A115: 113 | B115: 2018 | C115: 3 | E115: 51177524 | F115: 141.59488 | G115: {"type":"MultiPoint","coordinates":[]}
A116: 114 | B116: 2018 | C116: 3 | E116: 18918004 | F116: 168.53778 | G116: {"type":"MultiPoint","coordinates":[]}
A117: 115 | B117: 2018 | C117: 3 | E117: 1.6796886e+08 | F117: 195.55697 | G117: {"type":"MultiPoint","coordinates":[]}
A118: 116 | B118: 2018 | C118: 3 | E118: 81433392 | F118: 217.24305 | G118: {"type":"MultiPoint","coordinates":[]}
A119: 117 | B119: 2018 | C119: 3 | D119: 2AA | E119: 1.1550168e+10 | F119: 95.65186 | G119: {"type":"MultiPoint","coordinates":[]}
A120: 118 | B120: 2018 | C120: 3 | D120: 2D | E120: 1.3014403e+10 | F120: 150.7519 | G120: {"type":"MultiPoint","coordinates":[]}
A121: 119 | B121: 2018 | C121: 3 | D121: 2EJ | E121: 1.4230694e+09 | F121: 164.79466 | G121: {"type":"MultiPoint","coordinates":[]}
A122: 120 | B122: 2018 | C122: 3 | D122: 2EK | E122: 6.0435638e+08 | F122: 176.55498 | G122: {"type":"MultiPoint","coordinates":[]}
...

Sheet TanaRiver_Subbasin_Monthly
A1: system:index | B1: Year | C1: Month | D1: Subbasin_ID | E1: area_m2 | F1: mean_rf_mm | G1: .geo
A2: 0 | B2: 2018 | C2: 1 | D2: 4GC | E2: 1.8338258e+09 | F2: 0.61726873 | G2: {"type":"MultiPoint","coordinates":[]} | J2: Year | K2: Year | L2: Year | M2: Year | N2: Year | O2: Year | P2: Year
A3: 1 | B3: 2018 | C3: 1 | D3: 4EA | E3: 7.4866526e+08 | F3: 13.228085 | G3: {"type":"MultiPoint","coordinates":[]} | I3: Month | J3: 2018 | K3: 2019 | L3: 2020 | M3: 2021 | N3: 2022 | O3: 2023 | P3: 2024
A4: 2 | B4: 2018 | C4: 1 | D4: 4KA | E4: 8.2691711e+09 | F4: 4.6051588 | G4: {"type":"MultiPoint","coordinates":[]} | I4: 1 | J4: =AVERAGEIFS($F:$F,$B:$B,J$3,$C:$C,$I4) -> 14.516938 | K4: =AVERAGEIFS($F:$F,$B:$B,K$3,$C:$C,$I4) -> 29.906756 | L4: =AVERAGEIFS($F:$F,$B:$B,L$3,$C:$C,$I4) -> 79.878943 | M4: =AVERAGEIFS($F:$F,$B:$B,M$3,$C:$C,$I4) -> 36.889523 | N4: =AVERAGEIFS($F:$F,$B:$B,N$3,$C:$C,$I4) -> 23.682735 | O4: =AVERAGEIFS($F:$F,$B:$B,O$3,$C:$C,$I4) -> 22.765883 | P4: =AVERAGEIFS($F:$F,$B:$B,P$3,$C:$C,$I4) -> 52.061099
A5: 3 | B5: 2018 | C5: 1 | D5: 4DA | E5: 7.2138355e+08 | F5: 16.192916 | G5: {"type":"MultiPoint","coordinates":[]} | I5: 2 | J5: =AVERAGEIFS($F:$F,$B:$B,J$3,$C:$C,$I5) -> 11.129098 | K5: =AVERAGEIFS($F:$F,$B:$B,K$3,$C:$C,$I5) -> 17.798898 | L5: =AVERAGEIFS($F:$F,$B:$B,L$3,$C:$C,$I5) -> 41.621456 | M5: =AVERAGEIFS($F:$F,$B:$B,M$3,$C:$C,$I5) -> 28.40047 | N5: =AVERAGEIFS($F:$F,$B:$B,N$3,$C:$C,$I5) -> 19.445685 | O5: =AVERAGEIFS($F:$F,$B:$B,O$3,$C:$C,$I5) -> 4.9831213 | P5: =AVERAGEIFS($F:$F,$B:$B,P$3,$C:$C,$I5) -> 40.352366
A6: 4 | B6: 2018 | C6: 1 | D6: 4BB | E6: 2.5828756e+08 | F6: 22.848785 | G6: {"type":"MultiPoint","coordinates":[]} | I6: 3 | J6: =AVERAGEIFS($F:$F,$B:$B,J$3,$C:$C,$I6) -> 189.45065 | K6: =AVERAGEIFS($F:$F,$B:$B,K$3,$C:$C,$I6) -> 19.952317 | L6: =AVERAGEIFS($F:$F,$B:$B,L$3,$C:$C,$I6) -> 130.66147 | M6: =AVERAGEIFS($F:$F,$B:$B,M$3,$C:$C,$I6) -> 41.538713 | N6: =AVERAGEIFS($F:$F,$B:$B,N$3,$C:$C,$I6) -> 31.320183 | O6: =AVERAGEIFS($F:$F,$B:$B,O$3,$C:$C,$I6) -> 83.858737 | P6: =AVERAGEIFS($F:$F,$B:$B,P$3,$C:$C,$I6) -> 54.201932
A7: 5 | B7: 2018 | C7: 1 | D7: 4EC | E7: 6.1097463e+08 | F7: 7.277723 | G7: {"type":"MultiPoint","coordinates":[]} | I7: 4 | J7: =AVERAGEIFS($F:$F,$B:$B,J$3,$C:$C,$I7) -> 394.53917 | K7: =AVERAGEIFS($F:$F,$B:$B,K$3,$C:$C,$I7) -> 142.78302 | L7: =AVERAGEIFS($F:$F,$B:$B,L$3,$C:$C,$I7) -> 404.1967 | M7: =AVERAGEIFS($F:$F,$B:$B,M$3,$C:$C,$I7) -> 144.20306 | N7: =AVERAGEIFS($F:$F,$B:$B,N$3,$C:$C,$I7) -> 158.09437 | O7: =AVERAGEIFS($F:$F,$B:$B,O$3,$C:$C,$I7) -> 317.58338 | P7: =AVERAGEIFS($F:$F,$B:$B,P$3,$C:$C,$I7) -> 427.49048
A8: 6 | B8: 2018 | C8: 1 | D8: 4BC | E8: 2.2721178e+08 | F8: 19.491538 | G8: {"type":"MultiPoint","coordinates":[]} | I8: 5 | J8: =AVERAGEIFS($F:$F,$B:$B,J$3,$C:$C,$I8) -> 274.23927 | K8: =AVERAGEIFS($F:$F,$B:$B,K$3,$C:$C,$I8) -> 141.7351 | L8: =AVERAGEIFS($F:$F,$B:$B,L$3,$C:$C,$I8) -> 147.96822 | M8: =AVERAGEIFS($F:$F,$B:$B,M$3,$C:$C,$I8) -> 144.62814 | N8: =AVERAGEIFS($F:$F,$B:$B,N$3,$C:$C,$I8) -> 76.844798 | O8: =AVERAGEIFS($F:$F,$B:$B,O$3,$C:$C,$I8) -> 68.374231 | P8: =AVERAGEIFS($F:$F,$B:$B,P$3,$C:$C,$I8) -> 199.14891
A9: 7 | B9: 2018 | C9: 1 | D9: 4ED | E9: 3.1779501e+09 | F9: 9.7686319 | G9: {"type":"MultiPoint","coordinates":[]} | I9: 6 | J9: =AVERAGEIFS($F:$F,$B:$B,J$3,$C:$C,$I9) -> 80.671388 | K9: =AVERAGEIFS($F:$F,$B:$B,K$3,$C:$C,$I9) -> 37.073572 | L9: =AVERAGEIFS($F:$F,$B:$B,L$3,$C:$C,$I9) -> 56.179629 | M9: =AVERAGEIFS($F:$F,$B:$B,M$3,$C:$C,$I9) -> 23.076413 | N9: =AVERAGEIFS($F:$F,$B:$B,N$3,$C:$C,$I9) -> 26.613912 | O9: =AVERAGEIFS($F:$F,$B:$B,O$3,$C:$C,$I9) -> 32.619744 | P9: =AVERAGEIFS($F:$F,$B:$B,P$3,$C:$C,$I9) -> 26.517022
A10: 8 | B10: 2018 | C10: 1 | D10: 4GD | E10: 7.4432996e+09 | F10: 2.6740172 | G10: {"type":"MultiPoint","coordinates":[]} | I10: 7 | J10: =AVERAGEIFS($F:$F,$B:$B,J$3,$C:$C,$I10) -> 46.195614 | K10: =AVERAGEIFS($F:$F,$B:$B,K$3,$C:$C,$I10) -> 35.499837 | L10: =AVERAGEIFS($F:$F,$B:$B,L$3,$C:$C,$I10) -> 47.530334 | M10: =AVERAGEIFS($F:$F,$B:$B,M$3,$C:$C,$I10) -> 35.245025 | N10: =AVERAGEIFS($F:$F,$B:$B,N$3,$C:$C,$I10) -> 32.262213 | O10: =AVERAGEIFS($F:$F,$B:$B,O$3,$C:$C,$I10) -> 31.232928 | P10: =AVERAGEIFS($F:$F,$B:$B,P$3,$C:$C,$I10) -> 39.346364
A11: 9 | B11: 2018 | C11: 1 | D11: 4BA | E11: 3.2081475e+08 | F11: 29.361146 | G11: {"type":"MultiPoint","coordinates":[]} | I11: 8 | J11: =AVERAGEIFS($F:$F,$B:$B,J$3,$C:$C,$I11) -> 28.846234 | K11: =AVERAGEIFS($F:$F,$B:$B,K$3,$C:$C,$I11) -> 31.000674 | L11: =AVERAGEIFS($F:$F,$B:$B,L$3,$C:$C,$I11) -> 31.915019 | M11: =AVERAGEIFS($F:$F,$B:$B,M$3,$C:$C,$I11) -> 22.439777 | N11: =AVERAGEIFS($F:$F,$B:$B,N$3,$C:$C,$I11) -> 28.176221 | O11: =AVERAGEIFS($F:$F,$B:$B,O$3,$C:$C,$I11) -> 26.265621 | P11: =AVERAGEIFS($F:$F,$B:$B,P$3,$C:$C,$I11) -> 26.398697
A12: 10 | B12: 2018 | C12: 1 | D12: 4KB | E12: 1.0295749e+10 | F12: 4.6712664 | G12: {"type":"MultiPoint","coordinates":[]} | I12: 9 | J12: =AVERAGEIFS($F:$F,$B:$B,J$3,$C:$C,$I12) -> 30.36277 | K12: =AVERAGEIFS($F:$F,$B:$B,K$3,$C:$C,$I12) -> 37.826673 | L12: =AVERAGEIFS($F:$F,$B:$B,L$3,$C:$C,$I12) -> 35.874735 | M12: =AVERAGEIFS($F:$F,$B:$B,M$3,$C:$C,$I12) -> 18.003652 | N12: =AVERAGEIFS($F:$F,$B:$B,N$3,$C:$C,$I12) -> 21.22887 | O12: =AVERAGEIFS($F:$F,$B:$B,O$3,$C:$C,$I12) -> 26.343731 | P12: =AVERAGEIFS($F:$F,$B:$B,P$3,$C:$C,$I12) -> 17.011603
A13: 11 | B13: 2018 | C13: 1 | D13: 4DD | E13: 4.5316791e+08 | F13: 10.084739 | G13: {"type":"MultiPoint","coordinates":[]} | I13: 10 | J13: =AVERAGEIFS($F:$F,$B:$B,J$3,$C:$C,$I13) -> 65.732633 | K13: =AVERAGEIFS($F:$F,$B:$B,K$3,$C:$C,$I13) -> 302.44466 | L13: =AVERAGEIFS($F:$F,$B:$B,L$3,$C:$C,$I13) -> 70.350674 | M13: =AVERAGEIFS($F:$F,$B:$B,M$3,$C:$C,$I13) -> 57.002652 | N13: =AVERAGEIFS($F:$F,$B:$B,N$3,$C:$C,$I13) -> 36.609786 | O13: =AVERAGEIFS($F:$F,$B:$B,O$3,$C:$C,$I13) -> 112.13397 | P13: =AVERAGEIFS($F:$F,$B:$B,P$3,$C:$C,$I13) -> 45.173401
A14: 12 | B14: 2018 | C14: 1 | D14: 4GE | E14: 1.1800845e+10 | F14: 6.555522 | G14: {"type":"MultiPoint","coordinates":[]} | I14: 11 | J14: =AVERAGEIFS($F:$F,$B:$B,J$3,$C:$C,$I14) -> 119.97796 | K14: =AVERAGEIFS($F:$F,$B:$B,K$3,$C:$C,$I14) -> 328.014 | L14: =AVERAGEIFS($F:$F,$B:$B,L$3,$C:$C,$I14) -> 150.07071 | M14: =AVERAGEIFS($F:$F,$B:$B,M$3,$C:$C,$I14) -> 102.07135 | N14: =AVERAGEIFS($F:$F,$B:$B,N$3,$C:$C,$I14) -> 205.08794 | O14: =AVERAGEIFS($F:$F,$B:$B,O$3,$C:$C,$I14) -> 373.932 | P14: =AVERAGEIFS($F:$F,$B:$B,P$3,$C:$C,$I14) -> 252.52525
A15: 13 | B15: 2018 | C15: 1 | D15: 4BF | E15: 3.765969e+08 | F15: 33.0171 | G15: {"type":"MultiPoint","coordinates":[]} | I15: 12 | J15: =AVERAGEIFS($F:$F,$B:$B,J$3,$C:$C,$I15) -> 160.58118 | K15: =AVERAGEIFS($F:$F,$B:$B,K$3,$C:$C,$I15) -> 195.78787 | L15: =AVERAGEIFS($F:$F,$B:$B,L$3,$C:$C,$I15) -> 59.844208 | M15: =AVERAGEIFS($F:$F,$B:$B,M$3,$C:$C,$I15) -> 168.98597 | N15: =AVERAGEIFS($F:$F,$B:$B,N$3,$C:$C,$I15) -> 47.892921 | O15: =AVERAGEIFS($F:$F,$B:$B,O$3,$C:$C,$I15) -> 79.21488 | P15: =AVERAGEIFS($F:$F,$B:$B,P$3,$C:$C,$I15) -> 61.941592
A16: 14 | B16: 2018 | C16: 1 | D16: 4BG | E16: 4.455162e+08 | F16: 25.242488 | G16: {"type":"MultiPoint","coordinates":[]}
A17: 15 | B17: 2018 | C17: 1 | D17: 4JB | E17: 3.6765904e+09 | F17: 2.9361985 | G17: {"type":"MultiPoint","coordinates":[]} | I17: TotalAnnual Rf from Monthly Avg | J17: =SUM(J4:J15) -> 1416.2429 | K17: =SUM(K4:K15) -> 1319.8234 | L17: =SUM(L4:L15) -> 1256.0921 | M17: =SUM(M4:M15) -> 822.48474 | N17: =SUM(N4:N15) -> 707.25963 | O17: =SUM(O4:O15) -> 1179.3082 | P17: =SUM(P4:P15) -> 1242.1687
A18: 16 | B18: 2018 | C18: 1 | D18: 4GF | E18: 1.5608902e+10 | F18: 7.0829241 | G18: {"type":"MultiPoint","coordinates":[]}
A19: 17 | B19: 2018 | C19: 1 | D19: 4HB | E19: 9.119548e+09 | F19: 6.1236031 | G19: {"type":"MultiPoint","coordinates":[]} | I19: WB_Area_sqkm | J19: ='Lakes Area'!$D$6/1000000 -> 424.39293 | K19: ='Lakes Area'!$D$6/1000000 -> 424.39293 | L19: ='Lakes Area'!$D$6/1000000 -> 424.39293 | M19: ='Lakes Area'!$D$6/1000000 -> 424.39293 | N19: ='Lakes Area'!$D$6/1000000 -> 424.39293 | O19: ='Lakes Area'!$D$6/1000000 -> 424.39293 | P19: ='Lakes Area'!$D$6/1000000 -> 424.39293
A20: 18 | B20: 2018 | C20: 1 | E20: 1.6150196e+08 | F20: 3.1129808 | G20: {"type":"MultiPoint","coordinates":[]} | I20: Basin_Area_sqkm | J20: 126208 | K20: 126208 | L20: 126208 | M20: 126208 | N20: 126208 | O20: 126208 | P20: 126208
A21: 19 | B21: 2018 | C21: 1 | E21: 65243578 | F21: 0 | G21: {"type":"MultiPoint","coordinates":[]} | I21: proportion(WB/BA)
A22: 20 | B22: 2018 | C22: 1 | E22: 50371439 | F22: 0 | G22: {"type":"MultiPoint","coordinates":[]} | I22: TotalRf_mm | J22: =J17 -> 1416.2429 | K22: =K17 -> 1319.8234 | L22: =L17 -> 1256.0921 | M22: =M17 -> 822.48474 | N22: =N17 -> 707.25963 | O22: =O17 -> 1179.3082 | P22: =P17 -> 1242.1687
A23: 21 | B23: 2018 | C23: 1 | D23: 4BE | E23: 5.5612612e+08 | F23: 39.656927 | G23: {"type":"MultiPoint","coordinates":[]} | I23: Rainfall_MCM_on_Lake | J23: =(J22*100*J19*10)/1000000 -> 601.04348 | K23: =(K22*100*K19*10)/1000000 -> 560.12371 | L23: =(L22*100*L19*10)/1000000 -> 533.0766 | M23: =(M22*100*M19*10)/1000000 -> 349.05671 | N23: =(N22*100*N19*10)/1000000 -> 300.15599 | O23: =(O22*100*O19*10)/1000000 -> 500.49007 | P23: =(P22*100*P19*10)/1000000 -> 527.16762
A24: 22 | B24: 2018 | C24: 1 | D24: 4CC | E24: 1.0243122e+09 | F24: 29.745633 | G24: {"type":"MultiPoint","coordinates":[]} | I24: BASIN_MAR | J24: =(J22*100*J20*10)/1000000 -> 178741.19 | K24: =(K22*100*K20*10)/1000000 -> 166572.27 | L24: =(L22*100*L20*10)/1000000 -> 158528.87 | M24: =(M22*100*M20*10)/1000000 -> 103804.15 | N24: =(N22*100*N20*10)/1000000 -> 89261.824 | O24: =(O22*100*O20*10)/1000000 -> 148838.13 | P24: =(P22*100*P20*10)/1000000 -> 156771.63
A25: 23 | B25: 2018 | C25: 1 | D25: 4DE | E25: 7.3999224e+08 | F25: 19.653881 | G25: {"type":"MultiPoint","coordinates":[]}
A26: 24 | B26: 2018 | C26: 1 | D26: 4HA | E26: 5.5127092e+09 | F26: 14.324562 | G26: {"type":"MultiPoint","coordinates":[]}
A27: 25 | B27: 2018 | C27: 1 | D27: 4GG | E27: 7.1644721e+09 | F27: 6.0188932 | G27: {"type":"MultiPoint","coordinates":[]}
A28: 26 | B28: 2018 | C28: 1 | D28: 4HC | E28: 6.6618128e+09 | F28: 2.170638 | G28: {"type":"MultiPoint","coordinates":[]}
A29: 27 | B29: 2018 | C29: 1 | D29: 3HD2 | E29: 4.0628645e+08 | F29: 5.7189246 | G29: {"type":"MultiPoint","coordinates":[]}
A30: 28 | B30: 2018 | C30: 1 | D30: 4GA | E30: 3.9327061e+09 | F30: 5.7482136 | G30: {"type":"MultiPoint","coordinates":[]}
A31: 29 | B31: 2018 | C31: 1 | D31: 4FB | E31: 3.9730883e+09 | F31: 6.7679747 | G31: {"type":"MultiPoint","coordinates":[]}
A32: 30 | B32: 2018 | C32: 1 | D32: 4GB | E32: 5.5351201e+09 | F32: 3.3543146 | G32: {"type":"MultiPoint","coordinates":[]}
A33: 31 | B33: 2018 | C33: 1 | D33: 4FA | E33: 2.192164e+09 | F33: 11.362784 | G33: {"type":"MultiPoint","coordinates":[]}
A34: 32 | B34: 2018 | C34: 1 | D34: 4JA | E34: 8.4070244e+09 | F34: 2.1570325 | G34: {"type":"MultiPoint","coordinates":[]}
A35: 33 | B35: 2018 | C35: 1 | D35: 4EB | E35: 1.1982913e+09 | F35: 12.156622 | G35: {"type":"MultiPoint","coordinates":[]}
A36: 34 | B36: 2018 | C36: 1 | D36: 4DC | E36: 3.56173e+08 | F36: 12.694003 | G36: {"type":"MultiPoint","coordinates":[]}
... A60: 58 | B60: 2018 | C60: 2 | D60: 4HB | E60: 9.119548e+09 | F60: 7.151751 | G60: {"type":"MultiPoint","coordinates":[]}
A61: 59 | B61: 2018 | C61: 2 | E61: 1.6150196e+08 | F61: 0 | G61: {"type":"MultiPoint","coordinates":[]}
A62: 60 | B62: 2018 | C62: 2 | E62: 65243578 | F62: 0 | G62: {"type":"MultiPoint","coordinates":[]}
A63: 61 | B63: 2018 | C63: 2 | E63: 50371439 | F63: 0 | G63: {"type":"MultiPoint","coordinates":[]}
A64: 62 | B64: 2018 | C64: 2 | D64: 4BE | E64: 5.5612612e+08 | F64: 28.363293 | G64: {"type":"MultiPoint","coordinates":[]}
A65: 63 | B65: 2018 | C65: 2 | D65: 4CC | E65: 1.0243122e+09 | F65: 17.74114 | G65: {"type":"MultiPoint","coordinates":[]}
A66: 64 | B66: 2018 | C66: 2 | D66: 4DE | E66: 7.3999224e+08 | F66: 10.023076 | G66: {"type":"MultiPoint","coordinates":[]}
A67: 65 | B67: 2018 | C67: 2 | D67: 4HA | E67: 5.5127092e+09 | F67: 11.566769 | G67: {"type":"MultiPoint","coordinates":[]}
A68: 66 | B68: 2018 | C68: 2 | D68: 4GG | E68: 7.1644721e+09 | F68: 7.536134 | G68: {"type":"MultiPoint","coordinates":[]}
A69: 67 | B69: 2018 | C69: 2 | D69: 4HC | E69: 6.6618128e+09 | F69: 6.3745893 | G69: {"type":"MultiPoint","coordinates":[]}
A70: 68 | B70: 2018 | C70: 2 | D70: 3HD2 | E70: 4.0628645e+08 | F70: 2.4693474 | G70: {"type":"MultiPoint","coordinates":[]}
A71: 69 | B71: 2018 | C71: 2 | D71: 4GA | E71: 3.9327061e+09 | F71: 1.3855811 | G71: {"type":"MultiPoint","coordinates":[]}
A72: 70 | B72: 2018 | C72: 2 | D72: 4FB | E72: 3.9730883e+09 | F72: 3.2474824 | G72: {"type":"MultiPoint","coordinates":[]}
A73: 71 | B73: 2018 | C73: 2 | D73: 4GB | E73: 5.5351201e+09 | F73: 1.7811024 | G73: {"type":"MultiPoint","coordinates":[]}
A74: 72 | B74: 2018 | C74: 2 | D74: 4FA | E74: 2.192164e+09 | F74: 8.9353735 | G74: {"type":"MultiPoint","coordinates":[]}
A75: 73 | B75: 2018 | C75: 2 | D75: 4JA | E75: 8.4070244e+09 | F75: 3.2716112 | G75: {"type":"MultiPoint","coordinates":[]}
... A101: 99 | B101: 2018 | C101: 3 | D101: 4HB | E101: 9.119548e+09 | F101: 153.74494 | G101: {"type":"MultiPoint","coordinates":[]}
A102: 100 | B102: 2018 | C102: 3 | E102: 1.6150196e+08 | F102: 27.025715 | G102: {"type":"MultiPoint","coordinates":[]}
A103: 101 | B103: 2018 | C103: 3 | E103: 65243578 | F103: 53.535175 | G103: {"type":"MultiPoint","coordinates":[]}
A104: 102 | B104: 2018 | C104: 3 | E104: 50371439 | F104: 64.393696 | G104: {"type":"MultiPoint","coordinates":[]}
A105: 103 | B105: 2018 | C105: 3 | D105: 4BE | E105: 5.5612612e+08 | F105: 243.22471 | G105: {"type":"MultiPoint","coordinates":[]}
A106: 104 | B106: 2018 | C106: 3 | D106: 4CC | E106: 1.0243122e+09 | F106: 233.66477 | G106: {"type":"MultiPoint","coordinates":[]}
A107: 105 | B107: 2018 | C107: 3 | D107: 4DE | E107: 7.3999224e+08 | F107: 190.7748 | G107: {"type":"MultiPoint","coordinates":[]}
A108: 106 | B108: 2018 | C108: 3 | D108: 4HA | E108: 5.5127092e+09 | F108: 210.56582 | G108: {"type":"MultiPoint","coordinates":[]}
A109: 107 | B109: 2018 | C109: 3 | D109: 4GG | E109: 7.1644721e+09 | F109: 110.4838 | G109: {"type":"MultiPoint","coordinates":[]}
A110: 108 | B110: 2018 | C110: 3 | D110: 4HC | E110: 6.6618128e+09 | F110: 168.03011 | G110: {"type":"MultiPoint","coordinates":[]}
A111: 109 | B111: 2018 | C111: 3 | D111: 3HD2 | E111: 4.0628645e+08 | F111: 92.395207 | G111: {"type":"MultiPoint","coordinates":[]}
A112: 110 | B112: 2018 | C112: 3 | D112: 4GA | E112: 3.9327061e+09 | F112: 200.3008 | G112: {"type":"MultiPoint","coordinates":[]}
A113: 111 | B113: 2018 | C113: 3 | D113: 4FB | E113: 3.9730883e+09 | F113: 242.00285 | G113: {"type":"MultiPoint","coordinates":[]}
A114: 112 | B114: 2018 | C114: 3 | D114: 4GB | E114: 5.5351201e+09 | F114: 173.29621 | G114: {"type":"MultiPoint","coordinates":[]}
A115: 113 | B115: 2018 | C115: 3 | D115: 4FA | E115: 2.192164e+09 | F115: 271.81951 | G115: {"type":"MultiPoint","coordinates":[]}
A116: 114 | B116: 2018 | C116: 3 | D116: 4JA | E116: 8.4070244e+09 | F116: 133.6485 | G116: {"type":"MultiPoint","coordinates":[]}
... A142: 140 | B142: 2018 | C142: 4 | D142: 4HB | E142: 9.119548e+09 | F142: 204.72603 | G142: {"type":"MultiPoint","coordinates":[]}
A143: 141 | B143: 2018 | C143: 4 | E143: 1.6150196e+08 | F143: 192.43482 | G143: {"type":"MultiPoint","coordinates":[]}
A144: 142 | B144: 2018 | C144: 4 | E144: 65243578 | F144: 204.746 | G144: {"type":"MultiPoint","coordinates":[]}
A145: 143 | B145: 2018 | C145: 4 | E145: 50371439 | F145: 183.48308 | G145: {"type":"MultiPoint","coordinates":[]}
A146: 144 | B146: 2018 | C146: 4 | D146: 4BE | E146: 5.5612612e+08 | F146: 701.95885 | G146: {"type":"MultiPoint","coordinates":[]}
A147: 145 | B147: 2018 | C147: 4 | D147: 4CC | E147: 1.0243122e+09 | F147: 463.06672 | G147: {"type":"MultiPoint","coordinates":[]}
A148: 146 | B148: 2018 | C148: 4 | D148: 4DE | E148: 7.3999224e+08 | F148: 407.21245 | G148: {"type":"MultiPoint","coordinates":[]}
A149: 147 | B149: 2018 | C149: 4 | D149: 4HA | E149: 5.5127092e+09 | F149: 319.76086 | G149: {"type":"MultiPoint","coordinates":[]}
A150: 148 | B150: 2018 | C150: 4 | D150: 4GG | E150: 7.1644721e+09 | F150: 172.34928 | G150: {"type":"MultiPoint","coordinates":[]}
A151: 149 | B151: 2018 | C151: 4 | D151: 4HC | E151: 6.6618128e+09 | F151: 151.6806 | G151: {"type":"MultiPoint","coordinates":[]}
A152: 150 | B152: 2018 | C152: 4 | D152: 3HD2 | E152: 4.0628645e+08 | F152: 261.09667 | G152: {"type":"MultiPoint","coordinates":[]}
A153: 151 | B153: 2018 | C153: 4 | D153: 4GA | E153: 3.9327061e+09 | F153: 307.76262 | G153: {"type":"MultiPoint","coordinates":[]}
A154: 152 | B154: 2018 | C154: 4 | D154: 4FB | E154: 3.9730883e+09 | F154: 463.85874 | G154: {"type":"MultiPoint","coordinates":[]}
A155: 153 | B155: 2018 | C155: 4 | D155: 4GB | E155: 5.5351201e+09 | F155: 153.9655 | G155: {"type":"MultiPoint","coordinates":[]}
A156: 154 | B156: 2018 | C156: 4 | D156: 4FA | E156: 2.192164e+09 | F156: 580.73991 | G156: {"type":"MultiPoint","coordinates":[]}
A157: 155 | B157: 2018 | C157: 4 | D157: 4JA | E157: 8.4070244e+09 | F157: 202.78876 | G157: {"type":"MultiPoint","coordinates":[]}
... A183: 181 | B183: 2018 | C183: 5 | D183: 4HB | E183: 9.119548e+09 | F183: 44.903177 | G183: {"type":"MultiPoint","coordinates":[]}
A184: 182 | B184: 2018 | C184: 5 | E184: 1.6150196e+08 | F184: 661.28038 | G184: {"type":"MultiPoint","coordinates":[]}
A185: 183 | B185: 2018 | C185: 5 | E185: 65243578 | F185: 697.34078 | G185: {"type":"MultiPoint","coordinates":[]}
A186: 184 | B186: 2018 | C186: 5 | E186: 50371439 | F186: 774.75531 | G186: {"type":"MultiPoint","coordinates":[]}
A187: 185 | B187: 2018 | C187: 5 | D187: 4BE | E187: 5.5612612e+08 | F187: 575.66853 | G187: {"type":"MultiPoint","coordinates":[]}
A188: 186 | B188: 2018 | C188: 5 | D188: 4CC | E188: 1.0243122e+09 | F188: 247.57098 | G188: {"type":"MultiPoint","coordinates":[]}
A189: 187 | B189: 2018 | C189: 5 | D189: 4DE | E189: 7.3999224e+08 | F189: 97.91643 | G189: {"type":"MultiPoint","coordinates":[]}
A190: 188 | B190: 2018 | C190: 5 | D190: 4HA | E190: 5.5127092e+09 | F190: 36.795033 | G190: {"type":"MultiPoint","coordinates":[]}
A191: 189 | B191: 2018 | C191: 5 | D191: 4GG | E191: 7.1644721e+09 | F191: 230.76809 | G191: {"type":"MultiPoint","coordinates":[]}
A192: 190 | B192: 2018 | C192: 5 | D192: 4HC | E192: 6.6618128e+09 | F192: 33.613953 | G192: {"type":"MultiPoint","coordinates":[]}
A193: 191 | B193: 2018 | C193: 5 | D193: 3HD2 | E193: 4.0628645e+08 | F193: 349.716 | G193: {"type":"MultiPoint","coordinates":[]}
A194: 192 | B194: 2018 | C194: 5 | D194: 4GA | E194: 3.9327061e+09 | F194: 38.47799 | G194: {"type":"MultiPoint","coordinates":[]}
A195: 193 | B195: 2018 | C195: 5 | D195: 4FB | E195: 3.9730883e+09 | F195: 85.439547 | G195: {"type":"MultiPoint","coordinates":[]}
A196: 194 | B196: 2018 | C196: 5 | D196: 4GB | E196: 5.5351201e+09 | F196: 16.054845 | G196: {"type":"MultiPoint","coordinates":[]}
A197: 195 | B197: 2018 | C197: 5 | D197: 4FA | E197: 2.192164e+09 | F197: 196.29722 | G197: {"type":"MultiPoint","coordinates":[]}
A198: 196 | B198: 2018 | C198: 5 | D198: 4JA | E198: 8.4070244e+09 | F198: 56.80452 | G198: {"type":"MultiPoint","coordinates":[]}
...

Sheet LakeVictoriaSouth_Subbasin_Mont
A1: system:index | B1: Year | C1: Month | D1: Subbasin_ID | E1: area_m2 | F1: mean_rf_mm | G1: .geo
A2: 0 | B2: 2018 | C2: 1 | E2: 60992067 | F2: 29.05052 | G2: {"type":"MultiPoint","coordinates":[]} | J2: Year | K2: Year | L2: Year | M2: Year | N2: Year | O2: Year | P2: Year
A3: 1 | B3: 2018 | C3: 1 | D3: 1GE | E3: 3.9188315e+08 | F3: 25.531527 | G3: {"type":"MultiPoint","coordinates":[]} | I3: Month | J3: 2018 | K3: 2019 | L3: 2020 | M3: 2021 | N3: 2022 | O3: 2023 | P3: 2024
A4: 2 | B4: 2018 | C4: 1 | D4: 1GD | E4: 7.210051e+08 | F4: 24.271736 | G4: {"type":"MultiPoint","coordinates":[]} | I4: 1 | J4: =AVERAGEIFS($F:$F,$B:$B,J$3,$C:$C,$I4) -> 39.35118 | K4: =AVERAGEIFS($F:$F,$B:$B,K$3,$C:$C,$I4) -> 25.431682 | L4: =AVERAGEIFS($F:$F,$B:$B,L$3,$C:$C,$I4) -> 149.65933 | M4: =AVERAGEIFS($F:$F,$B:$B,M$3,$C:$C,$I4) -> 84.917832 | N4: =AVERAGEIFS($F:$F,$B:$B,N$3,$C:$C,$I4) -> 130.13121 | O4: =AVERAGEIFS($F:$F,$B:$B,O$3,$C:$C,$I4) -> 22.112507 | P4: =AVERAGEIFS($F:$F,$B:$B,P$3,$C:$C,$I4) -> 191.90627
A5: 3 | B5: 2018 | C5: 1 | D5: 1GB | E5: 5.179049e+08 | F5: 23.386028 | G5: {"type":"MultiPoint","coordinates":[]} | I5: 2 | J5: =AVERAGEIFS($F:$F,$B:$B,J$3,$C:$C,$I5) -> 50.325771 | K5: =AVERAGEIFS($F:$F,$B:$B,K$3,$C:$C,$I5) -> 50.999787 | L5: =AVERAGEIFS($F:$F,$B:$B,L$3,$C:$C,$I5) -> 89.497822 | M5: =AVERAGEIFS($F:$F,$B:$B,M$3,$C:$C,$I5) -> 107.64276 | N5: =AVERAGEIFS($F:$F,$B:$B,N$3,$C:$C,$I5) -> 223.75729 | O5: =AVERAGEIFS($F:$F,$B:$B,O$3,$C:$C,$I5) -> 16.793003 | P5: =AVERAGEIFS($F:$F,$B:$B,P$3,$C:$C,$I5) -> 117.89708
A6: 4 | B6: 2018 | C6: 1 | D6: 1GC | E6: 9.1360535e+08 | F6: 17.155477 | G6: {"type":"MultiPoint","coordinates":[]} | I6: 3 | J6: =AVERAGEIFS($F:$F,$B:$B,J$3,$C:$C,$I6) -> 239.98432 | K6: =AVERAGEIFS($F:$F,$B:$B,K$3,$C:$C,$I6) -> 76.271464 | L6: =AVERAGEIFS($F:$F,$B:$B,L$3,$C:$C,$I6) -> 284.6017 | M6: =AVERAGEIFS($F:$F,$B:$B,M$3,$C:$C,$I6) -> 106.46585 | N6: =AVERAGEIFS($F:$F,$B:$B,N$3,$C:$C,$I6) -> 118.03388 | O6: =AVERAGEIFS($F:$F,$B:$B,O$3,$C:$C,$I6) -> 239.25315 | P6: =AVERAGEIFS($F:$F,$B:$B,P$3,$C:$C,$I6) -> 132.20051
A7: 5 | B7: 2018 | C7: 1 | D7: 1GA | E7: 4.4259285e+08 | F7: 23.471674 | G7: {"type":"MultiPoint","coordinates":[]} | I7: 4 | J7: =AVERAGEIFS($F:$F,$B:$B,J$3,$C:$C,$I7) -> 340.49061 | K7: =AVERAGEIFS($F:$F,$B:$B,K$3,$C:$C,$I7) -> 179.74158 | L7: =AVERAGEIFS($F:$F,$B:$B,L$3,$C:$C,$I7) -> 289.06966 | M7: =AVERAGEIFS($F:$F,$B:$B,M$3,$C:$C,$I7) -> 285.89974 | N7: =AVERAGEIFS($F:$F,$B:$B,N$3,$C:$C,$I7) -> 198.07843 | O7: =AVERAGEIFS($F:$F,$B:$B,O$3,$C:$C,$I7) -> 264.46509 | P7: =AVERAGEIFS($F:$F,$B:$B,P$3,$C:$C,$I7) -> 271.16244
A8: 6 | B8: 2018 | C8: 1 | D8: 1GF | E8: 2.6889632e+08 | F8: 29.2862 | G8: {"type":"MultiPoint","coordinates":[]} | I8: 5 | J8: =AVERAGEIFS($F:$F,$B:$B,J$3,$C:$C,$I8) -> 253.28902 | K8: =AVERAGEIFS($F:$F,$B:$B,K$3,$C:$C,$I8) -> 185.77616 | L8: =AVERAGEIFS($F:$F,$B:$B,L$3,$C:$C,$I8) -> 169.11497 | M8: =AVERAGEIFS($F:$F,$B:$B,M$3,$C:$C,$I8) -> 227.17554 | N8: =AVERAGEIFS($F:$F,$B:$B,N$3,$C:$C,$I8) -> 218.22706 | O8: =AVERAGEIFS($F:$F,$B:$B,O$3,$C:$C,$I8) -> 173.31445 | P8: =AVERAGEIFS($F:$F,$B:$B,P$3,$C:$C,$I8) -> 194.27127
A9: 7 | B9: 2018 | C9: 1 | D9: 1GG | E9: 3.7443863e+08 | F9: 18.534629 | G9: {"type":"MultiPoint","coordinates":[]} | I9: 6 | J9: =AVERAGEIFS($F:$F,$B:$B,J$3,$C:$C,$I9) -> 166.43969 | K9: =AVERAGEIFS($F:$F,$B:$B,K$3,$C:$C,$I9) -> 165.11031 | L9: =AVERAGEIFS($F:$F,$B:$B,L$3,$C:$C,$I9) -> 140.68638 | M9: =AVERAGEIFS($F:$F,$B:$B,M$3,$C:$C,$I9) -> 85.150512 | N9: =AVERAGEIFS($F:$F,$B:$B,N$3,$C:$C,$I9) -> 97.240222 | O9: =AVERAGEIFS($F:$F,$B:$B,O$3,$C:$C,$I9) -> 146.82097 | P9: =AVERAGEIFS($F:$F,$B:$B,P$3,$C:$C,$I9) -> 71.00041
A10: 8 | B10: 2018 | C10: 1 | D10: 1HG | E10: 3.7321124e+08 | F10: 35.584976 | G10: {"type":"MultiPoint","coordinates":[]} | I10: 7 | J10: =AVERAGEIFS($F:$F,$B:$B,J$3,$C:$C,$I10) -> 84.358495 | K10: =AVERAGEIFS($F:$F,$B:$B,K$3,$C:$C,$I10) -> 106.91301 | L10: =AVERAGEIFS($F:$F,$B:$B,L$3,$C:$C,$I10) -> 131.73458 | M10: =AVERAGEIFS($F:$F,$B:$B,M$3,$C:$C,$I10) -> 78.650504 | N10: =AVERAGEIFS($F:$F,$B:$B,N$3,$C:$C,$I10) -> 73.836336 | O10: =AVERAGEIFS($F:$F,$B:$B,O$3,$C:$C,$I10) -> 60.318543 | P10: =AVERAGEIFS($F:$F,$B:$B,P$3,$C:$C,$I10) -> 127.46658
A11: 9 | B11: 2018 | C11: 1 | D11: 1HB | E11: 7.641634e+08 | F11: 30.033098 | G11: {"type":"MultiPoint","coordinates":[]} | I11: 8 | J11: =AVERAGEIFS($F:$F,$B:$B,J$3,$C:$C,$I11) -> 121.85281 | K11: =AVERAGEIFS($F:$F,$B:$B,K$3,$C:$C,$I11) -> 129.2058 | L11: =AVERAGEIFS($F:$F,$B:$B,L$3,$C:$C,$I11) -> 147.23925 | M11: =AVERAGEIFS($F:$F,$B:$B,M$3,$C:$C,$I11) -> 150.31397 | N11: =AVERAGEIFS($F:$F,$B:$B,N$3,$C:$C,$I11) -> 209.99247 | O11: =AVERAGEIFS($F:$F,$B:$B,O$3,$C:$C,$I11) -> 84.423045 | P11: =AVERAGEIFS($F:$F,$B:$B,P$3,$C:$C,$I11) -> 116.56345
A12: 10 | B12: 2018 | C12: 1 | D12: 1HA | E12: 8.5861782e+08 | F12: 31.197757 | G12: {"type":"MultiPoint","coordinates":[]} | I12: 9 | J12: =AVERAGEIFS($F:$F,$B:$B,J$3,$C:$C,$I12) -> 60.935926 | K12: =AVERAGEIFS($F:$F,$B:$B,K$3,$C:$C,$I12) -> 125.57144 | L12: =AVERAGEIFS($F:$F,$B:$B,L$3,$C:$C,$I12) -> 151.83335 | M12: =AVERAGEIFS($F:$F,$B:$B,M$3,$C:$C,$I12) -> 164.07086 | N12: =AVERAGEIFS($F:$F,$B:$B,N$3,$C:$C,$I12) -> 146.65812 | O12: =AVERAGEIFS($F:$F,$B:$B,O$3,$C:$C,$I12) -> 195.35032 | P12: =AVERAGEIFS($F:$F,$B:$B,P$3,$C:$C,$I12) -> 101.15678
A13: 11 | B13: 2018 | C13: 1 | D13: 1HF | E13: 8.7637017e+08 | F13: 33.915836 | G13: {"type":"MultiPoint","coordinates":[]} | I13: 10 | J13: =AVERAGEIFS($F:$F,$B:$B,J$3,$C:$C,$I13) -> 159.22859 | K13: =AVERAGEIFS($F:$F,$B:$B,K$3,$C:$C,$I13) -> 235.76735 | L13: =AVERAGEIFS($F:$F,$B:$B,L$3,$C:$C,$I13) -> 223.80097 | M13: =AVERAGEIFS($F:$F,$B:$B,M$3,$C:$C,$I13) -> 107.51711 | N13: =AVERAGEIFS($F:$F,$B:$B,N$3,$C:$C,$I13) -> 89.642314 | O13: =AVERAGEIFS($F:$F,$B:$B,O$3,$C:$C,$I13) -> 179.53513 | P13: =AVERAGEIFS($F:$F,$B:$B,P$3,$C:$C,$I13) -> 115.62494
A14: 12 | B14: 2018 | C14: 1 | D14: 1HE | E14: 8.047415e+08 | F14: 35.155488 | G14: {"type":"MultiPoint","coordinates":[]} | I14: 11 | J14: =AVERAGEIFS($F:$F,$B:$B,J$3,$C:$C,$I14) -> 92.856422 | K14: =AVERAGEIFS($F:$F,$B:$B,K$3,$C:$C,$I14) -> 208.94198 | L14: =AVERAGEIFS($F:$F,$B:$B,L$3,$C:$C,$I14) -> 335.95415 | M14: =AVERAGEIFS($F:$F,$B:$B,M$3,$C:$C,$I14) -> 104.10688 | N14: =AVERAGEIFS($F:$F,$B:$B,N$3,$C:$C,$I14) -> 206.175 | O14: =AVERAGEIFS($F:$F,$B:$B,O$3,$C:$C,$I14) -> 221.37019 | P14: =AVERAGEIFS($F:$F,$B:$B,P$3,$C:$C,$I14) -> 219.65466
A15: 13 | B15: 2018 | C15: 1 | D15: 1HC | E15: 6.1786161e+08 | F15: 29.427796 | G15: {"type":"MultiPoint","coordinates":[]} | I15: 12 | J15: =AVERAGEIFS($F:$F,$B:$B,J$3,$C:$C,$I15) -> 139.11977 | K15: =AVERAGEIFS($F:$F,$B:$B,K$3,$C:$C,$I15) -> 254.32632 | L15: =AVERAGEIFS($F:$F,$B:$B,L$3,$C:$C,$I15) -> 85.793689 | M15: =AVERAGEIFS($F:$F,$B:$B,M$3,$C:$C,$I15) -> 82.782837 | N15: =AVERAGEIFS($F:$F,$B:$B,N$3,$C:$C,$I15) -> 218.69032 | O15: =AVERAGEIFS($F:$F,$B:$B,O$3,$C:$C,$I15) -> 124.33878 | P15: =AVERAGEIFS($F:$F,$B:$B,P$3,$C:$C,$I15) -> 112.31998
A16: 14 | B16: 2018 | C16: 1 | D16: 1HD | E16: 7.8579194e+08 | F16: 33.808396 | G16: {"type":"MultiPoint","coordinates":[]}
A17: 15 | B17: 2018 | C17: 1 | D17: 1JA | E17: 7.5015032e+08 | F17: 25.953881 | G17: {"type":"MultiPoint","coordinates":[]} | I17: TotalAnnual Rf | J17: =SUM(J4:J15) -> 1748.2326 | K17: =SUM(K4:K15) -> 1744.0569 | L17: =SUM(L4:L15) -> 2198.9859 | M17: =SUM(M4:M15) -> 1584.6944 | N17: =SUM(N4:N15) -> 1930.4626 | O17: =SUM(O4:O15) -> 1728.0952 | P17: =SUM(P4:P15) -> 1771.2244
A18: 16 | B18: 2018 | C18: 1 | D18: 1JE | E18: 6.0134782e+08 | F18: 58.199129 | G18: {"type":"MultiPoint","coordinates":[]}
A19: 17 | B19: 2018 | C19: 1 | D19: 1JB | E19: 2.6183888e+08 | F19: 31.650935 | G19: {"type":"MultiPoint","coordinates":[]}
A20: 18 | B20: 2018 | C20: 1 | D20: 1JF | E20: 1.0098121e+09 | F20: 40.8202 | G20: {"type":"MultiPoint","coordinates":[]} | I20: WB_Area_sqkm | J20: ='Lakes Area'!$D$3/1000000 -> 22.750702 | K20: ='Lakes Area'!$D$3/1000000 -> 22.750702 | L20: ='Lakes Area'!$D$3/1000000 -> 22.750702 | M20: ='Lakes Area'!$D$3/1000000 -> 22.750702 | N20: ='Lakes Area'!$D$3/1000000 -> 22.750702 | O20: ='Lakes Area'!$D$3/1000000 -> 22.750702 | P20: ='Lakes Area'!$D$3/1000000 -> 22.750702
A21: 19 | B21: 2018 | C21: 1 | D21: 1JD | E21: 2.1350576e+08 | F21: 26.017339 | G21: {"type":"MultiPoint","coordinates":[]} | I21: Basin_Area_sqkm | J21: 22507 | K21: 22507 | L21: 22507 | M21: 22507 | N21: 22507 | O21: 22507 | P21: 22507
A22: 20 | B22: 2018 | C22: 1 | D22: 1JG | E22: 3.3065365e+08 | F22: 30.777678 | G22: {"type":"MultiPoint","coordinates":[]} | I22: proportion(WB/BA)
A23: 21 | B23: 2018 | C23: 1 | D23: 1JC | E23: 3.4031747e+08 | F23: 25.587328 | G23: {"type":"MultiPoint","coordinates":[]} | I23: TotalRf_mm | J23: =J17 -> 1748.2326 | K23: =K17 -> 1744.0569 | L23: =L17 -> 2198.9859 | M23: =M17 -> 1584.6944 | N23: =N17 -> 1930.4626 | O23: =O17 -> 1728.0952 | P23: =P17 -> 1771.2244
A24: 22 | B24: 2018 | C24: 1 | D24: 1KA | E24: 4.6290219e+08 | F24: 36.498057 | G24: {"type":"MultiPoint","coordinates":[]} | I24: Rainfall_MCM_on_Lake | J24: =(J23*100*J20*10)/1000000 -> 39.773518 | K24: =(K23*100*K20*10)/1000000 -> 39.678518 | L24: =(L23*100*L20*10)/1000000 -> 50.028472 | M24: =(M23*100*M20*10)/1000000 -> 36.05291 | N24: =(N23*100*N20*10)/1000000 -> 43.91938 | O24: =(O23*100*O20*10)/1000000 -> 39.315378 | P24: =(P23*100*P20*10)/1000000 -> 40.296597
A25: 23 | B25: 2018 | C25: 1 | D25: 1KC | E25: 2.8901703e+09 | F25: 66.925546 | G25: {"type":"MultiPoint","coordinates":[]} | I25: BASIN_MAR
A26: 24 | B26: 2018 | C26: 1 | D26: 1KB | E26: 3.5350283e+09 | F26: 45.175088 | G26: {"type":"MultiPoint","coordinates":[]}
A27: 25 | B27: 2018 | C27: 1 | D27: 1LA3 | E27: 2.8945988e+09 | F27: 117.31373 | G27: {"type":"MultiPoint","coordinates":[]}
A28: 26 | B28: 2018 | C28: 1 | D28: 1LB1 | E28: 1.4526325e+09 | F28: 56.477007 | G28: {"type":"MultiPoint","coordinates":[]}
A29: 27 | B29: 2018 | C29: 1 | D29: 1LB2 | E29: 2.7210238e+09 | F29: 88.316163 | G29: {"type":"MultiPoint","coordinates":[]}
A30: 28 | B30: 2018 | C30: 1 | D30: 1LA2 | E30: 1.004232e+09 | F30: 65.392878 | G30: {"type":"MultiPoint","coordinates":[]}
A31: 29 | B31: 2018 | C31: 1 | D31: 1LA1 | E31: 9.1374606e+08 | F31: 45.619318 | G31: {"type":"MultiPoint","coordinates":[]}
A32: 30 | B32: 2018 | C32: 2 | E32: 60992067 | F32: 56.834233 | G32: {"type":"MultiPoint","coordinates":[]}
A33: 31 | B33: 2018 | C33: 2 | D33: 1GE | E33: 3.9188315e+08 | F33: 52.791926 | G33: {"type":"MultiPoint","coordinates":[]}
A34: 32 | B34: 2018 | C34: 2 | D34: 1GD | E34: 7.210051e+08 | F34: 61.62308 | G34: {"type":"MultiPoint","coordinates":[]}
A35: 33 | B35: 2018 | C35: 2 | D35: 1GB | E35: 5.179049e+08 | F35: 56.975294 | G35: {"type":"MultiPoint","coordinates":[]}
A36: 34 | B36: 2018 | C36: 2 | D36: 1GC | E36: 9.1360535e+08 | F36: 33.369995 | G36: {"type":"MultiPoint","coordinates":[]}
A37: 35 | B37: 2018 | C37: 2 | D37: 1GA | E37: 4.4259285e+08 | F37: 37.856925 | G37: {"type":"MultiPoint","coordinates":[]}
A38: 36 | B38: 2018 | C38: 2 | D38: 1GF | E38: 2.6889632e+08 | F38: 44.160729 | G38: {"type":"MultiPoint","coordinates":[]}
A39: 37 | B39: 2018 | C39: 2 | D39: 1GG | E39: 3.7443863e+08 | F39: 34.65834 | G39: {"type":"MultiPoint","coordinates":[]}
A40: 38 | B40: 2018 | C40: 2 | D40: 1HG | E40: 3.7321124e+08 | F40: 74.912705 | G40: {"type":"MultiPoint","coordinates":[]}
A41: 39 | B41: 2018 | C41: 2 | D41: 1HB | E41: 7.641634e+08 | F41: 73.210745 | G41: {"type":"MultiPoint","coordinates":[]}
A42: 40 | B42: 2018 | C42: 2 | D42: 1HA | E42: 8.5861782e+08 | F42: 67.494029 | G42: {"type":"MultiPoint","coordinates":[]}
A43: 41 | B43: 2018 | C43: 2 | D43: 1HF | E43: 8.7637017e+08 | F43: 58.095098 | G43: {"type":"MultiPoint","coordinates":[]}
A44: 42 | B44: 2018 | C44: 2 | D44: 1HE | E44: 8.047415e+08 | F44: 47.960718 | G44: {"type":"MultiPoint","coordinates":[]}
... A61: 59 | B61: 2018 | C61: 2 | D61: 1LA1 | E61: 9.1374606e+08 | F61: 38.03583 | G61: {"type":"MultiPoint","coordinates":[]}
A62: 60 | B62: 2018 | C62: 3 | E62: 60992067 | F62: 121.88287 | G62: {"type":"MultiPoint","coordinates":[]}
A63: 61 | B63: 2018 | C63: 3 | D63: 1GE | E63: 3.9188315e+08 | F63: 253.35045 | G63: {"type":"MultiPoint","coordinates":[]}
A64: 62 | B64: 2018 | C64: 3 | D64: 1GD | E64: 7.210051e+08 | F64: 296.95757 | G64: {"type":"MultiPoint","coordinates":[]}
A65: 63 | B65: 2018 | C65: 3 | D65: 1GB | E65: 5.179049e+08 | F65: 261.41999 | G65: {"type":"MultiPoint","coordinates":[]}
A66: 64 | B66: 2018 | C66: 3 | D66: 1GC | E66: 9.1360535e+08 | F66: 221.55798 | G66: {"type":"MultiPoint","coordinates":[]}
A67: 65 | B67: 2018 | C67: 3 | D67: 1GA | E67: 4.4259285e+08 | F67: 230.81293 | G67: {"type":"MultiPoint","coordinates":[]}
A68: 66 | B68: 2018 | C68: 3 | D68: 1GF | E68: 2.6889632e+08 | F68: 240.7569 | G68: {"type":"MultiPoint","coordinates":[]}
A69: 67 | B69: 2018 | C69: 3 | D69: 1GG | E69: 3.7443863e+08 | F69: 223.82142 | G69: {"type":"MultiPoint","coordinates":[]}
A70: 68 | B70: 2018 | C70: 3 | D70: 1HG | E70: 3.7321124e+08 | F70: 166.17552 | G70: {"type":"MultiPoint","coordinates":[]}
A71: 69 | B71: 2018 | C71: 3 | D71: 1HB | E71: 7.641634e+08 | F71: 250.37537 | G71: {"type":"MultiPoint","coordinates":[]}
A72: 70 | B72: 2018 | C72: 3 | D72: 1HA | E72: 8.5861782e+08 | F72: 287.08981 | G72: {"type":"MultiPoint","coordinates":[]}
A73: 71 | B73: 2018 | C73: 3 | D73: 1HF | E73: 8.7637017e+08 | F73: 175.21881 | G73: {"type":"MultiPoint","coordinates":[]}
A74: 72 | B74: 2018 | C74: 3 | D74: 1HE | E74: 8.047415e+08 | F74: 206.93729 | G74: {"type":"MultiPoint","coordinates":[]}
... A91: 89 | B91: 2018 | C91: 3 | D91: 1LA1 | E91: 9.1374606e+08 | F91: 256.73851 | G91: {"type":"MultiPoint","coordinates":[]}
A92: 90 | B92: 2018 | C92: 4 | E92: 60992067 | F92: 275.5686 | G92: {"type":"MultiPoint","coordinates":[]}
A93: 91 | B93: 2018 | C93: 4 | D93: 1GE | E93: 3.9188315e+08 | F93: 365.13407 | G93: {"type":"MultiPoint","coordinates":[]}
A94: 92 | B94: 2018 | C94: 4 | D94: 1GD | E94: 7.210051e+08 | F94: 359.90256 | G94: {"type":"MultiPoint","coordinates":[]}
A95: 93 | B95: 2018 | C95: 4 | D95: 1GB | E95: 5.179049e+08 | F95: 392.57246 | G95: {"type":"MultiPoint","coordinates":[]}
A96: 94 | B96: 2018 | C96: 4 | D96: 1GC | E96: 9.1360535e+08 | F96: 370.51825 | G96: {"type":"MultiPoint","coordinates":[]}
A97: 95 | B97: 2018 | C97: 4 | D97: 1GA | E97: 4.4259285e+08 | F97: 408.03048 | G97: {"type":"MultiPoint","coordinates":[]}
A98: 96 | B98: 2018 | C98: 4 | D98: 1GF | E98: 2.6889632e+08 | F98: 336.47226 | G98: {"type":"MultiPoint","coordinates":[]}
A99: 97 | B99: 2018 | C99: 4 | D99: 1GG | E99: 3.7443863e+08 | F99: 374.11973 | G99: {"type":"MultiPoint","coordinates":[]}
A100: 98 | B100: 2018 | C100: 4 | D100: 1HG | E100: 3.7321124e+08 | F100: 244.73215 | G100: {"type":"MultiPoint","coordinates":[]}
A101: 99 | B101: 2018 | C101: 4 | D101: 1HB | E101: 7.641634e+08 | F101: 297.74528 | G101: {"type":"MultiPoint","coordinates":[]}
A102: 100 | B102: 2018 | C102: 4 | D102: 1HA | E102: 8.5861782e+08 | F102: 354.38006 | G102: {"type":"MultiPoint","coordinates":[]}
A103: 101 | B103: 2018 | C103: 4 | D103: 1HF | E103: 8.7637017e+08 | F103: 252.00671 | G103: {"type":"MultiPoint","coordinates":[]}
A104: 102 | B104: 2018 | C104: 4 | D104: 1HE | E104: 8.047415e+08 | F104: 277.63048 | G104: {"type":"MultiPoint","coordinates":[]}
... A121: 119 | B121: 2018 | C121: 4 | D121: 1LA1 | E121: 9.1374606e+08 | F121: 372.98981 | G121: {"type":"MultiPoint","coordinates":[]}
A122: 120 | B122: 2018 | C122: 5 | E122: 60992067 | F122: 193.13048 | G122: {"type":"MultiPoint","coordinates":[]}
A123: 121 | B123: 2018 | C123: 5 | D123: 1GE | E123: 3.9188315e+08 | F123: 270.09844 | G123: {"type":"MultiPoint","coordinates":[]}
A124: 122 | B124: 2018 | C124: 5 | D124: 1GD | E124: 7.210051e+08 | F124: 239.68573 | G124: {"type":"MultiPoint","coordinates":[]}
A125: 123 | B125: 2018 | C125: 5 | D125: 1GB | E125: 5.179049e+08 | F125: 238.82916 | G125: {"type":"MultiPoint","coordinates":[]}
A126: 124 | B126: 2018 | C126: 5 | D126: 1GC | E126: 9.1360535e+08 | F126: 275.06037 | G126: {"type":"MultiPoint","coordinates":[]}
A127: 125 | B127: 2018 | C127: 5 | D127: 1GA | E127: 4.4259285e+08 | F127: 257.35224 | G127: {"type":"MultiPoint","coordinates":[]}
A128: 126 | B128: 2018 | C128: 5 | D128: 1GF | E128: 2.6889632e+08 | F128: 258.29574 | G128: {"type":"MultiPoint","coordinates":[]}
A129: 127 | B129: 2018 | C129: 5 | D129: 1GG | E129: 3.7443863e+08 | F129: 252.95212 | G129: {"type":"MultiPoint","coordinates":[]}
A130: 128 | B130: 2018 | C130: 5 | D130: 1HG | E130: 3.7321124e+08 | F130: 213.09537 | G130: {"type":"MultiPoint","coordinates":[]}
A131: 129 | B131: 2018 | C131: 5 | D131: 1HB | E131: 7.641634e+08 | F131: 279.87476 | G131: {"type":"MultiPoint","coordinates":[]}
A132: 130 | B132: 2018 | C132: 5 | D132: 1HA | E132: 8.5861782e+08 | F132: 270.98486 | G132: {"type":"MultiPoint","coordinates":[]}
A133: 131 | B133: 2018 | C133: 5 | D133: 1HF | E133: 8.7637017e+08 | F133: 222.90338 | G133: {"type":"MultiPoint","coordinates":[]}
A134: 132 | B134: 2018 | C134: 5 | D134: 1HE | E134: 8.047415e+08 | F134: 269.18195 | G134: {"type":"MultiPoint","coordinates":[]}
... A151: 149 | B151: 2018 | C151: 5 | D151: 1LA1 | E151: 9.1374606e+08 | F151: 328.65561 | G151: {"type":"MultiPoint","coordinates":[]}
A152: 150 | B152: 2018 | C152: 6 | E152: 60992067 | F152: 106.66574 | G152: {"type":"MultiPoint","coordinates":[]}
A153: 151 | B153: 2018 | C153: 6 | D153: 1GE | E153: 3.9188315e+08 | F153: 185.51668 | G153: {"type":"MultiPoint","coordinates":[]}
A154: 152 | B154: 2018 | C154: 6 | D154: 1GD | E154: 7.210051e+08 | F154: 189.05015 | G154: {"type":"MultiPoint","coordinates":[]}
A155: 153 | B155: 2018 | C155: 6 | D155: 1GB | E155: 5.179049e+08 | F155: 205.33752 | G155: {"type":"MultiPoint","coordinates":[]}
A156: 154 | B156: 2018 | C156: 6 | D156: 1GC | E156: 9.1360535e+08 | F156: 301.4864 | G156: {"type":"MultiPoint","coordinates":[]}
A157: 155 | B157: 2018 | C157: 6 | D157: 1GA | E157: 4.4259285e+08 | F157: 270.94598 | G157: {"type":"MultiPoint","coordinates":[]}
A158: 156 | B158: 2018 | C158: 6 | D158: 1GF | E158: 2.6889632e+08 | F158: 145.25528 | G158: {"type":"MultiPoint","coordinates":[]}
A159: 157 | B159: 2018 | C159: 6 | D159: 1GG | E159: 3.7443863e+08 | F159: 271.70607 | G159: {"type":"MultiPoint","coordinates":[]}
A160: 158 | B160: 2018 | C160: 6 | D160: 1HG | E160: 3.7321124e+08 | F160: 82.821219 | G160: {"type":"MultiPoint","coordinates":[]}
A161: 159 | B161: 2018 | C161: 6 | D161: 1HB | E161: 7.641634e+08 | F161: 114.72279 | G161: {"type":"MultiPoint","coordinates":[]}
A162: 160 | B162: 2018 | C162: 6 | D162: 1HA | E162: 8.5861782e+08 | F162: 140.00181 | G162: {"type":"MultiPoint","coordinates":[]}
A163: 161 | B163: 2018 | C163: 6 | D163: 1HF | E163: 8.7637017e+08 | F163: 96.464031 | G163: {"type":"MultiPoint","coordinates":[]}
A164: 162 | B164: 2018 | C164: 6 | D164: 1HE | E164: 8.047415e+08 | F164: 139.32383 | G164: {"type":"MultiPoint","coordinates":[]}
...

Sheet AthiBasin_Subbasin_Monthly
A1: system:index | B1: Year | C1: Month | D1: Subbasin_ID | E1: area_m2 | F1: mean_rf_mm | G1: .geo | I1: Year | J1: Year | K1: Year | L1: Year | M1: Year | N1: Year | O1: Year
A2: 0 | B2: 2018 | C2: 1 | D2: 4CA | E2: 5.3882945e+08 | F2: 59.917438 | G2: {"type":"MultiPoint","coordinates":[]} | H2: Month | I2: 2018 | J2: 2019 | K2: 2020 | L2: 2021 | M2: 2022 | N2: 2023 | O2: 2024
A3: 1 | B3: 2018 | C3: 1 | D3: 3BD | E3: 3.2966944e+08 | F3: 40.589688 | G3: {"type":"MultiPoint","coordinates":[]} | H3: 1 | I3: =AVERAGEIFS($F:$F,$B:$B,I$2,$C:$C,$H3) -> 28.833024 | J3: =AVERAGEIFS($F:$F,$B:$B,J$2,$C:$C,$H3) -> 22.091912 | K3: =AVERAGEIFS($F:$F,$B:$B,K$2,$C:$C,$H3) -> 112.93936 | L3: =AVERAGEIFS($F:$F,$B:$B,L$2,$C:$C,$H3) -> 38.96405 | M3: =AVERAGEIFS($F:$F,$B:$B,M$2,$C:$C,$H3) -> 27.194327 | N3: =AVERAGEIFS($F:$F,$B:$B,N$2,$C:$C,$H3) -> 22.586906 | O3: =AVERAGEIFS($F:$F,$B:$B,O$2,$C:$C,$H3) -> 77.917308
A4: 2 | B4: 2018 | C4: 1 | D4: 3BC | E4: 4.7760072e+08 | F4: 45.579408 | G4: {"type":"MultiPoint","coordinates":[]} | H4: 2 | I4: =AVERAGEIFS(F:F,B:B,I$2,C:C,$H4) -> 17.551603 | J4: =AVERAGEIFS($F:$F,$B:$B,J$2,$C:$C,$H4) -> 19.148915 | K4: =AVERAGEIFS($F:$F,$B:$B,K$2,$C:$C,$H4) -> 47.093009 | L4: =AVERAGEIFS($F:$F,$B:$B,L$2,$C:$C,$H4) -> 42.094603 | M4: =AVERAGEIFS($F:$F,$B:$B,M$2,$C:$C,$H4) -> 34.745167 | N4: =AVERAGEIFS($F:$F,$B:$B,N$2,$C:$C,$H4) -> 5.1480191 | O4: =AVERAGEIFS($F:$F,$B:$B,O$2,$C:$C,$H4) -> 36.101971
A5: 3 | B5: 2018 | C5: 1 | D5: 3BB | E5: 2.5779628e+08 | F5: 37.80965 | G5: {"type":"MultiPoint","coordinates":[]} | H5: 3 | I5: =AVERAGEIFS(F:F,B:B,I$2,C:C,$H5) -> 220.72412 | J5: =AVERAGEIFS($F:$F,$B:$B,J$2,$C:$C,$H5) -> 19.231266 | K5: =AVERAGEIFS($F:$F,$B:$B,K$2,$C:$C,$H5) -> 171.26005 | L5: =AVERAGEIFS($F:$F,$B:$B,L$2,$C:$C,$H5) -> 38.781561 | M5: =AVERAGEIFS($F:$F,$B:$B,M$2,$C:$C,$H5) -> 35.112168 | N5: =AVERAGEIFS($F:$F,$B:$B,N$2,$C:$C,$H5) -> 82.759207 | O5: =AVERAGEIFS($F:$F,$B:$B,O$2,$C:$C,$H5) -> 119.8075
A6: 4 | B6: 2018 | C6: 1 | D6: 3BA | E6: 8.3312886e+08 | F6: 43.046625 | G6: {"type":"MultiPoint","coordinates":[]} | H6: 4 | I6: =AVERAGEIFS(F:F,B:B,I$2,C:C,$H6) -> 317.33685 | J6: =AVERAGEIFS($F:$F,$B:$B,J$2,$C:$C,$H6) -> 116.73907 | K6: =AVERAGEIFS($F:$F,$B:$B,K$2,$C:$C,$H6) -> 328.61394 | L6: =AVERAGEIFS($F:$F,$B:$B,L$2,$C:$C,$H6) -> 113.16848 | M6: =AVERAGEIFS($F:$F,$B:$B,M$2,$C:$C,$H6) -> 135.19466 | N6: =AVERAGEIFS($F:$F,$B:$B,N$2,$C:$C,$H6) -> 221.75919 | O6: =AVERAGEIFS($F:$F,$B:$B,O$2,$C:$C,$H6) -> 381.44392
A7: 5 | B7: 2018 | C7: 1 | D7: 3AA | E7: 7.0083537e+08 | F7: 56.098205 | G7: {"type":"MultiPoint","coordinates":[]} | H7: 5 | I7: =AVERAGEIFS(F:F,B:B,I$2,C:C,$H7) -> 222.64322 | J7: =AVERAGEIFS($F:$F,$B:$B,J$2,$C:$C,$H7) -> 144.46777 | K7: =AVERAGEIFS($F:$F,$B:$B,K$2,$C:$C,$H7) -> 102.74981 | L7: =AVERAGEIFS($F:$F,$B:$B,L$2,$C:$C,$H7) -> 141.72629 | M7: =AVERAGEIFS($F:$F,$B:$B,M$2,$C:$C,$H7) -> 77.231823 | N7: =AVERAGEIFS($F:$F,$B:$B,N$2,$C:$C,$H7) -> 77.718936 | O7: =AVERAGEIFS($F:$F,$B:$B,O$2,$C:$C,$H7) -> 168.2701
A8: 6 | B8: 2018 | C8: 1 | D8: 3AB | E8: 1.7950716e+09 | F8: 54.097295 | G8: {"type":"MultiPoint","coordinates":[]} | H8: 6 | I8: =AVERAGEIFS(F:F,B:B,I$2,C:C,$H8) -> 58.010996 | J8: =AVERAGEIFS($F:$F,$B:$B,J$2,$C:$C,$H8) -> 45.055504 | K8: =AVERAGEIFS($F:$F,$B:$B,K$2,$C:$C,$H8) -> 61.105278 | L8: =AVERAGEIFS($F:$F,$B:$B,L$2,$C:$C,$H8) -> 23.544116 | M8: =AVERAGEIFS($F:$F,$B:$B,M$2,$C:$C,$H8) -> 32.226872 | N8: =AVERAGEIFS($F:$F,$B:$B,N$2,$C:$C,$H8) -> 33.446173 | O8: =AVERAGEIFS($F:$F,$B:$B,O$2,$C:$C,$H8) -> 35.986997
A9: 7 | B9: 2018 | C9: 1 | D9: 3FA | E9: 1.0046151e+10 | F9: 52.208256 | G9: {"type":"MultiPoint","coordinates":[]} | H9: 7 | I9: =AVERAGEIFS(F:F,B:B,I$2,C:C,$H9) -> 50.281302 | J9: =AVERAGEIFS($F:$F,$B:$B,J$2,$C:$C,$H9) -> 42.633974 | K9: =AVERAGEIFS($F:$F,$B:$B,K$2,$C:$C,$H9) -> 42.238894 | L9: =AVERAGEIFS($F:$F,$B:$B,L$2,$C:$C,$H9) -> 43.836685 | M9: =AVERAGEIFS($F:$F,$B:$B,M$2,$C:$C,$H9) -> 47.875571 | N9: =AVERAGEIFS($F:$F,$B:$B,N$2,$C:$C,$H9) -> 37.273823 | O9: =AVERAGEIFS($F:$F,$B:$B,O$2,$C:$C,$H9) -> 29.550262
A10: 8 | B10: 2018 | C10: 1 | D10: 3N | E10: 3.1613646e+09 | F10: 70.972994 | G10: {"type":"MultiPoint","coordinates":[]} | H10: 8 | I10: =AVERAGEIFS(F:F,B:B,I$2,C:C,$H10) -> 37.112089 | J10: =AVERAGEIFS($F:$F,$B:$B,J$2,$C:$C,$H10) -> 36.29135 | K10: =AVERAGEIFS($F:$F,$B:$B,K$2,$C:$C,$H10) -> 22.582064 | L10: =AVERAGEIFS($F:$F,$B:$B,L$2,$C:$C,$H10) -> 28.948185 | M10: =AVERAGEIFS($F:$F,$B:$B,M$2,$C:$C,$H10) -> 23.798012 | N10: =AVERAGEIFS($F:$F,$B:$B,N$2,$C:$C,$H10) -> 22.852519 | O10: =AVERAGEIFS($F:$F,$B:$B,O$2,$C:$C,$H10) -> 24.570912
A11: 9 | B11: 2018 | C11: 1 | D11: 4CB | E11: 3.1458028e+08 | F11: 46.040887 | G11: {"type":"MultiPoint","coordinates":[]} | H11: 9 | I11: =AVERAGEIFS(F:F,B:B,I$2,C:C,$H11) -> 38.827793 | J11: =AVERAGEIFS($F:$F,$B:$B,J$2,$C:$C,$H11) -> 38.439134 | K11: =AVERAGEIFS($F:$F,$B:$B,K$2,$C:$C,$H11) -> 30.187649 | L11: =AVERAGEIFS($F:$F,$B:$B,L$2,$C:$C,$H11) -> 16.44859 | M11: =AVERAGEIFS($F:$F,$B:$B,M$2,$C:$C,$H11) -> 18.859395 | N11: =AVERAGEIFS($F:$F,$B:$B,N$2,$C:$C,$H11) -> 22.249367 | O11: =AVERAGEIFS($F:$F,$B:$B,O$2,$C:$C,$H11) -> 18.866178
A12: 10 | B12: 2018 | C12: 1 | D12: 3CB | E12: 3.9691378e+08 | F12: 40.206401 | G12: {"type":"MultiPoint","coordinates":[]} | H12: 10 | I12: =AVERAGEIFS(F:F,B:B,I$2,C:C,$H12) -> 101.59547 | J12: =AVERAGEIFS($F:$F,$B:$B,J$2,$C:$C,$H12) -> 269.13996 | K12: =AVERAGEIFS($F:$F,$B:$B,K$2,$C:$C,$H12) -> 45.865082 | L12: =AVERAGEIFS($F:$F,$B:$B,L$2,$C:$C,$H12) -> 42.404027 | M12: =AVERAGEIFS($F:$F,$B:$B,M$2,$C:$C,$H12) -> 30.939193 | N12: =AVERAGEIFS($F:$F,$B:$B,N$2,$C:$C,$H12) -> 80.217569 | O12: =AVERAGEIFS($F:$F,$B:$B,O$2,$C:$C,$H12) -> 35.898724
A13: 11 | B13: 2018 | C13: 1 | D13: 3DA | E13: 8.1128388e+08 | F13: 22.925402 | G13: {"type":"MultiPoint","coordinates":[]} | H13: 11 | I13: =AVERAGEIFS(F:F,B:B,I$2,C:C,$H13) -> 105.14459 | J13: =AVERAGEIFS($F:$F,$B:$B,J$2,$C:$C,$H13) -> 247.18867 | K13: =AVERAGEIFS($F:$F,$B:$B,K$2,$C:$C,$H13) -> 166.42394 | L13: =AVERAGEIFS($F:$F,$B:$B,L$2,$C:$C,$H13) -> 107.41769 | M13: =AVERAGEIFS($F:$F,$B:$B,M$2,$C:$C,$H13) -> 155.25259 | N13: =AVERAGEIFS($F:$F,$B:$B,N$2,$C:$C,$H13) -> 385.33144 | O13: =AVERAGEIFS($F:$F,$B:$B,O$2,$C:$C,$H13) -> 205.28757
A14: 12 | B14: 2018 | C14: 1 | D14: 3DB | E14: 8.2735656e+08 | F14: 19.426859 | G14: {"type":"MultiPoint","coordinates":[]} | H14: 12 | I14: =AVERAGEIFS(F:F,B:B,I$2,C:C,$H14) -> 171.0216 | J14: =AVERAGEIFS($F:$F,$B:$B,J$2,$C:$C,$H14) -> 234.13362 | K14: =AVERAGEIFS($F:$F,$B:$B,K$2,$C:$C,$H14) -> 76.141685 | L14: =AVERAGEIFS($F:$F,$B:$B,L$2,$C:$C,$H14) -> 147.61106 | M14: =AVERAGEIFS($F:$F,$B:$B,M$2,$C:$C,$H14) -> 50.233083 | N14: =AVERAGEIFS($F:$F,$B:$B,N$2,$C:$C,$H14) -> 102.78056 | O14: =AVERAGEIFS($F:$F,$B:$B,O$2,$C:$C,$H14) -> 110.35546
A15: 13 | B15: 2018 | C15: 1 | D15: 3FB | E15: 4.2209466e+09 | F15: 12.374153 | G15: {"type":"MultiPoint","coordinates":[]}
A16: 14 | B16: 2018 | C16: 1 | D16: 3HC | E16: 2.9596072e+09 | F16: 7.1383426 | G16: {"type":"MultiPoint","coordinates":[]} | H16: TotalAnnual Rf_mm | I16: =SUM(I3:I14) -> 1369.0826 | J16: =SUM(J3:J14) -> 1234.5611 | K16: =SUM(K3:K14) -> 1207.2008 | L16: =SUM(L3:L14) -> 784.94534 | M16: =SUM(M3:M14) -> 668.66287 | N16: =SUM(N3:N14) -> 1094.1237 | O16: =SUM(O3:O14) -> 1244.0569
A17: 15 | B17: 2018 | C17: 1 | D17: 3HB | E17: 2.5106039e+09 | F17: 4.3301614 | G17: {"type":"MultiPoint","coordinates":[]}
A18: 16 | B18: 2018 | C18: 1 | D18: 3HA | E18: 9.2608382e+08 | F18: 5.747263 | G18: {"type":"MultiPoint","coordinates":[]}
A19: 17 | B19: 2018 | C19: 1 | D19: 3HD1 | E19: 6.322851e+08 | F19: 6.5979339 | G19: {"type":"MultiPoint","coordinates":[]} | H19: WB_Area_sqkm | I19: ='Lakes Area'!$D$2/1000000 -> 170.39735 | J19: ='Lakes Area'!$D$2/1000000 -> 170.39735 | K19: ='Lakes Area'!$D$2/1000000 -> 170.39735 | L19: ='Lakes Area'!$D$2/1000000 -> 170.39735 | M19: ='Lakes Area'!$D$2/1000000 -> 170.39735 | N19: ='Lakes Area'!$D$2/1000000 -> 170.39735 | O19: ='Lakes Area'!$D$2/1000000 -> 170.39735
A20: 18 | B20: 2018 | C20: 1 | E20: 1.7039735e+08 | F20: 59.829734 | G20: {"type":"MultiPoint","coordinates":[]} | H20: Basin_Area_sqkm | I20: ='Lakes Area'!$G$2/1000000 -> 66559 | J20: ='Lakes Area'!$G$2/1000000 -> 66559 | K20: ='Lakes Area'!$G$2/1000000 -> 66559 | L20: ='Lakes Area'!$G$2/1000000 -> 66559 | M20: ='Lakes Area'!$G$2/1000000 -> 66559 | N20: ='Lakes Area'!$G$2/1000000 -> 66559 | O20: ='Lakes Area'!$G$2/1000000 -> 66559
A21: 19 | B21: 2018 | C21: 1 | D21: 3AC | E21: 8.9214077e+08 | F21: 30.82615 | G21: {"type":"MultiPoint","coordinates":[]} | H21: proportion(WB/BA) | I21: =I19/I20 -> 0.0025600948 | J21: =J19/J20 -> 0.0025600948 | K21: =K19/K20 -> 0.0025600948 | L21: =L19/L20 -> 0.0025600948 | M21: =M19/M20 -> 0.0025600948 | N21: =N19/N20 -> 0.0025600948 | O21: =O19/O20 -> 0.0025600948
A22: 20 | B22: 2018 | C22: 1 | D22: 3EA | E22: 8.798824e+08 | F22: 28.525278 | G22: {"type":"MultiPoint","coordinates":[]} | H22: TotalRf_mm | I22: =I16 -> 1369.0826 | J22: =J16 -> 1234.5611 | K22: =K16 -> 1207.2008 | L22: =L16 -> 784.94534 | M22: =M16 -> 668.66287 | N22: =N16 -> 1094.1237 | O22: =O16 -> 1244.0569
A23: 21 | B23: 2018 | C23: 1 | D23: 3EB | E23: 8.0789592e+08 | F23: 27.750843 | G23: {"type":"MultiPoint","coordinates":[]} | H23: Rainfall_MCM_on_Lake | I23: =(I22*100*I19*10)/1000000 -> 233.28806 | J23: =(J22*100*J19*10)/1000000 -> 210.36595 | K23: =(K22*100*K19*10)/1000000 -> 205.70381 | L23: =(L22*100*L19*10)/1000000 -> 133.75261 | M23: =(M22*100*M19*10)/1000000 -> 113.93838 | N23: =(N22*100*N19*10)/1000000 -> 186.43578 | O23: =(O22*100*O19*10)/1000000 -> 211.984
A24: 22 | B24: 2018 | C24: 1 | D24: 3ED | E24: 5.7289114e+08 | F24: 22.963661 | G24: {"type":"MultiPoint","coordinates":[]} | H24: BASIN_MAR | I24: =I22*100*I20*10/1000000 -> 91124.772 | J24: =J22*100*J20*10/1000000 -> 82171.155 | K24: =K22*100*K20*10/1000000 -> 80350.076 | L24: =L22*100*L20*10/1000000 -> 52245.177 | M24: =M22*100*M20*10/1000000 -> 44505.532 | N24: =N22*100*N20*10/1000000 -> 72823.78 | O24: =O22*100*O20*10/1000000 -> 82803.183
A25: 23 | B25: 2018 | C25: 1 | D25: 3EC | E25: 6.7420896e+08 | F25: 42.109814 | G25: {"type":"MultiPoint","coordinates":[]}
A26: 24 | B26: 2018 | C26: 1 | D26: 3G | E26: 6.3021441e+09 | F26: 27.577393 | G26: {"type":"MultiPoint","coordinates":[]}
A27: 25 | B27: 2018 | C27: 1 | D27: 3LA | E27: 7.349765e+09 | F27: 7.7344066 | G27: {"type":"MultiPoint","coordinates":[]} | J27: =(I19*52248)/66559 -> 133.75983
A28: 26 | B28: 2018 | C28: 1 | D28: 3J | E28: 2.8072957e+09 | F28: 30.083497 | G28: {"type":"MultiPoint","coordinates":[]} | L28: =L23/L24 -> 0.0025600948
A29: 27 | B29: 2018 | C29: 1 | D29: 3LB | E29: 7.8841806e+08 | F29: 5.2997499 | G29: {"type":"MultiPoint","coordinates":[]}
A30: 28 | B30: 2018 | C30: 1 | D30: 3MA | E30: 6.1570601e+09 | F30: 17.594793 | G30: {"type":"MultiPoint","coordinates":[]}
A31: 29 | B31: 2018 | C31: 1 | D31: 3MB | E31: 1.7125789e+09 | F31: 5.1365623 | G31: {"type":"MultiPoint","coordinates":[]}
A32: 30 | B32: 2018 | C32: 1 | D32: 3MD1 | E32: 1.3043892e+09 | F32: 7.8775298 | G32: {"type":"MultiPoint","coordinates":[]}
A33: 31 | B33: 2018 | C33: 1 | D33: 3MC | E33: 1.0504051e+09 | F33: 14.158991 | G33: {"type":"MultiPoint","coordinates":[]}
A34: 32 | B34: 2018 | C34: 1 | D34: 3K | E34: 4.1095886e+09 | F34: 18.470851 | G34: {"type":"MultiPoint","coordinates":[]}
A35: 33 | B35: 2018 | C35: 1 | D35: 3MD2 | E35: 1.8771208e+08 | F35: 9.2766178 | G35: {"type":"MultiPoint","coordinates":[]}
A36: 34 | B36: 2018 | C36: 2 | D36: 4CA | E36: 5.3882945e+08 | F36: 44.141407 | G36: {"type":"MultiPoint","coordinates":[]}
A37: 35 | B37: 2018 | C37: 2 | D37: 3BD | E37: 3.2966944e+08 | F37: 28.381948 | G37: {"type":"MultiPoint","coordinates":[]}
A38: 36 | B38: 2018 | C38: 2 | D38: 3BC | E38: 4.7760072e+08 | F38: 29.988661 | G38: {"type":"MultiPoint","coordinates":[]}
A39: 37 | B39: 2018 | C39: 2 | D39: 3BB | E39: 2.5779628e+08 | F39: 30.010848 | G39: {"type":"MultiPoint","coordinates":[]}
A40: 38 | B40: 2018 | C40: 2 | D40: 3BA | E40: 8.3312886e+08 | F40: 31.876564 | G40: {"type":"MultiPoint","coordinates":[]}
... A53: 51 | B53: 2018 | C53: 2 | D53: 3HD1 | E53: 6.322851e+08 | F53: 6.8962948 | G53: {"type":"MultiPoint","coordinates":[]}
A54: 52 | B54: 2018 | C54: 2 | E54: 1.7039735e+08 | F54: 12.150809 | G54: {"type":"MultiPoint","coordinates":[]}
A55: 53 | B55: 2018 | C55: 2 | D55: 3AC | E55: 8.9214077e+08 | F55: 25.90552 | G55: {"type":"MultiPoint","coordinates":[]}
A56: 54 | B56: 2018 | C56: 2 | D56: 3EA | E56: 8.798824e+08 | F56: 31.773565 | G56: {"type":"MultiPoint","coordinates":[]}
A57: 55 | B57: 2018 | C57: 2 | D57: 3EB | E57: 8.0789592e+08 | F57: 25.310824 | G57: {"type":"MultiPoint","coordinates":[]}
A58: 56 | B58: 2018 | C58: 2 | D58: 3ED | E58: 5.7289114e+08 | F58: 18.101236 | G58: {"type":"MultiPoint","coordinates":[]}
A59: 57 | B59: 2018 | C59: 2 | D59: 3EC | E59: 6.7420896e+08 | F59: 25.52596 | G59: {"type":"MultiPoint","coordinates":[]}
A60: 58 | B60: 2018 | C60: 2 | D60: 3G | E60: 6.3021441e+09 | F60: 5.5399745 | G60: {"type":"MultiPoint","coordinates":[]}
A61: 59 | B61: 2018 | C61: 2 | D61: 3LA | E61: 7.349765e+09 | F61: 7.5925005 | G61: {"type":"MultiPoint","coordinates":[]}
A62: 60 | B62: 2018 | C62: 2 | D62: 3J | E62: 2.8072957e+09 | F62: 7.2891574 | G62: {"type":"MultiPoint","coordinates":[]}
A63: 61 | B63: 2018 | C63: 2 | D63: 3LB | E63: 7.8841806e+08 | F63: 5.4361553 | G63: {"type":"MultiPoint","coordinates":[]}
A64: 62 | B64: 2018 | C64: 2 | D64: 3MA | E64: 6.1570601e+09 | F64: 7.9256604 | G64: {"type":"MultiPoint","coordinates":[]}
A65: 63 | B65: 2018 | C65: 2 | D65: 3MB | E65: 1.7125789e+09 | F65: 9.4174385 | G65: {"type":"MultiPoint","coordinates":[]}
A66: 64 | B66: 2018 | C66: 2 | D66: 3MD1 | E66: 1.3043892e+09 | F66: 8.2435346 | G66: {"type":"MultiPoint","coordinates":[]}
... A87: 85 | B87: 2018 | C87: 3 | D87: 3HD1 | E87: 6.322851e+08 | F87: 108.26332 | G87: {"type":"MultiPoint","coordinates":[]}
A88: 86 | B88: 2018 | C88: 3 | E88: 1.7039735e+08 | F88: 260.60848 | G88: {"type":"MultiPoint","coordinates":[]}
A89: 87 | B89: 2018 | C89: 3 | D89: 3AC | E89: 8.9214077e+08 | F89: 233.1773 | G89: {"type":"MultiPoint","coordinates":[]}
A90: 88 | B90: 2018 | C90: 3 | D90: 3EA | E90: 8.798824e+08 | F90: 270.23663 | G90: {"type":"MultiPoint","coordinates":[]}
A91: 89 | B91: 2018 | C91: 3 | D91: 3EB | E91: 8.0789592e+08 | F91: 274.40309 | G91: {"type":"MultiPoint","coordinates":[]}
A92: 90 | B92: 2018 | C92: 3 | D92: 3ED | E92: 5.7289114e+08 | F92: 220.22648 | G92: {"type":"MultiPoint","coordinates":[]}
A93: 91 | B93: 2018 | C93: 3 | D93: 3EC | E93: 6.7420896e+08 | F93: 296.64867 | G93: {"type":"MultiPoint","coordinates":[]}
A94: 92 | B94: 2018 | C94: 3 | D94: 3G | E94: 6.3021441e+09 | F94: 278.07276 | G94: {"type":"MultiPoint","coordinates":[]}
A95: 93 | B95: 2018 | C95: 3 | D95: 3LA | E95: 7.349765e+09 | F95: 163.80607 | G95: {"type":"MultiPoint","coordinates":[]}
A96: 94 | B96: 2018 | C96: 3 | D96: 3J | E96: 2.8072957e+09 | F96: 273.80091 | G96: {"type":"MultiPoint","coordinates":[]}
A97: 95 | B97: 2018 | C97: 3 | D97: 3LB | E97: 7.8841806e+08 | F97: 86.646468 | G97: {"type":"MultiPoint","coordinates":[]}
A98: 96 | B98: 2018 | C98: 3 | D98: 3MA | E98: 6.1570601e+09 | F98: 210.86976 | G98: {"type":"MultiPoint","coordinates":[]}
A99: 97 | B99: 2018 | C99: 3 | D99: 3MB | E99: 1.7125789e+09 | F99: 140.34896 | G99: {"type":"MultiPoint","coordinates":[]}
A100: 98 | B100: 2018 | C100: 3 | D100: 3MD1 | E100: 1.3043892e+09 | F100: 127.36549 | G100: {"type":"MultiPoint","coordinates":[]}
... A121: 119 | B121: 2018 | C121: 4 | D121: 3HD1 | E121: 6.322851e+08 | F121: 235.76606 | G121: {"type":"MultiPoint","coordinates":[]}
A122: 120 | B122: 2018 | C122: 4 | E122: 1.7039735e+08 | F122: 238.58205 | G122: {"type":"MultiPoint","coordinates":[]}
A123: 121 | B123: 2018 | C123: 4 | D123: 3AC | E123: 8.9214077e+08 | F123: 314.20204 | G123: {"type":"MultiPoint","coordinates":[]}
A124: 122 | B124: 2018 | C124: 4 | D124: 3EA | E124: 8.798824e+08 | F124: 364.02569 | G124: {"type":"MultiPoint","coordinates":[]}
A125: 123 | B125: 2018 | C125: 4 | D125: 3EB | E125: 8.0789592e+08 | F125: 372.59776 | G125: {"type":"MultiPoint","coordinates":[]}
A126: 124 | B126: 2018 | C126: 4 | D126: 3ED | E126: 5.7289114e+08 | F126: 330.05041 | G126: {"type":"MultiPoint","coordinates":[]}
A127: 125 | B127: 2018 | C127: 4 | D127: 3EC | E127: 6.7420896e+08 | F127: 442.78493 | G127: {"type":"MultiPoint","coordinates":[]}
A128: 126 | B128: 2018 | C128: 4 | D128: 3G | E128: 6.3021441e+09 | F128: 248.44252 | G128: {"type":"MultiPoint","coordinates":[]}
A129: 127 | B129: 2018 | C129: 4 | D129: 3LA | E129: 7.349765e+09 | F129: 172.93578 | G129: {"type":"MultiPoint","coordinates":[]}
A130: 128 | B130: 2018 | C130: 4 | D130: 3J | E130: 2.8072957e+09 | F130: 216.94921 | G130: {"type":"MultiPoint","coordinates":[]}
A131: 129 | B131: 2018 | C131: 4 | D131: 3LB | E131: 7.8841806e+08 | F131: 276.94123 | G131: {"type":"MultiPoint","coordinates":[]}
A132: 130 | B132: 2018 | C132: 4 | D132: 3MA | E132: 6.1570601e+09 | F132: 187.22131 | G132: {"type":"MultiPoint","coordinates":[]}
A133: 131 | B133: 2018 | C133: 4 | D133: 3MB | E133: 1.7125789e+09 | F133: 170.48282 | G133: {"type":"MultiPoint","coordinates":[]}
A134: 132 | B134: 2018 | C134: 4 | D134: 3MD1 | E134: 1.3043892e+09 | F134: 208.41502 | G134: {"type":"MultiPoint","coordinates":[]}
... A155: 153 | B155: 2018 | C155: 5 | D155: 3HD1 | E155: 6.322851e+08 | F155: 342.13831 | G155: {"type":"MultiPoint","coordinates":[]}
A156: 154 | B156: 2018 | C156: 5 | E156: 1.7039735e+08 | F156: 21.756685 | G156: {"type":"MultiPoint","coordinates":[]}
A157: 155 | B157: 2018 | C157: 5 | D157: 3AC | E157: 8.9214077e+08 | F157: 154.75935 | G157: {"type":"MultiPoint","coordinates":[]}
A158: 156 | B158: 2018 | C158: 5 | D158: 3EA | E158: 8.798824e+08 | F158: 118.84594 | G158: {"type":"MultiPoint","coordinates":[]}
A159: 157 | B159: 2018 | C159: 5 | D159: 3EB | E159: 8.0789592e+08 | F159: 104.29993 | G159: {"type":"MultiPoint","coordinates":[]}
A160: 158 | B160: 2018 | C160: 5 | D160: 3ED | E160: 5.7289114e+08 | F160: 60.016989 | G160: {"type":"MultiPoint","coordinates":[]}
A161: 159 | B161: 2018 | C161: 5 | D161: 3EC | E161: 6.7420896e+08 | F161: 87.176012 | G161: {"type":"MultiPoint","coordinates":[]}
A162: 160 | B162: 2018 | C162: 5 | D162: 3G | E162: 6.3021441e+09 | F162: 29.515678 | G162: {"type":"MultiPoint","coordinates":[]}
A163: 161 | B163: 2018 | C163: 5 | D163: 3LA | E163: 7.349765e+09 | F163: 135.30858 | G163: {"type":"MultiPoint","coordinates":[]}
A164: 162 | B164: 2018 | C164: 5 | D164: 3J | E164: 2.8072957e+09 | F164: 41.20712 | G164: {"type":"MultiPoint","coordinates":[]}
A165: 163 | B165: 2018 | C165: 5 | D165: 3LB | E165: 7.8841806e+08 | F165: 474.18137 | G165: {"type":"MultiPoint","coordinates":[]}
A166: 164 | B166: 2018 | C166: 5 | D166: 3MA | E166: 6.1570601e+09 | F166: 70.303567 | G166: {"type":"MultiPoint","coordinates":[]}
A167: 165 | B167: 2018 | C167: 5 | D167: 3MB | E167: 1.7125789e+09 | F167: 225.35551 | G167: {"type":"MultiPoint","coordinates":[]}
A168: 166 | B168: 2018 | C168: 5 | D168: 3MD1 | E168: 1.3043892e+09 | F168: 377.2839 | G168: {"type":"MultiPoint","coordinates":[]}
... A189: 187 | B189: 2018 | C189: 6 | D189: 3HD1 | E189: 6.322851e+08 | F189: 126.42481 | G189: {"type":"MultiPoint","coordinates":[]}
A190: 188 | B190: 2018 | C190: 6 | E190: 1.7039735e+08 | F190: 0.37014613 | G190: {"type":"MultiPoint","coordinates":[]}
A191: 189 | B191: 2018 | C191: 6 | D191: 3AC | E191: 8.9214077e+08 | F191: 23.174935 | G191: {"type":"MultiPoint","coordinates":[]}
A192: 190 | B192: 2018 | C192: 6 | D192: 3EA | E192: 8.798824e+08 | F192: 22.377318 | G192: {"type":"MultiPoint","coordinates":[]}
...

Sheet EwasoNgiro_Subbasin_Monthly
A1: system:index | B1: Year | C1: Month | D1: Subbasin_ID | E1: area_m2 | F1: mean_rf_mm | G1: .geo
A2: 0 | B2: 2018 | C2: 1 | D2: 5H | E2: 6.6565798e+09 | F2: 7.8063648e-05 | G2: {"type":"MultiPoint","coordinates":[]} | J2: Year | K2: Year | L2: Year | M2: Year | N2: Year | O2: Year | P2: Year
A3: 1 | B3: 2018 | C3: 1 | D3: 5GA | E3: 2.2453045e+10 | F3: 0 | G3: {"type":"MultiPoint","coordinates":[]} | I3: Month | J3: 2018 | K3: 2019 | L3: 2020 | M3: 2021 | N3: 2022 | O3: 2023 | P3: 2024
A4: 2 | B4: 2018 | C4: 1 | D4: 5GB | E4: 3.3554558e+09 | F4: 2.8911803e-06 | G4: {"type":"MultiPoint","coordinates":[]} | I4: 1 | J4: =AVERAGEIFS($F:$F,$B:$B,J$3,$C:$C,$I4) -> 7.6857345 | K4: =AVERAGEIFS($F:$F,$B:$B,K$3,$C:$C,$I4) -> 20.55772 | L4: =AVERAGEIFS($F:$F,$B:$B,L$3,$C:$C,$I4) -> 43.114808 | M4: =AVERAGEIFS($F:$F,$B:$B,M$3,$C:$C,$I4) -> 27.311927 | N4: =AVERAGEIFS($F:$F,$B:$B,N$3,$C:$C,$I4) -> 21.532777 | O4: =AVERAGEIFS($F:$F,$B:$B,O$3,$C:$C,$I4) -> 16.293503 | P4: =AVERAGEIFS($F:$F,$B:$B,P$3,$C:$C,$I4) -> 38.008196
A5: 3 | B5: 2018 | C5: 1 | D5: 5EB | E5: 2.7218095e+10 | F5: 0.03210697 | G5: {"type":"MultiPoint","coordinates":[]} | I5: 2 | J5: =AVERAGEIFS($F:$F,$B:$B,J$3,$C:$C,$I5) -> 8.8743927 | K5: =AVERAGEIFS($F:$F,$B:$B,K$3,$C:$C,$I5) -> 12.727334 | L5: =AVERAGEIFS($F:$F,$B:$B,L$3,$C:$C,$I5) -> 33.49477 | M5: =AVERAGEIFS($F:$F,$B:$B,M$3,$C:$C,$I5) -> 26.628894 | N5: =AVERAGEIFS($F:$F,$B:$B,N$3,$C:$C,$I5) -> 15.831148 | O5: =AVERAGEIFS($F:$F,$B:$B,O$3,$C:$C,$I5) -> 3.4237095 | P5: =AVERAGEIFS($F:$F,$B:$B,P$3,$C:$C,$I5) -> 46.86212
A6: 4 | B6: 2018 | C6: 1 | D6: 5EC | E6: 2.9429244e+10 | F6: 3.0949693 | G6: {"type":"MultiPoint","coordinates":[]} | I6: 3 | J6: =AVERAGEIFS($F:$F,$B:$B,J$3,$C:$C,$I6) -> 155.82657 | K6: =AVERAGEIFS($F:$F,$B:$B,K$3,$C:$C,$I6) -> 21.842966 | L6: =AVERAGEIFS($F:$F,$B:$B,L$3,$C:$C,$I6) -> 108.98857 | M6: =AVERAGEIFS($F:$F,$B:$B,M$3,$C:$C,$I6) -> 36.213602 | N6: =AVERAGEIFS($F:$F,$B:$B,N$3,$C:$C,$I6) -> 30.898874 | O6: =AVERAGEIFS($F:$F,$B:$B,O$3,$C:$C,$I6) -> 99.557303 | P6: =AVERAGEIFS($F:$F,$B:$B,P$3,$C:$C,$I6) -> 23.049137
A7: 5 | B7: 2018 | C7: 1 | D7: 5EA | E7: 2.5314563e+10 | F7: 0 | G7: {"type":"MultiPoint","coordinates":[]} | I7: 4 | J7: =AVERAGEIFS($F:$F,$B:$B,J$3,$C:$C,$I7) -> 242.91971 | K7: =AVERAGEIFS($F:$F,$B:$B,K$3,$C:$C,$I7) -> 88.951773 | L7: =AVERAGEIFS($F:$F,$B:$B,L$3,$C:$C,$I7) -> 256.3422 | M7: =AVERAGEIFS($F:$F,$B:$B,M$3,$C:$C,$I7) -> 74.156766 | N7: =AVERAGEIFS($F:$F,$B:$B,N$3,$C:$C,$I7) -> 96.968995 | O7: =AVERAGEIFS($F:$F,$B:$B,O$3,$C:$C,$I7) -> 203.17122 | P7: =AVERAGEIFS($F:$F,$B:$B,P$3,$C:$C,$I7) -> 223.34999
A8: 6 | B8: 2018 | C8: 1 | D8: 5CB | E8: 2.2694165e+09 | F8: 5.8096598 | G8: {"type":"MultiPoint","coordinates":[]} | I8: 5 | J8: =AVERAGEIFS($F:$F,$B:$B,J$3,$C:$C,$I8) -> 108.83625 | K8: =AVERAGEIFS($F:$F,$B:$B,K$3,$C:$C,$I8) -> 54.906291 | L8: =AVERAGEIFS($F:$F,$B:$B,L$3,$C:$C,$I8) -> 73.139617 | M8: =AVERAGEIFS($F:$F,$B:$B,M$3,$C:$C,$I8) -> 96.032303 | N8: =AVERAGEIFS($F:$F,$B:$B,N$3,$C:$C,$I8) -> 33.671765 | O8: =AVERAGEIFS($F:$F,$B:$B,O$3,$C:$C,$I8) -> 42.872745 | P8: =AVERAGEIFS($F:$F,$B:$B,P$3,$C:$C,$I8) -> 103.99033
A9: 7 | B9: 2018 | C9: 1 | D9: 5FB | E9: 8.2153523e+09 | F9: 0.030903916 | G9: {"type":"MultiPoint","coordinates":[]} | I9: 6 | J9: =AVERAGEIFS($F:$F,$B:$B,J$3,$C:$C,$I9) -> 97.03983 | K9: =AVERAGEIFS($F:$F,$B:$B,K$3,$C:$C,$I9) -> 53.561785 | L9: =AVERAGEIFS($F:$F,$B:$B,L$3,$C:$C,$I9) -> 52.060598 | M9: =AVERAGEIFS($F:$F,$B:$B,M$3,$C:$C,$I9) -> 10.324022 | N9: =AVERAGEIFS($F:$F,$B:$B,N$3,$C:$C,$I9) -> 13.190895 | O9: =AVERAGEIFS($F:$F,$B:$B,O$3,$C:$C,$I9) -> 32.007569 | P9: =AVERAGEIFS($F:$F,$B:$B,P$3,$C:$C,$I9) -> 11.707778
A10: 8 | B10: 2018 | C10: 1 | D10: 5DD | E10: 1.8916824e+09 | F10: 4.4611669 | G10: {"type":"MultiPoint","coordinates":[]} | I10: 7 | J10: =AVERAGEIFS($F:$F,$B:$B,J$3,$C:$C,$I10) -> 29.924425 | K10: =AVERAGEIFS($F:$F,$B:$B,K$3,$C:$C,$I10) -> 32.429488 | L10: =AVERAGEIFS($F:$F,$B:$B,L$3,$C:$C,$I10) -> 37.61657 | M10: =AVERAGEIFS($F:$F,$B:$B,M$3,$C:$C,$I10) -> 25.846181 | N10: =AVERAGEIFS($F:$F,$B:$B,N$3,$C:$C,$I10) -> 19.844823 | O10: =AVERAGEIFS($F:$F,$B:$B,O$3,$C:$C,$I10) -> 20.126628 | P10: =AVERAGEIFS($F:$F,$B:$B,P$3,$C:$C,$I10) -> 38.961447
A11: 9 | B11: 2018 | C11: 1 | D11: 5DC | E11: 1.274624e+09 | F11: 7.5054223 | G11: {"type":"MultiPoint","coordinates":[]} | I11: 8 | J11: =AVERAGEIFS($F:$F,$B:$B,J$3,$C:$C,$I11) -> 27.1474 | K11: =AVERAGEIFS($F:$F,$B:$B,K$3,$C:$C,$I11) -> 37.675389 | L11: =AVERAGEIFS($F:$F,$B:$B,L$3,$C:$C,$I11) -> 59.729476 | M11: =AVERAGEIFS($F:$F,$B:$B,M$3,$C:$C,$I11) -> 26.254575 | N11: =AVERAGEIFS($F:$F,$B:$B,N$3,$C:$C,$I11) -> 38.157077 | O11: =AVERAGEIFS($F:$F,$B:$B,O$3,$C:$C,$I11) -> 18.942843 | P11: =AVERAGEIFS($F:$F,$B:$B,P$3,$C:$C,$I11) -> 43.721023
A12: 10 | B12: 2018 | C12: 1 | D12: 5DB | E12: 1.292373e+09 | F12: 12.331483 | G12: {"type":"MultiPoint","coordinates":[]} | I12: 9 | J12: =AVERAGEIFS($F:$F,$B:$B,J$3,$C:$C,$I12) -> 18.698444 | K12: =AVERAGEIFS($F:$F,$B:$B,K$3,$C:$C,$I12) -> 24.268028 | L12: =AVERAGEIFS($F:$F,$B:$B,L$3,$C:$C,$I12) -> 24.732306 | M12: =AVERAGEIFS($F:$F,$B:$B,M$3,$C:$C,$I12) -> 19.269076 | N12: =AVERAGEIFS($F:$F,$B:$B,N$3,$C:$C,$I12) -> 27.043967 | O12: =AVERAGEIFS($F:$F,$B:$B,O$3,$C:$C,$I12) -> 19.479502 | P12: =AVERAGEIFS($F:$F,$B:$B,P$3,$C:$C,$I12) -> 10.434023
A13: 11 | B13: 2018 | C13: 1 | D13: 5AD | E13: 5.1993226e+08 | F13: 10.498103 | G13: {"type":"MultiPoint","coordinates":[]} | I13: 10 | J13: =AVERAGEIFS($F:$F,$B:$B,J$3,$C:$C,$I13) -> 51.682694 | K13: =AVERAGEIFS($F:$F,$B:$B,K$3,$C:$C,$I13) -> 156.117 | L13: =AVERAGEIFS($F:$F,$B:$B,L$3,$C:$C,$I13) -> 66.727722 | M13: =AVERAGEIFS($F:$F,$B:$B,M$3,$C:$C,$I13) -> 48.042658 | N13: =AVERAGEIFS($F:$F,$B:$B,N$3,$C:$C,$I13) -> 35.261166 | O13: =AVERAGEIFS($F:$F,$B:$B,O$3,$C:$C,$I13) -> 117.05309 | P13: =AVERAGEIFS($F:$F,$B:$B,P$3,$C:$C,$I13) -> 45.725117
A14: 12 | B14: 2018 | C14: 1 | D14: 5BD | E14: 6.769237e+08 | F14: 14.191052 | G14: {"type":"MultiPoint","coordinates":[]} | I14: 11 | J14: =AVERAGEIFS($F:$F,$B:$B,J$3,$C:$C,$I14) -> 62.536206 | K14: =AVERAGEIFS($F:$F,$B:$B,K$3,$C:$C,$I14) -> 195.49553 | L14: =AVERAGEIFS($F:$F,$B:$B,L$3,$C:$C,$I14) -> 65.85914 | M14: =AVERAGEIFS($F:$F,$B:$B,M$3,$C:$C,$I14) -> 56.472158 | N14: =AVERAGEIFS($F:$F,$B:$B,N$3,$C:$C,$I14) -> 90.960926 | O14: =AVERAGEIFS($F:$F,$B:$B,O$3,$C:$C,$I14) -> 214.07255 | P14: =AVERAGEIFS($F:$F,$B:$B,P$3,$C:$C,$I14) -> 110.09064
A15: 13 | B15: 2018 | C15: 1 | D15: 5ED | E15: 1.804048e+10 | F15: 1.1018667 | G15: {"type":"MultiPoint","coordinates":[]} | I15: 12 | J15: =AVERAGEIFS($F:$F,$B:$B,J$3,$C:$C,$I15) -> 115.12955 | K15: =AVERAGEIFS($F:$F,$B:$B,K$3,$C:$C,$I15) -> 111.2514 | L15: =AVERAGEIFS($F:$F,$B:$B,L$3,$C:$C,$I15) -> 32.061477 | M15: =AVERAGEIFS($F:$F,$B:$B,M$3,$C:$C,$I15) -> 68.565947 | N15: =AVERAGEIFS($F:$F,$B:$B,N$3,$C:$C,$I15) -> 41.914712 | O15: =AVERAGEIFS($F:$F,$B:$B,O$3,$C:$C,$I15) -> 30.891913 | P15: =AVERAGEIFS($F:$F,$B:$B,P$3,$C:$C,$I15) -> 19.967686
A16: 14 | B16: 2018 | C16: 1 | D16: 5FA | E16: 1.8521643e+10 | F16: 0.49120727 | G16: {"type":"MultiPoint","coordinates":[]}
A17: 15 | B17: 2018 | C17: 1 | D17: 5DA | E17: 2.2496159e+09 | F17: 9.9930818 | G17: {"type":"MultiPoint","coordinates":[]} | I17: TotalAnnual Rf | J17: =SUM(J4:J15) -> 926.30122 | K17: =SUM(K4:K15) -> 809.78471 | L17: =SUM(L4:L15) -> 853.86725 | M17: =SUM(M4:M15) -> 515.11811 | N17: =SUM(N4:N15) -> 465.27712 | O17: =SUM(O4:O15) -> 817.89257 | P17: =SUM(P4:P15) -> 715.86749
A18: 16 | B18: 2018 | C18: 1 | D18: 5BE | E18: 1.2433968e+09 | F18: 12.261721 | G18: {"type":"MultiPoint","coordinates":[]}
A19: 17 | B19: 2018 | C19: 1 | D19: 5BB | E19: 4.5181867e+08 | F19: 25.154459 | G19: {"type":"MultiPoint","coordinates":[]} | I19: WB_Area_sqkm | J19: 43 | K19: 43 | L19: 43 | M19: 43 | N19: 43 | O19: 43 | P19: 43
A20: 18 | B20: 2018 | C20: 1 | D20: 5BA | E20: 2.696955e+08 | F20: 23.607128 | G20: {"type":"MultiPoint","coordinates":[]} | I20: Basin_Area_sqkm | J20: 22507 | K20: 22507 | L20: 22507 | M20: 22507 | N20: 22507 | O20: 22507 | P20: 22507
A21: 19 | B21: 2018 | C21: 1 | D21: 5J | E21: 2.9390707e+10 | F21: 1.0522616 | G21: {"type":"MultiPoint","coordinates":[]} | I21: proportion(WB/BA)
A22: 20 | B22: 2018 | C22: 1 | D22: 5CC | E22: 3.0196649e+09 | F22: 5.2020704 | G22: {"type":"MultiPoint","coordinates":[]} | I22: TotalRf_mm | J22: =J17 -> 926.30122 | K22: =K17 -> 809.78471 | L22: =L17 -> 853.86725 | M22: =M17 -> 515.11811 | N22: =N17 -> 465.27712 | O22: =O17 -> 817.89257 | P22: =P17 -> 715.86749
A23: 21 | B23: 2018 | C23: 1 | D23: 5CA | E23: 2.3515078e+09 | F23: 7.9060294 | G23: {"type":"MultiPoint","coordinates":[]} | I23: Rainfall_MCM_on_Lake | J23: =(J22*100*J19*10)/1000000 -> 39.830952 | K23: =(K22*100*K19*10)/1000000 -> 34.820742 | L23: =(L22*100*L19*10)/1000000 -> 36.716292 | M23: =(M22*100*M19*10)/1000000 -> 22.150079 | N23: =(N22*100*N19*10)/1000000 -> 20.006916 | O23: =(O22*100*O19*10)/1000000 -> 35.169381 | P23: =(P22*100*P19*10)/1000000 -> 30.782302
A24: 22 | B24: 2018 | C24: 1 | D24: 5AC | E24: 1.0899844e+09 | F24: 9.0474237 | G24: {"type":"MultiPoint","coordinates":[]} | I24: BASIN_MAR
A25: 23 | B25: 2018 | C25: 1 | D25: 5AA | E25: 1.2516992e+09 | F25: 14.596663 | G25: {"type":"MultiPoint","coordinates":[]}
A26: 24 | B26: 2018 | C26: 1 | D26: 5AB | E26: 4.8411462e+08 | F26: 16.323228 | G26: {"type":"MultiPoint","coordinates":[]}
A27: 25 | B27: 2018 | C27: 1 | D27: 5BC | E27: 1.6448147e+09 | F27: 15.137008 | G27: {"type":"MultiPoint","coordinates":[]}
A28: 26 | B28: 2018 | C28: 2 | D28: 5H | E28: 6.6565798e+09 | F28: 11.777523 | G28: {"type":"MultiPoint","coordinates":[]}
A29: 27 | B29: 2018 | C29: 2 | D29: 5GA | E29: 2.2453045e+10 | F29: 9.9432017 | G29: {"type":"MultiPoint","coordinates":[]}
A30: 28 | B30: 2018 | C30: 2 | D30: 5GB | E30: 3.3554558e+09 | F30: 1.9582586 | G30: {"type":"MultiPoint","coordinates":[]}
A31: 29 | B31: 2018 | C31: 2 | D31: 5EB | E31: 2.7218095e+10 | F31: 14.242342 | G31: {"type":"MultiPoint","coordinates":[]}
A32: 30 | B32: 2018 | C32: 2 | D32: 5EC | E32: 2.9429244e+10 | F32: 8.3027825 | G32: {"type":"MultiPoint","coordinates":[]}
A33: 31 | B33: 2018 | C33: 2 | D33: 5EA | E33: 2.5314563e+10 | F33: 6.1159285 | G33: {"type":"MultiPoint","coordinates":[]}
A34: 32 | B34: 2018 | C34: 2 | D34: 5CB | E34: 2.2694165e+09 | F34: 6.5834628 | G34: {"type":"MultiPoint","coordinates":[]}
A35: 33 | B35: 2018 | C35: 2 | D35: 5FB | E35: 8.2153523e+09 | F35: 1.2159363 | G35: {"type":"MultiPoint","coordinates":[]}
A36: 34 | B36: 2018 | C36: 2 | D36: 5DD | E36: 1.8916824e+09 | F36: 5.6002371 | G36: {"type":"MultiPoint","coordinates":[]}
... A2185: 2183 | B2185: 2024 | C2185: 12 | D2185: 5BC | E2185: 1.6448147e+09 | F2185: 38.186941 | G2185: {"type":"MultiPoint","coordinates":[]}

Sheet Cover Page
F4: DRAFT Kenya Water Asset Accounts at Basin Level
J9: Version 1.3 | L9: 12-07-2025
J11: Prepared For:
J24: Prepared By:
J35: Contact People:
I37: Bernice Macquela b.macquela@primeafrica.net | L37: Jackie Crafford j.crafford@primeafrica.net

Sheet Colour Coding
B2: Data Cell Colour Codes within Water Accounts
B3: White | C3: Expected empty cells
B4: Grey | C4: Not applicable
B5: Green | C5: Official statistics from reputable data sources
B6: Light Green | C6: Data estimates by based on official statistics
B7: Orange | C7: Data derived from Green and Light Green statistics
B8: Red | C8: Literature estimates
B10: Data Text Colour Codes within Water Accounts
B11: Black Text | C11: Calculations
B12: Blue Text | C12: Data entered from data input sources
B13: Red Text | C13: Work in progress
B15: Tab Colour Codes within Water Accounts
B16: Yellow | C16: Work in progress
B17: Data Inputs | C17: Data entered from data input sources
B18: Output Tables | C18: Water Accounts

Sheet Notes to Water Accounts
B3: Notes for the Water Accounts
B4: General Framework
B5: 1 | C5: Data for the water accounts is drawn from multiple sources, including WRA reports, WASREB data, Chirp Data and basin-level hydrological assessments. While these sources vary in format, scope, and temporal resolution, efforts were made to ensure consistency through appropriate standardization and cross-referencing. In some cases, approximations were necessary to enable alignment across datasets.
B6: 2 | C6: The water accounts have been prepared for the years 2021 and 2023, consistent with the water Supply and Use Tables (SUTs).
B7: 3 | C7: All flows are reported in Million Cubic Metres per Annum (MCM/a).
B10: Methodology and Assumptions for Opening Stocks
B11: 4 | C11: Lakes and dams: Opening stocks are based on storage capacity, due to lack of observed level data.
B12: 5 | C12: Rivers: Represented by the Mean Annual Runoff (MAR) for each year.
B13: 6 | C13: Groundwater: Stocks reflect potential groundwater recharge. Additional recharge is based on abstrcated per year
B16: Data Inputs and Hydrological Components
B17: 7 | C17: The precipitation data was modelled using CHIRPs and was compared with basin level reports
B18: 8 | C18: The basin level reports were used to calculate the ratio's of ET per basin.
B19: 9 | C19: Return flows are based on WASREB and WRA data
B20: 10 | C20: Cells containing estimated or assumed values include comments that provide explanations for the basis or rationale behind those estimations.
B21: 11 | C21: Lake estimates: storage capacity is estimated based on lake depth and area. Depth was obtained from literature and area was obtained from a GIS analysis
B23: Model Architecture
B24: 12 | C24: This workbook contains multiple worksheets that contribute to various components of the accounts. These include sub-basin reports presenting hydrological data such as rainfall patterns, and the distribution of rainfall across lakes and rivers over different years. Given the volume and complexity of data involved in compiling the accounts, some worksheets have been hidden for clarity and structure. These worksheets can be unhidden by right clicking on any of the worksheet tabs, and selecting the unhide option.

Sheet Basin-Stock flow 2021-2023
A1: 2021
A2: Basins | B2: Precipitation (mm) | C2: Basin size (km2) | D2: Precipitation (MCM) | E2: ET (mm) | F2: ET (MCM) | G2: Ecological reserve (MCM/a) | H2: Groundwater recharge (MCM/a) | I2: Soil (MCM) | J2: MAR (MCM) | K2: Dam (storage capacity (MCM)) | L2: Inter-transfers (MCM/a) | M2: Groundwater yield (MCM/a) | N2: Total Yield (MCM) | O2: Domestic:SW (MCM/a) | P2: Domestic:GW (MCM/a) | Q2: Public:SW (MCM/a) | R2: Public:GW (MCM/a) | S2: Agri: SW (MCM/a) | T2: Agri: GW (MCM/a) | U2: Industrial: SW (MCM/a) | V2: Industrial:GW (MCM/a) | W2: Return Flows: (MCM)/a) | X2: Total Use: (MCM/a) | Y2: Total Outflows Calculated | Z2: Flow into lake (MCM/a) | AA2: Flow to neighbouring country | AB2: Flow from neighbouring country | AC2: Flow to ocean (MCM/a) | AD2: Total Outflows Reported
A3: Athi | B3: =rainfall!C2 -> 354 | C3: ='Basin Data WS1'!B3 -> 66559 | D3: =B3*100*C3*10/1000000 -> 23561.886 | E3: =rainfall!D2 -> 147 | F3: =C3*100*E3*10/1000000 -> 9784.173 | G3: -156 | H3: 2943 | I3: =H3*0.2 -> 588.6 | J3: =D3-F3+G3-H3-I3 -> 10090.113 | K3: 22 | L3: 181 | M3: =H3*'Basin Data WS1'!I15 -> 549 | N3: =SUM(L3+M3+J3) -> 10820.113 | O3: ='WRA 2021-2024'!C4 -> 2.8585008 | P3: ='WRA 2021-2024'!D4 -> 24.864548 | Q3: ='WRA 2021-2024'!C3 -> 9.6399648 | R3: ='WRA 2021-2024'!D3 -> 19.008522 | S3: ='WRA 2021-2024'!C5+'WRA 2021-2024'!C6+'WRA 2021-2024'!C7 -> 67.29687 | T3: ='WRA 2021-2024'!D5+'WRA 2021-2024'!D6+'WRA 2021-2024'!D7 -> 6.1697016 | U3: ='WRA 2021-2024'!C8 -> 13.241048 | V3: ='WRA 2021-2024'!D8 -> 7.89462 | X3: =SUM(O3+Q3+S3+U3) -> 93.036384 | Y3: =N3-X3 -> 10727.077 | Z3: ='Basin Data WS1'!B28 -> 104 | AA3: ='Basin Data WS1'!B29 -> 156 | AB3: 0 | AC3: ='Basin Data WS1'!B30 -> 2210
A4: Ewaso Ngiro North | B4: =rainfall!C3 -> 201 | C4: ='Basin Data WS1'!C3 -> 210000 | D4: =B4*100*C4*10/1000000 -> 42210 | E4: =rainfall!D3 -> 74 | F4: =C4*100*E4*10/1000000 -> 15540 | G4: -168 | H4: 3241 | I4: =H4*0.2 -> 648.2 | J4: =D4-F4+G4-H4-I4 -> 22612.8 | K4: 0 | L4: 0 | M4: ='Basin Data WS1'!C15 -> 449 | N4: =SUM(L4+M4+J4) -> 23061.8 | O4: ='WRA 2021-2024'!M4 -> 11.146586 | P4: ='WRA 2021-2024'!N4 -> 1.8552312 | Q4: ='WRA 2021-2024'!M3 -> 5.881392 | R4: ='WRA 2021-2024'!N3 -> 0.455148 | S4: ='WRA 2021-2024'!M5+'WRA 2021-2024'!M6+'WRA 2021-2024'!M7 -> 30.741998 | T4: ='WRA 2021-2024'!N5+'WRA 2021-2024'!N6+'WRA 2021-2024'!N7 -> 7.275636 | U4: ='WRA 2021-2024'!M8 -> 1.1078244 | V4: ='WRA 2021-2024'!N8 -> 0.17748 | X4: =SUM(O4+Q4+S4+U4) -> 48.877801 | Y4: =N4-X4 -> 23012.922 | Z4: 34 | AA4: =Y4-Z4 -> 22978.922 | AB4: 0 | AC4: 0
A5: Lake Victoria North | B5: =rainfall!C4 -> 852 | C5: ='Basin Data WS1'!D3 -> 22507 | D5: =B5*100*C5*10/1000000 -> 19175.964 | E5: =rainfall!D4 -> 380 | F5: =C5*100*E5*10/1000000 -> 8552.66 | G5: -792 | H5: 1508 | I5: =H5*0.2 -> 301.6 | J5: =D5-F5+G5-H5-I5 -> 8021.704 | K5: 32 | L5: 0 | M5: ='Basin Data WS1'!D15 -> 216 | N5: =SUM(L5+M5+J5) -> 8237.704 | O5: ='WRA 2021-2024'!G4 -> 1.8635184 | P5: ='WRA 2021-2024'!H4 -> 5.201568 | Q5: ='WRA 2021-2024'!G3 -> 11.71112 | R5: ='WRA 2021-2024'!H3 -> 0.3141 | S5: ='WRA 2021-2024'!G5+'WRA 2021-2024'!G6+'WRA 2021-2024'!G7 -> 3.782394 | T5: ='WRA 2021-2024'!H5+'WRA 2021-2024'!H6+'WRA 2021-2024'!H7 -> 0.157356 | U5: ='WRA 2021-2024'!G8 -> 18.09972 | V5: ='WRA 2021-2024'!H8 -> 0.0594 | X5: =SUM(O5+Q5+S5+U5) -> 35.456753 | Y5: =N5-X5 -> 8202.2472 | Z5: =Y5-AA5 -> 7818.2472 | AA5: ='Basin Data WS1'!D29 -> 384 | AB5: 0 | AC5: 0
A6: Lake Victoria South | B6: =rainfall!C5 -> 763 | C6: ='Basin Data WS1'!E3 -> 26906 | D6: =B6*100*C6*10/1000000 -> 20529.278 | E6: =rainfall!D5 -> 407 | F6: =C6*100*E6*10/1000000 -> 10950.742 | G6: -316 | H6: 2095 | I6: =H6*0.2 -> 419 | J6: =D6-F6+G6-H6-I6 -> 6748.536 | K6: 1 | M6: ='Basin Data WS1'!E15 -> 292 | N6: =SUM(L6+M6+J6) -> 7040.536 | O6: ='WRA 2021-2024'!I4 -> 2.14389 | P6: ='WRA 2021-2024'!J4 -> 1.5488208 | Q6: ='WRA 2021-2024'!I3 -> 34.928604 | R6: ='WRA 2021-2024'!J3 -> 0.0457524 | S6: ='WRA 2021-2024'!I6+'WRA 2021-2024'!I5+'WRA 2021-2024'!I7 -> 3.2785596 | T6: ='WRA 2021-2024'!J6+'WRA 2021-2024'!J5+'WRA 2021-2024'!J7 -> 0.210636 | U6: ='WRA 2021-2024'!I8 -> 7.3758132 | V6: ='WRA 2021-2024'!J8 -> 0.09828 | X6: =SUM(O6+Q6+S6+U6) -> 47.726867 | Y6: =N6-X6 -> 6992.8091 | Z6: =Y6-AA6 -> 563.80913 | AA6: ='Basin Data WS1'!E31 -> 6429 | AB6: 0 | AC6: 0
A7: Rift Valley | B7: =rainfall!C6 -> 253 | C7: ='Basin Data WS1'!G3 -> 131423 | D7: =B7*100*C7*10/1000000 -> 33250.019 | E7: =rainfall!D6 -> 160 | F7: =C7*100*E7*10/1000000 -> 21027.68 | G7: -251 | H7: 3168 | I7: =H7*0.2 -> 633.6 | J7: =D7-F7+G7-H7-I7 -> 8169.739 | K7: 1659 | L7: 0 | M7: ='Basin Data WS1'!G15 -> 398 | N7: =SUM(L7+M7+J7) -> 8567.739 | O7: ='WRA 2021-2024'!K4 -> 8.5153536 | P7: ='WRA 2021-2024'!L4 -> 7.1315244 | Q7: ='WRA 2021-2024'!K3 -> 5.2134912 | R7: ='WRA 2021-2024'!L3 -> 22.994374 | S7: ='WRA 2021-2024'!K5+'WRA 2021-2024'!K6+'WRA 2021-2024'!K7 -> 58.157467 | T7: ='WRA 2021-2024'!L5+'WRA 2021-2024'!L6+'WRA 2021-2024'!L7 -> 63.885715 | U7: ='WRA 2021-2024'!K8 -> 6.269652 | V7: ='WRA 2021-2024'!L8 -> 0.9914112 | X7: =SUM(O7+Q7+S7+U7) -> 78.155964 | Y7: =N7-X7 -> 8489.583 | Z7: =Y7-AA7 -> 8059.583 | AA7: ='Basin Data WS1'!G29 -> 430 | AB7: ='Basin Data WS1'!G36 -> 15469 | AC7: 0
A8: Tana | B8: =rainfall!C7 -> 293 | C8: ='Basin Data WS1'!F3 -> 126208 | D8: =B8*100*C8*10/1000000 -> 36978.944 | E8: =rainfall!D7 -> 118 | F8: =C8*100*E8*10/1000000 -> 14892.544 | G8: -251 | H8: 4479 | I8: =H7*0.2 -> 633.6 | J8: =D8-F8+G8-H8-I8 -> 16722.8 | K8: =16+70+1560+123+20+16+585 -> 2390 | L8: -181 | M8: ='Basin Data WS1'!F15 -> 693 | N8: =SUM(L8+M8+J8) -> 17234.8 | O8: ='WRA 2021-2024'!E4 -> 158.24904 | P8: ='WRA 2021-2024'!F4 -> 2.29383 | Q8: ='WRA 2021-2024'!E3 -> 49.201884 | R8: ='WRA 2021-2024'!F3 -> 0.0072 | S8: ='WRA 2021-2024'!E5+'WRA 2021-2024'!E6+'WRA 2021-2024'!E7 -> 134.26854 | T8: ='WRA 2021-2024'!F5+'WRA 2021-2024'!F6+'WRA 2021-2024'!F7 -> 0.503622 | U8: ='WRA 2021-2024'!E8 -> 2.6370792 | V8: ='WRA 2021-2024'!F8 -> 0.0207 | X8: =SUM(O8+Q8+S8+U8) -> 344.35655 | Y8: =N8-X8 -> 16890.443
A10: 2022
A11: Basins | B11: Precipitation (mm) | C11: Basin size (km2) | D11: Precipitation (MCM) | E11: ET (mm) | F11: ET (MCM) | G11: Ecological reserve (MCM/a) | H11: Groundwater recharge (MCM/a) | I11: Soil (MCM) | J11: MAR (MCM) | K11: Dam (storage capacity (MCM)) | L11: Inter-transfers (MCM/a) | M11: Groundwater yield (MCM/a) | N11: Total Yield (MCM) | O11: Domestic:SW (MCM/a) | P11: Domestic:GW (MCM/a) | Q11: Public:SW (MCM/a) | R11: Public:GW (MCM/a) | S11: Agri: SW (MCM/a) | T11: Agri: GW (MCM/a) | U11: Industrial: SW (MCM/a) | V11: Industrial:GW (MCM/a) | W11: Return Flows: (MCM)/a) | X11: Total Use: (MCM/a) | Y11: Total Outflows Calculated | Z11: Flow into lake (MCM/a) | AA11: Flow to neighbouring country | AB11: Flow from neighbouring country | AC11: Flow to ocean (MCM/a) | AD11: Total Outflows Reported
A12: Athi | B12: =rainfall!C8 -> 364 | C12: =C3 -> 66559 | D12: =B12*100*C12*10/1000000 -> 24227.476 | E12: =rainfall!D8 -> 110 | F12: =C12*100*E12*10/1000000 -> 7321.49 | G12: -156 | H12: 2943 | I12: =H12*0.2 -> 588.6 | J12: =D12-F12+G12-H12-I12 -> 13218.386 | K12: 22 | L12: 181 | M12: ='Basin Data WS1'!B24 -> 971 | N12: =SUM(L12+M12+J12) -> 14370.386 | O12: ='WRA 2021-2024'!C17 -> 2.8753128 | P12: ='WRA 2021-2024'!D17 -> 27.731678 | Q12: ='WRA 2021-2024'!C16 -> 9.6399648 | R12: ='WRA 2021-2024'!D16 -> 19.216692 | S12: ='WRA 2021-2024'!C18+'WRA 2021-2024'!C19+'WRA 2021-2024'!C20 -> 67.870908 | T12: ='WRA 2021-2024'!D18+'WRA 2021-2024'!D19+'WRA 2021-2024'!D20 -> 6.6323016 | U12: ='WRA 2021-2024'!C21 -> 13.305784 | V12: ='WRA 2021-2024'!D21 -> 8.52714 | X12: =SUM(O12+Q12+S12+U12) -> 93.691969 | Y12: =N12-X12 -> 14276.694 | Z12: ='Basin Data WS1'!B37 -> 0 | AA12: 156 | AB12: 0 | AC12: 2210
A13: Ewaso Ngiro North | B13: =rainfall!C9 -> 215 | C13: =C4 -> 210000 | D13: =B13*100*C13*10/1000000 -> 45150 | E13: =rainfall!D9 -> 49 | F13: =C13*100*E13*10/1000000 -> 10290 | G13: -168 | H13: 3241 | I13: =H13*0.2 -> 648.2 | J13: =D13-F13+G13-H13-I13 -> 30802.8 | K13: 0 | L13: 0 | M13: ='Basin Data WS1'!C24 -> 246 | N13: =SUM(L13+M13+J13) -> 31048.8 | O13: ='WRA 2021-2024'!M17 -> 11.42654 | P13: ='WRA 2021-2024'!N17 -> 2.1786732 | Q13: ='WRA 2021-2024'!M16 -> 5.881392 | R13: ='WRA 2021-2024'!N16 -> 0.458748 | S13: ='WRA 2021-2024'!M18+'WRA 2021-2024'!M19+'WRA 2021-2024'!M20 -> 31.121669 | T13: ='WRA 2021-2024'!N18+'WRA 2021-2024'!N19+'WRA 2021-2024'!N20 -> 7.554906 | U13: ='WRA 2021-2024'!M21 -> 1.1468124 | V13: ='WRA 2021-2024'!N21 -> 0.17748 | X13: =SUM(O13+Q13+S13+U13) -> 49.576414 | Y13: =N13-X13 -> 30999.224 | Z13: 34 | AA13: =Y13-Z13 -> 30965.224 | AB13: 0 | AC13: 0
A14: Lake Victoria North | B14: =rainfall!C10 -> 763 | C14: =C5 -> 22507 | D14: =B14*100*C14*10/1000000 -> 17172.841 | E14: =rainfall!D10 -> 299 | F14: =C14*100*E14*10/1000000 -> 6729.593 | G14: -792 | H14: 1508 | I14: =H14*0.2 -> 301.6 | J14: =D14-F14+G14-H14-I14 -> 7841.648 | K14: 32 | L14: 0 | M14: ='Basin Data WS1'!D24 -> 286 | N14: =SUM(L14+M14+J14) -> 8127.648 | O14: ='WRA 2021-2024'!G17 -> 2.7692784 | P14: ='WRA 2021-2024'!H17 -> 5.559228 | Q14: ='WRA 2021-2024'!G16 -> 11.71112 | R14: ='WRA 2021-2024'!H16 -> 0.3141 | S14: ='WRA 2021-2024'!G18+'WRA 2021-2024'!G19+'WRA 2021-2024'!G20 -> 3.782394 | T14: ='WRA 2021-2024'!H18+'WRA 2021-2024'!H19+'WRA 2021-2024'!H20 -> 0.169236 | U14: ='WRA 2021-2024'!G21 -> 44.39412 | V14: ='WRA 2021-2024'!H21 -> 0.0738 | X14: =SUM(O14+Q14+S14+U14) -> 62.656913 | Y14: =N14-X14 -> 8064.9911 | Z14: =Y14-AA14 -> 7680.9911 | AA14: 384 | AB14: 0 | AC14: 0
A15: Lake Victoria South | B15: =rainfall!C11 -> 771 | C15: =C6 -> 26906 | D15: =B15*100*C15*10/1000000 -> 20744.526 | E15: =rainfall!D11 -> 335 | F15: =C15*100*E15*10/1000000 -> 9013.51 | G15: -316 | H15: 2095 | I15: =H15*0.2 -> 419 | J15: =D15-F15+G15-H15-I15 -> 8901.016 | K15: 1 | M15: ='Basin Data WS1'!E24 -> 633 | N15: =SUM(L15+M15+J15) -> 9534.016 | O15: ='WRA 2021-2024'!I17 -> 2.196576 | P15: ='WRA 2021-2024'!J17 -> 1.7241408 | Q15: ='WRA 2021-2024'!I16 -> 34.928604 | R15: ='WRA 2021-2024'!J16 -> 0.0565524 | S15: ='WRA 2021-2024'!I18+'WRA 2021-2024'!I19+'WRA 2021-2024'!I20 -> 4.6105596 | T15: ='WRA 2021-2024'!J18+'WRA 2021-2024'!J19+'WRA 2021-2024'!J20 -> 0.217836 | U15: ='WRA 2021-2024'!I21 -> 8.2995732 | V15: ='WRA 2021-2024'!J21 -> 0.09828 | X15: =SUM(O15+Q15+S15+U15) -> 50.035313 | Y15: =N15-X15 -> 9483.9807 | Z15: =Y15-AA15 -> 8673.9807 | AA15: 810 | AB15: 0 | AC15: 0
A16: Rift Valley | B16: =rainfall!C12 -> 250 | C16: =C7 -> 131423 | D16: =B16*100*C16*10/1000000 -> 32855.75 | E16: =rainfall!D12 -> 114 | F16: =C16*100*E16*10/1000000 -> 14982.222 | G16: -251 | H16: 3168 | I16: =H16*0.2 -> 633.6 | J16: =D16-F16+G16-H16-I16 -> 13820.928 | K16: 1659 | L16: 0 | M16: ='Basin Data WS1'!G24 -> 481 | N16: =SUM(L16+M16+J16) -> 14301.928 | O16: ='WRA 2021-2024'!K17 -> 8.8868304 | P16: ='WRA 2021-2024'!L17 -> 7.6515444 | Q16: ='WRA 2021-2024'!K16 -> 5.2296912 | R16: ='WRA 2021-2024'!L16 -> 23.019574 | S16: ='WRA 2021-2024'!L18+'WRA 2021-2024'!L19+'WRA 2021-2024'!L20 -> 67.991623 | T16: ='WRA 2021-2024'!M18+'WRA 2021-2024'!M19+'WRA 2021-2024'!M20 -> 31.121669 | U16: ='WRA 2021-2024'!K21 -> 0.0180396 | V16: ='WRA 2021-2024'!L21 -> 0.9932112 | X16: =SUM(O16+Q16+S16+U16) -> 82.126184 | Y16: =N16-X16 -> 14219.802 | Z16: =Y16-AA16 -> 13789.802 | AA16: 430 | AB16: 15469 | AC16: 0
A17: Tana | B17: =rainfall!C13 -> 337 | C17: =C8 -> 126208 | D17: =B17*100*C17*10/1000000 -> 42532.096 | E17: =rainfall!D13 -> 105 | F17: =C17*100*E17*10/1000000 -> 13251.84 | G17: -251 | H17: 4479 | I17: =H16*0.2 -> 633.6 | J17: =D17-F17+G17-H17-I17 -> 23916.656 | K17: =16+70+1560+123+20+16+585 -> 2390 | L17: -181 | M17: ='Basin Data WS1'!F24 -> 1639 | N17: =SUM(L17+M17+J17) -> 25374.656 | O17: ='WRA 2021-2024'!E17 -> 158.45902 | P17: ='WRA 2021-2024'!F17 -> 2.78019 | Q17: ='WRA 2021-2024'!E16 -> 49.201884 | R17: ='WRA 2021-2024'!F16 -> 0.0288 | S17: ='WRA 2021-2024'!E18+'WRA 2021-2024'!E19+'WRA 2021-2024'!E20 -> 136.87967 | T17: ='WRA 2021-2024'!F18+'WRA 2021-2024'!F19+'WRA 2021-2024'!F20 -> 0.33705 | U17: ='WRA 2021-2024'!E21 -> 2.7990792 | V17: ='WRA 2021-2024'!F21 -> 0.0279 | X17: =SUM(O17+Q17+S17+U17) -> 347.33965 | Y17: =N17-X17 -> 25027.316
A19: 2023
A20: Basins | B20: Precipitation (mm) | C20: Basin size (km2) | D20: Precipitation (MCM) | E20: ET (mm) | F20: ET (MCM) | G20: Ecological reserve (MCM/a) | H20: Groundwater recharge (MCM/a) | I20: Soil (MCM) | J20: MAR (MCM) | K20: Dam (storage capacity (MCM)) | L20: Inter-transfers (MCM/a) | M20: Groundwater yield (MCM/a) | N20: Total Yield (MCM) | O20: Domestic:SW (MCM/a) | P20: Domestic:GW (MCM/a) | Q20: Public:SW (MCM/a) | R20: Public:GW (MCM/a) | S20: Agri: SW (MCM/a) | T20: Agri: GW (MCM/a) | U20: Industrial: SW (MCM/a) | V20: Industrial:GW (MCM/a) | W20: Return Flows: (MCM)/a) | X20: Total Use: (MCM/a) | Y20: Total Outflows Calculated | Z20: Flow into lake (MCM/a) | AA20: Flow to neighbouring country | AB20: Flow from neighbouring country | AC20: Flow to ocean (MCM/a) | AD20: Total Outflows Reported
A21: Athi | B21: =rainfall!C14 -> 775 | C21: =C12 -> 66559 | D21: =B21*100*C21*10/1000000 -> 51583.225 | E21: =rainfall!D14 -> 234.2033 | F21: =C21*100*E21*10/1000000 -> 15588.337 | G21: -156 | H21: 2943 | I21: =H21*0.2 -> 588.6 | J21: =D21-F21+G21-H21-I21 -> 32307.288 | K21: 22 | L21: 181 | M21: ='Basin Data WS1'!B33 -> 0 | N21: =SUM(L21+M21+J21) -> 32488.288 | O21: ='WRA 2021-2024'!C30 -> 3.0448368 | P21: ='WRA 2021-2024'!D30 -> 32.242766 | Q21: ='WRA 2021-2024'!C29 -> 11.019845 | R21: ='WRA 2021-2024'!D29 -> 19.395972 | S21: ='WRA 2021-2024'!C31+'WRA 2021-2024'!C32+'WRA 2021-2024'!C33 -> 68.499497 | T21: ='WRA 2021-2024'!D31+'WRA 2021-2024'!D32+'WRA 2021-2024'!D33 -> 7.5111336 | U21: ='WRA 2021-2024'!C34 -> 13.305784 | V21: ='WRA 2021-2024'!D34 -> 8.867412 | X21: =SUM(O21+Q21+S21+U21) -> 95.869962 | Y21: =N21-X21 -> 32392.418 | Z21: ='Basin Data WS1'!B46 -> 0 | AA21: ='Basin Data WS1'!B47 -> 0 | AB21: 0 | AC21: ='Basin Data WS1'!B48 -> 0
A22: Ewaso Ngiro North | B22: =rainfall!C15 -> 681 | C22: =C13 -> 210000 | D22: =B22*100*C22*10/1000000 -> 143010 | E22: =rainfall!D15 -> 155.20465 | F22: =C22*100*E22*10/1000000 -> 32592.977 | G22: -168 | H22: 3241 | I22: =H22*0.2 -> 648.2 | J22: =D22-F22+G22-H22-I22 -> 106359.82 | K22: 0 | L22: 0 | M22: ='Basin Data WS1'!C33 -> 0 | N22: =SUM(L22+M22+J22) -> 106359.82 | O22: ='WRA 2021-2024'!M30 -> 14.090587 | P22: ='WRA 2021-2024'!N30 -> 2.6925012 | Q22: ='WRA 2021-2024'!M29 -> 5.881392 | R22: ='WRA 2021-2024'!N29 -> 0.472788 | S22: ='WRA 2021-2024'!M31+'WRA 2021-2024'!M32+'WRA 2021-2024'!M33 -> 32.823191 | T22: ='WRA 2021-2024'!N31+'WRA 2021-2024'!N32+'WRA 2021-2024'!N33 -> 8.975322 | U22: ='WRA 2021-2024'!M34 -> 1.1468124 | V22: ='WRA 2021-2024'!N34 -> 0.17748 | X22: =SUM(O22+Q22+S22+U22) -> 53.941982 | Y22: =N22-X22 -> 106305.88 | Z22: 34 | AA22: =Y22-Z22 -> 106271.88 | AB22: 0 | AC22: 0
A23: Lake Victoria North | B23: =rainfall!C16 -> 963 | C23: =C14 -> 22507 | D23: =B23*100*C23*10/1000000 -> 21674.241 | E23: =rainfall!D16 -> 377.37484 | F23: =C23*100*E23*10/1000000 -> 8493.5754 | G23: -792 | H23: 1508 | I23: =H23*0.2 -> 301.6 | J23: =D23-F23+G23-H23-I23 -> 10579.066 | K23: 32 | L23: 0 | M23: ='Basin Data WS1'!D33 -> 0 | N23: =SUM(L23+M23+J23) -> 10579.066 | O23: ='WRA 2021-2024'!G30 -> 2.7825984 | P23: ='WRA 2021-2024'!H30 -> 6.078528 | Q23: ='WRA 2021-2024'!G29 -> 11.74712 | R23: ='WRA 2021-2024'!H29 -> 0.4995 | S23: ='WRA 2021-2024'!G31+'WRA 2021-2024'!G32+'WRA 2021-2024'!G33 -> 4.1418756 | T23: ='WRA 2021-2024'!H31+'WRA 2021-2024'!H32+'WRA 2021-2024'!H33 -> 0.234036 | U23: ='WRA 2021-2024'!G34 -> 44.64972 | V23: ='WRA 2021-2024'!H34 -> 0.0936 | X23: =SUM(O23+Q23+S23+U23) -> 63.321314 | Y23: =N23-X23 -> 10515.744 | Z23: =Y23-AA23 -> 10515.744 | AA23: ='Basin Data WS1'!D47 -> 0 | AB23: 0 | AC23: 0
A24: Lake Victoria South | B24: =rainfall!C17 -> 991 | C24: =C15 -> 26906 | D24: =B24*100*C24*10/1000000 -> 26663.846 | E24: =rainfall!D17 -> 430.59014 | F24: =C24*100*E24*10/1000000 -> 11585.458 | G24: -316 | H24: 2095 | I24: =H24*0.2 -> 419 | J24: =D24-F24+G24-H24-I24 -> 12248.388 | K24: 1 | M24: ='Basin Data WS1'!E33 -> 0 | N24: =SUM(L24+M24+J24) -> 12248.388 | O24: ='WRA 2021-2024'!I30 -> 2.327202 | P24: ='WRA 2021-2024'!J30 -> 1.8645408 | Q24: ='WRA 2021-2024'!I29 -> 34.957404 | R24: ='WRA 2021-2024'!J29 -> 0.0637524 | S24: ='WRA 2021-2024'!I31+'WRA 2021-2024'!I32+'WRA 2021-2024'!I33 -> 4.7689596 | T24: ='WRA 2021-2024'!J31+'WRA 2021-2024'!J32+'WRA 2021-2024'!J33 -> 0.261396 | U24: ='WRA 2021-2024'!I34 -> 8.4550932 | V24: ='WRA 2021-2024'!J34 -> 0.10008 | X24: =SUM(O24+Q24+S24+U24) -> 50.508659 | Y24: =N24-X24 -> 12197.879 | Z24: =Y24-AA24 -> 12197.879 | AA24: ='Basin Data WS1'!E49 -> 0 | AB24: 0 | AC24: 0
A25: Rift Valley | B25: =rainfall!C18 -> 418 | C25: =C16 -> 131423 | D25: =B25*100*C25*10/1000000 -> 54934.814 | E25: =rainfall!D18 -> 190.608 | F25: =C25*100*E25*10/1000000 -> 25050.275 | G25: -251 | H25: 3168 | I25: =H25*0.2 -> 633.6 | J25: =D25-F25+G25-H25-I25 -> 25831.939 | K25: 1659 | L25: 0 | M25: ='Basin Data WS1'!G33 -> 0 | N25: =SUM(L25+M25+J25) -> 25831.939 | O25: ='WRA 2021-2024'!K22 -> 597.09588 | P25: ='WRA 2021-2024'!L22 -> 0.11592 | Q25: ='WRA 2021-2024'!K29 -> 5.3445312 | R25: ='WRA 2021-2024'!L29 -> 23.251054 | S25: ='WRA 2021-2024'!K31+'WRA 2021-2024'!K32+'WRA 2021-2024'!K33 -> 61.313101 | T25: ='WRA 2021-2024'!L31+'WRA 2021-2024'!L32+'WRA 2021-2024'!L33 -> 68.95741 | U25: ='WRA 2021-2024'!K34 -> 0.0360396 | V25: ='WRA 2021-2024'!L34 -> 0.9932112 | X25: =SUM(O25+Q25+S25+U25) -> 663.78956 | Y25: =N25-X25 -> 25168.149 | Z25: =Y25-AA25 -> 25168.149 | AA25: ='Basin Data WS1'!G47 -> 0 | AB25: ='Basin Data WS1'!G54 -> 0 | AC25: 0
A26: Tana | B26: =rainfall!C19 -> 784 | C26: =C17 -> 126208 | D26: =B26*100*C26*10/1000000 -> 98947.072 | E26: =rainfall!D19 -> 244.273 | F26: =C26*100*E26*10/1000000 -> 30829.206 | G26: -251 | H26: 4479 | I26: =H25*0.2 -> 633.6 | J26: =D26-F26+G26-H26-I26 -> 62754.266 | K26: =16+70+1560+123+20+16+585 -> 2390 | L26: -181 | M26: ='Basin Data WS1'!F33 -> 0 | N26: =SUM(L26+M26+J26) -> 62573.266 | O26: ='WRA 2021-2024'!E30 -> 159.23154 | P26: ='WRA 2021-2024'!F30 -> 3.43251 | Q26: ='WRA 2021-2024'!E29 -> 82.611864 | R26: ='WRA 2021-2024'!F29 -> 0.0288 | S26: ='WRA 2021-2024'!E31+'WRA 2021-2024'!E32+'WRA 2021-2024'!E33 -> 144.94085 | T26: ='WRA 2021-2024'!F31+'WRA 2021-2024'!F32+'WRA 2021-2024'!F33 -> 0.47169 | U26: ='WRA 2021-2024'!E34 -> 2.7990792 | V26: ='WRA 2021-2024'!F34 -> 0.03618 | X26: =SUM(O26+Q26+S26+U26) -> 389.58333 | Y26: =N26-X26 -> 62183.682

Sheet Metadata description 
B2: Data Sources
A3: 1 | B3: Water Resources Authority (WRA) – Performance report data for 2021 & 2023
A4: 2 | B4: Water Services Regulatory Board (WASREB) – Data for 2021–2023
A5: 3 | B5: Climate Hazards Center – CHIRPS (Climate Hazards Group InfraRed Precipitation with Station data) – Time series rainfall data
A6: 4 | B6: WRA GIS Data – Rivers and lakes (sourced from WRA website)
A7: 5 | B7: Humanitarian Data Exchange (HDX) – Basin and sub-basin demarcation
A8: 6 | B8: OpenStreetMap (OSM) – Land use and land cover data
A9: 7 | B9: Shuttle Radar Topography Mission (SRTM) – Digital Elevation Model for country topography
A10: 8 | B10: Ministry of Water, Sanitation and Irrigation – National Water Master Plan 2030 (NWMP 2030)
A11: 9 | B11: Ministry of Water, Sanitation and Irrigation – Basin Water Resources Management and Development Plans (2020)
A12: 10 | B12: World Reference Base for Soil Resources (2014) – Global soil map
A13: 11 | B13: Google Earth Engine – MODIS Evapotranspiration – Time series data for ET

Sheet WASREB 2020-2021
A1: Data Source | B1: Ewaso Basin | I1: Total | L1: Tana Basin | AM1: Total | AP1: Athi Basin | BT1: Total | BW1: Rift Valley | CH1: Total | CK1: Lake Victoria South | CR1: Total | CU1: Lake Victoria North | CY1: WASREB | DC1: Total
A2: County | B2: Wajir | C2: Mandera | D2: Mandera | E2: Laikipia | F2: Lakipia | G2: Nyeri | H2: Samburu | L2: Lamu | M2: Embu | N2: Embu | O2: Embu | P2: Embu | Q2: Kitui | R2: Kitui | S2: Kirinyaga | T2: Tharaka-Nithi | U2: Embu | V2: Nyeri | W2: Tharaka-Nithi | X2: Tharaka-Nithi | Y2: Meru | Z2: Meru | AA2: Meru | AB2: Nyeri | AC2: Nyeri | AD2: Nyeri | AE2: Garissa | AF2: Isiolo | AG2: Murang'a | AH2: Murang'a | AI2: Murang'a | AJ2: Murang'a | AK2: Kiambu | AL2: Tana River | AP2: Kwale | AQ2: Taita-Taveta | AR2: Nairobi | AS2: Nairobi | AT2: Makueni | AU2: Makueni | AV2: Kiambu | AW2: Kiambu | AX2: Kiambu | AY2: Kiambu | AZ2: Kiambu | BA2: Kiambu | BB2: Kiambu | BC2: Kiambu | BD2: Murang'a | BE2: Kilifi | BF2: Kilifi | BG2: Machakos | BH2: Machakos | BI2: Machakos | BJ2: Machakos | BK2: Machakos | BL2: Machakos | BM2: Kirinyaga | BN2: Kiambu | BO2: Makueni | BP2: Mombasa | BQ2: Kajiado | BR2: Kajiado | BS2: Kajiado | BW2: Turkana | BX2: West Pokot | BY2: Baringo | BZ2: Nyandarua | CA2: Nyandarua | CB2: Nakuru | CC2: Nakuru | CD2: Nakuru | CE2: Narok | CF2: Baringo | CG2: Elgeiyo Marakwet | CK2: Migori | CL2: Homabay | CM2: Bomet | CN2: Migori | CO2: Kericho | CP2: Kisumu | CQ2: Gusii | CU2: Nandi | CV2: Busia | CW2: Kakamega | CX2: Bungoma | CY2: Vihiga | CZ2: Siaya | DA2: Uasin Gishu | DB2: Nandi | DO2: Totals
A3: INDICATORS | B3: Wajir | C3: Elwak | D3: Mandera | E3: Nyahururu | F3: Nanyuki | G3: Naromoru | H3: Samburu | L3: Lamu | M3: Ngagaka | N3: Ngandori Nginda | O3: Embe | P3: Embu | Q3: Kitui | R3: Kiambere Mwingi | S3: Kirinyaga | T3: Murugi Mugumango | U3: Kyeni | V3: Mathira | W3: Nithi | X3: Muthambi 4K | Y3: Tuuru | Z3: Imetha | AA3: Meru | AB3: Othaya Mukurweni | AC3: Nyeri | AD3: Tetu Aberdare | AE3: Garissa | AF3: Isiolo | AG3: Kahuti | AH3: Gatamathi | AI3: Murang'a | AJ3: Murang'a South | AK3: Thika | AL3: Tana | AP3: Kwale | AQ3: Tavevo | AR3: Nairobi | AS3: Runda | AT3: Kibwezi Makindu | AU3: Mbooni | AV3: Gatundu | AW3: Githunguri | AX3: Kiamumbi | AY3: Kikuyu | AZ3: Limuru | BA3: Karuri | BB3: Ruiru-Juja | BC3: Kiambu | BD3: Gatanga | BE3: Kilifi Mariakani | BF3: Malindi | BG3: Kathiani | BH3: Machakos | BI3: Matungulu Kangundo | BJ3: Mwala | BK3: Yatta | BL3: Mavoko | BM3: Rukanga | BN3: Tatu City | BO3: Wote | BP3: Mombasa | BQ3: Nol Turesh Loitokitok | BR3: Olkejuado | BS3: Oloolaiser | BW3: Lodwar | BX3: Kapenguria | BY3: Chemususu | BZ3: Nyandarua | CA3: Ol Kalou | CB3: Naivasha | CC3: Nakuru | CD3: Nakuru Rural | CE3: Narok | CF3: Kirandich | CG3: Iten Tambach | CK3: Migori | CL3: Homabay | CM3: Bomet | CN3: Nyasare | CO3: Kericho | CP3: Kisumu | CQ3: Gusii | CU3: Tachasis | CV3: Busia | CW3: Kakamega | CX3: Nzoia | CY3: Amatsi | CZ3: Sibo | DA3: Eldoret | DB3: Kapsabet Nandi
A4: Surface water abstracted | B4: =B14 -> 571536 | C4: 349920 | D4: 582496 | E4: 3184387 | F4: 4551704 | G4: 269700 | H4: 648000 | I4: =SUM(B4:H4) -> 10157743 | L4: 600563 | M4: 1157580 | N4: 2758450 | O4: 1034205 | P4: 7637891 | Q4: 3626236 | R4: 974979 | S4: 6722945 | T4: 2214840 | U4: 1039740 | V4: 2281551 | W4: 3700773 | X4: 648456 | Y4: 1885587 | Z4: 1184866 | AA4: 3001251 | AB4: 5460800 | AC4: 7401710 | AD4: 3028040 | AE4: 5961600 | AF4: 2286780 | AG4: 3335937 | AH4: 2790003 | AI4: 2742691 | AJ4: 5690163 | AK4: 13172207 | AL4: 1908000 | AM4: =SUM(L4:AL4) -> 94247844 | AP4: 0 | AQ4: 0 | AR4: 193642797 | AS4: 834833 | AT4: 1298437 | AU4: 64972 | AV4: 7169376 | AW4: 1183987 | AX4: 523274 | AY4: 0 | AZ4: 2148401 | BA4: 1410393 | BB4: 10747235 | BC4: 2132758 | BD4: 2273106 | BE4: 0 | BF4: 0 | BG4: 100541 | BH4: 1242862 | BI4: =BI10 -> 153695 | BJ4: 51337 | BK4: 389392 | BL4: 960832 | BM4: 384030 | BN4: 136818 | BO4: 181233 | BP4: 0 | BQ4: 2190000 | BR4: 0 | BS4: 1792633 | BT4: =SUM(AP4:BS4) -> 231012942 | BW4: 2304940 | BX4: 243026 | BY4: 850153 | BZ4: 659793 | CA4: 621290 | CB4: 1899235 | CC4: 11537195 | CD4: 8242189 | CE4: 882905 | CF4: 1036000 | CG4: 1168859 | CH4: =SUM(BW4:CG4) -> 29445585 | CK4: 481921 | CL4: 1018819 | CM4: 4424004 | CN4: 114293 | CO4: 4100926 | CP4: 9915691 | CQ4: 3231652 | CR4: =SUM(CK4:CQ4) -> 23287306 | CU4: 350447 | CV4: 1207650 | CW4: 5432762 | CX4: 8265495 | CY4: 1573007 | CZ4: 3224003 | DA4: 15290495 | DB4: 1085366 | DC4: =SUM(CU4:DB4) -> 36429225 | DO4: =SUM(CY4:DM4) -> 57602096
A5: Groundwater abstracted | F5: 109546 | I5: =SUM(B5:H5) -> 109546 | AF5: 76160 | AM5: =SUM(L5:AL5) -> 76160 | AQ5: 408110 | AW5: 256968 | AY5: 2507323 | BA5: 779729 | BC5: 215399 | BH5: 21120 | BJ5: 32196 | BL5: 99230 | BO5: 278132 | BR5: 357800 | BS5: 654586 | BT5: =SUM(AP5:BS5) -> 5610593 | BZ5: 28928 | CB5: 1974833 | CH5: =SUM(BW5:CG5) -> 2003761 | CN5: 25979 | CR5: =SUM(CK5:CQ5) -> 25979 | CW5: 274551 | DC5: =SUM(CU5:DB5) -> 274551 | DO5: =SUM(CY5:DM5) -> 274551
A6: Total volume of water treated | E6: 3180625 | F6: 4661250 | I6: =SUM(I4:I5) -> 10267289 | AC6: 7401710 | AD6: 1010520 | AE6: 5166915 | AF6: 0 | AH6: 2790003 | AI6: 2742691 | AR6: 179341134 | AX6: 465132 | AY6: 2507323 | BC6: 2132758 | BF6: 0 | BH6: 1208832 | BI6: 0 | BJ6: 115101 | BK6: 389392 | BO6: =SUM(BO4:BO5) -> 459365 | BR6: 0 | BS6: 1792633 | BZ6: 267731 | CG6: 1168859 | CN6: 0 | CU6: 0 | DO6: =SUM(CY6:DM6) -> 0
A7: Imported treated water | E7: 0 | F7: 0 | AC7: 0 | AD7: 0 | AE7: 0 | AF7: 0 | AH7: 0 | AI7: 0 | AP7: 4521589 | AQ7: 5357895 | AR7: 0 | AX7: 0 | AY7: 0 | BC7: 819034 | BE7: 11231993 | BF7: 6886695 | BH7: 0 | BI7: 0 | BJ7: 0 | BK7: 0 | BO7: 0 | BP7: 12495475 | BR7: 0 | BS7: 0 | BT7: =SUM(AP7:BS7) -> 41312681 | BZ7: 50287 | CG7: 0 | CH7: =SUM(BW7:CG7) -> 50287 | CN7: 0 | CU7: 0 | DO7: =SUM(CY7:DM7) -> 0
A8: Exported treated water | E8: 0 | F8: 0 | AC8: 0 | AD8: 0 | AE8: 0 | AF8: 0 | AH8: 0 | AI8: 0 | AR8: 0 | AX8: 0 | AY8: 0 | BC8: 0 | BF8: 0 | BH8: 0 | BI8: 0 | BJ8: 0 | BK8: 0 | BO8: 0 | BR8: 0 | BS8: 0 | BZ8: 0 | CG8: 0 | CN8: 0 | CU8: 0 | DO8: =SUM(CY8:DM8) -> 0
A9: Metered volume produced | B9: n.d. | C9: 349920 | D9: 582496 | E9: 3180625 | F9: 4661250 | G9: 269700 | H9: 648000 | L9: 600563 | M9: 1157580 | N9: 2758450 | O9: 1034205 | P9: 7637891 | Q9: 3626236 | R9: 974979 | S9: 6722945 | T9: 2214840 | U9: 1039740 | V9: 2281551 | W9: 3700773 | X9: 648456 | Y9: 1885587 | Z9: 1184866 | AA9: 3001251 | AB9: 5460800 | AC9: 7401710 | AD9: 1990520 | AE9: 0 | AF9: 2362940 | AG9: 3335937 | AH9: 2790003 | AI9: 2742691 | AJ9: 5690163 | AK9: 13172207 | AL9: 1908000 | AP9: 4521589 | AQ9: 5357895 | AR9: 179341134 | AS9: 834833 | AT9: 1298437 | AU9: 64972 | AV9: 7169376 | AW9: 1183987 | AX9: 465132 | AY9: 2507323 | AZ9: 2148401 | BA9: 1410393 | BB9: 10747235 | BC9: 3162191 | BD9: 2273106 | BE9: 11231993 | BF9: 6886695 | BG9: 100541 | BH9: 1208832 | BI9: 119125 | BJ9: 115101 | BK9: 389392 | BL9: 960832 | BM9: 384030 | BN9: 136818 | BO9: 459365 | BP9: 12495475 | BQ9: 2190000 | BR9: 357800 | BS9: 2447219 | BW9: 2304940 | BX9: 243026 | BY9: 850153 | BZ9: 657679 | CA9: 621290 | CB9: 1899235 | CC9: 11537195 | CD9: 8242189 | CE9: 882905 | CF9: 1036000 | CG9: 1168859 | CK9: 481921 | CL9: 1018819 | CM9: 4424004 | CN9: 0 | CO9: 4100926 | CP9: 9915691 | CQ9: 3231652 | CU9: 0 | CV9: 1207650 | CW9: 5432762 | CX9: 8265495 | CY9: 1573007 | CZ9: 3224003 | DA9: 15290495 | DB9: 1085366 | DO9: =SUM(CY9:DM9) -> 21172871
A10: Total Water Produced | B10: =SUM(B4:B5,B7) -> 571536 | C10: 349920 | D10: 582496 | E10: 3184387 | F10: 4661250 | G10: 269700 | H10: 648000 | I10: =SUM(B10:H10) -> 10267289 | L10: 600563 | M10: 1157580 | N10: 2758450 | O10: 1034205 | P10: 7637891 | Q10: 3626236 | R10: 974979 | S10: 6722945 | T10: 2214840 | U10: 1039740 | V10: 2281551 | W10: 3700773 | X10: 648456 | Y10: 1885587 | Z10: 1184866 | AA10: 3001251 | AB10: 5460800 | AC10: 7401710 | AD10: 3028040 | AE10: 5961600 | AF10: 2362940 | AG10: 3335937 | AH10: 2790003 | AI10: 2742691 | AJ10: 5690163 | AK10: 13172207 | AL10: 1908000 | AM10: =SUM(L10:AL10) -> 94324004 | AP10: 4521589 | AQ10: =SUM(AQ4:AQ5,AQ7) -> 5766005 | AR10: =SUM(AR4:AR5,AR7) -> 193642797 | AS10: 834833 | AT10: 1298437 | AU10: 64972 | AV10: 7169376 | AW10: =SUM(AW4:AW5,AW7) -> 1440955 | AX10: =SUM(AX4:AX5,AX7) -> 523274 | AY10: 2507323 | AZ10: 2148401 | BA10: =SUM(BA4:BA5,BA7) -> 2190122 | BB10: 10747235 | BC10: 3167191 | BD10: 2273106 | BE10: 11231993 | BF10: 6886695 | BG10: 100541 | BH10: 1263982 | BI10: 153695 | BJ10: =SUM(BJ4:BJ5,BJ7) -> 83533 | BK10: 389392 | BL10: =SUM(BL4:BL5,BL7) -> 1060062 | BM10: 384030 | BN10: 136818 | BO10: 459365 | BP10: 12495475 | BQ10: 2190000 | BR10: =SUM(BR4:BR5,BR7) -> 357800 | BS10: 2447219 | BT10: =SUM(AP10:BS10) -> 277936216 | BW10: 2304940 | BX10: 243026 | BY10: 850153 | BZ10: 739008 | CA10: 621290 | CB10: =SUM(CB4:CB5,CB7) -> 3874068 | CC10: 11537195 | CD10: 8242189 | CE10: 882905 | CF10: 1036000 | CG10: 1168859 | CH10: =SUM(BW10:CG10) -> 31499633 | CK10: 481921 | CL10: 1018819 | CM10: 4424004 | CN10: 140272 | CO10: 4100926 | CP10: 9915691 | CQ10: 3231652 | CR10: =SUM(CK10:CQ10) -> 23313285 | CU10: 350447 | CV10: 1207650 | CW10: =SUM(CW4:CW5,CW7) -> 5707313 | CX10: 8265495 | CY10: 1573007 | CZ10: 3224003 | DA10: 15290495 | DB10: 1085366 | DC10: =SUM(CU10:DB10) -> 36703776 | DO10: =SUM(CY10:DM10) -> 57876647
B11: =SUM(B4:B5,B7)-B10 -> 0 | C11: =SUM(C4:C5,C7)-C10 -> 0 | D11: =SUM(D4:D5,D7)-D10 -> 0 | E11: =SUM(E4:E5,E7)-E10 -> 0 | F11: =SUM(F4:F5,F7)-F10 -> 0 | G11: =SUM(G4:G5,G7)-G10 -> 0 | H11: =SUM(H4:H5,H7)-H10 -> 0 | L11: =SUM(L4:L5,L7)-L10 -> 0 | M11: =SUM(M4:M5,M7)-M10 -> 0 | N11: =SUM(N4:N5,N7)-N10 -> 0 | O11: =SUM(O4:O5,O7)-O10 -> 0 | P11: =SUM(P4:P5,P7)-P10 -> 0 | Q11: =SUM(Q4:Q5,Q7)-Q10 -> 0 | R11: =SUM(R4:R5,R7)-R10 -> 0 | S11: =SUM(S4:S5,S7)-S10 -> 0 | ... AL11: =SUM(AL4:AL5,AL7)-AL10 -> 0 | AP11: =SUM(AP4:AP5,AP7)-AP10 -> 0 | AQ11: =SUM(AQ4:AQ5,AQ7)-AQ10 -> 0 | AR11: =SUM(AR4:AR5,AR7)-AR10 -> 0 | AS11: =SUM(AS4:AS5,AS7)-AS10 -> 0 | AT11: =SUM(AT4:AT5,AT7)-AT10 -> 0 | AU11: =SUM(AU4:AU5,AU7)-AU10 -> 0 | AV11: =SUM(AV4:AV5,AV7)-AV10 -> 0 | AW11: =SUM(AW4:AW5,AW7)-AW10 -> 0 | ... BS11: =SUM(BS4:BS5,BS7)-BS10 -> 0 | BW11: =SUM(BW4:BW5,BW7)-BW10 -> 0 | BX11: =SUM(BX4:BX5,BX7)-BX10 -> 0 | BY11: =SUM(BY4:BY5,BY7)-BY10 -> 0 | BZ11: =SUM(BZ4:BZ5,BZ7)-BZ10 -> 0 | CA11: =SUM(CA4:CA5,CA7)-CA10 -> 0 | CB11: =SUM(CB4:CB5,CB7)-CB10 -> 0 | CC11: =SUM(CC4:CC5,CC7)-CC10 -> 0 | CD11: =SUM(CD4:CD5,CD7)-CD10 -> 0 | ... CG11: =SUM(CG4:CG5,CG7)-CG10 -> 0 | CK11: =SUM(CK4:CK5,CK7)-CK10 -> 0 | CL11: =SUM(CL4:CL5,CL7)-CL10 -> 0 | CM11: =SUM(CM4:CM5,CM7)-CM10 -> 0 | CN11: =SUM(CN4:CN5,CN7)-CN10 -> 0 | CO11: =SUM(CO4:CO5,CO7)-CO10 -> 0 | CP11: =SUM(CP4:CP5,CP7)-CP10 -> 0 | CQ11: =SUM(CQ4:CQ5,CQ7)-CQ10 -> 0 | CU11: =SUM(CU4:CU5,CU7)-CU10 -> 0 | CV11: =SUM(CV4:CV5,CV7)-CV10 -> 0 | CW11: =SUM(CW4:CW5,CW7)-CW10 -> 0 | CX11: =SUM(CX4:CX5,CX7)-CX10 -> 0 | CY11: =SUM(CY4:CY5,CY7)-CY10 -> 0 | CZ11: =SUM(CZ4:CZ5,CZ7)-CZ10 -> 0 | DA11: =SUM(DA4:DA5,DA7)-DA10 -> 0 | DB11: =SUM(DB4:DB5,DB7)-DB10 -> 0
A12: Value of Water Abstracted/ Produced | B12: NO DATA | C12: 79772794 | D12: 1.7856676e+08 | E12: 2.219596e+08 | F12: 3.9550335e+08 | G12: 16540076 | H12: 58365545 | L12: 85334549 | M12: 38340240 | N12: 69827129 | O12: 38597578 | P12: 3.6295737e+08 | Q12: 278521048 | R12: 135178025 | S12: 175178481 | T12: 21187941 | U12: 16654271 | V12: 148496925 | W12: 110540087 | X12: 11512382 | Y12: 20530487 | Z12: 56402541 | AA12: 2.155529e+08 | AB12: 158301093 | AC12: 4.5253676e+08 | AD12: 66044176 | AE12: 4.6772077e+08 | AF12: 82307738 | AG12: 76336089 | AH12: 60579777 | AI12: 2.2835782e+08 | AJ12: 228667569 | AK12: 497763520 | AL12: 86273989 | AP12: 208215827 | AQ12: 415995123 | AR12: 6.7833619e+09 | AS12: 55328906 | AT12: 86202402 | AU12: 5071016 | AV12: 136723929 | AW12: 70805791 | AX12: 22573822 | AY12: 139042955 | AZ12: 141350626 | BA12: 109157959 | BB12: 5.321785e+08 | BC12: 201580632 | BD12: 58531874 | BE12: 5.6720057e+08 | BF12: 556219860 | BG12: 14266064 | BH12: 130523129 | BI12: 16952185 | BJ12: 18538604 | BK12: 46115044 | BL12: 208513398 | BM12: 8885446 | BN12: 52349712 | BO12: 42400663 | BP12: 913363452 | BQ12: 69932275 | BR12: 32142167 | BS12: 187075312 | BW12: 54230924 | BX12: 12673451 | BY12: 23063224 | BZ12: 51195602 | CA12: 36236035 | CB12: 93019470 | CC12: 8.2898502e+08 | CD12: 314924993 | CE12: 110004557 | CF12: 59753784 | CG12: 35013579 | CK12: 51740623 | CL12: 97875348 | CM12: 240039575 | CN12: 4239561 | CO12: 263530219 | CP12: 8.2584084e+08 | CQ12: 1.7539918e+08 | CU12: 2006154 | CV12: 79258129 | CW12: 2.4503747e+08 | CX12: 3.3822517e+08 | CY12: 73930703 | CZ12: 136008536 | DA12: 7.1223858e+08 | DB12: 75328017
A13: Value of Imported treated water | B13: 0 | C13: 0 | D13: 0 | E13: 0 | F13: 0 | G13: 0 | H13: 0 | L13: 0 | M13: 0 | N13: 0 | O13: 0 | P13: 0 | Q13: 0 | R13: 0 | S13: 0 | T13: 0 | U13: 0 | V13: 0 | W13: 0 | X13: 0 | Y13: 0 | Z13: 0 | AA13: 0 | AB13: 0 | AC13: 0 | AD13: 0 | AE13: 0 | AF13: 0 | AG13: 0 | AH13: 0 | AI13: 0 | AJ13: 0 | AK13: 0 | AL13: 0 | AP13: 208215827 | AQ13: 415995123 | AR13: 0 | AS13: 0 | AT13: 0 | AU13: 0 | AV13: 0 | AW13: 0 | AX13: 0 | AY13: 0 | AZ13: 0 | BA13: 0 | BB13: 0 | BC13: 52128650 | BD13: 0 | BE13: 5.6720057e+08 | BF13: 556219860 | BG13: 0 | BH13: 0 | BI13: 0 | BJ13: 0 | BK13: 0 | BL13: 0 | BM13: 0 | BN13: 0 | BO13: 0 | BP13: 913363452 | BQ13: 0 | BR13: 0 | BS13: 0 | BW13: 0 | BX13: 0 | BY13: 0 | BZ13: 3483687.9 | CA13: 0 | CB13: 0 | CC13: 0 | CD13: 0 | CE13: 0 | CF13: 0 | CG13: 0 | CK13: 0 | CL13: 0 | CM13: 0 | CN13: 0 | CO13: 0 | CP13: 0 | CQ13: 0 | CU13: 0 | CV13: 0 | CW13: 0 | CX13: 0 | CY13: 0 | CZ13: 0 | DA13: 0 | DB13: 0
A14: Total Billed Volume | B14: 571536 | C14: 141426 | D14: 344242 | E14: 1931100 | F14: 2789074 | G14: 167689 | H14: 361390 | L14: 352197 | M14: 721694 | N14: 1740204 | O14: 461783 | P14: 4739448 | Q14: 1653210 | R14: 602643 | S14: 2701227 | T14: 1771192 | U14: 573552 | V14: 1214018 | W14: 1298768 | X14: 486523 | Y14: 435051 | Z14: 716731 | AA14: 2421650 | AB14: 2986416 | AC14: 6117001 | AD14: 2149900 | AE14: 3576960 | AF14: 1638248 | AG14: 1214494 | AH14: 1020766 | AI14: 2068366 | AJ14: 2977634 | AK14: 9214087 | AL14: 566988 | AP14: 1835915 | AQ14: 3350520 | AR14: 89727204 | AS14: 618158 | AT14: 935944 | AU14: 42602 | AV14: 4742140 | AW14: 690912 | AX14: 354485 | AY14: 1454089 | AZ14: 1519934 | BA14: 1005557 | BB14: 6915527 | BC14: 2072421 | BD14: 1370875 | BE14: 5347542 | BF14: 5164287 | BG14: 70381 | BH14: 710419 | BI14: 90678 | BJ14: 42682 | BK14: 274619 | BL14: 604643 | BM14: 156414 | BN14: 125326 | BO14: 298451 | BP14: 5823200 | BQ14: 1081545 | BR14: 219878 | BS14: 1428834 | BW14: 1273305 | BX14: 75766 | BY14: 272266 | BZ14: 394594 | CA14: 322268 | CB14: 1358834.9 | CC14: 7905899 | CD14: 3830215 | CE14: 785675 | CF14: 440400 | CG14: 794825 | CK14: 249630 | CL14: 569227 | CM14: 2005094 | CN14: 89065 | CO14: 1946176 | CP14: 6696511 | CQ14: 1348246 | CU14: 262729 | CV14: 620242 | CW14: 3072689 | CX14: 4254899 | CY14: 1101104.9 | CZ14: 974798 | DA14: 8869969 | DB14: 681984
A15: Water Value | AL15: =AL12/AL10 -> 45.216975 | CU15: =CU12/CU10 -> 5.7245575 | CZ15: =CZ12/CZ10 -> 42.186231
A16: Total Water Produced | C16: 349920 | D16: 582496 | E16: 3184387 | F16: 4661250 | G16: 269700 | H16: 648000 | L16: 600563 | M16: 1157580 | N16: 2758450 | O16: 1034205 | P16: 7637891 | Q16: 3626236 | R16: 974979 | S16: 6722945 | T16: 2214840 | U16: 1039740 | V16: 2281551 | W16: 3700773 | X16: 648456 | Y16: 1885587 | Z16: 1184866 | AA16: 3001251 | AB16: 5460800 | AC16: 7401710 | AD16: 3028040 | AE16: 5961600 | AF16: 2362940 | AG16: 3335937 | AH16: 2790003 | AI16: 2742691 | AJ16: 5690163 | AK16: 13172207 | AL16: 1908000 | AP16: 4521589 | AQ16: 5357895 | AR16: 179341134 | AS16: 834833 | AT16: 1298437 | AU16: 64972 | AV16: 7169376 | AW16: 1183987 | AX16: 465132 | AY16: 2507323 | AZ16: 2148401 | BA16: 1410393 | BB16: 10747235 | BC16: 3167191 | BD16: 2273106 | BE16: 11231993 | BF16: 6886695 | BG16: 100541 | BH16: 1263982 | BI16: 153695 | BJ16: 58205 | BK16: 389392 | BL16: 960832 | BM16: 384030 | BN16: 136818 | BO16: 459365 | BP16: 12495475 | BQ16: 2190000 | BR16: 377280 | BS16: 2447219 | BW16: 2304940 | BX16: 243026 | BY16: 850153 | BZ16: 739008 | CA16: 621290 | CB16: 1899235 | CC16: 11537195 | CD16: 8242189 | CE16: 882905 | CF16: 1036000 | CG16: 1168859 | CK16: 481921 | CL16: 1018819 | CM16: 4424004 | CN16: 140272 | CO16: 4100926 | CP16: 9915691 | CQ16: 3231652 | CU16: 350447 | CV16: 1207650 | CW16: 5432762 | CX16: 8265495 | CY16: 1573007 | CZ16: 3224003 | DA16: 15290495 | DB16: 1085366 | DO16: =SUM(CY16:DM16) -> 21172871
A17: Total sewage treated | E17: 1116976 | F17: 995579.1 | I17: =SUM(B17:H17) -> 2112555.1 | P17: 1950734 | Q17: NO DATA | AC17: 3810236 | AE17: 240000 | AF17: 297423 | AI17: 1261585.9 | AK17: 4015000 | AM17: =SUM(L17:AL17) -> 11574979 | AR17: 80525515 | BB17: 1379820.5 | BC17: 2500 | BH17: 72204 | BL17: 752000 | BP17: 6000 | BT17: =SUM(AP17:BS17) -> 82738039 | CB17: 993631 | CC17: 4393860 | CH17: =SUM(BW17:CG17) -> 5387491 | CL17: NO DATA | CO17: 175140 | CP17: 4692420 | CQ17: 1816500 | CR17: =SUM(CK17:CQ17) -> 6684060 | CW17: 396060 | CX17: 1471640 | DA17: 7850064 | DC17: =SUM(CU17:DB17) -> 9717764 | DO17: =SUM(CY17:DM17) -> 17567828
A18: Total Expenditures | B18: n.d. | C18: 79772794 | D18: 178566758 | E18: 261128942 | F18: 416319319 | G18: 16540076 | H18: 58365545 | L18: 85334549 | M18: 38340240 | N18: 69827129 | O18: 38597578 | P18: 427008665 | Q18: 278521048 | R18: 135178025 | S18: 175178481 | T18: 21187941 | U18: 16654271 | V18: 148496925 | W18: 110540087 | X18: 11512382 | Y18: 20530487 | Z18: 56402541 | AA18: 215552899 | AB18: 158301093 | AC18: 502818624 | AD18: 66044176 | AE18: 550259733 | AF18: 96832633 | AG18: 76336089 | AH18: 60579777 | AI18: 235420437 | AJ18: 228667569 | AK18: 654952000 | AL18: 86273989 | AP18: 208215827 | AQ18: 415995123 | AR18: 10435941392 | AS18: 55328906 | AT18: 86202402 | AU18: 5071016 | AV18: 136723929 | AW18: 70805791 | AX18: 22573822 | AY18: 139042955 | AZ18: 141350626 | BA18: 109157959 | BB18: 626092351 | BC18: 201580632 | BD18: 58531874 | BE18: 667294785 | BF18: 556219860 | BG18: 14266064 | BH18: 130523129 | BI18: 16952185 | BJ18: 18538604 | BK18: 46115044 | BL18: 208513398 | BM18: 8885446 | BN18: 52349712 | BO18: 42400663 | BP18: 913363452 | BQ18: 69932275 | BR18: 32142167 | BS18: 187075312 | BW18: 54230924 | BX18: 12673451 | BY18: 23063224 | BZ18: 51195602 | CA18: 36236035 | CB18: 186038940 | CC18: 975276497 | CD18: 314924993 | CE18: 110004557 | CF18: 59753784 | CG18: 35013579 | CK18: 51740623 | CL18: 97875348 | CM18: 240039575 | CN18: 4239561 | CO18: 263530219 | CP18: 943818099 | CQ18: 206351982 | CU18: 2006154 | CV18: 79258129 | CW18: 350053531 | CX18: 397911961 | CY18: 73930703 | CZ18: 136008536 | DA18: 837927741 | DB18: 75328017
A19: Total Expenditures-water | B19: n.d. | C19: 79772794 | D19: 178566758 | E19: 2.219596e+08 | F19: 3.9550335e+08 | G19: 16540076 | H19: 58365545 | L19: 85334549 | M19: 38340240 | N19: 69827129 | O19: 38597578 | P19: 3.6295737e+08 | Q19: 278521048 | R19: 135178025 | S19: 175178481 | T19: 21187941 | U19: 16654271 | V19: 148496925 | W19: 110540087 | X19: 11512382 | Y19: 20530487 | Z19: 56402541 | AA19: 215552899 | AB19: 158301093 | AC19: 4.5253676e+08 | AD19: 66044176 | AE19: 4.6772077e+08 | AF19: 82307738 | AG19: 76336089 | AH19: 60579777 | AI19: 2.2835782e+08 | AJ19: 228667569 | AK19: 497763520 | AL19: 86273989 | AP19: 208215827 | AQ19: 415995123 | AR19: 6.7833619e+09 | AS19: 55328906 | AT19: 86202402 | AU19: 5071016 | AV19: 136723929 | AW19: 70805791 | AX19: 22573822 | AY19: 139042955 | AZ19: 141350626 | BA19: 109157959 | BB19: 5.321785e+08 | BC19: 201580632 | BD19: 58531874 | BE19: 5.6720057e+08 | BF19: 556219860 | BG19: 14266064 | BH19: 130523129 | BI19: 16952185 | BJ19: 18538604 | BK19: 46115044 | BL19: 208513398 | BM19: 8885446 | BN19: 52349712 | BO19: 42400663 | BP19: 913363452 | BQ19: 69932275 | BR19: 32142167 | BS19: 187075312 | BW19: 54230924 | BX19: 12673451 | BY19: 23063224 | BZ19: 51195602 | CA19: 36236035 | CB19: 93019470 | CC19: 8.2898502e+08 | CD19: 314924993 | CE19: 110004557 | CF19: 59753784 | CG19: 35013579 | CK19: 51740623 | CL19: 97875348 | CM19: 240039575 | CN19: 4239561 | CO19: 263530219 | CP19: 8.2584084e+08 | CQ19: 1.7539918e+08 | CU19: 2006154 | CV19: 79258129 | CW19: 2.4503747e+08 | CX19: 3.3822517e+08 | CY19: 73930703 | CZ19: 136008536 | DA19: 7.1223858e+08 | DB19: 75328017
A20: Total Expenditures-sewage | E20: 39169341 | F20: 19775168 | P20: 54443605 | Q20: NO DATA | AC20: 45253676 | AE20: 70158116 | AF20: 12346161 | AI20: 6850734.7 | AK20: 1.1946324e+08 | AR20: 3.6525795e+09 | BB20: 79826775 | BC20: No Data | BH20: NO DATA | BL20: NO DATA | BP20: NO DATA | CB20: 79066550 | CC20: 1.2434775e+08 | CL20: NO DATA | CP20: 1.032301e+08 | CQ20: 26309878 | CW20: 73511242 | CX20: 59686794 | DA20: 1.0683579e+08
A21: Actual cost-water produced | C21: 227.97438 | D21: 306.55448 | E21: 69.702458 | F21: 84.849204 | G21: 61.327683 | H21: 90.070285 | L21: 142.09092 | M21: 33.121028 | N21: 25.313901 | O21: 37.321013 | P21: 47.520626 | Q21: 76.807204 | R21: 138.64711 | S21: 26.056807 | T21: 9.5663529 | U21: 16.017727 | V21: 65.085955 | W21: 29.869459 | X21: 17.753528 | Y21: 10.888114 | Z21: 47.602464 | AA21: 71.821017 | AB21: 28.988627 | AC21: 61.139488 | AD21: 21.810866 | AE21: 78.455578 | AF21: 34.832767 | AG21: 22.882953 | AH21: 21.713158 | AI21: 83.2605 | AJ21: 40.186471 | AK21: 37.788923 | AL21: 45.216975 | AP21: 46.04926 | AQ21: 77.641522 | AR21: 37.823793 | AS21: 66.275418 | AT21: 66.38936 | AU21: 78.049252 | AV21: 19.070548 | AW21: 59.802845 | AX21: 48.532077 | AY21: 55.454744 | AZ21: 65.793409 | BA21: 77.39542 | BB21: 49.517713 | BC21: 63.646503 | BD21: 25.749734 | BE21: 50.498657 | BF21: 80.767314 | BG21: 141.893 | BH21: 103.26344 | BI21: 110.29757 | BJ21: 318.50535 | BK21: 118.42833 | BL21: 217.01338 | BM21: 23.137375 | BN21: 382.62299 | BO21: =BO19/BO16 -> 92.302772 | BP21: 73.095537 | BQ21: 31.932546 | BR21: 85.194463 | BS21: 76.444042 | BW21: 23.528128 | BX21: 52.14854 | BY21: 27.128322 | BZ21: 69.276113 | CA21: 58.323866 | CB21: 48.977336 | CC21: 71.853256 | CD21: 38.208902 | CE21: 124.59388 | CF21: 57.677398 | CG21: 29.955349 | CK21: 107.36329 | CL21: 96.067455 | CM21: 54.258444 | CN21: 30.223858 | CO21: 64.26115 | CP21: 83.286262 | CQ21: 54.275394 | CU21: 5.7245575 | CV21: 65.630049 | CW21: 45.103664 | CX21: 40.920134 | CY21: 46.999602 | CZ21: 42.186231 | DA21: 46.580479 | DB21: 69.403332
A22: Actual unit cost- sewage treated | E22: 35.067308 | F22: 19.86298 | P22: 27.909292 | Q22: NO DATA | AC22: 11.87687 | AE22: 292.32548 | AF22: 41.510444 | AI22: 5.4302563 | AK22: 29.754233 | AR22: 45.359281 | BB22: 57.853015 | BC22: No Data | BH22: NO DATA | BL22: NO DATA | BP22: NO DATA | CB22: 79.573352 | CC22: 28.300345 | CL22: NO DATA | CP22: 21.999332 | CQ22: 14.48383 | CW22: 185.60633 | CX22: 40.558013 | DA22: 13.609543
A23: Value of Water sold (in Ksh.) per category
A24: Individual | B24: 18488.9 | C24: 0 | D24: 0 | E24: 73522410 | F24: 1.5101064e+08 | G24: 5092117.4 | H24: 44440.05 | L24: 36876824 | M24: 20025061 | N24: 16861229 | O24: 7786394.9 | P24: 1.6031273e+08 | Q24: 18344917 | R24: 30070880 | S24: 57462831 | T24: 13555082 | U24: 8414365.9 | V24: 54209125 | W24: 19396775 | X24: 8466014.4 | Y24: 3961054.7 | Z24: 15353162 | AA24: 1.3776964e+08 | AB24: 74144825 | AC24: 1.40106e+08 | AD24: 44366639 | AE24: 1.0383424e+08 | AF24: 50701249 | AG24: 35563472 | AH24: 15388491 | AI24: 1523830 | AJ24: 86160436 | AK24: 2.1494393e+08 | AL24: 1356368 | AP24: 70917884 | AQ24: 2.0149155e+08 | AR24: 4.0950422e+08 | AS24: 40450736 | AT24: 29805271 | AU24: 0 | AV24: 86659010 | AW24: 30353412 | AX24: 12042750 | AY24: 32738041 | AZ24: 71373818 | BA24: 25838616 | BB24: 2.2115818e+08 | BC24: 72299666 | BD24: 19767830 | BE24: 2.031948e+08 | BF24: 3.0394807e+08 | BG24: 1497955.3 | BH24: 12309951 | BI24: 7022967.2 | BJ24: 2933434.3 | BK24: 7807824.4 | BL24: 39279779 | BM24: 3047196.8 | BN24: 14186.35 | BO24: 4610180.2 | BP24: 2.0080056e+08 | BQ24: 22202016 | BR24: 3692515.3 | BS24: 29188372 | BW24: 0 | BX24: 1503167.7 | BY24: 3545319 | BZ24: 24314669 | CA24: 13326245 | CB24: 37280976 | CC24: 2.9226675e+08 | CD24: 22681368 | CE24: 56705041 | CF24: 135194.5 | CG24: 10217606 | CK24: 20011917 | CL24: 47893487 | CM24: 20777512 | CN24: 1894884.8 | CO24: 1.0455852e+08 | CP24: 2.6956399e+08 | CQ24: 28543890 | CU24: 1253844.1 | CV24: 36328002 | CW24: 47338910 | CX24: 1.2646976e+08 | CY24: 17102919 | CZ24: 22732432 | DA24: 3.2215111e+08 | DB24: 17126215
A25: Multi-dwelling units | B25: 0 | C25: 0 | D25: 0 | E25: 0 | F25: 0 | G25: 4403161.1 | H25: 74067.7 | L25: 0 | M25: 0 | N25: 0 | O25: 3909376.1 | P25: 0 | Q25: 7678624.5 | R25: 9854667.9 | S25: 0 | T25: 0 | U25: 0 | V25: 0 | W25: 0 | X25: 0 | Y25: 0 | Z25: 5117703.5 | AA25: 0 | AB25: 0 | AC25: 1.2470144e+08 | AD25: 201227.05 | AE25: 19644354 | AF25: 0 | AG25: 2045000.1 | AH25: 0 | AI25: 0 | AJ25: 0 | AK25: 7929790.5 | AL25: 3390.55 | AP25: 0 | AQ25: 0 | AR25: 1.4628397e+08 | AS25: 0 | AT25: 8845359.8 | AU25: 0 | AV25: 0 | AW25: 1866088 | AX25: 3440778.7 | AY25: 0 | AZ25: 0 | BA25: 35177999 | BB25: 81980456 | BC25: 35955451 | BD25: 0 | BE25: 0 | BF25: 0 | BG25: 1597875.7 | BH25: 11111834 | BI25: 393192.61 | BJ25: 2682770.6 | BK25: 14936879 | BL25: 23194413 | BM25: 0 | BN25: 8196.6 | BO25: 3504950.5 | BP25: 86057439 | BQ25: 0 | BR25: 6857451.5 | BS25: 71322465 | BW25: 0 | BX25: 0 | BY25: 0 | BZ25: 0 | CA25: 0 | CB25: 9568550.2 | CC25: 2.4991362e+08 | CD25: 26374560 | CE25: 3279310.8 | CF25: 66592.15 | CG25: 2707124.6 | CK25: 0 | CL25: 0 | CM25: 0 | CN25: 266876.67 | CO25: 0 | CP25: 0 | CQ25: 17248783 | CU25: 0 | CV25: 0 | CW25: 61544690 | CX25: 6813027.6 | CY25: 0 | CZ25: 83409.509 | DA25: 1706298.6 | DB25: 2753280.9
A26: Institutions | B26: 0 | C26: 0 | D26: 0 | E26: 6628106 | F26: 0 | G26: 208819.74 | H26: 85919.9 | L26: 0 | M26: 1544298.3 | N26: 7945165.4 | O26: 1562966.7 | P26: 9875403.2 | Q26: 4639138.5 | R26: 4585285.8 | S26: 5403341.5 | T26: 1186065.1 | U26: 0 | V26: 11754660 | W26: 7758704.8 | X26: 7483.3654 | Y26: 402763.83 | Z26: 3411836.9 | AA26: 6850291.8 | AB26: 2425256.9 | AC26: 36237422 | AD26: 745168.25 | AE26: 33675762 | AF26: 1688591.2 | AG26: 3943954.6 | AH26: 1323559.9 | AI26: 0 | AJ26: 1297138.9 | AK26: 4464327.2 | AL26: 113596.3 | AP26: 1476790.7 | AQ26: 17888995 | AR26: 21055236 | AS26: 0 | AT26: 2125946.7 | AU26: 0 | AV26: 2185471 | AW26: 580924.84 | AX26: 1204275 | AY26: 0 | AZ26: 5775482.8 | BA26: 311284.38 | BB26: 2231363.6 | BC26: 1976746.2 | BD26: 10589903 | BE26: 13245608 | BF26: 12649946 | BG26: 3495269.5 | BH26: 13577122 | BI26: 584881.84 | BJ26: 1732669.1 | BK26: 837178.62 | BL26: 1252829.4 | BM26: 18101.584 | BN26: 18442.35 | BO26: 7754379.3 | BP26: 8256502.7 | BQ26: 0 | BR26: 3260925 | BS26: 392974 | BW26: 0 | BX26: 583632.86 | BY26: 960234.07 | BZ26: 1737306.4 | CA26: 908219.25 | CB26: 281029.63 | CC26: 791458.34 | CD26: 15593298 | CE26: 8547513.7 | CF26: 7789.05 | CG26: 4029602 | CK26: 3147823.2 | CL26: 2630372.4 | CM26: 35945785 | CN26: 133438.33 | CO26: 1165231.9 | CP26: 23590508 | CQ26: 5234768.7 | CU26: 0 | CV26: 372229.84 | CW26: 3377634.6 | CX26: 500202.34 | CY26: 29588618 | CZ26: 1973596.7 | DA26: 16646106 | DB26: 9466406.5
A27: Schools | B27: 0 | C27: 0 | D27: 0 | E27: 5952057.3 | F27: 5606603.5 | G27: 147540.1 | H27: 35551.85 | L27: 7790134.7 | M27: 0 | N27: 8193120.6 | O27: 2830686.9 | P27: 13665285 | Q27: 1988193.3 | R27: 3920850 | S27: 2673085.3 | T27: 1694382.9 | U27: 772633.22 | V27: 0 | W27: 3879365.7 | X27: 147538.71 | Y27: 301828.22 | Z27: 3070642.9 | AA27: 2947328.8 | AB27: 6230170 | AC27: 26490252 | AD27: 748243.58 | AE27: 50513643 | AF27: 0 | AG27: 2048788.8 | AH27: 2727641 | AI27: 70075.8 | AJ27: 7022867.1 | AK27: 5764383.5 | AL27: 169546.5 | AP27: 2215243.6 | AQ27: 8696394 | AR27: 2031389.2 | AS27: 400088.4 | AT27: 1471932.4 | AU27: 0 | AV27: 1280817.8 | AW27: 3788988.7 | AX27: 516090.11 | AY27: 8869099 | AZ27: 4215554 | BA27: 233424.59 | BB27: 2514942.1 | BC27: 557833.66 | BD27: 0 | BE27: 12705388 | BF27: 6474726.5 | BG27: 1797595 | BH27: 7977224.7 | BI27: 408853.5 | BJ27: 1748594.4 | BK27: 2887072.1 | BL27: 498598.63 | BM27: 97713.688 | BN27: 22541.6 | BO27: 4281543.5 | BP27: 5504388.5 | BQ27: 7048268.1 | BR27: 1468773.4 | BS27: 1442000.8 | BW27: 0 | BX27: 659920 | BY27: 590881.97 | BZ27: 1203741.7 | CA27: 500418.77 | CB27: 1474026.8 | CC27: 809073.62 | CD27: 2846788.3 | CE27: 5379589.8 | CF27: 0 | CG27: 3471327 | CK27: 1488623.8 | CL27: 1215686.1 | CM27: 3559299.7 | CN27: 53375.333 | CO27: 6269337.6 | CP27: 4095088.1 | CQ27: 1877309.7 | CU27: 250163.16 | CV27: 2258876.8 | CW27: 9907012.2 | CX27: 17156812 | CY27: 2929822.1 | CZ27: 1695246.9 | DA27: 2702905.3 | DB27: 2240297.2
A28: Commercial customers | B28: 0 | C28: 0 | D28: 0 | E28: 23729291 | F28: 79599887 | G28: 427153.84 | H28: 50366.15 | L28: 8068917.1 | M28: 2333888.6 | N28: 5532888.2 | O28: 877043.8 | P28: 39533920 | Q28: 2419728.7 | R28: 2606377.4 | S28: 4831150.9 | T28: 491375.72 | U28: 0 | V28: 12950455 | W28: 7370752.3 | X28: 4490.0192 | Y28: 0 | Z28: 6823621.9 | AA28: 23699029 | AB28: 3658573.1 | AC28: 45611036 | AD28: 826522.78 | AE28: 58933061 | AF28: 4316444.5 | AG28: 4289674.2 | AH28: 2686955.3 | AI28: 1084050 | AJ28: 24828367 | AK28: 85600892 | AL28: 50863.95 | AP28: 2616545.4 | AQ28: 26278239 | AR28: 1.032914e+08 | AS28: 42738.125 | AT28: 4235807.2 | AU28: 0 | AV28: 150682.25 | AW28: 406719.15 | AX28: 0 | AY28: 36578005 | AZ28: 11845285 | BA28: 13775379 | BB28: 0 | BC28: 4685638.9 | BD28: 2823985 | BE28: 7566299.3 | BF28: 63200671 | BG28: 1398156.4 | BH28: 14427435 | BI28: 0 | BJ28: 1661323.9 | BK28: 0 | BL28: 44608668 | BM28: 383619.93 | BN28: 12294.9 | BO28: 5461665.4 | BP28: 41282513 | BQ28: 0 | BR28: 2877239.2 | BS28: 5020171.9 | BW28: 0 | BX28: 335305.64 | BY28: 2215814.2 | BZ28: 0 | CA28: 3360912.8 | CB28: 13516937 | CC28: 23888769 | CD28: 19496335 | CE28: 15276954 | CF28: 52540.7 | CG28: 3273981.1 | CK28: 1790456.5 | CL28: 1939059.2 | CM28: 2300395.3 | CN28: 266876.67 | CO28: 12474448 | CP28: 1.4358967e+08 | CQ28: 4123544.5 | CU28: 0 | CV28: 347300.77 | CW28: 4422118 | CX28: 19829485 | CY28: 1893560.4 | CZ28: 897937.14 | DA28: 49128097 | DB28: 14199539
A29: Industries | B29: 0 | C29: 0 | D29: 0 | E29: 7558959.4 | F29: 0 | G29: 0 | H29: 0 | L29: 0 | M29: 0 | N29: 5518947.9 | O29: 0 | P29: 0 | Q29: 0 | R29: 10814424 | S29: 0 | T29: 0 | U29: 0 | V29: 0 | W29: 0 | X29: 0 | Y29: 0 | Z29: 0 | AA29: 0 | AB29: 0 | AC29: 0 | AD29: 0 | AE29: 14031408 | AF29: 0 | AG29: 2185994.2 | AH29: 34005.944 | AI29: 0 | AJ29: 0 | AK29: 29125841 | AL29: 0 | AP29: 1744382.8 | AQ29: 2407120.1 | AR29: 6656737.9 | AS29: 0 | AT29: 0 | AU29: 0 | AV29: 0 | AW29: 2722524.5 | AX29: 0 | AY29: 0 | AZ29: 0 | BA29: 0 | BB29: 31576691 | BC29: 0 | BD29: 0 | BE29: 13979136 | BF29: 2384113.8 | BG29: 0 | BH29: 11808594 | BI29: 0 | BJ29: 0 | BK29: 0 | BL29: 17533743 | BM29: 0 | BN29: 0 | BO29: 0 | BP29: 27521702 | BQ29: 0 | BR29: 0 | BS29: 0 | BW29: 0 | BX29: 0 | BY29: 0 | BZ29: 0 | CA29: 0 | CB29: 0 | CC29: 0 | CD29: 126897.63 | CE29: 0 | CF29: 0 | CG29: 0 | CK29: 0 | CL29: 56442.197 | CM29: 0 | CN29: 49718.246 | CO29: 0 | CP29: 953250.7 | CQ29: 3551.8416 | CU29: 0 | CV29: 28341.411 | CW29: 0 | CX29: 0 | CY29: 0 | CZ29: 13106.16 | DA29: 0 | DB29: 1159684.9
A30: Kiosks | B30: 0 | C30: 0 | D30: 0 | E30: 249758.95 | F30: 433576.45 | G30: 5185.5475 | H30: 5925.15 | L30: 363326.48 | M30: 0 | N30: 0 | O30: 267740.95 | P30: 1834195 | Q30: 8357401.9 | R30: 19192629 | S30: 14942.432 | T30: 16942.011 | U30: 0 | V30: 0 | W30: 387899.43 | X30: 11973.385 | Y30: 71238.335 | Z30: 341194.08 | AA30: 2659072.6 | AB30: 113273.62 | AC30: 844164.98 | AD30: 3380.6843 | AE30: 0 | AF30: 358425.88 | AG30: 0 | AH30: 3400.5944 | AI30: 2480.45 | AJ30: 351792.37 | AK30: 361262.89 | AL30: 1694.8 | AP30: 5571680.2 | AQ30: 3098595.5 | AR30: 58388793 | AS30: 0 | AT30: 9385890 | AU30: 0 | AV30: 159227.62 | AW30: 236580.05 | AX30: 0 | AY30: 2450988.8 | AZ30: 1128398.4 | BA30: 155564.79 | BB30: 2979449.8 | BC30: 680540.69 | BD30: 703357.89 | BE30: 11083829 | BF30: 28288423 | BG30: 199719.27 | BH30: 2148148.9 | BI30: 1591667.9 | BJ30: 2835653.1 | BK30: 2534103.1 | BL30: 4847589.6 | BM30: 72377.281 | BN30: 3152.1 | BO30: 1935135.8 | BP30: 48712142 | BQ30: 0 | BR30: 575483.78 | BS30: 1859862.7 | BW30: 0 | BX30: 0 | BY30: 73870.42 | BZ30: 80221.739 | CA30: 645878.5 | CB30: 4016223.5 | CC30: 394909.86 | CD30: 1203902.7 | CE30: 3774197.7 | CF30: 1102.95 | CG30: 109619.21 | CK30: 362277.44 | CL30: 945614.31 | CM30: 287406.98 | CN30: 26717.89 | CO30: 587711.96 | CP30: 33834000 | CQ30: 16144734 | CU30: 0 | CV30: 1371762.2 | CW30: 11999168 | CX30: 3019756.4 | CY30: 236577.81 | CZ30: 12917717 | DA30: 20832883 | DB30: 386538.11
A31: Bulk | B31: 0 | C31: 0 | D31: 0 | E31: 15523760 | F31: 0 | G31: 0 | H31: 0 | L31: 0 | M31: 0 | N31: 0 | O31: 0 | P31: 0 | Q31: 1764740.2 | R31: 0 | S31: 0 | T31: 0 | U31: 0 | V31: 101281.07 | W31: 0 | X31: 0 | Y31: 0 | Z31: 0 | AA31: 0 | AB31: 0 | AC31: 0 | AD31: 0 | AE31: 0 | AF31: 0 | AG31: 4701245.1 | AH31: 0 | AI31: 0 | AJ31: 0 | AK31: 0 | AL31: 0 | AP31: 0 | AQ31: 278577.78 | AR31: 1.1054998e+08 | AS31: 75117.372 | AT31: 0 | AU31: 0 | AV31: 0 | AW31: 1363265.7 | AX31: 0 | AY31: 0 | AZ31: 5663101.5 | BA31: 2334787.6 | BB31: 0 | BC31: 15746473 | BD31: 1414590.1 | BE31: 8231531.3 | BF31: 159643.87 | BG31: 0 | BH31: 0 | BI31: 0 | BJ31: 0 | BK31: 3519612 | BL31: 0 | BM31: 0 | BN31: 0 | BO31: 0 | BP31: 7514684.1 | BQ31: 5286201.1 | BR31: 0 | BS31: 0 | BW31: 0 | BX31: 869060.08 | BY31: 0 | BZ31: 0 | CA31: 54241.196 | CB31: 414374.69 | CC31: 0 | CD31: 58025161 | CE31: 3403530.9 | CF31: 0 | CG31: 0 | CK31: 0 | CL31: 0 | CM31: 0 | CN31: 0 | CO31: 8259.0708 | CP31: 56385511 | CQ31: 0 | CU31: 0 | CV31: 0 | CW31: 0 | CX31: 321991.7 | CY31: 0 | CZ31: 809608.23 | DA31: 0 | DB31: 0
A32: Others | B32: 0 | C32: 0 | D32: 0 | E32: 1438072.5 | F32: 0 | G32: 0 | H32: 0 | L32: 0 | M32: 0 | N32: 0 | O32: 0 | P32: 0 | Q32: 0 | R32: 2509598.7 | S32: 0 | T32: 0 | U32: 0 | V32: 0 | W32: 0 | X32: 0 | Y32: 0 | Z32: 0 | AA32: 0 | AB32: 0 | AC32: 0 | AD32: 0 | AE32: 0 | AF32: 0 | AG32: 0 | AH32: 0 | AI32: 0 | AJ32: 0 | AK32: 0 | AL32: 0 | AP32: 0 | AQ32: 0 | AR32: 18818470 | AS32: 0 | AT32: 6266516.9 | AU32: 0 | AV32: 0 | AW32: 0 | AX32: 0 | AY32: 0 | AZ32: 0 | BA32: 0 | BB32: 0 | BC32: 0 | BD32: 0 | BE32: 37101.75 | BF32: 0 | BG32: 0 | BH32: 0 | BI32: 0 | BJ32: 0 | BK32: 3519612 | BL32: 0 | BM32: 0 | BN32: 0 | BO32: 0 | BP32: 0 | BQ32: 0 | BR32: 0 | BS32: 0 | BW32: 0 | BX32: 0 | BY32: 0 | BZ32: 0 | CA32: 0 | CB32: 0 | CC32: 0 | CD32: 0 | CE32: 1524156.9 | CF32: 0 | CG32: 0 | CK32: 0 | CL32: 3527.6373 | CM32: 0 | CN32: 0 | CO32: 0 | CP32: 25715349 | CQ32: 0 | CU32: 0 | CV32: 0 | CW32: 0 | CX32: 0 | CY32: 0 | CZ32: 0 | DA32: 0 | DB32: 0
A33: Total Value of water sold | B33: =SUM(B24:B32) -> 18488.9 | C33: =SUM(C24:C32) -> 0 | D33: =SUM(D24:D32) -> 0 | E33: =SUM(E24:E32) -> 1.3460242e+08 | F33: =SUM(F24:F32) -> 2.3665071e+08 | G33: =SUM(G24:G32) -> 10283978 | H33: =SUM(H24:H32) -> 296270.8 | L33: =SUM(L24:L32) -> 53099202 | M33: =SUM(M24:M32) -> 23903247 | N33: =SUM(N24:N32) -> 44051351 | O33: =SUM(O24:O32) -> 17234209 | P33: =SUM(P24:P32) -> 2.2522154e+08 | Q33: =SUM(Q24:Q32) -> 45192744 | R33: =SUM(R24:R32) -> 83554713 | S33: =SUM(S24:S32) -> 70385351 | ... AL33: =SUM(AL24:AL32) -> 1695460.1 | AP33: =SUM(AP24:AP32) -> 84542527 | AQ33: =SUM(AQ24:AQ32) -> 2.6013947e+08 | AR33: =SUM(AR24:AR32) -> 8.7658018e+08 | AS33: =SUM(AS24:AS32) -> 40968680 | AT33: =SUM(AT24:AT32) -> 62136724 | AU33: =SUM(AU24:AU32) -> 0 | AV33: =SUM(AV24:AV32) -> 90435208 | AW33: =SUM(AW24:AW32) -> 41318503 | ... BS33: =SUM(BS24:BS32) -> 1.0922585e+08 | BW33: =SUM(BW24:BW32) -> 0 | BX33: =SUM(BX24:BX32) -> 3951086.3 | BY33: =SUM(BY24:BY32) -> 7386119.6 | BZ33: =SUM(BZ24:BZ32) -> 27335939 | CA33: =SUM(CA24:CA32) -> 18795916 | CB33: =SUM(CB24:CB32) -> 66552118 | CC33: =SUM(CC24:CC32) -> 5.6806458e+08 | CD33: =SUM(CD24:CD32) -> 1.4634831e+08 | ... CG33: =SUM(CG24:CG32) -> 23809260 | CK33: =SUM(CK24:CK32) -> 26801098 | CL33: =SUM(CL24:CL32) -> 54684189 | CM33: =SUM(CM24:CM32) -> 62870399 | CN33: =SUM(CN24:CN32) -> 2691887.9 | CO33: =SUM(CO24:CO32) -> 1.2506351e+08 | CP33: =SUM(CP24:CP32) -> 5.5772737e+08 | CQ33: =SUM(CQ24:CQ32) -> 73176582 | CU33: =SUM(CU24:CU32) -> 1504007.3 | CV33: =SUM(CV24:CV32) -> 40706513 | CW33: =SUM(CW24:CW32) -> 1.3858953e+08 | CX33: =SUM(CX24:CX32) -> 1.7411104e+08 | CY33: =SUM(CY24:CY32) -> 51751497 | CZ33: =SUM(CZ24:CZ32) -> 41123054 | DA33: =SUM(DA24:DA32) -> 4.131674e+08 | DB33: =SUM(DB24:DB32) -> 47331962
A37: Water Sold in cubic meters
A38: Individual | C38: =C24/$C$21 -> 0 | D38: =D24/$D$21 -> 0 | E38: =E24/$E$21 -> 1054803.7 | F38: =F24/$F$21 -> 1779753.2 | G38: =G24/$G$21 -> 83031.304 | H38: =H24/$H$21 -> 493.39302 | I38: =SUM(B38:H38) -> 2918081.6 | L38: =L24/$L$21 -> 259529.77 | M38: =M24/$M$21 -> 604602.62 | N38: =N24/$N$21 -> 666085.77 | O38: =O24/$O$21 -> 208633 | P38: =P24/$P$21 -> 3373540 | Q38: =Q24/$Q$21 -> 238843.71 | R38: =R24/$R$21 -> 216887.89 | S38: =S24/$S$21 -> 2205290.6 | T38: =T24/$T$21 -> 1416954 | U38: =U24/$U$21 -> 525315.86 | V38: =V24/$V$21 -> 832885.14 | W38: =W24/$W$21 -> 649384.89 | X38: =X24/$X$21 -> 476863.77 | Y38: =Y24/$Y$21 -> 363796.2 | Z38: =Z24/$Z$21 -> 322528.73 | AA38: =AA24/$AA$21 -> 1918235.8 | AB38: =AB24/$AB$21 -> 2557721.2 | AC38: =AC24/$AC$21 -> 2291579.5 | AD38: =AD24/$AD$21 -> 2034153 | AE38: =AE24/$AE$21 -> 1323478.1 | AF38: =AF24/$AF$21 -> 1455561.9 | AG38: =AG24/$AG$21 -> 1554147 | AH38: =AH24/$AH$21 -> 708717.3 | AI38: =AI24/$AI$21 -> 18301.956 | AJ38: =AJ24/$AJ$21 -> 2144016 | AK38: =AK24/$AK$21 -> 5688014.1 | AL38: =AL24/$AL$21 -> 29996.876 | AM38: =SUM(L38:AL38) -> 34085065 | AP38: =AP24/$AP$21 -> 1540044 | AQ38: =AQ24/$AQ$21 -> 2595152 | AR38: =AR24/$AR$21 -> 10826630 | AS38: =AS24/$AS$21 -> 610342.98 | AT38: =AT24/$AT$21 -> 448946.49 | AU38: =AU24/$AU$21 -> 0 | AV38: =AV24/$AV$21 -> 4544127.9 | AW38: =AW24/$AW$21 -> 507558 | AX38: =AX24/$AX$21 -> 248140 | AY38: =AY24/$AY$21 -> 590356 | AZ38: =AZ24/$AZ$21 -> 1084817.1 | BA38: =BA24/$BA$21 -> 333852 | BB38: =BB24/$BB$21 -> 4466243.8 | BC38: =BC24/$BC$21 -> 1135956.6 | BD38: =BD24/$BD$21 -> 767690.66 | BE38: =BE24/$BE$21 -> 4023766.4 | BF38: =BF24/$BF$21 -> 3763255.8 | BG38: =BG24/$BG$21 -> 10556.936 | BH38: =BH24/$BH$21 -> 119209.19 | BI38: =BI24/$BI$21 -> 63672.909 | BJ38: =BJ24/$BJ$21 -> 9210 | BK38: =BK24/$BK$21 -> 65928.689 | BL38: =BL24/$BL$21 -> 181001.65 | BM38: =BM24/$BM$21 -> 131700.2 | BN38: =BN24/$BN$21 -> 37.076575 | BO38: =BO24/$BO$21 -> 49946.281 | BP38: =BP24/$BP$21 -> 2747097.4 | BQ38: =BQ24/$BQ$21 -> 695278.61 | BR38: =BR24/$BR$21 -> 43342.199 | BS38: =BS24/$BS$21 -> 381826.64 | BT38: =SUM(AP38:BS38) -> 41985688 | BW38: =BW24/$BW$21 -> 0 | BX38: =BX24/$BX$21 -> 28824.732 | BY38: =BY24/$BY$21 -> 130687 | BZ38: =BZ24/$BZ$21 -> 350982 | CA38: =CA24/$CA$21 -> 228487 | CB38: =CB24/$CB$21 -> 761188.33 | CC38: =CC24/$CC$21 -> 4067550.5 | CD38: =CD24/$CD$21 -> 593614.74 | CE38: =CE24/$CE$21 -> 455119 | CF38: =CF24/$CF$21 -> 2343.9771 | CG38: =CG24/$CG$21 -> 341094.55 | CH38: =SUM(BW38:CG38) -> 6959891.9 | CK38: =CK24/$CK$21 -> 186394.41 | CL38: =CL24/$CL$21 -> 498540.19 | CM38: =CM24/$CM$21 -> 382936 | CN38: =CN24/$CN$21 -> 62695 | CO38: =CO24/$CO$21 -> 1627087.6 | CP38: =CP24/$CP$21 -> 3236596.1 | CQ38: =CQ24/$CQ$21 -> 525908.49 | CR38: =SUM(CK38:CQ38) -> 6520157.8 | CU38: =CU24/$CU$21 -> 219029 | CV38: =CV24/$CV$21 -> 553526.96 | CW38: =CW24/$CW$21 -> 1049558 | CX38: =CX24/$CX$21 -> 3090648.8 | CY38: =CY24/$CY$21 -> 363894.97 | CZ38: =CZ24/$CZ$21 -> 538859.04 | DA38: =DA24/$DA$21 -> 6916011.2 | DB38: =DB24/$DB$21 -> 246763.59 | DC38: =SUM(CU38:DB38) -> 12978292 | DO38: =SUM(CY38:DM38) -> 21043820
A39: Multi-dwelling units | C39: =C25/$C$21 -> 0 | D39: =D25/$D$21 -> 0 | E39: =E25/$E$21 -> 0 | F39: =F25/$F$21 -> 0 | G39: =G25/$G$21 -> 71797.285 | H39: =H25/$H$21 -> 822.33224 | I39: =SUM(B39:H39) -> 72619.617 | L39: =L25/$L$21 -> 0 | M39: =M25/$M$21 -> 0 | N39: =N25/$N$21 -> 0 | O39: =O25/$O$21 -> 104750 | P39: =P25/$P$21 -> 0 | Q39: =Q25/$Q$21 -> 99972.713 | R39: =R25/$R$21 -> 71077.338 | S39: =S25/$S$21 -> 0 | T39: =T25/$T$21 -> 0 | U39: =U25/$U$21 -> 0 | V39: =V25/$V$21 -> 0 | W39: =W25/$W$21 -> 0 | X39: =X25/$X$21 -> 0 | Y39: =Y25/$Y$21 -> 0 | Z39: =Z25/$Z$21 -> 107509.21 | AA39: =AA25/$AA$21 -> 0 | AB39: =AB25/$AB$21 -> 0 | AC39: =AC25/$AC$21 -> 2039621.9 | AD39: =AD25/$AD$21 -> 9226 | AE39: =AE25/$AE$21 -> 250388.24 | AF39: =AF25/$AF$21 -> 0 | AG39: =AG25/$AG$21 -> 89367.843 | AH39: =AH25/$AH$21 -> 0 | AI39: =AI25/$AI$21 -> 0 | AJ39: =AJ25/$AJ$21 -> 0 | AK39: =AK25/$AK$21 -> 209844.31 | AL39: =AL25/$AL$21 -> 74.984007 | AM39: =SUM(L39:AL39) -> 2981832.5 | AP39: =AP25/$AP$21 -> 0 | AQ39: =AQ25/$AQ$21 -> 0 | AR39: =AR25/$AR$21 -> 3867511.8 | AS39: =AS25/$AS$21 -> 0 | AT39: =AT25/$AT$21 -> 133234.6 | AU39: =AU25/$AU$21 -> 0 | AV39: =AV25/$AV$21 -> 0 | AW39: =AW25/$AW$21 -> 31204 | AX39: =AX25/$AX$21 -> 70897 | AY39: =AY25/$AY$21 -> 0 | AZ39: =AZ25/$AZ$21 -> 0 | BA39: =BA25/$BA$21 -> 454523 | BB39: =BB25/$BB$21 -> 1655578.4 | BC39: =BC25/$BC$21 -> 564924.22 | BD39: =BD25/$BD$21 -> 0 | BE39: =BE25/$BE$21 -> 0 | BF39: =BF25/$BF$21 -> 0 | BG39: =BG25/$BG$21 -> 11261.131 | BH39: =BH25/$BH$21 -> 107606.66 | BI39: =BI25/$BI$21 -> 3564.8348 | BJ39: =BJ25/$BJ$21 -> 8423 | BK39: =BK25/$BK$21 -> 126125.9 | BL39: =BL25/$BL$21 -> 106880.11 | BM39: =BM25/$BM$21 -> 0 | BN39: =BN25/$BN$21 -> 21.422132 | BO39: =BO25/$BO$21 -> 37972.321 | BP39: =BP25/$BP$21 -> 1177328.2 | BQ39: =BQ25/$BQ$21 -> 0 | BR39: =BR25/$BR$21 -> 80491.751 | BS39: =BS25/$BS$21 -> 933002.27 | BT39: =SUM(AP39:BS39) -> 9370550.7 | BW39: =BW25/$BW$21 -> 0 | BX39: =BX25/$BX$21 -> 0 | BY39: =BY25/$BY$21 -> 0 | BZ39: =BZ25/$BZ$21 -> 0 | CA39: =CA25/$CA$21 -> 0 | CB39: =CB25/$CB$21 -> 195366.9 | CC39: =CC25/$CC$21 -> 3478111.3 | CD39: =CD25/$CD$21 -> 690272.65 | CE39: =CE25/$CE$21 -> 26320 | CF39: =CF25/$CF$21 -> 1154.5623 | CG39: =CG25/$CG$21 -> 90371.993 | CH39: =SUM(BW39:CG39) -> 4481597.4 | CK39: =CK25/$CK$21 -> 0 | CL39: =CL25/$CL$21 -> 0 | CM39: =CM25/$CM$21 -> 0 | CN39: =CN25/$CN$21 -> 8830 | CO39: =CO25/$CO$21 -> 0 | CP39: =CP25/$CP$21 -> 0 | CQ39: =CQ25/$CQ$21 -> 317801.16 | CR39: =SUM(CK39:CQ39) -> 326631.16 | CU39: =CU25/$CU$21 -> 0 | CV39: =CV25/$CV$21 -> 0 | CW39: =CW25/$CW$21 -> 1364516.4 | CX39: =CX25/$CX$21 -> 166495.73 | CY39: =CY25/$CY$21 -> 0 | CZ39: =CZ25/$CZ$21 -> 1977.1737 | DA39: =DA25/$DA$21 -> 36631.195 | DB39: =DB25/$DB$21 -> 39670.731 | DC39: =SUM(CU39:DB39) -> 1609291.2 | DO39: =SUM(CY39:DM39) -> 1687570.3
A40: Institutions | C40: =C26/$C$21 -> 0 | D40: =D26/$D$21 -> 0 | E40: =E26/$E$21 -> 95091.425 | F40: =F26/$F$21 -> 0 | G40: =G26/$G$21 -> 3404.9834 | H40: =H26/$H$21 -> 953.92059 | I40: =SUM(B40:H40) -> 99450.329 | L40: =L26/$L$21 -> 0 | M40: =M26/$M$21 -> 46625.916 | N40: =N26/$N$21 -> 313865.71 | O40: =O26/$O$21 -> 41879 | P40: =P26/$P$21 -> 207812.98 | Q40: =Q26/$Q$21 -> 60399.783 | R40: =R26/$R$21 -> 33071.628 | S40: =S26/$S$21 -> 207367.75 | T40: =T26/$T$21 -> 123983 | U40: =U26/$U$21 -> 0 | V40: =V26/$V$21 -> 180602.09 | W40: =W26/$W$21 -> 259753.78 | X40: =X26/$X$21 -> 421.51426 | Y40: =Y26/$Y$21 -> 36991.146 | Z40: =Z26/$Z$21 -> 71673.537 | AA40: =AA26/$AA$21 -> 95380.045 | AB40: =AB26/$AB$21 -> 83662.36 | AC40: =AC26/$AC$21 -> 592700.77 | AD40: =AD26/$AD$21 -> 34165 | AE40: =AE26/$AE$21 -> 429233.49 | AF40: =AF26/$AF$21 -> 48477.09 | AG40: =AG26/$AG$21 -> 172353.39 | AH40: =AH26/$AH$21 -> 60956.581 | AI40: =AI26/$AI$21 -> 0 | AJ40: =AJ26/$AJ$21 -> 32278 | AK40: =AK26/$AK$21 -> 118138.51 | AL40: =AL26/$AL$21 -> 2512.249 | AM40: =SUM(L40:AL40) -> 3254305.3 | AP40: =AP26/$AP$21 -> 32069.803 | AQ40: =AQ26/$AQ$21 -> 230405 | AR40: =AR26/$AR$21 -> 556666.44 | AS40: =AS26/$AS$21 -> 0 | AT40: =AT26/$AT$21 -> 32022.401 | AU40: =AU26/$AU$21 -> 0 | AV40: =AV26/$AV$21 -> 114599.28 | AW40: =AW26/$AW$21 -> 9714 | AX40: =AX26/$AX$21 -> 24814 | AY40: =AY26/$AY$21 -> 0 | AZ40: =AZ26/$AZ$21 -> 87782.088 | BA40: =BA26/$BA$21 -> 4022 | BB40: =BB26/$BB$21 -> 45061.927 | BC40: =BC26/$BC$21 -> 31058.207 | BD40: =BD26/$BD$21 -> 411262.63 | BE40: =BE26/$BE$21 -> 262296.25 | BF40: =BF26/$BF$21 -> 156622.1 | BG40: =BG26/$BG$21 -> 24633.136 | BH40: =BH26/$BH$21 -> 131480.43 | BI40: =BI26/$BI$21 -> 5302.7627 | BJ40: =BJ26/$BJ$21 -> 5440 | BK40: =BK26/$BK$21 -> 7069.074 | BL40: =BL26/$BL$21 -> 5773.0517 | BM40: =BM26/$BM$21 -> 782.35255 | BN40: =BN26/$BN$21 -> 48.199796 | BO40: =BO26/$BO$21 -> 84010.253 | BP40: =BP26/$BP$21 -> 112954.95 | BQ40: =BQ26/$BQ$21 -> 0 | BR40: =BR26/$BR$21 -> 38276.255 | BS40: =BS26/$BS$21 -> 5140.6754 | BT40: =SUM(AP40:BS40) -> 2419307.3 | BW40: =BW26/$BW$21 -> 0 | BX40: =BX26/$BX$21 -> 11191.739 | BY40: =BY26/$BY$21 -> 35396 | BZ40: =BZ26/$BZ$21 -> 25078 | CA40: =CA26/$CA$21 -> 15572 | CB40: =CB26/$CB$21 -> 5737.9526 | CC40: =CC26/$CC$21 -> 11014.927 | CD40: =CD26/$CD$21 -> 408106.42 | CE40: =CE26/$CE$21 -> 68603 | CF40: =CF26/$CF$21 -> 135.0451 | CG40: =CG26/$CG$21 -> 134520.28 | CH40: =SUM(BW40:CG40) -> 715355.36 | CK40: =CK26/$CK$21 -> 29319.363 | CL40: =CL26/$CL$21 -> 27380.474 | CM40: =CM26/$CM$21 -> 662492 | CN40: =CN26/$CN$21 -> 4415 | CO40: =CO26/$CO$21 -> 18132.758 | CP40: =CP26/$CP$21 -> 283246.09 | CQ40: =CQ26/$CQ$21 -> 96448.285 | CR40: =SUM(CK40:CQ40) -> 1121434 | CU40: =CU26/$CU$21 -> 0 | CV40: =CV26/$CV$21 -> 5671.6374 | CW40: =CW26/$CW$21 -> 74886.036 | CX40: =CX26/$CX$21 -> 12223.868 | CY40: =CY26/$CY$21 -> 629550.39 | CZ40: =CZ26/$CZ$21 -> 46782.959 | DA40: =DA26/$DA$21 -> 357362.28 | DB40: =DB26/$DB$21 -> 136397 | DC40: =SUM(CU40:DB40) -> 1262874.2 | DO40: =SUM(CY40:DM40) -> 2432966.8
A41: Schools | C41: =C27/$C$21 -> 0 | D41: =D27/$D$21 -> 0 | E41: =E27/$E$21 -> 85392.359 | F41: =F27/$F$21 -> 66077.267 | G41: =G27/$G$21 -> 2405.7667 | H41: =H27/$H$21 -> 394.71231 | I41: =SUM(B41:H41) -> 154270.1 | L41: =L27/$L$21 -> 54825 | M41: =M27/$M$21 -> 0 | N41: =N27/$N$21 -> 323660.93 | O41: =O27/$O$21 -> 75847 | P41: =P27/$P$21 -> 287565.34 | Q41: =Q27/$Q$21 -> 25885.505 | R41: =R27/$R$21 -> 28279.348 | S41: =S27/$S$21 -> 102586.83 | T41: =T27/$T$21 -> 177119 | U41: =U27/$U$21 -> 48236.135 | V41: =V27/$V$21 -> 0 | W41: =W27/$W$21 -> 129877.33 | X41: =X27/$X$21 -> 8310.3878 | Y41: =Y27/$Y$21 -> 27720.89 | Z41: =Z27/$Z$21 -> 64505.965 | AA41: =AA27/$AA$21 -> 41037.135 | AB41: =AB27/$AB$21 -> 214917.74 | AC41: =AC27/$AC$21 -> 433275.67 | AD41: =AD27/$AD$21 -> 34306 | AE41: =AE27/$AE$21 -> 643850.24 | AF41: =AF27/$AF$21 -> 0 | AG41: =AG27/$AG$21 -> 89533.412 | AH41: =AH27/$AH$21 -> 125621.57 | AI41: =AI27/$AI$21 -> 841.6452 | AJ41: =AJ27/$AJ$21 -> 174757 | AK41: =AK27/$AK$21 -> 152541.62 | AL41: =AL27/$AL$21 -> 3749.6205 | AM41: =SUM(L41:AL41) -> 3268851.3 | AP41: =AP27/$AP$21 -> 48105.954 | AQ41: =AQ27/$AQ$21 -> 112007 | AR41: =AR27/$AR$21 -> 53706.65 | AS41: =AS27/$AS$21 -> 6036.7541 | AT41: =AT27/$AT$21 -> 22171.209 | AU41: =AU27/$AU$21 -> 0 | AV41: =AV27/$AV$21 -> 67162.085 | AW41: =AW27/$AW$21 -> 63358 | AX41: =AX27/$AX$21 -> 10634 | AY41: =AY27/$AY$21 -> 159934 | AZ41: =AZ27/$AZ$21 -> 64072.587 | BA41: =BA27/$BA$21 -> 3016 | BB41: =BB27/$BB$21 -> 50788.738 | BC41: =BC27/$BC$21 -> 8764.561 | BD41: =BD27/$BD$21 -> 0 | BE41: =BE27/$BE$21 -> 251598.53 | BF41: =BF27/$BF$21 -> 80165.183 | BG41: =BG27/$BG$21 -> 12668.666 | BH41: =BH27/$BH$21 -> 77251.201 | BI41: =BI27/$BI$21 -> 3706.8224 | BJ41: =BJ27/$BJ$21 -> 5490 | BK41: =BK27/$BK$21 -> 24378.222 | BL41: =BL27/$BL$21 -> 2297.5479 | BM41: =BM27/$BM$21 -> 4223.1968 | BN41: =BN27/$BN$21 -> 58.913345 | BO41: =BO27/$BO$21 -> 46385.861 | BP41: =BP27/$BP$21 -> 75304.029 | BQ41: =BQ27/$BQ$21 -> 220723.65 | BR41: =BR27/$BR$21 -> 17240.245 | BS41: =BS27/$BS$21 -> 18863.482 | BT41: =SUM(AP41:BS41) -> 1510113.1 | BW41: =BW27/$BW$21 -> 0 | BX41: =BX27/$BX$21 -> 12654.621 | BY41: =BY27/$BY$21 -> 21781 | BZ41: =BZ27/$BZ$21 -> 17376 | CA41: =CA27/$CA$21 -> 8580 | CB41: =CB27/$CB$21 -> 30096.099 | CC41: =CC27/$CC$21 -> 11260.083 | CD41: =CD27/$CD$21 -> 74505.892 | CE41: =CE27/$CE$21 -> 43177 | CF41: =CF27/$CF$21 -> 0 | CG41: =CG27/$CG$21 -> 115883.38 | CH41: =SUM(BW41:CG41) -> 335314.07 | CK41: =CK27/$CK$21 -> 13865.297 | CL41: =CL27/$CL$21 -> 12654.505 | CM41: =CM27/$CM$21 -> 65599 | CN41: =CN27/$CN$21 -> 1766 | CO41: =CO27/$CO$21 -> 97560.31 | CP41: =CP27/$CP$21 -> 49168.83 | CQ41: =CQ27/$CQ$21 -> 34588.597 | CR41: =SUM(CK41:CQ41) -> 275202.54 | CU41: =CU27/$CU$21 -> 43700 | CV41: =CV27/$CV$21 -> 34418.332 | CW41: =CW27/$CW$21 -> 219649.83 | CX41: =CX27/$CX$21 -> 419275.55 | CY41: =CY27/$CY$21 -> 62337.169 | CZ41: =CZ27/$CZ$21 -> 40184.838 | DA41: =DA27/$DA$21 -> 58026.568 | DB41: =DB27/$DB$21 -> 32279.39 | DC41: =SUM(CU41:DB41) -> 909871.68 | DO41: =SUM(CY41:DM41) -> 1102699.6
A42: Commercial customers | C42: =C28/$C$21 -> 0 | D42: =D28/$D$21 -> 0 | E42: =E28/$E$21 -> 340436.94 | F42: =F28/$F$21 -> 938133.57 | G42: =G28/$G$21 -> 6965.1064 | H42: =H28/$H$21 -> 559.18719 | I42: =SUM(B42:H42) -> 1286094.8 | L42: =L28/$L$21 -> 56787 | M42: =M28/$M$21 -> 70465.464 | N42: =N28/$N$21 -> 218571.15 | O42: =O28/$O$21 -> 23500 | P42: =P28/$P$21 -> 831931.79 | Q42: =Q28/$Q$21 -> 31503.929 | R42: =R28/$R$21 -> 18798.641 | S42: =S28/$S$21 -> 185408.4 | T42: =T28/$T$21 -> 51365 | U42: =U28/$U$21 -> 0 | V42: =V28/$V$21 -> 198974.65 | W42: =W28/$W$21 -> 246765.51 | X42: =X28/$X$21 -> 252.90856 | Y42: =Y28/$Y$21 -> 0 | Z42: =Z28/$Z$21 -> 143345.98 | AA42: =AA28/$AA$21 -> 329973.45 | AB42: =AB28/$AB$21 -> 126207.19 | AC42: =AC28/$AC$21 -> 746015.98 | AD42: =AD28/$AD$21 -> 37895 | AE42: =AE28/$AE$21 -> 751164.71 | AF42: =AF28/$AF$21 -> 123919.08 | AG42: =AG28/$AG$21 -> 187461.57 | AH42: =AH28/$AH$21 -> 123747.79 | AI42: =AI28/$AI$21 -> 13019.979 | AJ42: =AJ28/$AJ$21 -> 617829 | AK42: =AK28/$AK$21 -> 2265237.7 | AL42: =AL28/$AL$21 -> 1124.8862 | AM42: =SUM(L42:AL42) -> 7401266.7 | AP42: =AP28/$AP$21 -> 56820.574 | AQ42: =AQ28/$AQ$21 -> 338456 | AR42: =AR28/$AR$21 -> 2730857.8 | AS42: =AS28/$AS$21 -> 644.85636 | AT42: =AT28/$AT$21 -> 63802.501 | AU42: =AU28/$AU$21 -> 0 | AV42: =AV28/$AV$21 -> 7901.3066 | AW42: =AW28/$AW$21 -> 6801 | AX42: =AX28/$AX$21 -> 0 | AY42: =AY28/$AY$21 -> 659601 | AZ42: =AZ28/$AZ$21 -> 180037.57 | BA42: =BA28/$BA$21 -> 177987 | BB42: =BB28/$BB$21 -> 0 | BC42: =BC28/$BC$21 -> 73619.739 | BD42: =BD28/$BD$21 -> 109670.46 | BE42: =BE28/$BE$21 -> 149831.69 | BF42: =BF28/$BF$21 -> 782503.07 | BG42: =BG28/$BG$21 -> 9853.597 | BH42: =BH28/$BH$21 -> 139714.84 | BI42: =BI28/$BI$21 -> 0 | BJ42: =BJ28/$BJ$21 -> 5216 | BK42: =BK28/$BK$21 -> 0 | BL42: =BL28/$BL$21 -> 205557.22 | BM42: =BM28/$BM$21 -> 16580.097 | BN42: =BN28/$BN$21 -> 32.133197 | BO42: =BO28/$BO$21 -> 59171.195 | BP42: =BP28/$BP$21 -> 564774.75 | BQ42: =BQ28/$BQ$21 -> 0 | BR42: =BR28/$BR$21 -> 33772.608 | BS42: =BS28/$BS$21 -> 65671.199 | BT42: =SUM(AP42:BS42) -> 6438878.2 | BW42: =BW28/$BW$21 -> 0 | BX42: =BX28/$BX$21 -> 6429.8184 | BY42: =BY28/$BY$21 -> 81679 | BZ42: =BZ28/$BZ$21 -> 0 | CA42: =CA28/$CA$21 -> 57625 | CB42: =CB28/$CB$21 -> 275983.51 | CC42: =CC28/$CC$21 -> 332466.06 | CD42: =CD28/$CD$21 -> 510256.34 | CE42: =CE28/$CE$21 -> 122614 | CF42: =CF28/$CF$21 -> 910.94089 | CG42: =CG28/$CG$21 -> 109295.38 | CH42: =SUM(BW42:CG42) -> 1497260 | CK42: =CK28/$CK$21 -> 16676.618 | CL42: =CL28/$CL$21 -> 20184.351 | CM42: =CM28/$CM$21 -> 42397 | CN42: =CN28/$CN$21 -> 8830 | CO42: =CO28/$CO$21 -> 194121.14 | CP42: =CP28/$CP$21 -> 1724049.9 | CQ42: =CQ28/$CQ$21 -> 75974.475 | CR42: =SUM(CK42:CQ42) -> 2082233.5 | CU42: =CU28/$CU$21 -> 0 | CV42: =CV28/$CV$21 -> 5291.7951 | CW42: =CW28/$CW$21 -> 98043.431 | CX42: =CX28/$CX$21 -> 484589.92 | CY42: =CY28/$CY$21 -> 40288.86 | CZ42: =CZ28/$CZ$21 -> 21285.076 | DA42: =DA28/$DA$21 -> 1054692.8 | DB42: =DB28/$DB$21 -> 204594.49 | DC42: =SUM(CU42:DB42) -> 1908786.4 | DO42: =SUM(CY42:DM42) -> 3229647.7
A43: Industries | C43: =C29/$C$21 -> 0 | D43: =D29/$D$21 -> 0 | E43: =E29/$E$21 -> 108446.1 | F43: =F29/$F$21 -> 0 | G43: =G29/$G$21 -> 0 | H43: =H29/$H$21 -> 0 | I43: =SUM(B43:H43) -> 108446.1 | L43: =L29/$L$21 -> 0 | M43: =M29/$M$21 -> 0 | N43: =N29/$N$21 -> 218020.45 | O43: =O29/$O$21 -> 0 | P43: =P29/$P$21 -> 0 | Q43: =Q29/$Q$21 -> 0 | R43: =R29/$R$21 -> 77999.632 | S43: =S29/$S$21 -> 0 | T43: =T29/$T$21 -> 0 | U43: =U29/$U$21 -> 0 | V43: =V29/$V$21 -> 0 | W43: =W29/$W$21 -> 0 | X43: =X29/$X$21 -> 0 | Y43: =Y29/$Y$21 -> 0 | Z43: =Z29/$Z$21 -> 0 | AA43: =AA29/$AA$21 -> 0 | AB43: =AB29/$AB$21 -> 0 | AC43: =AC29/$AC$21 -> 0 | AD43: =AD29/$AD$21 -> 0 | AE43: =AE29/$AE$21 -> 178845.26 | AF43: =AF29/$AF$21 -> 0 | AG43: =AG29/$AG$21 -> 95529.375 | AH43: =AH29/$AH$21 -> 1566.1445 | AI43: =AI29/$AI$21 -> 0 | AJ43: =AJ29/$AJ$21 -> 0 | AK43: =AK29/$AK$21 -> 770750.74 | AL43: =AL29/$AL$21 -> 0 | AM43: =SUM(L43:AL43) -> 1342711.6 | AP43: =AP29/$AP$21 -> 37880.799 | AQ43: =AQ29/$AQ$21 -> 31003 | AR43: =AR29/$AR$21 -> 175993.4 | AS43: =AS29/$AS$21 -> 0 | AT43: =AT29/$AT$21 -> 0 | AU43: =AU29/$AU$21 -> 0 | AV43: =AV29/$AV$21 -> 0 | AW43: =AW29/$AW$21 -> 45525 | AX43: =AX29/$AX$21 -> 0 | AY43: =AY29/$AY$21 -> 0 | AZ43: =AZ29/$AZ$21 -> 0 | BA43: =BA29/$BA$21 -> 0 | BB43: =BB29/$BB$21 -> 637684.77 | BC43: =BC29/$BC$21 -> 0 | BD43: =BD29/$BD$21 -> 0 | BE43: =BE29/$BE$21 -> 276821.93 | BF43: =BF29/$BF$21 -> 29518.3 | BG43: =BG29/$BG$21 -> 0 | BH43: =BH29/$BH$21 -> 114354.06 | BI43: =BI29/$BI$21 -> 0 | BJ43: =BJ29/$BJ$21 -> 0 | BK43: =BK29/$BK$21 -> 0 | BL43: =BL29/$BL$21 -> 80795.677 | BM43: =BM29/$BM$21 -> 0 | BN43: =BN29/$BN$21 -> 0 | BO43: =BO29/$BO$21 -> 0 | BP43: =BP29/$BP$21 -> 376516.86 | BQ43: =BQ29/$BQ$21 -> 0 | BR43: =BR29/$BR$21 -> 0 | BS43: =BS29/$BS$21 -> 0 | BT43: =SUM(AP43:BS43) -> 1806093.8 | BW43: =BW29/$BW$21 -> 0 | BX43: =BX29/$BX$21 -> 0 | BY43: =BY29/$BY$21 -> 0 | BZ43: =BZ29/$BZ$21 -> 0 | CA43: =CA29/$CA$21 -> 0 | CB43: =CB29/$CB$21 -> 0 | CC43: =CC29/$CC$21 -> 0 | CD43: =CD29/$CD$21 -> 3321.1536 | CE43: =CE29/$CE$21 -> 0 | CF43: =CF29/$CF$21 -> 0 | CG43: =CG29/$CG$21 -> 0 | CH43: =SUM(BW43:CG43) -> 3321.1536 | CK43: =CK29/$CK$21 -> 0 | CL43: =CL29/$CL$21 -> 587.52673 | CM43: =CM29/$CM$21 -> 0 | CN43: =CN29/$CN$21 -> 1645 | CO43: =CO29/$CO$21 -> 0 | CP43: =CP29/$CP$21 -> 11445.473 | CQ43: =CQ29/$CQ$21 -> 65.441102 | CR43: =SUM(CK43:CQ43) -> 13743.441 | CU43: =CU29/$CU$21 -> 0 | CV43: =CV29/$CV$21 -> 431.8359 | CW43: =CW29/$CW$21 -> 0 | CX43: =CX29/$CX$21 -> 0 | CY43: =CY29/$CY$21 -> 0 | CZ43: =CZ29/$CZ$21 -> 310.67387 | DA43: =DA29/$DA$21 -> 0 | DB43: =DB29/$DB$21 -> 16709.355 | DC43: =SUM(CU43:DB43) -> 17451.865 | DO43: =SUM(CY43:DM43) -> 34471.894
A44: Kiosks | C44: =C30/$C$21 -> 0 | D44: =D30/$D$21 -> 0 | E44: =E30/$E$21 -> 3583.2159 | F44: =F30/$F$21 -> 5109.9648 | G44: =G30/$G$21 -> 84.55476 | H44: =H30/$H$21 -> 65.783626 | I44: =SUM(B44:H44) -> 8843.5191 | L44: =L30/$L$21 -> 2557 | M44: =M30/$M$21 -> 0 | N44: =N30/$N$21 -> 0 | O44: =O30/$O$21 -> 7174 | P44: =P30/$P$21 -> 38597.871 | Q44: =Q30/$Q$21 -> 108810.13 | R44: =R30/$R$21 -> 138427.9 | S44: =S30/$S$21 -> 573.45598 | T44: =T30/$T$21 -> 1771 | U44: =U30/$U$21 -> 0 | V44: =V30/$V$21 -> 0 | W44: =W30/$W$21 -> 12986.49 | X44: =X30/$X$21 -> 674.42282 | Y44: =Y30/$Y$21 -> 6542.7614 | Z44: =Z30/$Z$21 -> 7167.5719 | AA44: =AA30/$AA$21 -> 37023.6 | AB44: =AB30/$AB$21 -> 3907.5192 | AC44: =AC30/$AC$21 -> 13807.197 | AD44: =AD30/$AD$21 -> 155 | AE44: =AE30/$AE$21 -> 0 | AF44: =AF30/$AF$21 -> 10289.905 | AG44: =AG30/$AG$21 -> 0 | AH44: =AH30/$AH$21 -> 156.61445 | AI44: =AI30/$AI$21 -> 29.791438 | AJ44: =AJ30/$AJ$21 -> 8754 | AK44: =AK30/$AK$21 -> 9560.0208 | AL44: =AL30/$AL$21 -> 37.481499 | AM44: =SUM(L44:AL44) -> 409003.74 | AP44: =AP30/$AP$21 -> 120993.91 | AQ44: =AQ30/$AQ$21 -> 39909 | AR44: =AR30/$AR$21 -> 1543705.4 | AS44: =AS30/$AS$21 -> 0 | AT44: =AT30/$AT$21 -> 141376.42 | AU44: =AU30/$AU$21 -> 0 | AV44: =AV30/$AV$21 -> 8349.3996 | AW44: =AW30/$AW$21 -> 3956 | AX44: =AX30/$AX$21 -> 0 | AY44: =AY30/$AY$21 -> 44198 | AZ44: =AZ30/$AZ$21 -> 17150.63 | BA44: =BA30/$BA$21 -> 2010 | BB44: =BB30/$BB$21 -> 60169.373 | BC44: =BC30/$BC$21 -> 10692.507 | BD44: =BD30/$BD$21 -> 27315.152 | BE44: =BE30/$BE$21 -> 219487.59 | BF44: =BF30/$BF$21 -> 350245.92 | BG44: =BG30/$BG$21 -> 1407.5343 | BH44: =BH30/$BH$21 -> 20802.608 | BI44: =BI30/$BI$21 -> 14430.671 | BJ44: =BJ30/$BJ$21 -> 8903 | BK44: =BK30/$BK$21 -> 21397.778 | BL44: =BL30/$BL$21 -> 22337.746 | BM44: =BM30/$BM$21 -> 3128.1544 | BN44: =BN30/$BN$21 -> 8.2381354 | BO44: =BO30/$BO$21 -> 20965.089 | BP44: =BP30/$BP$21 -> 666417.45 | BQ44: =BQ30/$BQ$21 -> 0 | BR44: =BR30/$BR$21 -> 6754.9435 | BS44: =BS30/$BS$21 -> 24329.727 | BT44: =SUM(AP44:BS44) -> 3400442.2 | BW44: =BW30/$BW$21 -> 0 | BX44: =BX30/$BX$21 -> 0 | BY44: =BY30/$BY$21 -> 2723 | BZ44: =BZ30/$BZ$21 -> 1158 | CA44: =CA30/$CA$21 -> 11074 | CB44: =CB30/$CB$21 -> 82001.673 | CC44: =CC30/$CC$21 -> 5496.0607 | CD44: =CD30/$CD$21 -> 31508.435 | CE44: =CE30/$CE$21 -> 30292 | CF44: =CF30/$CF$21 -> 19.122742 | CG44: =CG30/$CG$21 -> 3659.4201 | CH44: =SUM(BW44:CG44) -> 167931.71 | CK44: =CK30/$CK$21 -> 3374.314 | CL44: =CL30/$CL$21 -> 9843.2327 | CM44: =CM30/$CM$21 -> 5297 | CN44: =CN30/$CN$21 -> 884 | CO44: =CO30/$CO$21 -> 9145.6808 | CP44: =CP30/$CP$21 -> 406237.47 | CQ44: =CQ30/$CQ$21 -> 297459.55 | CR44: =SUM(CK44:CQ44) -> 732241.25 | CU44: =CU30/$CU$21 -> 0 | CV44: =CV30/$CV$21 -> 20901.435 | CW44: =CW30/$CW$21 -> 266035.32 | CX44: =CX30/$CX$21 -> 73796.347 | CY44: =CY30/$CY$21 -> 5033.6131 | CZ44: =CZ30/$CZ$21 -> 306206.95 | DA44: =DA30/$DA$21 -> 447244.92 | DB44: =DB30/$DB$21 -> 5569.446 | DC44: =SUM(CU44:DB44) -> 1124788 | DO44: =SUM(CY44:DM44) -> 1888843
A45: Bulk | C45: =C31/$C$21 -> 0 | D45: =D31/$D$21 -> 0 | E45: =E31/$E$21 -> 222714.68 | F45: =F31/$F$21 -> 0 | G45: =G31/$G$21 -> 0 | H45: =H31/$H$21 -> 0 | I45: =SUM(B45:H45) -> 222714.68 | L45: =L31/$L$21 -> 0 | M45: =M31/$M$21 -> 0 | N45: =N31/$N$21 -> 0 | O45: =O31/$O$21 -> 0 | P45: =P31/$P$21 -> 0 | Q45: =Q31/$Q$21 -> 22976.233 | R45: =R31/$R$21 -> 0 | S45: =S31/$S$21 -> 0 | T45: =T31/$T$21 -> 0 | U45: =U31/$U$21 -> 0 | V45: =V31/$V$21 -> 1556.1125 | W45: =W31/$W$21 -> 0 | X45: =X31/$X$21 -> 0 | Y45: =Y31/$Y$21 -> 0 | Z45: =Z31/$Z$21 -> 0 | AA45: =AA31/$AA$21 -> 0 | AB45: =AB31/$AB$21 -> 0 | AC45: =AC31/$AC$21 -> 0 | AD45: =AD31/$AD$21 -> 0 | AE45: =AE31/$AE$21 -> 0 | AF45: =AF31/$AF$21 -> 0 | AG45: =AG31/$AG$21 -> 205447.48 | AH45: =AH31/$AH$21 -> 0 | AI45: =AI31/$AI$21 -> 0 | AJ45: =AJ31/$AJ$21 -> 0 | AK45: =AK31/$AK$21 -> 0 | AL45: =AL31/$AL$21 -> 0 | AM45: =SUM(L45:AL45) -> 229979.83 | AP45: =AP31/$AP$21 -> 0 | AQ45: =AQ31/$AQ$21 -> 3588 | AR45: =AR31/$AR$21 -> 2922762.8 | AS45: =AS31/$AS$21 -> 1133.4123 | AT45: =AT31/$AT$21 -> 0 | AU45: =AU31/$AU$21 -> 0 | AV45: =AV31/$AV$21 -> 0 | AW45: =AW31/$AW$21 -> 22796 | AX45: =AX31/$AX$21 -> 0 | AY45: =AY31/$AY$21 -> 0 | AZ45: =AZ31/$AZ$21 -> 86073.994 | BA45: =BA31/$BA$21 -> 30167 | BB45: =BB31/$BB$21 -> 0 | BC45: =BC31/$BC$21 -> 247405.15 | BD45: =BD31/$BD$21 -> 54936.104 | BE45: =BE31/$BE$21 -> 163004.95 | BF45: =BF31/$BF$21 -> 1976.59 | BG45: =BG31/$BG$21 -> 0 | BH45: =BH31/$BH$21 -> 0 | BI45: =BI31/$BI$21 -> 0 | BJ45: =BJ31/$BJ$21 -> 0 | BK45: =BK31/$BK$21 -> 29719.342 | BL45: =BL31/$BL$21 -> 0 | BM45: =BM31/$BM$21 -> 0 | BN45: =BN31/$BN$21 -> 0 | BO45: =BO31/$BO$21 -> 0 | BP45: =BP31/$BP$21 -> 102806.33 | BQ45: =BQ31/$BQ$21 -> 165542.74 | BR45: =BR31/$BR$21 -> 0 | BS45: =BS31/$BS$21 -> 0 | BT45: =SUM(AP45:BS45) -> 3831912.4 | BW45: =BW31/$BW$21 -> 0 | BX45: =BX31/$BX$21 -> 16665.089 | BY45: =BY31/$BY$21 -> 0 | BZ45: =BZ31/$BZ$21 -> 0 | CA45: =CA31/$CA$21 -> 930 | CB45: =CB31/$CB$21 -> 8460.5397 | CC45: =CC31/$CC$21 -> 0 | CD45: =CD31/$CD$21 -> 1518629.4 | CE45: =CE31/$CE$21 -> 27317 | CF45: =CF31/$CF$21 -> 0 | CG45: =CG31/$CG$21 -> 0 | CH45: =SUM(BW45:CG45) -> 1572002 | CK45: =CK31/$CK$21 -> 0 | CL45: =CL31/$CL$21 -> 0 | CM45: =CM31/$CM$21 -> 0 | CN45: =CN31/$CN$21 -> 0 | CO45: =CO31/$CO$21 -> 128.52355 | CP45: =CP31/$CP$21 -> 677008.55 | CQ45: =CQ31/$CQ$21 -> 0 | CR45: =SUM(CK45:CQ45) -> 677137.07 | CU45: =CU31/$CU$21 -> 0 | CV45: =CV31/$CV$21 -> 0 | CW45: =CW31/$CW$21 -> 0 | CX45: =CX31/$CX$21 -> 7868.7841 | CY45: =CY31/$CY$21 -> 0 | CZ45: =CZ31/$CZ$21 -> 19191.291 | DA45: =DA31/$DA$21 -> 0 | DB45: =DB31/$DB$21 -> 0 | DC45: =SUM(CU45:DB45) -> 27060.075 | DO45: =SUM(CY45:DM45) -> 46251.366
A46: Others | C46: =C32/$C$21 -> 0 | D46: =D32/$D$21 -> 0 | E46: =E32/$E$21 -> 20631.589 | F46: =F32/$F$21 -> 0 | G46: =G32/$G$21 -> 0 | H46: =H32/$H$21 -> 0 | I46: =SUM(B46:H46) -> 20631.589 | L46: =L32/$L$21 -> 0 | M46: =M32/$M$21 -> 0 | N46: =N32/$N$21 -> 0 | O46: =O32/$O$21 -> 0 | P46: =P32/$P$21 -> 0 | Q46: =Q32/$Q$21 -> 0 | R46: =R32/$R$21 -> 18100.62 | S46: =S32/$S$21 -> 0 | T46: =T32/$T$21 -> 0 | U46: =U32/$U$21 -> 0 | V46: =V32/$V$21 -> 0 | W46: =W32/$W$21 -> 0 | X46: =X32/$X$21 -> 0 | Y46: =Y32/$Y$21 -> 0 | Z46: =Z32/$Z$21 -> 0 | AA46: =AA32/$AA$21 -> 0 | AB46: =AB32/$AB$21 -> 0 | AC46: =AC32/$AC$21 -> 0 | AD46: =AD32/$AD$21 -> 0 | AE46: =AE32/$AE$21 -> 0 | AF46: =AF32/$AF$21 -> 0 | AG46: =AG32/$AG$21 -> 0 | AH46: =AH32/$AH$21 -> 0 | AI46: =AI32/$AI$21 -> 0 | AJ46: =AJ32/$AJ$21 -> 0 | AK46: =AK32/$AK$21 -> 0 | AL46: =AL32/$AL$21 -> 0 | AM46: =SUM(L46:AL46) -> 18100.62 | AP46: =AP32/$AP$21 -> 0 | AQ46: =AQ32/$AQ$21 -> 0 | AR46: =AR32/$AR$21 -> 497529.95 | AS46: =AS32/$AS$21 -> 0 | AT46: =AT32/$AT$21 -> 94390.379 | AU46: =AU32/$AU$21 -> 0 | AV46: =AV32/$AV$21 -> 0 | AW46: =AW32/$AW$21 -> 0 | AX46: =AX32/$AX$21 -> 0 | AY46: =AY32/$AY$21 -> 0 | AZ46: =AZ32/$AZ$21 -> 0 | BA46: =BA32/$BA$21 -> 0 | BB46: =BB32/$BB$21 -> 0 | BC46: =BC32/$BC$21 -> 0 | BD46: =BD32/$BD$21 -> 0 | BE46: =BE32/$BE$21 -> 734.70765 | BF46: =BF32/$BF$21 -> 0 | BG46: =BG32/$BG$21 -> 0 | BH46: =BH32/$BH$21 -> 0 | BI46: =BI32/$BI$21 -> 0 | BJ46: =BJ32/$BJ$21 -> 0 | BK46: =BK32/$BK$21 -> 29719.342 | BL46: =BL32/$BL$21 -> 0 | BM46: =BM32/$BM$21 -> 0 | BN46: =BN32/$BN$21 -> 0 | BO46: =BO32/$BO$21 -> 0 | BP46: =BP32/$BP$21 -> 0 | BQ46: =BQ32/$BQ$21 -> 0 | BR46: =BR32/$BR$21 -> 0 | BS46: =BS32/$BS$21 -> 0 | BT46: =SUM(AP46:BS46) -> 622374.38 | BW46: =BW32/$BW$21 -> 0 | BX46: =BX32/$BX$21 -> 0 | BY46: =BY32/$BY$21 -> 0 | BZ46: =BZ32/$BZ$21 -> 0 | CA46: =CA32/$CA$21 -> 0 | CB46: =CB32/$CB$21 -> 0 | CC46: =CC32/$CC$21 -> 0 | CD46: =CD32/$CD$21 -> 0 | CE46: =CE32/$CE$21 -> 12233 | CF46: =CF32/$CF$21 -> 0 | CG46: =CG32/$CG$21 -> 0 | CH46: =SUM(BW46:CG46) -> 12233 | CK46: =CK32/$CK$21 -> 0 | CL46: =CL32/$CL$21 -> 36.720421 | CM46: =CM32/$CM$21 -> 0 | CN46: =CN32/$CN$21 -> 0 | CO46: =CO32/$CO$21 -> 0 | CP46: =CP32/$CP$21 -> 308758.6 | CQ46: =CQ32/$CQ$21 -> 0 | CR46: =SUM(CK46:CQ46) -> 308795.32 | CU46: =CU32/$CU$21 -> 0 | CV46: =CV32/$CV$21 -> 0 | CW46: =CW32/$CW$21 -> 0 | CX46: =CX32/$CX$21 -> 0 | CY46: =CY32/$CY$21 -> 0 | CZ46: =CZ32/$CZ$21 -> 0 | DA46: =DA32/$DA$21 -> 0 | DB46: =DB32/$DB$21 -> 0 | DC46: =SUM(CU46:DB46) -> 0 | DO46: =SUM(CY46:DM46) -> 0
A47: Total Sold | B47: =SUM(B38:B46) -> 0 | C47: =SUM(C38:C46) -> 0 | D47: =SUM(D38:D46) -> 0 | E47: =SUM(E38:E46) -> 1931100 | F47: =SUM(F38:F46) -> 2789074 | G47: =SUM(G38:G46) -> 167689 | H47: =SUM(H38:H46) -> 3289.329 | L47: =SUM(L38:L46) -> 373698.77 | M47: =SUM(M38:M46) -> 721694 | N47: =SUM(N38:N46) -> 1740204 | O47: =SUM(O38:O46) -> 461783 | P47: =SUM(P38:P46) -> 4739448 | Q47: =SUM(Q38:Q46) -> 588392 | R47: =SUM(R38:R46) -> 602643 | S47: =SUM(S38:S46) -> 2701227 | ... AL47: =SUM(AL38:AL46) -> 37496.097 | AP47: =SUM(AP38:AP46) -> 1835915 | AQ47: =SUM(AQ38:AQ46) -> 3350520 | AR47: =SUM(AR38:AR46) -> 23175364 | AS47: =SUM(AS38:AS46) -> 618158 | AT47: =SUM(AT38:AT46) -> 935944 | AU47: =SUM(AU38:AU46) -> 0 | AV47: =SUM(AV38:AV46) -> 4742140 | AW47: =SUM(AW38:AW46) -> 690912 | ... BS47: =SUM(BS38:BS46) -> 1428834 | BW47: =SUM(BW38:BW46) -> 0 | BX47: =SUM(BX38:BX46) -> 75766 | BY47: =SUM(BY38:BY46) -> 272266 | BZ47: =SUM(BZ38:BZ46) -> 394594 | CA47: =SUM(CA38:CA46) -> 322268 | CB47: =SUM(CB38:CB46) -> 1358835 | CC47: =SUM(CC38:CC46) -> 7905899 | CD47: =SUM(CD38:CD46) -> 3830215 | ... CG47: =SUM(CG38:CG46) -> 794825 | CK47: =SUM(CK38:CK46) -> 249630 | CL47: =SUM(CL38:CL46) -> 569227 | CM47: =SUM(CM38:CM46) -> 1158721 | CN47: =SUM(CN38:CN46) -> 89065 | CO47: =SUM(CO38:CO46) -> 1946176 | CP47: =SUM(CP38:CP46) -> 6696511 | CQ47: =SUM(CQ38:CQ46) -> 1348246 | CU47: =SUM(CU38:CU46) -> 262729 | CV47: =SUM(CV38:CV46) -> 620242 | CW47: =SUM(CW38:CW46) -> 3072689 | CX47: =SUM(CX38:CX46) -> 4254899 | CY47: =SUM(CY38:CY46) -> 1101105 | CZ47: =SUM(CZ38:CZ46) -> 974798 | DA47: =SUM(DA38:DA46) -> 8869969 | DB47: =SUM(DB38:DB46) -> 681984 | DO47: =SUM(CY47:DM47) -> 11627856
A48: Total Billed Volume | B48: 571536 | C48: 141426 | D48: 344242 | E48: 1931100 | F48: 2789074 | G48: 167689 | H48: 361390 | L48: 352197 | M48: 721694 | N48: 1740204 | O48: 461783 | P48: 4739448 | Q48: 1653210 | R48: 602643 | S48: 2701227 | T48: 1771192 | U48: 573552 | V48: 1214018 | W48: 1298768 | X48: 486523 | Y48: 435051 | Z48: 716731 | AA48: 2421650 | AB48: 2986416 | AC48: 6117001 | AD48: 2149900 | AE48: 3576960 | AF48: 1638248 | AG48: 1214494 | AH48: 1020766 | AI48: 2068366 | AJ48: 2977634 | AK48: 9214087 | AL48: 566988 | AP48: 1835915 | AQ48: 3350520 | AR48: 89727204 | AS48: 618158 | AT48: 935944 | AU48: 42602 | AV48: 4742140 | AW48: 690912 | AX48: 354485 | AY48: 1454089 | AZ48: 1519934 | BA48: 1005557 | BB48: 6915527 | BC48: 2072421 | BD48: 1370875 | BE48: 5347542 | BF48: 5164287 | BG48: 70381 | BH48: 710419 | BI48: 90678 | BJ48: 42682 | BK48: 274619 | BL48: 604643 | BM48: 156414 | BN48: 125326 | BO48: 298451 | BP48: 5823200 | BQ48: 1081545 | BR48: 219878 | BS48: 1428834 | BW48: 1273305 | BX48: 75766 | BY48: 272266 | BZ48: 394594 | CA48: 322268 | CB48: 1358834.9 | CC48: 7905899 | CD48: 3830215 | CE48: 785675 | CF48: 440400 | CG48: 794825 | CK48: 249630 | CL48: 569227 | CM48: 2005094 | CN48: 89065 | CO48: 1946176 | CP48: 6696511 | CQ48: 1348246 | CU48: 262729 | CV48: 620242 | CW48: 3072689 | CX48: 4254899 | CY48: 1101104.9 | CZ48: 974798 | DA48: 8869969 | DB48: 681984 | DO48: =SUM(CY48:DM48) -> 11627856
A49: Non-payment of billed | DO49: =DO48-DO47 -> -0.1
A52: Non-Revenue Water | B52: =B10-B14 -> 0 | C52: =C10-C14 -> 208494 | D52: =D10-D14 -> 238254 | E52: =E10-E14 -> 1253287 | F52: =F10-F14 -> 1872176 | G52: =G10-G14 -> 102011 | H52: =H10-H14 -> 286610 | I52: =SUM(B52:H52) -> 3960832 | L52: =L10-L14 -> 248366 | M52: =M10-M14 -> 435886 | N52: =N10-N14 -> 1018246 | O52: =O10-O14 -> 572422 | P52: =P10-P14 -> 2898443 | Q52: =Q10-Q14 -> 1973026 | R52: =R10-R14 -> 372336 | S52: =S10-S14 -> 4021718 | ... AL52: =AL10-AL14 -> 1341012 | AM52: =SUM(L52:AL52) -> 38903253 | AP52: =AP10-AP14 -> 2685674 | AQ52: =AQ10-AQ14 -> 2415485 | AR52: =AR10-AR14 -> 103915593 | AS52: =AS10-AS14 -> 216675 | AT52: =AT10-AT14 -> 362493 | AU52: =AU10-AU14 -> 22370 | AV52: =AV10-AV14 -> 2427236 | AW52: =AW10-AW14 -> 750043 | ... BS52: =BS10-BS14 -> 1018385 | BT52: =SUM(AP52:BS52) -> 139861034 | BW52: =BW10-BW14 -> 1031635 | BX52: =BX10-BX14 -> 167260 | BY52: =BY10-BY14 -> 577887 | BZ52: =BZ10-BZ14 -> 344414 | CA52: =CA10-CA14 -> 299022 | CB52: =CB10-CB14 -> 2515233.1 | CC52: =CC10-CC14 -> 3631296 | CD52: =CD10-CD14 -> 4411974 | ... CG52: =CG10-CG14 -> 374034 | CH52: =SUM(BW52:CG52) -> 14045585 | CK52: =CK10-CK14 -> 232291 | CL52: =CL10-CL14 -> 449592 | CM52: =CM10-CM14 -> 2418910 | CN52: =CN10-CN14 -> 51207 | CO52: =CO10-CO14 -> 2154750 | CP52: =CP10-CP14 -> 3219180 | CQ52: =CQ10-CQ14 -> 1883406 | CR52: =SUM(CK52:CQ52) -> 10409336 | CU52: =CU10-CU14 -> 87718 | CV52: =CV10-CV14 -> 587408 | CW52: =CW10-CW14 -> 2634624 | CX52: =CX10-CX14 -> 4010596 | CY52: =CY10-CY14 -> 471902.1 | CZ52: =CZ10-CZ14 -> 2249205 | DA52: =DA10-DA14 -> 6420526 | DB52: =DB10-DB14 -> 403382 | DC52: =SUM(CU52:DB52) -> 16865361 | DO52: =SUM(CY52:DM52) -> 26410376
A54: Water Proportions
A55: Individual | B55: =B38/B47 -> #DIV/0! | C55: =C38/C47 -> #DIV/0! | D55: =D38/D47 -> #DIV/0! | E55: =E38/$E$47 -> 0.5462191 | F55: =F38/$F$47 -> 0.63811616 | G55: =G38/$G$47 -> 0.49515057 | H55: =H38/$H$47 -> 0.14999808 | L55: =L38/$L$47 -> 0.69448923 | M55: =M38/$M$47 -> 0.83775481 | N55: =N38/$N$47 -> 0.38276304 | O55: =O38/$O$47 -> 0.45179879 | P55: =P38/$P$47 -> 0.71180019 | Q55: =Q38/$Q$47 -> 0.40592616 | R55: =R38/$R$47 -> 0.35989448 | S55: =S38/$S$47 -> 0.81640327 | T55: =T38/$T$47 -> 0.80000023 | U55: =U38/$U$47 -> 0.91589928 | V55: =V38/$V$47 -> 0.68605667 | W55: =W38/$W$47 -> 0.50000068 | X55: =X38/$X$47 -> 0.9801464 | Y55: =Y38/$Y$47 -> 0.83621507 | Z55: =Z38/$Z$47 -> 0.4499997 | AA55: =AA38/$AA$47 -> 0.79211933 | AB55: =AB38/$AB$47 -> 0.85645175 | AC55: =AC38/$AC$47 -> 0.37462467 | AD55: =AD38/$AD$47 -> 0.94616168 | AE55: =AE38/$AE$47 -> 0.3700008 | AF55: =AF38/$AF$47 -> 0.88848692 | AG55: =AG38/$AG$47 -> 0.64922758 | AH55: =AH38/$AH$47 -> 0.69429948 | AI55: =AI38/$AI$47 -> 0.56850074 | AJ55: =AJ38/$AJ$47 -> 0.72004014 | AK55: =AK38/$AK$47 -> 0.61731717 | AL55: =AL38/$AL$47 -> 0.79999995 | AP55: =AP38/$AP$47 -> 0.83884273 | AQ55: =AQ38/$AQ$47 -> 0.77455201 | AR55: =AR38/$AR$47 -> 0.46716116 | AS55: =AS38/$AS$47 -> 0.98735756 | AT55: =AT38/$AT$47 -> 0.47967239 | AU55: =AU38/AU47 -> #DIV/0! | AV55: =AV38/$AV$47 -> 0.95824415 | AW55: =AW38/$AW$47 -> 0.73462033 | AX55: =AX38/$AX$47 -> 0.70000141 | AY55: =AY38/$AY$47 -> 0.40599716 | AZ55: =AZ38/$AZ$47 -> 0.71372647 | BA55: =BA38/$BA$47 -> 0.33200043 | BB55: =BB38/$BB$47 -> 0.64582841 | BC55: =BC38/$BC$47 -> 0.54813024 | BD55: =BD38/$BD$47 -> 0.56000048 | BE55: =BE38/$BE$47 -> 0.75245157 | BF55: =BF38/$BF$47 -> 0.72870773 | BG55: =BG38/$BG$47 -> 0.14999696 | BH55: =BH38/$BH$47 -> 0.16780124 | BI55: =BI38/$BI$47 -> 0.70218696 | BJ55: =BJ38/$BJ$47 -> 0.21578183 | BK55: =BK38/$BK$47 -> 0.21662959 | BL55: =BL38/$BL$47 -> 0.29935292 | BM55: =BM38/$BM$47 -> 0.84199751 | BN55: =BN38/$BN$47 -> 0.17999807 | BO55: =BO38/$BO$47 -> 0.1673517 | BP55: =BP38/$BP$47 -> 0.47175048 | BQ55: =BQ38/$BQ$47 -> 0.64285685 | BR55: =BR38/$BR$47 -> 0.19711931 | BS55: =BS38/$BS$47 -> 0.26722953 | BW55: =BW38/BW47 -> #DIV/0! | BX55: =BX38/$BX$47 -> 0.38044416 | BY55: =BY38/$BY$47 -> 0.4799975 | BZ55: =BZ38/$BZ$47 -> 0.88947627 | CA55: =CA38/$CA$47 -> 0.70899686 | CB55: =CB38/$CB$47 -> 0.56017716 | CC55: =CC38/$CC$47 -> 0.51449564 | CD55: =CD38/$CD$47 -> 0.15498209 | CE55: =CE38/$CE$47 -> 0.57927133 | CF55: =CF38/$CF$47 -> 0.51361915 | CG55: =CG38/$CG$47 -> 0.42914421 | CK55: =CK38/$CK$47 -> 0.74668272 | CL55: =CL38/$CL$47 -> 0.87581965 | CM55: =CM38/$CM$47 -> 0.33048163 | CN55: =CN38/$CN$47 -> 0.7039241 | CO55: =CO38/$CO$47 -> 0.83604339 | CP55: =CP38/$CP$47 -> 0.48332573 | CQ55: =CQ38/$CQ$47 -> 0.39006864 | CU55: =CU38/$CU$47 -> 0.83366891 | CV55: =CV38/$CV$47 -> 0.89243709 | CW55: =CW38/$CW$47 -> 0.34157638 | CX55: =CX38/$CX$47 -> 0.72637419 | CY55: =CY38/CY47 -> 0.33048163 | CZ55: =CZ38/$CZ$47 -> 0.55279046 | DA55: =DA38/$DA$47 -> 0.77971087 | DB55: =DB38/$DB$47 -> 0.36183193
A56: Multi-dwelling units | E56: =E39/$E$47 -> 0 | F56: =F39/$F$47 -> 0 | G56: =G39/$G$47 -> 0.42815739 | H56: =H39/$H$47 -> 0.25 | L56: =L39/$L$47 -> 0 | M56: =M39/$M$47 -> 0 | N56: =N39/$N$47 -> 0 | O56: =O39/$O$47 -> 0.22683815 | P56: =P39/$P$47 -> 0 | Q56: =Q39/$Q$47 -> 0.16990835 | R56: =R39/$R$47 -> 0.11794269 | S56: =S39/$S$47 -> 0 | T56: =T39/$T$47 -> 0 | U56: =U39/$U$47 -> 0 | V56: =V39/$V$47 -> 0 | W56: =W39/$W$47 -> 0 | X56: =X39/$X$47 -> 0 | Y56: =Y39/$Y$47 -> 0 | Z56: =Z39/$Z$47 -> 0.14999939 | AA56: =AA39/$AA$47 -> 0 | AB56: =AB39/$AB$47 -> 0 | AC56: =AC39/$AC$47 -> 0.33343495 | AD56: =AD39/$AD$47 -> 0.0042913624 | AE56: =AE39/$AE$47 -> 0.07000029 | AF56: =AF39/$AF$47 -> 0 | AG56: =AG39/$AG$47 -> 0.03733242 | AH56: =AH39/$AH$47 -> 0 | AI56: =AI39/$AI$47 -> 0 | AJ56: =AJ39/$AJ$47 -> 0 | AK56: =AK39/$AK$47 -> 0.022774292 | AL56: =AL39/$AL$47 -> 0.0019997817 | AP56: =AP39/$AP$47 -> 0 | AQ56: =AQ39/$AQ$47 -> 0 | AR56: =AR39/$AR$47 -> 0.1668803 | AS56: =AS39/$AS$47 -> 0 | AT56: =AT39/$AT$47 -> 0.14235317 | AV56: =AV39/$AV$47 -> 0 | AW56: =AW39/$AW$47 -> 0.045163494 | AX56: =AX39/$AX$47 -> 0.2 | AY56: =AY39/$AY$47 -> 0 | AZ56: =AZ39/$AZ$47 -> 0 | BA56: =BA39/$BA$47 -> 0.45200218 | BB56: =BB39/$BB$47 -> 0.23940018 | BC56: =BC39/$BC$47 -> 0.27259144 | BD56: =BD39/$BD$47 -> 0 | BE56: =BE39/$BE$47 -> 0 | BF56: =BF39/$BF$47 -> 0 | BG56: =BG39/$BG$47 -> 0.16000243 | BH56: =BH39/$BH$47 -> 0.15146929 | BI56: =BI39/$BI$47 -> 0.039313117 | BJ56: =BJ39/$BJ$47 -> 0.19734314 | BK56: =BK39/$BK$47 -> 0.41442657 | BL56: =BL39/$BL$47 -> 0.17676564 | BM56: =BM39/$BM$47 -> 0 | BN56: =BN39/$BN$47 -> 0.10399942 | BO56: =BO39/$BO$47 -> 0.12723134 | BP56: =BP39/$BP$47 -> 0.20217891 | BQ56: =BQ39/$BQ$47 -> 0 | BR56: =BR39/$BR$47 -> 0.3660746 | BS56: =BS39/$BS$47 -> 0.65298157 | BX56: =BX39/$BX$47 -> 0 | BY56: =BY39/$BY$47 -> 0 | BZ56: =BZ39/$BZ$47 -> 0 | CA56: =CA39/$CA$47 -> 0 | CB56: =CB39/$CB$47 -> 0.14377529 | CC56: =CC39/$CC$47 -> 0.43993875 | CD56: =CD39/$CD$47 -> 0.18021773 | CE56: =CE39/$CE$47 -> 0.033499857 | CF56: =CF39/$CF$47 -> 0.25299109 | CG56: =CG39/$CG$47 -> 0.11370049 | CK56: =CK39/$CK$47 -> 0 | CL56: =CL39/$CL$47 -> 0 | CM56: =CM39/$CM$47 -> 0 | CN56: =CN39/$CN$47 -> 0.099141077 | CO56: =CO39/$CO$47 -> 0 | CP56: =CP39/$CP$47 -> 0 | CQ56: =CQ39/$CQ$47 -> 0.23571452 | CU56: =CU39/$CU$47 -> 0 | CV56: =CV39/$CV$47 -> 0 | CW56: =CW39/$CW$47 -> 0.44407892 | CX56: =CX39/$CX$47 -> 0.03913036 | CY56: =CY39/$CY$47 -> 0 | CZ56: =CZ39/$CZ$47 -> 0.0020282907 | DA56: =DA39/$DA$47 -> 0.0041297997 | DB56: =DB39/$DB$47 -> 0.058169592
A57: Institutions | E57: =E40/$E$47 -> 0.049242103 | F57: =F40/$F$47 -> 0 | G57: =G40/$G$47 -> 0.020305348 | H57: =H40/$H$47 -> 0.29000462 | L57: =L40/$L$47 -> 0 | M57: =M40/$M$47 -> 0.064606213 | N57: =N40/$N$47 -> 0.18036145 | O57: =O40/$O$47 -> 0.090689783 | P57: =P40/$P$47 -> 0.043847508 | Q57: =Q40/$Q$47 -> 0.10265228 | R57: =R40/$R$47 -> 0.054877645 | S57: =S40/$S$47 -> 0.076767985 | T57: =T40/$T$47 -> 0.069999752 | U57: =U40/$U$47 -> 0 | V57: =V40/$V$47 -> 0.14876393 | W57: =W40/$W$47 -> 0.20000014 | X57: =X40/$X$47 -> 0.00086638095 | Y57: =Y40/$Y$47 -> 0.085027149 | Z57: =Z40/$Z$47 -> 0.10000061 | AA57: =AA40/$AA$47 -> 0.039386387 | AB57: =AB40/$AB$47 -> 0.028014302 | AC57: =AC40/$AC$47 -> 0.096894012 | AD57: =AD40/$AD$47 -> 0.015891437 | AE57: =AE40/$AE$47 -> 0.11999952 | AF57: =AF40/$AF$47 -> 0.029590813 | AG57: =AG40/$AG$47 -> 0.071998709 | AH57: =AH40/$AH$47 -> 0.059716508 | AI57: =AI40/$AI$47 -> 0 | AJ57: =AJ40/$AJ$47 -> 0.01084015 | AK57: =AK40/$AK$47 -> 0.01282151 | AL57: =AL40/$AL$47 -> 0.067000279 | AP57: =AP40/$AP$47 -> 0.017468022 | AQ57: =AQ40/$AQ$47 -> 0.068766938 | AR57: =AR40/$AR$47 -> 0.024019749 | AS57: =AS40/$AS$47 -> 0 | AT57: =AT40/$AT$47 -> 0.034214014 | AV57: =AV40/$AV$47 -> 0.024166152 | AW57: =AW40/$AW$47 -> 0.014059678 | AX57: =AX40/$AX$47 -> 0.070000141 | AY57: =AY40/$AY$47 -> 0 | AZ57: =AZ40/$AZ$47 -> 0.057753881 | BA57: =BA40/$BA$47 -> 0.0039996937 | BB57: =BB40/$BB$47 -> 0.006516051 | BC57: =BC40/$BC$47 -> 0.014986437 | BD57: =BD40/$BD$47 -> 0.30000009 | BE57: =BE40/$BE$47 -> 0.049049871 | BF57: =BF40/$BF$47 -> 0.030327923 | BG57: =BG40/$BG$47 -> 0.34999696 | BH57: =BH40/$BH$47 -> 0.18507449 | BI57: =BI40/$BI$47 -> 0.058479044 | BJ57: =BJ40/$BJ$47 -> 0.1274542 | BK57: =BK40/$BK$47 -> 0.023227681 | BL57: =BL40/$BL$47 -> 0.0095478682 | BM57: =BM40/$BM$47 -> 0.0050018064 | BN57: =BN40/$BN$47 -> 0.2339987 | BO57: =BO40/$BO$47 -> 0.28148759 | BP57: =BP40/$BP$47 -> 0.019397402 | BQ57: =BQ40/$BQ$47 -> 0 | BR57: =BR40/$BR$47 -> 0.17407951 | BS57: =BS40/$BS$47 -> 0.0035978115 | BX57: =BX40/$BX$47 -> 0.14771453 | BY57: =BY40/$BY$47 -> 0.13000522 | BZ57: =BZ40/$BZ$47 -> 0.063553931 | CA57: =CA40/$CA$47 -> 0.048320032 | CB57: =CB40/$CB$47 -> 0.0042227 | CC57: =CC40/$CC$47 -> 0.0013932542 | CD57: =CD40/$CD$47 -> 0.10654922 | CE57: =CE40/$CE$47 -> 0.087317275 | CF57: =CF40/$CF$47 -> 0.02959148 | CG57: =CG40/$CG$47 -> 0.16924516 | CK57: =CK40/$CK$47 -> 0.11745128 | CL57: =CL40/$CL$47 -> 0.048101151 | CM57: =CM40/$CM$47 -> 0.57174419 | CN57: =CN40/$CN$47 -> 0.049570538 | CO57: =CO40/$CO$47 -> 0.0093171215 | CP57: =CP40/$CP$47 -> 0.042297562 | CQ57: =CQ40/$CQ$47 -> 0.071536118 | CU57: =CU40/$CU$47 -> 0 | CV57: =CV40/$CV$47 -> 0.009144233 | CW57: =CW40/$CW$47 -> 0.024371499 | CX57: =CX40/$CX$47 -> 0.0028728927 | CY57: =CY40/$CY$47 -> 0.57174419 | CZ57: =CZ40/$CZ$47 -> 0.047992465 | DA57: =DA40/$DA$47 -> 0.040289011 | DB57: =DB40/$DB$47 -> 0.2000003
A58: Schools | E58: =E41/$E$47 -> 0.044219543 | F58: =F41/$F$47 -> 0.023691471 | G58: =G41/$G$47 -> 0.014346598 | H58: =H41/$H$47 -> 0.11999782 | L58: =L41/$L$47 -> 0.14670907 | M58: =M41/$M$47 -> 0 | N58: =N41/$N$47 -> 0.18599022 | O58: =O41/$O$47 -> 0.16424814 | P58: =P41/$P$47 -> 0.06067486 | Q58: =Q41/$Q$47 -> 0.043993639 | R58: =R41/$R$47 -> 0.04692554 | S58: =S41/$S$47 -> 0.037977864 | T58: =T41/$T$47 -> 0.099999887 | U58: =U41/$U$47 -> 0.084100718 | V58: =V41/$V$47 -> 0 | W58: =W41/$W$47 -> 0.10000041 | X58: =X41/$X$47 -> 0.017081182 | Y58: =Y41/$Y$47 -> 0.063718713 | Z58: =Z41/$Z$47 -> 0.090000244 | AA58: =AA41/$AA$47 -> 0.01694594 | AB58: =AB41/$AB$47 -> 0.071965103 | AC58: =AC41/$AC$47 -> 0.070831387 | AD58: =AD41/$AD$47 -> 0.015957021 | AE58: =AE41/$AE$47 -> 0.17999928 | AF58: =AF41/$AF$47 -> 0 | AG58: =AG41/$AG$47 -> 0.037401585 | AH58: =AH41/$AH$47 -> 0.12306598 | AI58: =AI41/$AI$47 -> 0.026143431 | AJ58: =AJ41/$AJ$47 -> 0.058689886 | AK58: =AK41/$AK$47 -> 0.016555261 | AL58: =AL41/$AL$47 -> 0.10000029 | AP58: =AP41/$AP$47 -> 0.026202713 | AQ58: =AQ41/$AQ$47 -> 0.033429736 | AR58: =AR41/$AR$47 -> 0.0023174026 | AS58: =AS41/$AS$47 -> 0.0097657137 | AT58: =AT41/$AT$47 -> 0.023688607 | AV58: =AV41/$AV$47 -> 0.014162822 | AW58: =AW41/$AW$47 -> 0.091701982 | AX58: =AX41/$AX$47 -> 0.029998448 | AY58: =AY41/$AY$47 -> 0.10998914 | AZ58: =AZ41/$AZ$47 -> 0.042154848 | BA58: =BA41/$BA$47 -> 0.0029992731 | BB58: =BB41/$BB$47 -> 0.0073441601 | BC58: =BC41/$BC$47 -> 0.0042291412 | BD58: =BD41/$BD$47 -> 0 | BE58: =BE41/$BE$47 -> 0.047049379 | BF58: =BF41/$BF$47 -> 0.015522991 | BG58: =BG41/$BG$47 -> 0.18000122 | BH58: =BH41/$BH$47 -> 0.10874034 | BI58: =BI41/$BI$47 -> 0.04087896 | BJ58: =BJ41/$BJ$47 -> 0.12862565 | BK58: =BK41/$BK$47 -> 0.08010237 | BL58: =BL41/$BL$47 -> 0.003799842 | BM58: =BM41/$BM$47 -> 0.02700012 | BN58: =BN41/$BN$47 -> 0.28601046 | BO58: =BO41/$BO$47 -> 0.15542203 | BP58: =BP41/$BP$47 -> 0.012931726 | BQ58: =BQ41/$BQ$47 -> 0.2040818 | BR58: =BR41/$BR$47 -> 0.078408229 | BS58: =BS41/$BS$47 -> 0.013202011 | BX58: =BX41/$BX$47 -> 0.16702242 | BY58: =BY41/$BY$47 -> 0.079998972 | BZ58: =BZ41/$BZ$47 -> 0.044035135 | CA58: =CA41/$CA$47 -> 0.026623804 | CB58: =CB41/$CB$47 -> 0.022148457 | CC58: =CC41/$CC$47 -> 0.0014242634 | CD58: =CD41/$CD$47 -> 0.019452144 | CE58: =CE41/$CE$47 -> 0.054955293 | CF58: =CF41/$CF$47 -> 0 | CG58: =CG41/$CG$47 -> 0.14579735 | CK58: =CK41/$CK$47 -> 0.055543391 | CL58: =CL41/$CL$47 -> 0.022231034 | CM58: =CM41/$CM$47 -> 0.056613283 | CN58: =CN41/$CN$47 -> 0.019828215 | CO58: =CO41/$CO$47 -> 0.050129233 | CP58: =CP41/$CP$47 -> 0.0073424549 | CQ58: =CQ41/$CQ$47 -> 0.025654515 | CU58: =CU41/$CU$47 -> 0.16633109 | CV58: =CV41/$CV$47 -> 0.055491779 | CW58: =CW41/$CW$47 -> 0.071484563 | CX58: =CX41/$CX$47 -> 0.098539484 | CY58: =CY41/$CY$47 -> 0.056613283 | CZ58: =CZ41/$CZ$47 -> 0.041223759 | DA58: =DA41/$DA$47 -> 0.0065419133 | DB58: =DB41/$DB$47 -> 0.047331594
A59: Commercial customers | E59: =E42/$E$47 -> 0.17629172 | F59: =F42/$F$47 -> 0.33636023 | G59: =G42/$G$47 -> 0.041535858 | H59: =H42/$H$47 -> 0.17000038 | L59: =L42/$L$47 -> 0.15195929 | M59: =M42/$M$47 -> 0.097638977 | N59: =N42/$N$47 -> 0.12560088 | O59: =O42/$O$47 -> 0.050889704 | P59: =P42/$P$47 -> 0.17553348 | Q59: =Q42/$Q$47 -> 0.053542416 | R59: =R42/$R$47 -> 0.031193661 | S59: =S42/$S$47 -> 0.068638585 | T59: =T42/$T$47 -> 0.029000244 | U59: =U42/$U$47 -> 0 | V59: =V42/$V$47 -> 0.16389761 | W59: =W42/$W$47 -> 0.18999969 | X59: =X42/$X$47 -> 0.00051982857 | Y59: =Y42/$Y$47 -> 0 | Z59: =Z42/$Z$47 -> 0.1999997 | AA59: =AA42/$AA$47 -> 0.13625976 | AB59: =AB42/$AB$47 -> 0.042260418 | AC59: =AC42/$AC$47 -> 0.1219578 | AD59: =AD42/$AD$47 -> 0.017626401 | AE59: =AE42/$AE$47 -> 0.21000087 | AF59: =AF42/$AF$47 -> 0.075641223 | AG59: =AG42/$AG$47 -> 0.078309979 | AH59: =AH42/$AH$47 -> 0.12123032 | AI59: =AI42/$AI$47 -> 0.40443044 | AJ59: =AJ42/$AJ$47 -> 0.20748991 | AK59: =AK42/$AK$47 -> 0.24584505 | AL59: =AL42/$AL$47 -> 0.030000087 | AP59: =AP42/$AP$47 -> 0.030949458 | AQ59: =AQ42/$AQ$47 -> 0.10101596 | AR59: =AR42/$AR$47 -> 0.11783452 | AS59: =AS42/$AS$47 -> 0.0010431902 | AT59: =AT42/$AT$47 -> 0.068169143 | AV59: =AV42/$AV$47 -> 0.0016661901 | AW59: =AW42/$AW$47 -> 0.0098435112 | AX59: =AX42/$AX$47 -> 0 | AY59: =AY42/$AY$47 -> 0.45361804 | AZ59: =AZ42/$AZ$47 -> 0.11845091 | BA59: =BA42/$BA$47 -> 0.17699987 | BB59: =BB42/$BB$47 -> 0 | BC59: =BC42/$BC$47 -> 0.035523544 | BD59: =BD42/$BD$47 -> 0.080000333 | BE59: =BE42/$BE$47 -> 0.028018797 | BF59: =BF42/$BF$47 -> 0.151522 | BG59: =BG42/$BG$47 -> 0.14000365 | BH59: =BH42/$BH$47 -> 0.19666541 | BI59: =BI42/$BI$47 -> 0 | BJ59: =BJ42/$BJ$47 -> 0.12220608 | BK59: =BK42/$BK$47 -> 0 | BL59: =BL42/$BL$47 -> 0.33996461 | BM59: =BM42/$BM$47 -> 0.10600136 | BN59: =BN42/$BN$47 -> 0.15599913 | BO59: =BO42/$BO$47 -> 0.19826101 | BP59: =BP42/$BP$47 -> 0.096987008 | BQ59: =BQ42/$BQ$47 -> 0 | BR59: =BR42/$BR$47 -> 0.15359703 | BS59: =BS42/$BS$47 -> 0.045961392 | BX59: =BX42/$BX$47 -> 0.084864166 | BY59: =BY42/$BY$47 -> 0.29999706 | BZ59: =BZ42/$BZ$47 -> 0 | CA59: =CA42/$CA$47 -> 0.1788108 | CB59: =CB42/$CB$47 -> 0.20310303 | CC59: =CC42/$CC$47 -> 0.04205291 | CD59: =CD42/$CD$47 -> 0.13321872 | CE59: =CE42/$CE$47 -> 0.15606198 | CF59: =CF42/$CF$47 -> 0.19960805 | CG59: =CG42/$CG$47 -> 0.13750873 | CK59: =CK42/$CK$47 -> 0.066805343 | CL59: =CL42/$CL$47 -> 0.03545923 | CM59: =CM42/$CM$47 -> 0.036589481 | CN59: =CN42/$CN$47 -> 0.099141077 | CO59: =CO42/$CO$47 -> 0.099744907 | CP59: =CP42/$CP$47 -> 0.25745495 | CQ59: =CQ42/$CQ$47 -> 0.056350603 | CU59: =CU42/$CU$47 -> 0 | CV59: =CV42/$CV$47 -> 0.0085318232 | CW59: =CW42/$CW$47 -> 0.031908023 | CX59: =CX42/$CX$47 -> 0.11388988 | CY59: =CY42/$CY$47 -> 0.036589481 | CZ59: =CZ42/$CZ$47 -> 0.021835371 | DA59: =DA42/$DA$47 -> 0.11890603 | DB59: =DB42/$DB$47 -> 0.29999896
A60: Industries | E60: =E43/$E$47 -> 0.05615768 | F60: =F43/$F$47 -> 0 | G60: =G43/$G$47 -> 0 | H60: =H43/$H$47 -> 0 | L60: =L43/$L$47 -> 0 | M60: =M43/$M$47 -> 0 | N60: =N43/$N$47 -> 0.12528442 | O60: =O43/$O$47 -> 0 | P60: =P43/$P$47 -> 0 | Q60: =Q43/$Q$47 -> 0 | R60: =R43/$R$47 -> 0.12942925 | S60: =S43/$S$47 -> 0 | T60: =T43/$T$47 -> 0 | U60: =U43/$U$47 -> 0 | V60: =V43/$V$47 -> 0 | W60: =W43/$W$47 -> 0 | X60: =X43/$X$47 -> 0 | Y60: =Y43/$Y$47 -> 0 | Z60: =Z43/$Z$47 -> 0 | AA60: =AA43/$AA$47 -> 0 | AB60: =AB43/$AB$47 -> 0 | AC60: =AC43/$AC$47 -> 0 | AD60: =AD43/$AD$47 -> 0 | AE60: =AE43/$AE$47 -> 0.049999233 | AF60: =AF43/$AF$47 -> 0 | AG60: =AG43/$AG$47 -> 0.039906331 | AH60: =AH43/$AH$47 -> 0.0015342836 | AI60: =AI43/$AI$47 -> 0 | AJ60: =AJ43/$AJ$47 -> 0 | AK60: =AK43/$AK$47 -> 0.083649171 | AL60: =AL43/$AL$47 -> 0 | AP60: =AP43/$AP$47 -> 0.020633199 | AQ60: =AQ43/$AQ$47 -> 0.0092531905 | AR60: =AR43/$AR$47 -> 0.0075939862 | AS60: =AS43/$AS$47 -> 0 | AT60: =AT43/$AT$47 -> 0 | AV60: =AV43/$AV$47 -> 0 | AW60: =AW43/$AW$47 -> 0.06589117 | AX60: =AX43/$AX$47 -> 0 | AY60: =AY43/$AY$47 -> 0 | AZ60: =AZ43/$AZ$47 -> 0 | BA60: =BA43/$BA$47 -> 0 | BB60: =BB43/$BB$47 -> 0.092210582 | BC60: =BC43/$BC$47 -> 0 | BD60: =BD43/$BD$47 -> 0 | BE60: =BE43/$BE$47 -> 0.0517662 | BF60: =BF43/$BF$47 -> 0.005715852 | BG60: =BG43/$BG$47 -> 0 | BH60: =BH43/$BH$47 -> 0.16096706 | BI60: =BI43/$BI$47 -> 0 | BJ60: =BJ43/$BJ$47 -> 0 | BK60: =BK43/$BK$47 -> 0 | BL60: =BL43/$BL$47 -> 0.13362542 | BM60: =BM43/$BM$47 -> 0 | BN60: =BN43/$BN$47 -> 0 | BO60: =BO43/$BO$47 -> 0 | BP60: =BP43/$BP$47 -> 0.064658068 | BQ60: =BQ43/$BQ$47 -> 0 | BR60: =BR43/$BR$47 -> 0 | BS60: =BS43/$BS$47 -> 0 | BX60: =BX43/$BX$47 -> 0 | BY60: =BY43/$BY$47 -> 0 | BZ60: =BZ43/$BZ$47 -> 0 | CA60: =CA43/$CA$47 -> 0 | CB60: =CB43/$CB$47 -> 0 | CC60: =CC43/$CC$47 -> 0 | CD60: =CD43/$CD$47 -> 0.00086709326 | CE60: =CE43/$CE$47 -> 0 | CF60: =CF43/$CF$47 -> 0 | CG60: =CG43/$CG$47 -> 0 | CK60: =CK43/$CK$47 -> 0 | CL60: =CL43/$CL$47 -> 0.0010321484 | CM60: =CM43/$CM$47 -> 0 | CN60: =CN43/$CN$47 -> 0.018469657 | CO60: =CO43/$CO$47 -> 0 | CP60: =CP43/$CP$47 -> 0.0017091697 | CQ60: =CQ43/$CQ$47 -> 4.8537953e-05 | CU60: =CU43/$CU$47 -> 0 | CV60: =CV43/$CV$47 -> 0.00069623775 | CW60: =CW43/$CW$47 -> 0 | CX60: =CX43/$CX$47 -> 0 | CY60: =CY43/$CY$47 -> 0 | CZ60: =CZ43/$CZ$47 -> 0.00031870589 | DA60: =DA43/$DA$47 -> 0 | DB60: =DB43/$DB$47 -> 0.024501096
A61: Kiosks | E61: =E44/$E$47 -> 0.001855531 | F61: =F44/$F$47 -> 0.0018321367 | G61: =G44/$G$47 -> 0.00050423558 | H61: =H44/$H$47 -> 0.019999102 | L61: =L44/$L$47 -> 0.0068424095 | M61: =M44/$M$47 -> 0 | N61: =N44/$N$47 -> 0 | O61: =O44/$O$47 -> 0.015535435 | P61: =P44/$P$47 -> 0.0081439593 | Q61: =Q44/$Q$47 -> 0.18492796 | R61: =R44/$R$47 -> 0.22970134 | S61: =S44/$S$47 -> 0.00021229463 | T61: =T44/$T$47 -> 0.0009998916 | U61: =U44/$U$47 -> 0 | V61: =V44/$V$47 -> 0 | W61: =W44/$W$47 -> 0.0099990837 | X61: =X44/$X$47 -> 0.0013862095 | Y61: =Y44/$Y$47 -> 0.015039068 | Z61: =Z44/$Z$47 -> 0.010000365 | AA61: =AA44/$AA$47 -> 0.015288584 | AB61: =AB44/$AB$47 -> 0.001308431 | AC61: =AC44/$AC$47 -> 0.0022571841 | AD61: =AD44/$AD$47 -> 7.2096377e-05 | AE61: =AE44/$AE$47 -> 0 | AF61: =AF44/$AF$47 -> 0.0062810426 | AG61: =AG44/$AG$47 -> 0 | AH61: =AH44/$AH$47 -> 0.00015342836 | AI61: =AI44/$AI$47 -> 0.00092539041 | AJ61: =AJ44/$AJ$47 -> 0.0029399181 | AK61: =AK44/$AK$47 -> 0.001037544 | AL61: =AL44/$AL$47 -> 0.00099961067 | AP61: =AP44/$AP$47 -> 0.065903876 | AQ61: =AQ44/$AQ$47 -> 0.011911285 | AR61: =AR44/$AR$47 -> 0.066609756 | AS61: =AS44/$AS$47 -> 0 | AT61: =AT44/$AT$47 -> 0.15105222 | AV61: =AV44/$AV$47 -> 0.0017606818 | AW61: =AW44/$AW$47 -> 0.0057257654 | AX61: =AX44/$AX$47 -> 0 | AY61: =AY44/$AY$47 -> 0.030395664 | AZ61: =AZ44/$AZ$47 -> 0.011283799 | BA61: =BA44/$BA$47 -> 0.0019988524 | BB61: =BB44/$BB$47 -> 0.0087006201 | BC61: =BC44/$BC$47 -> 0.0051594281 | BD61: =BD44/$BD$47 -> 0.019925341 | BE61: =BE44/$BE$47 -> 0.041044576 | BF61: =BF44/$BF$47 -> 0.067820771 | BG61: =BG44/$BG$47 -> 0.019998783 | BH61: =BH44/$BH$47 -> 0.029282167 | BI61: =BI44/$BI$47 -> 0.15914192 | BJ61: =BJ44/$BJ$47 -> 0.2085891 | BK61: =BK44/$BK$47 -> 0.070309176 | BL61: =BL44/$BL$47 -> 0.036943693 | BM61: =BM44/$BM$47 -> 0.019999197 | BN61: =BN44/$BN$47 -> 0.039994214 | BO61: =BO44/$BO$47 -> 0.070246334 | BP61: =BP44/$BP$47 -> 0.11444179 | BQ61: =BQ44/$BQ$47 -> 0 | BR61: =BR44/$BR$47 -> 0.030721325 | BS61: =BS44/$BS$47 -> 0.017027679 | BX61: =BX44/$BX$47 -> 0 | BY61: =BY44/$BY$47 -> 0.010001249 | BZ61: =BZ44/$BZ$47 -> 0.002934662 | CA61: =CA44/$CA$47 -> 0.034362704 | CB61: =CB44/$CB$47 -> 0.060347042 | CC61: =CC44/$CC$47 -> 0.00069518479 | CD61: =CD44/$CD$47 -> 0.0082262836 | CE61: =CE44/$CE$47 -> 0.038555382 | CF61: =CF44/$CF$47 -> 0.0041902315 | CG61: =CG44/$CG$47 -> 0.0046040576 | CK61: =CK44/$CK$47 -> 0.013517262 | CL61: =CL44/$CL$47 -> 0.01729228 | CM61: =CM44/$CM$47 -> 0.0045714197 | CN61: =CN44/$CN$47 -> 0.0099253354 | CO61: =CO44/$CO$47 -> 0.0046993082 | CP61: =CP44/$CP$47 -> 0.060664049 | CQ61: =CQ44/$CQ$47 -> 0.22062706 | CU61: =CU44/$CU$47 -> 0 | CV61: =CV44/$CV$47 -> 0.033698839 | CW61: =CW44/$CW$47 -> 0.08658062 | CX61: =CX44/$CX$47 -> 0.017343854 | CY61: =CY44/$CY$47 -> 0.0045714197 | CZ61: =CZ44/$CZ$47 -> 0.31412349 | DA61: =DA44/$DA$47 -> 0.050422377 | DB61: =DB44/$DB$47 -> 0.0081665347
