Workbook
Name DBDef1: #REF!
Name DBDef2: #REF!
Name DBDef2a: #REF!
Name DBDef3: #REF!
Name DBLinks: #REF!
Name dbsourcefiles: #REF!
Name FinalUse: #REF!
Name Input_A: #REF!
Name Output: #REF!
Name Prod_acc: #REF!
Name Supply: #REF!
Name TabDef1: #REF!
Name TabDef2: #REF!
Name TabDef3: #REF!
Name TabDef4: #REF!

Sheet Cover Page
F4: Kenya Water Accounts V2
J9: 20-06-2025
J11: Prepared For:
J24: Prepared By:
J35: Contact People:
I37: Bernice Macquela b.macquela@primeafrica.net | L37: Jackie Crafford j.crafford@primeafrica.net

Sheet Colour coding
B2: Data Cell Colour Codes within Water Accounts
B3: White | C3: Expected empty cells
B4: Green | C4: Official statistics from KNBS and other government departments
B5: Light Green | C5: Data estimates by KNBS and other government departments based on official statistics
B6: Orange | C6: Data derived from Green and Light Green statistics
B7: Red | C7: Literature estimates
B9: Data Text Colour Codes within Water Accounts
B10: Black Text | C10: Calculations
B11: Blue Text | C11: Data entered from data input sources
B12: Red Text | C12: Work in progress
B14: Tab Colour Codes within Water Accounts
B15: Yellow | C15: Work in progress
B16: Data Inputs | C16: Data entered from data input sources
B17: Output Tables | C17: Water IO tables and SUTs
B18: 2022 Output Tables | C18: Problematic Data, Recommend not to publish

Sheet Notes to Water Accounts
D3: Notes
C4: 1 | D4: This spreadsheet contains comments using the Excel comment function.The comments report on data problems identified, any key assumptions made, and other matters that need clarification.
C5: 2 | D5: These accounts were constructed using data reported for the Kenya government financial year which is from July to June. Key Data sources were from the Water Resources Authority (WRA) and WASREB. This data is available for 2021 and 2023. Some data is available for 2022 however, WRA data was reported on a calendar year basis, and in addition is not a full dataset as a result of a data loss that occured during a database migration in 2022.
C6: 3 | D6: For the reasons explained above the 2022 water SUT data is problematic and we recommend against it's publication.
C7: 4 | D7: The Irrigation data received from the WRA does not include all the irrigation schemes therefore this still needs to be reconciled with all the hectares of irrigated land within the country. This is still work in progress
C8: 5 | D8: Sewerage treatment data is problematic. The data is reported by WASREB. The 2021 WASREB data appears most comprehensive, and for this reason we used the 2021 WASREB sewerage volumes because for the 2023 SUT.
C9: 6 | D9: The 2023 WRA data reports an extremely high Household surface water value, and is likely erroneous. Needs verification from WRA.
C10: 7 | D10: Different datasets sourced from WRA reported vast differences in hydropower water requirements, varying by an order of magnitude. The values used, were the lower end values as reported officially on the WRA website.

Sheet Metadata and definitions 
B2: Data Sources
A3: 1 | B3: Water Resources Authority (WRA) Data for 2021-2023 - Database download received from WRA with data summarised by calendar year
A4: 2 | B4: Water Resources Authority (WRA) Data for 2021 & 2023 - data sourced from their performance reports
A5: 3 | B5: Water Services Regualtory Board (WASREB) Data for 2021-2023
A6: 4 | B6: National Irrigation Authority (NIA) Irrigation Data was received (not yet incorporated into the SUTs)
B10: Definitions
A11: 1 | B11: Non-Revenue Water | C11: Unbilled use by governmnet, water losses, water theft, water billed but not paid for

Sheet NIA Irrigation Data
A1: ANNUAL CROP PRODUCTION AND WATER USE DATA - PUBLIC IRRIGATION SCHEMES
E2: 2024 | K2: 2023 | N2: 2022 | Q2: 2021
B3: Irrigation Scheme | C3: County | D3: Crops | E3: Volume of Water Use (cubic meters) | F3: Area Cropped (acres) | G3: Area in Hectares | H3: Production (Tonnes) | I3: Volume of Use per Hectare | J3: Volume of Water use per production | K3: Volume of Water Use (cubic meters) | L3: Area Cropped (acres) | M3: Production (Tonnes) | N3: Volume of Water Use (cubic meters) | O3: Area Cropped (acres) | P3: Production (Tonnes) | Q3: Volume of Water Use (cubic meters) | R3: Area Cropped (acres) | S3: Production (Tonnes)
A4: 1 | B4: Mwea | C4: Kirinyaga | D4: Rice
B5: Main season 1 | E5: 143664192 | F5: 26485 | G5: =F5*$C$36 -> 10718.109 | H5: 66848 | I5: =E5/G5 -> 13403.875 | J5: =E5/H5 -> 2149.1173 | K5: 182492352 | L5: 26310 | M5: 66741 | N5: 133791264 | O5: 30600 | P5: 68268 | Q5: 152127496 | R5: 28100 | S5: 60282
B6: Crop season 2 | E6: 91971936 | F6: 26485 | G6: =F6*$C$36 -> 10718.109 | H6: 52239 | I6: =E6/G6 -> 8580.9856 | J6: =E6/H6 -> 1760.5991 | K6: 116829236 | L6: 26310 | M6: 18200 | N6: 78032160 | O6: 10000 | P6: 21492 | Q6: 86196960 | R6: 10492 | S6: 26200
B7: Ratoon | E7: 60419520 | F7: 26485 | G7: =F7*$C$36 -> 10718.109 | H7: 41120 | I7: =E7/G7 -> 5637.1438 | J7: =E7/H7 -> 1469.3463 | K7: 76749120 | L7: 26310 | M7: 33024 | N7: 45747072 | O7: 30600 | P7: 42000 | Q7: 47316096 | R7: 28100 | S7: 31000
A8: 2 | B8: Tana | C8: Tana River | D8: Rice, Maize
B9: Main season 1 | E9: 6158592 | F9: 3361 | G9: =F9*$C$36 -> 1360.1496 | H9: 6771 | I9: =E9/G9 -> 4527.8783 | J9: =E9/H9 -> 909.55428 | K9: 4800286 | L9: 2856 | M9: 4773 | N9: 2983168 | O9: 1084 | Q9: 476096 | R9: 173 | S9: 468
B10: Crop season 2 | E10: 3890240 | F10: 1989 | G10: =F10*$C$36 -> 804.92045 | H10: 3788 | J10: =E10/H10 -> 1026.9905 | K10: 2323443 | L10: 1268 | M10: 2155 | N10: 2064836 | O10: 987
B11: Ratoon
A12: 3 | B12: Bura | C12: Tana River | D12: Rice, Maize
B13: Main season 1 | E13: 29450328 | F13: 4200 | G13: =F13*$C$36 -> 1699.6812 | H13: 10940 | K13: 26763880 | L13: 4200 | M13: 11608 | N13: 5936866.4 | O13: 1987 | P13: 4967.5 | Q13: 5013619.4 | R13: 1678 | S13: 4195
B14: Crop season 2 | E14: 24465758 | F14: 2100 | G14: =F14*$C$36 -> 849.8406 | H14: 5764 | K14: 16095240 | L14: 2100 | M14: 4964 | N14: NIL | Q14: NIL
B15: Ratoon | N15: 5277214.6 | O15: 1987 | P15: 3170.2 | Q15: 4456550.6 | R15: 1678 | S15: 2684.8
A16: 4 | B16: Perkerra | C16: Baringo | D16: Maize
B17: Main season 1 | E17: 4950000 | F17: 1650 | G17: =F17*$C$36 -> 667.7319 | H17: 3600 | I17: =E17/G17 -> 7413.1549 | J17: =E17/H17 -> 1375 | K17: 4500000 | L17: 1500 | M17: 3200 | N17: 5000000 | O17: 2500 | P17: 4200 | Q17: 4400000 | R17: 2200
B18: Crop season 2 | E18: 1500000 | F18: 1250 | G18: =F18*$C$36 -> 505.8575 | H18: 550 | I18: =E18/G18 -> 2965.262 | J18: =E18/H18 -> 2727.2727 | K18: 1200000 | L18: 1000 | M18: 410 | N18: 900000 | O18: 750 | P18: 320 | Q18: 600000 | R18: 500
B19: Ratoon
A20: 5 | B20: Ahero | C20: Kisumu | D20: Rice
B21: Main season 1 | E21: 6870657 | F21: 2168 | G21: =F21*C36 -> 877.35925 | H21: 6829.2 | I21: =E21/G21 -> 7831.0647 | J21: =E21/H21 -> 1006.0705 | K21: 6621849 | L21: 2168 | M21: 7804.8 | N21: 6314083.2 | O21: 2168 | P21: 6070.4 | Q21: 6314083.2 | R21: 2168 | S21: 6937.6
B22: Crop season 2 | F22: 146 | H22: 275.94
B23: Ratoon
A24: 6 | B24: West Kano | C24: Kisumu | D24: Rice
B25: Main season 1 | E25: 5179300 | F25: 1550 | G25: =F25*$C$36 -> 627.2633 | H25: 4550.4 | I25: =E25/G25 -> 8256.9792 | J25: =E25/H25 -> 1138.2076 | K25: 5868320 | L25: 2055 | M25: 5797 | N25: 5899056 | O25: 2083 | P25: 6561.45 | Q25: 3738240 | R25: 1320 | S25: 3214
B26: Crop season 2 | N26: 801456 | O26: 283 | P26: 636750
B27: Ratoon
A28: 7 | B28: Bunyala | C28: Busia/Siaya | D28: Rice
B29: Main season 1 | E29: 4403442.4 | F29: 3126 | G29: =F29*$C$36 -> 1265.0484 | H29: 10467 | I29: =E29/G29 -> 3480.8489 | J29: =E29/H29 -> 420.69766 | K29: 4561768.8 | L29: 3126 | M29: 10324 | N29: =774882+900360+1092780+932580+692982+1003086 -> 5396670 | O29: 3226 | P29: 13024.9 | Q29: =908298+675684+689874+270270+499122+790668 -> 3833916 | R29: 2454 | S29: 7771.2
B30: Crop season 2 | E30: 5283863.4 | K30: 3993196.6 | N30: =1085562+512424+494134+536677.02+401098.5+652742.64 -> 3682638.2 | O30: 376 | Q30: =1113984+1381968+841068+906354+1026018+1178892 -> 6448284
B31: Ratoon
B32: Ratoon
B33: Total | E33: =SUM(E5:E32) -> 3.8820783e+08 | F33: =SUM(F5:F32) -> 100995 | N33: =SUM(N5:N30) -> 3.0182648e+08 | O33: =SUM(O5:O30) -> 88631 | Q33: =SUM(Q5:Q32) -> 3.2092134e+08 | R33: =SUM(R5:R32) -> 78863
B35: Acres | C35: Hectares | D35: Source
B36: 1 | C36: 0.404686 | D36: Google Calculator as at 20.06.2022

Sheet Irrigation Calculations
A1: Data Source | B1: Source: Economic Survey 2023 | I1: Source: Economic Survey 2023 | P1: Source: Economic Survey 2023
A2: Year | B2: 2021 | F2: Alternative estimate | I2: 2022 | M2: Alternative estimate | P2: 2023 | T2: Alternative estimate
A3: Crops Produced | B3: Volume Produced (in tonnes) | C3: In Kgs | D3: Average Water Use per ton (m3) | F3: Area under crop production (acres) | G3: Ave water use (m3/acre) | H3: Water Use m3 | I3: Volume Produced (in tonnes) | J3: In Kgs | K3: Average Water Use per Kg (litre per Kg) | M3: Area under crop production (acres) | N3: Ave water use (m3/acre) | O3: Water Use m3 | P3: Volume Produced (in tonnes) | Q3: In Kgs | R3: Average Water Use per Kg (litre per Kg) | T3: Area under crop production (acres) | U3: Ave water use (m3/acre) | V3: Water Use m3
A4: Rice - Irrigation | B4: ='[3]Table 7.15'!$F$24 -> 186000 | C4: =B4*[2]Notes!$B$68 -> 186000000 | D4: =AVERAGE('NIA Irrigation Data'!J5:J7,'NIA Irrigation Data'!J21,'NIA Irrigation Data'!J25,'NIA Irrigation Data'!J29) -> 1324.0064 | E4: =D4*C4 -> 2.4626519e+11 | H4: =E4/[2]Notes!$B$69 -> 2.4626519e+08 | I4: ='[3]Table 7.15'!$G$24 -> 192299 | J4: =I4*[2]Notes!$B$68 -> 192299000 | K4: =[2]Notes!I47 -> 0 | L4: =K4*J4 -> 0 | O4: =L4/[2]Notes!$B$69 -> 0 | P4: ='[3]Table 7.15'!$H$24 -> 229064 | Q4: =P4*[2]Notes!$B$68 -> 229064000 | R4: =[2]Notes!P47 -> 0 | S4: =R4*Q4 -> 0 | V4: =S4/[2]Notes!$B$69 -> 0
A5: Cut Flowers | B5: 210100 | C5: =B5*[2]Notes!$B$68 -> 210100000 | D5: =[2]Notes!B49 -> 2800 | E5: =D5*C5 -> 588280000000 | H5: =E5/[2]Notes!$B$69 -> 588280000 | I5: 202900 | J5: =I5*[2]Notes!$B$68 -> 202900000 | K5: =[2]Notes!I49 -> 0 | L5: =K5*J5 -> 0 | O5: =L5/[2]Notes!$B$69 -> 0 | P5: 221100 | Q5: =P5*[2]Notes!$B$68 -> 221100000 | R5: =[2]Notes!P49 -> 0 | S5: =R5*Q5 -> 0 | V5: =S5/[2]Notes!$B$69 -> 0
A6: Fruits | B6: 117300 | C6: =B6*[2]Notes!$B$68 -> 117300000 | D6: =[2]Notes!B51 -> 748 | E6: =D6*C6 -> 87740400000 | H6: =E6/[2]Notes!B69 -> 87740400 | I6: 113300 | J6: =I6*[2]Notes!$B$68 -> 113300000 | K6: =[2]Notes!I51 -> 0 | L6: =K6*J6 -> 0 | O6: =L6/[2]Notes!I69 -> #DIV/0! | P6: 131000 | Q6: =P6*[2]Notes!$B$68 -> 131000000 | R6: =[2]Notes!P51 -> 0 | S6: =R6*Q6 -> 0 | V6: =S6/[2]Notes!P69 -> #DIV/0!
A7: Vegetables | B7: 78100 | C7: =B7*[2]Notes!$B$68 -> 78100000 | D7: =[2]Notes!B50 -> 336 | E7: =D7*C7 -> 26241600000 | H7: =E7/[2]Notes!B69 -> 26241600 | I7: 75400 | J7: =I7*[2]Notes!$B$68 -> 75400000 | K7: =[2]Notes!I50 -> 0 | L7: =K7*J7 -> 0 | O7: =L7/[2]Notes!I69 -> #DIV/0! | P7: 78100 | Q7: =P7*[2]Notes!$B$68 -> 78100000 | R7: =[2]Notes!P50 -> 0 | S7: =R7*Q7 -> 0 | V7: =S7/[2]Notes!P69 -> #DIV/0!
A8: [Add new crop]
A9: [Add new crop]
A10: [Add new crop]
A11: [Add new crop]
A12: [Add new crop]
A13: [Add new crop]
A14: [Add new crop]
A15: [Add new crop]
B16: Total | H16: =SUM(H4:H7) -> 9.4852719e+08 | I16: Total | O16: =SUM(O4:O7) -> #DIV/0! | P16: Total | V16: =SUM(V4:V7) -> #DIV/0!

Sheet WRA Report Data
A1: Water use up to June 2023 (1000 m3/day)
A2: Basin | B2: Public_SW | C2: Public_GW | D2: Domestic_SW | E2: Domestic_GW | F2: Livestock_SW | G2: Livestock_GW | H2: Irrigation_SW | I2: Irrigation_GW | J2: Industrial_SW | K2: Industrial_GW | L2: Power_SW | M2: Power_GW | N2: Other_SW | O2: Other_GW | P2: Total
A3: LVN | B3: 134.62 | C3: 0.9325 | D3: 5526.04 | E3: 16.78 | F3: 2.03 | G3: 0.235 | H3: 11.4 | I3: 0.3 | J3: 224.45 | K3: 0.232 | L3: 411 | M3: 0 | N3: 12.466 | O3: 0.18 | P3: =SUM(B3:O3) -> 6340.6655
A4: LVS | B4: 104.84 | C4: 0.232 | D4: 7.192 | E4: 6.521 | F4: 0.102 | G4: 0.085 | H4: 17.546 | I4: 0.306 | J4: 24.63 | K4: 0.32 | L4: 2836.644 | M4: 0 | N4: 1.906 | O4: 0.09 | P4: =SUM(B4:O4) -> 3000.414
A5: RV | B5: 13.804 | C5: 65.111 | D5: 18.518 | E5: 26.464 | F5: 3.741 | G5: 2.479 | H5: 100.152 | I5: 268.269 | J5: 12.174 | K5: 3.334 | L5: 1658.509 | M5: 1.52 | N5: 13.06 | O5: 18.364 | P5: =SUM(B5:O5) -> 2205.499
A6: Athi | B6: 88.788 | C6: 60.364 | D6: 12.141 | E6: 111.543 | F6: 0.165 | G6: 2.819 | H6: 299.482 | I6: 33.984 | J6: 38.71 | K6: 33.91 | L6: 0.07 | M6: 1.48 | N6: 1.06 | O6: 1.854 | P6: =SUM(B6:O6) -> 686.37
A7: Tana | B7: 408.68 | C7: 107 | D7: 490.943 | E7: 108.184 | F7: 3.829 | G7: 1.82 | H7: 952.148 | I7: 2.2 | J7: 12.2 | K7: 0.16 | L7: 806.36 | M7: 0 | N7: 60.15 | O7: 1.1 | P7: =SUM(B7:O7) -> 2954.774
A8: ENN | B8: 31.233 | C8: 2.241 | D8: 61.898 | E8: 10.52 | F8: 8.32 | G8: 1.38 | H8: 116.92 | I8: 228.693 | J8: 1.068 | K8: 0.18 | L8: 0.07 | M8: 4.4 | N8: 5.715 | O8: 0 | P8: =SUM(B8:O8) -> 472.638
A9: Total | B9: =SUM(B3:B8) -> 781.965 | C9: =SUM(C3:C8) -> 235.8805 | D9: =SUM(D3:D8) -> 6116.732 | E9: =SUM(E3:E8) -> 280.012 | F9: =SUM(F3:F8) -> 18.187 | G9: =SUM(G3:G8) -> 8.818 | H9: =SUM(H3:H8) -> 1497.648 | I9: =SUM(I3:I8) -> 533.752 | ... P9: =SUM(P3:P8) -> 15660.361
A11: 2023 Water Use in Yearly Values (m3/year)
A12: Basin | B12: Public_SW | C12: Public_GW | D12: Domestic_SW | E12: Domestic_GW | F12: Livestock_SW | G12: Livestock_GW | H12: Irrigation_SW | I12: Irrigation_GW | J12: Industrial_SW | K12: Industrial_GW | L12: Power_SW | M12: Power_GW | N12: Other_SW | O12: Other_GW | P12: Total
A13: LVN | B13: =(B3*1000)*365 -> 49136300 | C13: =(C3*1000)*365 -> 340362.5 | D13: =(D3*1000)*365 -> 2017004600 | E13: =(E3*1000)*365 -> 6124700 | F13: =(F3*1000)*365 -> 740950 | G13: =(G3*1000)*365 -> 85775 | H13: =(H3*1000)*365 -> 4161000 | I13: =(I3*1000)*365 -> 109500 | ... O13: =(O3*1000)*365 -> 65700 | P13: =SUM(B13:O13) -> 2.3143429e+09
A14: LVS | B14: =(B4*1000)*365 -> 38266600 | C14: =(C4*1000)*365 -> 84680 | D14: =(D4*1000)*365 -> 2625080 | E14: =(E4*1000)*365 -> 2380165 | F14: =(F4*1000)*365 -> 37230 | G14: =(G4*1000)*365 -> 31025 | H14: =(H4*1000)*365 -> 6404290 | I14: =(I4*1000)*365 -> 111690 | ... O14: =(O4*1000)*365 -> 32850 | P14: =SUM(B14:O14) -> 1095151110
A15: RV | B15: =(B5*1000)*365 -> 5038460 | C15: =(C5*1000)*365 -> 23765515 | D15: =(D5*1000)*365 -> 6759070 | E15: =(E5*1000)*365 -> 9659360 | F15: =(F5*1000)*365 -> 1365465 | G15: =(G5*1000)*365 -> 904835 | H15: =(H5*1000)*365 -> 36555480 | I15: =(I5*1000)*365 -> 97918185 | ... O15: =(O5*1000)*365 -> 6702860 | P15: =SUM(B15:O15) -> 805007135
A16: Athi | B16: =(B6*1000)*365 -> 32407620 | C16: =(C6*1000)*365 -> 22032860 | D16: =(D6*1000)*365 -> 4431465 | E16: =(E6*1000)*365 -> 40713195 | F16: =(F6*1000)*365 -> 60225 | G16: =(G6*1000)*365 -> 1028935 | H16: =(H6*1000)*365 -> 109310930 | I16: =(I6*1000)*365 -> 12404160 | ... O16: =(O6*1000)*365 -> 676710 | P16: =SUM(B16:O16) -> 250525050
A17: Tana | B17: =(B7*1000)*365 -> 149168200 | C17: =(C7*1000)*365 -> 39055000 | D17: =(D7*1000)*365 -> 179194195 | E17: =(E7*1000)*365 -> 39487160 | F17: =(F7*1000)*365 -> 1397585 | G17: =(G7*1000)*365 -> 664300 | H17: =(H7*1000)*365 -> 347534020 | I17: =(I7*1000)*365 -> 803000 | ... O17: =(O7*1000)*365 -> 401500 | P17: =SUM(B17:O17) -> 1078492510
A18: ENN | B18: =(B8*1000)*365 -> 11400045 | C18: =(C8*1000)*365 -> 817965 | D18: =(D8*1000)*365 -> 22592770 | E18: =(E8*1000)*365 -> 3839800 | F18: =(F8*1000)*365 -> 3036800 | G18: =(G8*1000)*365 -> 503700 | H18: =(H8*1000)*365 -> 42675800 | I18: =(I8*1000)*365 -> 83472945 | ... O18: =(O8*1000)*365 -> 0 | P18: =SUM(B18:O18) -> 172512870
A19: Total | B19: =SUM(B13:B18) -> 285417225 | C19: =SUM(C13:C18) -> 86096382 | D19: =SUM(D13:D18) -> 2232607180 | E19: =SUM(E13:E18) -> 102204380 | F19: =SUM(F13:F18) -> 6638255 | G19: =SUM(G13:G18) -> 3218570 | H19: =SUM(H13:H18) -> 546641520 | I19: =SUM(I13:I18) -> 194819480 | ... P19: =SUM(P13:P18) -> 5.7160316e+09
A23: Calculations of Values for Industry, Domestic, Public and Other own supply values outside of WASREB supply
A24: Sector | B24: Surface Water | C24: % of total | D24: Derived Own Supply (% of Water left after WASREB deduction)
A25: Industrial | B25: =J19 -> 114329680 | C25: =B25/$B$29 -> 0.042871577 | D25: =($B$29-$B$31)*C25 -> 94886040
A26: Public | B26: =B19 -> 285417225 | C26: =B26/$B$29 -> 0.10702633 | D26: =($B$29-$B$31)*C26 -> 2.3687734e+08
A27: Domestic | B27: =D19 -> 2232607180 | C27: =B27/$B$29 -> 0.83718759 | D27: =($B$29-$B$31)*C27 -> 1.8529157e+09
A28: Other | B28: =N19 -> 34440305 | C28: =B28/$B$29 -> 0.012914496 | D28: =($B$29-$B$31)*C28 -> 28583165
A29: Total | B29: =SUM(B25:B28) -> 2666794390
A31: WASREB Total | B31: =SUM('Ph IO Table 2023'!H4) -> 4.5353219e+08
A32: Total | B32: =SUM(B19:E19,J19:K19,N19:O19) -> 2.8768944e+09
A35: Water Use Up to June 2021 (1000 m3/day)
A36: Basin | B36: Public_SW | C36: Public_GW | D36: Domestic_SW | E36: Domestic_GW | F36: Livestock_SW | G36: Livestock_GW | H36: Irrigation_SW | I36: Irrigation_GW | J36: Industrial_SW | K36: Industrial_GW | L36: Power_SW | M36: Power_GW | N36: Other_SW | O36: Other_GW | P36: Total
A37: LVN | B37: 88.15 | C37: 0.92 | D37: 10.04 | E37: 16.29 | F37: 2.03 | G37: 0.23 | H37: 11.1 | I37: 0.29 | J37: 123.3 | K37: 0.23 | L37: 411.5 | M37: 0 | N37: 12.4 | O37: 0.18 | P37: =SUM(B37:O37) -> 676.66
A38: LVS | B38: 104.75 | C38: 0.23 | D38: 6.64 | E38: 6.04 | F38: 0.012 | G38: 0.08 | H38: 17.14 | I38: 0.12 | J38: 24.12 | K38: 0.31 | L38: 2646.5 | M38: 0.01 | N38: 1.9 | O38: 0.09 | P38: =SUM(B38:O38) -> 2807.942
A39: RV | B39: 8.61 | C39: 64.5 | D39: 5.75 | E39: 22.8 | F39: 3.6 | G39: 1.9 | H39: 55.04 | I39: 202.24 | J39: 3.24 | K39: 0.47 | L39: 1657.9 | M39: 0.32 | N39: 6.18 | O39: 8 | P39: =SUM(B39:O39) -> 2040.55
A40: Athi | B40: 84.2 | C40: 60 | D40: 12 | E40: 102.33 | F40: 0.16 | G40: 2.44 | H40: 288.14 | I40: 31.16 | J40: 38.33 | K40: 31.4 | L40: 0.07 | M40: 1.48 | N40: 1.06 | O40: 1.75 | P40: =SUM(B40:O40) -> 654.52
A41: Tana | B41: 407.8 | C41: 10.7 | D41: 488.2 | E41: 10.7 | F41: 3.7 | G41: 1.8 | H41: 934.9 | I41: 1.9 | J41: 12.1 | K41: 0.14 | L41: 806.28 | M41: 0 | N41: 60.1 | O41: 1.1 | P41: =SUM(B41:O41) -> 2739.42
A42: ENN | B42: 30.6 | C42: 2.23 | D42: 45.3 | E42: 8.7 | F42: 6.5 | G42: 0.99 | H42: 101.9 | I42: 22 | J42: 4.4 | K42: 0.71 | L42: 0.07 | M42: 4.4 | N42: 0.165 | O42: 0 | P42: =SUM(B42:O42) -> 227.965
A43: Total | B43: =SUM(B37:B42) -> 724.11 | C43: =SUM(C37:C42) -> 138.58 | D43: =SUM(D37:D42) -> 567.93 | E43: =SUM(E37:E42) -> 166.86 | F43: =SUM(F37:F42) -> 16.002 | G43: =SUM(G37:G42) -> 7.44 | H43: =SUM(H37:H42) -> 1408.22 | I43: =SUM(I37:I42) -> 257.71 | ... P43: =SUM(P37:P42) -> 9147.057
A45: 2021 Water Use in Yearly Values (m3/year)
A46: Basin | B46: Public_SW | C46: Public_GW | D46: Domestic_SW | E46: Domestic_GW | F46: Livestock_SW | G46: Livestock_GW | H46: Irrigation_SW | I46: Irrigation_GW | J46: Industrial_SW | K46: Industrial_GW | L46: Power_SW | M46: Power_GW | N46: Other_SW | O46: Other_GW | P46: Total
A47: LVN | B47: =(B37*1000)*365 -> 32174750 | C47: =(C37*1000)*365 -> 335800 | D47: =(D37*1000)*365 -> 3664600 | E47: =(E37*1000)*365 -> 5945850 | F47: =(F37*1000)*365 -> 740950 | G47: =(G37*1000)*365 -> 83950 | H47: =(H37*1000)*365 -> 4051500 | I47: =(I37*1000)*365 -> 105850 | ... O47: =(O37*1000)*365 -> 65700 | P47: =SUM(B47:O47) -> 246980900
A48: LVS | B48: =(B38*1000)*365 -> 38233750 | C48: =(C38*1000)*365 -> 83950 | D48: =(D38*1000)*365 -> 2423600 | E48: =(E38*1000)*365 -> 2204600 | F48: =(F38*1000)*365 -> 4380 | G48: =(G38*1000)*365 -> 29200 | H48: =(H38*1000)*365 -> 6256100 | I48: =(I38*1000)*365 -> 43800 | ... O48: =(O38*1000)*365 -> 32850 | P48: =SUM(B48:O48) -> 1024898830
A49: RV | B49: =(B39*1000)*365 -> 3142650 | C49: =(C39*1000)*365 -> 23542500 | D49: =(D39*1000)*365 -> 2098750 | E49: =(E39*1000)*365 -> 8322000 | F49: =(F39*1000)*365 -> 1314000 | G49: =(G39*1000)*365 -> 693500 | H49: =(H39*1000)*365 -> 20089600 | I49: =(I39*1000)*365 -> 73817600 | ... O49: =(O39*1000)*365 -> 2920000 | P49: =SUM(B49:O49) -> 744800750
A50: Athi | B50: =(B40*1000)*365 -> 30733000 | C50: =(C40*1000)*365 -> 21900000 | D50: =(D40*1000)*365 -> 4380000 | E50: =(E40*1000)*365 -> 37350450 | F50: =(F40*1000)*365 -> 58400 | G50: =(G40*1000)*365 -> 890600 | H50: =(H40*1000)*365 -> 105171100 | I50: =(I40*1000)*365 -> 11373400 | ... O50: =(O40*1000)*365 -> 638750 | P50: =SUM(B50:O50) -> 238899800
A51: Tana | B51: =(B41*1000)*365 -> 148847000 | C51: =(C41*1000)*365 -> 3905500 | D51: =(D41*1000)*365 -> 178193000 | E51: =(E41*1000)*365 -> 3905500 | F51: =(F41*1000)*365 -> 1350500 | G51: =(G41*1000)*365 -> 657000 | H51: =(H41*1000)*365 -> 341238500 | I51: =(I41*1000)*365 -> 693500 | ... O51: =(O41*1000)*365 -> 401500 | P51: =SUM(B51:O51) -> 999888300
A52: ENN | B52: =(B42*1000)*365 -> 11169000 | C52: =(C42*1000)*365 -> 813950 | D52: =(D42*1000)*365 -> 16534500 | E52: =(E42*1000)*365 -> 3175500 | F52: =(F42*1000)*365 -> 2372500 | G52: =(G42*1000)*365 -> 361350 | H52: =(H42*1000)*365 -> 37193500 | I52: =(I42*1000)*365 -> 8030000 | ... O52: =(O42*1000)*365 -> 0 | P52: =SUM(B52:O52) -> 83207225
A53: Total | B53: =SUM(B47:B52) -> 264300150 | C53: =SUM(C47:C52) -> 50581700 | D53: =SUM(D47:D52) -> 207294450 | E53: =SUM(E47:E52) -> 60903900 | F53: =SUM(F47:F52) -> 5840730 | G53: =SUM(G47:G52) -> 2715600 | H53: =SUM(H47:H52) -> 514000300 | I53: =SUM(I47:I52) -> 94064150 | ... P53: =SUM(P47:P52) -> 3338675805
A57: Calculations of Values for Industry, Domestic, Public and Other own supply values outside of WASREB supply
A60: Sector | B60: Ground Water Use | C60: % of Total | D60: Derived own use of Groundwater | E60: Surface Water Use | F60: % of total | G60: Derived own use for Surface water
A61: Industrial | B61: =K53 -> 12139900 | C61: =B61/$B$65 -> 0.095077468 | D61: =($B$65-$B$67)*C61 -> 11369716 | E61: =J53 -> 75003850 | F61: =E61/$E$65 -> 0.13011172 | G61: =($E$65-$B$68)*F61 -> 19760930
A62: Public | B62: =C53 -> 50581700 | C62: =B62/$B$65 -> 0.39614659 | D62: =($B$65-$B$67)*C62 -> 47372679 | E62: =B53 -> 264300150 | F62: =E62/$E$65 -> 0.45849044 | G62: =($E$65-$B$68)*F62 -> 69633983
A63: Domestic | B63: =E53 -> 60903900 | C63: =B63/$B$65 -> 0.47698817 | D63: =($B$65-$B$67)*C63 -> 57040014 | E63: =D53 -> 207294450 | F63: =E63/$E$65 -> 0.35960072 | G63: =($E$65-$B$68)*F63 -> 54614945
A64: Other | B64: =O53 -> 4058800 | C64: =B64/$B$65 -> 0.031787777 | D64: =($B$65-$B$67)*C64 -> 3801300.3 | E64: =N53 -> 29858825 | F64: =E64/$E$65 -> 0.051797117 | G64: =($E$65-$B$68)*F64 -> 7866771.6
A65: Total | B65: =SUM(B61:B64) -> 127684300 | E65: =SUM(E61:E64) -> 576457275
A67: WASREB Groundwater use | B67: ='WASREB 20-21'!CO5 -> 8100590
A68: WASREB Surface water use | B68: ='WASREB 20-21'!CO4 -> 424580645

Sheet WASREB 20-21
A1: Data Source | B1: WASREB | C1: m3
A2: County | B2: Vihiga | C2: Bomet | D2: Busia | E2: Baringo | F2: Uasin Gishu | G2: Mandera | H2: Embu | I2: Embu | J2: Garissa | K2: Murang'a | L2: Murang'a | M2: Kiambu | N2: Kiambu | O2: Gusii | P2: Homabay | Q2: Meru | R2: Isiolo | S2: Murang'a | T2: Kakamega | U2: Kiambu | V2: Machakos | W2: Kericho | X2: Kitui | Y2: Kiambu | Z2: Makueni | AA2: Kiambu | AB2: Kilifi | AC2: Baringo | AD2: Kirinyaga | AE2: Kisumu | AF2: Kitui | AG2: Kwale | AH2: Embu | AI2: Kiambu | AJ2: Turkana | AK2: Machakos | AL2: Kilifi | AM2: Mandera | AN2: Nyeri | AO2: Machakos | AP2: Machakos | AQ2: Makueni | AR2: Meru | AS2: Migori | AT2: Mombasa | AU2: Murang'a | AV2: Murang'a | AW2: Tharaka-Nithi | AX2: Machakos | AY2: Nairobi | AZ2: Nakuru | BA2: Nakuru | BB2: Nakuru | BC2: Lakipia | BD2: Narok | BE2: Embu | BF2: Embu | BG2: Tharaka-Nithi | BH2: Kajiado | BI2: Laikipia | BJ2: Migori | BK2: Nyeri | BL2: Bungoma | BM2: Kajiado | BN2: Kajiado | BO2: Nyeri | BP2: Kiambu | BQ2: Kirinyaga | BR2: Siaya | BS2: Nandi | BT2: Taita-Taveta | BU2: Nyeri | BV2: Kiambu | BW2: Meru | BX2: Machakos | BY2: Elgeiyo Marakwet | BZ2: West Pokot | CA2: Nandi | CB2: Kiambu | CC2: Lamu | CD2: Tharaka-Nithi | CE2: Nyeri | CF2: Nyandarua | CG2: Nyandarua | CH2: Nairobi | CI2: Samburu | CJ2: Tana River | CK2: Kiambu | CL2: Wajir | CM2: Makueni | CO2: Totals
A3: INDICATORS | B3: Amatsi | C3: Bomet | D3: Busia | E3: Chemususu | F3: Eldoret | G3: Elwak | H3: Embe | I3: Embu | J3: Garissa | K3: Gatamathi | L3: Gatanga | M3: Gatundu | N3: Githunguri | O3: Gusii | P3: Homabay | Q3: Imetha | R3: Isiolo | S3: Kahuti | T3: Kakamega | U3: Karuri | V3: Kathiani | W3: Kericho | X3: Kiambere Mwingi | Y3: Kiamumbi | Z3: Kibwezi Makindu | AA3: Kikuyu | AB3: Kilifi Mariakani | AC3: Kirandich | AD3: Kirinyaga | AE3: Kisumu | AF3: Kitui | AG3: Kwale | AH3: Kyeni | AI3: Limuru | AJ3: Lodwar | AK3: Machakos | AL3: Malindi | AM3: Mandera | AN3: Mathira | AO3: Matungulu Kangundo | AP3: Mavoko | AQ3: Mbooni | AR3: Meru | AS3: Migori | AT3: Mombasa | AU3: Murang'a | AV3: Murang'a South | AW3: Murugi Mugumango | AX3: Mwala | AY3: Nairobi | AZ3: Naivasha | BA3: Nakuru | BB3: Nakuru Rural | BC3: Nanyuki | BD3: Narok | BE3: Ngagaka | BF3: Ngandori Nginda | BG3: Nithi | BH3: Nol Turesh Loitokitok | BI3: Nyahururu | BJ3: Nyasare | BK3: Nyeri | BL3: Nzoia | BM3: Olkejuado | BN3: Oloolaiser | BO3: Othaya Mukurweni | BP3: Ruiru-Juja | BQ3: Rukanga | BR3: Sibo | BS3: Tachasis | BT3: Tavevo | BU3: Tetu Aberdare | BV3: Thika | BW3: Tuuru | BX3: Yatta | BY3: Iten Tambach | BZ3: Kapenguria | CA3: Kapsabet Nandi | CB3: Kiambu | CC3: Lamu | CD3: Muthambi 4K | CE3: Naromoru | CF3: Nyandarua | CG3: Ol Kalou | CH3: Runda | CI3: Samburu | CJ3: Tana | CK3: Tatu City | CL3: Wajir | CM3: Wote
A4: Surface water abstracted | B4: 1573007 | C4: 4424004 | D4: 1207650 | E4: 850153 | F4: 15290495 | G4: 349920 | H4: 1034205 | I4: 7637891 | J4: 5961600 | K4: 2790003 | L4: 2273106 | M4: 7169376 | N4: 1183987 | O4: 3231652 | P4: 1018819 | Q4: 1184866 | R4: 2286780 | S4: 3335937 | T4: 5432762 | U4: 1410393 | V4: 100541 | W4: 4100926 | X4: 974979 | Y4: 523274 | Z4: 1298437 | AA4: 0 | AB4: 0 | AC4: 1036000 | AD4: 6722945 | AE4: 9915691 | AF4: 3626236 | AG4: 0 | AH4: 1039740 | AI4: 2148401 | AJ4: 2304940 | AK4: 1242862 | AL4: 0 | AM4: 582496 | AN4: 2281551 | AO4: =AO10 -> 153695 | AP4: 960832 | AQ4: 64972 | AR4: 3001251 | AS4: 481921 | AT4: 0 | AU4: 2742691 | AV4: 5690163 | AW4: 2214840 | AX4: 51337 | AY4: 193642797 | AZ4: 1899235 | BA4: 11537195 | BB4: 8242189 | BC4: 4551704 | BD4: 882905 | BE4: 1157580 | BF4: 2758450 | BG4: 3700773 | BH4: 2190000 | BI4: 3184387 | BJ4: 114293 | BK4: 7401710 | BL4: 8265495 | BM4: 0 | BN4: 1792633 | BO4: 5460800 | BP4: 10747235 | BQ4: 384030 | BR4: 3224003 | BS4: 350447 | BT4: 0 | BU4: 3028040 | BV4: 13172207 | BW4: 1885587 | BX4: 389392 | BY4: 1168859 | BZ4: 243026 | CA4: 1085366 | CB4: 2132758 | CC4: 600563 | CD4: 648456 | CE4: 269700 | CF4: 659793 | CG4: 621290 | CH4: 834833 | CI4: 648000 | CJ4: 1908000 | CK4: 136818 | CL4: =CL14 -> 571536 | CM4: 181233 | CO4: =SUM(B4:CM4) -> 424580645
A5: Groundwater abstracted | N5: 256968 | R5: 76160 | T5: 274551 | U5: 779729 | AA5: 2507323 | AK5: 21120 | AP5: 99230 | AX5: 32196 | AZ5: 1974833 | BC5: 109546 | BJ5: 25979 | BM5: 357800 | BN5: 654586 | BT5: 408110 | CB5: 215399 | CF5: 28928 | CM5: 278132 | CO5: =SUM(B5:CM5) -> 8100590
A6: Total volume of water treated | J6: 5166915 | K6: 2790003 | R6: 0 | Y6: 465132 | AA6: 2507323 | AK6: 1208832 | AL6: 0 | AO6: 0 | AU6: 2742691 | AX6: 115101 | AY6: 179341134 | BC6: 4661250 | BI6: 3180625 | BJ6: 0 | BK6: 7401710 | BM6: 0 | BN6: 1792633 | BS6: 0 | BU6: 1010520 | BX6: 389392 | BY6: 1168859 | CB6: 2132758 | CF6: 267731 | CM6: =SUM(CM4:CM5) -> 459365 | CO6: =SUM(B6:CM6) -> 216801974
A7: Imported treated water | J7: 0 | K7: 0 | R7: 0 | Y7: 0 | AA7: 0 | AB7: 11231993 | AG7: 4521589 | AK7: 0 | AL7: 6886695 | AO7: 0 | AT7: 12495475 | AU7: 0 | AX7: 0 | AY7: 0 | BC7: 0 | BI7: 0 | BJ7: 0 | BK7: 0 | BM7: 0 | BN7: 0 | BS7: 0 | BT7: 5357895 | BU7: 0 | BX7: 0 | BY7: 0 | CB7: 819034 | CF7: 50287 | CM7: 0 | CO7: =SUM(B7:CM7) -> 41362968
A8: Exported treated water | J8: 0 | K8: 0 | R8: 0 | Y8: 0 | AA8: 0 | AK8: 0 | AL8: 0 | AO8: 0 | AU8: 0 | AX8: 0 | AY8: 0 | BC8: 0 | BI8: 0 | BJ8: 0 | BK8: 0 | BM8: 0 | BN8: 0 | BS8: 0 | BU8: 0 | BX8: 0 | BY8: 0 | CB8: 0 | CF8: 0 | CM8: 0 | CO8: =SUM(B8:CM8) -> 0
A9: Metered volume produced | B9: 1573007 | C9: 4424004 | D9: 1207650 | E9: 850153 | F9: 15290495 | G9: 349920 | H9: 1034205 | I9: 7637891 | J9: 0 | K9: 2790003 | L9: 2273106 | M9: 7169376 | N9: 1183987 | O9: 3231652 | P9: 1018819 | Q9: 1184866 | R9: 2362940 | S9: 3335937 | T9: 5432762 | U9: 1410393 | V9: 100541 | W9: 4100926 | X9: 974979 | Y9: 465132 | Z9: 1298437 | AA9: 2507323 | AB9: 11231993 | AC9: 1036000 | AD9: 6722945 | AE9: 9915691 | AF9: 3626236 | AG9: 4521589 | AH9: 1039740 | AI9: 2148401 | AJ9: 2304940 | AK9: 1208832 | AL9: 6886695 | AM9: 582496 | AN9: 2281551 | AO9: 119125 | AP9: 960832 | AQ9: 64972 | AR9: 3001251 | AS9: 481921 | AT9: 12495475 | AU9: 2742691 | AV9: 5690163 | AW9: 2214840 | AX9: 115101 | AY9: 179341134 | AZ9: 1899235 | BA9: 11537195 | BB9: 8242189 | BC9: 4661250 | BD9: 882905 | BE9: 1157580 | BF9: 2758450 | BG9: 3700773 | BH9: 2190000 | BI9: 3180625 | BJ9: 0 | BK9: 7401710 | BL9: 8265495 | BM9: 357800 | BN9: 2447219 | BO9: 5460800 | BP9: 10747235 | BQ9: 384030 | BR9: 3224003 | BS9: 0 | BT9: 5357895 | BU9: 1990520 | BV9: 13172207 | BW9: 1885587 | BX9: 389392 | BY9: 1168859 | BZ9: 243026 | CA9: 1085366 | CB9: 3162191 | CC9: 600563 | CD9: 648456 | CE9: 269700 | CF9: 657679 | CG9: 621290 | CH9: 834833 | CI9: 648000 | CJ9: 1908000 | CK9: 136818 | CL9: n.d. | CM9: 459365 | CO9: =SUM(B9:CM9) -> 447681359
A10: Total Water Produced | B10: 1573007 | C10: 4424004 | D10: 1207650 | E10: 850153 | F10: 15290495 | G10: 349920 | H10: 1034205 | I10: 7637891 | J10: 5961600 | K10: 2790003 | L10: 2273106 | M10: 7169376 | N10: =SUM(N4:N5,N7) -> 1440955 | O10: 3231652 | P10: 1018819 | Q10: 1184866 | R10: 2362940 | S10: 3335937 | T10: =SUM(T4:T5,T7) -> 5707313 | U10: =SUM(U4:U5,U7) -> 2190122 | V10: 100541 | W10: 4100926 | X10: 974979 | Y10: =SUM(Y4:Y5,Y7) -> 523274 | Z10: 1298437 | AA10: 2507323 | AB10: 11231993 | AC10: 1036000 | AD10: 6722945 | AE10: 9915691 | AF10: 3626236 | AG10: 4521589 | AH10: 1039740 | AI10: 2148401 | AJ10: 2304940 | AK10: 1263982 | AL10: 6886695 | AM10: 582496 | AN10: 2281551 | AO10: 153695 | AP10: =SUM(AP4:AP5,AP7) -> 1060062 | AQ10: 64972 | AR10: 3001251 | AS10: 481921 | AT10: 12495475 | AU10: 2742691 | AV10: 5690163 | AW10: 2214840 | AX10: =SUM(AX4:AX5,AX7) -> 83533 | AY10: =SUM(AY4:AY5,AY7) -> 193642797 | AZ10: =SUM(AZ4:AZ5,AZ7) -> 3874068 | BA10: 11537195 | BB10: 8242189 | BC10: 4661250 | BD10: 882905 | BE10: 1157580 | BF10: 2758450 | BG10: 3700773 | BH10: 2190000 | BI10: 3184387 | BJ10: 140272 | BK10: 7401710 | BL10: 8265495 | BM10: =SUM(BM4:BM5,BM7) -> 357800 | BN10: 2447219 | BO10: 5460800 | BP10: 10747235 | BQ10: 384030 | BR10: 3224003 | BS10: 350447 | BT10: =SUM(BT4:BT5,BT7) -> 5766005 | BU10: 3028040 | BV10: 13172207 | BW10: 1885587 | BX10: 389392 | BY10: 1168859 | BZ10: 243026 | CA10: 1085366 | CB10: 3167191 | CC10: 600563 | CD10: 648456 | CE10: 269700 | CF10: 739008 | CG10: 621290 | CH10: 834833 | CI10: 648000 | CJ10: 1908000 | CK10: 136818 | CL10: =SUM(CL4:CL5,CL7) -> 571536 | CM10: 459365 | CO10: =SUM(B10:CM10) -> 474044203
B11: =SUM(B4:B5,B7)-B10 -> 0 | C11: =SUM(C4:C5,C7)-C10 -> 0 | D11: =SUM(D4:D5,D7)-D10 -> 0 | E11: =SUM(E4:E5,E7)-E10 -> 0 | F11: =SUM(F4:F5,F7)-F10 -> 0 | G11: =SUM(G4:G5,G7)-G10 -> 0 | H11: =SUM(H4:H5,H7)-H10 -> 0 | I11: =SUM(I4:I5,I7)-I10 -> 0 | ... CM11: =SUM(CM4:CM5,CM7)-CM10 -> 0
A12: Value of Water Abstracted/ Produced | B12: 73930703 | C12: 240039575 | D12: 79258129 | E12: 23063224 | F12: 7.1223858e+08 | G12: 79772794 | H12: 38597578 | I12: 3.6295737e+08 | J12: 4.6772077e+08 | K12: 60579777 | L12: 58531874 | M12: 136723929 | N12: 70805791 | O12: 1.7539918e+08 | P12: 97875348 | Q12: 56402541 | R12: 82307738 | S12: 76336089 | T12: 2.4503747e+08 | U12: 109157959 | V12: 14266064 | W12: 263530219 | X12: 135178025 | Y12: 22573822 | Z12: 86202402 | AA12: 139042955 | AB12: 5.6720057e+08 | AC12: 59753784 | AD12: 175178481 | AE12: 8.2584084e+08 | AF12: 278521048 | AG12: 208215827 | AH12: 16654271 | AI12: 141350626 | AJ12: 54230924 | AK12: 130523129 | AL12: 556219860 | AM12: 1.7856676e+08 | AN12: 148496925 | AO12: 16952185 | AP12: 208513398 | AQ12: 5071016 | AR12: 2.155529e+08 | AS12: 51740623 | AT12: 913363452 | AU12: 2.2835782e+08 | AV12: 228667569 | AW12: 21187941 | AX12: 18538604 | AY12: 6.7833619e+09 | AZ12: 93019470 | BA12: 8.2898502e+08 | BB12: 314924993 | BC12: 3.9550335e+08 | BD12: 110004557 | BE12: 38340240 | BF12: 69827129 | BG12: 110540087 | BH12: 69932275 | BI12: 2.219596e+08 | BJ12: 4239561 | BK12: 4.5253676e+08 | BL12: 3.3822517e+08 | BM12: 32142167 | BN12: 187075312 | BO12: 158301093 | BP12: 5.321785e+08 | BQ12: 8885446 | BR12: 136008536 | BS12: 2006154 | BT12: 415995123 | BU12: 66044176 | BV12: 497763520 | BW12: 20530487 | BX12: 46115044 | BY12: 35013579 | BZ12: 12673451 | CA12: 75328017 | CB12: 201580632 | CC12: 85334549 | CD12: 11512382 | CE12: 16540076 | CF12: 51195602 | CG12: 36236035 | CH12: 55328906 | CI12: 58365545 | CJ12: 86273989 | CK12: 52349712 | CL12: NO DATA | CM12: 42400663
A13: Value of Imported treated water | B13: 0 | C13: 0 | D13: 0 | E13: 0 | F13: 0 | G13: 0 | H13: 0 | I13: 0 | J13: 0 | K13: 0 | L13: 0 | M13: 0 | N13: 0 | O13: 0 | P13: 0 | Q13: 0 | R13: 0 | S13: 0 | T13: 0 | U13: 0 | V13: 0 | W13: 0 | X13: 0 | Y13: 0 | Z13: 0 | AA13: 0 | AB13: 5.6720057e+08 | AC13: 0 | AD13: 0 | AE13: 0 | AF13: 0 | AG13: 208215827 | AH13: 0 | AI13: 0 | AJ13: 0 | AK13: 0 | AL13: 556219860 | AM13: 0 | AN13: 0 | AO13: 0 | AP13: 0 | AQ13: 0 | AR13: 0 | AS13: 0 | AT13: 913363452 | AU13: 0 | AV13: 0 | AW13: 0 | AX13: 0 | AY13: 0 | AZ13: 0 | BA13: 0 | BB13: 0 | BC13: 0 | BD13: 0 | BE13: 0 | BF13: 0 | BG13: 0 | BH13: 0 | BI13: 0 | BJ13: 0 | BK13: 0 | BL13: 0 | BM13: 0 | BN13: 0 | BO13: 0 | BP13: 0 | BQ13: 0 | BR13: 0 | BS13: 0 | BT13: 415995123 | BU13: 0 | BV13: 0 | BW13: 0 | BX13: 0 | BY13: 0 | BZ13: 0 | CA13: 0 | CB13: 52128650 | CC13: 0 | CD13: 0 | CE13: 0 | CF13: 3483687.9 | CG13: 0 | CH13: 0 | CI13: 0 | CJ13: 0 | CK13: 0 | CL13: 0 | CM13: 0
A14: Total Billed Volume | B14: 1101104.9 | C14: 2005094 | D14: 620242 | E14: 272266 | F14: 8869969 | G14: 141426 | H14: 461783 | I14: 4739448 | J14: 3576960 | K14: 1020766 | L14: 1370875 | M14: 4742140 | N14: 690912 | O14: 1348246 | P14: 569227 | Q14: 716731 | R14: 1638248 | S14: 1214494 | T14: 3072689 | U14: 1005557 | V14: 70381 | W14: 1946176 | X14: 602643 | Y14: 354485 | Z14: 935944 | AA14: 1454089 | AB14: 5347542 | AC14: 440400 | AD14: 2701227 | AE14: 6696511 | AF14: 1653210 | AG14: 1835915 | AH14: 573552 | AI14: 1519934 | AJ14: 1273305 | AK14: 710419 | AL14: 5164287 | AM14: 344242 | AN14: 1214018 | AO14: 90678 | AP14: 604643 | AQ14: 42602 | AR14: 2421650 | AS14: 249630 | AT14: 5823200 | AU14: 2068366 | AV14: 2977634 | AW14: 1771192 | AX14: 42682 | AY14: 89727204 | AZ14: 1358834.9 | BA14: 7905899 | BB14: 3830215 | BC14: 2789074 | BD14: 785675 | BE14: 721694 | BF14: 1740204 | BG14: 1298768 | BH14: 1081545 | BI14: 1931100 | BJ14: 89065 | BK14: 6117001 | BL14: 4254899 | BM14: 219878 | BN14: 1428834 | BO14: 2986416 | BP14: 6915527 | BQ14: 156414 | BR14: 974798 | BS14: 262729 | BT14: 3350520 | BU14: 2149900 | BV14: 9214087 | BW14: 435051 | BX14: 274619 | BY14: 794825 | BZ14: 75766 | CA14: 681984 | CB14: 2072421 | CC14: 352197 | CD14: 486523 | CE14: 167689 | CF14: 394594 | CG14: 322268 | CH14: 618158 | CI14: 361390 | CJ14: 566988 | CK14: 125326 | CL14: 571536 | CM14: 298451
A15: Water Value | BR15: =BR12/BR10 -> 42.186231 | BS15: =BS12/BS10 -> 5.7245575 | CJ15: =CJ12/CJ10 -> 45.216975
A16: Total Water Produced | B16: 1573007 | C16: 4424004 | D16: 1207650 | E16: 850153 | F16: 15290495 | G16: 349920 | H16: 1034205 | I16: 7637891 | J16: 5961600 | K16: 2790003 | L16: 2273106 | M16: 7169376 | N16: 1183987 | O16: 3231652 | P16: 1018819 | Q16: 1184866 | R16: 2362940 | S16: 3335937 | T16: 5432762 | U16: 1410393 | V16: 100541 | W16: 4100926 | X16: 974979 | Y16: 465132 | Z16: 1298437 | AA16: 2507323 | AB16: 11231993 | AC16: 1036000 | AD16: 6722945 | AE16: 9915691 | AF16: 3626236 | AG16: 4521589 | AH16: 1039740 | AI16: 2148401 | AJ16: 2304940 | AK16: 1263982 | AL16: 6886695 | AM16: 582496 | AN16: 2281551 | AO16: 153695 | AP16: 960832 | AQ16: 64972 | AR16: 3001251 | AS16: 481921 | AT16: 12495475 | AU16: 2742691 | AV16: 5690163 | AW16: 2214840 | AX16: 58205 | AY16: 179341134 | AZ16: 1899235 | BA16: 11537195 | BB16: 8242189 | BC16: 4661250 | BD16: 882905 | BE16: 1157580 | BF16: 2758450 | BG16: 3700773 | BH16: 2190000 | BI16: 3184387 | BJ16: 140272 | BK16: 7401710 | BL16: 8265495 | BM16: 377280 | BN16: 2447219 | BO16: 5460800 | BP16: 10747235 | BQ16: 384030 | BR16: 3224003 | BS16: 350447 | BT16: 5357895 | BU16: 3028040 | BV16: 13172207 | BW16: 1885587 | BX16: 389392 | BY16: 1168859 | BZ16: 243026 | CA16: 1085366 | CB16: 3167191 | CC16: 600563 | CD16: 648456 | CE16: 269700 | CF16: 739008 | CG16: 621290 | CH16: 834833 | CI16: 648000 | CJ16: 1908000 | CK16: 136818 | CM16: 459365 | CO16: =SUM(B16:CM16) -> 455313593
A17: Total sewage treated | F17: 7850064 | I17: 1950734 | J17: 240000 | O17: 1816500 | P17: NO DATA | R17: 297423 | T17: 396060 | W17: 175140 | AE17: 4692420 | AF17: NO DATA | AK17: 72204 | AP17: 752000 | AT17: 6000 | AU17: 1261585.9 | AY17: 80525515 | AZ17: 993631 | BA17: 4393860 | BC17: 995579.1 | BI17: 1116976 | BK17: 3810236 | BL17: 1471640 | BP17: 1379820.5 | BV17: 4015000 | CB17: 2500 | CO17: =SUM(B17:CM17) -> 1.1821489e+08
A18: Total Expenditures | B18: 73930703 | C18: 240039575 | D18: 79258129 | E18: 23063224 | F18: 837927741 | G18: 79772794 | H18: 38597578 | I18: 427008665 | J18: 550259733 | K18: 60579777 | L18: 58531874 | M18: 136723929 | N18: 70805791 | O18: 206351982 | P18: 97875348 | Q18: 56402541 | R18: 96832633 | S18: 76336089 | T18: 350053531 | U18: 109157959 | V18: 14266064 | W18: 263530219 | X18: 135178025 | Y18: 22573822 | Z18: 86202402 | AA18: 139042955 | AB18: 667294785 | AC18: 59753784 | AD18: 175178481 | AE18: 943818099 | AF18: 278521048 | AG18: 208215827 | AH18: 16654271 | AI18: 141350626 | AJ18: 54230924 | AK18: 130523129 | AL18: 556219860 | AM18: 178566758 | AN18: 148496925 | AO18: 16952185 | AP18: 208513398 | AQ18: 5071016 | AR18: 215552899 | AS18: 51740623 | AT18: 913363452 | AU18: 235420437 | AV18: 228667569 | AW18: 21187941 | AX18: 18538604 | AY18: 10435941392 | AZ18: 186038940 | BA18: 975276497 | BB18: 314924993 | BC18: 416319319 | BD18: 110004557 | BE18: 38340240 | BF18: 69827129 | BG18: 110540087 | BH18: 69932275 | BI18: 261128942 | BJ18: 4239561 | BK18: 502818624 | BL18: 397911961 | BM18: 32142167 | BN18: 187075312 | BO18: 158301093 | BP18: 626092351 | BQ18: 8885446 | BR18: 136008536 | BS18: 2006154 | BT18: 415995123 | BU18: 66044176 | BV18: 654952000 | BW18: 20530487 | BX18: 46115044 | BY18: 35013579 | BZ18: 12673451 | CA18: 75328017 | CB18: 201580632 | CC18: 85334549 | CD18: 11512382 | CE18: 16540076 | CF18: 51195602 | CG18: 36236035 | CH18: 55328906 | CI18: 58365545 | CJ18: 86273989 | CK18: 52349712 | CL18: n.d. | CM18: 42400663
A19: Total Expenditures-water | B19: 73930703 | C19: 240039575 | D19: 79258129 | E19: 23063224 | F19: 7.1223858e+08 | G19: 79772794 | H19: 38597578 | I19: 3.6295737e+08 | J19: 4.6772077e+08 | K19: 60579777 | L19: 58531874 | M19: 136723929 | N19: 70805791 | O19: 1.7539918e+08 | P19: 97875348 | Q19: 56402541 | R19: 82307738 | S19: 76336089 | T19: 2.4503747e+08 | U19: 109157959 | V19: 14266064 | W19: 263530219 | X19: 135178025 | Y19: 22573822 | Z19: 86202402 | AA19: 139042955 | AB19: 5.6720057e+08 | AC19: 59753784 | AD19: 175178481 | AE19: 8.2584084e+08 | AF19: 278521048 | AG19: 208215827 | AH19: 16654271 | AI19: 141350626 | AJ19: 54230924 | AK19: 130523129 | AL19: 556219860 | AM19: 178566758 | AN19: 148496925 | AO19: 16952185 | AP19: 208513398 | AQ19: 5071016 | AR19: 215552899 | AS19: 51740623 | AT19: 913363452 | AU19: 2.2835782e+08 | AV19: 228667569 | AW19: 21187941 | AX19: 18538604 | AY19: 6.7833619e+09 | AZ19: 93019470 | BA19: 8.2898502e+08 | BB19: 314924993 | BC19: 3.9550335e+08 | BD19: 110004557 | BE19: 38340240 | BF19: 69827129 | BG19: 110540087 | BH19: 69932275 | BI19: 2.219596e+08 | BJ19: 4239561 | BK19: 4.5253676e+08 | BL19: 3.3822517e+08 | BM19: 32142167 | BN19: 187075312 | BO19: 158301093 | BP19: 5.321785e+08 | BQ19: 8885446 | BR19: 136008536 | BS19: 2006154 | BT19: 415995123 | BU19: 66044176 | BV19: 497763520 | BW19: 20530487 | BX19: 46115044 | BY19: 35013579 | BZ19: 12673451 | CA19: 75328017 | CB19: 201580632 | CC19: 85334549 | CD19: 11512382 | CE19: 16540076 | CF19: 51195602 | CG19: 36236035 | CH19: 55328906 | CI19: 58365545 | CJ19: 86273989 | CK19: 52349712 | CL19: n.d. | CM19: 42400663
A20: Total Expenditures-sewage | F20: 1.0683579e+08 | I20: 54443605 | J20: 70158116 | O20: 26309878 | P20: NO DATA | R20: 12346161 | T20: 73511242 | AE20: 1.032301e+08 | AF20: NO DATA | AK20: NO DATA | AP20: NO DATA | AT20: NO DATA | AU20: 6850734.7 | AY20: 3.6525795e+09 | AZ20: 79066550 | BA20: 1.2434775e+08 | BC20: 19775168 | BI20: 39169341 | BK20: 45253676 | BL20: 59686794 | BP20: 79826775 | BV20: 1.1946324e+08 | CB20: No Data
A21: Actual cost-water produced | B21: 46.999602 | C21: 54.258444 | D21: 65.630049 | E21: 27.128322 | F21: 46.580479 | G21: 227.97438 | H21: 37.321013 | I21: 47.520626 | J21: 78.455578 | K21: 21.713158 | L21: 25.749734 | M21: 19.070548 | N21: 59.802845 | O21: 54.275394 | P21: 96.067455 | Q21: 47.602464 | R21: 34.832767 | S21: 22.882953 | T21: 45.103664 | U21: 77.39542 | V21: 141.893 | W21: 64.26115 | X21: 138.64711 | Y21: 48.532077 | Z21: 66.38936 | AA21: 55.454744 | AB21: 50.498657 | AC21: 57.677398 | AD21: 26.056807 | AE21: 83.286262 | AF21: 76.807204 | AG21: 46.04926 | AH21: 16.017727 | AI21: 65.793409 | AJ21: 23.528128 | AK21: 103.26344 | AL21: 80.767314 | AM21: 306.55448 | AN21: 65.085955 | AO21: 110.29757 | AP21: 217.01338 | AQ21: 78.049252 | AR21: 71.821017 | AS21: 107.36329 | AT21: 73.095537 | AU21: 83.2605 | AV21: 40.186471 | AW21: 9.5663529 | AX21: 318.50535 | AY21: 37.823793 | AZ21: 48.977336 | BA21: 71.853256 | BB21: 38.208902 | BC21: 84.849204 | BD21: 124.59388 | BE21: 33.121028 | BF21: 25.313901 | BG21: 29.869459 | BH21: 31.932546 | BI21: 69.702458 | BJ21: 30.223858 | BK21: 61.139488 | BL21: 40.920134 | BM21: 85.194463 | BN21: 76.444042 | BO21: 28.988627 | BP21: 49.517713 | BQ21: 23.137375 | BR21: 42.186231 | BS21: 5.7245575 | BT21: 77.641522 | BU21: 21.810866 | BV21: 37.788923 | BW21: 10.888114 | BX21: 118.42833 | BY21: 29.955349 | BZ21: 52.14854 | CA21: 69.403332 | CB21: 63.646503 | CC21: 142.09092 | CD21: 17.753528 | CE21: 61.327683 | CF21: 69.276113 | CG21: 58.323866 | CH21: 66.275418 | CI21: 90.070285 | CJ21: 45.216975 | CK21: 382.62299 | CM21: =CM19/CM16 -> 92.302772
A22: Actual unit cost- sewage treated | F22: 13.609543 | I22: 27.909292 | J22: 292.32548 | O22: 14.48383 | P22: NO DATA | R22: 41.510444 | T22: 185.60633 | AE22: 21.999332 | AF22: NO DATA | AK22: NO DATA | AP22: NO DATA | AT22: NO DATA | AU22: 5.4302563 | AY22: 45.359281 | AZ22: 79.573352 | BA22: 28.300345 | BC22: 19.86298 | BI22: 35.067308 | BK22: 11.87687 | BL22: 40.558013 | BP22: 57.853015 | BV22: 29.754233 | CB22: No Data
A23: Value of Water sold (in Ksh.) per category
A24: Individual | B24: 17102919 | C24: 20777512 | D24: 36328002 | E24: 3545319 | F24: 3.2215111e+08 | G24: 0 | H24: 7786394.9 | I24: 1.6031273e+08 | J24: 1.0383424e+08 | K24: 15388491 | L24: 19767830 | M24: 86659010 | N24: 30353412 | O24: 28543890 | P24: 47893487 | Q24: 15353162 | R24: 50701249 | S24: 35563472 | T24: 47338910 | U24: 25838616 | V24: 1497955.3 | W24: 1.0455852e+08 | X24: 30070880 | Y24: 12042750 | Z24: 29805271 | AA24: 32738041 | AB24: 2.031948e+08 | AC24: 135194.5 | AD24: 57462831 | AE24: 2.6956399e+08 | AF24: 18344917 | AG24: 70917884 | AH24: 8414365.9 | AI24: 71373818 | AJ24: 0 | AK24: 12309951 | AL24: 3.0394807e+08 | AM24: 0 | AN24: 54209125 | AO24: 7022967.2 | AP24: 39279779 | AQ24: 0 | AR24: 1.3776964e+08 | AS24: 20011917 | AT24: 2.0080056e+08 | AU24: 1523830 | AV24: 86160436 | AW24: 13555082 | AX24: 2933434.3 | AY24: 4.0950422e+08 | AZ24: 37280976 | BA24: 2.9226675e+08 | BB24: 22681368 | BC24: 1.5101064e+08 | BD24: 56705041 | BE24: 20025061 | BF24: 16861229 | BG24: 19396775 | BH24: 22202016 | BI24: 73522410 | BJ24: 1894884.8 | BK24: 1.40106e+08 | BL24: 1.2646976e+08 | BM24: 3692515.3 | BN24: 29188372 | BO24: 74144825 | BP24: 2.2115818e+08 | BQ24: 3047196.8 | BR24: 22732432 | BS24: 1253844.1 | BT24: 2.0149155e+08 | BU24: 44366639 | BV24: 2.1494393e+08 | BW24: 3961054.7 | BX24: 7807824.4 | BY24: 10217606 | BZ24: 1503167.7 | CA24: 17126215 | CB24: 72299666 | CC24: 36876824 | CD24: 8466014.4 | CE24: 5092117.4 | CF24: 24314669 | CG24: 13326245 | CH24: 40450736 | CI24: 44440.05 | CJ24: 1356368 | CK24: 14186.35 | CL24: 18488.9 | CM24: 4610180.2
A25: Multi-dwelling units | B25: 0 | C25: 0 | D25: 0 | E25: 0 | F25: 1706298.6 | G25: 0 | H25: 3909376.1 | I25: 0 | J25: 19644354 | K25: 0 | L25: 0 | M25: 0 | N25: 1866088 | O25: 17248783 | P25: 0 | Q25: 5117703.5 | R25: 0 | S25: 2045000.1 | T25: 61544690 | U25: 35177999 | V25: 1597875.7 | W25: 0 | X25: 9854667.9 | Y25: 3440778.7 | Z25: 8845359.8 | AA25: 0 | AB25: 0 | AC25: 66592.15 | AD25: 0 | AE25: 0 | AF25: 7678624.5 | AG25: 0 | AH25: 0 | AI25: 0 | AJ25: 0 | AK25: 11111834 | AL25: 0 | AM25: 0 | AN25: 0 | AO25: 393192.61 | AP25: 23194413 | AQ25: 0 | AR25: 0 | AS25: 0 | AT25: 86057439 | AU25: 0 | AV25: 0 | AW25: 0 | AX25: 2682770.6 | AY25: 1.4628397e+08 | AZ25: 9568550.2 | BA25: 2.4991362e+08 | BB25: 26374560 | BC25: 0 | BD25: 3279310.8 | BE25: 0 | BF25: 0 | BG25: 0 | BH25: 0 | BI25: 0 | BJ25: 266876.67 | BK25: 1.2470144e+08 | BL25: 6813027.6 | BM25: 6857451.5 | BN25: 71322465 | BO25: 0 | BP25: 81980456 | BQ25: 0 | BR25: 83409.509 | BS25: 0 | BT25: 0 | BU25: 201227.05 | BV25: 7929790.5 | BW25: 0 | BX25: 14936879 | BY25: 2707124.6 | BZ25: 0 | CA25: 2753280.9 | CB25: 35955451 | CC25: 0 | CD25: 0 | CE25: 4403161.1 | CF25: 0 | CG25: 0 | CH25: 0 | CI25: 74067.7 | CJ25: 3390.55 | CK25: 8196.6 | CL25: 0 | CM25: 3504950.5
A26: Institutions | B26: 29588618 | C26: 35945785 | D26: 372229.84 | E26: 960234.07 | F26: 16646106 | G26: 0 | H26: 1562966.7 | I26: 9875403.2 | J26: 33675762 | K26: 1323559.9 | L26: 10589903 | M26: 2185471 | N26: 580924.84 | O26: 5234768.7 | P26: 2630372.4 | Q26: 3411836.9 | R26: 1688591.2 | S26: 3943954.6 | T26: 3377634.6 | U26: 311284.38 | V26: 3495269.5 | W26: 1165231.9 | X26: 4585285.8 | Y26: 1204275 | Z26: 2125946.7 | AA26: 0 | AB26: 13245608 | AC26: 7789.05 | AD26: 5403341.5 | AE26: 23590508 | AF26: 4639138.5 | AG26: 1476790.7 | AH26: 0 | AI26: 5775482.8 | AJ26: 0 | AK26: 13577122 | AL26: 12649946 | AM26: 0 | AN26: 11754660 | AO26: 584881.84 | AP26: 1252829.4 | AQ26: 0 | AR26: 6850291.8 | AS26: 3147823.2 | AT26: 8256502.7 | AU26: 0 | AV26: 1297138.9 | AW26: 1186065.1 | AX26: 1732669.1 | AY26: 21055236 | AZ26: 281029.63 | BA26: 791458.34 | BB26: 15593298 | BC26: 0 | BD26: 8547513.7 | BE26: 1544298.3 | BF26: 7945165.4 | BG26: 7758704.8 | BH26: 0 | BI26: 6628106 | BJ26: 133438.33 | BK26: 36237422 | BL26: 500202.34 | BM26: 3260925 | BN26: 392974 | BO26: 2425256.9 | BP26: 2231363.6 | BQ26: 18101.584 | BR26: 1973596.7 | BS26: 0 | BT26: 17888995 | BU26: 745168.25 | BV26: 4464327.2 | BW26: 402763.83 | BX26: 837178.62 | BY26: 4029602 | BZ26: 583632.86 | CA26: 9466406.5 | CB26: 1976746.2 | CC26: 0 | CD26: 7483.3654 | CE26: 208819.74 | CF26: 1737306.4 | CG26: 908219.25 | CH26: 0 | CI26: 85919.9 | CJ26: 113596.3 | CK26: 18442.35 | CL26: 0 | CM26: 7754379.3
A27: Schools | B27: 2929822.1 | C27: 3559299.7 | D27: 2258876.8 | E27: 590881.97 | F27: 2702905.3 | G27: 0 | H27: 2830686.9 | I27: 13665285 | J27: 50513643 | K27: 2727641 | L27: 0 | M27: 1280817.8 | N27: 3788988.7 | O27: 1877309.7 | P27: 1215686.1 | Q27: 3070642.9 | R27: 0 | S27: 2048788.8 | T27: 9907012.2 | U27: 233424.59 | V27: 1797595 | W27: 6269337.6 | X27: 3920850 | Y27: 516090.11 | Z27: 1471932.4 | AA27: 8869099 | AB27: 12705388 | AC27: 0 | AD27: 2673085.3 | AE27: 4095088.1 | AF27: 1988193.3 | AG27: 2215243.6 | AH27: 772633.22 | AI27: 4215554 | AJ27: 0 | AK27: 7977224.7 | AL27: 6474726.5 | AM27: 0 | AN27: 0 | AO27: 408853.5 | AP27: 498598.63 | AQ27: 0 | AR27: 2947328.8 | AS27: 1488623.8 | AT27: 5504388.5 | AU27: 70075.8 | AV27: 7022867.1 | AW27: 1694382.9 | AX27: 1748594.4 | AY27: 2031389.2 | AZ27: 1474026.8 | BA27: 809073.62 | BB27: 2846788.3 | BC27: 5606603.5 | BD27: 5379589.8 | BE27: 0 | BF27: 8193120.6 | BG27: 3879365.7 | BH27: 7048268.1 | BI27: 5952057.3 | BJ27: 53375.333 | BK27: 26490252 | BL27: 17156812 | BM27: 1468773.4 | BN27: 1442000.8 | BO27: 6230170 | BP27: 2514942.1 | BQ27: 97713.688 | BR27: 1695246.9 | BS27: 250163.16 | BT27: 8696394 | BU27: 748243.58 | BV27: 5764383.5 | BW27: 301828.22 | BX27: 2887072.1 | BY27: 3471327 | BZ27: 659920 | CA27: 2240297.2 | CB27: 557833.66 | CC27: 7790134.7 | CD27: 147538.71 | CE27: 147540.1 | CF27: 1203741.7 | CG27: 500418.77 | CH27: 400088.4 | CI27: 35551.85 | CJ27: 169546.5 | CK27: 22541.6 | CL27: 0 | CM27: 4281543.5
A28: Commercial customers | B28: 1893560.4 | C28: 2300395.3 | D28: 347300.77 | E28: 2215814.2 | F28: 49128097 | G28: 0 | H28: 877043.8 | I28: 39533920 | J28: 58933061 | K28: 2686955.3 | L28: 2823985 | M28: 150682.25 | N28: 406719.15 | O28: 4123544.5 | P28: 1939059.2 | Q28: 6823621.9 | R28: 4316444.5 | S28: 4289674.2 | T28: 4422118 | U28: 13775379 | V28: 1398156.4 | W28: 12474448 | X28: 2606377.4 | Y28: 0 | Z28: 4235807.2 | AA28: 36578005 | AB28: 7566299.3 | AC28: 52540.7 | AD28: 4831150.9 | AE28: 1.4358967e+08 | AF28: 2419728.7 | AG28: 2616545.4 | AH28: 0 | AI28: 11845285 | AJ28: 0 | AK28: 14427435 | AL28: 63200671 | AM28: 0 | AN28: 12950455 | AO28: 0 | AP28: 44608668 | AQ28: 0 | AR28: 23699029 | AS28: 1790456.5 | AT28: 41282513 | AU28: 1084050 | AV28: 24828367 | AW28: 491375.72 | AX28: 1661323.9 | AY28: 1.032914e+08 | AZ28: 13516937 | BA28: 23888769 | BB28: 19496335 | BC28: 79599887 | BD28: 15276954 | BE28: 2333888.6 | BF28: 5532888.2 | BG28: 7370752.3 | BH28: 0 | BI28: 23729291 | BJ28: 266876.67 | BK28: 45611036 | BL28: 19829485 | BM28: 2877239.2 | BN28: 5020171.9 | BO28: 3658573.1 | BP28: 0 | BQ28: 383619.93 | BR28: 897937.14 | BS28: 0 | BT28: 26278239 | BU28: 826522.78 | BV28: 85600892 | BW28: 0 | BX28: 0 | BY28: 3273981.1 | BZ28: 335305.64 | CA28: 14199539 | CB28: 4685638.9 | CC28: 8068917.1 | CD28: 4490.0192 | CE28: 427153.84 | CF28: 0 | CG28: 3360912.8 | CH28: 42738.125 | CI28: 50366.15 | CJ28: 50863.95 | CK28: 12294.9 | CL28: 0 | CM28: 5461665.4
A29: Industries | B29: 0 | C29: 0 | D29: 28341.411 | E29: 0 | F29: 0 | G29: 0 | H29: 0 | I29: 0 | J29: 14031408 | K29: 34005.944 | L29: 0 | M29: 0 | N29: 2722524.5 | O29: 3551.8416 | P29: 56442.197 | Q29: 0 | R29: 0 | S29: 2185994.2 | T29: 0 | U29: 0 | V29: 0 | W29: 0 | X29: 10814424 | Y29: 0 | Z29: 0 | AA29: 0 | AB29: 13979136 | AC29: 0 | AD29: 0 | AE29: 953250.7 | AF29: 0 | AG29: 1744382.8 | AH29: 0 | AI29: 0 | AJ29: 0 | AK29: 11808594 | AL29: 2384113.8 | AM29: 0 | AN29: 0 | AO29: 0 | AP29: 17533743 | AQ29: 0 | AR29: 0 | AS29: 0 | AT29: 27521702 | AU29: 0 | AV29: 0 | AW29: 0 | AX29: 0 | AY29: 6656737.9 | AZ29: 0 | BA29: 0 | BB29: 126897.63 | BC29: 0 | BD29: 0 | BE29: 0 | BF29: 5518947.9 | BG29: 0 | BH29: 0 | BI29: 7558959.4 | BJ29: 49718.246 | BK29: 0 | BL29: 0 | BM29: 0 | BN29: 0 | BO29: 0 | BP29: 31576691 | BQ29: 0 | BR29: 13106.16 | BS29: 0 | BT29: 2407120.1 | BU29: 0 | BV29: 29125841 | BW29: 0 | BX29: 0 | BY29: 0 | BZ29: 0 | CA29: 1159684.9 | CB29: 0 | CC29: 0 | CD29: 0 | CE29: 0 | CF29: 0 | CG29: 0 | CH29: 0 | CI29: 0 | CJ29: 0 | CK29: 0 | CL29: 0 | CM29: 0
A30: Kiosks | B30: 236577.81 | C30: 287406.98 | D30: 1371762.2 | E30: 73870.42 | F30: 20832883 | G30: 0 | H30: 267740.95 | I30: 1834195 | J30: 0 | K30: 3400.5944 | L30: 703357.89 | M30: 159227.62 | N30: 236580.05 | O30: 16144734 | P30: 945614.31 | Q30: 341194.08 | R30: 358425.88 | S30: 0 | T30: 11999168 | U30: 155564.79 | V30: 199719.27 | W30: 587711.96 | X30: 19192629 | Y30: 0 | Z30: 9385890 | AA30: 2450988.8 | AB30: 11083829 | AC30: 1102.95 | AD30: 14942.432 | AE30: 33834000 | AF30: 8357401.9 | AG30: 5571680.2 | AH30: 0 | AI30: 1128398.4 | AJ30: 0 | AK30: 2148148.9 | AL30: 28288423 | AM30: 0 | AN30: 0 | AO30: 1591667.9 | AP30: 4847589.6 | AQ30: 0 | AR30: 2659072.6 | AS30: 362277.44 | AT30: 48712142 | AU30: 2480.45 | AV30: 351792.37 | AW30: 16942.011 | AX30: 2835653.1 | AY30: 58388793 | AZ30: 4016223.5 | BA30: 394909.86 | BB30: 1203902.7 | BC30: 433576.45 | BD30: 3774197.7 | BE30: 0 | BF30: 0 | BG30: 387899.43 | BH30: 0 | BI30: 249758.95 | BJ30: 26717.89 | BK30: 844164.98 | BL30: 3019756.4 | BM30: 575483.78 | BN30: 1859862.7 | BO30: 113273.62 | BP30: 2979449.8 | BQ30: 72377.281 | BR30: 12917717 | BS30: 0 | BT30: 3098595.5 | BU30: 3380.6843 | BV30: 361262.89 | BW30: 71238.335 | BX30: 2534103.1 | BY30: 109619.21 | BZ30: 0 | CA30: 386538.11 | CB30: 680540.69 | CC30: 363326.48 | CD30: 11973.385 | CE30: 5185.5475 | CF30: 80221.739 | CG30: 645878.5 | CH30: 0 | CI30: 5925.15 | CJ30: 1694.8 | CK30: 3152.1 | CL30: 0 | CM30: 1935135.8
A31: Bulk | B31: 0 | C31: 0 | D31: 0 | E31: 0 | F31: 0 | G31: 0 | H31: 0 | I31: 0 | J31: 0 | K31: 0 | L31: 1414590.1 | M31: 0 | N31: 1363265.7 | O31: 0 | P31: 0 | Q31: 0 | R31: 0 | S31: 4701245.1 | T31: 0 | U31: 2334787.6 | V31: 0 | W31: 8259.0708 | X31: 0 | Y31: 0 | Z31: 0 | AA31: 0 | AB31: 8231531.3 | AC31: 0 | AD31: 0 | AE31: 56385511 | AF31: 1764740.2 | AG31: 0 | AH31: 0 | AI31: 5663101.5 | AJ31: 0 | AK31: 0 | AL31: 159643.87 | AM31: 0 | AN31: 101281.07 | AO31: 0 | AP31: 0 | AQ31: 0 | AR31: 0 | AS31: 0 | AT31: 7514684.1 | AU31: 0 | AV31: 0 | AW31: 0 | AX31: 0 | AY31: 1.1054998e+08 | AZ31: 414374.69 | BA31: 0 | BB31: 58025161 | BC31: 0 | BD31: 3403530.9 | BE31: 0 | BF31: 0 | BG31: 0 | BH31: 5286201.1 | BI31: 15523760 | BJ31: 0 | BK31: 0 | BL31: 321991.7 | BM31: 0 | BN31: 0 | BO31: 0 | BP31: 0 | BQ31: 0 | BR31: 809608.23 | BS31: 0 | BT31: 278577.78 | BU31: 0 | BV31: 0 | BW31: 0 | BX31: 3519612 | BY31: 0 | BZ31: 869060.08 | CA31: 0 | CB31: 15746473 | CC31: 0 | CD31: 0 | CE31: 0 | CF31: 0 | CG31: 54241.196 | CH31: 75117.372 | CI31: 0 | CJ31: 0 | CK31: 0 | CL31: 0 | CM31: 0
A32: Others | B32: 0 | C32: 0 | D32: 0 | E32: 0 | F32: 0 | G32: 0 | H32: 0 | I32: 0 | J32: 0 | K32: 0 | L32: 0 | M32: 0 | N32: 0 | O32: 0 | P32: 3527.6373 | Q32: 0 | R32: 0 | S32: 0 | T32: 0 | U32: 0 | V32: 0 | W32: 0 | X32: 2509598.7 | Y32: 0 | Z32: 6266516.9 | AA32: 0 | AB32: 37101.75 | AC32: 0 | AD32: 0 | AE32: 25715349 | AF32: 0 | AG32: 0 | AH32: 0 | AI32: 0 | AJ32: 0 | AK32: 0 | AL32: 0 | AM32: 0 | AN32: 0 | AO32: 0 | AP32: 0 | AQ32: 0 | AR32: 0 | AS32: 0 | AT32: 0 | AU32: 0 | AV32: 0 | AW32: 0 | AX32: 0 | AY32: 18818470 | AZ32: 0 | BA32: 0 | BB32: 0 | BC32: 0 | BD32: 1524156.9 | BE32: 0 | BF32: 0 | BG32: 0 | BH32: 0 | BI32: 1438072.5 | BJ32: 0 | BK32: 0 | BL32: 0 | BM32: 0 | BN32: 0 | BO32: 0 | BP32: 0 | BQ32: 0 | BR32: 0 | BS32: 0 | BT32: 0 | BU32: 0 | BV32: 0 | BW32: 0 | BX32: 3519612 | BY32: 0 | BZ32: 0 | CA32: 0 | CB32: 0 | CC32: 0 | CD32: 0 | CE32: 0 | CF32: 0 | CG32: 0 | CH32: 0 | CI32: 0 | CJ32: 0 | CK32: 0 | CL32: 0 | CM32: 0
A33: Total Value of water sold | B33: =SUM(B24:B32) -> 51751497 | C33: =SUM(C24:C32) -> 62870399 | D33: =SUM(D24:D32) -> 40706513 | E33: =SUM(E24:E32) -> 7386119.6 | F33: =SUM(F24:F32) -> 4.131674e+08 | G33: =SUM(G24:G32) -> 0 | H33: =SUM(H24:H32) -> 17234209 | I33: =SUM(I24:I32) -> 2.2522154e+08 | ... CM33: =SUM(CM24:CM32) -> 27547855
A37: Water Sold in cubic meters
A38: Individual | B38: =B24/$B$21 -> 363894.97 | C38: =C24/$C$21 -> 382936 | D38: =D24/$D$21 -> 553526.96 | E38: =E24/$E$21 -> 130687 | F38: =F24/$F$21 -> 6916011.2 | G38: =G24/$G$21 -> 0 | H38: =H24/$H$21 -> 208633 | I38: =I24/$I$21 -> 3373540 | J38: =J24/$J$21 -> 1323478.1 | K38: =K24/$K$21 -> 708717.3 | L38: =L24/$L$21 -> 767690.66 | M38: =M24/$M$21 -> 4544127.9 | N38: =N24/$N$21 -> 507558 | O38: =O24/$O$21 -> 525908.49 | P38: =P24/$P$21 -> 498540.19 | Q38: =Q24/$Q$21 -> 322528.73 | R38: =R24/$R$21 -> 1455561.9 | S38: =S24/$S$21 -> 1554147 | T38: =T24/$T$21 -> 1049558 | U38: =U24/$U$21 -> 333852 | V38: =V24/$V$21 -> 10556.936 | W38: =W24/$W$21 -> 1627087.6 | X38: =X24/$X$21 -> 216887.89 | Y38: =Y24/$Y$21 -> 248140 | Z38: =Z24/$Z$21 -> 448946.49 | AA38: =AA24/$AA$21 -> 590356 | AB38: =AB24/$AB$21 -> 4023766.4 | AC38: =AC24/$AC$21 -> 2343.9771 | AD38: =AD24/$AD$21 -> 2205290.6 | AE38: =AE24/$AE$21 -> 3236596.1 | AF38: =AF24/$AF$21 -> 238843.71 | AG38: =AG24/$AG$21 -> 1540044 | AH38: =AH24/$AH$21 -> 525315.86 | AI38: =AI24/$AI$21 -> 1084817.1 | AJ38: =AJ24/$AJ$21 -> 0 | AK38: =AK24/$AK$21 -> 119209.19 | AL38: =AL24/$AL$21 -> 3763255.8 | AM38: =AM24/$AM$21 -> 0 | AN38: =AN24/$AN$21 -> 832885.14 | AO38: =AO24/$AO$21 -> 63672.909 | AP38: =AP24/$AP$21 -> 181001.65 | AQ38: =AQ24/$AQ$21 -> 0 | AR38: =AR24/$AR$21 -> 1918235.8 | AS38: =AS24/$AS$21 -> 186394.41 | AT38: =AT24/$AT$21 -> 2747097.4 | AU38: =AU24/$AU$21 -> 18301.956 | AV38: =AV24/$AV$21 -> 2144016 | AW38: =AW24/$AW$21 -> 1416954 | AX38: =AX24/$AX$21 -> 9210 | AY38: =AY24/$AY$21 -> 10826630 | AZ38: =AZ24/$AZ$21 -> 761188.33 | BA38: =BA24/$BA$21 -> 4067550.5 | BB38: =BB24/$BB$21 -> 593614.74 | BC38: =BC24/$BC$21 -> 1779753.2 | BD38: =BD24/$BD$21 -> 455119 | BE38: =BE24/$BE$21 -> 604602.62 | BF38: =BF24/$BF$21 -> 666085.77 | BG38: =BG24/$BG$21 -> 649384.89 | BH38: =BH24/$BH$21 -> 695278.61 | BI38: =BI24/$BI$21 -> 1054803.7 | BJ38: =BJ24/$BJ$21 -> 62695 | BK38: =BK24/$BK$21 -> 2291579.5 | BL38: =BL24/$BL$21 -> 3090648.8 | BM38: =BM24/$BM$21 -> 43342.199 | BN38: =BN24/$BN$21 -> 381826.64 | BO38: =BO24/$BO$21 -> 2557721.2 | BP38: =BP24/$BP$21 -> 4466243.8 | BQ38: =BQ24/$BQ$21 -> 131700.2 | BR38: =BR24/$BR$21 -> 538859.04 | BS38: =BS24/$BS$21 -> 219029 | BT38: =BT24/$BT$21 -> 2595152 | BU38: =BU24/$BU$21 -> 2034153 | BV38: =BV24/$BV$21 -> 5688014.1 | BW38: =BW24/$BW$21 -> 363796.2 | BX38: =BX24/$BX$21 -> 65928.689 | BY38: =BY24/$BY$21 -> 341094.55 | BZ38: =BZ24/$BZ$21 -> 28824.732 | CA38: =CA24/$CA$21 -> 246763.59 | CB38: =CB24/$CB$21 -> 1135956.6 | CC38: =CC24/$CC$21 -> 259529.77 | CD38: =CD24/$CD$21 -> 476863.77 | CE38: =CE24/$CE$21 -> 83031.304 | CF38: =CF24/$CF$21 -> 350982 | CG38: =CG24/$CG$21 -> 228487 | CH38: =CH24/$CH$21 -> 610342.98 | CI38: =CI24/$CI$21 -> 493.39302 | CJ38: =CJ24/$CJ$21 -> 29996.876 | CK38: =CK24/$CK$21 -> 37.076575 | CM38: =CM24/$CM$21 -> 49946.281 | CO38: =SUM(B38:CM38) -> 1.0544718e+08
A39: Multi-dwelling units | B39: =B25/$B$21 -> 0 | C39: =C25/$C$21 -> 0 | D39: =D25/$D$21 -> 0 | E39: =E25/$E$21 -> 0 | F39: =F25/$F$21 -> 36631.195 | G39: =G25/$G$21 -> 0 | H39: =H25/$H$21 -> 104750 | I39: =I25/$I$21 -> 0 | J39: =J25/$J$21 -> 250388.24 | K39: =K25/$K$21 -> 0 | L39: =L25/$L$21 -> 0 | M39: =M25/$M$21 -> 0 | N39: =N25/$N$21 -> 31204 | O39: =O25/$O$21 -> 317801.16 | P39: =P25/$P$21 -> 0 | Q39: =Q25/$Q$21 -> 107509.21 | R39: =R25/$R$21 -> 0 | S39: =S25/$S$21 -> 89367.843 | T39: =T25/$T$21 -> 1364516.4 | U39: =U25/$U$21 -> 454523 | V39: =V25/$V$21 -> 11261.131 | W39: =W25/$W$21 -> 0 | X39: =X25/$X$21 -> 71077.338 | Y39: =Y25/$Y$21 -> 70897 | Z39: =Z25/$Z$21 -> 133234.6 | AA39: =AA25/$AA$21 -> 0 | AB39: =AB25/$AB$21 -> 0 | AC39: =AC25/$AC$21 -> 1154.5623 | AD39: =AD25/$AD$21 -> 0 | AE39: =AE25/$AE$21 -> 0 | AF39: =AF25/$AF$21 -> 99972.713 | AG39: =AG25/$AG$21 -> 0 | AH39: =AH25/$AH$21 -> 0 | AI39: =AI25/$AI$21 -> 0 | AJ39: =AJ25/$AJ$21 -> 0 | AK39: =AK25/$AK$21 -> 107606.66 | AL39: =AL25/$AL$21 -> 0 | AM39: =AM25/$AM$21 -> 0 | AN39: =AN25/$AN$21 -> 0 | AO39: =AO25/$AO$21 -> 3564.8348 | AP39: =AP25/$AP$21 -> 106880.11 | AQ39: =AQ25/$AQ$21 -> 0 | AR39: =AR25/$AR$21 -> 0 | AS39: =AS25/$AS$21 -> 0 | AT39: =AT25/$AT$21 -> 1177328.2 | AU39: =AU25/$AU$21 -> 0 | AV39: =AV25/$AV$21 -> 0 | AW39: =AW25/$AW$21 -> 0 | AX39: =AX25/$AX$21 -> 8423 | AY39: =AY25/$AY$21 -> 3867511.8 | AZ39: =AZ25/$AZ$21 -> 195366.9 | BA39: =BA25/$BA$21 -> 3478111.3 | BB39: =BB25/$BB$21 -> 690272.65 | BC39: =BC25/$BC$21 -> 0 | BD39: =BD25/$BD$21 -> 26320 | BE39: =BE25/$BE$21 -> 0 | BF39: =BF25/$BF$21 -> 0 | BG39: =BG25/$BG$21 -> 0 | BH39: =BH25/$BH$21 -> 0 | BI39: =BI25/$BI$21 -> 0 | BJ39: =BJ25/$BJ$21 -> 8830 | BK39: =BK25/$BK$21 -> 2039621.9 | BL39: =BL25/$BL$21 -> 166495.73 | BM39: =BM25/$BM$21 -> 80491.751 | BN39: =BN25/$BN$21 -> 933002.27 | BO39: =BO25/$BO$21 -> 0 | BP39: =BP25/$BP$21 -> 1655578.4 | BQ39: =BQ25/$BQ$21 -> 0 | BR39: =BR25/$BR$21 -> 1977.1737 | BS39: =BS25/$BS$21 -> 0 | BT39: =BT25/$BT$21 -> 0 | BU39: =BU25/$BU$21 -> 9226 | BV39: =BV25/$BV$21 -> 209844.31 | BW39: =BW25/$BW$21 -> 0 | BX39: =BX25/$BX$21 -> 126125.9 | BY39: =BY25/$BY$21 -> 90371.993 | BZ39: =BZ25/$BZ$21 -> 0 | CA39: =CA25/$CA$21 -> 39670.731 | CB39: =CB25/$CB$21 -> 564924.22 | CC39: =CC25/$CC$21 -> 0 | CD39: =CD25/$CD$21 -> 0 | CE39: =CE25/$CE$21 -> 71797.285 | CF39: =CF25/$CF$21 -> 0 | CG39: =CG25/$CG$21 -> 0 | CH39: =CH25/$CH$21 -> 0 | CI39: =CI25/$CI$21 -> 822.33224 | CJ39: =CJ25/$CJ$21 -> 74.984007 | CK39: =CK25/$CK$21 -> 21.422132 | CM39: =CM25/$CM$21 -> 37972.321 | CO39: =SUM(B39:CM39) -> 18842523
A40: Institutions | B40: =B26/$B$21 -> 629550.39 | C40: =C26/$C$21 -> 662492 | D40: =D26/$D$21 -> 5671.6374 | E40: =E26/$E$21 -> 35396 | F40: =F26/$F$21 -> 357362.28 | G40: =G26/$G$21 -> 0 | H40: =H26/$H$21 -> 41879 | I40: =I26/$I$21 -> 207812.98 | J40: =J26/$J$21 -> 429233.49 | K40: =K26/$K$21 -> 60956.581 | L40: =L26/$L$21 -> 411262.63 | M40: =M26/$M$21 -> 114599.28 | N40: =N26/$N$21 -> 9714 | O40: =O26/$O$21 -> 96448.285 | P40: =P26/$P$21 -> 27380.474 | Q40: =Q26/$Q$21 -> 71673.537 | R40: =R26/$R$21 -> 48477.09 | S40: =S26/$S$21 -> 172353.39 | T40: =T26/$T$21 -> 74886.036 | U40: =U26/$U$21 -> 4022 | V40: =V26/$V$21 -> 24633.136 | W40: =W26/$W$21 -> 18132.758 | X40: =X26/$X$21 -> 33071.628 | Y40: =Y26/$Y$21 -> 24814 | Z40: =Z26/$Z$21 -> 32022.401 | AA40: =AA26/$AA$21 -> 0 | AB40: =AB26/$AB$21 -> 262296.25 | AC40: =AC26/$AC$21 -> 135.0451 | AD40: =AD26/$AD$21 -> 207367.75 | AE40: =AE26/$AE$21 -> 283246.09 | AF40: =AF26/$AF$21 -> 60399.783 | AG40: =AG26/$AG$21 -> 32069.803 | AH40: =AH26/$AH$21 -> 0 | AI40: =AI26/$AI$21 -> 87782.088 | AJ40: =AJ26/$AJ$21 -> 0 | AK40: =AK26/$AK$21 -> 131480.43 | AL40: =AL26/$AL$21 -> 156622.1 | AM40: =AM26/$AM$21 -> 0 | AN40: =AN26/$AN$21 -> 180602.09 | AO40: =AO26/$AO$21 -> 5302.7627 | AP40: =AP26/$AP$21 -> 5773.0517 | AQ40: =AQ26/$AQ$21 -> 0 | AR40: =AR26/$AR$21 -> 95380.045 | AS40: =AS26/$AS$21 -> 29319.363 | AT40: =AT26/$AT$21 -> 112954.95 | AU40: =AU26/$AU$21 -> 0 | AV40: =AV26/$AV$21 -> 32278 | AW40: =AW26/$AW$21 -> 123983 | AX40: =AX26/$AX$21 -> 5440 | AY40: =AY26/$AY$21 -> 556666.44 | AZ40: =AZ26/$AZ$21 -> 5737.9526 | BA40: =BA26/$BA$21 -> 11014.927 | BB40: =BB26/$BB$21 -> 408106.42 | BC40: =BC26/$BC$21 -> 0 | BD40: =BD26/$BD$21 -> 68603 | BE40: =BE26/$BE$21 -> 46625.916 | BF40: =BF26/$BF$21 -> 313865.71 | BG40: =BG26/$BG$21 -> 259753.78 | BH40: =BH26/$BH$21 -> 0 | BI40: =BI26/$BI$21 -> 95091.425 | BJ40: =BJ26/$BJ$21 -> 4415 | BK40: =BK26/$BK$21 -> 592700.77 | BL40: =BL26/$BL$21 -> 12223.868 | BM40: =BM26/$BM$21 -> 38276.255 | BN40: =BN26/$BN$21 -> 5140.6754 | BO40: =BO26/$BO$21 -> 83662.36 | BP40: =BP26/$BP$21 -> 45061.927 | BQ40: =BQ26/$BQ$21 -> 782.35255 | BR40: =BR26/$BR$21 -> 46782.959 | BS40: =BS26/$BS$21 -> 0 | BT40: =BT26/$BT$21 -> 230405 | BU40: =BU26/$BU$21 -> 34165 | BV40: =BV26/$BV$21 -> 118138.51 | BW40: =BW26/$BW$21 -> 36991.146 | BX40: =BX26/$BX$21 -> 7069.074 | BY40: =BY26/$BY$21 -> 134520.28 | BZ40: =BZ26/$BZ$21 -> 11191.739 | CA40: =CA26/$CA$21 -> 136397 | CB40: =CB26/$CB$21 -> 31058.207 | CC40: =CC26/$CC$21 -> 0 | CD40: =CD26/$CD$21 -> 421.51426 | CE40: =CE26/$CE$21 -> 3404.9834 | CF40: =CF26/$CF$21 -> 25078 | CG40: =CG26/$CG$21 -> 15572 | CH40: =CH26/$CH$21 -> 0 | CI40: =CI26/$CI$21 -> 953.92059 | CJ40: =CJ26/$CJ$21 -> 2512.249 | CK40: =CK26/$CK$21 -> 48.199796 | CM40: =CM26/$CM$21 -> 84010.253 | CO40: =SUM(B40:CM40) -> 8872726.4
A41: Schools | B41: =B27/$B$21 -> 62337.169 | C41: =C27/$C$21 -> 65599 | D41: =D27/$D$21 -> 34418.332 | E41: =E27/$E$21 -> 21781 | F41: =F27/$F$21 -> 58026.568 | G41: =G27/$G$21 -> 0 | H41: =H27/$H$21 -> 75847 | I41: =I27/$I$21 -> 287565.34 | J41: =J27/$J$21 -> 643850.24 | K41: =K27/$K$21 -> 125621.57 | L41: =L27/$L$21 -> 0 | M41: =M27/$M$21 -> 67162.085 | N41: =N27/$N$21 -> 63358 | O41: =O27/$O$21 -> 34588.597 | P41: =P27/$P$21 -> 12654.505 | Q41: =Q27/$Q$21 -> 64505.965 | R41: =R27/$R$21 -> 0 | S41: =S27/$S$21 -> 89533.412 | T41: =T27/$T$21 -> 219649.83 | U41: =U27/$U$21 -> 3016 | V41: =V27/$V$21 -> 12668.666 | W41: =W27/$W$21 -> 97560.31 | X41: =X27/$X$21 -> 28279.348 | Y41: =Y27/$Y$21 -> 10634 | Z41: =Z27/$Z$21 -> 22171.209 | AA41: =AA27/$AA$21 -> 159934 | AB41: =AB27/$AB$21 -> 251598.53 | AC41: =AC27/$AC$21 -> 0 | AD41: =AD27/$AD$21 -> 102586.83 | AE41: =AE27/$AE$21 -> 49168.83 | AF41: =AF27/$AF$21 -> 25885.505 | AG41: =AG27/$AG$21 -> 48105.954 | AH41: =AH27/$AH$21 -> 48236.135 | AI41: =AI27/$AI$21 -> 64072.587 | AJ41: =AJ27/$AJ$21 -> 0 | AK41: =AK27/$AK$21 -> 77251.201 | AL41: =AL27/$AL$21 -> 80165.183 | AM41: =AM27/$AM$21 -> 0 | AN41: =AN27/$AN$21 -> 0 | AO41: =AO27/$AO$21 -> 3706.8224 | AP41: =AP27/$AP$21 -> 2297.5479 | AQ41: =AQ27/$AQ$21 -> 0 | AR41: =AR27/$AR$21 -> 41037.135 | AS41: =AS27/$AS$21 -> 13865.297 | AT41: =AT27/$AT$21 -> 75304.029 | AU41: =AU27/$AU$21 -> 841.6452 | AV41: =AV27/$AV$21 -> 174757 | AW41: =AW27/$AW$21 -> 177119 | AX41: =AX27/$AX$21 -> 5490 | AY41: =AY27/$AY$21 -> 53706.65 | AZ41: =AZ27/$AZ$21 -> 30096.099 | BA41: =BA27/$BA$21 -> 11260.083 | BB41: =BB27/$BB$21 -> 74505.892 | BC41: =BC27/$BC$21 -> 66077.267 | BD41: =BD27/$BD$21 -> 43177 | BE41: =BE27/$BE$21 -> 0 | BF41: =BF27/$BF$21 -> 323660.93 | BG41: =BG27/$BG$21 -> 129877.33 | BH41: =BH27/$BH$21 -> 220723.65 | BI41: =BI27/$BI$21 -> 85392.359 | BJ41: =BJ27/$BJ$21 -> 1766 | BK41: =BK27/$BK$21 -> 433275.67 | BL41: =BL27/$BL$21 -> 419275.55 | BM41: =BM27/$BM$21 -> 17240.245 | BN41: =BN27/$BN$21 -> 18863.482 | BO41: =BO27/$BO$21 -> 214917.74 | BP41: =BP27/$BP$21 -> 50788.738 | BQ41: =BQ27/$BQ$21 -> 4223.1968 | BR41: =BR27/$BR$21 -> 40184.838 | BS41: =BS27/$BS$21 -> 43700 | BT41: =BT27/$BT$21 -> 112007 | BU41: =BU27/$BU$21 -> 34306 | BV41: =BV27/$BV$21 -> 152541.62 | BW41: =BW27/$BW$21 -> 27720.89 | BX41: =BX27/$BX$21 -> 24378.222 | BY41: =BY27/$BY$21 -> 115883.38 | BZ41: =BZ27/$BZ$21 -> 12654.621 | CA41: =CA27/$CA$21 -> 32279.39 | CB41: =CB27/$CB$21 -> 8764.561 | CC41: =CC27/$CC$21 -> 54825 | CD41: =CD27/$CD$21 -> 8310.3878 | CE41: =CE27/$CE$21 -> 2405.7667 | CF41: =CF27/$CF$21 -> 17376 | CG41: =CG27/$CG$21 -> 8580 | CH41: =CH27/$CH$21 -> 6036.7541 | CI41: =CI27/$CI$21 -> 394.71231 | CJ41: =CJ27/$CJ$21 -> 3749.6205 | CK41: =CK27/$CK$21 -> 58.913345 | CM41: =CM27/$CM$21 -> 46385.861 | CO41: =SUM(B41:CM41) -> 6453622.8
A42: Commercial customers | B42: =B28/$B$21 -> 40288.86 | C42: =C28/$C$21 -> 42397 | D42: =D28/$D$21 -> 5291.7951 | E42: =E28/$E$21 -> 81679 | F42: =F28/$F$21 -> 1054692.8 | G42: =G28/$G$21 -> 0 | H42: =H28/$H$21 -> 23500 | I42: =I28/$I$21 -> 831931.79 | J42: =J28/$J$21 -> 751164.71 | K42: =K28/$K$21 -> 123747.79 | L42: =L28/$L$21 -> 109670.46 | M42: =M28/$M$21 -> 7901.3066 | N42: =N28/$N$21 -> 6801 | O42: =O28/$O$21 -> 75974.475 | P42: =P28/$P$21 -> 20184.351 | Q42: =Q28/$Q$21 -> 143345.98 | R42: =R28/$R$21 -> 123919.08 | S42: =S28/$S$21 -> 187461.57 | T42: =T28/$T$21 -> 98043.431 | U42: =U28/$U$21 -> 177987 | V42: =V28/$V$21 -> 9853.597 | W42: =W28/$W$21 -> 194121.14 | X42: =X28/$X$21 -> 18798.641 | Y42: =Y28/$Y$21 -> 0 | Z42: =Z28/$Z$21 -> 63802.501 | AA42: =AA28/$AA$21 -> 659601 | AB42: =AB28/$AB$21 -> 149831.69 | AC42: =AC28/$AC$21 -> 910.94089 | AD42: =AD28/$AD$21 -> 185408.4 | AE42: =AE28/$AE$21 -> 1724049.9 | AF42: =AF28/$AF$21 -> 31503.929 | AG42: =AG28/$AG$21 -> 56820.574 | AH42: =AH28/$AH$21 -> 0 | AI42: =AI28/$AI$21 -> 180037.57 | AJ42: =AJ28/$AJ$21 -> 0 | AK42: =AK28/$AK$21 -> 139714.84 | AL42: =AL28/$AL$21 -> 782503.07 | AM42: =AM28/$AM$21 -> 0 | AN42: =AN28/$AN$21 -> 198974.65 | AO42: =AO28/$AO$21 -> 0 | AP42: =AP28/$AP$21 -> 205557.22 | AQ42: =AQ28/$AQ$21 -> 0 | AR42: =AR28/$AR$21 -> 329973.45 | AS42: =AS28/$AS$21 -> 16676.618 | AT42: =AT28/$AT$21 -> 564774.75 | AU42: =AU28/$AU$21 -> 13019.979 | AV42: =AV28/$AV$21 -> 617829 | AW42: =AW28/$AW$21 -> 51365 | AX42: =AX28/$AX$21 -> 5216 | AY42: =AY28/$AY$21 -> 2730857.8 | AZ42: =AZ28/$AZ$21 -> 275983.51 | BA42: =BA28/$BA$21 -> 332466.06 | BB42: =BB28/$BB$21 -> 510256.34 | BC42: =BC28/$BC$21 -> 938133.57 | BD42: =BD28/$BD$21 -> 122614 | BE42: =BE28/$BE$21 -> 70465.464 | BF42: =BF28/$BF$21 -> 218571.15 | BG42: =BG28/$BG$21 -> 246765.51 | BH42: =BH28/$BH$21 -> 0 | BI42: =BI28/$BI$21 -> 340436.94 | BJ42: =BJ28/$BJ$21 -> 8830 | BK42: =BK28/$BK$21 -> 746015.98 | BL42: =BL28/$BL$21 -> 484589.92 | BM42: =BM28/$BM$21 -> 33772.608 | BN42: =BN28/$BN$21 -> 65671.199 | BO42: =BO28/$BO$21 -> 126207.19 | BP42: =BP28/$BP$21 -> 0 | BQ42: =BQ28/$BQ$21 -> 16580.097 | BR42: =BR28/$BR$21 -> 21285.076 | BS42: =BS28/$BS$21 -> 0 | BT42: =BT28/$BT$21 -> 338456 | BU42: =BU28/$BU$21 -> 37895 | BV42: =BV28/$BV$21 -> 2265237.7 | BW42: =BW28/$BW$21 -> 0 | BX42: =BX28/$BX$21 -> 0 | BY42: =BY28/$BY$21 -> 109295.38 | BZ42: =BZ28/$BZ$21 -> 6429.8184 | CA42: =CA28/$CA$21 -> 204594.49 | CB42: =CB28/$CB$21 -> 73619.739 | CC42: =CC28/$CC$21 -> 56787 | CD42: =CD28/$CD$21 -> 252.90856 | CE42: =CE28/$CE$21 -> 6965.1064 | CF42: =CF28/$CF$21 -> 0 | CG42: =CG28/$CG$21 -> 57625 | CH42: =CH28/$CH$21 -> 644.85636 | CI42: =CI28/$CI$21 -> 559.18719 | CJ42: =CJ28/$CJ$21 -> 1124.8862 | CK42: =CK28/$CK$21 -> 32.133197 | CM42: =CM28/$CM$21 -> 59171.195 | CO42: =SUM(B42:CM42) -> 20614520
A43: Industries | B43: =B29/$B$21 -> 0 | C43: =C29/$C$21 -> 0 | D43: =D29/$D$21 -> 431.8359 | E43: =E29/$E$21 -> 0 | F43: =F29/$F$21 -> 0 | G43: =G29/$G$21 -> 0 | H43: =H29/$H$21 -> 0 | I43: =I29/$I$21 -> 0 | J43: =J29/$J$21 -> 178845.26 | K43: =K29/$K$21 -> 1566.1445 | L43: =L29/$L$21 -> 0 | M43: =M29/$M$21 -> 0 | N43: =N29/$N$21 -> 45525 | O43: =O29/$O$21 -> 65.441102 | P43: =P29/$P$21 -> 587.52673 | Q43: =Q29/$Q$21 -> 0 | R43: =R29/$R$21 -> 0 | S43: =S29/$S$21 -> 95529.375 | T43: =T29/$T$21 -> 0 | U43: =U29/$U$21 -> 0 | V43: =V29/$V$21 -> 0 | W43: =W29/$W$21 -> 0 | X43: =X29/$X$21 -> 77999.632 | Y43: =Y29/$Y$21 -> 0 | Z43: =Z29/$Z$21 -> 0 | AA43: =AA29/$AA$21 -> 0 | AB43: =AB29/$AB$21 -> 276821.93 | AC43: =AC29/$AC$21 -> 0 | AD43: =AD29/$AD$21 -> 0 | AE43: =AE29/$AE$21 -> 11445.473 | AF43: =AF29/$AF$21 -> 0 | AG43: =AG29/$AG$21 -> 37880.799 | AH43: =AH29/$AH$21 -> 0 | AI43: =AI29/$AI$21 -> 0 | AJ43: =AJ29/$AJ$21 -> 0 | AK43: =AK29/$AK$21 -> 114354.06 | AL43: =AL29/$AL$21 -> 29518.3 | AM43: =AM29/$AM$21 -> 0 | AN43: =AN29/$AN$21 -> 0 | AO43: =AO29/$AO$21 -> 0 | AP43: =AP29/$AP$21 -> 80795.677 | AQ43: =AQ29/$AQ$21 -> 0 | AR43: =AR29/$AR$21 -> 0 | AS43: =AS29/$AS$21 -> 0 | AT43: =AT29/$AT$21 -> 376516.86 | AU43: =AU29/$AU$21 -> 0 | AV43: =AV29/$AV$21 -> 0 | AW43: =AW29/$AW$21 -> 0 | AX43: =AX29/$AX$21 -> 0 | AY43: =AY29/$AY$21 -> 175993.4 | AZ43: =AZ29/$AZ$21 -> 0 | BA43: =BA29/$BA$21 -> 0 | BB43: =BB29/$BB$21 -> 3321.1536 | BC43: =BC29/$BC$21 -> 0 | BD43: =BD29/$BD$21 -> 0 | BE43: =BE29/$BE$21 -> 0 | BF43: =BF29/$BF$21 -> 218020.45 | BG43: =BG29/$BG$21 -> 0 | BH43: =BH29/$BH$21 -> 0 | BI43: =BI29/$BI$21 -> 108446.1 | BJ43: =BJ29/$BJ$21 -> 1645 | BK43: =BK29/$BK$21 -> 0 | BL43: =BL29/$BL$21 -> 0 | BM43: =BM29/$BM$21 -> 0 | BN43: =BN29/$BN$21 -> 0 | BO43: =BO29/$BO$21 -> 0 | BP43: =BP29/$BP$21 -> 637684.77 | BQ43: =BQ29/$BQ$21 -> 0 | BR43: =BR29/$BR$21 -> 310.67387 | BS43: =BS29/$BS$21 -> 0 | BT43: =BT29/$BT$21 -> 31003 | BU43: =BU29/$BU$21 -> 0 | BV43: =BV29/$BV$21 -> 770750.74 | BW43: =BW29/$BW$21 -> 0 | BX43: =BX29/$BX$21 -> 0 | BY43: =BY29/$BY$21 -> 0 | BZ43: =BZ29/$BZ$21 -> 0 | CA43: =CA29/$CA$21 -> 16709.355 | CB43: =CB29/$CB$21 -> 0 | CC43: =CC29/$CC$21 -> 0 | CD43: =CD29/$CD$21 -> 0 | CE43: =CE29/$CE$21 -> 0 | CF43: =CF29/$CF$21 -> 0 | CG43: =CG29/$CG$21 -> 0 | CH43: =CH29/$CH$21 -> 0 | CI43: =CI29/$CI$21 -> 0 | CJ43: =CJ29/$CJ$21 -> 0 | CK43: =CK29/$CK$21 -> 0 | CM43: =CM29/$CM$21 -> 0 | CO43: =SUM(B43:CM43) -> 3291767.9
A44: Kiosks | B44: =B30/$B$21 -> 5033.6131 | C44: =C30/$C$21 -> 5297 | D44: =D30/$D$21 -> 20901.435 | E44: =E30/$E$21 -> 2723 | F44: =F30/$F$21 -> 447244.92 | G44: =G30/$G$21 -> 0 | H44: =H30/$H$21 -> 7174 | I44: =I30/$I$21 -> 38597.871 | J44: =J30/$J$21 -> 0 | K44: =K30/$K$21 -> 156.61445 | L44: =L30/$L$21 -> 27315.152 | M44: =M30/$M$21 -> 8349.3996 | N44: =N30/$N$21 -> 3956 | O44: =O30/$O$21 -> 297459.55 | P44: =P30/$P$21 -> 9843.2327 | Q44: =Q30/$Q$21 -> 7167.5719 | R44: =R30/$R$21 -> 10289.905 | S44: =S30/$S$21 -> 0 | T44: =T30/$T$21 -> 266035.32 | U44: =U30/$U$21 -> 2010 | V44: =V30/$V$21 -> 1407.5343 | W44: =W30/$W$21 -> 9145.6808 | X44: =X30/$X$21 -> 138427.9 | Y44: =Y30/$Y$21 -> 0 | Z44: =Z30/$Z$21 -> 141376.42 | AA44: =AA30/$AA$21 -> 44198 | AB44: =AB30/$AB$21 -> 219487.59 | AC44: =AC30/$AC$21 -> 19.122742 | AD44: =AD30/$AD$21 -> 573.45598 | AE44: =AE30/$AE$21 -> 406237.47 | AF44: =AF30/$AF$21 -> 108810.13 | AG44: =AG30/$AG$21 -> 120993.91 | AH44: =AH30/$AH$21 -> 0 | AI44: =AI30/$AI$21 -> 17150.63 | AJ44: =AJ30/$AJ$21 -> 0 | AK44: =AK30/$AK$21 -> 20802.608 | AL44: =AL30/$AL$21 -> 350245.92 | AM44: =AM30/$AM$21 -> 0 | AN44: =AN30/$AN$21 -> 0 | AO44: =AO30/$AO$21 -> 14430.671 | AP44: =AP30/$AP$21 -> 22337.746 | AQ44: =AQ30/$AQ$21 -> 0 | AR44: =AR30/$AR$21 -> 37023.6 | AS44: =AS30/$AS$21 -> 3374.314 | AT44: =AT30/$AT$21 -> 666417.45 | AU44: =AU30/$AU$21 -> 29.791438 | AV44: =AV30/$AV$21 -> 8754 | AW44: =AW30/$AW$21 -> 1771 | AX44: =AX30/$AX$21 -> 8903 | AY44: =AY30/$AY$21 -> 1543705.4 | AZ44: =AZ30/$AZ$21 -> 82001.673 | BA44: =BA30/$BA$21 -> 5496.0607 | BB44: =BB30/$BB$21 -> 31508.435 | BC44: =BC30/$BC$21 -> 5109.9648 | BD44: =BD30/$BD$21 -> 30292 | BE44: =BE30/$BE$21 -> 0 | BF44: =BF30/$BF$21 -> 0 | BG44: =BG30/$BG$21 -> 12986.49 | BH44: =BH30/$BH$21 -> 0 | BI44: =BI30/$BI$21 -> 3583.2159 | BJ44: =BJ30/$BJ$21 -> 884 | BK44: =BK30/$BK$21 -> 13807.197 | BL44: =BL30/$BL$21 -> 73796.347 | BM44: =BM30/$BM$21 -> 6754.9435 | BN44: =BN30/$BN$21 -> 24329.727 | BO44: =BO30/$BO$21 -> 3907.5192 | BP44: =BP30/$BP$21 -> 60169.373 | BQ44: =BQ30/$BQ$21 -> 3128.1544 | BR44: =BR30/$BR$21 -> 306206.95 | BS44: =BS30/$BS$21 -> 0 | BT44: =BT30/$BT$21 -> 39909 | BU44: =BU30/$BU$21 -> 155 | BV44: =BV30/$BV$21 -> 9560.0208 | BW44: =BW30/$BW$21 -> 6542.7614 | BX44: =BX30/$BX$21 -> 21397.778 | BY44: =BY30/$BY$21 -> 3659.4201 | BZ44: =BZ30/$BZ$21 -> 0 | CA44: =CA30/$CA$21 -> 5569.446 | CB44: =CB30/$CB$21 -> 10692.507 | CC44: =CC30/$CC$21 -> 2557 | CD44: =CD30/$CD$21 -> 674.42282 | CE44: =CE30/$CE$21 -> 84.55476 | CF44: =CF30/$CF$21 -> 1158 | CG44: =CG30/$CG$21 -> 11074 | CH44: =CH30/$CH$21 -> 0 | CI44: =CI30/$CI$21 -> 65.783626 | CJ44: =CJ30/$CJ$21 -> 37.481499 | CK44: =CK30/$CK$21 -> 8.2381354 | CM44: =CM30/$CM$21 -> 20965.089 | CO44: =SUM(B44:CM44) -> 5843250.5
A45: Bulk | B45: =B31/$B$21 -> 0 | C45: =C31/$C$21 -> 0 | D45: =D31/$D$21 -> 0 | E45: =E31/$E$21 -> 0 | F45: =F31/$F$21 -> 0 | G45: =G31/$G$21 -> 0 | H45: =H31/$H$21 -> 0 | I45: =I31/$I$21 -> 0 | J45: =J31/$J$21 -> 0 | K45: =K31/$K$21 -> 0 | L45: =L31/$L$21 -> 54936.104 | M45: =M31/$M$21 -> 0 | N45: =N31/$N$21 -> 22796 | O45: =O31/$O$21 -> 0 | P45: =P31/$P$21 -> 0 | Q45: =Q31/$Q$21 -> 0 | R45: =R31/$R$21 -> 0 | S45: =S31/$S$21 -> 205447.48 | T45: =T31/$T$21 -> 0 | U45: =U31/$U$21 -> 30167 | V45: =V31/$V$21 -> 0 | W45: =W31/$W$21 -> 128.52355 | X45: =X31/$X$21 -> 0 | Y45: =Y31/$Y$21 -> 0 | Z45: =Z31/$Z$21 -> 0 | AA45: =AA31/$AA$21 -> 0 | AB45: =AB31/$AB$21 -> 163004.95 | AC45: =AC31/$AC$21 -> 0 | AD45: =AD31/$AD$21 -> 0 | AE45: =AE31/$AE$21 -> 677008.55 | AF45: =AF31/$AF$21 -> 22976.233 | AG45: =AG31/$AG$21 -> 0 | AH45: =AH31/$AH$21 -> 0 | AI45: =AI31/$AI$21 -> 86073.994 | AJ45: =AJ31/$AJ$21 -> 0 | AK45: =AK31/$AK$21 -> 0 | AL45: =AL31/$AL$21 -> 1976.59 | AM45: =AM31/$AM$21 -> 0 | AN45: =AN31/$AN$21 -> 1556.1125 | AO45: =AO31/$AO$21 -> 0 | AP45: =AP31/$AP$21 -> 0 | AQ45: =AQ31/$AQ$21 -> 0 | AR45: =AR31/$AR$21 -> 0 | AS45: =AS31/$AS$21 -> 0 | AT45: =AT31/$AT$21 -> 102806.33 | AU45: =AU31/$AU$21 -> 0 | AV45: =AV31/$AV$21 -> 0 | AW45: =AW31/$AW$21 -> 0 | AX45: =AX31/$AX$21 -> 0 | AY45: =AY31/$AY$21 -> 2922762.8 | AZ45: =AZ31/$AZ$21 -> 8460.5397 | BA45: =BA31/$BA$21 -> 0 | BB45: =BB31/$BB$21 -> 1518629.4 | BC45: =BC31/$BC$21 -> 0 | BD45: =BD31/$BD$21 -> 27317 | BE45: =BE31/$BE$21 -> 0 | BF45: =BF31/$BF$21 -> 0 | BG45: =BG31/$BG$21 -> 0 | BH45: =BH31/$BH$21 -> 165542.74 | BI45: =BI31/$BI$21 -> 222714.68 | BJ45: =BJ31/$BJ$21 -> 0 | BK45: =BK31/$BK$21 -> 0 | BL45: =BL31/$BL$21 -> 7868.7841 | BM45: =BM31/$BM$21 -> 0 | BN45: =BN31/$BN$21 -> 0 | BO45: =BO31/$BO$21 -> 0 | BP45: =BP31/$BP$21 -> 0 | BQ45: =BQ31/$BQ$21 -> 0 | BR45: =BR31/$BR$21 -> 19191.291 | BS45: =BS31/$BS$21 -> 0 | BT45: =BT31/$BT$21 -> 3588 | BU45: =BU31/$BU$21 -> 0 | BV45: =BV31/$BV$21 -> 0 | BW45: =BW31/$BW$21 -> 0 | BX45: =BX31/$BX$21 -> 29719.342 | BY45: =BY31/$BY$21 -> 0 | BZ45: =BZ31/$BZ$21 -> 16665.089 | CA45: =CA31/$CA$21 -> 0 | CB45: =CB31/$CB$21 -> 247405.15 | CC45: =CC31/$CC$21 -> 0 | CD45: =CD31/$CD$21 -> 0 | CE45: =CE31/$CE$21 -> 0 | CF45: =CF31/$CF$21 -> 0 | CG45: =CG31/$CG$21 -> 930 | CH45: =CH31/$CH$21 -> 1133.4123 | CI45: =CI31/$CI$21 -> 0 | CJ45: =CJ31/$CJ$21 -> 0 | CK45: =CK31/$CK$21 -> 0 | CM45: =CM31/$CM$21 -> 0 | CO45: =SUM(B45:CM45) -> 6560806.1
A46: Others | B46: =B32/$B$21 -> 0 | C46: =C32/$C$21 -> 0 | D46: =D32/$D$21 -> 0 | E46: =E32/$E$21 -> 0 | F46: =F32/$F$21 -> 0 | G46: =G32/$G$21 -> 0 | H46: =H32/$H$21 -> 0 | I46: =I32/$I$21 -> 0 | J46: =J32/$J$21 -> 0 | K46: =K32/$K$21 -> 0 | L46: =L32/$L$21 -> 0 | M46: =M32/$M$21 -> 0 | N46: =N32/$N$21 -> 0 | O46: =O32/$O$21 -> 0 | P46: =P32/$P$21 -> 36.720421 | Q46: =Q32/$Q$21 -> 0 | R46: =R32/$R$21 -> 0 | S46: =S32/$S$21 -> 0 | T46: =T32/$T$21 -> 0 | U46: =U32/$U$21 -> 0 | V46: =V32/$V$21 -> 0 | W46: =W32/$W$21 -> 0 | X46: =X32/$X$21 -> 18100.62 | Y46: =Y32/$Y$21 -> 0 | Z46: =Z32/$Z$21 -> 94390.379 | AA46: =AA32/$AA$21 -> 0 | AB46: =AB32/$AB$21 -> 734.70765 | AC46: =AC32/$AC$21 -> 0 | AD46: =AD32/$AD$21 -> 0 | AE46: =AE32/$AE$21 -> 308758.6 | AF46: =AF32/$AF$21 -> 0 | AG46: =AG32/$AG$21 -> 0 | AH46: =AH32/$AH$21 -> 0 | AI46: =AI32/$AI$21 -> 0 | AJ46: =AJ32/$AJ$21 -> 0 | AK46: =AK32/$AK$21 -> 0 | AL46: =AL32/$AL$21 -> 0 | AM46: =AM32/$AM$21 -> 0 | AN46: =AN32/$AN$21 -> 0 | AO46: =AO32/$AO$21 -> 0 | AP46: =AP32/$AP$21 -> 0 | AQ46: =AQ32/$AQ$21 -> 0 | AR46: =AR32/$AR$21 -> 0 | AS46: =AS32/$AS$21 -> 0 | AT46: =AT32/$AT$21 -> 0 | AU46: =AU32/$AU$21 -> 0 | AV46: =AV32/$AV$21 -> 0 | AW46: =AW32/$AW$21 -> 0 | AX46: =AX32/$AX$21 -> 0 | AY46: =AY32/$AY$21 -> 497529.95 | AZ46: =AZ32/$AZ$21 -> 0 | BA46: =BA32/$BA$21 -> 0 | BB46: =BB32/$BB$21 -> 0 | BC46: =BC32/$BC$21 -> 0 | BD46: =BD32/$BD$21 -> 12233 | BE46: =BE32/$BE$21 -> 0 | BF46: =BF32/$BF$21 -> 0 | BG46: =BG32/$BG$21 -> 0 | BH46: =BH32/$BH$21 -> 0 | BI46: =BI32/$BI$21 -> 20631.589 | BJ46: =BJ32/$BJ$21 -> 0 | BK46: =BK32/$BK$21 -> 0 | BL46: =BL32/$BL$21 -> 0 | BM46: =BM32/$BM$21 -> 0 | BN46: =BN32/$BN$21 -> 0 | BO46: =BO32/$BO$21 -> 0 | BP46: =BP32/$BP$21 -> 0 | BQ46: =BQ32/$BQ$21 -> 0 | BR46: =BR32/$BR$21 -> 0 | BS46: =BS32/$BS$21 -> 0 | BT46: =BT32/$BT$21 -> 0 | BU46: =BU32/$BU$21 -> 0 | BV46: =BV32/$BV$21 -> 0 | BW46: =BW32/$BW$21 -> 0 | BX46: =BX32/$BX$21 -> 29719.342 | BY46: =BY32/$BY$21 -> 0 | BZ46: =BZ32/$BZ$21 -> 0 | CA46: =CA32/$CA$21 -> 0 | CB46: =CB32/$CB$21 -> 0 | CC46: =CC32/$CC$21 -> 0 | CD46: =CD32/$CD$21 -> 0 | CE46: =CE32/$CE$21 -> 0 | CF46: =CF32/$CF$21 -> 0 | CG46: =CG32/$CG$21 -> 0 | CH46: =CH32/$CH$21 -> 0 | CI46: =CI32/$CI$21 -> 0 | CJ46: =CJ32/$CJ$21 -> 0 | CK46: =CK32/$CK$21 -> 0 | CM46: =CM32/$CM$21 -> 0 | CO46: =SUM(B46:CM46) -> 982134.91
A47: Total Sold | B47: =SUM(B38:B46) -> 1101105 | C47: =SUM(C38:C46) -> 1158721 | D47: =SUM(D38:D46) -> 620242 | E47: =SUM(E38:E46) -> 272266 | F47: =SUM(F38:F46) -> 8869969 | G47: =SUM(G38:G46) -> 0 | H47: =SUM(H38:H46) -> 461783 | I47: =SUM(I38:I46) -> 4739448 | ... CM47: =SUM(CM38:CM46) -> 298451 | CO47: =SUM(B47:CM47) -> 1.7690853e+08
A48: Total Billed Volume | B48: 1101104.9 | C48: 2005094 | D48: 620242 | E48: 272266 | F48: 8869969 | G48: 141426 | H48: 461783 | I48: 4739448 | J48: 3576960 | K48: 1020766 | L48: 1370875 | M48: 4742140 | N48: 690912 | O48: 1348246 | P48: 569227 | Q48: 716731 | R48: 1638248 | S48: 1214494 | T48: 3072689 | U48: 1005557 | V48: 70381 | W48: 1946176 | X48: 602643 | Y48: 354485 | Z48: 935944 | AA48: 1454089 | AB48: 5347542 | AC48: 440400 | AD48: 2701227 | AE48: 6696511 | AF48: 1653210 | AG48: 1835915 | AH48: 573552 | AI48: 1519934 | AJ48: 1273305 | AK48: 710419 | AL48: 5164287 | AM48: 344242 | AN48: 1214018 | AO48: 90678 | AP48: 604643 | AQ48: 42602 | AR48: 2421650 | AS48: 249630 | AT48: 5823200 | AU48: 2068366 | AV48: 2977634 | AW48: 1771192 | AX48: 42682 | AY48: 89727204 | AZ48: 1358834.9 | BA48: 7905899 | BB48: 3830215 | BC48: 2789074 | BD48: 785675 | BE48: 721694 | BF48: 1740204 | BG48: 1298768 | BH48: 1081545 | BI48: 1931100 | BJ48: 89065 | BK48: 6117001 | BL48: 4254899 | BM48: 219878 | BN48: 1428834 | BO48: 2986416 | BP48: 6915527 | BQ48: 156414 | BR48: 974798 | BS48: 262729 | BT48: 3350520 | BU48: 2149900 | BV48: 9214087 | BW48: 435051 | BX48: 274619 | BY48: 794825 | BZ48: 75766 | CA48: 681984 | CB48: 2072421 | CC48: 352197 | CD48: 486523 | CE48: 167689 | CF48: 394594 | CG48: 322268 | CH48: 618158 | CI48: 361390 | CJ48: 566988 | CK48: 125326 | CL48: 571536 | CM48: 298451 | CO48: =SUM(B48:CM48) -> 2.499988e+08
A49: Non-payment of billed | CO49: =CO48-CO47 -> 73090276
A52: Non-Revenue Water | B52: =B10-B14 -> 471902.1 | C52: =C10-C14 -> 2418910 | D52: =D10-D14 -> 587408 | E52: =E10-E14 -> 577887 | F52: =F10-F14 -> 6420526 | G52: =G10-G14 -> 208494 | H52: =H10-H14 -> 572422 | I52: =I10-I14 -> 2898443 | ... CM52: =CM10-CM14 -> 160914 | CO52: =SUM(B52:CM52) -> 2.240454e+08
A54: Water Proportions
A55: Individual | B55: =B38/B47 -> 0.33048163 | C55: =C38/$C$47 -> 0.33048163 | D55: =D38/$D$47 -> 0.89243709 | E55: =E38/$E$47 -> 0.4799975 | F55: =F38/$F$47 -> 0.77971087 | G55: =G38/G47 -> #DIV/0! | H55: =H38/$H$47 -> 0.45179879 | I55: =I38/$I$47 -> 0.71180019 | J55: =J38/$J$47 -> 0.3700008 | K55: =K38/$K$47 -> 0.69429948 | L55: =L38/$L$47 -> 0.56000048 | M55: =M38/$M$47 -> 0.95824415 | N55: =N38/$N$47 -> 0.73462033 | O55: =O38/$O$47 -> 0.39006864 | P55: =P38/$P$47 -> 0.87581965 | Q55: =Q38/$Q$47 -> 0.4499997 | R55: =R38/$R$47 -> 0.88848692 | S55: =S38/$S$47 -> 0.64922758 | T55: =T38/$T$47 -> 0.34157638 | U55: =U38/$U$47 -> 0.33200043 | V55: =V38/$V$47 -> 0.14999696 | W55: =W38/$W$47 -> 0.83604339 | X55: =X38/$X$47 -> 0.35989448 | Y55: =Y38/$Y$47 -> 0.70000141 | Z55: =Z38/$Z$47 -> 0.47967239 | AA55: =AA38/$AA$47 -> 0.40599716 | AB55: =AB38/$AB$47 -> 0.75245157 | AC55: =AC38/$AC$47 -> 0.51361915 | AD55: =AD38/$AD$47 -> 0.81640327 | AE55: =AE38/$AE$47 -> 0.48332573 | AF55: =AF38/$AF$47 -> 0.40592616 | AG55: =AG38/$AG$47 -> 0.83884273 | AH55: =AH38/$AH$47 -> 0.91589928 | AI55: =AI38/$AI$47 -> 0.71372647 | AJ55: =AJ38/AJ47 -> #DIV/0! | AK55: =AK38/$AK$47 -> 0.16780124 | AL55: =AL38/$AL$47 -> 0.72870773 | AM55: =AM38/AM47 -> #DIV/0! | AN55: =AN38/$AN$47 -> 0.68605667 | AO55: =AO38/$AO$47 -> 0.70218696 | AP55: =AP38/$AP$47 -> 0.29935292 | AQ55: =AQ38/AQ47 -> #DIV/0! | AR55: =AR38/$AR$47 -> 0.79211933 | AS55: =AS38/$AS$47 -> 0.74668272 | AT55: =AT38/$AT$47 -> 0.47175048 | AU55: =AU38/$AU$47 -> 0.56850074 | AV55: =AV38/$AV$47 -> 0.72004014 | AW55: =AW38/$AW$47 -> 0.80000023 | AX55: =AX38/$AX$47 -> 0.21578183 | AY55: =AY38/$AY$47 -> 0.46716116 | AZ55: =AZ38/$AZ$47 -> 0.56017716 | BA55: =BA38/$BA$47 -> 0.51449564 | BB55: =BB38/$BB$47 -> 0.15498209 | BC55: =BC38/$BC$47 -> 0.63811616 | BD55: =BD38/$BD$47 -> 0.57927133 | BE55: =BE38/$BE$47 -> 0.83775481 | BF55: =BF38/$BF$47 -> 0.38276304 | BG55: =BG38/$BG$47 -> 0.50000068 | BH55: =BH38/$BH$47 -> 0.64285685 | BI55: =BI38/$BI$47 -> 0.5462191 | BJ55: =BJ38/$BJ$47 -> 0.7039241 | BK55: =BK38/$BK$47 -> 0.37462467 | BL55: =BL38/$BL$47 -> 0.72637419 | BM55: =BM38/$BM$47 -> 0.19711931 | BN55: =BN38/$BN$47 -> 0.26722953 | BO55: =BO38/$BO$47 -> 0.85645175 | BP55: =BP38/$BP$47 -> 0.64582841 | BQ55: =BQ38/$BQ$47 -> 0.84199751 | BR55: =BR38/$BR$47 -> 0.55279046 | BS55: =BS38/$BS$47 -> 0.83366891 | BT55: =BT38/$BT$47 -> 0.77455201 | BU55: =BU38/$BU$47 -> 0.94616168 | BV55: =BV38/$BV$47 -> 0.61731717 | BW55: =BW38/$BW$47 -> 0.83621507 | BX55: =BX38/$BX$47 -> 0.21662959 | BY55: =BY38/$BY$47 -> 0.42914421 | BZ55: =BZ38/$BZ$47 -> 0.38044416 | CA55: =CA38/$CA$47 -> 0.36183193 | CB55: =CB38/$CB$47 -> 0.54813024 | CC55: =CC38/$CC$47 -> 0.69448923 | CD55: =CD38/$CD$47 -> 0.9801464 | CE55: =CE38/$CE$47 -> 0.49515057 | CF55: =CF38/$CF$47 -> 0.88947627 | CG55: =CG38/$CG$47 -> 0.70899686 | CH55: =CH38/$CH$47 -> 0.98735756 | CI55: =CI38/$CI$47 -> 0.14999808 | CJ55: =CJ38/$CJ$47 -> 0.79999995 | CK55: =CK38/$CK$47 -> 0.17999807 | CL55: =CL38/CL47 -> #DIV/0! | CM55: =CM38/$CM$47 -> 0.1673517
A56: Multi-dwelling units | B56: =B39/$B$47 -> 0 | C56: =C39/$C$47 -> 0 | D56: =D39/$D$47 -> 0 | E56: =E39/$E$47 -> 0 | F56: =F39/$F$47 -> 0.0041297997 | H56: =H39/$H$47 -> 0.22683815 | I56: =I39/$I$47 -> 0 | J56: =J39/$J$47 -> 0.07000029 | K56: =K39/$K$47 -> 0 | L56: =L39/$L$47 -> 0 | M56: =M39/$M$47 -> 0 | N56: =N39/$N$47 -> 0.045163494 | O56: =O39/$O$47 -> 0.23571452 | P56: =P39/$P$47 -> 0 | Q56: =Q39/$Q$47 -> 0.14999939 | R56: =R39/$R$47 -> 0 | S56: =S39/$S$47 -> 0.03733242 | T56: =T39/$T$47 -> 0.44407892 | U56: =U39/$U$47 -> 0.45200218 | V56: =V39/$V$47 -> 0.16000243 | W56: =W39/$W$47 -> 0 | X56: =X39/$X$47 -> 0.11794269 | Y56: =Y39/$Y$47 -> 0.2 | Z56: =Z39/$Z$47 -> 0.14235317 | AA56: =AA39/$AA$47 -> 0 | AB56: =AB39/$AB$47 -> 0 | AC56: =AC39/$AC$47 -> 0.25299109 | AD56: =AD39/$AD$47 -> 0 | AE56: =AE39/$AE$47 -> 0 | AF56: =AF39/$AF$47 -> 0.16990835 | AG56: =AG39/$AG$47 -> 0 | AH56: =AH39/$AH$47 -> 0 | AI56: =AI39/$AI$47 -> 0 | AK56: =AK39/$AK$47 -> 0.15146929 | AL56: =AL39/$AL$47 -> 0 | AN56: =AN39/$AN$47 -> 0 | AO56: =AO39/$AO$47 -> 0.039313117 | AP56: =AP39/$AP$47 -> 0.17676564 | AR56: =AR39/$AR$47 -> 0 | AS56: =AS39/$AS$47 -> 0 | AT56: =AT39/$AT$47 -> 0.20217891 | AU56: =AU39/$AU$47 -> 0 | AV56: =AV39/$AV$47 -> 0 | AW56: =AW39/$AW$47 -> 0 | AX56: =AX39/$AX$47 -> 0.19734314 | AY56: =AY39/$AY$47 -> 0.1668803 | AZ56: =AZ39/$AZ$47 -> 0.14377529 | BA56: =BA39/$BA$47 -> 0.43993875 | BB56: =BB39/$BB$47 -> 0.18021773 | BC56: =BC39/$BC$47 -> 0 | BD56: =BD39/$BD$47 -> 0.033499857 | BE56: =BE39/$BE$47 -> 0 | BF56: =BF39/$BF$47 -> 0 | BG56: =BG39/$BG$47 -> 0 | BH56: =BH39/$BH$47 -> 0 | BI56: =BI39/$BI$47 -> 0 | BJ56: =BJ39/$BJ$47 -> 0.099141077 | BK56: =BK39/$BK$47 -> 0.33343495 | BL56: =BL39/$BL$47 -> 0.03913036 | BM56: =BM39/$BM$47 -> 0.3660746 | BN56: =BN39/$BN$47 -> 0.65298157 | BO56: =BO39/$BO$47 -> 0 | BP56: =BP39/$BP$47 -> 0.23940018 | BQ56: =BQ39/$BQ$47 -> 0 | BR56: =BR39/$BR$47 -> 0.0020282907 | BS56: =BS39/$BS$47 -> 0 | BT56: =BT39/$BT$47 -> 0 | BU56: =BU39/$BU$47 -> 0.0042913624 | BV56: =BV39/$BV$47 -> 0.022774292 | BW56: =BW39/$BW$47 -> 0 | BX56: =BX39/$BX$47 -> 0.41442657 | BY56: =BY39/$BY$47 -> 0.11370049 | BZ56: =BZ39/$BZ$47 -> 0 | CA56: =CA39/$CA$47 -> 0.058169592 | CB56: =CB39/$CB$47 -> 0.27259144 | CC56: =CC39/$CC$47 -> 0 | CD56: =CD39/$CD$47 -> 0 | CE56: =CE39/$CE$47 -> 0.42815739 | CF56: =CF39/$CF$47 -> 0 | CG56: =CG39/$CG$47 -> 0 | CH56: =CH39/$CH$47 -> 0 | CI56: =CI39/$CI$47 -> 0.25 | CJ56: =CJ39/$CJ$47 -> 0.0019997817 | CK56: =CK39/$CK$47 -> 0.10399942 | CM56: =CM39/$CM$47 -> 0.12723134
A57: Institutions | B57: =B40/$B$47 -> 0.57174419 | C57: =C40/$C$47 -> 0.57174419 | D57: =D40/$D$47 -> 0.009144233 | E57: =E40/$E$47 -> 0.13000522 | F57: =F40/$F$47 -> 0.040289011 | H57: =H40/$H$47 -> 0.090689783 | I57: =I40/$I$47 -> 0.043847508 | J57: =J40/$J$47 -> 0.11999952 | K57: =K40/$K$47 -> 0.059716508 | L57: =L40/$L$47 -> 0.30000009 | M57: =M40/$M$47 -> 0.024166152 | N57: =N40/$N$47 -> 0.014059678 | O57: =O40/$O$47 -> 0.071536118 | P57: =P40/$P$47 -> 0.048101151 | Q57: =Q40/$Q$47 -> 0.10000061 | R57: =R40/$R$47 -> 0.029590813 | S57: =S40/$S$47 -> 0.071998709 | T57: =T40/$T$47 -> 0.024371499 | U57: =U40/$U$47 -> 0.0039996937 | V57: =V40/$V$47 -> 0.34999696 | W57: =W40/$W$47 -> 0.0093171215 | X57: =X40/$X$47 -> 0.054877645 | Y57: =Y40/$Y$47 -> 0.070000141 | Z57: =Z40/$Z$47 -> 0.034214014 | AA57: =AA40/$AA$47 -> 0 | AB57: =AB40/$AB$47 -> 0.049049871 | AC57: =AC40/$AC$47 -> 0.02959148 | AD57: =AD40/$AD$47 -> 0.076767985 | AE57: =AE40/$AE$47 -> 0.042297562 | AF57: =AF40/$AF$47 -> 0.10265228 | AG57: =AG40/$AG$47 -> 0.017468022 | AH57: =AH40/$AH$47 -> 0 | AI57: =AI40/$AI$47 -> 0.057753881 | AK57: =AK40/$AK$47 -> 0.18507449 | AL57: =AL40/$AL$47 -> 0.030327923 | AN57: =AN40/$AN$47 -> 0.14876393 | AO57: =AO40/$AO$47 -> 0.058479044 | AP57: =AP40/$AP$47 -> 0.0095478682 | AR57: =AR40/$AR$47 -> 0.039386387 | AS57: =AS40/$AS$47 -> 0.11745128 | AT57: =AT40/$AT$47 -> 0.019397402 | AU57: =AU40/$AU$47 -> 0 | AV57: =AV40/$AV$47 -> 0.01084015 | AW57: =AW40/$AW$47 -> 0.069999752 | AX57: =AX40/$AX$47 -> 0.1274542 | AY57: =AY40/$AY$47 -> 0.024019749 | AZ57: =AZ40/$AZ$47 -> 0.0042227 | BA57: =BA40/$BA$47 -> 0.0013932542 | BB57: =BB40/$BB$47 -> 0.10654922 | BC57: =BC40/$BC$47 -> 0 | BD57: =BD40/$BD$47 -> 0.087317275 | BE57: =BE40/$BE$47 -> 0.064606213 | BF57: =BF40/$BF$47 -> 0.18036145 | BG57: =BG40/$BG$47 -> 0.20000014 | BH57: =BH40/$BH$47 -> 0 | BI57: =BI40/$BI$47 -> 0.049242103 | BJ57: =BJ40/$BJ$47 -> 0.049570538 | BK57: =BK40/$BK$47 -> 0.096894012 | BL57: =BL40/$BL$47 -> 0.0028728927 | BM57: =BM40/$BM$47 -> 0.17407951 | BN57: =BN40/$BN$47 -> 0.0035978115 | BO57: =BO40/$BO$47 -> 0.028014302 | BP57: =BP40/$BP$47 -> 0.006516051 | BQ57: =BQ40/$BQ$47 -> 0.0050018064 | BR57: =BR40/$BR$47 -> 0.047992465 | BS57: =BS40/$BS$47 -> 0 | BT57: =BT40/$BT$47 -> 0.068766938 | BU57: =BU40/$BU$47 -> 0.015891437 | BV57: =BV40/$BV$47 -> 0.01282151 | BW57: =BW40/$BW$47 -> 0.085027149 | BX57: =BX40/$BX$47 -> 0.023227681 | BY57: =BY40/$BY$47 -> 0.16924516 | BZ57: =BZ40/$BZ$47 -> 0.14771453 | CA57: =CA40/$CA$47 -> 0.2000003 | CB57: =CB40/$CB$47 -> 0.014986437 | CC57: =CC40/$CC$47 -> 0 | CD57: =CD40/$CD$47 -> 0.00086638095 | CE57: =CE40/$CE$47 -> 0.020305348 | CF57: =CF40/$CF$47 -> 0.063553931 | CG57: =CG40/$CG$47 -> 0.048320032 | CH57: =CH40/$CH$47 -> 0 | CI57: =CI40/$CI$47 -> 0.29000462 | CJ57: =CJ40/$CJ$47 -> 0.067000279 | CK57: =CK40/$CK$47 -> 0.2339987 | CM57: =CM40/$CM$47 -> 0.28148759
A58: Schools | B58: =B41/$B$47 -> 0.056613283 | C58: =C41/$C$47 -> 0.056613283 | D58: =D41/$D$47 -> 0.055491779 | E58: =E41/$E$47 -> 0.079998972 | F58: =F41/$F$47 -> 0.0065419133 | H58: =H41/$H$47 -> 0.16424814 | I58: =I41/$I$47 -> 0.06067486 | J58: =J41/$J$47 -> 0.17999928 | K58: =K41/$K$47 -> 0.12306598 | L58: =L41/$L$47 -> 0 | M58: =M41/$M$47 -> 0.014162822 | N58: =N41/$N$47 -> 0.091701982 | O58: =O41/$O$47 -> 0.025654515 | P58: =P41/$P$47 -> 0.022231034 | Q58: =Q41/$Q$47 -> 0.090000244 | R58: =R41/$R$47 -> 0 | S58: =S41/$S$47 -> 0.037401585 | T58: =T41/$T$47 -> 0.071484563 | U58: =U41/$U$47 -> 0.0029992731 | V58: =V41/$V$47 -> 0.18000122 | W58: =W41/$W$47 -> 0.050129233 | X58: =X41/$X$47 -> 0.04692554 | Y58: =Y41/$Y$47 -> 0.029998448 | Z58: =Z41/$Z$47 -> 0.023688607 | AA58: =AA41/$AA$47 -> 0.10998914 | AB58: =AB41/$AB$47 -> 0.047049379 | AC58: =AC41/$AC$47 -> 0 | AD58: =AD41/$AD$47 -> 0.037977864 | AE58: =AE41/$AE$47 -> 0.0073424549 | AF58: =AF41/$AF$47 -> 0.043993639 | AG58: =AG41/$AG$47 -> 0.026202713 | AH58: =AH41/$AH$47 -> 0.084100718 | AI58: =AI41/$AI$47 -> 0.042154848 | AK58: =AK41/$AK$47 -> 0.10874034 | AL58: =AL41/$AL$47 -> 0.015522991 | AN58: =AN41/$AN$47 -> 0 | AO58: =AO41/$AO$47 -> 0.04087896 | AP58: =AP41/$AP$47 -> 0.003799842 | AR58: =AR41/$AR$47 -> 0.01694594 | AS58: =AS41/$AS$47 -> 0.055543391 | AT58: =AT41/$AT$47 -> 0.012931726 | AU58: =AU41/$AU$47 -> 0.026143431 | AV58: =AV41/$AV$47 -> 0.058689886 | AW58: =AW41/$AW$47 -> 0.099999887 | AX58: =AX41/$AX$47 -> 0.12862565 | AY58: =AY41/$AY$47 -> 0.0023174026 | AZ58: =AZ41/$AZ$47 -> 0.022148457 | BA58: =BA41/$BA$47 -> 0.0014242634 | BB58: =BB41/$BB$47 -> 0.019452144 | BC58: =BC41/$BC$47 -> 0.023691471 | BD58: =BD41/$BD$47 -> 0.054955293 | BE58: =BE41/$BE$47 -> 0 | BF58: =BF41/$BF$47 -> 0.18599022 | BG58: =BG41/$BG$47 -> 0.10000041 | BH58: =BH41/$BH$47 -> 0.2040818 | BI58: =BI41/$BI$47 -> 0.044219543 | BJ58: =BJ41/$BJ$47 -> 0.019828215 | BK58: =BK41/$BK$47 -> 0.070831387 | BL58: =BL41/$BL$47 -> 0.098539484 | BM58: =BM41/$BM$47 -> 0.078408229 | BN58: =BN41/$BN$47 -> 0.013202011 | BO58: =BO41/$BO$47 -> 0.071965103 | BP58: =BP41/$BP$47 -> 0.0073441601 | BQ58: =BQ41/$BQ$47 -> 0.02700012 | BR58: =BR41/$BR$47 -> 0.041223759 | BS58: =BS41/$BS$47 -> 0.16633109 | BT58: =BT41/$BT$47 -> 0.033429736 | BU58: =BU41/$BU$47 -> 0.015957021 | BV58: =BV41/$BV$47 -> 0.016555261 | BW58: =BW41/$BW$47 -> 0.063718713 | BX58: =BX41/$BX$47 -> 0.08010237 | BY58: =BY41/$BY$47 -> 0.14579735 | BZ58: =BZ41/$BZ$47 -> 0.16702242 | CA58: =CA41/$CA$47 -> 0.047331594 | CB58: =CB41/$CB$47 -> 0.0042291412 | CC58: =CC41/$CC$47 -> 0.14670907 | CD58: =CD41/$CD$47 -> 0.017081182 | CE58: =CE41/$CE$47 -> 0.014346598 | CF58: =CF41/$CF$47 -> 0.044035135 | CG58: =CG41/$CG$47 -> 0.026623804 | CH58: =CH41/$CH$47 -> 0.0097657137 | CI58: =CI41/$CI$47 -> 0.11999782 | CJ58: =CJ41/$CJ$47 -> 0.10000029 | CK58: =CK41/$CK$47 -> 0.28601046 | CM58: =CM41/$CM$47 -> 0.15542203
A59: Commercial customers | B59: =B42/$B$47 -> 0.036589481 | C59: =C42/$C$47 -> 0.036589481 | D59: =D42/$D$47 -> 0.0085318232 | E59: =E42/$E$47 -> 0.29999706 | F59: =F42/$F$47 -> 0.11890603 | H59: =H42/$H$47 -> 0.050889704 | I59: =I42/$I$47 -> 0.17553348 | J59: =J42/$J$47 -> 0.21000087 | K59: =K42/$K$47 -> 0.12123032 | L59: =L42/$L$47 -> 0.080000333 | M59: =M42/$M$47 -> 0.0016661901 | N59: =N42/$N$47 -> 0.0098435112 | O59: =O42/$O$47 -> 0.056350603 | P59: =P42/$P$47 -> 0.03545923 | Q59: =Q42/$Q$47 -> 0.1999997 | R59: =R42/$R$47 -> 0.075641223 | S59: =S42/$S$47 -> 0.078309979 | T59: =T42/$T$47 -> 0.031908023 | U59: =U42/$U$47 -> 0.17699987 | V59: =V42/$V$47 -> 0.14000365 | W59: =W42/$W$47 -> 0.099744907 | X59: =X42/$X$47 -> 0.031193661 | Y59: =Y42/$Y$47 -> 0 | Z59: =Z42/$Z$47 -> 0.068169143 | AA59: =AA42/$AA$47 -> 0.45361804 | AB59: =AB42/$AB$47 -> 0.028018797 | AC59: =AC42/$AC$47 -> 0.19960805 | AD59: =AD42/$AD$47 -> 0.068638585 | AE59: =AE42/$AE$47 -> 0.25745495 | AF59: =AF42/$AF$47 -> 0.053542416 | AG59: =AG42/$AG$47 -> 0.030949458 | AH59: =AH42/$AH$47 -> 0 | AI59: =AI42/$AI$47 -> 0.11845091 | AK59: =AK42/$AK$47 -> 0.19666541 | AL59: =AL42/$AL$47 -> 0.151522 | AN59: =AN42/$AN$47 -> 0.16389761 | AO59: =AO42/$AO$47 -> 0 | AP59: =AP42/$AP$47 -> 0.33996461 | AR59: =AR42/$AR$47 -> 0.13625976 | AS59: =AS42/$AS$47 -> 0.066805343 | AT59: =AT42/$AT$47 -> 0.096987008 | AU59: =AU42/$AU$47 -> 0.40443044 | AV59: =AV42/$AV$47 -> 0.20748991 | AW59: =AW42/$AW$47 -> 0.029000244 | AX59: =AX42/$AX$47 -> 0.12220608 | AY59: =AY42/$AY$47 -> 0.11783452 | AZ59: =AZ42/$AZ$47 -> 0.20310303 | BA59: =BA42/$BA$47 -> 0.04205291 | BB59: =BB42/$BB$47 -> 0.13321872 | BC59: =BC42/$BC$47 -> 0.33636023 | BD59: =BD42/$BD$47 -> 0.15606198 | BE59: =BE42/$BE$47 -> 0.097638977 | BF59: =BF42/$BF$47 -> 0.12560088 | BG59: =BG42/$BG$47 -> 0.18999969 | BH59: =BH42/$BH$47 -> 0 | BI59: =BI42/$BI$47 -> 0.17629172 | BJ59: =BJ42/$BJ$47 -> 0.099141077 | BK59: =BK42/$BK$47 -> 0.1219578 | BL59: =BL42/$BL$47 -> 0.11388988 | BM59: =BM42/$BM$47 -> 0.15359703 | BN59: =BN42/$BN$47 -> 0.045961392 | BO59: =BO42/$BO$47 -> 0.042260418 | BP59: =BP42/$BP$47 -> 0 | BQ59: =BQ42/$BQ$47 -> 0.10600136 | BR59: =BR42/$BR$47 -> 0.021835371 | BS59: =BS42/$BS$47 -> 0 | BT59: =BT42/$BT$47 -> 0.10101596 | BU59: =BU42/$BU$47 -> 0.017626401 | BV59: =BV42/$BV$47 -> 0.24584505 | BW59: =BW42/$BW$47 -> 0 | BX59: =BX42/$BX$47 -> 0 | BY59: =BY42/$BY$47 -> 0.13750873 | BZ59: =BZ42/$BZ$47 -> 0.084864166 | CA59: =CA42/$CA$47 -> 0.29999896 | CB59: =CB42/$CB$47 -> 0.035523544 | CC59: =CC42/$CC$47 -> 0.15195929 | CD59: =CD42/$CD$47 -> 0.00051982857 | CE59: =CE42/$CE$47 -> 0.041535858 | CF59: =CF42/$CF$47 -> 0 | CG59: =CG42/$CG$47 -> 0.1788108 | CH59: =CH42/$CH$47 -> 0.0010431902 | CI59: =CI42/$CI$47 -> 0.17000038 | CJ59: =CJ42/$CJ$47 -> 0.030000087 | CK59: =CK42/$CK$47 -> 0.15599913 | CM59: =CM42/$CM$47 -> 0.19826101
A60: Industries | B60: =B43/$B$47 -> 0 | C60: =C43/$C$47 -> 0 | D60: =D43/$D$47 -> 0.00069623775 | E60: =E43/$E$47 -> 0 | F60: =F43/$F$47 -> 0 | H60: =H43/$H$47 -> 0 | I60: =I43/$I$47 -> 0 | J60: =J43/$J$47 -> 0.049999233 | K60: =K43/$K$47 -> 0.0015342836 | L60: =L43/$L$47 -> 0 | M60: =M43/$M$47 -> 0 | N60: =N43/$N$47 -> 0.06589117 | O60: =O43/$O$47 -> 4.8537953e-05 | P60: =P43/$P$47 -> 0.0010321484 | Q60: =Q43/$Q$47 -> 0 | R60: =R43/$R$47 -> 0 | S60: =S43/$S$47 -> 0.039906331 | T60: =T43/$T$47 -> 0 | U60: =U43/$U$47 -> 0 | V60: =V43/$V$47 -> 0 | W60: =W43/$W$47 -> 0 | X60: =X43/$X$47 -> 0.12942925 | Y60: =Y43/$Y$47 -> 0 | Z60: =Z43/$Z$47 -> 0 | AA60: =AA43/$AA$47 -> 0 | AB60: =AB43/$AB$47 -> 0.0517662 | AC60: =AC43/$AC$47 -> 0 | AD60: =AD43/$AD$47 -> 0 | AE60: =AE43/$AE$47 -> 0.0017091697 | AF60: =AF43/$AF$47 -> 0 | AG60: =AG43/$AG$47 -> 0.020633199 | AH60: =AH43/$AH$47 -> 0 | AI60: =AI43/$AI$47 -> 0 | AK60: =AK43/$AK$47 -> 0.16096706 | AL60: =AL43/$AL$47 -> 0.005715852 | AN60: =AN43/$AN$47 -> 0 | AO60: =AO43/$AO$47 -> 0 | AP60: =AP43/$AP$47 -> 0.13362542 | AR60: =AR43/$AR$47 -> 0 | AS60: =AS43/$AS$47 -> 0 | AT60: =AT43/$AT$47 -> 0.064658068 | AU60: =AU43/$AU$47 -> 0 | AV60: =AV43/$AV$47 -> 0 | AW60: =AW43/$AW$47 -> 0 | AX60: =AX43/$AX$47 -> 0 | AY60: =AY43/$AY$47 -> 0.0075939862 | AZ60: =AZ43/$AZ$47 -> 0 | BA60: =BA43/$BA$47 -> 0 | BB60: =BB43/$BB$47 -> 0.00086709326 | BC60: =BC43/$BC$47 -> 0 | BD60: =BD43/$BD$47 -> 0 | BE60: =BE43/$BE$47 -> 0 | BF60: =BF43/$BF$47 -> 0.12528442 | BG60: =BG43/$BG$47 -> 0 | BH60: =BH43/$BH$47 -> 0 | BI60: =BI43/$BI$47 -> 0.05615768 | BJ60: =BJ43/$BJ$47 -> 0.018469657 | BK60: =BK43/$BK$47 -> 0 | BL60: =BL43/$BL$47 -> 0 | BM60: =BM43/$BM$47 -> 0 | BN60: =BN43/$BN$47 -> 0 | BO60: =BO43/$BO$47 -> 0 | BP60: =BP43/$BP$47 -> 0.092210582 | BQ60: =BQ43/$BQ$47 -> 0 | BR60: =BR43/$BR$47 -> 0.00031870589 | BS60: =BS43/$BS$47 -> 0 | BT60: =BT43/$BT$47 -> 0.0092531905 | BU60: =BU43/$BU$47 -> 0 | BV60: =BV43/$BV$47 -> 0.083649171 | BW60: =BW43/$BW$47 -> 0 | BX60: =BX43/$BX$47 -> 0 | BY60: =BY43/$BY$47 -> 0 | BZ60: =BZ43/$BZ$47 -> 0 | CA60: =CA43/$CA$47 -> 0.024501096 | CB60: =CB43/$CB$47 -> 0 | CC60: =CC43/$CC$47 -> 0 | CD60: =CD43/$CD$47 -> 0 | CE60: =CE43/$CE$47 -> 0 | CF60: =CF43/$CF$47 -> 0 | CG60: =CG43/$CG$47 -> 0 | CH60: =CH43/$CH$47 -> 0 | CI60: =CI43/$CI$47 -> 0 | CJ60: =CJ43/$CJ$47 -> 0 | CK60: =CK43/$CK$47 -> 0 | CM60: =CM43/$CM$47 -> 0
A61: Kiosks | B61: =B44/$B$47 -> 0.0045714197 | C61: =C44/$C$47 -> 0.0045714197 | D61: =D44/$D$47 -> 0.033698839 | E61: =E44/$E$47 -> 0.010001249 | F61: =F44/$F$47 -> 0.050422377 | H61: =H44/$H$47 -> 0.015535435 | I61: =I44/$I$47 -> 0.0081439593 | J61: =J44/$J$47 -> 0 | K61: =K44/$K$47 -> 0.00015342836 | L61: =L44/$L$47 -> 0.019925341 | M61: =M44/$M$47 -> 0.0017606818 | N61: =N44/$N$47 -> 0.0057257654 | O61: =O44/$O$47 -> 0.22062706 | P61: =P44/$P$47 -> 0.01729228 | Q61: =Q44/$Q$47 -> 0.010000365 | R61: =R44/$R$47 -> 0.0062810426 | S61: =S44/$S$47 -> 0 | T61: =T44/$T$47 -> 0.08658062 | U61: =U44/$U$47 -> 0.0019988524 | V61: =V44/$V$47 -> 0.019998783 | W61: =W44/$W$47 -> 0.0046993082 | X61: =X44/$X$47 -> 0.22970134 | Y61: =Y44/$Y$47 -> 0 | Z61: =Z44/$Z$47 -> 0.15105222 | AA61: =AA44/$AA$47 -> 0.030395664 | AB61: =AB44/$AB$47 -> 0.041044576 | AC61: =AC44/$AC$47 -> 0.0041902315 | AD61: =AD44/$AD$47 -> 0.00021229463 | AE61: =AE44/$AE$47 -> 0.060664049 | AF61: =AF44/$AF$47 -> 0.18492796 | AG61: =AG44/$AG$47 -> 0.065903876 | AH61: =AH44/$AH$47 -> 0 | AI61: =AI44/$AI$47 -> 0.011283799 | AK61: =AK44/$AK$47 -> 0.029282167 | AL61: =AL44/$AL$47 -> 0.067820771 | AN61: =AN44/$AN$47 -> 0 | AO61: =AO44/$AO$47 -> 0.15914192 | AP61: =AP44/$AP$47 -> 0.036943693 | AR61: =AR44/$AR$47 -> 0.015288584 | AS61: =AS44/$AS$47 -> 0.013517262 | AT61: =AT44/$AT$47 -> 0.11444179 | AU61: =AU44/$AU$47 -> 0.00092539041 | AV61: =AV44/$AV$47 -> 0.0029399181 | AW61: =AW44/$AW$47 -> 0.0009998916 | AX61: =AX44/$AX$47 -> 0.2085891 | AY61: =AY44/$AY$47 -> 0.066609756 | AZ61: =AZ44/$AZ$47 -> 0.060347042 | BA61: =BA44/$BA$47 -> 0.00069518479 | BB61: =BB44/$BB$47 -> 0.0082262836 | BC61: =BC44/$BC$47 -> 0.0018321367 | BD61: =BD44/$BD$47 -> 0.038555382 | BE61: =BE44/$BE$47 -> 0 | BF61: =BF44/$BF$47 -> 0 | BG61: =BG44/$BG$47 -> 0.0099990837 | BH61: =BH44/$BH$47 -> 0 | BI61: =BI44/$BI$47 -> 0.001855531 | BJ61: =BJ44/$BJ$47 -> 0.0099253354 | BK61: =BK44/$BK$47 -> 0.0022571841 | BL61: =BL44/$BL$47 -> 0.017343854 | BM61: =BM44/$BM$47 -> 0.030721325 | BN61: =BN44/$BN$47 -> 0.017027679 | BO61: =BO44/$BO$47 -> 0.001308431 | BP61: =BP44/$BP$47 -> 0.0087006201 | BQ61: =BQ44/$BQ$47 -> 0.019999197 | BR61: =BR44/$BR$47 -> 0.31412349 | BS61: =BS44/$BS$47 -> 0 | BT61: =BT44/$BT$47 -> 0.011911285 | BU61: =BU44/$BU$47 -> 7.2096377e-05 | BV61: =BV44/$BV$47 -> 0.001037544 | BW61: =BW44/$BW$47 -> 0.015039068 | BX61: =BX44/$BX$47 -> 0.070309176 | BY61: =BY44/$BY$47 -> 0.0046040576 | BZ61: =BZ44/$BZ$47 -> 0 | CA61: =CA44/$CA$47 -> 0.0081665347 | CB61: =CB44/$CB$47 -> 0.0051594281 | CC61: =CC44/$CC$47 -> 0.0068424095 | CD61: =CD44/$CD$47 -> 0.0013862095 | CE61: =CE44/$CE$47 -> 0.00050423558 | CF61: =CF44/$CF$47 -> 0.002934662 | CG61: =CG44/$CG$47 -> 0.034362704 | CH61: =CH44/$CH$47 -> 0 | CI61: =CI44/$CI$47 -> 0.019999102 | CJ61: =CJ44/$CJ$47 -> 0.00099961067 | CK61: =CK44/$CK$47 -> 0.039994214 | CM61: =CM44/$CM$47 -> 0.070246334
A62: Bulk | B62: =B45/$B$47 -> 0 | C62: =C45/$C$47 -> 0 | D62: =D45/$D$47 -> 0 | E62: =E45/$E$47 -> 0 | F62: =F45/$F$47 -> 0 | H62: =H45/$H$47 -> 0 | I62: =I45/$I$47 -> 0 | J62: =J45/$J$47 -> 0 | K62: =K45/$K$47 -> 0 | L62: =L45/$L$47 -> 0.040073752 | M62: =M45/$M$47 -> 0 | N62: =N45/$N$47 -> 0.032994072 | O62: =O45/$O$47 -> 0 | P62: =P45/$P$47 -> 0 | Q62: =Q45/$Q$47 -> 0 | R62: =R45/$R$47 -> 0 | S62: =S45/$S$47 -> 0.085823396 | T62: =T45/$T$47 -> 0 | U62: =U45/$U$47 -> 0.029999692 | V62: =V45/$V$47 -> 0 | W62: =W45/$W$47 -> 6.6039015e-05 | X62: =X45/$X$47 -> 0 | Y62: =Y45/$Y$47 -> 0 | Z62: =Z45/$Z$47 -> 0 | AA62: =AA45/$AA$47 -> 0 | AB62: =AB45/$AB$47 -> 0.03048222 | AC62: =AC45/$AC$47 -> 0 | AD62: =AD45/$AD$47 -> 0 | AE62: =AE45/$AE$47 -> 0.1010987 | AF62: =AF45/$AF$47 -> 0.039049193 | AG62: =AG45/$AG$47 -> 0 | AH62: =AH45/$AH$47 -> 0 | AI62: =AI45/$AI$47 -> 0.056630086 | AK62: =AK45/$AK$47 -> 0 | AL62: =AL45/$AL$47 -> 0.00038274209 | AN62: =AN45/$AN$47 -> 0.001281787 | AO62: =AO45/$AO$47 -> 0 | AP62: =AP45/$AP$47 -> 0 | AR62: =AR45/$AR$47 -> 0 | AS62: =AS45/$AS$47 -> 0 | AT62: =AT45/$AT$47 -> 0.017654611 | AU62: =AU45/$AU$47 -> 0 | AV62: =AV45/$AV$47 -> 0 | AW62: =AW45/$AW$47 -> 0 | AX62: =AX45/$AX$47 -> 0 | AY62: =AY45/$AY$47 -> 0.12611507 | AZ62: =AZ45/$AZ$47 -> 0.0062263187 | BA62: =BA45/$BA$47 -> 0 | BB62: =BB45/$BB$47 -> 0.39648672 | BC62: =BC45/$BC$47 -> 0 | BD62: =BD45/$BD$47 -> 0.034768829 | BE62: =BE45/$BE$47 -> 0 | BF62: =BF45/$BF$47 -> 0 | BG62: =BG45/$BG$47 -> 0 | BH62: =BH45/$BH$47 -> 0.15306135 | BI62: =BI45/$BI$47 -> 0.11533047 | BJ62: =BJ45/$BJ$47 -> 0 | BK62: =BK45/$BK$47 -> 0 | BL62: =BL45/$BL$47 -> 0.0018493469 | BM62: =BM45/$BM$47 -> 0 | BN62: =BN45/$BN$47 -> 0 | BO62: =BO45/$BO$47 -> 0 | BP62: =BP45/$BP$47 -> 0 | BQ62: =BQ45/$BQ$47 -> 0 | BR62: =BR45/$BR$47 -> 0.019687454 | BS62: =BS45/$BS$47 -> 0 | BT62: =BT45/$BT$47 -> 0.0010708786 | BU62: =BU45/$BU$47 -> 0 | BV62: =BV45/$BV$47 -> 0 | BW62: =BW45/$BW$47 -> 0 | BX62: =BX45/$BX$47 -> 0.097652308 | BY62: =BY45/$BY$47 -> 0 | BZ62: =BZ45/$BZ$47 -> 0.21995472 | CA62: =CA45/$CA$47 -> 0 | CB62: =CB45/$CB$47 -> 0.11937978 | CC62: =CC45/$CC$47 -> 0 | CD62: =CD45/$CD$47 -> 0 | CE62: =CE45/$CE$47 -> 0 | CF62: =CF45/$CF$47 -> 0 | CG62: =CG45/$CG$47 -> 0.0028857969 | CH62: =CH45/$CH$47 -> 0.0018335317 | CI62: =CI45/$CI$47 -> 0 | CJ62: =CJ45/$CJ$47 -> 0 | CK62: =CK45/$CK$47 -> 0 | CM62: =CM45/$CM$47 -> 0
A63: Others | B63: =B46/$B$47 -> 0 | C63: =C46/$C$47 -> 0 | D63: =D46/$D$47 -> 0 | E63: =E46/$E$47 -> 0 | F63: =F46/$F$47 -> 0 | H63: =H46/$H$47 -> 0 | I63: =I46/$I$47 -> 0 | J63: =J46/$J$47 -> 0 | K63: =K46/$K$47 -> 0 | L63: =L46/$L$47 -> 0 | M63: =M46/$M$47 -> 0 | N63: =N46/$N$47 -> 0 | O63: =O46/$O$47 -> 0 | P63: =P46/$P$47 -> 6.4509274e-05 | Q63: =Q46/$Q$47 -> 0 | R63: =R46/$R$47 -> 0 | S63: =S46/$S$47 -> 0 | T63: =T46/$T$47 -> 0 | U63: =U46/$U$47 -> 0 | V63: =V46/$V$47 -> 0 | W63: =W46/$W$47 -> 0 | X63: =X46/$X$47 -> 0.030035394 | Y63: =Y46/$Y$47 -> 0 | Z63: =Z46/$Z$47 -> 0.10085046 | AA63: =AA46/$AA$47 -> 0 | AB63: =AB46/$AB$47 -> 0.00013739166 | AC63: =AC46/$AC$47 -> 0 | AD63: =AD46/$AD$47 -> 0 | AE63: =AE46/$AE$47 -> 0.046107383 | AF63: =AF46/$AF$47 -> 0 | AG63: =AG46/$AG$47 -> 0 | AH63: =AH46/$AH$47 -> 0 | AI63: =AI46/$AI$47 -> 0 | AK63: =AK46/$AK$47 -> 0 | AL63: =AL46/$AL$47 -> 0 | AN63: =AN46/$AN$47 -> 0 | AO63: =AO46/$AO$47 -> 0 | AP63: =AP46/$AP$47 -> 0 | AR63: =AR46/$AR$47 -> 0 | AS63: =AS46/$AS$47 -> 0 | AT63: =AT46/$AT$47 -> 0 | AU63: =AU46/$AU$47 -> 0 | AV63: =AV46/$AV$47 -> 0 | AW63: =AW46/$AW$47 -> 0 | AX63: =AX46/$AX$47 -> 0 | AY63: =AY46/$AY$47 -> 0.021468053 | AZ63: =AZ46/$AZ$47 -> 0 | BA63: =BA46/$BA$47 -> 0 | BB63: =BB46/$BB$47 -> 0 | BC63: =BC46/$BC$47 -> 0 | BD63: =BD46/$BD$47 -> 0.015570051 | BE63: =BE46/$BE$47 -> 0 | BF63: =BF46/$BF$47 -> 0 | BG63: =BG46/$BG$47 -> 0 | BH63: =BH46/$BH$47 -> 0 | BI63: =BI46/$BI$47 -> 0.010683853 | BJ63: =BJ46/$BJ$47 -> 0 | BK63: =BK46/$BK$47 -> 0 | BL63: =BL46/$BL$47 -> 0 | BM63: =BM46/$BM$47 -> 0 | BN63: =BN46/$BN$47 -> 0 | BO63: =BO46/$BO$47 -> 0 | BP63: =BP46/$BP$47 -> 0 | BQ63: =BQ46/$BQ$47 -> 0 | BR63: =BR46/$BR$47 -> 0 | BS63: =BS46/$BS$47 -> 0 | BT63: =BT46/$BT$47 -> 0 | BU63: =BU46/$BU$47 -> 0 | BV63: =BV46/$BV$47 -> 0 | BW63: =BW46/$BW$47 -> 0 | BX63: =BX46/$BX$47 -> 0.097652308 | BY63: =BY46/$BY$47 -> 0 | BZ63: =BZ46/$BZ$47 -> 0 | CA63: =CA46/$CA$47 -> 0 | CB63: =CB46/$CB$47 -> 0 | CC63: =CC46/$CC$47 -> 0 | CD63: =CD46/$CD$47 -> 0 | CE63: =CE46/$CE$47 -> 0 | CF63: =CF46/$CF$47 -> 0 | CG63: =CG46/$CG$47 -> 0 | CH63: =CH46/$CH$47 -> 0 | CI63: =CI46/$CI$47 -> 0 | CJ63: =CJ46/$CJ$47 -> 0 | CK63: =CK46/$CK$47 -> 0 | CM63: =CM46/$CM$47 -> 0
A64: Total | B64: =SUM(B55:B63) -> 1 | C64: =SUM(C55:C63) -> 1 | D64: =SUM(D55:D63) -> 1 | E64: =SUM(E55:E63) -> 1 | F64: =SUM(F55:F63) -> 1 | G64: =SUM(G55:G63) -> #DIV/0! | H64: =SUM(H55:H63) -> 1 | I64: =SUM(I55:I63) -> 1 | ... CM64: =SUM(CM55:CM63) -> 1
A67: Total Sewerage Treated | B67: =B17 -> 0 | C67: =C17 -> 0 | D67: =D17 -> 0 | E67: =E17 -> 0 | F67: =F17 -> 7850064 | G67: =G17 -> 0 | H67: =H17 -> 0 | I67: =I17 -> 1950734 | ... CM67: =CM17 -> 0
A68: Individual | F68: =$F$67*F55 -> 6120780.2 | I68: =$I$67*I55 -> 1388532.8 | J68: =$J$67*J55 -> 88800.192 | O68: =$O$67*O55 -> 708559.69 | R68: =$R$67*R55 -> 264256.45 | T68: =$T$67*T55 -> 135284.74 | W68: =$W$67*W55 -> 146424.64 | AE68: =$AE$67*AE55 -> 2267967.3 | AK68: =$AK$67*AK55 -> 12115.921 | AP68: =$AP$67*AP55 -> 225113.4 | AT68: =$AT$67*AT55 -> 2830.5029 | AU68: =$AU$67*AU55 -> 717212.51 | AY68: =$AY$67*AY55 -> 37618393 | AZ68: =$AZ$67*AZ55 -> 556609.39 | BA68: =$BA$67*BA55 -> 2260621.8 | BC68: =$BC$67*BC55 -> 635295.11 | BI68: =$BI$67*BI55 -> 610113.62 | BK68: =$BK$67*BK55 -> 1427408.4 | BL68: =$BL$67*BL55 -> 1068961.3 | BP68: =$BP$67*BP55 -> 891127.26 | BV68: =$BV$67*BV55 -> 2478528.4 | CB68: =$CB$67*CB55 -> 1370.3256
A69: Multi-dwelling units | F69: =$F$67*F56 -> 32419.192 | I69: =$I$67*I56 -> 0 | J69: =$J$67*J56 -> 16800.069 | O69: =$O$67*O56 -> 428175.43 | R69: =$R$67*R56 -> 0 | T69: =$T$67*T56 -> 175881.9 | W69: =$W$67*W56 -> 0 | AE69: =$AE$67*AE56 -> 0 | AK69: =$AK$67*AK56 -> 10936.689 | AP69: =$AP$67*AP56 -> 132927.76 | AT69: =$AT$67*AT56 -> 1213.0735 | AU69: =$AU$67*AU56 -> 0 | AY69: =$AY$67*AY56 -> 13438122 | AZ69: =$AZ$67*AZ56 -> 142859.59 | BA69: =$BA$67*BA56 -> 1933029.3 | BC69: =$BC$67*BC56 -> 0 | BI69: =$BI$67*BI56 -> 0 | BK69: =$BK$67*BK56 -> 1270465.8 | BL69: =$BL$67*BL56 -> 57585.802 | BP69: =$BP$67*BP56 -> 330329.27 | BV69: =$BV$67*BV56 -> 91438.783 | CB69: =$CB$67*CB56 -> 681.4786
A70: Institutions | F70: =$F$67*F57 -> 316271.31 | I70: =$I$67*I57 -> 85534.825 | J70: =$J$67*J57 -> 28799.886 | O70: =$O$67*O57 -> 129945.36 | R70: =$R$67*R57 -> 8800.9883 | T70: =$T$67*T57 -> 9652.5758 | W70: =$W$67*W57 -> 1631.8007 | AE70: =$AE$67*AE57 -> 198477.93 | AK70: =$AK$67*AK57 -> 13363.118 | AP70: =$AP$67*AP57 -> 7179.9969 | AT70: =$AT$67*AT57 -> 116.38441 | AU70: =$AU$67*AU57 -> 0 | AY70: =$AY$67*AY57 -> 1934202.7 | AZ70: =$AZ$67*AZ57 -> 4195.8056 | BA70: =$BA$67*BA57 -> 6121.7637 | BC70: =$BC$67*BC57 -> 0 | BI70: =$BI$67*BI57 -> 55002.247 | BK70: =$BK$67*BK57 -> 369189.05 | BL70: =$BL$67*BL57 -> 4227.8639 | BP70: =$BP$67*BP57 -> 8990.9806 | BV70: =$BV$67*BV57 -> 51478.364 | CB70: =$CB$67*CB57 -> 37.466092
A71: Schools | F71: =$F$67*F58 -> 51354.438 | I71: =$I$67*I58 -> 118360.51 | J71: =$J$67*J58 -> 43199.828 | O71: =$O$67*O58 -> 46601.426 | R71: =$R$67*R58 -> 0 | T71: =$T$67*T58 -> 28312.176 | W71: =$W$67*W58 -> 8779.6338 | AE71: =$AE$67*AE58 -> 34453.882 | AK71: =$AK$67*AK58 -> 7851.4872 | AP71: =$AP$67*AP58 -> 2857.4812 | AT71: =$AT$67*AT58 -> 77.590359 | AU71: =$AU$67*AU58 -> 32982.183 | AY71: =$AY$67*AY58 -> 186610.04 | AZ71: =$AZ$67*AZ58 -> 22007.394 | BA71: =$BA$67*BA58 -> 6258.0142 | BC71: =$BC$67*BC58 -> 23586.734 | BI71: =$BI$67*BI58 -> 49392.168 | BK71: =$BK$67*BK58 -> 269884.3 | BL71: =$BL$67*BL58 -> 145014.65 | BP71: =$BP$67*BP58 -> 10133.623 | BV71: =$BV$67*BV58 -> 66469.374 | CB71: =$CB$67*CB58 -> 10.572853
A72: Commercial customers | F72: =$F$67*F59 -> 933419.97 | I72: =$I$67*I59 -> 342419.12 | J72: =$J$67*J59 -> 50400.208 | O72: =$O$67*O59 -> 102360.87 | R72: =$R$67*R59 -> 22497.439 | T72: =$T$67*T59 -> 12637.492 | W72: =$W$67*W59 -> 17469.323 | AE72: =$AE$67*AE59 -> 1208086.8 | AK72: =$AK$67*AK59 -> 14200.029 | AP72: =$AP$67*AP59 -> 255653.39 | AT72: =$AT$67*AT59 -> 581.92205 | AU72: =$AU$67*AU59 -> 510223.73 | AY72: =$AY$67*AY59 -> 9488685 | AZ72: =$AZ$67*AZ59 -> 201809.47 | BA72: =$BA$67*BA59 -> 184774.6 | BC72: =$BC$67*BC59 -> 334873.21 | BI72: =$BI$67*BI59 -> 196913.62 | BK72: =$BK$67*BK59 -> 464688 | BL72: =$BL$67*BL59 -> 167604.9 | BP72: =$BP$67*BP59 -> 0 | BV72: =$BV$67*BV59 -> 987067.87 | CB72: =$CB$67*CB59 -> 88.80886
A73: Industries | F73: =$F$67*F60 -> 0 | I73: =$I$67*I60 -> 0 | J73: =$J$67*J60 -> 11999.816 | O73: =$O$67*O60 -> 88.169193 | R73: =$R$67*R60 -> 0 | T73: =$T$67*T60 -> 0 | W73: =$W$67*W60 -> 0 | AE73: =$AE$67*AE60 -> 8020.1419 | AK73: =$AK$67*AK60 -> 11622.466 | AP73: =$AP$67*AP60 -> 100486.32 | AT73: =$AT$67*AT60 -> 387.94841 | AU73: =$AU$67*AU60 -> 0 | AY73: =$AY$67*AY60 -> 611509.65 | AZ73: =$AZ$67*AZ60 -> 0 | BA73: =$BA$67*BA60 -> 0 | BC73: =$BC$67*BC60 -> 0 | BI73: =$BI$67*BI60 -> 62726.78 | BK73: =$BK$67*BK60 -> 0 | BL73: =$BL$67*BL60 -> 0 | BP73: =$BP$67*BP60 -> 127234.05 | BV73: =$BV$67*BV60 -> 335851.42 | CB73: =$CB$67*CB60 -> 0
A74: Kiosks | F74: =$F$67*F61 -> 395818.88 | I74: =$I$67*I61 -> 15886.698 | J74: =$J$67*J61 -> 0 | O74: =$O$67*O61 -> 400769.06 | R74: =$R$67*R61 -> 1868.1265 | T74: =$T$67*T61 -> 34291.12 | W74: =$W$67*W61 -> 823.03684 | AE74: =$AE$67*AE61 -> 284661.2 | AK74: =$AK$67*AK61 -> 2114.2896 | AP74: =$AP$67*AP61 -> 27781.657 | AT74: =$AT$67*AT61 -> 686.65076 | AU74: =$AU$67*AU61 -> 1167.4595 | AY74: =$AY$67*AY61 -> 5363784.9 | AZ74: =$AZ$67*AZ61 -> 59962.692 | BA74: =$BA$67*BA61 -> 3054.5446 | BC74: =$BC$67*BC61 -> 1824.037 | BI74: =$BI$67*BI61 -> 2072.5836 | BK74: =$BK$67*BK61 -> 8600.4041 | BL74: =$BL$67*BL61 -> 25523.909 | BP74: =$BP$67*BP61 -> 12005.294 | BV74: =$BV$67*BV61 -> 4165.7392 | CB74: =$CB$67*CB61 -> 12.89857
A75: Bulk | F75: =$F$67*F62 -> 0 | I75: =$I$67*I62 -> 0 | J75: =$J$67*J62 -> 0 | O75: =$O$67*O62 -> 0 | R75: =$R$67*R62 -> 0 | T75: =$T$67*T62 -> 0 | W75: =$W$67*W62 -> 11.566073 | AE75: =$AE$67*AE62 -> 474397.55 | AK75: =$AK$67*AK62 -> 0 | AP75: =$AP$67*AP62 -> 0 | AT75: =$AT$67*AT62 -> 105.92767 | AU75: =$AU$67*AU62 -> 0 | AY75: =$AY$67*AY62 -> 10155481 | AZ75: =$AZ$67*AZ62 -> 6186.6632 | BA75: =$BA$67*BA62 -> 0 | BC75: =$BC$67*BC62 -> 0 | BI75: =$BI$67*BI62 -> 128821.37 | BK75: =$BK$67*BK62 -> 0 | BL75: =$BL$67*BL62 -> 2721.5728 | BP75: =$BP$67*BP62 -> 0 | BV75: =$BV$67*BV62 -> 0 | CB75: =$CB$67*CB62 -> 298.44944
A76: Others | F76: =$F$67*F63 -> 0 | I76: =$I$67*I63 -> 0 | J76: =$J$67*J63 -> 0 | O76: =$O$67*O63 -> 0 | R76: =$R$67*R63 -> 0 | T76: =$T$67*T63 -> 0 | W76: =$W$67*W63 -> 0 | AE76: =$AE$67*AE63 -> 216355.21 | AK76: =$AK$67*AK63 -> 0 | AP76: =$AP$67*AP63 -> 0 | AT76: =$AT$67*AT63 -> 0 | AU76: =$AU$67*AU63 -> 0 | AY76: =$AY$67*AY63 -> 1728726 | AZ76: =$AZ$67*AZ63 -> 0 | BA76: =$BA$67*BA63 -> 0 | BC76: =$BC$67*BC63 -> 0 | BI76: =$BI$67*BI63 -> 11933.608 | BK76: =$BK$67*BK63 -> 0 | BL76: =$BL$67*BL63 -> 0 | BP76: =$BP$67*BP63 -> 0 | BV76: =$BV$67*BV63 -> 0 | CB76: =$CB$67*CB63 -> 0
A77: Total
A79: Total water supplied
A80: Individual | B80: =B38 -> 363894.97 | C80: =C38 -> 382936 | D80: =D38 -> 553526.96 | E80: =E38 -> 130687 | F80: =F38 -> 6916011.2 | G80: =G38 -> 0 | H80: =H38 -> 208633 | I80: =I38 -> 3373540 | ... CM80: =CM38 -> 49946.281 | CO80: =SUM(B80:CM81) -> 1.242897e+08
A81: Multi-dwelling units | B81: =B39 -> 0 | C81: =C39 -> 0 | D81: =D39 -> 0 | E81: =E39 -> 0 | F81: =F39 -> 36631.195 | G81: =G39 -> 0 | H81: =H39 -> 104750 | I81: =I39 -> 0 | ... CM81: =CM39 -> 37972.321
A82: Institutions | B82: =B40 -> 629550.39 | C82: =C40 -> 662492 | D82: =D40 -> 5671.6374 | E82: =E40 -> 35396 | F82: =F40 -> 357362.28 | G82: =G40 -> 0 | H82: =H40 -> 41879 | I82: =I40 -> 207812.98 | ... CM82: =CM40 -> 84010.253 | CO82: =SUM(B82:CM83) -> 15326349
A83: Schools | B83: =B41 -> 62337.169 | C83: =C41 -> 65599 | D83: =D41 -> 34418.332 | E83: =E41 -> 21781 | F83: =F41 -> 58026.568 | G83: =G41 -> 0 | H83: =H41 -> 75847 | I83: =I41 -> 287565.34 | ... CM83: =CM41 -> 46385.861
A84: Commercial customers | B84: =B42 -> 40288.86 | C84: =C42 -> 42397 | D84: =D42 -> 5291.7951 | E84: =E42 -> 81679 | F84: =F42 -> 1054692.8 | G84: =G42 -> 0 | H84: =H42 -> 23500 | I84: =I42 -> 831931.79 | ... CM84: =CM42 -> 59171.195 | CO84: =SUM(B84:CM87) -> 36310344
A85: Industries | B85: =B43 -> 0 | C85: =C43 -> 0 | D85: =D43 -> 431.8359 | E85: =E43 -> 0 | F85: =F43 -> 0 | G85: =G43 -> 0 | H85: =H43 -> 0 | I85: =I43 -> 0 | ... CM85: =CM43 -> 0
A86: Kiosks | B86: =B44 -> 5033.6131 | C86: =C44 -> 5297 | D86: =D44 -> 20901.435 | E86: =E44 -> 2723 | F86: =F44 -> 447244.92 | G86: =G44 -> 0 | H86: =H44 -> 7174 | I86: =I44 -> 38597.871 | ... CM86: =CM44 -> 20965.089
A87: Bulk | B87: =B45 -> 0 | C87: =C45 -> 0 | D87: =D45 -> 0 | E87: =E45 -> 0 | F87: =F45 -> 0 | G87: =G45 -> 0 | H87: =H45 -> 0 | I87: =I45 -> 0 | ... CM87: =CM45 -> 0
A88: Others | B88: =B48-B47 -> -0.1 | C88: =C48-C47 -> 846373 | D88: =D48-D47 -> 0 | E88: =E48-E47 -> 0 | F88: =F48-F47 -> 0 | G88: =G48-G47 -> 141426 | H88: =H48-H47 -> 0 | I88: =I48-I47 -> 0 | ... CM88: =CM48-CM47 -> 0 | CO88: =SUM(B88:CM88) -> 73090276
A89: Total | CO89: =SUM(CO80:CO88) -> 2.4901667e+08

Sheet WASREB 21-2022
A1: unit | B1: m3
A2: County | B2: Nairobi | C2: Uasin Gishu | D2: Mombasa | E2: Nakuru | F2: Kisumu | G2: Bungoma | H2: Kiambu | I2: Nyeri | J2: Murang'a | K2: Kiambu | L2: Kiambu | M2: Kilifi | N2: Embu | O2: Nakuru | P2: Kirinyaga | Q2: Kakamega | R2: Kericho | S2: Kilifi | T2: Nyeri | U2: Taita-Taveta | V2: Nyeri | W2: Lakipia | X2: Murang'a | Y2: Murang'a | Z2: Laikipia | AA2: Gusii | AB2: Garissa | AC2: Meru | AD2: Kwale | AE2: Bomet | AF2: Embu | AG2: Kitui | AH2: Tharaka-Nithi | AI2: Nyeri | AJ2: Siaya | AK2: Kiambu | AL2: Machakos | AM2: Kiambu | AN2: Murang'a | AO2: Isiolo | AP2: Busia | AQ2: Kiambu | AR2: Kajiado | AS2: Murang'a | AT2: Embu | AU2: Nakuru | AV2: Meru | AW2: Embu | AX2: Kiambu | AY2: Kiambu | AZ2: Turkana | BA2: Kajiado | BB2: Machakos | BC2: Vihiga | BD2: Homabay | BE2: Meru | BF2: Makueni | BG2: Nyandarua | BH2: Embu | BI2: Narok | BJ2: Tana River | BK2: Migori | BL2: Nandi | BM2: Tharaka-Nithi | BN2: Baringo | BO2: Lamu | BP2: Baringo | BQ2: Kitui | BR2: Nyeri | BS2: Elgeiyo Marakwet | BT2: Mandera | BU2: Samburu | BV2: Nyandarua | BW2: Kajiado | BX2: Tharaka-Nithi | BY2: West Pokot | BZ2: Makueni | CA2: Nyeri | CB2: Mandera | CC2: Kirinyaga | CD2: Machakos | CE2: Nyandarua | CF2: Machakos | CG2: Kiambu | CH2: Makueni | CI2: Migori | CJ2: Nairobi | CK2: Nandi | CL2: Machakos | CM2: Machakos | CN2: Kiambu | CO2: Nairobi
A3: INDICATORS | B3: Nairobi | C3: Eldoret | D3: Mombasa | E3: Nakuru | F3: Kisumu | G3: Nzoia | H3: Thika | I3: Nyeri | J3: Murang'a South | K3: Ruiru-Juja | L3: Gatundu | M3: Kilifi Mariakani | N3: Embu | O3: Nakuru Rural | P3: Kirinyaga | Q3: Kakamega | R3: Kericho | S3: Malindi | T3: Othaya Mukurweni | U3: Tavevo | V3: Mathira | W3: Nanyuki | X3: Murang'a | Y3: Murang'a West | Z3: Nyahururu | AA3: Gusii | AB3: Garissa | AC3: Meru | AD3: Kwale | AE3: Bomet | AF3: Ngandori Nginda | AG3: Kitui | AH3: Nithi | AI3: Tetu Aberdare | AJ3: Sibo | AK3: Limuru | AL3: Mavoko | AM3: Kikuyu | AN3: Gatamathi | AO3: Isiolo | AP3: Busia | AQ3: Kiambu | AR3: Oloolaiser | AS3: Gatanga | AT3: Ngagaka | AU3: Naivasha | AV3: Imetha | AW3: Kyeni | AX3: Karuri | AY3: Githunguri | AZ3: Lodwar | BA3: Nol Turesh | BB3: Machakos | BC3: Amatsi | BD3: Homabay | BE3: Tuuru | BF3: Kibwezi Makindu | BG3: Nyandarua | BH3: Embe | BI3: Narok | BJ3: Tana | BK3: Migori | BL3: Kapsabet Nandi | BM3: Murugi Mugumango | BN3: Chemususu | BO3: Lamu | BP3: Kirandich | BQ3: Kiambere Mwingi | BR3: Mutitu | BS3: Iten Tambach | BT3: Mandera | BU3: Samburu | BV3: Ol Kalou | BW3: Olkejuado | BX3: Muthambi 4K | BY3: Kapenguria | BZ3: Wote | CA3: Naromoru | CB3: Elwak | CC3: Rukanga | CD3: Yatta | CE3: Ndaragwa | CF3: Matungulu Kangundo | CG3: Kiamumbi | CH3: Mbooni | CI3: Nyasare | CJ3: Runda | CK3: Tachasis | CL3: Kathiani | CM3: Mwala | CN3: Tatu City | CO3: Two Rivers | CQ3: Total
A4: Surface water abstracted | B4: 178526913 | C4: 15451881 | D4: 11904294 | E4: 11507540 | F4: 10497618 | G4: 8309282 | H4: 14022595 | I4: 7882990 | J4: 6119845 | K4: 11544566 | L4: 7406276 | M4: 10880179 | N4: 7705097 | O4: 8233972 | P4: 6341902 | Q4: 4499131 | R4: 3645781 | S4: 7173382 | T4: 6461280 | U4: 5420914 | V4: 2048705 | W4: 4119964 | X4: 3042245 | Y4: 2757153 | Z4: 3310246 | AA4: 4668790 | AB4: 6523000 | AC4: 3223424 | AD4: 5085497 | AE4: 3504344 | AF4: 2856496 | AG4: 3451316 | AH4: 4285186 | AI4: 2859376 | AJ4: 2597908 | AK4: 2104947 | AL4: 1554173 | AM4: 2489757 | AN4: 2849400 | AO4: 2389931 | AP4: 870412 | AQ4: 3310911 | AR4: 2342232 | AS4: 1759789 | AT4: 1156808 | AU4: 2050141 | AV4: 1149036 | AW4: 1039740 | AX4: 1599344 | AY4: 2069213 | AZ4: 2209336 | BA4: 2190000 | BB4: 1199030 | BC4: 1647625 | BD4: 751854 | BE4: 1493177 | BF4: 1482807 | BG4: 765880 | BH4: 1158366 | BI4: 1253209 | BJ4: 2034457 | BK4: 330657 | BL4: 1212867 | BM4: 2232990 | BN4: 882803 | BO4: 548534 | BP4: 1150250 | BQ4: 991263 | BR4: 987235 | BS4: 1100600 | BT4: 543620 | BU4: 648254 | BV4: 580027 | BW4: 329610 | BX4: 648456 | BY4: 135000 | BZ4: 457366 | CA4: 318679 | CB4: 349920 | CC4: 192138 | CD4: 260579 | CE4: 19462 | CF4: 152611 | CG4: 541980 | CH4: 55311 | CI4: 148053 | CJ4: 871181 | CK4: 364897 | CL4: 118692 | CM4: 59656 | CN4: 242416 | CO4: 95375 | CQ4: =SUM(B4:CO4) -> 459361145
A5: Ground water abstracted | CQ5: =SUM(B5:CO5) -> 0
A6: Total Volume of water treated | CQ6: =SUM(B6:CO6) -> 0
A7: Imported treated water | CQ7: =SUM(B7:CO7) -> 0
A8: Exported treated water | CQ8: =SUM(B8:CO8) -> 0
A9: Metered volume produced | B9: 178526913 | C9: 15451881 | D9: 11904294 | E9: 11507540 | F9: 10497618 | G9: 8309282 | H9: 14022595 | I9: 7882990 | J9: 6119845 | K9: 11544566 | L9: 7406276 | M9: 10880179 | N9: 7705097 | O9: 8233972 | P9: 6341902 | Q9: 4499131 | R9: 3645781 | S9: 7173382 | T9: 6461280 | U9: 5420914 | V9: 2048705 | W9: 4119964 | X9: 3042245 | Y9: 2757153 | Z9: 3310246 | AA9: 4668790 | AB9: 6523000 | AC9: 3223424 | AD9: 5085497 | AE9: 3504344 | AF9: 2856496 | AG9: 3451316 | AH9: 4285186 | AI9: 2859376 | AJ9: 2597908 | AK9: 2104947 | AL9: 1554173 | AM9: 2489757 | AN9: 2849400 | AO9: 2389931 | AP9: 870412 | AQ9: 3310911 | AR9: 2342232 | AS9: 1759789 | AT9: 1156808 | AU9: 2050141 | AV9: 1149036 | AW9: 1039740 | AX9: 1599344 | AY9: 2069213 | AZ9: 2209336 | BA9: 2190000 | BB9: 1199030 | BC9: 1647625 | BD9: 751854 | BE9: 1493177 | BF9: 1482807 | BG9: 765880 | BH9: 1158366 | BI9: 1253209 | BJ9: 2034457 | BK9: 330657 | BL9: 1212867 | BM9: 2232990 | BN9: 882803 | BO9: 548534 | BP9: 1150250 | BQ9: 991263 | BR9: 987235 | BS9: 1100600 | BT9: 543620 | BU9: 648254 | BV9: 580027 | BW9: 329610 | BX9: 648456 | BY9: 135000 | BZ9: 457366 | CA9: 318679 | CB9: 349920 | CC9: 192138 | CD9: 260579 | CE9: 19462 | CF9: 152611 | CG9: 541980 | CH9: 55311 | CI9: 148053 | CJ9: 871181 | CK9: 364897 | CL9: 118692 | CM9: 59656 | CN9: 242416 | CO9: 95375 | CQ9: =SUM(B9:CO9) -> 459361145
A10: Total Billed Volume | B10: 89354658 | C10: 9390958 | D10: 5857951 | E10: 8021159 | F10: 7196567 | G10: 4029508 | H10: 10035329 | I10: 6518879 | J10: 3251362 | K10: 7176263 | L10: 4790134 | M10: 5735266 | N10: 4803192 | O10: 4174940 | P10: 2619147 | Q10: 2860604 | R10: 1729915 | S10: 5063398 | T10: 3505364 | U10: 3452279 | V10: 1168246 | W10: 2821512 | X10: 2309753 | Y10: 1132125 | Z10: 1981221 | AA10: 1082267 | AB10: 3913798 | AC10: 2633472 | AD10: 2255913 | AE10: 1552417.5 | AF10: 1847078 | AG10: 1641373 | AH10: 1462434 | AI10: 1715626 | AJ10: 1122874 | AK10: 1384751 | AL10: 1035882 | AM10: 1533733 | AN10: 1177267 | AO10: 1683819 | AP10: 451202 | AQ10: 2184974 | AR10: 1410179 | AS10: 1100525 | AT10: 714398 | AU10: 1509089 | AV10: 694696 | AW10: 544490 | AX10: 1012049 | AY10: 632186 | AZ10: 1096386 | BA10: 986358 | BB10: 747585 | BC10: 1158721 | BD10: 408492 | BE10: 370119 | BF10: 1046177 | BG10: 414063 | BH10: 515264 | BI10: 828725 | BJ10: 591852 | BK10: 140507 | BL10: 730785 | BM10: 1784695 | BN10: 356049 | BO10: 308573 | BP10: 460217 | BQ10: 632818 | BR10: 679966 | BS10: 748404 | BT10: 302011 | BU10: 446190 | BV10: 341170 | BW10: 213422 | BX10: 519402 | BY10: 92760 | BZ10: 311864 | CA10: 228068 | CB10: 141978 | CC10: 149048 | CD10: 150404.03 | CE10: 19462 | CF10: 95706 | CG10: 454680 | CH10: 37031 | CI10: 95856 | CJ10: 660474 | CK10: 274750 | CL10: 82962 | CM10: 43000 | CN10: 227620 | CO10: 91707 | CQ10: =SUM(B10:CO10) -> 2.5426154e+08
CQ11: =SUM(B11:CO11) -> 0
CQ12: =SUM(B12:CO12) -> 0
A13: Total Water Produced | B13: 178526913 | C13: 15451881 | D13: 11904294 | E13: 11507540 | F13: 10497618 | G13: 8309282 | H13: 14022595 | I13: 7882990 | J13: 6119845 | K13: 11544566 | L13: 7406276 | M13: 10880179 | N13: 7705097 | O13: 8233972 | P13: 6341902 | Q13: 4499131 | R13: 3645781 | S13: 7173382 | T13: 6461280 | U13: 5420914 | V13: 2048705 | W13: 4119964 | X13: 3042245 | Y13: 2757153 | Z13: 3310246 | AA13: 4668790 | AB13: 6523000 | AC13: 3223424 | AD13: 5085497 | AE13: 3504344 | AF13: 2856496 | AG13: 3451316 | AH13: 4285186 | AI13: 2859376 | AJ13: 2597908 | AK13: 2104947 | AL13: 1554173 | AM13: 2489757 | AN13: 2849400 | AO13: 2389931 | AP13: 870412 | AQ13: 3310911 | AR13: 2342232 | AS13: 1759789 | AT13: 1156808 | AU13: 2050141 | AV13: 1149036 | AW13: 1039740 | AX13: 1599344 | AY13: 2069213 | AZ13: 2209336 | BA13: 2190000 | BB13: 1199030 | BC13: 1647625 | BD13: 751854 | BE13: 1493177 | BF13: 1482807 | BG13: 765880 | BH13: 1158366 | BI13: 1253209 | BJ13: 2034457 | BK13: 330657 | BL13: 1212867 | BM13: 2232990 | BN13: 882803 | BO13: 548534 | BP13: 1150250 | BQ13: 991263 | BR13: 987235 | BS13: 1100600 | BT13: 543620 | BU13: 648254 | BV13: 580027 | BW13: 329610 | BX13: 648456 | BY13: 135000 | BZ13: 457366 | CA13: 318679 | CB13: 349920 | CC13: 192138 | CD13: 260579 | CE13: 19462 | CF13: 152611 | CG13: 541980 | CH13: 55311 | CI13: 148053 | CJ13: 871181 | CK13: 364897 | CL13: 118692 | CM13: 59656 | CN13: 242416 | CO13: 95375 | CQ13: =SUM(B13:CO13) -> 459361145
A14: Total sewage treated
A15: Total Expenditures | B15: 10645852878 | C15: 962233117 | D15: 918680449 | E15: 996646360 | F15: 1000565717 | G15: 412187848 | H15: 836862000 | I15: 638968937 | J15: 230551211 | K15: 877093054 | L15: 146932368 | M15: 751489827 | N15: 455314422 | O15: 349466529 | P15: 215437017 | Q15: 432492755 | R15: 250782412 | S15: 632230497 | T15: 201158045 | U15: 488015895 | V15: 159770663 | W15: 324882829 | X15: 297985199 | Y15: 84981101 | Z15: 259360405 | AA15: 270108010 | AB15: 264527307 | AC15: 241435421 | AD15: 2.7523509e+08 | AE15: 178447107 | AF15: 78682282 | AG15: 294634864 | AH15: 107360302 | AI15: 62717211 | AJ15: 169078907 | AK15: 166290541 | AL15: 295135809 | AM15: 165643468 | AN15: 75645459 | AO15: 99494001 | AP15: 87528323 | AQ15: 223949944 | AR15: 201710245 | AS15: 72401030 | AT15: 40355352 | AU15: 2.1451749e+08 | AV15: 59550550 | AW15: 16324511 | AX15: 103287907 | AY15: 83098624 | AZ15: 44397948 | BA15: 92675395 | BB15: 143372243 | BC15: 1.5557779e+08 | BD15: 95831971 | BE15: 18637934 | BF15: 108493396 | BG15: 46435497 | BH15: 41318340 | BI15: 129791550 | BJ15: 46188784 | BK15: 49575380 | BL15: 75253661 | BM15: 22012332 | BN15: 22161656 | BO15: 90717198 | BP15: 67667449 | BQ15: 1.3225202e+08 | BR15: 24009594 | BS15: 36512693 | BT15: 159253591 | BU15: 58031115 | BV15: 45037444 | BW15: 37098608 | BX15: 11898059 | BY15: 16994345 | BZ15: 47431817 | CA15: 20566296 | CB15: 79017863 | CC15: 9773893 | CD15: 39085517 | CE15: 2957665 | CF15: 19971306 | CG15: 25428305 | CH15: 5112489 | CI15: 6994627 | CJ15: 66928505 | CK15: 3913867 | CL15: 15371900 | CM15: 21286265 | CN15: 76697000 | CO15: 46674030
A16: Total Expenditures-water | B16: 6.9198044e+09 | C16: 8.1789815e+08 | D16: 7.3494436e+08 | E16: 996646360 | F16: 8.75495e+08 | G16: 3.5035967e+08 | H16: 636015120 | I16: 5.7507204e+08 | J16: 230551211 | K16: 877093054 | L16: 146932368 | M16: 751489827 | N16: 3.8701726e+08 | O16: 349466529 | P16: 215437017 | Q16: 3.0274493e+08 | R16: 2.1316505e+08 | S16: 632230497 | T16: 201158045 | U16: 488015895 | V16: 159770663 | W16: 3.0863869e+08 | X16: 2.8904564e+08 | Y16: 84981101 | Z16: 2.2045634e+08 | AA16: 2.2959181e+08 | AB16: 2.2484821e+08 | AC16: 241435421 | AD16: 2.7523509e+08 | AE16: 178447107 | AF16: 78682282 | AG16: 294634864 | AH16: 107360302 | AI16: 62717211 | AJ16: 169078907 | AK16: 166290541 | AL16: 2.5086544e+08 | AM16: 165643468 | AN16: 75645459 | AO16: 84569901 | AP16: 87528323 | AQ16: 1.9035745e+08 | AR16: 201710245 | AS16: 72401030 | AT16: 40355352 | AU16: 1.8233987e+08 | AV16: 59550550 | AW16: 16324511 | AX16: 103287907 | AY16: 83098624 | AZ16: 44397948 | BA16: 92675395 | BB16: 1.2186641e+08 | BC16: 1.5557779e+08 | BD16: 95831971 | BE16: 18637934 | BF16: 108493396 | BG16: 46435497 | BH16: 41318340 | BI16: 129791550 | BJ16: 46188784 | BK16: 49575380 | BL16: 75253661 | BM16: 22012332 | BN16: 22161656 | BO16: 90717198 | BP16: 67667449 | BQ16: 1.3225202e+08 | BR16: 24009594 | BS16: 36512693 | BT16: 159253591 | BU16: 58031115 | BV16: 45037444 | BW16: 37098608 | BX16: 11898059 | BY16: 16994345 | BZ16: 47431817 | CA16: 20566296 | CB16: 79017863 | CC16: 9773893 | CD16: 39085517 | CE16: 2957665 | CF16: 19971306 | CG16: 25428305 | CH16: 5112489 | CI16: 6994627 | CJ16: 66928505 | CK16: 3913867 | CL16: 15371900 | CM16: 21286265 | CN16: 76697000 | CO16: 46674030
A17: Total Expenditures-sewerage | B17: 2.4219315e+09 | C17: 1.2268472e+08 | D17: 1.4698887e+08 | E17: 149496954 | F17: 1.0943688e+08 | G17: 52553951 | H17: 1.5264363e+08 | I17: 57507204 | K17: 87709305 | N17: 58052589 | Q17: 90823479 | R17: 31974758 | W17: 15431934 | X17: 8671369.3 | Z17: 33068452 | AA17: 34438771 | AB17: 33727232 | AG17: 44195230 | AL17: 37629816 | AO17: 12685485 | AQ17: 28553618 | AU17: 27350980 | BB17: 18279961 | BD17: 14374796
A18: Actual cost-water produced | B18: 38.760567 | C18: 52.931947 | D18: 61.737753 | E18: 86.608116 | F18: 83.399396 | G18: 42.164855 | H18: 45.356449 | I18: 72.951005 | J18: 37.672721 | K18: 75.974537 | L18: 19.8389 | M18: 69.06962 | N18: 50.228733 | O18: 42.442035 | P18: 33.970411 | Q18: 67.289645 | R18: 58.468967 | S18: 88.135624 | T18: 31.132848 | U18: 90.024652 | V18: 77.986173 | W18: 74.912957 | X18: 95.01064 | Y18: 30.822048 | Z18: 66.598176 | AA18: 49.17587 | AB18: 34.470061 | AC18: 74.900299 | AD18: 54.121571 | AE18: 50.921687 | AF18: 27.545035 | AG18: 85.368846 | AH18: 25.053825 | AI18: 21.93388 | AJ18: 65.082715 | AK18: 78.999871 | AL18: 161.4141 | AM18: 66.529974 | AN18: 26.547855 | AO18: 35.385917 | AP18: 100.55965 | AQ18: 57.49398 | AR18: 86.118815 | AS18: 41.141881 | AT18: 34.885091 | AU18: 88.940159 | AV18: 51.826531 | AW18: 15.70057 | AX18: 64.58142 | AY18: 40.159531 | AZ18: 20.095607 | BA18: 42.317532 | BB18: 101.6375 | BC18: 94.425484 | BD18: 127.46088 | BE18: 12.482066 | BF18: 73.167577 | BG18: 60.630251 | BH18: 35.669503 | BI18: 103.56736 | BJ18: 22.703249 | BK18: 149.92993 | BL18: 62.046095 | BM18: 9.8577835 | BN18: 25.103739 | BO18: 165.38118 | BP18: 58.828471 | BQ18: 133.4177 | BR18: 24.32004 | BS18: 33.175262 | BT18: 292.95021 | BU18: 89.519101 | BV18: 77.647151 | BW18: 112.55304 | BX18: 18.34829 | BY18: 125.88404 | BZ18: 103.70648 | CA18: 64.536088 | CB18: 225.81694 | CC18: 50.869131 | CD18: 149.99488 | CE18: 151.97128 | CF18: 130.86413 | CG18: 46.917423 | CH18: 92.431686 | CI18: 47.244075 | CJ18: 76.825028 | CK18: 10.72595 | CL18: 129.51083 | CM18: 356.81683 | CN18: 316.38588 | CO18: 489.37384 | CQ18: =SUM(B18:CO18) -> 7449.4574
A19: ='[1]Abstraction & Water Value 20-21'!A21 -> Actual unit cost- sewage treated | B19: ='[1]Abstraction & Water Value 20-21'!AY21 -> 45.359281 | C19: ='[1]Abstraction & Water Value 20-21'!F21 -> 13.609543 | D19: =D18 -> 61.737753 | E19: ='[1]Abstraction & Water Value 20-21'!BA21 -> 28.300345 | F19: ='[1]Abstraction & Water Value 20-21'!AE21 -> 21.999332 | G19: ='[1]Abstraction & Water Value 20-21'!BL21 -> 40.558013 | H19: ='[1]Abstraction & Water Value 20-21'!BV21 -> 29.754233 | I19: ='[1]Abstraction & Water Value 20-21'!BK21 -> 11.87687 | K19: ='[1]Abstraction & Water Value 20-21'!BP21 -> 57.853015 | N19: ='[1]Abstraction & Water Value 20-21'!I21 -> 27.909292 | Q19: ='[1]Abstraction & Water Value 20-21'!T21 -> 185.60633 | R19: =R18 -> 58.468967 | W19: ='[1]Abstraction & Water Value 20-21'!BC21 -> 19.86298 | X19: =X18 -> 95.01064 | Z19: ='[1]Abstraction & Water Value 20-21'!BI21 -> 35.067308 | AA19: ='[1]Abstraction & Water Value 20-21'!O21 -> 14.48383 | AB19: ='[1]Abstraction & Water Value 20-21'!J21 -> 292.32548 | AG19: =AG18 -> 85.368846 | AL19: =AL18 -> 161.4141 | AO19: ='[1]Abstraction & Water Value 20-21'!R21 -> 41.510444 | AQ19: =AQ18 -> 57.49398 | AU19: ='[1]Abstraction & Water Value 20-21'!AZ21 -> 79.573352 | BB19: =BB18 -> 101.6375 | BD19: =BD18 -> 127.46088 | CQ19: =SUM(B19:CO19) -> 1694.2423
CQ20: =SUM(B20:CO20) -> 0
A21: Water Value (in Ksh.) per category | CQ21: =SUM(B21:CO21) -> 0
A22: Individual | B22: 4.4748137e+08 | C22: 3.8758e+08 | D22: 1.5493324e+08 | E22: 1.8536952e+08 | F22: 2.9008695e+08 | G22: 1.2049952e+08 | H22: 1.3924852e+08 | I22: 1.2479378e+08 | J22: 91988951 | K22: 3.5211421e+08 | L22: 91062889 | M22: 2.9694425e+08 | N22: 1.7172767e+08 | O22: 27461735 | P22: 72638256 | Q22: 56941978 | R22: 80076360 | S22: 2.4828111e+08 | T22: 93466260 | U22: 2.3507958e+08 | V22: 62504589 | W22: 68124870 | X22: 47046003 | Y22: 22499926 | Z22: 72819558 | AA22: 39124322 | AB22: 7487448.9 | AC22: 1.5624383e+08 | AD22: 1.0241729e+08 | AE22: 23315811 | AF22: 19474152 | AG22: 56879234 | AH22: 18319808 | AI22: 12876175 | AJ22: 40299933 | AK22: 65174893 | AL22: 41048090 | AM22: 41777751 | AN22: 21699576 | AO22: 39663792 | AP22: 40492292 | AQ22: 50745912 | AR22: 32453142 | AS22: 25355516 | AT22: 20878391 | AU22: 54108702 | AV22: 16201647 | AW22: 7829843 | AX22: 21699340 | AY22: 17738463 | AZ22: 0 | BA22: 26296368 | BB22: 10853055 | BC22: 36158917 | BD22: 45601082 | BE22: 3863188 | BF22: 36717116 | BG22: 22180920 | BH22: 8303705.3 | BI22: 48209981 | BJ22: 1356368 | BK22: 15729771 | BL22: 16406312 | BM22: 14074514 | BN22: 7264222 | BO22: 37604994 | BP22: 135194.5 | BQ22: 28977256 | BR22: 0 | BS22: 10655006 | BT22: 0 | BU22: 0 | BV22: 19779221 | BW22: 4624129.2 | BX22: 9340931.2 | BY22: 4442447.7 | BZ22: 5412541.6 | CA22: 7287931.4 | CB22: 0 | CC22: 6383976.4 | CD22: 5345217.7 | CE22: 35388196 | CF22: 8794528.4 | CG22: 13605602 | CH22: 26.247581 | CI22: 3191675.4 | CJ22: 50099445 | CK22: 2441793.3 | CL22: 1611639 | CM22: 3310767.3 | CN22: 14186.35 | CO22: 15374809
A23: Multi-dwelling units | B23: 1.5985024e+08 | C23: 2052847.8 | D23: 66400003 | E23: 1.5850714e+08 | F23: 0 | G23: 6491405.9 | H23: 5137207.5 | I23: 1.1107279e+08 | J23: 0 | K23: 1.3052415e+08 | L23: 0 | M23: 0 | N23: 0 | O23: 31933311 | P23: 0 | Q23: 74029511 | R23: 0 | S23: 0 | T23: 0 | U23: 0 | V23: 0 | W23: 0 | X23: 26190696 | Y23: 0 | Z23: 0 | AA23: 23642430 | AB23: 1416547.2 | AC23: 0 | AD23: 0 | AE23: 0 | AF23: 0 | AG23: 23807918 | AH23: 0 | AI23: 19758536 | AJ23: 147867.93 | AK23: 0 | AL23: 24238587 | AM23: 0 | AN23: 0 | AO23: 0 | AP23: 0 | AQ23: 25236523 | AR23: 79300005 | AS23: 0 | AT23: 0 | AU23: 13887561 | AV23: 5400530.6 | AW23: 0 | AX23: 29542517 | AY23: 1376019.4 | AZ23: 0 | BA23: 0 | BB23: 9796736.6 | BC23: 0 | BD23: 0 | BE23: 0 | BF23: 10896600 | BG23: 0 | BH23: 4169106.2 | BI23: 2868746.3 | BJ23: 3390.55 | BK23: 0 | BL23: 2637546.3 | BM23: 0 | BN23: 0 | BO23: 0 | BP23: 66592.15 | BQ23: 9496271.3 | BR23: 0 | BS23: 2823012.5 | BT23: 0 | BU23: 0 | BV23: 0 | BW23: 8587572 | BX23: 0 | BY23: 0 | BZ23: 4114956.4 | CA23: 6301884.5 | CB23: 0 | CC23: 0 | CD23: 10225751 | CE23: 0 | CF23: 492376.44 | CG23: 5333103.5 | CH23: 0 | CI23: 449546.52 | CJ23: 0 | CK23: 0 | CL23: 1719142.6 | CM23: 3027860.3 | CN23: 8196.6 | CO23: 21384727
A24: Institutions | B24: 23007885 | C24: 20026930 | D24: 6370533.5 | E24: 501980.64 | F24: 25386546 | G24: 476589.36 | H24: 2892154 | I24: 32277026 | J24: 1133754.1 | K24: 3552637.4 | L24: 2296533.3 | M24: 19356830 | N24: 10578573 | O24: 18879770 | P24: 6830316.3 | Q24: 4062814.2 | R24: 892395.27 | S24: 10333156 | T24: 3057255.8 | U24: 26434940 | V24: 13553441 | W24: 0 | X24: 2545203.6 | Y24: 2871124.1 | Z24: 6564743.4 | AA24: 7175152.8 | AB24: 2428346.9 | AC24: 7768879.8 | AD24: 2132732.9 | AE24: 1283868.8 | AF24: 9176398.7 | AG24: 14383856 | AH24: 7327918.2 | AI24: 2215063.3 | AJ24: 3498781.7 | AK24: 5273873.4 | AL24: 1309229.8 | AM24: 0 | AN24: 1866374.6 | AO24: 1320991.7 | AP24: 414898.66 | AQ24: 1387444.7 | AR24: 436928.82 | AS24: 13583305 | AT24: 1610105.6 | AU24: 407879.57 | AV24: 3600390.3 | AW24: 0 | AX24: 261466.74 | AY24: 374623.08 | AZ24: 0 | BA24: 0 | BB24: 11970254 | BC24: 62556128 | BD24: 2504470.5 | BE24: 392812.66 | BF24: 2618954 | BG24: 292401.19 | BH24: 1666806.7 | BI24: 7588697.9 | BJ24: 113596.3 | BK24: 2474252.7 | BL24: 9068484.6 | BM24: 1231516.7 | BN24: 35364.299 | BO24: 0 | BP24: 7789.05 | BQ24: 4418527.2 | BR24: 0 | BS24: 4202103.2 | BT24: 0 | BU24: 0 | BV24: 712495.74 | BW24: 4083649.5 | BX24: 8256.7307 | BY24: 1724863.1 | BZ24: 9103960.9 | CA24: 298866.62 | CB24: 0 | CC24: 37923.407 | CD24: 573130.45 | CE24: 13953703 | CF24: 732419.77 | CG24: 0 | CH24: 5.1656905 | CI24: 224748.29 | CJ24: 0 | CK24: 0 | CL24: 3760534.6 | CM24: 1955545.5 | CN24: 18442.35 | CO24: 6489970.9
A25: Schools | B25: 2219778.9 | C25: 3251865.3 | D25: 4247063.5 | E25: 513153.09 | F25: 4406863.2 | G25: 16346893 | H25: 3734377.9 | I25: 23595127 | J25: 6740697.2 | K25: 4004133.5 | L25: 1345907 | M25: 18567364 | N25: 14638310 | O25: 3446782.7 | P25: 3379023.4 | Q25: 11916727 | R25: 4801385.3 | S25: 5288904.4 | T25: 7853693 | U25: 10018291 | V25: 0 | W25: 2529286.2 | X25: 1375570.7 | Y25: 1498581.6 | Z25: 5895157.4 | AA25: 2573176.6 | AB25: 3642520.3 | AC25: 3342550 | AD25: 3199182.4 | AE25: 2057743.1 | AF25: 9462778.6 | AG25: 6164481.9 | AH25: 3663971.6 | AI25: 566924.07 | AJ25: 3005324.5 | AK25: 3849426.7 | AL25: 521044.72 | AM25: 11223249 | AN25: 3846293.6 | AO25: 0 | AP25: 2517812.6 | AQ25: 391534.01 | AR25: 1603291.1 | AS25: 0 | AT25: 0 | AU25: 2139366.6 | AV25: 3240340.3 | AW25: 718960.52 | AX25: 196081.31 | AY25: 2430247.2 | AZ25: 0 | BA25: 8348064.2 | BB25: 7033111.4 | BC25: 6194217.3 | BD25: 1157497.7 | BE25: 294370.88 | BF25: 1813273.7 | BG25: 2505771.9 | BH25: 3018751.3 | BI25: 5754613.3 | BJ25: 169546.5 | BK25: 1170088.4 | BL25: 2146126 | BM25: 1759316.7 | BN25: 68869.619 | BO25: 6447850.7 | BP25: 0 | BQ25: 3778255.7 | BR25: 0 | BS25: 3619929.3 | BT25: 0 | BU25: 0 | BV25: 976783.94 | BW25: 1839341.8 | BX25: 162786.03 | BY25: 1950321.4 | BZ25: 5026708.6 | CA25: 211162.08 | CB25: 0 | CC25: 204713.35 | CD25: 1976482.6 | CE25: 6903031.4 | CF25: 511987.83 | CG25: 2393708.2 | CH25: 2.555517 | CI25: 89899.315 | CJ25: 495521.43 | CK25: 472867.38 | CL25: 1934019.1 | CM25: 1973519.3 | CN25: 22541.6 | CO25: 2327454.4
A26: Commercial customers | B26: 1.1287058e+08 | C26: 59106012 | D26: 31852667 | E26: 15151397 | F26: 1.5452172e+08 | G26: 18893397 | H26: 55455380 | I26: 40626196 | J26: 22081014 | K26: 0 | L26: 158339.69 | M26: 11057217 | N26: 42348899 | O26: 23605418 | P26: 6107015.2 | Q26: 5319179.2 | R26: 9553582 | S26: 51625704 | T26: 4611962.4 | U26: 32835937 | V26: 14932225 | W26: 35909601 | X26: 24043787 | Y26: 2871095.4 | Z26: 23502447 | AA26: 5652028.6 | AB26: 4249641.5 | AC26: 26876944 | AD26: 3778729.4 | AE26: 5722985 | AF26: 6390299.7 | AG26: 7502476.8 | AH26: 6961506 | AI26: 2213636.5 | AJ26: 1591858.1 | AK26: 10816504 | AL26: 46616877 | AM26: 45974029 | AN26: 3788922 | AO26: 3376771.9 | AP26: 387111.97 | AQ26: 3288770.7 | AR26: 5581686.7 | AS26: 3622228.6 | AT26: 2433342.9 | AU26: 19618153 | AV26: 7200725.8 | AW26: 0 | AX26: 11568647 | AY26: 261530.74 | AZ26: 0 | BA26: 0 | BB26: 12719933 | BC26: 4003357.3 | BD26: 1846246.8 | BE26: 0 | BF26: 5218091.4 | BG26: 0 | BH26: 935312.6 | BI26: 12463763 | BJ26: 50863.95 | BK26: 1407335 | BL26: 13602659 | BM26: 510200.35 | BN26: 17648.641 | BO26: 6678597.3 | BP26: 52540.7 | BQ26: 2511588.1 | BR26: 0 | BS26: 3414135.3 | BT26: 0 | BU26: 0 | BV26: 4076352.4 | BW26: 3603160.5 | BX26: 4954.0384 | BY26: 990959.14 | BZ26: 6412220.3 | CA26: 611350.36 | CB26: 0 | CC26: 803696.22 | CD26: 0 | CE26: 12476065 | CF26: 0 | CG26: 0 | CH26: 4.6186661 | CI26: 449546.52 | CJ26: 52932.445 | CK26: 32294.079 | CL26: 1504266.1 | CM26: 1875023.1 | CN26: 12294.9 | CO26: 5112295.5
A27: Industries | B27: 7274079.3 | C27: 0 | D27: 21235132 | E27: 0 | F27: 1025825.4 | G27: 0 | H27: 18868782 | I27: 0 | J27: 0 | K27: 50274432 | L27: 0 | M27: 20428791 | N27: 0 | O27: 153642.81 | P27: 0 | Q27: 0 | R27: 0 | S27: 1947472.3 | T27: 0 | U27: 2490114.9 | V27: 0 | W27: 0 | X27: 2142983.2 | Y27: 1498581.6 | Z27: 7486698 | AA27: 4868.4111 | AB27: 1011799.7 | AC27: 0 | AD27: 2519180.6 | AE27: 4085.5015 | AF27: 6374199.1 | AG27: 0 | AH27: 0 | AI27: 0 | AJ27: 23234.529 | AK27: 0 | AL27: 18323083 | AM27: 0 | AN27: 47952.367 | AO27: 0 | AP27: 31590.196 | AQ27: 0 | AR27: 0 | AS27: 0 | AT27: 0 | AU27: 0 | AV27: 0 | AW27: 0 | AX27: 0 | AY27: 2612530.7 | AZ27: 0 | BA27: 0 | BB27: 10411034 | BC27: 0 | BD27: 53740.611 | BE27: 0 | BF27: 0 | BG27: 0 | BH27: 0 | BI27: 0 | BJ27: 0 | BK27: 0 | BL27: 1110937.4 | BM27: 0 | BN27: 0 | BO27: 0 | BP27: 0 | BQ27: 10421123 | BR27: 0 | BS27: 0 | BT27: 0 | BU27: 0 | BV27: 0 | BW27: 0 | BX27: 0 | BY27: 0 | BZ27: 0 | CA27: 0 | CB27: 0 | CC27: 0 | CD27: 0 | CE27: 0 | CF27: 0 | CG27: 0 | CH27: 0 | CI27: 78262.348 | CJ27: 0 | CK27: 0 | CL27: 0 | CM27: 0 | CN27: 0 | CO27: 4403.5085
A28: Kiosks | B28: 63803731 | C28: 25064040 | D28: 37585203 | E28: 250470.67 | F28: 36409916 | G28: 2877203.2 | H28: 234039.28 | I28: 751906.01 | J28: 543235.62 | K28: 4743693.4 | L28: 167319.33 | M28: 16197655 | N28: 1964797.3 | O28: 1457639.5 | P28: 18888.596 | Q28: 14433292 | R28: 450100.44 | S28: 23107503 | T28: 142791.64 | U28: 3456253.4 | V28: 0 | W28: 195597.73 | X28: 184930.17 | Y28: 0 | Z28: 247371.33 | AA28: 22129141 | AB28: 0 | AC28: 3015640.2 | AD28: 8046438.5 | AE28: 408550.15 | AF28: 0 | AG28: 25912497 | AH28: 366362.09 | AI28: 0 | AJ28: 22900460 | AK28: 1030395.3 | AL28: 5065820.1 | AM28: 3064187.4 | AN28: 4795.2367 | AO28: 280398.01 | AP28: 1529007.8 | AQ28: 477659.99 | AR28: 2067891.5 | AS28: 902173 | AT28: 0 | AU28: 5829049.1 | AV28: 360050 | AW28: 0 | AX28: 130695.88 | AY28: 114818.37 | AZ28: 0 | BA28: 0 | BB28: 1893913.1 | BC28: 500171.79 | BD28: 900352.81 | BE28: 69478.234 | BF28: 11562479 | BG28: 125650.69 | BH28: 285529.05 | BI28: 3352920 | BJ28: 1694.8 | BK28: 284757.39 | BL28: 370289.92 | BM28: 17589.691 | BN28: 4947.5636 | BO28: 300723.29 | BP28: 1102.95 | BQ28: 18494628 | BR28: 0 | BS28: 114311.84 | BT28: 0 | BU28: 0 | BV28: 860695.58 | BW28: 720677.12 | BX28: 13210.769 | BY28: 0 | BZ28: 2271929.2 | CA28: 7421.6501 | CB28: 0 | CC28: 151632.76 | CD28: 1734840.8 | CE28: 38587.649 | CF28: 1993170.2 | CG28: 0 | CH28: 0.01428523 | CI28: 44949.657 | CJ28: 0 | CK28: 0 | CL28: 214876.48 | CM28: 3200408.4 | CN28: 3152.1 | CO28: 20015948
A29: Bulk | B29: 1.2080231e+08 | C29: 0 | D29: 5798162.8 | E29: 0 | F29: 60678361 | G29: 306791.49 | H29: 0 | I29: 0 | J29: 0 | K29: 0 | L29: 0 | M29: 12029372 | N29: 0 | O29: 70254651 | P29: 0 | Q29: 0 | R29: 6325.2266 | S29: 130405.69 | T29: 0 | U29: 475101.6 | V29: 116779.81 | W29: 0 | X29: 0 | Y29: 3655102.2 | Z29: 15375358 | AA29: 0 | AB29: 0 | AC29: 0 | AD29: 0 | AE29: 0 | AF29: 0 | AG29: 5471655.6 | AH29: 0 | AI29: 0 | AJ29: 1435269.1 | AK29: 5171252.5 | AL29: 0 | AM29: 0 | AN29: 0 | AO29: 0 | AP29: 0 | AQ29: 11052183 | AR29: 0 | AS29: 1814446.1 | AT29: 0 | AU29: 601413.35 | AV29: 0 | AW29: 0 | AX29: 1960813.1 | AY29: 480060.87 | AZ29: 0 | BA29: 6261048.1 | BB29: 0 | BC29: 0 | BD29: 0 | BE29: 0 | BF29: 0 | BG29: 0 | BH29: 0 | BI29: 3648765.9 | BJ29: 0 | BK29: 0 | BL29: 0 | BM29: 0 | BN29: 0 | BO29: 0 | BP29: 0 | BQ29: 0 | BR29: 0 | BS29: 0 | BT29: 0 | BU29: 0 | BV29: 85329.911 | BW29: 0 | BX29: 0 | BY29: 2568412 | BZ29: 0 | CA29: 0 | CB29: 0 | CC29: 0 | CD29: 2409517.8 | CE29: 0 | CF29: 0 | CG29: 0 | CH29: 0 | CI29: 0 | CJ29: 93035.109 | CK29: 0 | CL29: 0 | CM29: 0 | CN29: 0 | CO29: 0
A30: Others | B30: 20563682 | C30: 0 | D30: 0 | E30: 0 | F30: 27673160 | G30: 0 | H30: 0 | I30: 0 | J30: 0 | K30: 0 | L30: 0 | M30: 54219.652 | N30: 0 | O30: 0 | P30: 0 | Q30: 0 | R30: 0 | S30: 0 | T30: 0 | U30: 0 | V30: 0 | W30: 0 | X30: 0 | Y30: 0 | Z30: 1424325 | AA30: 0 | AB30: 0 | AC30: 0 | AD30: 0 | AE30: 46258674 | AF30: 0 | AG30: 0 | AH30: 0 | AI30: 0 | AJ30: 0 | AK30: 0 | AL30: 0 | AM30: 0 | AN30: 0 | AO30: 0 | AP30: 0 | AQ30: 0 | AR30: 0 | AS30: 0 | AT30: 0 | AU30: 0 | AV30: 0 | AW30: 0 | AX30: 0 | AY30: 0 | AZ30: 0 | BA30: 0 | BB30: 0 | BC30: 0 | BD30: 3358.7882 | BE30: 0 | BF30: 7719722.9 | BG30: 0 | BH30: 0 | BI30: 1941374.5 | BJ30: 0 | BK30: 0 | BL30: 0 | BM30: 0 | BN30: 0 | BO30: 0 | BP30: 0 | BQ30: 2418329.1 | BR30: 0 | BS30: 0 | BT30: 0 | BU30: 0 | BV30: 0 | BW30: 0 | BX30: 0 | BY30: 0 | BZ30: 0 | CA30: 0 | CB30: 0 | CC30: 0 | CD30: 2409517.8 | CE30: 0 | CF30: 0 | CG30: 0 | CH30: 0 | CI30: 0 | CJ30: 0 | CK30: 0 | CL30: 0 | CM30: 0 | CN30: 0 | CO30: 0
CQ31: =SUM(B31:CO31) -> 0
A32: Sewer Value (in Ksh.) per category | CQ32: =SUM(B32:CO32) -> 0
A33: Individual | B33: 1.5661848e+08 | C33: 58137000 | D33: 30986647 | E33: 27805427 | F33: 36260869 | G33: 18074929 | H33: 33419644 | I33: 12479378 | K33: 52817132 | N33: 25759150 | Q33: 8541296.7 | R33: 12011454 | W33: 10218730 | X33: 7056900.4 | Z33: 10922934 | AA33: 5868648.3 | AB33: 1123117.3 | AG33: 8531885.1 | AL33: 6157213.5 | AO33: 5949568.8 | AQ33: 7611886.8 | AU33: 8116305.3 | BB33: 1627958.3 | BD33: 6840162.3
A34: Multi-dwelling units | B34: 55947586 | C34: 307927.17 | D34: 13280001 | E34: 23776071 | F34: 0 | G34: 973710.89 | H34: 1232929.8 | I34: 11107279 | K34: 19578623 | N34: 0 | Q34: 11104427 | R34: 0 | W34: 0 | X34: 3928604.4 | Z34: 0 | AA34: 3546364.6 | AB34: 212482.08 | AG34: 3571187.7 | AL34: 3635788.1 | AO34: 0 | AQ34: 3785478.4 | AU34: 2083134.2 | BB34: 1469510.5 | BD34: 0
A35: Institutions | B35: 8052759.7 | C35: 3004039.4 | D35: 1274106.7 | E35: 75297.096 | F35: 3173318.2 | G35: 71488.403 | H35: 694116.96 | I35: 3227702.6 | K35: 532895.61 | N35: 1586785.9 | Q35: 609422.13 | R35: 133859.29 | W35: 0 | X35: 381780.55 | Z35: 984711.5 | AA35: 1076272.9 | AB35: 364252.03 | AG35: 2157578.3 | AL35: 196384.47 | AO35: 198148.75 | AQ35: 208116.71 | AU35: 61181.935 | BB35: 1795538.2 | BD35: 375670.58
A36: Schools | B36: 776922.62 | C36: 487779.8 | D36: 849412.7 | E36: 76972.963 | F36: 550857.9 | G36: 2452033.9 | H36: 896250.7 | I36: 2359512.7 | K36: 600620.02 | N36: 2195746.5 | Q36: 1787509 | R36: 720207.8 | W36: 379392.93 | X36: 206335.6 | Z36: 884273.61 | AA36: 385976.48 | AB36: 546378.05 | AG36: 924672.29 | AL36: 78156.708 | AO36: 0 | AQ36: 58730.101 | AU36: 320904.99 | BB36: 1054966.7 | BD36: 173624.65
A37: Commercial customers | B37: 39504702 | C37: 8865901.9 | D37: 6370533.5 | E37: 2272709.6 | F37: 19315215 | G37: 2834009.5 | H37: 13309291 | I37: 4062619.6 | K37: 0 | N37: 6352334.9 | Q37: 797876.87 | R37: 1433037.3 | W37: 5386440.2 | X37: 3606568.1 | Z37: 3525367 | AA37: 847804.29 | AB37: 637446.23 | AG37: 1125371.5 | AL37: 6992531.5 | AO37: 506515.79 | AQ37: 493315.6 | AU37: 2942723 | BB37: 1907989.9 | BD37: 276937.03
A38: Industries | B38: 2545927.8 | C38: 0 | D38: 4247026.4 | E38: 0 | F38: 128228.18 | G38: 0 | H38: 4528507.6 | I38: 0 | K38: 7541164.8 | N38: 0 | Q38: 0 | R38: 0 | W38: 0 | X38: 321447.47 | Z38: 1123004.7 | AA38: 730.26166 | AB38: 151769.96 | AG38: 0 | AL38: 2748462.5 | AO38: 0 | AQ38: 0 | AU38: 0 | BB38: 1561655 | BD38: 8061.0916
A41: Water Sold in cubic meters | CQ41: =SUM(B41:CO41) -> 0
A42: Individual | B42: =B22/$B$18 -> 11544758 | C42: =C22/$C$18 -> 7322232 | D42: =D22/$D$18 -> 2509538 | E42: =E22/$E$18 -> 2140325 | F42: =F22/$F$18 -> 3478286 | G42: =G22/$G$18 -> 2857819 | H42: =H22/$H$18 -> 3070093 | I42: =I22/$I$18 -> 1710652 | J42: =J22/$J$18 -> 2441792.1 | K42: =K22/$K$18 -> 4634634.5 | L42: =L22/$L$18 -> 4590117.9 | M42: =M22/$M$18 -> 4299202 | N42: =N22/$N$18 -> 3418913 | O42: =O22/$O$18 -> 647040.95 | P42: =P22/$P$18 -> 2138280.2 | Q42: =Q22/$Q$18 -> 846222 | R42: =R22/$R$18 -> 1369553.2 | S42: =S22/$S$18 -> 2817034.7 | T42: =T22/$T$18 -> 3002175.1 | U42: =U22/$U$18 -> 2611280 | V42: =V22/$V$18 -> 801482.96 | W42: =W22/$W$18 -> 909387 | X42: =X22/$X$18 -> 495165.63 | Y42: =Y22/$Y$18 -> 729994.52 | Z42: =Z22/$Z$18 -> 1093416.7 | AA42: =AA22/$AA$18 -> 795600 | AB42: =AB22/$AB$18 -> 217216 | AC42: =AC22/$AC$18 -> 2086024.1 | AD42: =AD22/$AD$18 -> 1892356.2 | AE42: =AE22/$AE$18 -> 457875.86 | AF42: =AF22/$AF$18 -> 706993.18 | AG42: =AG22/$AG$18 -> 666276.24 | AH42: =AH22/$AH$18 -> 731218 | AI42: =AI22/$AI$18 -> 587045.02 | AJ42: =AJ22/$AJ$18 -> 619211 | AK42: =AK22/$AK$18 -> 825000 | AL42: =AL22/$AL$18 -> 254303 | AM42: =AM22/$AM$18 -> 627953.82 | AN42: =AN22/$AN$18 -> 817375.86 | AO42: =AO22/$AO$18 -> 1120892 | AP42: =AP22/$AP$18 -> 402669.4 | AQ42: =AQ22/$AQ$18 -> 882630 | AR42: =AR22/$AR$18 -> 376841.48 | AS42: =AS22/$AS$18 -> 616294.53 | AT42: =AT22/$AT$18 -> 598490.36 | AU42: =AU22/$AU$18 -> 608372 | AV42: =AV22/$AV$18 -> 312612.99 | AW42: =AW22/$AW$18 -> 498698 | AX42: =AX22/$AX$18 -> 335999.73 | AY42: =AY22/$AY$18 -> 441699.95 | AZ42: =AZ22/$AZ$18 -> 0 | BA42: =BA22/$BA$18 -> 621406 | BB42: =BB22/$BB$18 -> 106782 | BC42: =BC22/$BC$18 -> 382936 | BD42: =BD22/$BD$18 -> 357765.32 | BE42: =BE22/$BE$18 -> 309499.09 | BF42: =BF22/$BF$18 -> 501822.22 | BG42: =BG22/$BG$18 -> 365839.16 | BH42: =BH22/$BH$18 -> 232795.65 | BI42: =BI22/$BI$18 -> 465493.96 | BJ42: =BJ22/$BJ$18 -> 59743.343 | BK42: =BK22/$BK$18 -> 104914.15 | BL42: =BL22/$BL$18 -> 264421.35 | BM42: =BM22/$BM$18 -> 1427756.4 | BN42: =BN22/$BN$18 -> 289368.13 | BO42: =BO22/$BO$18 -> 227383.76 | BP42: =BP22/$BP$18 -> 2298.1134 | BQ42: =BQ22/$BQ$18 -> 217192 | BR42: =BR22/$BR$18 -> 0 | BS42: =BS22/$BS$18 -> 321173.24 | BT42: =BT22/BT18 -> 0 | BU42: =BU22/BU18 -> 0 | BV42: =BV22/$BV$18 -> 254732.09 | BW42: =BW22/$BW$18 -> 41084 | BX42: =BX22/$BX$18 -> 509090 | BY42: =BY22/$BY$18 -> 35290 | BZ42: =BZ22/$BZ$18 -> 52190.97 | CA42: =CA22/$CA$18 -> 112928 | CB42: =CB22/CB18 -> 0 | CC42: =CC22/$CC$18 -> 125498.05 | CD42: =CD22/$CD$18 -> 35636 | CE42: =CE22/$CE$18 -> 232861.08 | CF42: =CF22/$CF$18 -> 67203.505 | CG42: =CG22/$CG$18 -> 289990.4 | CH42: =CH22/$CH$18 -> 0.28396735 | CI42: =CI22/$CI$18 -> 67557.157 | CJ42: =CJ22/$CJ$18 -> 652124 | CK42: =CK22/$CK$18 -> 227652.87 | CL42: =CL22/$CL$18 -> 12444.048 | CM42: =CM22/$CM$18 -> 9278.6186 | CN42: =CN22/$CN$18 -> 44.838758 | CO42: =CO22/$CO$18 -> 31417.309 | CQ42: =SUM(B42:CO42) -> 97974657
A43: Multi-dwelling units | B43: =B23/$B$18 -> 4124043 | C43: =C23/$C$18 -> 38782.776 | D43: =D23/$D$18 -> 1075517 | E43: =E23/$E$18 -> 1830165 | F43: =F23/$F$18 -> 0 | G43: =G23/$G$18 -> 153953 | H43: =H23/$H$18 -> 113263 | I43: =I23/$I$18 -> 1522567 | J43: =J23/$J$18 -> 0 | K43: =K23/$K$18 -> 1717998.6 | L43: =L23/$L$18 -> 0 | M43: =M23/$M$18 -> 0 | N43: =N23/$N$18 -> 0 | O43: =O23/$O$18 -> 752398.2 | P43: =P23/$P$18 -> 0 | Q43: =Q23/$Q$18 -> 1100162 | R43: =R23/$R$18 -> 0 | S43: =S23/$S$18 -> 0 | T43: =T23/$T$18 -> 0 | U43: =U23/$U$18 -> 0 | V43: =V23/$V$18 -> 0 | W43: =W23/$W$18 -> 0 | X43: =X23/$X$18 -> 275660.67 | Y43: =Y23/$Y$18 -> 0 | Z43: =Z23/$Z$18 -> 0 | AA43: =AA23/$AA$18 -> 480773 | AB43: =AB23/$AB$18 -> 41095 | AC43: =AC23/$AC$18 -> 0 | AD43: =AD23/$AD$18 -> 0 | AE43: =AE23/$AE$18 -> 0 | AF43: =AF23/$AF$18 -> 0 | AG43: =AG23/$AG$18 -> 278882.97 | AH43: =AH23/$AH$18 -> 0 | AI43: =AI23/$AI$18 -> 900822.65 | AJ43: =AJ23/$AJ$18 -> 2272 | AK43: =AK23/$AK$18 -> 0 | AL43: =AL23/$AL$18 -> 150164 | AM43: =AM23/$AM$18 -> 0 | AN43: =AN23/$AN$18 -> 0 | AO43: =AO23/$AO$18 -> 0 | AP43: =AP23/$AP$18 -> 0 | AQ43: =AQ23/$AQ$18 -> 438942 | AR43: =AR23/$AR$18 -> 920820.9 | AS43: =AS23/$AS$18 -> 0 | AT43: =AT23/$AT$18 -> 0 | AU43: =AU23/$AU$18 -> 156145 | AV43: =AV23/$AV$18 -> 104203.98 | AW43: =AW23/$AW$18 -> 0 | AX43: =AX23/$AX$18 -> 457446.08 | AY43: =AY23/$AY$18 -> 34263.831 | AZ43: =AZ23/$AZ$18 -> 0 | BA43: =BA23/$BA$18 -> 0 | BB43: =BB23/$BB$18 -> 96389 | BC43: =BC23/$BC$18 -> 0 | BD43: =BD23/$BD$18 -> 0 | BE43: =BE23/$BE$18 -> 0 | BF43: =BF23/$BF$18 -> 148926.62 | BG43: =BG23/$BG$18 -> 0 | BH43: =BH23/$BH$18 -> 116881.53 | BI43: =BI23/$BI$18 -> 27699.328 | BJ43: =BJ23/$BJ$18 -> 149.34206 | BK43: =BK23/$BK$18 -> 0 | BL43: =BL23/$BL$18 -> 42509.466 | BM43: =BM23/$BM$18 -> 0 | BN43: =BN23/$BN$18 -> 0 | BO43: =BO23/$BO$18 -> 0 | BP43: =BP23/$BP$18 -> 1131.9715 | BQ43: =BQ23/$BQ$18 -> 71177 | BR43: =BR23/$BR$18 -> 0 | BS43: =BS23/$BS$18 -> 85093.903 | BV43: =BV23/$BV$18 -> 0 | BW43: =BW23/$BW$18 -> 76298 | BX43: =BX23/$BX$18 -> 0 | BY43: =BY23/$BY$18 -> 0 | BZ43: =BZ23/$BZ$18 -> 39678.875 | CA43: =CA23/$CA$18 -> 97649 | CC43: =CC23/$CC$18 -> 0 | CD43: =CD23/$CD$18 -> 68174 | CE43: =CE23/$CE$18 -> 0 | CF43: =CF23/$CF$18 -> 3762.5011 | CG43: =CG23/$CG$18 -> 113670 | CH43: =CH23/$CH$18 -> 0 | CI43: =CI23/$CI$18 -> 9515.4053 | CJ43: =CJ23/$CJ$18 -> 0 | CK43: =CK23/$CK$18 -> 0 | CL43: =CL23/$CL$18 -> 13274.122 | CM43: =CM23/$CM$18 -> 8485.7551 | CN43: =CN23/$CN$18 -> 25.906971 | CO43: =CO23/$CO$18 -> 43698.141 | CQ43: =SUM(B43:CO43) -> 17734532
A44: Institutions | B44: =B24/$B$18 -> 593590 | C44: =C24/$C$18 -> 378352.41 | D44: =D24/$D$18 -> 103187 | E44: =E24/$E$18 -> 5796 | F44: =F24/$F$18 -> 304397.24 | G44: =G24/$G$18 -> 11303 | H44: =H24/$H$18 -> 63765 | I44: =I24/$I$18 -> 442448 | J44: =J24/$J$18 -> 30094.831 | K44: =K24/$K$18 -> 46760.896 | L44: =L24/$L$18 -> 115759.11 | M44: =M24/$M$18 -> 280251 | N44: =N24/$N$18 -> 210608 | O44: =O24/$O$18 -> 444836.59 | P44: =P24/$P$18 -> 201066.64 | Q44: =Q24/$Q$18 -> 60378 | R44: =R24/$R$18 -> 15262.717 | S44: =S24/$S$18 -> 117241.54 | T44: =T24/$T$18 -> 98200.326 | U44: =U24/$U$18 -> 293641.13 | V44: =V24/$V$18 -> 173792.87 | W44: =W24/$W$18 -> 0 | X44: =X24/$X$18 -> 26788.617 | Y44: =Y24/$Y$18 -> 93151.634 | Z44: =Z24/$Z$18 -> 98572.42 | AA44: =AA24/$AA$18 -> 145908 | AB44: =AB24/$AB$18 -> 70448 | AC44: =AC24/$AC$18 -> 103722.95 | AD44: =AD24/$AD$18 -> 39406.337 | AE44: =AE24/$AE$18 -> 25212.614 | AF44: =AF24/$AF$18 -> 333141.66 | AG44: =AG24/$AG$18 -> 168490.69 | AH44: =AH24/$AH$18 -> 292487 | AI44: =AI24/$AI$18 -> 100988.21 | AJ44: =AJ24/$AJ$18 -> 53759 | AK44: =AK24/$AK$18 -> 66758 | AL44: =AL24/$AL$18 -> 8111 | AM44: =AM24/$AM$18 -> 0 | AN44: =AN24/$AN$18 -> 70302.274 | AO44: =AO24/$AO$18 -> 37331 | AP44: =AP24/$AP$18 -> 4125.8962 | AQ44: =AQ24/$AQ$18 -> 24132 | AR44: =AR24/$AR$18 -> 5073.5582 | AS44: =AS24/$AS$18 -> 330157.6 | AT44: =AT24/$AT$18 -> 46154.549 | AU44: =AU24/$AU$18 -> 4586 | AV44: =AV24/$AV$18 -> 69470.023 | AW44: =AW24/$AW$18 -> 0 | AX44: =AX24/$AX$18 -> 4048.6372 | AY44: =AY24/$AY$18 -> 9328.3729 | AZ44: =AZ24/$AZ$18 -> 0 | BA44: =BA24/$BA$18 -> 0 | BB44: =BB24/$BB$18 -> 117774 | BC44: =BC24/$BC$18 -> 662492 | BD44: =BD24/$BD$18 -> 19648.935 | BE44: =BE24/$BE$18 -> 31470.163 | BF44: =BF24/$BF$18 -> 35793.915 | BG44: =BG24/$BG$18 -> 4822.6946 | BH44: =BH24/$BH$18 -> 46729.18 | BI44: =BI24/$BI$18 -> 73273.064 | BJ44: =BJ24/$BJ$18 -> 5003.5261 | BK44: =BK24/$BK$18 -> 16502.727 | BL44: =BL24/$BL$18 -> 146157.22 | BM44: =BM24/$BM$18 -> 124928.36 | BN44: =BN24/$BN$18 -> 1408.7264 | BO44: =BO24/$BO$18 -> 0 | BP44: =BP24/$BP$18 -> 132.40273 | BQ44: =BQ24/$BQ$18 -> 33118 | BR44: =BR24/$BR$18 -> 0 | BS44: =BS24/$BS$18 -> 126663.75 | BV44: =BV24/$BV$18 -> 9176.0706 | BW44: =BW24/$BW$18 -> 36282 | BX44: =BX24/$BX$18 -> 450 | BY44: =BY24/$BY$18 -> 13702 | BZ44: =BZ24/$BZ$18 -> 87785.846 | CA44: =CA24/$CA$18 -> 4631 | CC44: =CC24/$CC$18 -> 745.50924 | CD44: =CD24/$CD$18 -> 3821 | CE44: =CE24/$CE$18 -> 91818.025 | CF44: =CF24/$CF$18 -> 5596.7954 | CG44: =CG24/$CG$18 -> 0 | CH44: =CH24/$CH$18 -> 0.055886576 | CI44: =CI24/$CI$18 -> 4757.1741 | CJ44: =CJ24/$CJ$18 -> 0 | CK44: =CK24/$CK$18 -> 0 | CL44: =CL24/$CL$18 -> 29036.448 | CM44: =CM24/$CM$18 -> 5480.5304 | CN44: =CN24/$CN$18 -> 58.290686 | CO44: =CO24/$CO$18 -> 13261.785 | CQ44: =SUM(B44:CO44) -> 7974909.5
A45: Schools | B45: =B25/$B$18 -> 57269 | C45: =C25/$C$18 -> 61434.833 | D45: =D25/$D$18 -> 68792 | E45: =E25/$E$18 -> 5925 | F45: =F25/$F$18 -> 52840.469 | G45: =G25/$G$18 -> 387690 | H45: =H25/$H$18 -> 82334 | I45: =I25/$I$18 -> 323438 | J45: =J25/$J$18 -> 178927.8 | K45: =K25/$K$18 -> 52703.625 | L45: =L25/$L$18 -> 67841.815 | M45: =M25/$M$18 -> 268821 | N45: =N25/$N$18 -> 291433 | O45: =O25/$O$18 -> 81211.532 | P45: =P25/$P$18 -> 99469.607 | Q45: =Q25/$Q$18 -> 177096 | R45: =R25/$R$18 -> 82118.525 | S45: =S25/$S$18 -> 60008.703 | T45: =T25/$T$18 -> 252263.88 | U45: =U25/$U$18 -> 111283.86 | V45: =V25/$V$18 -> 0 | W45: =W25/$W$18 -> 33763 | X45: =X25/$X$18 -> 14478.07 | Y45: =Y25/$Y$18 -> 48620.441 | Z45: =Z25/$Z$18 -> 88518.302 | AA45: =AA25/$AA$18 -> 52326 | AB45: =AB25/$AB$18 -> 105672 | AC45: =AC25/$AC$18 -> 44626.658 | AD45: =AD25/$AD$18 -> 59111.041 | AE45: =AE25/$AE$18 -> 40409.955 | AF45: =AF25/$AF$18 -> 343538.45 | AG45: =AG25/$AG$18 -> 72209.972 | AH45: =AH25/$AH$18 -> 146244 | AI45: =AI25/$AI$18 -> 25846.958 | AJ45: =AJ25/$AJ$18 -> 46177 | AK45: =AK25/$AK$18 -> 48727 | AL45: =AL25/$AL$18 -> 3228 | AM45: =AM25/$AM$18 -> 168694.62 | AN45: =AN25/$AN$18 -> 144881.52 | AO45: =AO25/$AO$18 -> 0 | AP45: =AP25/$AP$18 -> 25038.002 | AQ45: =AQ25/$AQ$18 -> 6810 | AR45: =AR25/$AR$18 -> 18617.199 | AS45: =AS25/$AS$18 -> 0 | AT45: =AT25/$AT$18 -> 0 | AU45: =AU25/$AU$18 -> 24054 | AV45: =AV25/$AV$18 -> 62522.809 | AW45: =AW25/$AW$18 -> 45792 | AX45: =AX25/$AX$18 -> 3036.1876 | AY45: =AY25/$AY$18 -> 60514.829 | AZ45: =AZ25/$AZ$18 -> 0 | BA45: =BA25/$BA$18 -> 197272 | BB45: =BB25/$BB$18 -> 69198 | BC45: =BC25/$BC$18 -> 65599 | BD45: =BD25/$BD$18 -> 9081.1997 | BE45: =BE25/$BE$18 -> 23583.506 | BF45: =BF25/$BF$18 -> 24782.475 | BG45: =BG25/$BG$18 -> 41328.74 | BH45: =BH25/$BH$18 -> 84631.155 | BI45: =BI25/$BI$18 -> 55563.965 | BJ45: =BJ25/$BJ$18 -> 7467.9399 | BK45: =BK25/$BK$18 -> 7804.2352 | BL45: =BL25/$BL$18 -> 34589.219 | BM45: =BM25/$BM$18 -> 178469.8 | BN45: =BN25/$BN$18 -> 2743.4009 | BO45: =BO25/$BO$18 -> 38987.815 | BP45: =BP25/$BP$18 -> 0 | BQ45: =BQ25/$BQ$18 -> 28319 | BR45: =BR25/$BR$18 -> 0 | BS45: =BS25/$BS$18 -> 109115.32 | BV45: =BV25/$BV$18 -> 12579.778 | BW45: =BW25/$BW$18 -> 16342 | BX45: =BX25/$BX$18 -> 8872 | BY45: =BY25/$BY$18 -> 15493 | BZ45: =BZ25/$BZ$18 -> 48470.536 | CA45: =CA25/$CA$18 -> 3272 | CC45: =CC25/$CC$18 -> 4024.3139 | CD45: =CD25/$CD$18 -> 13177 | CE45: =CE25/$CE$18 -> 45423.264 | CF45: =CF25/$CF$18 -> 3912.3618 | CG45: =CG25/$CG$18 -> 51019.602 | CH45: =CH25/$CH$18 -> 0.027647629 | CI45: =CI25/$CI$18 -> 1902.8696 | CJ45: =CJ25/$CJ$18 -> 6450 | CK45: =CK25/$CK$18 -> 44086.293 | CL45: =CL25/$CL$18 -> 14933.261 | CM45: =CM25/$CM$18 -> 5530.903 | CN45: =CN25/$CN$18 -> 71.247174 | CO45: =CO25/$CO$18 -> 4755.9845 | CQ45: =SUM(B45:CO45) -> 5775213.9
A46: Commercial customers | B46: =B26/$B$18 -> 2911995 | C46: =C26/$C$18 -> 1116641.6 | D46: =D26/$D$18 -> 515935 | E46: =E26/$E$18 -> 174942 | F46: =F26/$F$18 -> 1852791.8 | G46: =G26/$G$18 -> 448084 | H46: =H26/$H$18 -> 1222657 | I46: =I26/$I$18 -> 556897 | J46: =J26/$J$18 -> 586127.42 | K46: =K26/$K$18 -> 0 | L46: =L26/$L$18 -> 7981.2738 | M46: =M26/$M$18 -> 160088 | N46: =N26/$N$18 -> 843121 | O46: =O26/$O$18 -> 556180.16 | P46: =P26/$P$18 -> 179774.55 | Q46: =Q26/$Q$18 -> 79049 | R46: =R26/$R$18 -> 163395.77 | S46: =S26/$S$18 -> 585752.97 | T46: =T26/$T$18 -> 148138.15 | U46: =U26/$U$18 -> 364743.84 | V46: =V26/$V$18 -> 191472.73 | W46: =W26/$W$18 -> 479351 | X46: =X26/$X$18 -> 253064.16 | Y46: =Y26/$Y$18 -> 93150.704 | Z46: =Z26/$Z$18 -> 352899.26 | AA46: =AA26/$AA$18 -> 114935 | AB46: =AB26/$AB$18 -> 123285 | AC46: =AC26/$AC$18 -> 358836.27 | AD46: =AD26/$AD$18 -> 69819.284 | AE46: =AE26/$AE$18 -> 112387.97 | AF46: =AF26/$AF$18 -> 231994.61 | AG46: =AG26/$AG$18 -> 87883.076 | AH46: =AH26/$AH$18 -> 277862 | AI46: =AI26/$AI$18 -> 100923.16 | AJ46: =AJ26/$AJ$18 -> 24459 | AK46: =AK26/$AK$18 -> 136918 | AL46: =AL26/$AL$18 -> 288803 | AM46: =AM26/$AM$18 -> 691027.31 | AN46: =AN26/$AN$18 -> 142720.46 | AO46: =AO26/$AO$18 -> 95427 | AP46: =AP26/$AP$18 -> 3849.5757 | AQ46: =AQ26/$AQ$18 -> 57202 | AR46: =AR26/$AR$18 -> 64813.789 | AS46: =AS26/$AS$18 -> 88042.367 | AT46: =AT26/$AT$18 -> 69753.09 | AU46: =AU26/$AU$18 -> 220577 | AV46: =AV26/$AV$18 -> 138938.99 | AW46: =AW26/$AW$18 -> 0 | AX46: =AX26/$AX$18 -> 179132.75 | AY46: =AY26/$AY$18 -> 6512.2956 | AZ46: =AZ26/$AZ$18 -> 0 | BA46: =BA26/$BA$18 -> 0 | BB46: =BB26/$BB$18 -> 125150 | BC46: =BC26/$BC$18 -> 42397 | BD46: =BD26/$BD$18 -> 14484.812 | BE46: =BE26/$BE$18 -> 0 | BF46: =BF26/$BF$18 -> 71316.99 | BG46: =BG26/$BG$18 -> 0 | BH46: =BH26/$BH$18 -> 26221.632 | BI46: =BI26/$BI$18 -> 120344.51 | BJ46: =BJ26/$BJ$18 -> 2240.382 | BK46: =BK26/$BK$18 -> 9386.6183 | BL46: =BL26/$BL$18 -> 219234.74 | BM46: =BM26/$BM$18 -> 51756.092 | BN46: =BN26/$BN$18 -> 703.02839 | BO46: =BO26/$BO$18 -> 40383.056 | BP46: =BP26/$BP$18 -> 893.11687 | BQ46: =BQ26/$BQ$18 -> 18825 | BR46: =BR26/$BR$18 -> 0 | BS46: =BS26/$BS$18 -> 102912.08 | BV46: =BV26/$BV$18 -> 52498.415 | BW46: =BW26/$BW$18 -> 32013 | BX46: =BX26/$BX$18 -> 270 | BY46: =BY26/$BY$18 -> 7872 | BZ46: =BZ26/$BZ$18 -> 61830.47 | CA46: =CA26/$CA$18 -> 9473 | CC46: =CC26/$CC$18 -> 15799.291 | CD46: =CD26/$CD$18 -> 0 | CE46: =CE26/$CE$18 -> 82094.891 | CF46: =CF26/$CF$18 -> 0 | CG46: =CG26/$CG$18 -> 0 | CH46: =CH26/$CH$18 -> 0.049968428 | CI46: =CI26/$CI$18 -> 9515.4053 | CJ46: =CJ26/$CJ$18 -> 689 | CK46: =CK26/$CK$18 -> 3010.8362 | CL46: =CL26/$CL$18 -> 11614.983 | CM46: =CM26/$CM$18 -> 5254.8615 | CN46: =CN26/$CN$18 -> 38.860457 | CO46: =CO26/$CO$18 -> 10446.605 | CQ46: =SUM(B46:CO46) -> 18679007
A47: Industries | B47: =B27/$B$18 -> 187667 | C47: =C27/$C$18 -> 0 | D47: =D27/$D$18 -> 343957 | E47: =E27/$E$18 -> 0 | F47: =F27/$F$18 -> 12300.154 | G47: =G27/$G$18 -> 0 | H47: =H27/$H$18 -> 416011 | I47: =I27/$I$18 -> 0 | J47: =J27/$J$18 -> 0 | K47: =K27/$K$18 -> 661727.39 | L47: =L27/$L$18 -> 0 | M47: =M27/$M$18 -> 295771 | N47: =N27/$N$18 -> 0 | O47: =O27/$O$18 -> 3620.0623 | P47: =P27/$P$18 -> 0 | Q47: =Q27/$Q$18 -> 0 | R47: =R27/$R$18 -> 0 | S47: =S27/$S$18 -> 22096.312 | T47: =T27/$T$18 -> 0 | U47: =U27/$U$18 -> 27660.367 | V47: =V27/$V$18 -> 0 | W47: =W27/$W$18 -> 0 | X47: =X27/$X$18 -> 22555.191 | Y47: =Y27/$Y$18 -> 48620.441 | Z47: =Z27/$Z$18 -> 112415.96 | AA47: =AA27/$AA$18 -> 99 | AB47: =AB27/$AB$18 -> 29353 | AC47: =AC27/$AC$18 -> 0 | AD47: =AD27/$AD$18 -> 46546.701 | AE47: =AE27/$AE$18 -> 80.231071 | AF47: =AF27/$AF$18 -> 231410.09 | AG47: =AG27/$AG$18 -> 0 | AH47: =AH27/$AH$18 -> 0 | AI47: =AI27/$AI$18 -> 0 | AJ47: =AJ27/$AJ$18 -> 357 | AK47: =AK27/$AK$18 -> 0 | AL47: =AL27/$AL$18 -> 113516 | AM47: =AM27/$AM$18 -> 0 | AN47: =AN27/$AN$18 -> 1806.2614 | AO47: =AO27/$AO$18 -> 0 | AP47: =AP27/$AP$18 -> 314.14387 | AQ47: =AQ27/$AQ$18 -> 0 | AR47: =AR27/$AR$18 -> 0 | AS47: =AS27/$AS$18 -> 0 | AT47: =AT27/$AT$18 -> 0 | AU47: =AU27/$AU$18 -> 0 | AV47: =AV27/$AV$18 -> 0 | AW47: =AW27/$AW$18 -> 0 | AX47: =AX27/$AX$18 -> 0 | AY47: =AY27/$AY$18 -> 65053.815 | AZ47: =AZ27/$AZ$18 -> 0 | BA47: =BA27/$BA$18 -> 0 | BB47: =BB27/$BB$18 -> 102433 | BC47: =BC27/$BC$18 -> 0 | BD47: =BD27/$BD$18 -> 421.62436 | BE47: =BE27/$BE$18 -> 0 | BF47: =BF27/$BF$18 -> 0 | BG47: =BG27/$BG$18 -> 0 | BH47: =BH27/$BH$18 -> 0 | BI47: =BI27/$BI$18 -> 0 | BJ47: =BJ27/$BJ$18 -> 0 | BK47: =BK27/$BK$18 -> 0 | BL47: =BL27/$BL$18 -> 17905.033 | BM47: =BM27/$BM$18 -> 0 | BN47: =BN27/$BN$18 -> 0 | BO47: =BO27/$BO$18 -> 0 | BP47: =BP27/$BP$18 -> 0 | BQ47: =BQ27/$BQ$18 -> 78109 | BR47: =BR27/$BR$18 -> 0 | BS47: =BS27/$BS$18 -> 0 | BV47: =BV27/$BV$18 -> 0 | BW47: =BW27/$BW$18 -> 0 | BX47: =BX27/$BX$18 -> 0 | BY47: =BY27/$BY$18 -> 0 | BZ47: =BZ27/$BZ$18 -> 0 | CA47: =CA27/$CA$18 -> 0 | CC47: =CC27/$CC$18 -> 0 | CD47: =CD27/$CD$18 -> 0 | CE47: =CE27/$CE$18 -> 0 | CF47: =CF27/$CF$18 -> 0 | CG47: =CG27/$CG$18 -> 0 | CH47: =CH27/$CH$18 -> 0 | CI47: =CI27/$CI$18 -> 1656.5537 | CJ47: =CJ27/$CJ$18 -> 0 | CK47: =CK27/$CK$18 -> 0 | CL47: =CL27/$CL$18 -> 0 | CM47: =CM27/$CM$18 -> 0 | CN47: =CN27/$CN$18 -> 0 | CO47: =CO27/$CO$18 -> 8.9982506 | CQ47: =SUM(B47:CO47) -> 2843472.3
A48: Kiosks | B48: =B28/$B$18 -> 1646099 | C48: =C28/$C$18 -> 473514.42 | D48: =D28/$D$18 -> 608788 | E48: =E28/$E$18 -> 2892 | F48: =F28/$F$18 -> 436572.89 | G48: =G28/$G$18 -> 68237 | H48: =H28/$H$18 -> 5160 | I48: =I28/$I$18 -> 10307 | J48: =J28/$J$18 -> 14419.867 | K48: =K28/$K$18 -> 62437.938 | L48: =L28/$L$18 -> 8433.9017 | M48: =M28/$M$18 -> 234512 | N48: =N28/$N$18 -> 39117 | O48: =O28/$O$18 -> 34344.24 | P48: =P28/$P$18 -> 556.03084 | Q48: =Q28/$Q$18 -> 214495 | R48: =R28/$R$18 -> 7698.1082 | S48: =S28/$S$18 -> 262181.2 | T48: =T28/$T$18 -> 4586.5269 | U48: =U28/$U$18 -> 38392.299 | V48: =V28/$V$18 -> 0 | W48: =W28/$W$18 -> 2611 | X48: =X28/$X$18 -> 1946.4154 | Y48: =Y28/$Y$18 -> 0 | Z48: =Z28/$Z$18 -> 3714.386 | AA48: =AA28/$AA$18 -> 450000 | AB48: =AB28/$AB$18 -> 0 | AC48: =AC28/$AC$18 -> 40262.058 | AD48: =AD28/$AD$18 -> 148673.41 | AE48: =AE28/$AE$18 -> 8023.1071 | AF48: =AF28/$AF$18 -> 0 | AG48: =AG28/$AG$18 -> 303535.76 | AH48: =AH28/$AH$18 -> 14623 | AI48: =AI28/$AI$18 -> 0 | AJ48: =AJ28/$AJ$18 -> 351867 | AK48: =AK28/$AK$18 -> 13043 | AL48: =AL28/$AL$18 -> 31384 | AM48: =AM28/$AM$18 -> 46057.246 | AN48: =AN28/$AN$18 -> 180.62614 | AO48: =AO28/$AO$18 -> 7924 | AP48: =AP28/$AP$18 -> 15204.983 | AQ48: =AQ28/$AQ$18 -> 8308 | AR48: =AR28/$AR$18 -> 24012.076 | AS48: =AS28/$AS$18 -> 21928.336 | AT48: =AT28/$AT$18 -> 0 | AU48: =AU28/$AU$18 -> 65539 | AV48: =AV28/$AV$18 -> 6947.2139 | AW48: =AW28/$AW$18 -> 0 | AX48: =AX28/$AX$18 -> 2023.7381 | AY48: =AY28/$AY$18 -> 2859.0566 | AZ48: =AZ28/$AZ$18 -> 0 | BA48: =BA28/$BA$18 -> 0 | BB48: =BB28/$BB$18 -> 18634 | BC48: =BC28/$BC$18 -> 5297 | BD48: =BD28/$BD$18 -> 7063.7581 | BE48: =BE28/$BE$18 -> 5566.2447 | BF48: =BF28/$BF$18 -> 158027.36 | BG48: =BG28/$BG$18 -> 2072.4091 | BH48: =BH28/$BH$18 -> 8004.8506 | BI48: =BI28/$BI$18 -> 32374.292 | BJ48: =BJ28/$BJ$18 -> 74.650108 | BK48: =BK28/$BK$18 -> 1899.2699 | BL48: =BL28/$BL$18 -> 5967.981 | BM48: =BM28/$BM$18 -> 1784.3454 | BN48: =BN28/$BN$18 -> 197.08473 | BO48: =BO28/$BO$18 -> 1818.3647 | BP48: =BP28/$BP$18 -> 18.748575 | BQ48: =BQ28/$BQ$18 -> 138622 | BR48: =BR28/$BR$18 -> 0 | BS48: =BS28/$BS$18 -> 3445.6951 | BV48: =BV28/$BV$18 -> 11084.703 | BW48: =BW28/$BW$18 -> 6403 | BX48: =BX28/$BX$18 -> 720 | BY48: =BY28/$BY$18 -> 0 | BZ48: =BZ28/$BZ$18 -> 21907.303 | CA48: =CA28/$CA$18 -> 115 | CC48: =CC28/$CC$18 -> 2980.8403 | CD48: =CD28/$CD$18 -> 11566 | CE48: =CE28/$CE$18 -> 253.9141 | CF48: =CF28/$CF$18 -> 15230.836 | CG48: =CG28/$CG$18 -> 0 | CH48: =CH28/$CH$18 -> 0.00015454906 | CI48: =CI28/$CI$18 -> 951.43481 | CJ48: =CJ28/$CJ$18 -> 0 | CK48: =CK28/$CK$18 -> 0 | CL48: =CL28/$CL$18 -> 1659.139 | CM48: =CM28/$CM$18 -> 8969.3313 | CN48: =CN28/$CN$18 -> 9.9628339 | CO48: =CO28/$CO$18 -> 40901.139 | CQ48: =SUM(B48:CO48) -> 6257032.5
A49: Bulk | B49: =B29/$B$18 -> 3116629 | C49: =C29/$C$18 -> 0 | D49: =D29/$D$18 -> 93916 | E49: =E29/$E$18 -> 0 | F49: =F29/$F$18 -> 727563.56 | G49: =G29/$G$18 -> 7276 | H49: =H29/$H$18 -> 0 | I49: =I29/$I$18 -> 0 | J49: =J29/$J$18 -> 0 | K49: =K29/$K$18 -> 0 | L49: =L29/$L$18 -> 0 | M49: =M29/$M$18 -> 174163 | N49: =N29/$N$18 -> 0 | O49: =O29/$O$18 -> 1655308.3 | P49: =P29/$P$18 -> 0 | Q49: =Q29/$Q$18 -> 0 | R49: =R29/$R$18 -> 108.18092 | S49: =S29/$S$18 -> 1479.6025 | T49: =T29/$T$18 -> 0 | U49: =U29/$U$18 -> 5277.4612 | V49: =V29/$V$18 -> 1497.4425 | W49: =W29/$W$18 -> 0 | X49: =X29/$X$18 -> 0 | Y49: =Y29/$Y$18 -> 118587.26 | Z49: =Z29/$Z$18 -> 230867.56 | AA49: =AA29/$AA$18 -> 0 | AB49: =AB29/$AB$18 -> 0 | AC49: =AC29/$AC$18 -> 0 | AD49: =AD29/$AD$18 -> 0 | AE49: =AE29/$AE$18 -> 0 | AF49: =AF29/$AF$18 -> 0 | AG49: =AG29/$AG$18 -> 64094.29 | AH49: =AH29/$AH$18 -> 0 | AI49: =AI29/$AI$18 -> 0 | AJ49: =AJ29/$AJ$18 -> 22053 | AK49: =AK29/$AK$18 -> 65459 | AL49: =AL29/$AL$18 -> 0 | AM49: =AM29/$AM$18 -> 0 | AN49: =AN29/$AN$18 -> 0 | AO49: =AO29/$AO$18 -> 0 | AP49: =AP29/$AP$18 -> 0 | AQ49: =AQ29/$AQ$18 -> 192232 | AR49: =AR29/$AR$18 -> 0 | AS49: =AS29/$AS$18 -> 44102.166 | AT49: =AT29/$AT$18 -> 0 | AU49: =AU29/$AU$18 -> 6762 | AV49: =AV29/$AV$18 -> 0 | AW49: =AW29/$AW$18 -> 0 | AX49: =AX29/$AX$18 -> 30361.876 | AY49: =AY29/$AY$18 -> 11953.846 | AZ49: =AZ29/$AZ$18 -> 0 | BA49: =BA29/$BA$18 -> 147954 | BB49: =BB29/$BB$18 -> 0 | BC49: =BC29/$BC$18 -> 0 | BD49: =BD29/$BD$18 -> 0 | BE49: =BE29/$BE$18 -> 0 | BF49: =BF29/$BF$18 -> 0 | BG49: =BG29/$BG$18 -> 0 | BH49: =BH29/$BH$18 -> 0 | BI49: =BI29/$BI$18 -> 35230.847 | BJ49: =BJ29/$BJ$18 -> 0 | BK49: =BK29/$BK$18 -> 0 | BL49: =BL29/$BL$18 -> 0 | BM49: =BM29/$BM$18 -> 0 | BN49: =BN29/$BN$18 -> 0 | BO49: =BO29/$BO$18 -> 0 | BP49: =BP29/$BP$18 -> 0 | BQ49: =BQ29/$BQ$18 -> 0 | BR49: =BR29/$BR$18 -> 0 | BS49: =BS29/$BS$18 -> 0 | BV49: =BV29/$BV$18 -> 1098.9445 | BW49: =BW29/$BW$18 -> 0 | BX49: =BX29/$BX$18 -> 0 | BY49: =BY29/$BY$18 -> 20403 | BZ49: =BZ29/$BZ$18 -> 0 | CA49: =CA29/$CA$18 -> 0 | CC49: =CC29/$CC$18 -> 0 | CD49: =CD29/$CD$18 -> 16064 | CE49: =CE29/$CE$18 -> 0 | CF49: =CF29/$CF$18 -> 0 | CG49: =CG29/$CG$18 -> 0 | CH49: =CH29/$CH$18 -> 0 | CI49: =CI29/$CI$18 -> 0 | CJ49: =CJ29/$CJ$18 -> 1211 | CK49: =CK29/$CK$18 -> 0 | CL49: =CL29/$CL$18 -> 0 | CM49: =CM29/$CM$18 -> 0 | CN49: =CN29/$CN$18 -> 0 | CO49: =CO29/$CO$18 -> 0 | CQ49: =SUM(B49:CO49) -> 6791653.3
A50: Others | B50: =B30/$B$18 -> 530531 | C50: =C30/$C$18 -> 0 | D50: =D30/$D$18 -> 0 | E50: =E30/$E$18 -> 0 | F50: =F30/$F$18 -> 331814.87 | G50: =G30/$G$18 -> 0 | H50: =H30/$H$18 -> 0 | I50: =I30/$I$18 -> 0 | J50: =J30/$J$18 -> 0 | K50: =K30/$K$18 -> 0 | L50: =L30/$L$18 -> 0 | M50: =M30/$M$18 -> 785 | N50: =N30/$N$18 -> 0 | O50: =O30/$O$18 -> 0 | P50: =P30/$P$18 -> 0 | Q50: =Q30/$Q$18 -> 0 | R50: =R30/$R$18 -> 0 | S50: =S30/$S$18 -> 0 | T50: =T30/$T$18 -> 0 | U50: =U30/$U$18 -> 0 | V50: =V30/$V$18 -> 0 | W50: =W30/$W$18 -> 0 | X50: =X30/$X$18 -> 0 | Y50: =Y30/$Y$18 -> 0 | Z50: =Z30/$Z$18 -> 21386.846 | AA50: =AA30/$AA$18 -> 0 | AB50: =AB30/$AB$18 -> 0 | AC50: =AC30/$AC$18 -> 0 | AD50: =AD30/$AD$18 -> 0 | AE50: =AE30/$AE$18 -> 908427.76 | AF50: =AF30/$AF$18 -> 0 | AG50: =AG30/$AG$18 -> 0 | AH50: =AH30/$AH$18 -> 0 | AI50: =AI30/$AI$18 -> 0 | AJ50: =AJ30/$AJ$18 -> 0 | AK50: =AK30/$AK$18 -> 0 | AL50: =AL30/$AL$18 -> 0 | AM50: =AM30/$AM$18 -> 0 | AN50: =AN30/$AN$18 -> 0 | AO50: =AO30/$AO$18 -> 0 | AP50: =AP30/$AP$18 -> 0 | AQ50: =AQ30/$AQ$18 -> 0 | AR50: =AR30/$AR$18 -> 0 | AS50: =AS30/$AS$18 -> 0 | AT50: =AT30/$AT$18 -> 0 | AU50: =AU30/$AU$18 -> 0 | AV50: =AV30/$AV$18 -> 0 | AW50: =AW30/$AW$18 -> 0 | AX50: =AX30/$AX$18 -> 0 | AY50: =AY30/$AY$18 -> 0 | AZ50: =AZ30/$AZ$18 -> 0 | BA50: =BA30/$BA$18 -> 0 | BB50: =BB30/$BB$18 -> 0 | BC50: =BC30/$BC$18 -> 0 | BD50: =BD30/$BD$18 -> 26.351522 | BE50: =BE30/$BE$18 -> 0 | BF50: =BF30/$BF$18 -> 105507.43 | BG50: =BG30/$BG$18 -> 0 | BH50: =BH30/$BH$18 -> 0 | BI50: =BI30/$BI$18 -> 18745.041 | BJ50: =BJ30/$BJ$18 -> 0 | BK50: =BK30/$BK$18 -> 0 | BL50: =BL30/$BL$18 -> 0 | BM50: =BM30/$BM$18 -> 0 | BN50: =BN30/$BN$18 -> 0 | BO50: =BO30/$BO$18 -> 0 | BP50: =BP30/$BP$18 -> 0 | BQ50: =BQ30/$BQ$18 -> 18126 | BR50: =BR30/$BR$18 -> 0 | BS50: =BS30/$BS$18 -> 0 | BV50: =BV30/$BV$18 -> 0 | BW50: =BW30/$BW$18 -> 0 | BX50: =BX30/$BX$18 -> 0 | BY50: =BY30/$BY$18 -> 0 | BZ50: =BZ30/$BZ$18 -> 0 | CA50: =CA30/$CA$18 -> 0 | CC50: =CC30/$CC$18 -> 0 | CD50: =CD30/$CD$18 -> 16064 | CE50: =CE30/$CE$18 -> 0 | CF50: =CF30/$CF$18 -> 0 | CG50: =CG30/$CG$18 -> 0 | CH50: =CH30/$CH$18 -> 0 | CI50: =CI30/$CI$18 -> 0 | CJ50: =CJ30/$CJ$18 -> 0 | CK50: =CK30/$CK$18 -> 0 | CL50: =CL30/$CL$18 -> 0 | CM50: =CM30/$CM$18 -> 0 | CN50: =CN30/$CN$18 -> 0 | CO50: =CO30/$CO$18 -> 0 | CQ50: =SUM(B50:CO50) -> 1951414.3
A51: Total Sold | B51: =SUM(B42:B50) -> 24712581 | C51: =SUM(C42:C50) -> 9390958 | D51: =SUM(D42:D50) -> 5319630 | E51: =SUM(E42:E50) -> 4160045 | F51: =SUM(F42:F50) -> 7196567 | G51: =SUM(G42:G50) -> 3934362 | H51: =SUM(H42:H50) -> 4973283 | I51: =SUM(I42:I50) -> 4566309 | ... CO51: =SUM(CO42:CO50) -> 144489.96 | CQ51: =SUM(B51:CO51) -> 1.6598189e+08
A52: Total Billed | B52: =B10 -> 89354658 | C52: =C10 -> 9390958 | D52: =D10 -> 5857951 | E52: =E10 -> 8021159 | F52: =F10 -> 7196567 | G52: =G10 -> 4029508 | H52: =H10 -> 10035329 | I52: =I10 -> 6518879 | ... CO52: =CO10 -> 91707
A53: Difference | B53: =B52-B51 -> 64642077 | C53: =C52-C51 -> 0 | D53: =D52-D51 -> 538321 | E53: =E52-E51 -> 3861114 | F53: =F52-F51 -> 0 | G53: =G52-G51 -> 95146 | H53: =H52-H51 -> 5062046 | I53: =I52-I51 -> 1952570 | ... CO53: =CO52-CO51 -> -52782.962 | CQ53: =SUM(B53:CO53) -> 88279652
A55: Non-Revenue Water | B55: =B13-B10 -> 89172255 | C55: =C13-C10 -> 6060923 | D55: =D13-D10 -> 6046343 | E55: =E13-E10 -> 3486381 | F55: =F13-F10 -> 3301051 | G55: =G13-G10 -> 4279774 | H55: =H13-H10 -> 3987266 | I55: =I13-I10 -> 1364111 | ... CO55: =CO13-CO10 -> 3668 | CQ55: =SUM(B55:CO55) -> 2.050996e+08
CQ56: =SUM(B56:CO56) -> 0
A57: Sewerage in cubic meters | CQ57: =SUM(B57:CO57) -> 0
A58: Individual | B58: =B33/$B$19 -> 3452843 | C58: =C33/$C$19 -> 4271781.8 | D58: =D33/$D$19 -> 501907.6 | E58: =E33/$E$19 -> 982511.96 | F58: =F33/$F$19 -> 1648271.4 | G58: =G33/$G$19 -> 445656.17 | H58: =H33/$H$19 -> 1123189.6 | I58: =I33/$I$19 -> 1050729.6 | K58: =K33/$K$19 -> 912953.83 | N58: =N33/$N$19 -> 922959.64 | Q58: =Q33/$Q$19 -> 46018.349 | R58: =R33/$R$19 -> 205432.98 | W58: =W33/$W$19 -> 514461.1 | X58: =X33/$X$19 -> 74274.844 | Z58: =Z33/$Z$19 -> 311484.81 | AA58: =AA33/$AA$19 -> 405186.21 | AB58: =AB33/$AB$19 -> 3842.0097 | AG58: =AG33/$AG$19 -> 99941.436 | AL58: =AL33/$AL$19 -> 38145.45 | AO58: =AO33/$AO$19 -> 143327.03 | AQ58: =AQ33/$AQ$19 -> 132394.5 | AU58: =AU33/AU19 -> 101997.78 | BB58: =BB33/$BB$19 -> 16017.3 | BD58: =BD33/$BD$19 -> 53664.798 | CQ58: =SUM(B58:CO58) -> 17458993
A59: Multi-dwelling units | B59: =B34/$B$19 -> 1233431.9 | C59: =C34/$C$19 -> 22625.827 | D59: =D34/$D$19 -> 215103.4 | E59: =E34/$E$19 -> 840133.63 | F59: =F34/$F$19 -> 0 | G59: =G34/$G$19 -> 24007.855 | H59: =H34/$H$19 -> 41437.123 | I59: =I34/$I$19 -> 935202.6 | K59: =K34/$K$19 -> 338420.09 | N59: =N34/$N$19 -> 0 | Q59: =Q34/$Q$19 -> 59827.845 | R59: =R34/$R$19 -> 0 | W59: =W34/$W$19 -> 0 | X59: =X34/$X$19 -> 41349.1 | Z59: =Z34/$Z$19 -> 0 | AA59: =AA34/$AA$19 -> 244849.91 | AB59: =AB34/$AB$19 -> 726.86813 | AG59: =AG34/$AG$19 -> 41832.446 | AL59: =AL34/$AL$19 -> 22524.6 | AO59: =AO34/$AO$19 -> 0 | AQ59: =AQ34/$AQ$19 -> 65841.3 | AU59: =AU34/$AU$19 -> 26178.791 | BB59: =BB34/$BB$19 -> 14458.35 | BD59: =BD34/$BD$19 -> 0 | CQ59: =SUM(B59:CO59) -> 4167951.7
A60: Institutions | B60: =B35/$B$19 -> 177532.79 | C60: =C35/$C$19 -> 220730.36 | D60: =D35/$D$19 -> 20637.4 | E60: =E35/$E$19 -> 2660.6423 | F60: =F35/$F$19 -> 144246.12 | G60: =G35/$G$19 -> 1762.621 | H60: =H35/$H$19 -> 23328.343 | I60: =I35/$I$19 -> 271763.75 | K60: =K35/$K$19 -> 9211.1986 | N60: =N35/$N$19 -> 56855.113 | Q60: =Q35/$Q$19 -> 3283.4125 | R60: =R35/$R$19 -> 2289.4075 | W60: =W35/$W$19 -> 0 | X60: =X35/$X$19 -> 4018.2926 | Z60: =Z35/$Z$19 -> 28080.613 | AA60: =AA35/$AA$19 -> 74308.584 | AB60: =AB35/$AB$19 -> 1246.0495 | AG60: =AG35/$AG$19 -> 25273.603 | AL60: =AL35/$AL$19 -> 1216.65 | AO60: =AO35/$AO$19 -> 4773.4675 | AQ60: =AQ35/$AQ$19 -> 3619.8 | AU60: =AU35/$AU$19 -> 768.87467 | BB60: =BB35/$BB$19 -> 17666.1 | BD60: =BD35/$BD$19 -> 2947.3403 | CQ60: =SUM(B60:CO60) -> 1098220.5
A61: Schools | B61: =B36/$B$19 -> 17128.195 | C61: =C36/$C$19 -> 35841.011 | D61: =D36/$D$19 -> 13758.4 | E61: =E36/$E$19 -> 2719.8595 | F61: =F36/$F$19 -> 25039.756 | G61: =G36/$G$19 -> 60457.446 | H61: =H36/$H$19 -> 30121.788 | I61: =I36/$I$19 -> 198664.53 | K61: =K36/$K$19 -> 10381.827 | N61: =N36/$N$19 -> 78674.391 | Q61: =Q36/$Q$19 -> 9630.6472 | R61: =R36/$R$19 -> 12317.779 | W61: =W36/$W$19 -> 19100.504 | X61: =X36/$X$19 -> 2171.7105 | Z61: =Z36/$Z$19 -> 25216.467 | AA61: =AA36/$AA$19 -> 26648.785 | AB61: =AB36/$AB$19 -> 1869.0743 | AG61: =AG36/$AG$19 -> 10831.496 | AL61: =AL36/$AL$19 -> 484.2 | AO61: =AO36/$AO$19 -> 0 | AQ61: =AQ36/$AQ$19 -> 1021.5 | AU61: =AU36/$AU$19 -> 4032.8198 | BB61: =BB36/$BB$19 -> 10379.7 | BD61: =BD36/$BD$19 -> 1362.1799 | CQ61: =SUM(B61:CO61) -> 597854.07
A62: Commercial customers | B62: =B37/$B$19 -> 870928.75 | C62: =C37/$C$19 -> 651447.41 | D62: =D37/$D$19 -> 103187 | E62: =E37/$E$19 -> 80306.779 | F62: =F37/$F$19 -> 877990.97 | G62: =G37/$G$19 -> 69875.453 | H62: =H37/$H$19 -> 447307.49 | I62: =I37/$I$19 -> 342061.48 | K62: =K37/$K$19 -> 0 | N62: =N37/$N$19 -> 227606.45 | Q62: =Q37/$Q$19 -> 4298.759 | R62: =R37/$R$19 -> 24509.366 | W62: =W37/$W$19 -> 271179.86 | X62: =X37/$X$19 -> 37959.623 | Z62: =Z37/$Z$19 -> 100531.44 | AA62: =AA37/$AA$19 -> 58534.536 | AB62: =AB37/$AB$19 -> 2180.6044 | AG62: =AG37/$AG$19 -> 13182.461 | AL62: =AL37/$AL$19 -> 43320.45 | AO62: =AO37/$AO$19 -> 12202.129 | AQ62: =AQ37/$AQ$19 -> 8580.3 | AU62: =AU37/$AU$19 -> 36981.262 | BB62: =BB37/$BB$19 -> 18772.5 | BD62: =BD37/$BD$19 -> 2172.7218 | CQ62: =SUM(B62:CO62) -> 4305117.8
A63: Industries | B63: =B38/$B$19 -> 56128.045 | C63: =C38/$C$19 -> 0 | D63: =D38/$D$19 -> 68791.4 | E63: =E38/$E$19 -> 0 | F63: =F38/$F$19 -> 5828.7306 | G63: =G38/$G$19 -> 0 | H63: =H38/$H$19 -> 152197.09 | I63: =I38/$I$19 -> 0 | K63: =K38/$K$19 -> 130350.42 | N63: =N38/$N$19 -> 0 | Q63: =Q38/$Q$19 -> 0 | R63: =R38/$R$19 -> 0 | W63: =W38/$W$19 -> 0 | X63: =X38/$X$19 -> 3383.2787 | Z63: =Z38/$Z$19 -> 32024.263 | AA63: =AA38/$AA$19 -> 50.419098 | AB63: =AB38/$AB$19 -> 519.18141 | AG63: =AG38/$AG$19 -> 0 | AL63: =AL38/$AL$19 -> 17027.4 | AO63: =AO38/$AO$19 -> 0 | AQ63: =AQ38/$AQ$19 -> 0 | AU63: =AU38/$AU$19 -> 0 | BB63: =BB38/$BB$19 -> 15364.95 | BD63: =BD38/$BD$19 -> 63.243654 | CQ63: =SUM(B63:CO63) -> 481728.42
A64: Total | B64: =SUM(B58:B63) -> 5807992.7 | C64: =SUM(C58:C63) -> 5202426.4 | D64: =SUM(D58:D63) -> 923385.2 | E64: =SUM(E58:E63) -> 1908332.9 | F64: =SUM(F58:F63) -> 2701377 | G64: =SUM(G58:G63) -> 601759.54 | H64: =SUM(H58:H63) -> 1817581.4 | I64: =SUM(I58:I63) -> 2798421.9 | ... BD64: =SUM(BD58:BD63) -> 60210.284 | CQ64: =SUM(B64:CO64) -> 28109866

Sheet WASREB 22-23
A1: unit | B1: m3
A2: County | B2: Nairobi | C2: Uasin Gishu | D2: Mombasa | E2: Kisumu | F2: Nakuru | G2: Nyeri | H2: Kiambu | I2: Kiambu | J2: Murang'a | K2: Bungoma | L2: Kilifi | M2: Kiambu | N2: Embu | O2: Kirinyaga | P2: Kilifi | Q2: Kakamega | R2: Kericho | S2: Nyeri | T2: Nyeri | U2: Nakuru | V2: Taita-Taveta | W2: Laikipia | X2: Murang'a | Y2: Murang'a | Z2: Laikipia | AA2: Kisii | AB2: Garissa | AC2: Bomet | AD2: Kwale | AE2: Meru | AF2: Embu | AG2: Kitui | AH2: Siaya | AI2: Nyeri | AJ2: Tharaka-Nithi | AK2: Murang'a | AL2: Machakos | AM2: Kiambu | AN2: Isiolo | AO2: Kiambu | AP2: Kiambu | AQ2: Murang'a | AR2: Kiambu | AS2: Nakuru | AT2: Embu | AU2: Kajiado | AV2: Meru | AW2: Vihiga | AX2: Kiambu | AY2: Embu | AZ2: Busia | BA2: Homabay | BB2: Kajiado | BC2: Machakos | BD2: Meru | BE2: Nyandarua | BF2: Makueni | BG2: Narok | BH2: Embu | BI2: Tana River | BJ2: Migori | BK2: Nandi | BL2: Baringo | BM2: Tharaka-Nithi | BN2: Baringo | BO2: Samburu | BP2: Lamu | BQ2: Kitui | BR2: Elgeiyo Marakwet | BS2: Mandera | BT2: Kakamega | BU2: Nyandarua | BV2: Kajiado | BW2: Tharaka-Nithi | BX2: West Pokot | BY2: Kirinyaga | BZ2: Nyeri | CA2: Mandera | CB2: Wajir | CC2: Machakos | CD2: Machakos | CE2: Kiambu | CF2: Machakos | CG2: Makueni | CH2: Makueni | CI2: Migori | CJ2: Nandi | CK2: Nairobi | CL2: Machakos | CM2: Nairobi | CN2: Kiambu | CO2: Marsabit
A3: INDICATORS | B3: Nairobi | C3: Eldoret | D3: Mombasa | E3: Kisumu | F3: Nakuru Urban | G3: Nyeri | H3: Thika | I3: Ruiru-Juja | J3: Murang'a South | K3: Nzoia | L3: Kilifi Mariakani | M3: Gatundu | N3: Embu | O3: Kirinyaga | P3: Malindi | Q3: Kakamega | R3: Kericho | S3: Othaya Mukurweini | T3: Mathira | U3: Nakuru Rural | V3: Tavevo | W3: Nanyuki | X3: Murang'a West | Y3: Murang'a Urban | Z3: Nyahururu | AA3: Gusii | AB3: Garissa | AC3: Bomet | AD3: Kwale | AE3: Meru | AF3: Ngandori Nginda | AG3: Kitui | AH3: Sibo | AI3: Tetu Aberdare | AJ3: Nithi | AK3: Gatamathi | AL3: Mavoko | AM3: Kikuyu | AN3: Isiolo | AO3: Kiambu | AP3: Limuru | AQ3: Gatanga | AR3: Githunguri | AS3: Naivasha | AT3: Ngagaka | AU3: Oloolaiser | AV3: Imetha | AW3: Amatsi | AX3: Karuri | AY3: Kyeni | AZ3: Busia | BA3: Homabay | BB3: Nol Turesh | BC3: Machakos | BD3: Tuuru | BE3: Nyandarua | BF3: Kibwezi Makindu | BG3: Narok | BH3: Embe | BI3: Tana | BJ3: Migori | BK3: Kapsabet Nandi | BL3: Kirandich | BM3: Murugi Mugumango | BN3: Chemususu | BO3: Samburu | BP3: Lamu | BQ3: Kiambere Mwingi | BR3: Iten Tambach | BS3: Mandera | BT3: Kakamega Rural | BU3: Ol Kalou | BV3: Olkejuado | BW3: Muthambi 4K | BX3: Kapenguria | BY3: Rukanga | BZ3: Naromoru | CA3: Elwak | CB3: Wajir | CC3: Yatta | CD3: Kathiani | CE3: Kiamumbi | CF3: Matungulu Kangundo | CG3: Wote | CH3: Mbooni | CI3: Nyasare | CJ3: Tachasis | CK3: Runda | CL3: Mwala | CM3: Two Rivers | CN3: Tatu City | CO3: Marsabit | CR3: Total
A4: Surface Water Abstracted | B4: 1.8081615e+08 | C4: 14891969 | D4: 11310975 | E4: 11722682 | F4: 11966635 | G4: 7802800 | H4: 14141295 | I4: 13179011 | J4: 6163553 | K4: 8188812 | L4: 10278570 | M4: 5216907 | N4: 7510145 | O4: 6206683 | P4: 6910230 | Q4: 4565123 | R4: 3910733 | S4: 6461280 | T4: 2022607 | U4: 7451705 | V4: 6118445 | W4: 4037242 | X4: 2716661 | Y4: 3086430 | Z4: 3241297 | AA4: 3583935 | AB4: 5553603 | AC4: 3626535 | AD4: 4628377 | AE4: 3371599 | AF4: 2720468 | AG4: 3178823 | AH4: 2530098 | AI4: 2566769 | AJ4: 3509726 | AK4: 3286000 | AL4: 1164891 | AM4: 2837290 | AN4: 2147913 | AO4: 3360749 | AP4: 1862867 | AQ4: 1839189 | AR4: 1829423 | AS4: 2234129 | AT4: 1122612 | AU4: 1643799 | AV4: 1186698 | AW4: 1748197 | AX4: 1377973 | AY4: 675720 | AZ4: 996774 | BA4: 732063 | BB4: 1540936 | BC4: 968302 | BD4: 1590175 | BE4: 884377 | BF4: 1481649 | BG4: 1205444.6 | BH4: 1114978 | BI4: 1837363 | BJ4: 531836 | BK4: 1243599 | BL4: 1700700 | BM4: 3613666 | BN4: 882803 | BO4: 420485 | BP4: 589736 | BQ4: 932601 | BR4: 724558 | BS4: 532415 | BT4: 287414.5 | BU4: 547153 | BV4: 255014 | BW4: 741960 | BX4: 339988 | BY4: 223278 | BZ4: 317105 | CA4: 145830 | CB4: 201066 | CC4: 341740 | CD4: 116065 | CE4: 471593 | CF4: 155692 | CG4: 426171 | CH4: 44020 | CI4: 134403 | CJ4: 375737 | CK4: 861970 | CL4: 55424 | CM4: 96374 | CN4: 331605.2 | CO4: 32800 | CR4: =SUM(B4:CO4) -> 4.5353219e+08
A5: Ground water abstracted | CR5: =SUM(B5:CO5) -> 0
A6: Total volume of water treated | CR6: =SUM(B6:CO6) -> 0
A7: Imported treated water | CR7: =SUM(B7:CO7) -> 0
A8: Exported treated water | CR8: =SUM(B8:CO8) -> 0
A9: Metered volume produced | B9: 1.8081615e+08 | C9: 14891969 | D9: 11310975 | E9: 11722682 | F9: 11966635 | G9: 7802800 | H9: 14141295 | I9: 13179011 | J9: 6163553 | K9: 8188812 | L9: 10278570 | M9: 5216907 | N9: 7510145 | O9: 6206683 | P9: 6910230 | Q9: 4565123 | R9: 3910733 | S9: 6461280 | T9: 2022607 | U9: 7451705 | V9: 6118445 | W9: 4037242 | X9: 2716661 | Y9: 3086430 | Z9: 3241297 | AA9: 3583935 | AB9: 5553603 | AC9: 3626535 | AD9: 4628377 | AE9: 3371599 | AF9: 2720468 | AG9: 3178823 | AH9: 2530098 | AI9: 2566769 | AJ9: 3509726 | AK9: 3286000 | AL9: 1164891 | AM9: 2837290 | AN9: 2147913 | AO9: 3360749 | AP9: 1862867 | AQ9: 1839189 | AR9: 1829423 | AS9: 2234129 | AT9: 1122612 | AU9: 1643799 | AV9: 1186698 | AW9: 1748197 | AX9: 1377973 | AY9: 675720 | AZ9: 996774 | BA9: 732063 | BB9: 1540936 | BC9: 968302 | BD9: 1590175 | BE9: 884377 | BF9: 1481649 | BG9: 1205444.6 | BH9: 1114978 | BI9: 1837363 | BJ9: 531836 | BK9: 1243599 | BL9: 1700700 | BM9: 3613666 | BN9: 882803 | BO9: 420485 | BP9: 589736 | BQ9: 932601 | BR9: 724558 | BS9: 532415 | BT9: 287414.5 | BU9: 547153 | BV9: 255014 | BW9: 741960 | BX9: 339988 | BY9: 223278 | BZ9: 317105 | CA9: 145830 | CB9: 201066 | CC9: 341740 | CD9: 116065 | CE9: 471593 | CF9: 155692 | CG9: 426171 | CH9: 44020 | CI9: 134403 | CJ9: 375737 | CK9: 861970 | CL9: 55424 | CM9: 96374 | CN9: 331605.2 | CO9: 32800 | CR9: =SUM(B9:CO9) -> 4.5353219e+08
A10: Unmeterd volume produced | CR10: =SUM(B10:CO10) -> 0
A11: Total Billed Volume | B11: 95379600 | C11: 9285682 | D11: 5469410 | E11: 7330450 | F11: 8464454 | G11: 6492661 | H11: 9577143 | I11: 7988954.8 | J11: 3372588 | K11: 4220573 | L11: 5674189 | M11: 3521139 | N11: 4607024 | O11: 2618120 | P11: 5313433 | Q11: 2855783 | R11: 1836073 | S11: 4128699 | T11: 1275266 | U11: 4080087 | V11: 3545108 | W11: 2818164 | X11: 1320935 | Y11: 2330911 | Z11: 1995241 | AA11: 1230624 | AB11: 3468770 | AC11: 1237626 | AD11: 2167423 | AE11: 2723122 | AF11: 1784778 | AG11: 1630325 | AH11: 1101993 | AI11: 1650627 | AJ11: 1448674 | AK11: 1358955 | AL11: 784687 | AM11: 1731476 | AN11: 1507078 | AO11: 2201798 | AP11: 1285825 | AQ11: 1210384 | AR11: 595642 | AS11: 1667181 | AT11: 713983 | AU11: 1065353 | AV11: 723087 | AW11: 1198500.1 | AX11: 991285 | AY11: 325704 | AZ11: 464162 | BA11: 425838 | BB11: 969113 | BC11: 660034 | BD11: 260656 | BE11: 477219 | BF11: 939527 | BG11: 795853 | BH11: 509340 | BI11: 650881 | BJ11: 302085 | BK11: 777903 | BL11: 575807 | BM11: 1914434 | BN11: 391802 | BO11: 215970 | BP11: 300510 | BQ11: 604831 | BR11: 494732 | BS11: 280192 | BT11: 184716 | BU11: 345096 | BV11: 142828 | BW11: 557518 | BX11: 220834 | BY11: 185407 | BZ11: 229023 | CA11: 74265 | CB11: 80159 | CC11: 214532 | CD11: 83267 | CE11: 400514 | CF11: 99834 | CG11: 310285 | CH11: 29694.5 | CI11: 85640 | CJ11: 284946 | CK11: 690520 | CL11: 40676 | CM11: 93296 | CN11: 311401.27 | CO11: 13454.06 | CR11: =SUM(B11:CO11) -> 2.5799538e+08
CR12: =SUM(B12:CO12) -> 0
CR13: =SUM(B13:CO13) -> 0
A14: Total Water Produced | B14: 1.8081615e+08 | C14: 14891969 | D14: 11310975 | E14: 11722682 | F14: 11966635 | G14: 7802800 | H14: 14141295 | I14: 13179011 | J14: 6163553 | K14: 8188812 | L14: 10278570 | M14: 5216907 | N14: 7510145 | O14: 6206683 | P14: 6910230 | Q14: 4565123 | R14: 3910733 | S14: 6461280 | T14: 2022607 | U14: 7451705 | V14: 6118445 | W14: 4037242 | X14: 2716661 | Y14: 3086430 | Z14: 3241297 | AA14: 3583935 | AB14: 5553603 | AC14: 3626535 | AD14: 4628377 | AE14: 3371599 | AF14: 2720468 | AG14: 3178823 | AH14: 2530098 | AI14: 2566769 | AJ14: 3509726 | AK14: 3286000 | AL14: 1164891 | AM14: 2837290 | AN14: 2147913 | AO14: 3360749 | AP14: 1862867 | AQ14: 1839189 | AR14: 1829423 | AS14: 2234129 | AT14: 1122612 | AU14: 1643799 | AV14: 1186698 | AW14: 1748197 | AX14: 1377973 | AY14: 675720 | AZ14: 996774 | BA14: 732063 | BB14: 1540936 | BC14: 968302 | BD14: 1590175 | BE14: 884377 | BF14: 1481649 | BG14: 1205444.6 | BH14: 1114978 | BI14: 1837363 | BJ14: 531836 | BK14: 1243599 | BL14: 1700700 | BM14: 3613666 | BN14: 882803 | BO14: 420485 | BP14: 589736 | BQ14: 932601 | BR14: 724558 | BS14: 532415 | BT14: 287414.5 | BU14: 547153 | BV14: 255014 | BW14: 741960 | BX14: 339988 | BY14: 223278 | BZ14: 317105 | CA14: 145830 | CB14: 201066 | CC14: 341740 | CD14: 116065 | CE14: 471593 | CF14: 155692 | CG14: 426171 | CH14: 44020 | CI14: 134403 | CJ14: 375737 | CK14: 861970 | CL14: 55424 | CM14: 96374 | CN14: 331605.2 | CO14: 32800 | CR14: =SUM(B14:CO14) -> 4.5353219e+08
A15: Total sewage treated
A16: Total Expenditures | B16: 1.1632909e+10 | C16: 1055419275 | D16: 816014942 | E16: 1.070204e+09 | F16: 1.0739888e+09 | G16: 657197325 | H16: 8.5089244e+08 | I16: 7.3467417e+08 | J16: 245827558 | K16: 431313913 | L16: 7.1257983e+08 | M16: 154589404 | N16: 5.1861608e+08 | O16: 223242901 | P16: 612053158 | Q16: 382389692 | R16: 257760856 | S16: 246540394 | T16: 148469463 | U16: 3.6647996e+08 | V16: 474020896 | W16: 351935603 | X16: 92675223 | Y16: 310029727 | Z16: 276962653 | AA16: 2.6430668e+08 | AB16: 284576028 | AC16: 220661779 | AD16: 309066285 | AE16: 2.3739241e+08 | AF16: 95425177 | AG16: 267978728 | AH16: 1.9061828e+08 | AI16: 68911736 | AJ16: 106838686 | AK16: 77442485 | AL16: 245601505 | AM16: 208931771 | AN16: 107107775 | AO16: 259914211 | AP16: 177334886 | AQ16: 73183709 | AR16: 76240390 | AS16: 2.3610816e+08 | AT16: 42270520 | AU16: 1.690706e+08 | AV16: 58282567 | AW16: 110244131 | AX16: 111987365 | AY16: 18699824 | AZ16: 80747255 | BA16: 145392625 | BB16: 82424703 | BC16: 125634730 | BD16: 35483198 | BE16: 57716262 | BF16: 110113458 | BG16: 138599083 | BH16: 40349065 | BI16: 52772446 | BJ16: 57555958 | BK16: 80103070 | BL16: 91116332 | BM16: 23187853 | BN16: 23112236 | BO16: 44737801 | BP16: 65851192 | BQ16: 152468987 | BR16: 36285781 | BS16: 1.9406554e+08 | BT16: 33696652 | BU16: 45211152 | BV16: 30021932 | BW16: 4673862 | BX16: 21169793 | BY16: 12814492 | BZ16: 17811126 | CA16: 1.1098317e+08 | CB16: 608395986 | CC16: 29467723 | CD16: 18286375 | CE16: 25832593 | CF16: 17336981 | CG16: 50612521 | CH16: 5256306 | CI16: 6425389 | CJ16: 3301138 | CK16: 64943336 | CL16: 13088052 | CM16: 36125633 | CN16: 85452381 | CO16: 2629350
A17: Total Expenditures-Water | B17: 7.5613908e+09 | C17: 8.9710638e+08 | D17: 6.5281195e+08 | E17: 9.364285e+08 | F17: 1.0739888e+09 | G17: 5.9147759e+08 | H17: 6.4667825e+08 | I17: 7.3467417e+08 | J17: 245827558 | K17: 3.6661683e+08 | L17: 7.1257983e+08 | M17: 154589404 | N17: 4.4082367e+08 | O17: 223242901 | P17: 612053158 | Q17: 2.6767278e+08 | R17: 2.1909673e+08 | S17: 246540394 | T17: 148469463 | U17: 3.6647996e+08 | V17: 474020896 | W17: 3.3433882e+08 | X17: 92675223 | Y17: 3.0072884e+08 | Z17: 2.3541826e+08 | AA17: 2.2466068e+08 | AB17: 2.4188962e+08 | AC17: 220661779 | AD17: 309066285 | AE17: 2.3739241e+08 | AF17: 95425177 | AG17: 267978728 | AH17: 1.9061828e+08 | AI17: 68911736 | AJ17: 106838686 | AK17: 77442485 | AL17: 2.0876128e+08 | AM17: 208931771 | AN17: 91041609 | AO17: 2.2092708e+08 | AP17: 177334886 | AQ17: 73183709 | AR17: 76240390 | AS17: 2.0069193e+08 | AT17: 42270520 | AU17: 1.690706e+08 | AV17: 58282567 | AW17: 110244131 | AX17: 111987365 | AY17: 18699824 | AZ17: 80747255 | BA17: 145392625 | BB17: 82424703 | BC17: 1.0678952e+08 | BD17: 35483198 | BE17: 57716262 | BF17: 110113458 | BG17: 138599083 | BH17: 40349065 | BI17: 52772446 | BJ17: 57555958 | BK17: 80103070 | BL17: 91116332 | BM17: 23187853 | BN17: 23112236 | BO17: 44737801 | BP17: 65851192 | BQ17: 152468987 | BR17: 36285781 | BS17: 1.9406554e+08 | BT17: 33696652 | BU17: 45211152 | BV17: 30021932 | BW17: 4673862 | BX17: 21169793 | BY17: 12814492 | BZ17: 17811126 | CA17: 1.1098317e+08 | CB17: 608395986 | CC17: 29467723 | CD17: 18286375 | CE17: 25832593 | CF17: 17336981 | CG17: 50612521 | CH17: 5256306 | CI17: 6425389 | CJ17: 3301138 | CK17: 64943336 | CL17: 13088052 | CM17: 36125633 | CN17: 85452381 | CO17: 2629350
A18: Total expenditures-sewerage | B18: 2.6464868e+09 | C18: 1.3456596e+08 | D18: 1.3056239e+08 | E18: 1.1705356e+08 | F18: 1.6109831e+08 | G18: 59147759 | H18: 1.5520278e+08 | I18: 1.1020112e+08 | K18: 54992524 | N18: 66123550 | Q18: 80301835 | R18: 32864509 | W18: 16716941 | Y18: 9021865.1 | Z18: 35312738 | AA18: 33699101 | AB18: 36283444 | AG18: 40196809 | AL18: 31314192 | AN18: 13656241 | AO18: 33139062 | AS18: 30103790 | BA18: 21808894 | BC18: 16018428
A19: Total expenditures Other | B19: =B16-SUM(B17:B18) -> 1.4250313e+09 | C19: =C16-SUM(C17:C18) -> 23746934 | D19: =D16-SUM(D17:D18) -> 32640598 | E19: =E16-SUM(E17:E18) -> 16721938 | F19: =F16-SUM(F17:F18) -> -1.6109831e+08 | G19: =G16-SUM(G17:G18) -> 6571973.2 | H19: =H16-SUM(H17:H18) -> 49011405 | I19: =I16-SUM(I17:I18) -> -1.1020112e+08 | ... CO19: =CO16-SUM(CO17:CO18) -> 0
A20: Actual cost of water produced | B20: =B17/B14 -> 41.818116 | C20: =C17/C14 -> 60.240952 | D20: =D17/D14 -> 57.714915 | E20: =E17/E14 -> 79.881763 | F20: =F17/F14 -> 89.748602 | G20: =G17/G14 -> 75.803249 | H20: =H17/H14 -> 45.729776 | I20: =I17/I14 -> 55.745774 | ... CO20: =CO17/CO14 -> 80.16311 | CR20: =SUM(B20:CO20) -> 10937.93
A21: ='[1]FY 2021-2022'!A19 -> Actual unit cost- sewage treated | B21: ='[1]FY 2021-2022'!B19 -> 45.359281 | C21: ='[1]FY 2021-2022'!C19 -> 13.609543 | D21: ='[1]FY 2021-2022'!D19 -> 61.737753 | E21: ='[1]FY 2021-2022'!F19 -> 21.999332 | F21: ='[1]FY 2021-2022'!E19 -> 28.300345 | G21: ='[1]FY 2021-2022'!I19 -> 11.87687 | H21: ='[1]FY 2021-2022'!H19 -> 29.754233 | I21: ='[1]FY 2021-2022'!K19 -> 57.853015 | K21: ='[1]FY 2021-2022'!G19 -> 40.558013 | N21: ='[1]FY 2021-2022'!N19 -> 27.909292 | Q21: ='[1]FY 2021-2022'!Q19 -> 185.60633 | R21: =R20 -> 56.024466 | W21: ='[1]FY 2021-2022'!W19 -> 19.86298 | Y21: =Y20 -> 97.435819 | Z21: ='[1]FY 2021-2022'!Z19 -> 35.067308 | AA21: ='[1]FY 2021-2022'!AA19 -> 14.48383 | AB21: ='[1]FY 2021-2022'!AB19 -> 292.32548 | AG21: =AG20 -> 84.301242 | AL21: =AL20 -> 179.211 | AN21: ='[1]FY 2021-2022'!AO19 -> 41.510444 | AO21: =AO20 -> 65.737453 | AS21: ='[1]FY 2021-2022'!AU19 -> 79.573352 | BA21: =BA20 -> 198.60671 | BC21: =BC20 -> 110.28535
A23: Water Value (in Ksh.) per category | CR23: =SUM(B23:CO23) -> 0
A24: Individual | B24: 1.8633168e+09 | C24: 4.3615335e+08 | D24: 1.4891584e+08 | E24: 2.830207e+08 | F24: 3.908484e+08 | G24: 1.0171466e+08 | H24: 1.3398462e+08 | I24: 2.8761998e+08 | J24: 1.010197e+08 | K24: 1.3725346e+08 | L24: 2.9599418e+08 | M24: 99982957 | N24: 1.9248423e+08 | O24: 76879823 | P24: 1.6191722e+08 | Q24: 49534012 | R24: 70761819 | S24: 1.3492289e+08 | T24: 64222381 | U24: 26443286 | V24: 2.0774638e+08 | W24: 1.4892515e+08 | X24: 29055935 | Y24: 48688824 | Z24: 79155947 | AA24: 30090774 | AB24: 55901129 | AC24: 22210784 | AD24: 1.2140795e+08 | AE24: 1.5187581e+08 | AF24: 23962578 | AG24: 55789851 | AH24: 45895128 | AI24: 15163664 | AJ24: 22049391 | AK24: 22236357 | AL24: 42096367 | AM24: 52202966 | AN24: 42523336 | AO24: 79336695 | AP24: 87362691 | AQ24: 26971160 | AR24: 17343581 | AS24: 83893791 | AT24: 22522299 | AU24: 29281774 | AV24: 15980900 | AW24: 24977588 | AX24: 26746333 | AY24: 8255465.3 | AZ24: 33556624 | BA24: 74071820 | BB24: 32657887 | BC24: 12214601 | BD24: 4863663.8 | BE24: 27517074 | BF24: 33492615 | BG24: 51398396 | BH24: 8327603.2 | BI24: 1356368 | BJ24: 24410564 | BK24: 18130139 | BL24: 135194.5 | BM24: 9827499.7 | BN24: 8336538.1 | BO24: 0 | BP24: 24726717 | BQ24: 35587286 | BR24: 10632529 | BS24: 0 | BT24: 0 | BU24: 21290680 | BV24: 3236842 | BW24: 3442272.4 | BX24: 5231303.1 | BY24: 8959677.9 | BZ24: 6369490.1 | CA24: 0 | CB24: 0 | CC24: 4441060.6 | CD24: 1967803.5 | CE24: 13992526 | CF24: 7806177.3 | CG24: 6166872.6 | CI24: 2885487.4 | CJ24: 2074329.3 | CK24: 51368060 | CL24: 2072670.4 | CN24: 14186.35
A25: Multi-dwelling units | B25: 6.6561797e+08 | C25: 2310120.4 | D25: 63821116 | E25: 0 | F25: 3.3420955e+08 | G25: 90531206 | H25: 4943010 | I25: 1.0661698e+08 | J25: 0 | K25: 7393954.1 | L25: 0 | M25: 0 | N25: 0 | O25: 0 | P25: 0 | Q25: 0 | R25: 0 | S25: 0 | T25: 0 | U25: 30749028 | V25: 0 | W25: 0 | X25: 0 | Y25: 27105261 | Z25: 0 | AA25: 18183549 | AB25: 10575910 | AC25: 0 | AD25: 0 | AE25: 0 | AF25: 0 | AG25: 23351935 | AH25: 168397.74 | AI25: 23268695 | AJ25: 0 | AK25: 0 | AL25: 24857587 | AM25: 0 | AN25: 0 | AO25: 39455046 | AP25: 0 | AQ25: 0 | AR25: 1345387.3 | AS25: 21532214 | AT25: 0 | AU25: 71550694 | AV25: 5326948.6 | AW25: 0 | AX25: 36413734 | AY25: 0 | AZ25: 0 | BA25: 0 | BB25: 0 | BC25: 11025765 | BD25: 0 | BE25: 0 | BF25: 9939659 | BG25: 3058473.7 | BH25: 4181104.8 | BI25: 3390.55 | BJ25: 0 | BK25: 2914675.9 | BL25: 66592.15 | BM25: 0 | BN25: 0 | BO25: 0 | BP25: 0 | BQ25: 11662475 | BR25: 2817057.2 | BS25: 0 | BT25: 0 | BU25: 0 | BV25: 6011210.5 | BW25: 0 | BX25: 0 | BY25: 0 | BZ25: 5507707 | CA25: 0 | CB25: 0 | CC25: 8496039.6 | CD25: 2099064.9 | CE25: 5484769.3 | CF25: 437041.95 | CG25: 4688446.5 | CI25: 406420.03 | CJ25: 0 | CK25: 0 | CL25: 1895559.5 | CN25: 8196.6
A26: Institutions | B26: 95805056 | C26: 22536799 | D26: 6123110.5 | E26: 24768152 | F26: 1058417.4 | G26: 26307776 | H26: 2782824.4 | I26: 2901926.3 | J26: 1245057.2 | K26: 542853.1 | L26: 19294898 | M26: 2521490.3 | N26: 11857195 | O26: 7229159.1 | P26: 6738796.6 | Q26: 0 | R26: 788591.2 | S26: 4413290.9 | T26: 13925926 | U26: 18179593 | V26: 23361294 | W26: 0 | X26: 3707709.8 | Y26: 2634080.8 | Z26: 7135974 | AA26: 5518457.3 | AB26: 18129984 | AC26: 1223021.3 | AD26: 2528193.5 | AE26: 7551690.1 | AF26: 11291386 | AG26: 14108368 | AH26: 3984548.4 | AI26: 2608575.4 | AJ26: 8819750.2 | AK26: 1912543 | AL26: 1342664.6 | AM26: 0 | AN26: 1416228 | AO26: 2169145.8 | AP26: 7069283.1 | AQ26: 14448828 | AR26: 366283.46 | AS26: 632404.06 | AT26: 1736881 | AU26: 394231.51 | AV26: 3551335.2 | AW26: 43212057 | AX26: 322280.61 | AY26: 0 | AZ26: 343833.3 | BA26: 4068120.4 | BB26: 0 | BC26: 13471956 | BD26: 494541.99 | BE26: 362745.32 | BF26: 2388957.2 | BG26: 8090584.1 | BH26: 1671603.7 | BI26: 113596.3 | BJ26: 3839719.3 | BK26: 10021319 | BL26: 7789.05 | BM26: 859903.97 | BN26: 40584.638 | BO26: 0 | BP26: 0 | BQ26: 5426441.7 | BR26: 4193238.6 | BS26: 0 | BT26: 0 | BU26: 766942.18 | BV26: 2858511.9 | BW26: 3042.7284 | BX26: 2031150.9 | BY26: 53224.117 | BZ26: 261202.79 | CA26: 0 | CB26: 0 | CC26: 476183.99 | CD26: 4591594.7 | CE26: 0 | CF26: 650108.6 | CG26: 10372755 | CI26: 203187.44 | CJ26: 0 | CK26: 0 | CL26: 1224248.3 | CN26: 18442.35
A27: Schools | B27: 9243180.9 | C27: 3659404.5 | D27: 4082113.3 | E27: 4299515.9 | F27: 1081974.4 | G27: 19231490 | H27: 3593210.4 | I27: 3270725.1 | J27: 7402445.7 | K27: 18619722 | L27: 18507959 | M27: 1477745.3 | N27: 16407629 | O27: 3576334.8 | P27: 3449173.9 | Q27: 0 | R27: 4242884.7 | S27: 11337171 | T27: 0 | U27: 3318954.9 | V27: 8853443 | W27: 5529174.8 | X27: 1935237 | Y27: 1423604.9 | Z27: 6408124.1 | AA27: 1979047.1 | AB27: 27194977 | AC27: 1960218.6 | AD27: 3792388.7 | AE27: 3249104.4 | AF27: 11643771 | AG27: 6046416.4 | AH27: 3422580.3 | AI27: 667639.71 | AJ27: 4409890.2 | AK27: 3941439 | AL27: 534351.04 | AM27: 14023897 | AN27: 0 | AO27: 612128.4 | AP27: 5159905.3 | AQ27: 0 | AR27: 2376146.6 | AS27: 3317018.6 | AT27: 0 | AU27: 1446615.2 | AV27: 3196190.8 | AW27: 4278795.4 | AX27: 241687.35 | AY27: 758042.48 | AZ27: 2086552.4 | BA27: 1880173.8 | BB27: 10367597 | BC27: 7915435 | BD27: 370606.09 | BE27: 3108595.6 | BF27: 1654031.8 | BG27: 6135200.4 | BH27: 3027439.2 | BI27: 169546.5 | BJ27: 1815825.5 | BK27: 2371621.5 | BL27: 0 | BM27: 1228439.2 | BN27: 79035.883 | BO27: 0 | BP27: 4239707.6 | BQ27: 4640117.3 | BR27: 3612292.9 | BS27: 0 | BT27: 0 | BU27: 1051426.4 | BV27: 1287520 | BW27: 59989.08 | BX27: 2296644.3 | BY27: 287307.72 | BZ27: 184550.97 | CA27: 0 | CB27: 0 | CC27: 1642155.6 | CD27: 2361428 | CE27: 2461781.9 | CF27: 454449.35 | CG27: 5727267.1 | CI27: 81274.976 | CJ27: 401705.85 | CK27: 508069 | CL27: 1235500.6 | CN27: 22541.6
A28: Commercial customers | B28: 4.6999418e+08 | C28: 66513457 | D28: 30615553 | E28: 1.5075771e+08 | F28: 31946457 | G28: 33112866 | H28: 53359048 | I28: 0 | J28: 24248754 | K28: 21520286 | L28: 11021840 | M28: 173849.86 | N28: 47467572 | O28: 6463622.2 | P28: 33667848 | Q28: 0 | R28: 8442302.3 | S28: 6657582.2 | T28: 15342603 | U28: 22729985 | V28: 29018033 | W28: 78500592 | X28: 3707672.8 | Y28: 24883383 | Z28: 25547510 | AA28: 4347012.5 | AB28: 31727730 | AC28: 5451750.4 | AD28: 4479397.8 | AE28: 26125562 | AF28: 7863143.9 | AG28: 7358785.2 | AH28: 1812869.8 | AI28: 2606895.2 | AJ28: 8378743.1 | AK28: 3882648.3 | AL28: 47807368 | AM28: 57446382 | AN28: 3620218.9 | AO28: 5141698.8 | AP28: 14498818 | AQ28: 3853035.6 | AR28: 255708.71 | AS28: 30417312 | AT28: 2624937.7 | AU28: 5036236.3 | AV28: 7102616.2 | AW28: 2765409.4 | AX28: 14259369 | AY28: 0 | AZ28: 320806.01 | BA28: 2998939 | BB28: 0 | BC28: 14315684 | BD28: 0 | BE28: 0 | BF28: 4759838 | BG28: 13288067 | BH28: 938004.41 | BI28: 50863.95 | BJ28: 2184001.4 | BK28: 15031904 | BL28: 52540.7 | BM28: 356246.32 | BN28: 20253.865 | BO28: 0 | BP28: 4391432.3 | BQ28: 3084508.9 | BR28: 3406933 | BS28: 0 | BT28: 0 | BU28: 4387853 | BV28: 2522174.7 | BW28: 1825.637 | BX28: 1166926 | BY28: 1127958.3 | BZ28: 534306.64 | CA28: 0 | CB28: 0 | CC28: 0 | CD28: 1836701.7 | CE28: 0 | CF28: 0 | CG28: 7305873.7 | CI28: 406420.03 | CJ28: 27434.162 | CK28: 54272.797 | CL28: 1173838.1 | CN28: 12294.9
A29: Industries | B29: 30289337 | C29: 0 | D29: 20410388 | E29: 1000837.2 | F29: 0 | G29: 0 | H29: 18155501 | I29: 41066025 | J29: 0 | K29: 0 | L29: 20363429 | M29: 0 | N29: 0 | O29: 0 | P29: 1270049.5 | Q29: 0 | R29: 0 | S29: 0 | T29: 0 | U29: 147944.8 | V29: 2200584 | W29: 0 | X29: 1935237 | Y29: 2217815 | Z29: 8138152.5 | AA29: 3744.3271 | AB29: 7554074.4 | AC29: 3891.8736 | AD29: 2986298 | AE29: 0 | AF29: 7843332.3 | AG29: 0 | AH29: 26460.384 | AI29: 0 | AJ29: 0 | AK29: 49138.561 | AL29: 18791014 | AM29: 0 | AN29: 0 | AO29: 0 | AP29: 0 | AQ29: 0 | AR29: 2554372.2 | AS29: 0 | AT29: 0 | AU29: 0 | AV29: 0 | AW29: 0 | AX29: 0 | AY29: 0 | AZ29: 26179.311 | BA29: 87293.212 | BB29: 0 | BC29: 11717127 | BD29: 0 | BE29: 0 | BF29: 0 | BG29: 0 | BH29: 0 | BI29: 0 | BJ29: 0 | BK29: 1227664.6 | BL29: 0 | BM29: 0 | BN29: 0 | BO29: 0 | BP29: 0 | BQ29: 12798295 | BR29: 0 | BS29: 0 | BT29: 0 | BU29: 0 | BV29: 0 | BW29: 0 | BX29: 0 | BY29: 0 | BZ29: 0 | CA29: 0 | CB29: 0 | CC29: 0 | CD29: 0 | CE29: 0 | CF29: 0 | CG29: 0 | CI29: 70754.382 | CJ29: 0 | CK29: 0 | CL29: 0 | CN29: 0
A30: Kiosks | B30: 2.6567935e+08 | C30: 28205184 | D30: 36125444 | E30: 35523003 | F30: 528113.05 | G30: 612849.97 | H30: 225192.09 | I30: 3874825.2 | J30: 596566.21 | K30: 3277242 | L30: 16145831 | M30: 183709.1 | N30: 2202280.6 | O30: 19991.558 | P30: 15069623 | Q30: 0 | R30: 397744.42 | S30: 206126.38 | T30: 0 | U30: 1403581.3 | V30: 3054387.5 | W30: 427588.65 | X30: 0 | Y30: 191387.83 | Z30: 268896.33 | AA30: 17019669 | AB30: 0 | AC30: 389187.36 | AD30: 9538444.1 | AE30: 2931333.8 | AF30: 0 | AG30: 25416207 | AH30: 26079933 | AI30: 0 | AJ30: 440946.8 | AK30: 4913.8561 | AL30: 5195189.9 | AM30: 3828824.3 | AN30: 300613.19 | AO30: 746778.68 | AP30: 1381177.7 | AQ30: 959659.13 | AR30: 112262.36 | AS30: 9037751.8 | AT30: 0 | AU30: 1865814.2 | AV30: 355144.33 | AW30: 345504.95 | AX30: 161094.09 | AY30: 0 | AZ30: 1267113.7 | BA30: 1462482.2 | BB30: 0 | BC30: 2131509.8 | BD30: 87471.48 | BE30: 155878.98 | BF30: 10547061 | BG30: 3574668.7 | BH30: 286350.79 | BI30: 1694.8 | BJ30: 441906.54 | BK30: 409196.63 | BL30: 1102.95 | BM30: 12281.965 | BN30: 5677.9036 | BO30: 0 | BP30: 197737.02 | BQ30: 22713455 | BR30: 114070.69 | BS30: 0 | BT30: 0 | BU30: 926466.94 | BV30: 504466.45 | BW30: 4868.3654 | BX30: 0 | BY30: 212811.04 | BZ30: 6486.3574 | CA30: 0 | CB30: 0 | CC30: 1441388.1 | CD30: 262363.15 | CE30: 0 | CF30: 1769172.7 | CG30: 2588561.7 | CI30: 40637.488 | CJ30: 0 | CK30: 0 | CL30: 2003581.4 | CN30: 3152.1
