Workbook
Name _Toc368579723: SYB_2015_Table_7.2.1!$B$4
Name Products: [1]RPCA1!$A$2:$E$228

Sheet TOC
A1: Content
A3: Worksheet | B3: Content
A5: 2012
A6: Table 1 | B6: Water Asset Table, 2012
A7: Table 2 | B7: Water_Asset_Table_Data_&_Method, 2012
A8: Table 3 | B8: Water Asset Table, 2012 - Balanced
A9: Table 4 | B9: Water_PSUT_Table_Data_&_Method, 2012
A10: Table 5 | B10: PSUT: Physical Supply & Use Table Water (detailed), 2012
A11: Table 6 | B11: RBM&E-2017_Study
A12: Table 9 | B12: WA_PHYSICAL Water - PSUT, timeseries
A13: Table 10 | B13: NA_Economic_data, timeseries
A14: Table 11 | B14: NA_Economic_data, timeseries - Processed
A15: Table 12 | B15: NA_Labour_Force_Data, timeseries
A16: Table 13 | B16: NA_INTEGRATED: Labour - Economic - Water data, timeseries
A17: Table 14 | B17: Water Sector Analysis - Sheets
A19: Analysis & timeseries
B20: Check by Closing Stocks
B21: Asset trends Charts I
B22: Asset trends Charts II
B23: PSUT trends Charts
B24: PSUT trends Charts & ISIC breakdown
A26: Indices | B26: Indicators
B27: Indicators
B28: IRWR
B29: TRWR
B30: Water availability / capita
B31: SDG 6.4.1 - Water Use Efficiency
B32: SDG 6.4.1 - Water Use Efficiency - Time Series
B33: SDG - Water Resources
B34: SDG 6.4.2 - Water stress
A37: 2013
A38: Table 14-A | B38: Water Asset Table, 2013
A39: Table 14-B | B39: Water_Asset_Table_Data_&_Method, 2013
A40: Table 14-C | B40: Water Asset Table, 2013 - Balanced
A41: Table 14-D | B41: Water_PSUT_Table_Data_&_Method, 2013
A42: Table 14-E | B42: PSUT: Physical Supply & Use Table Water (detailed), 2013
A44: 2014
A45: Table 15-A | B45: Water Asset Table, 2014
A46: Table 15-B | B46: Water_Asset_Table_Data_&_Method, 2014
A47: Table 15-C | B47: Water Asset Table, 2014 - Balanced
A48: Table 15-D | B48: Water_PSUT_Table_Data_&_Method, 2014
A49: Table 15-E | B49: PSUT: Physical Supply & Use Table Water (detailed), 2014
A51: 2015
A52: Table 16-A | B52: Water Asset Table, 2015
A53: Table 16-B | B53: Water_Asset_Table_Data_&_Method, 2015
A54: Table 16-C | B54: Water Asset Table, 2015 - Balanced
A55: Table 16-D | B55: Water_PSUT_Table_Data_&_Method, 2015
A56: Table 16-E | B56: PSUT: Physical Supply & Use Table Water (detailed), 2015
A60: Notes | B60: Notes to the tabels
A65: Question on this publication can be send to XXXX@NISR putting it under reference number Rwanda-NCA_SEEA_Water_Accounts_2018.
A66: Our e-mailadres is: | B66: XXXX@NISR.Rw
A70: Explanation of symbols
A71: Empty cell = Figure not applicable
A72: . = Figure is unknown, insufficiently reliable or confidential
A73: …
A74: * = Provisional figure
A75: ** = Revised provisional figure
A76: 2012–2015 = 2012 to 2015 inclusive
A77: ….

Sheet 2012NWRMP
A1: 000m3 (Consumptive Water demand) | B1: Agriculture | I1: Mining | K1: Manufacturing | P1: Water
A2: Year 2012 | B2: Fish ponds | C2: Irr. RWH | D2: Irr. Marshlands | E2: Irr. Surface water | F2: Irr. Dam | G2: Irr. Gr. Water | H2: Livestock | I2: Mining WS | K2: Coffee Washing Station | M2: Industry WS | O2: Other manufacturing | P2: Hydropower for Electricity | Q2: Household Urban DWS | R2: Household Rural DWS | T2: Total (000m3/yr) | V2: Population in 2012 Census
A3: CKIV (Lake Kivu, 2,425 km²) | B3: 135 | C3: 0 | D3: 440 | E3: 0 | F3: 0 | G3: 0 | H3: 2597 | I3: 562 | K3: 27 | M3: 1123 | P3: 56 | Q3: 2359 | R3: 20891 | T3: =SUM(B3:S3) -> 28190 | V3: 1415418
A4: CRUS (Rusizi, 1.005 km²) | B4: 60 | C4: 0 | D4: 890 | E4: 0 | F4: 0 | G4: 0 | H4: 585 | I4: 127 | K4: 11 | M4: 253 | P4: 0 | Q4: 435 | R4: 4774 | T4: =SUM(B4:S4) -> 7135 | V4: 318048
A5: NNYU (Upper Nyabarongo, 3,348 km²) | B5: 225 | C5: 44 | D5: 629 | E5: 0 | F5: 520 | G5: 0 | H5: 3775 | I5: 579 | K5: 4 | M5: 1157 | P5: 0 | Q5: 3606 | R5: 20746 | T5: =SUM(B5:S5) -> 31285 | V5: 1425492
A6: NMUK (Mukungwa, 1,949 km²) | B6: 30 | C6: 0 | D6: 0 | E6: 0 | F6: 0 | G6: 0 | H6: 2501 | I6: 490 | K6: 0 | M6: 981 | P6: 158 | Q6: 5443 | R6: 15987 | T6: =SUM(B6:S6) -> 25590 | V6: 1048631
A7: NNYL (Lower Nyabarongo, 3.304 km²) | B7: 420 | C7: 73 | D7: 1973 | E7: 0 | F7: 5938 | G7: 0 | H7: 4310 | I7: 840 | K7: 11 | M7: 1680 | P7: 570 | Q7: 19302 | R7: 20728 | T7: =SUM(B7:S7) -> 55845 | V7: 2181940
A8: NAKN (Akanyaru, 3,402 km²) | B8: 270 | C8: 157 | D8: 2804 | E8: 342 | F8: 17891 | G8: 0 | H8: 3766 | I8: 544 | K8: 5 | M8: 1088 | P8: 0 | Q8: 6771 | R8: 17245 | T8: =SUM(B8:S8) -> 50883 | V8: 1447480
A9: NAKU (Upper Akagera, 3.053 km²) | B9: 210 | C9: 208 | D9: 850 | E9: 13780 | F9: 1196 | G9: 0 | H9: 2460 | I9: 432 | K9: 7 | M9: 865 | P9: 0 | Q9: 7000 | R9: 12624 | T9: =SUM(B9:S9) -> 39632 | V9: 1318379
A10: NAKL (Lower Akagera, 4.288 km²) | B10: 105 | C10: 204 | D10: 1200 | E10: 4800 | F10: 2200 | G10: 0 | H10: 2165 | I10: 202 | K10: 1 | M10: 403 | P10: 0 | Q10: 847 | R10: 7498 | T10: =SUM(B10:S10) -> 19625 | V10: 725068
A11: NMUV (Muvumba, 1,568 km²) | B11: 105 | C11: 121 | D11: 3940 | E11: 3200 | F11: 2481 | G11: 0 | H11: 1457 | I11: 231 | K11: 0 | M11: 462 | P11: 0 | Q11: 1688 | R11: 8117 | T11: =SUM(B11:S11) -> 21802 | V11: 725068
A14: TOTAL FOR RWANDA (000m3/yr) | B14: =SUM(B3:B13) -> 1560 | C14: =SUM(C3:C13) -> 807 | D14: =SUM(D3:D13) -> 12726 | E14: =SUM(E3:E13) -> 22122 | F14: =SUM(F3:F13) -> 30226 | G14: =SUM(G3:G13) -> 0 | H14: =SUM(H3:H13) -> 23616 | I14: =SUM(I3:I13) -> 4007 | ... K14: =SUM(K3:K13) -> 66 | M14: =SUM(M3:M13) -> 8012 | N14: =SUM(N3:N13) -> 0 | O14: =SUM(O3:O13) -> 0 | P14: =SUM(P3:P13) -> 784 | Q14: =SUM(Q3:Q13) -> 47451 | R14: =SUM(R3:R13) -> 128610 | S14: =SUM(S3:S13) -> 0 | T14: =SUM(T3:T13) -> 279987 | U14: Abstraction of water 2012 | V14: =SUM(V3:V13) -> 10605524
A16: Total per Sector | B16: Agriculture | D16: =B14+C14+D14+E14+F14+G14+H14 -> 91057 | H16: Mining | I16: =I14+J14 -> 4007 | K16: Industry | M16: =K14+M14 -> 8078 | O16: Electricity | P16: =P14 -> 784 | Q16: Water Supply | R16: =Q14+R14 -> 176061 | T16: =R16+P16+M16+I16+D16 -> 279987
A18: Assets Accounts | D18: =D16-C14 -> 90250 | R18: =R16*0.85 -> 149651.85
A20: Consumptive Water demand | B20: Agriculture
A21: Year 2012 | B21: Rainfall | D21: Evaporation loss | F21: Surface water runoff | H21: Surface-water volume storage | I21: Groundwater recharge | K21: Groundwater volume storage | M21: Renewable resource | N21: Catch. Area (km2) | O21: Population
B22: (mm/yr) | C22: (MCM) | D22: (mm/yr) | E22: (MCM) | F22: (mm/yr) | G22: (MCM) | H22: (MCM) | I22: (mm/yr) | J22: (MCM) | K22: (MCM) | M22: ['000 m³] | Q22: Runoff | R22: Renewable water
A23: CKIV (Lake Kivu, 2,425 km²) | B23: 1240 | C23: =B23*N23*1000000/1000/1000000 -> 3007 | D23: 870 | E23: 2109 | F23: 370 | G23: 898 | H23: 550000 | I23: 250 | J23: 606 | K23: 2400 | L23: =K23+J23+H23+G23+E23+C23 -> 559020 | M23: 898000 | N23: 2425 | O23: 1415418 | P23: =+I23*N23/1000 -> 606.25 | Q23: =B23-D23 -> 370 | R23: =+F23*N23 -> 897250 | T23: .
A24: CRUS (Rusizi, 1.005 km²) | B24: 1295 | C24: 1301 | D24: 865 | E24: 869 | F24: 430 | G24: 432 | I24: 268 | J24: 269 | K24: 5000 | L24: =K24+J24+H24+G24+E24+C24 -> 7871 | M24: 432000 | N24: 1005 | O24: 318048 | P24: =+I24*N24/1000 -> 269.34 | Q24: =B24-D24 -> 430 | R24: =+F24*N24 -> 432150
A25: NNYU (Upper Nyabarongo, 3,348 km²) | B25: 1365 | C25: 4570 | D25: 980 | E25: 3281 | F25: 385 | G25: 1289 | I25: 292 | J25: 978 | K25: 25110 | L25: =K25+J25+H25+G25+E25+C25 -> 35228 | M25: 1290000 | N25: 3348 | O25: 1425492 | P25: =+I25*N25/1000 -> 977.616 | Q25: =B25-D25 -> 385 | R25: =+F25*N25 -> 1288980
A26: NMUK (Mukungwa, 1,949 km²) | B26: 1315 | C26: 2563 | D26: 851 | E26: 1659 | F26: 464 | G26: 904 | H26: 3508 | I26: 322 | J26: 628 | K26: 4872 | L26: =K26+J26+H26+G26+E26+C26 -> 14134 | M26: 905000 | N26: 1949 | O26: 1048631 | P26: =+I26*N26/1000 -> 627.578 | Q26: =B26-D26 -> 464 | R26: =+F26*N26 -> 904336
A27: NNYL (Lower Nyabarongo, 3.304 km²) | B27: 1191 | C27: 3935 | D27: 919 | E27: 3036 | F27: 272 | G27: 899 | H27: 330 | I27: 165 | J27: 545 | K27: 8673 | L27: =K27+J27+H27+G27+E27+C27 -> 17418 | M27: 899000 | N27: 3304 | O27: 2181940 | P27: =+I27*N27/1000 -> 545.16 | Q27: =B27-D27 -> 272 | R27: =+F27*N27 -> 898688
A28: NAKN (Akanyaru, 3,402 km²) | B28: 1225 | C28: 4167 | D28: 990 | E28: 3369 | F28: 235 | G28: 798 | I28: 156 | J28: 531 | K28: 5103 | L28: =K28+J28+H28+G28+E28+C28 -> 13968 | M28: 798000 | N28: 3402 | O28: 1447480 | P28: =+I28*N28/1000 -> 530.712 | Q28: =B28-D28 -> 235 | R28: =+F28*N28 -> 799470
A29: NAKU (Upper Akagera, 3.053 km²) | B29: 925 | C29: 2824 | D29: 760 | E29: 2320 | F29: 165 | G29: 504 | I29: 115 | J29: 351 | K29: 4580 | L29: =K29+J29+H29+G29+E29+C29 -> 10579 | M29: 504000 | N29: 3053 | O29: 1318379 | P29: =+I29*N29/1000 -> 351.095 | Q29: =B29-D29 -> 165 | R29: =+F29*N29 -> 503745
A30: NAKL (Lower Akagera, 4.288 km²) | B30: 835 | C30: 3580 | D30: 624 | E30: 2676 | F30: 211 | G30: 905 | I30: 125 | J30: 536 | K30: 4824 | L30: =K30+J30+H30+G30+E30+C30 -> 12521 | M30: 907000 | N30: 4288 | O30: 725068 | P30: =+I30*N30/1000 -> 536 | Q30: =B30-D30 -> 211 | R30: =+F30*N30 -> 904768
A31: NMUV (Muvumba, 1,568 km²) | B31: 995 | C31: 1560 | D31: 872 | E31: 1367 | F31: 123 | G31: 193 | I31: 71 | J31: 111.6 | K31: 1565 | L31: =K31+J31+H31+G31+E31+C31 -> 4796.6 | M31: 193000 | N31: 1568 | O31: 725068 | P31: =+I31*N31/1000 -> 111.328 | Q31: =B31-D31 -> 123 | R31: =+F31*N31 -> 192864
R33: =SUM(R23:R32) -> 6822251
A34: TOTAL FOR RWANDA (000m3/yr) | B34: =AVERAGE(B23:B31) -> 1154 | C34: =SUM(C23:C33) -> 27507 | D34: =AVERAGE(D23:D31) -> 859 | E34: =SUM(E23:E33) -> 20686 | F34: =AVERAGE(F23:F31) -> 295 | G34: =SUM(G23:G33) -> 6822 | H34: =SUM(H23:H33) -> 553838 | I34: =SUM(I23:I33) -> 1764 | J34: =SUM(J23:J33) -> 4555.6 | K34: =SUM(K23:K33) -> 62127 | L34: =SUM(L23:L33) -> 675535.6 | M34: =SUM(M23:M33) -> 6826000 | N34: =SUM(N23:N33) -> 24342 | O34: =SUM(O23:O33) -> 10605524 | P34: 10192072 | Q34: from water storage report
M35: =+M34*1000 -> 6826000000
N36: =M35/P34 -> 669.73624 | O36: m3/ca/yr
N37: =+N36/365 -> 1.8348938 | O37: m3/ca/day
A38: Year 2012 | B38: Renewable % of Prec. | N38: =+N36*1000/365 -> 1834.8938 | O38: l/ca/day
B39: (mm/yr) | D39: (MCM) | I39: Water Available for recharge | M39: =(I34/1000)*N34 -> 42939.288 | N39: m3/ca/yr
A40: CKIV (Lake Kivu, 2,425 km²) | B40: =+B23-D23 -> 370 | C40: =+B40/B23 -> 0.2983871 | D40: =+C23-E23 -> 898 | E40: =+I23/F23 -> 0.67567568 | I40: Water Available for recharge | M40: =(J36*1000000)/O34 -> 0 | N40: m3/ca/yr
A41: CRUS (Rusizi, 1.005 km²) | B41: =+B24-D24 -> 430 | C41: =+B41/B24 -> 0.33204633 | D41: =+C24-E24 -> 432 | E41: =+I24/F24 -> 0.62325581 | I41: Water Available for recharge | M41: =(J36*1000000)/(N34*100) -> 0 | N41: m3/ha/yr
A42: NNYU (Upper Nyabarongo, 3,348 km²) | B42: =+B25-D25 -> 385 | C42: =+B42/B25 -> 0.28205128 | D42: =+C25-E25 -> 1289 | E42: =+I25/F25 -> 0.75844156
A43: NMUK (Mukungwa, 1,949 km²) | B43: =+B26-D26 -> 464 | C43: =+B43/B26 -> 0.35285171 | D43: =+C26-E26 -> 904 | E43: =+I26/F26 -> 0.69396552 | I43: =(I28/1000)*(N28) -> 530.712
A44: NNYL (Lower Nyabarongo, 3.304 km²) | B44: =+B27-D27 -> 272 | C44: =+B44/B27 -> 0.22837951 | D44: =+C27-E27 -> 899 | E44: =+I27/F27 -> 0.60661765
A45: NAKN (Akanyaru, 3,402 km²) | B45: =+B28-D28 -> 235 | C45: =+B45/B28 -> 0.19183673 | D45: =+C28-E28 -> 798 | E45: =+I28/F28 -> 0.66382979
A46: NAKU (Upper Akagera, 3.053 km²) | B46: =+B29-D29 -> 165 | C46: =+B46/B29 -> 0.17837838 | D46: =+C29-E29 -> 504 | E46: =+I29/F29 -> 0.6969697
A47: NAKL (Lower Akagera, 4.288 km²) | B47: =+B30-D30 -> 211 | C47: =+B47/B30 -> 0.25269461 | D47: =+C30-E30 -> 904 | E47: =+I30/F30 -> 0.59241706
A48: NMUV (Muvumba, 1,568 km²) | B48: =+B31-D31 -> 123 | C48: =+B48/B31 -> 0.12361809 | D48: =+C31-E31 -> 193 | E48: =+I31/F31 -> 0.57723577

Sheet Lakes
A1: Stocks:
B2: Table 4: Sampled Lakes Area Volume estimations.
B3: For the rest of the eastern valley lakes, an approximation was adopted based on the average depth obtained from the Ihema, Rumira and Mirayi Lakes.
B4: The estimated average depth used to estimate the storage capacities of the remaining valley lakes was 4.14 meters depth.
B5: Table 5 provides the results of this estimation. The majority of the existing lakes are located in the Akagera Upstream and Akagara Downstream catchments.
I7: ?
B9: # | C9: Type | D9: Name | E9: Area sq.m | F9: Area sq.m (m2) | G9: Volume m3 | H9: Volume m3 | I9: Average depth calculated m (check:) | J9: Catchment
B10: 1 | C10: Lake | D10: Kishanju | E10: 5985696259 | F10: 598569.63 | G10: 2,478,078.25 | H10: 2478078.2 | I10: =+H10/F10 -> 4.14 | J10: Akagera downstream
B11: 2 | C11: Lake | D11: Muhari | E11: 8461370451 | F11: 846137.05 | G11: 3,503,007.37 | H11: 3503007.4 | I11: =+H11/F11 -> 4.14 | J11: Akagera downstream
B12: 3 | C12: Lake | D12: N/A | E12: 6713741109 | F12: 671374.11 | G12: 2,779,488.82 | H12: 2779488.8 | I12: =+H12/F12 -> 4.14 | J12: Akagera downstream
B13: 4 | C13: Lake | D13: N/A | E13: 1240145434 | F13: 1240145.4 | G13: 5,134,202.10 | H13: 5134202.1 | I13: =+H13/F13 -> 4.14 | J13: Akagera downstream
B14: 5 | C14: Lake | D14: N/A | E14: 5240879242 | F14: 524087.92 | G14: 2,169,724.01 | H14: 2169724 | I14: =+H14/F14 -> 4.14 | J14: Akagera downstream
B15: 6 | C15: Lake | D15: Kivumba | E15: 11202626.62 | F15: 11202627 | G15: 46,378,874.23 | H15: 46378874 | I15: =+H15/F15 -> 4.14 | J15: Akagera downstream
B16: 7 | C16: Lake | D16: Hago | E16: 17871953.05 | F16: 17871953 | G16: 73,989,885.64 | H16: 73989886 | I16: =+H16/F16 -> 4.14 | J16: Akagera downstream
B17: 8 | C17: Lake | D17: Cyambwe | E17: 22759797.77 | F17: 22759798 | G17: 94,225,562.78 | H17: 94225563 | I17: =+H17/F17 -> 4.14 | J17: Akagera downstream
B18: 9 | C18: Lake | D18: Mihindi | E18: 10476026.54 | F18: 10476027 | G18: 43,370,749.89 | H18: 43370750 | I18: =+H18/F18 -> 4.14 | J18: Akagera downstream
B19: 10 | C19: Lake | D19: Gishanda | E19: 2926052741 | F19: 292605.27 | G19: 1,211,385.84 | H19: 1211385.8 | I19: =+H19/F19 -> 4.14 | J19: Akagera downstream
B20: 11 | C20: Lake | D20: Rwakibali | E20: 3406910728 | F20: 3406910.7 | G20: 14,104,610.41 | H20: 14104610 | I20: =+H20/F20 -> 4.14 | J20: Akagera downstream
B21: 12 | C21: Lake | D21: N/A | E21: 2045633791 | F21: 2045633.8 | G21: 8,468,923.89 | H21: 8468923.9 | I21: =+H21/F21 -> 4.14 | J21: Akagera downstream
B22: 13 | C22: Lake | D22: Nasho | E22: 12723775.17 | F22: 12723775 | G22: 52,676,429.19 | H22: 52676429 | I22: =+H22/F22 -> 4.14 | J22: Akagera downstream
B23: 14 | C23: Lake | D23: Rwampanga | E23: 10142174.6 | F23: 10142175 | G23: 41,988,602.84 | H23: 41988603 | I23: =+H23/F23 -> 4.14 | J23: Akagera downstream
B24: 15 | C24: Lake | D24: Rwanyakizinga | E24: 22617508.52 | F24: 22617509 | G24: 93,636,485.29 | H24: 93636485 | I24: =+H24/F24 -> 4.14 | J24: Akagera downstream
B25: 16 | C25: Lake | D25: Kanaga | E25: 4355688614 | F25: 435568.86 | G25: 1,803,255.09 | H25: 1803255.1 | I25: =+H25/F25 -> 4.14 | J25: Akagera downstream
B26: 17 | C26: Lake | D26: Mugesera | E26: 44325011.45 | F26: 44325011 | G26: 183,505,547.40 | H26: 1.8350555e+08 | I26: =+H26/F26 -> 4.14 | J26: Akagera upstream
B27: 18 | C27: Lake | D27: Gashanga | E27: 1772827.23 | F27: 1772827.2 | G27: 7,339,504.73 | H27: 7339504.7 | I27: =+H27/F27 -> 4.14 | J27: Akagera upstream
B28: 19 | C28: Lake | D28: Bilira | E28: 5473955696 | F28: 5473955.7 | G28: 22,662,176.58 | H28: 22662177 | I28: =+H28/F28 -> 4.14 | J28: Akagera upstream
B29: 20 | C29: Lake | D29: Sake | E29: 16311884 | F29: 16311884 | G29: 67,531,201.29 | H29: 67531201 | I29: =+H29/F29 -> 4.14 | J29: Akagera upstream
B30: 21 | C30: Lake | D30: Kilimbi | E30: 2692706497 | F30: 2692706.5 | G30: 11,147,804.90 | H30: 11147805 | I30: =+H30/F30 -> 4.14 | J30: Akagera upstream
B31: 22 | C31: Lake | D31: Nyabugongwe | E31: 3230302142 | F31: 323030.21 | G31: 1,337,345.09 | H31: 1337345.1 | I31: =+H31/F31 -> 4.14 | J31: Akagera upstream
B32: 23 | C32: Lake | D32: Nyakabingo | E32: 1352628823 | F32: 135262.88 | G32: 559,988.33 | H32: 559988.33 | I32: =+H32/F32 -> 4.14 | J32: Akagera upstream
B33: 24 | C33: Lake | D33: Nyakabingo | E33: 2527406657 | F33: 252740.67 | G33: 1,046,346.36 | H33: 1046346.4 | I33: =+H33/F33 -> 4.14 | J33: Akagera upstream
B34: 25 | C34: Lake | D34: Cyohoha Nord | E34: 1879638967 | F34: 1879639 | G34: 7,781,705.32 | H34: 7781705.3 | I34: =+H34/F34 -> 4.14 | J34: Akanyaru
B35: 26 | C35: Lake | D35: Karago | E35: 1003163.93 | F35: 1003163.9 | G35: 4,153,098.67 | H35: 4153098.7 | I35: =+H35/F35 -> 4.14 | J35: Mukungwa
B36: 27 | C36: Lake | D36: Ntosho | E36: 2353036096 | F36: 235303.61 | G36: 974,156.94 | H36: 974156.94 | I36: =+H36/F36 -> 4.14 | J36: Mukungwa
B37: 28 | C37: Lake | D37: Bihinga | E37: 2043391163 | F37: 204339.12 | G37: 845,963.94 | H37: 845963.94 | I37: =+H37/F37 -> 4.14 | J37: Mukungwa
B38: 29 | C38: Lake | D38: Nyirakigugu | E38: 1550853432 | F38: 155085.34 | G38: 642,053.32 | H38: 642053.32 | I38: =+H38/F38 -> 4.14 | J38: Mukungwa
B39: 30 | C39: Lake | D39: Muhazi | E39: 35439908.56 | F39: 35439909 | G39: 146,721,221.40 | H39: 1.4672122e+08 | I39: =+H39/F39 -> 4.14 | J39: Nyabarongo downstream
F41: =SUM(F10:F40) -> 2.2805975e+08 | H41: =SUM(H10:H39) -> 9.4416738e+08
C44: TRANS-BOUNDARY LAKES | N44: VOLUMES (M3)
B45: 1 | C45: Lake | D45: Kivu | E45: 101059567533697 | F45: 101059567533697 | G45: 247,595,940,457.5577 | H45: 247,595,940,457.5577 | I45: Kivu | J45: 101059567533697 | K45: =J45/10 -> 1.0105957e+13 | N45: 2.4759594e+11
B46: 2 | C46: Lake | D46: Cyohoha South | E46: 55939618817885 | F46: 55939618817885 | G46: 231,590,021.9060439 | H46: 231,590,021.9060439 | I46: Akanyaru | J46: 55939618817885 | K46: =J46/10 -> 5.5939619e+12 | N46: 2.3159002e+08
B47: 3 | C47: Lake | D47: Rweru | E47: 126158712774633 | F47: 126158712774633 | G47: 522,297,070.8869806 | H47: 522,297,070.8869806 | I47: Akagera Upstream | J47: 126158712774633 | K47: =J47/10 -> 1.2615871e+13 | N47: 5.2229707e+08
N49: =SUM(N45:N47) -> 2.4834983e+11
E50: m2
C51: Total surface of lakes | E51: 2.2805975e+08 | F51: Eastern valley lakes
E52: 80238900 | F52: Burera | N52: 8080471791
E53: 88172100 | F53: Ihema | N53: 1.252774e+08
E54: 26064900 | F54: Ruhondo | N54: 6.2742854e+08
E55: 3960200 | F55: Rumira | N55: 1742259.8
E56: 2642200 | F56: Mirayi | N56: 2778705.4
E57: 1.0105957e+09 | F57: Kivu | G57: =E57/1000000 -> 1010.5957 | H57: Only Rwanda part!! Total lake Kivu = 2700 km2
E58: 55939619 | F58: Cyohoha South | G58: =E58/1000000 -> 55.939619 | N58: =SUM(N52:N56) -> 8.8376987e+09
E59: 1.2615871e+08 | F59: Rweru | G59: =E59/1000000 -> 126.15871
E60: =SUM(E51:E59) -> 1.6218321e+09 | F60: Total
M61: TOTAL VOLUME OF NATURAL LAKES | N61: =SUM(H41,N49,N58) -> 2.5813169e+11
A65: Stock changes:
A66: Date: | B66: Date of measurement | C66: Water_Level (m) | D66: Surface area (m2) | E66: Range of Water_volume_layer (mln m3) | F66: Water_volume_change (T --> T+1) (m3)
A67: 2012-01-01 | B67: 2012-01-01T00:00:00.000+02:00 | D67: 1.2923885e+09 | E67: 2.3599169e+09 | F67: 0
A68: 2013-01-01 | B68: 2013-01-01T01:00:00.000+02:00 | D68: 1.2884283e+09 | E68: 1.9046801e+09 | F68: -4.4169296e+08
A69: 2014-01-01 | B69: 2014-01-01T00:00:00.000+02:00 | D69: 1.2923885e+09 | E69: 1.9340977e+09 | F69: 15873773
A70: 2014-08-10 | B70: 2014-08-10T00:00:00.000+02:00 | D70: 2.8179285e+08 | E70: 4.3959156e+08 | F70: -1.2009606e+08
D74: =D67 -> 1.2923885e+09 | E74: =E67 -> 2.3599169e+09
B75: Total surface of lakes | C75: Total | D75: 1.6218321e+09 | E75: 2.5813169e+11
D76: =+D74/D$75 -> 0.79686951 | E76: =+E74/E$75 -> 0.0091422982
D77: =+D75/D$75 -> 1
E79: TOTAL VOLUME OF NATURAL LAKES
E80: 2.5813169e+11

Sheet Rivers
B1: Stocks:
B3: Possible Methods:
B4: 1, First start from stocks in rivers from Rwanda Resources Masterplan 2012 (RWRMP2012) | D4: 1264 | E4: MCM
B8: 1, Discharge of 1 day for Rwanda (Easiest one based upon availability of the data as proposed by Mr. Gilbert). | D8: Questionable to use a water flow for estimating a stock
D9: ?????
B12: 2. Combine surface area of rivers (km2) * Average depth (m). Surface area is known from spatial data like from RCMRD for Rwanda 2010 or 2015 data (RCMRD landcover data). There are 4 categories of rivers. We woud liek to use those for making assessment. For the biggest rivers use the river depth data from the 6 or 10 hydro measuring stations. | D12: Surface of the water area (possible measurement like form NASA)
D13: Average weighed water depth
B16: 3. Combine length (km) of rivers times some measured average cross-section areas (m2) of rivers done in the country.
B20: 2nd and 3rd method allow to monitor change of the stock over time, showing change 2012 - 2013, etc.
B22: Flows (incoming & outgoing):
B24: Data from RNRA as measured at 3 rivers mainly Ruvubu river from Burundi; Muvumba river from Uganda at Kabare; and at Rusumo River from Uganda at Butaro station (Kinyababa river). (Ruvubu river at Rusumo (TO BE CONFIRMED BY IWRM IF INLOW OR NOT..?) from Burundi with 25.7087m3/s; Muvumba river coming from Kabare 16.3806m3/s) Total inflows: 42.089m3/s = 1,327,326,492.03m3/yr in 365days = 1,327.34Million m3/yr | D24: 25.7087m3/s; Muvumba river coming from Kabare 16.3806m3/s)
D25: Total inflows:
D26: 42.089 | E26: m3/s
E27: = 1,327,326,492.03m3/yr in 365days = 1,327.34Million m3/yr
B28: Kinyababa river at Burera data to be added ... and gauging station to be installed to measure and collect the data in future ...
A31: The observed increasing trends for St8 (Kagera catchment) might be attributed to the response (inflow) of Ruvubu river (av. Streamflow: 200 m3/s) from a large catchment (40%) in Burundi (Kyaruzi et al., 2005), and the catchment is beyond of this the study area analyzed.
A32: From Munyaneza et al., 2013
A34: Ruvubu river at Rusumo from Burundi with | E34: Average discharge | I34: 25.708682 | J34: m3/sec
A35: Muvumba river before entering to Akagera at Kabare | F35: Average dicharge 1966-1974: | I35: 8.0849032 | J35: m3/sec
A36: Rusumo Rugezi river at Butaro Ruhengeri | D36: Average dicharge 1956-1989: | I36: 1.3606323 | J36: m3/sec
A37: (Kinyababa river)
G38: Total inflows | I38: =SUM(I34:I37) -> 35.154217 | J38: m3/sec
N39: Seconds / year:
I40: =I38*3600*24*30*12 -> 1.0934368e+09 | J40: m3/yr | L40: =30*12 -> 360 | M40: days | N40: =(60*60)*24*30*12 -> 31104000
I42: =I40/1000000 -> 1093.4368 | J42: Million m3/yr
I45: =I38*3600*24*365 -> 1.1086234e+09 | J45: m3/yr | L45: =365 -> 365 | M45: days | N45: =(3600)*24*365 -> 31536000
I47: =I45/1000000 -> 1108.6234 | J47: Million m3/yr
I48: =I47/1000 -> 1.1086234 | J48: Billion m3/yr
H50: Compare to annual precipitation:
H51: 2012 | I51: 33.6 | J51: Billion m3/yr
H52: 2013 | I52: 31.934825 | J52: Billion m3/yr
H53: 2014 | I53: 31.966431 | J53: Billion m3/yr
H54: 2015 | I54: 32.027008 | J54: Billion m3/yr
H56: 2012 | I56: =+I$18/I51 -> 0 | J56: Share of External inflow in total water resources
H57: 2015 | I57: =+I$18/I54 -> 0
B58: Outflows
A59: Akanyaru river at Butare to Ngozi | D59: Average discharge 1955-2000: | H59: 13.149402 | I59: m3/sec
A60: Ruhwa river | H60: 2.7163968 | I60: m3/sec
A61: Rusizi river at Kamanyora
A62: Sebeya river to Lake Kivu at Gisenyi | E62: Average dicharge 1950-1997: | H62: 2.4240833 | I62: m3/sec | J62: =H62*3600*24*365 -> 76445891 | K62: =J62/1000000 -> 76.445891 | L62: mln m3
A64: Kagitumba river at Bugaragara | D64: Average dicharge 1970-1988: | H64: 13.671931 | I64: m3/sec
A65: Akagera river at Rusumo | D65: Average dicharge 1955-2000: | H65: 225.70868 | I65: m3/sec | K65: =H65-150 -> 75.708682
F67: Total Outflows | H67: =SUM(H59:H66) -> 257.6705 | I67: m3/sec
N68: Seconds / year:
H69: =H67*3600*24*30*12 -> 8.0145831e+09 | I69: m3/yr | K69: =30*12 -> 360 | L69: days | N69: =(60*60)*24*30*12 -> 31104000
H71: =H69/1000000 -> 8014.5831 | I71: Million m3/yr
H74: =H67*3600*24*365 -> 8.1258967e+09 | I74: m3/yr | K74: =365 -> 365 | L74: days | N74: =(3600)*24*365 -> 31536000
H76: =H74/1000000 -> 8125.8967 | I76: Million m3/yr
H77: =H76/1000 -> 8.1258967 | I77: Billion m3/yr

Sheet Artificial_reserv
B1: Stocks:
B2: Table: Artificial Reservoirs.
E4: Artificial water storages
H5: FINAL REPOR 2016; COMPANY: Senior Construction Company Ltd.; ASSESSMENT OF WATER STORAGE PER CAPITA IN RWANDA, 2016. | R5: Actual water stored in dams annually (1st of January YEAR - JJJJ):
D6: Large ponds (>120 cubic meters) | H6: Dams and Valley dams ( From UPDATED Report 2016! )
E7: YEAR ? | I7: Design Capacity (Reporting Year 2016 ?) | P7: Reservoir in operation | Q7: 2011 | R7: 2012 | S7: 2013 | T7: 2014 | U7: 2015 | V7: 2016 | W7: 2017 | X7: 2018
D8: District | E8: Total volume m3 | G8: Installation date of the Dam ? | H8: Name | I8: Volume m3 | P8: From Year 20JJ (?)
P9: Try to fill | Q9: Result from column K
D10: Gisagara | E10: 2040 | G10: ? | H10: Cyarubare | I10: 70000 | J10: For irrigation | P10: 2010 | Q10: =$I10 -> 70000 | R10: =$I10 -> 70000 | S10: =$I10 -> 70000 | T10: =$I10 -> 70000 | U10: =$I10 -> 70000 | V10: =$I10 -> 70000
D11: Nyanza | E11: 7320 | G11: ? | H11: Gacaca | I11: 2500000 | J11: For irrigation | Q11: =$I11 -> 2500000 | R11: =$I11 -> 2500000 | S11: =$I11 -> 2500000 | T11: =$I11 -> 2500000 | U11: =$I11 -> 2500000 | V11: =$I11 -> 2500000
D12: Muhanga | E12: 250 | G12: ? | H12: Kayonza-4 | I12: 1600000 | J12: For irrigation | Q12: =$I12 -> 1600000 | R12: =$I12 -> 1600000 | S12: =$I12 -> 1600000 | T12: =$I12 -> 1600000 | U12: =$I12 -> 1600000 | V12: =$I12 -> 1600000
D13: Nyamagabe | E13: 1080 | G13: ? | H13: Mahama | I13: 1000000 | J13: For irrigation | Q13: =$I13 -> 1000000 | R13: =$I13 -> 1000000 | S13: =$I13 -> 1000000 | T13: =$I13 -> 1000000 | U13: =$I13 -> 1000000 | V13: =$I13 -> 1000000
D14: Huye | E14: 1560 | G14: ? | H14: Ntende | I14: 700000 | J14: For irrigation | Q14: =$I14 -> 700000 | R14: =$I14 -> 700000 | S14: =$I14 -> 700000 | T14: =$I14 -> 700000 | U14: =$I14 -> 700000 | V14: =$I14 -> 700000
D15: Kamonyi | E15: 1440 | G15: ? | H15: Ruramira | I15: 1500000 | J15: For irrigation | Q15: =$I15 -> 1500000 | R15: =$I15 -> 1500000 | S15: =$I15 -> 1500000 | T15: =$I15 -> 1500000 | U15: =$I15 -> 1500000 | V15: =$I15 -> 1500000
D16: Rutsiro | E16: 120 | G16: ? | H16: Rurenge | I16: 2450000 | J16: For irrigation | Q16: =$I16 -> 2450000 | R16: =$I16 -> 2450000 | S16: =$I16 -> 2450000 | T16: =$I16 -> 2450000 | U16: =$I16 -> 2450000 | V16: =$I16 -> 2450000
D17: Ngororero | E17: 1320 | G17: ? | H17: Rwagitima-Ntende | I17: 700000 | J17: For irrigation | Q17: =$I17 -> 700000 | R17: =$I17 -> 700000 | S17: =$I17 -> 700000 | T17: =$I17 -> 700000 | U17: =$I17 -> 700000 | V17: =$I17 -> 700000
D18: Karongi | E18: 600 | G18: ? | H18: Rwangigo-Karangazi | I18: 3500000 | J18: For irrigation | T18: =$I18 -> 3500000 | U18: =$I18 -> 3500000 | V18: =$I18 -> 3500000
D19: Rulindo | E19: 2400 | G19: ? | H19: Rwinkwavu | I19: 1800000 | J19: For irrigation | Q19: =$I19 -> 1800000 | R19: =$I19 -> 1800000 | S19: =$I19 -> 1800000 | T19: =$I19 -> 1800000 | U19: =$I19 -> 1800000 | V19: =$I19 -> 1800000
D20: Gakenke | E20: 960 | G20: ? | H20: Rwinkwavu | I20: 4200000 | J20: For irrigation | Q20: =$I20 -> 4200000 | R20: =$I20 -> 4200000 | S20: =$I20 -> 4200000 | T20: =$I20 -> 4200000 | U20: =$I20 -> 4200000 | V20: =$I20 -> 4200000
D21: Gicumbi | E21: 2040 | G21: ? | H21: Bugugu | I21: 500000 | J21: For irrigation | Q21: =$I21 -> 500000 | R21: =$I21 -> 500000 | S21: =$I21 -> 500000 | T21: =$I21 -> 500000 | U21: =$I21 -> 500000 | V21: =$I21 -> 500000
D22: Kirehe | E22: 43520 | G22: ? | H22: Cyinuzi | I22: 318000 | J22: For irrigation | Q22: =$I22 -> 318000 | R22: =$I22 -> 318000 | S22: =$I22 -> 318000 | T22: =$I22 -> 318000 | U22: =$I22 -> 318000 | V22: =$I22 -> 318000
D23: Nyagatare | E23: 78880 | G23: ? | H23: Cyaruhogo | I23: 800000 | J23: For irrigation | Q23: =$I23 -> 800000 | R23: =$I23 -> 800000 | S23: =$I23 -> 800000 | T23: =$I23 -> 800000 | U23: =$I23 -> 800000 | V23: =$I23 -> 800000
D24: Kayonza | E24: 3960 | G24: ? | H24: Cyimpima | I24: 500000 | J24: For irrigation | Q24: =$I24 -> 500000 | R24: =$I24 -> 500000 | S24: =$I24 -> 500000 | T24: =$I24 -> 500000 | U24: =$I24 -> 500000 | V24: =$I24 -> 500000
D25: Rwamagana | E25: 6560 | G25: ? | H25: Gashara | I25: 360000 | J25: For irrigation | Q25: =$I25 -> 360000 | R25: =$I25 -> 360000 | S25: =$I25 -> 360000 | T25: =$I25 -> 360000 | U25: =$I25 -> 360000 | V25: =$I25 -> 360000
D26: Gatsibo | E26: 1930 | G26: ? | H26: Gitinga | I26: 850000 | J26: For irrigation | Q26: =$I26 -> 850000 | R26: =$I26 -> 850000 | S26: =$I26 -> 850000 | T26: =$I26 -> 850000 | U26: =$I26 -> 850000 | V26: =$I26 -> 850000
D27: Ngoma | E27: 1440 | G27: ? | H27: Kayonza | I27: 850000 | J27: For irrigation | Q27: =$I27 -> 850000 | R27: =$I27 -> 850000 | S27: =$I27 -> 850000 | T27: =$I27 -> 850000 | U27: =$I27 -> 850000 | V27: =$I27 -> 850000
D28: Gasabo | E28: 3240 | G28: ? | H28: Ngoma22 | I28: 960000 | J28: For irrigation | Q28: =$I28 -> 960000 | R28: =$I28 -> 960000 | S28: =$I28 -> 960000 | T28: =$I28 -> 960000 | U28: =$I28 -> 960000 | V28: =$I28 -> 960000
D29: Nyarugenge | E29: 120 | G29: ? | H29: Nyamugali | I29: 550000 | J29: For irrigation | Q29: =$I29 -> 550000 | R29: =$I29 -> 550000 | S29: =$I29 -> 550000 | T29: =$I29 -> 550000 | U29: =$I29 -> 550000 | V29: =$I29 -> 550000
G30: ? | H30: Rugenge, Karembo, Remera | I30: 530000 | J30: For irrigation | Q30: =$I30 -> 530000 | R30: =$I30 -> 530000 | S30: =$I30 -> 530000 | T30: =$I30 -> 530000 | U30: =$I30 -> 530000 | V30: =$I30 -> 530000
B31: Total | E31: =SUM(E10:E29) -> 160780 | G31: ? | H31: Rwamagana-34 | I31: 1000000 | J31: For irrigation | Q31: =$I31 -> 1000000 | R31: =$I31 -> 1000000 | S31: =$I31 -> 1000000 | T31: =$I31 -> 1000000 | U31: =$I31 -> 1000000 | V31: =$I31 -> 1000000
G32: ? | H32: Sagatare | I32: 280000 | J32: For irrigation | Q32: =$I32 -> 280000 | R32: =$I32 -> 280000 | S32: =$I32 -> 280000 | T32: =$I32 -> 280000 | U32: =$I32 -> 280000 | V32: =$I32 -> 280000
B33: Actual storage 01-01-YEAR, in Share of Storage capacity (ASSUMPTION) | E33: 0.9 | G33: ? | H33: Agasasa | I33: 374000 | J33: For irrigation | Q33: =$I33 -> 374000 | R33: =$I33 -> 374000 | S33: =$I33 -> 374000 | T33: =$I33 -> 374000 | U33: =$I33 -> 374000 | V33: =$I33 -> 374000
G34: ? | H34: Cyiri | I34: 950000 | J34: For irrigation | Q34: =$I34 -> 950000 | R34: =$I34 -> 950000 | S34: =$I34 -> 950000 | T34: =$I34 -> 950000 | U34: =$I34 -> 950000 | V34: =$I34 -> 950000
B35: Total water contained in artificial storage | E35: =+E31*E33 -> 144702 | G35: ? | H35: Kiruhura | I35: 60000 | J35: For irrigation | Q35: =$I35 -> 60000 | R35: =$I35 -> 60000 | S35: =$I35 -> 60000 | T35: =$I35 -> 60000 | U35: =$I35 -> 60000 | V35: =$I35 -> 60000
G36: ? | H36: Nyarubogo | I36: 450000 | J36: For irrigation | Q36: =$I36 -> 450000 | R36: =$I36 -> 450000 | S36: =$I36 -> 450000 | T36: =$I36 -> 450000 | U36: =$I36 -> 450000 | V36: =$I36 -> 450000
G37: ? | H37: Rwabikwano | I37: 150000 | J37: For irrigation | Q37: =$I37 -> 150000 | R37: =$I37 -> 150000 | S37: =$I37 -> 150000 | T37: =$I37 -> 150000 | U37: =$I37 -> 150000 | V37: =$I37 -> 150000
G38: ? | H38: Rwasave | I38: 120000 | J38: For irrigation | Q38: =$I38 -> 120000 | R38: =$I38 -> 120000 | S38: =$I38 -> 120000 | T38: =$I38 -> 120000 | U38: =$I38 -> 120000 | V38: =$I38 -> 120000
G39: ? | H39: Shyara/Nyarugenge | I39: 500000 | J39: For irrigation | Q39: =$I39 -> 500000 | R39: =$I39 -> 500000 | S39: =$I39 -> 500000 | T39: =$I39 -> 500000 | U39: =$I39 -> 500000 | V39: =$I39 -> 500000
G40: ? | H40: Kinoni 1 | I40: 250000 | J40: For irrigation | Q40: =$I40 -> 250000 | R40: =$I40 -> 250000 | S40: =$I40 -> 250000 | T40: =$I40 -> 250000 | U40: =$I40 -> 250000 | V40: =$I40 -> 250000
G41: ? | H41: Kinoni 2 | I41: 300000 | J41: For irrigation | Q41: =$I41 -> 300000 | R41: =$I41 -> 300000 | S41: =$I41 -> 300000 | T41: =$I41 -> 300000 | U41: =$I41 -> 300000 | V41: =$I41 -> 300000
G42: ? | H42: Kiliba | I42: 400000 | J42: For irrigation | Q42: =$I42 -> 400000 | R42: =$I42 -> 400000 | S42: =$I42 -> 400000 | T42: =$I42 -> 400000 | U42: =$I42 -> 400000 | V42: =$I42 -> 400000
G43: ? | H43: Kajevuba | I43: 100000 | J43: For irrigation | Q43: =$I43 -> 100000 | R43: =$I43 -> 100000 | S43: =$I43 -> 100000 | T43: =$I43 -> 100000 | U43: =$I43 -> 100000 | V43: =$I43 -> 100000
G44: ? | H44: Kanyonyomba A | I44: 500000 | J44: For irrigation | Q44: =$I44 -> 500000 | R44: =$I44 -> 500000 | S44: =$I44 -> 500000 | T44: =$I44 -> 500000 | U44: =$I44 -> 500000 | V44: =$I44 -> 500000
G45: ? | H45: Kanyonyomba B | I45: 30000 | J45: For irrigation | Q45: =$I45 -> 30000 | R45: =$I45 -> 30000 | S45: =$I45 -> 30000 | T45: =$I45 -> 30000 | U45: =$I45 -> 30000 | V45: =$I45 -> 30000
G46: ? | H46: Nyanza-23 | I46: 1820000 | J46: For irrigation | Q46: =$I46 -> 1820000 | R46: =$I46 -> 1820000 | S46: =$I46 -> 1820000 | T46: =$I46 -> 1820000 | U46: =$I46 -> 1820000 | V46: =$I46 -> 1820000
G47: ? | H47: Rusuli-Rwamuginga | I47: 180000 | J47: For irrigation | Q47: =$I47 -> 180000 | R47: =$I47 -> 180000 | S47: =$I47 -> 180000 | T47: =$I47 -> 180000 | U47: =$I47 -> 180000 | V47: =$I47 -> 180000
G48: 2013 ? | H48: Rugeramigozi - II | I48: ? | Q48: =$I48 -> ? | R48: =$I48 -> ? | S48: =$I48 -> ? | T48: =$I48 -> ? | U48: =$I48 -> ? | V48: =$I48 -> ?
G49: 2018 | H49: Muyanza | I49: 2660000 | J49: New dam for irrigation (under constr.) | P49: 2010 | Q49: =$I49 -> 2660000 | R49: =$I49 -> 2660000 | S49: =$I49 -> 2660000 | T49: =$I49 -> 2660000 | U49: =$I49 -> 2660000 | V49: =$I49 -> 2660000
G51: ? | H51: Rugeramigozi - I | I51: 270000 | J51: For irrigation & domestic water supply | Q51: =$I51 -> 270000 | R51: =$I51 -> 270000 | S51: =$I51 -> 270000 | T51: =$I51 -> 270000 | U51: =$I51 -> 270000 | V51: =$I51 -> 270000
G53: March 2015 | H53: Nyabarongo 1 | I53: 35673400 | J53: New dam for Hydro electric | T53: =$I53*(1/12) -> 2972783.3 | U53: =$I53 -> 35673400 | V53: =$I53 -> 35673400
B55: A. | C55: OPERATIONAL HYDROPOWER PLANTS AS OF DEC 2015
B56: 1 | C56: DOMESTIC ON GRID GENERATION
B57: No | C57: Plant Name | D57: Location | F57: Owner | G57: Year of Coming | H57: Name | I57: Volume m3 | J57: Installed Capacity in MW | K57: Net Head in m | L57: Design Flow (m3/s) | M57: Design Flow translated to year (m3/year) | N57: Derived volume (via Design Flow OR Instal MW! | P57: Reservoir in operation | Q57: 2011 | R57: 2012 | S57: 2013 | T57: 2014 | U57: 2015 | V57: 2016 | W57: 2017 | X57: 2018
D58: Sector/District | E58: Province
B59: 1 | C59: Mukungwa | D59: Gacaca/Musanze | E59: North | F59: GoR | G59: 1982 | I59: =N59 -> 9792698 | J59: 12 | K59: 102 | L59: 14 | M59: =+L59*(3600*24*365) -> 441504000 | N59: =M59/N$76 -> 9792698 | Q59: =$I59 -> 9792698 | R59: =$I59 -> 9792698 | S59: =$I59 -> 9792698 | T59: =$I59 -> 9792698 | U59: =$I59 -> 9792698 | V59: =$I59 -> 9792698
B60: 2 | C60: Ntaruka | D60: Kinoni/Burera | E60: North | G60: 1959 | I60: =N60 -> 8393741.2 | J60: 11.25 | K60: 112 | L60: 12 | M60: =+L60*(3600*24*365) -> 378432000 | N60: =M60/N$76 -> 8393741.2 | Q60: =$I60 -> 8393741.2 | R60: =$I60 -> 8393741.2 | S60: =$I60 -> 8393741.2 | T60: =$I60 -> 8393741.2 | U60: =$I60 -> 8393741.2 | V60: =$I60 -> 8393741.2
B61: 3 | C61: Gisenyi | D61: Gisenyi/Rubavu | E61: West | G61: 1957 | I61: =N61 -> 1528860 | J61: 1.2 | M61: =+L61*(3600*24*365) -> 0 | N61: =+N$75*(J61/J$75) -> 1528860 | Q61: =$I61 -> 1528860 | R61: =$I61 -> 1528860 | S61: =$I61 -> 1528860 | T61: =$I61 -> 1528860 | U61: =$I61 -> 1528860 | V61: =$I61 -> 1528860
B62: 4 | C62: Gihira | D62: Rugerero/Rubavu | E62: West | G62: 1984 | I62: =N62 -> 2293290 | J62: 1.8 | M62: =+L62*(3600*24*365) -> 0 | N62: =+N$75*(J62/J$75) -> 2293290 | Q62: =$I62 -> 2293290 | R62: =$I62 -> 2293290 | S62: =$I62 -> 2293290 | T62: =$I62 -> 2293290 | U62: =$I62 -> 2293290 | V62: =$I62 -> 2293290
B63: 5 | C63: Murunda | D63: Murunda/Rutsiro | E63: West | F63: REPRO Ltd | G63: Apri,2010 | I63: =N63 -> 127405 | J63: 0.1 | M63: =+L63*(3600*24*365) -> 0 | N63: =+N$75*(J63/J$75) -> 127405 | Q63: =$I63 -> 127405 | R63: =$I63 -> 127405 | S63: =$I63 -> 127405 | T63: =$I63 -> 127405 | U63: =$I63 -> 127405 | V63: =$I63 -> 127405
B64: 6 | C64: Rukarara 1 | D64: Kibilizi/Nyamagabe | E64: South | F64: Ngali Energy Ltd | G64: Dec,2010 | I64: =N64 -> 5595827.5 | J64: 9 | K64: 137 | L64: 8 | M64: =+L64*(3600*24*365) -> 252288000 | N64: =M64/N$76 -> 5595827.5 | Q64: =$I64 -> 5595827.5 | R64: =$I64 -> 5595827.5 | S64: =$I64 -> 5595827.5 | T64: =$I64 -> 5595827.5 | U64: =$I64 -> 5595827.5 | V64: =$I64 -> 5595827.5
B65: 7 | C65: Rugezi | D65: Butaro/Burera | E65: North | F65: GoR | G65: Mar,2011 | I65: =N65 -> 1608800.4 | J65: 2.2 | K65: 135 | L65: 2.3 | M65: =+L65*(3600*24*365) -> 72532800 | N65: =M65/N$76 -> 1608800.4 | Q65: =$I65*(6/12) -> 804400.2 | R65: =$I65 -> 1608800.4 | S65: =$I65 -> 1608800.4 | T65: =$I65 -> 1608800.4 | U65: =$I65 -> 1608800.4 | V65: =$I65 -> 1608800.4
B66: 8 | C66: Keya | D66: Nyundo/Rubavu | E66: West | G66: July,2011 | I66: =N66 -> 2098435.3 | J66: 2.2 | K66: 88 | L66: 3 | M66: =+L66*(3600*24*365) -> 94608000 | N66: =M66/N$76 -> 2098435.3 | Q66: =$I66*(6/12) -> 1049217.6 | R66: =$I66 -> 2098435.3 | S66: =$I66 -> 2098435.3 | T66: =$I66 -> 2098435.3 | U66: =$I66 -> 2098435.3 | V66: =$I66 -> 2098435.3
B67: 9 | C67: Nkora | D67: Kigeyo/Rutsiro | E67: West | F67: ENNY Ltd | G67: July,2011 | I67: =N67 -> 866354 | J67: 0.68 | M67: =+L67*(3600*24*365) -> 0 | N67: =+N$75*(J67/J$75) -> 866354 | Q67: =$I67*(6/12) -> 433177 | R67: =$I67 -> 866354 | S67: =$I67 -> 866354 | T67: =$I67 -> 866354 | U67: =$I67 -> 866354 | V67: =$I67 -> 866354
B68: 10 | C68: Cyimbili | D68: Kigeyo/Rutsiro | E68: West | G68: July,2011 | I68: =N68 -> 153885.25 | J68: 0.3 | L68: 0.22 | M68: =+L68*(3600*24*365) -> 6937920 | N68: =M68/N$76 -> 153885.25 | Q68: =$I68*(6/12) -> 76942.627 | R68: =$I68 -> 153885.25 | S68: =$I68 -> 153885.25 | T68: =$I68 -> 153885.25 | U68: =$I68 -> 153885.25 | V68: =$I68 -> 153885.25
B69: 11 | C69: Mazimeru | D69: Nyabimata/Nyaruguru | E69: South | G69: May,2012 | I69: =N69 -> 637025 | J69: 0.5 | M69: =+L69*(3600*24*365) -> 0 | N69: =+N$75*(J69/J$75) -> 637025 | R69: =$I69*(8/12) -> 424683.33 | S69: =$I69 -> 637025 | T69: =$I69 -> 637025 | U69: =$I69 -> 637025 | V69: =$I69 -> 637025
B70: 12 | C70: Nshili1 | D70: Runyombyi/Nyaruguru | E70: South | F70: GoR | G70: 41244 | I70: =N70 -> 769426.27 | J70: 0.4 | K70: 48 (Gross head) | L70: 1.1 | M70: =+L70*(3600*24*365) -> 34689600 | N70: =M70/N$76 -> 769426.27 | R70: =$I70*(1/12) -> 64118.856 | S70: =$I70 -> 769426.27 | T70: =$I70 -> 769426.27 | U70: =$I70 -> 769426.27 | V70: =$I70 -> 769426.27
B71: 13 | C71: Musarara | D71: /Musanze | E71: North | F71: Amahoro Energy Ltd | G71: February 2013 | I71: =N71 -> 509620 | J71: 0.4 | M71: =+L71*(3600*24*365) -> 0 | N71: =+N$75*(J71/J$75) -> 509620 | S71: =$I71*(11/12) -> 467151.67 | T71: =$I71 -> 509620 | U71: =$I71 -> 509620 | V71: =$I71 -> 509620
B72: 14 | C72: Mukungwa 2 | D72: Nkotsi/Musanze | E72: North | F72: GoR | G72: May 2013 | I72: =N72 -> 7484419.2 | J72: 2.5 | K72: 32 | L72: 10.7 | M72: =+L72*(3600*24*365) -> 337435200 | N72: =M72/N$76 -> 7484419.2 | S72: =$I72*(8/12) -> 4989612.8 | T72: =$I72 -> 7484419.2 | U72: =$I72 -> 7484419.2 | V72: =$I72 -> 7484419.2
B73: 15 | C73: Rukarara 2 | D73: Uwinkingi/Nyamagabe | E73: South | F73: GOR | G73: 41730 | I73: =N73 -> 3917079.2 | J73: 2.2 | K73: 50.74 | L73: 5.6 | M73: =+L73*(3600*24*365) -> 176601600 | N73: =M73/N$76 -> 3917079.2 | T73: =$I73*(9/12) -> 2937809.4 | U73: =$I73 -> 3917079.2 | V73: =$I73 -> 3917079.2
B74: 16 | C74: Giciye | D74: ……../Nyabihu | E74: West | F74: RMT | G74: June 2014 | I74: =N74 -> 1678748.2 | J74: 4 | K74: 114 | L74: 2.4 | M74: =+L74*(3600*24*365) -> 75686400 | N74: =M74/N$76 -> 1678748.2 | T74: =$I74*(7/12) -> 979269.8 | U74: =$I74 -> 1678748.2 | V74: =$I74 -> 1678748.2
B75: 17 | C75: Nyabarongo 1 | D75: Mushishiro/Muhanga | E75: South | F75: GoR | G75: 41974 | J75: 28 | K75: 63 | L75: 51 | M75: =+L75*(3600*24*365) -> 1608336000 | N75: =I53 -> 35673400 | T75: =$I75*(1/12) -> 0 | U75: =$I75 -> 0 | V75: =$I75 -> 0
B76: 3 | C76: OFF GRID POWER PLANTS UNDER OPERATION | M76: ratio: | N76: =+M75/N75 -> 45.085021
B77: No | C77: Plant Name | D77: Location | G77: Year of operation | H77: Name | I77: Volume m3 | J77: Installed Capacity in MW | K77: Net Head in m | L77: Design Flow (m3/s) | M77: Design Flow translated to year (m3/year) | N77: Derived volume (via Design Flow OR Instal MW!
B78: 1 | C78: Nyamyotsi I | D78: Rugera/Nyabihu | E78: West | G78: 2007 | I78: =N78 -> 127405 | J78: 0.1 | N78: =+N$75*(J78/J$75) -> 127405 | Q78: =$I78 -> 127405 | R78: =$I78 -> 127405 | S78: =$I78 -> 127405 | T78: =$I78 -> 127405 | U78: =$I78 -> 127405 | V78: =$I78 -> 127405
B79: 2 | C79: Mutobo | D79: Nkotsi/Musanze | E79: North | G79: 2009 | I79: =N79 -> 254810 | J79: 0.2 | N79: =+N$75*(J79/J$75) -> 254810 | Q79: =$I79 -> 254810 | R79: =$I79 -> 254810 | S79: =$I79 -> 254810 | T79: =$I79 -> 254810 | U79: =$I79 -> 254810 | V79: =$I79 -> 254810
B80: 3 | C80: Agatobwe | D80: Ngoma/Nyaruguru | E80: South | G80: 2010 | I80: =N80 -> 254810 | J80: 0.2 | N80: =+N$75*(J80/J$75) -> 254810 | Q80: =$I80 -> 254810 | R80: =$I80 -> 254810 | S80: =$I80 -> 254810 | T80: =$I80 -> 254810 | U80: =$I80 -> 254810 | V80: =$I80 -> 254810
B81: 4 | C81: Nyamyotsi II | D81: Rugera/Nyabihu | E81: West | F81: Private | G81: 2011 | I81: =N81 -> 127405 | J81: 0.1 | N81: =+N$75*(J81/J$75) -> 127405 | Q81: =$I81*(6/12) -> 63702.5 | R81: =$I81 -> 127405 | S81: =$I81 -> 127405 | T81: =$I81 -> 127405 | U81: =$I81 -> 127405 | V81: =$I81 -> 127405
B82: 5 | C82: Janja | D82: Mugunga/Gakenke | E82: North | G82: 41153 | I82: =N82 -> 254810 | J82: 0.2 | K82: 78 | L82: 0.375 | N82: =+N$75*(J82/J$75) -> 254810 | R82: =$I82*(4/12) -> 84936.667 | S82: =$I82 -> 254810 | T82: =$I82 -> 254810 | U82: =$I82 -> 254810 | V82: =$I82 -> 254810
B83: 6 | C83: Nyabahanga | D83: Gitesi/Karongi | E83: West | G83: 41153 | I83: =N83 -> 254810 | J83: 0.2 | K83: 44(Gross head) | L83: 0.7 | N83: =+N$75*(J83/J$75) -> 254810 | R83: =$I83*(4/12) -> 84936.667 | S83: =$I83 -> 254810 | T83: =$I83 -> 254810 | U83: =$I83 -> 254810 | V83: =$I83 -> 254810
B84: 7 | C84: Nyirabuhombohombo | D84: Macuba/Nyamasheke | E84: West | G84: January 2013 | I84: =N84 -> 637025 | J84: 0.5 | K84: 81 | L84: 0.9 | N84: =+N$75*(J84/J$75) -> 637025 | S84: =$I84*(12/12) -> 637025 | T84: =$I84 -> 637025 | U84: =$I84 -> 637025 | V84: =$I84 -> 637025
B85: 8 | C85: Gashashi | D85: Kigeyo/Rutsiro | E85: West | G85: March 2013 | I85: =N85 -> 254810 | J85: 0.2 | K85: 112( Gross head ) | L85: 0.29 | N85: =+N$75*(J85/J$75) -> 254810 | S85: =$I85*(10/12) -> 212341.67 | T85: =$I85 -> 254810 | U85: =$I85 -> 254810 | V85: =$I85 -> 254810
B86: 2 | C86: FROM RUSIZI RIVER/ Imported
B87: No | C87: Source Name | D87: Location | F87: Owner | G87: Year of operation | J87: Rwanda quota in MW | M87: Type
B88: 1 | C88: Rusizi I | D88: Mururu/Rusizi | E88: West | F88: SNEL | G88: 1957 | I88: =N88 -> 4459175 | J88: 3.5 | M88: Hydro | N88: =+N$75*(J88/J$75) -> 4459175 | Q88: =$I88 -> 4459175 | R88: =$I88 -> 4459175 | S88: =$I88 -> 4459175 | T88: =$I88 -> 4459175 | U88: =$I88 -> 4459175 | V88: =$I88 -> 4459175
B89: 2 | C89: Rusizi II | D89: Mururu/Rusizi | E89: West | F89: SINELAC | G89: 1989 | I89: =N89 -> 15288600 | J89: 12 | M89: Hydro | N89: =+N$75*(J89/J$75) -> 15288600 | Q89: =$I89 -> 15288600 | R89: =$I89 -> 15288600 | S89: =$I89 -> 15288600 | T89: =$I89 -> 15288600 | U89: =$I89 -> 15288600 | V89: =$I89 -> 15288600
F93: Total Water Storage capacity (Design capacity) | I93: =SUM(I10:I91) -> 1.4167467e+08 | L93: Total Water Storage capacity (Design capacity) | Q93: =SUM(Q10:Q54,Q59:Q91) -> 83676062 | R93: =SUM(R10:R54,R59:R91) -> 86762177 | S93: =SUM(S10:S54,S59:S91) -> 94325704 | T93: =SUM(T10:T54,T59:T91) -> 1.0729531e+08 | U93: =SUM(U10:U54,U59:U91) -> 1.4167467e+08 | V93: =SUM(V10:V54,V59:V91) -> 1.4167467e+08 | W93: =SUM(W10:W54,W59:W91) -> 0 | X93: =SUM(X10:X54,X59:X91) -> 0
F95: Reduction % from design capacity to actual capacity (ASSUMPTION), Mainly due to sedimentation ! | I95: =+(100%-10%) -> 0.9 | L95: Reduction % from design capacity to actual capacity (ASSUMPTION), Mainly due to sedimentation ! | Q95: =+(100%-10%) -> 0.9 | R95: =+(100%-10%) -> 0.9 | S95: =+(100%-10%) -> 0.9 | T95: =+(100%-10%) -> 0.9 | U95: =+(100%-10%) -> 0.9 | V95: =+(100%-10%) -> 0.9 | W95: =+(100%-10%) -> 0.9 | X95: =+(100%-10%) -> 0.9
F97: Total Water Storage capacity (Actual Capacity, due to sedimentation) | I97: =+(I93*I95) -> 1.2750721e+08 | L97: Total Water Storage capacity (Actual Capacity, due to sedimentation) | Q97: =+(Q93*Q95) -> 75308455 | R97: =+(R93*R95) -> 78085959 | S97: =+(S93*S95) -> 84893134 | T97: =+(T93*T95) -> 96565779 | U97: =+(U93*U95) -> 1.2750721e+08 | V97: =+(V93*V95) -> 1.2750721e+08 | W97: =+(W93*W95) -> 0 | X97: =+(X93*X95) -> 0
F99: Actual storage 01-01-YEAR, in Share of Actual Storage capacity (ASSUMPTION), dependng on weather in that year (dry or wet, etc.) | I99: =+(80%) -> 0.8 | L99: Actual storage 01-01-YEAR, in Share of Actual Storage capacity (ASSUMPTION), dependng on weather in that year (dry or wet, etc.) | Q99: =+(80%) -> 0.8 | R99: =+(80%) -> 0.8 | S99: =+(80%) -> 0.8 | T99: =+(80%) -> 0.8 | U99: =+(80%) -> 0.8 | V99: =+(80%) -> 0.8 | W99: =+(80%) -> 0.8 | X99: =+(80%) -> 0.8
F101: Total reduction fromm design cap. To actual water stored | I101: =+I95*I99 -> 0.72 | L101: Total reduction fromm design cap. To actual water stored | Q101: =+Q95*Q99 -> 0.72 | R101: =+R95*R99 -> 0.72 | S101: =+S95*S99 -> 0.72 | T101: =+T95*T99 -> 0.72 | U101: =+U95*U99 -> 0.72 | V101: =+V95*V99 -> 0.72 | W101: =+W95*W99 -> 0.72 | X101: =+X95*X99 -> 0.72
H103: Total Water Actually stored | I103: =+(I97*I99) -> 1.0200577e+08 | M103: Total Water Actually stored | Q103: =+(Q97*Q99) -> 60246764 | R103: =+(R97*R99) -> 62468768 | S103: =+(S97*S99) -> 67914507 | T103: =+(T97*T99) -> 77252623 | U103: =+(U97*U99) -> 1.0200577e+08 | V103: =+(V97*V99) -> 1.0200577e+08 | W103: =+(W97*W99) -> 0 | X103: =+(X97*X99) -> 0
Q104: =+Q103/Q93 -> 0.72 | R104: =+R103/R93 -> 0.72
F107: Total artificial water storage CAPACITY | H107: m3 | I107: =SUM($E31,I93) -> 1.4183545e+08 | N107: Total artificial water storage CAPACITY | P107: m3 | Q107: =SUM($E31,Q93) -> 83836842 | R107: =SUM($E31,R93) -> 86922957 | S107: =SUM($E31,S93) -> 94486484 | T107: =SUM($E31,T93) -> 1.0745609e+08 | U107: =SUM($E31,U93) -> 1.4183545e+08 | V107: =SUM($E31,V93) -> 1.4183545e+08 | W107: =SUM($E31,W93) -> 160780 | X107: =SUM($E31,X93) -> 160780
H108: Million m3 | I108: =I107/1000000 -> 141.83545 | P108: Million m3 | Q108: =Q107/1000000 -> 83.836842 | R108: =R107/1000000 -> 86.922957 | S108: =S107/1000000 -> 94.486484 | T108: =T107/1000000 -> 107.45609 | U108: =U107/1000000 -> 141.83545 | V108: =V107/1000000 -> 141.83545 | W108: =W107/1000000 -> 0.16078 | X108: =X107/1000000 -> 0.16078
F111: Total water contained in artificial storage | H111: m3 | I111: =SUM($E35,I103) -> 1.0215047e+08 | N111: Total water contained in artificial storage | P111: m3 | Q111: =SUM($E35,Q103) -> 60391466 | R111: =SUM($E35,R103) -> 62613470 | S111: =SUM($E35,S103) -> 68059209 | T111: =SUM($E35,T103) -> 77397325 | U111: =SUM($E35,U103) -> 1.0215047e+08 | V111: =SUM($E35,V103) -> 1.0215047e+08 | W111: =SUM($E35,W103) -> 144702 | X111: =SUM($E35,X103) -> 144702
H112: Million m3 | I112: =I111/1000000 -> 102.15047 | P112: Million m3 | Q112: =Q111/1000000 -> 60.391466 | R112: =R111/1000000 -> 62.61347 | S112: =S111/1000000 -> 68.059209 | T112: =T111/1000000 -> 77.397325 | U112: =U111/1000000 -> 102.15047 | V112: =V111/1000000 -> 102.15047 | W112: =W111/1000000 -> 0.144702 | X112: =X111/1000000 -> 0.144702

Sheet GW&SOILW_2012
A1: Improved Water exchanged between the environment and the economy (abstractions) and within the economy (supply within the economy) for year 2012 based on NWRMP in 103 m3
A3: Water Stock calculation (1st of January for opening stock) & For closing stock 31 december of closing stock or simply 1st of January next year.
A4: Improved physical asset account for water resources Year 2012 in Million m3 | K4: Improved physical asset account for water resources Year 2013 in Million m3 | U4: Improved physical asset account for water resources Year 2014 in Million m3 | AE4: Improved physical asset account for water resources Year 2015 in Million m3
A7: Source: Land Use Matrix (Land Accounts results) | K7: Source: Land Use Matrix (Land Accounts results) | U7: Source: Land Use Matrix (Land Accounts results) | AE7: Source: Land Use Matrix (Land Accounts results)
C8: 26338 | D8: Km2 | E8: Rwanda size | M8: 26338 | N8: Km2 | O8: Rwanda size | W8: 26338 | X8: Km2 | Y8: Rwanda size | AG8: 26338 | AH8: Km2 | AI8: Rwanda size
C9: =C15+C16+C17+C18 -> 1553540.8 | D9: ha | E9: Total area of Agriculture sector | M9: =M15+M16+M17+M18 -> 1553540.8 | N9: ha | O9: Total area of Agriculture sector | W9: =W15+W16+W17+W18 -> 1563288.2 | X9: ha | Y9: Total area of Agriculture sector | AG9: =AG15+AG16+AG17+AG18 -> 1565439.2 | AH9: ha | AI9: Total area of Agriculture sector
C10: 1274 | D10: mm/yr | E10: Precipitation | G10: Source: Meteo Rwanda from 85 rain gauge stations countrywide | M10: 1212 | N10: mm/yr | O10: Precipitation | Q10: Source: Meteo Rwanda from 81 rain gauge stations countrywide | W10: 1213.7 | X10: mm/yr | Y10: Precipitation | AA10: Source: Meteo Rwanda from 59 rain gauge stations countrywide | AG10: 1260.4 | AH10: mm/yr | AI10: Precipitation | AK10: Source: Meteo Rwanda from 51 rain gauge stations countrywide
C11: 860 | D11: mm/yr | E11: Evapotranspiration | G11: Source: NWRMP, 2015 and Meteo Rwanda | M11: 824 | N11: mm/yr | O11: Evapotranspiration | Q11: Source: NWRMP, 2015 and Meteo Rwanda | W11: 850 | X11: mm/yr | Y11: Evapotranspiration | AA11: Source: Meteo Rwanda | AG11: 870 | AH11: mm/yr | AI11: Evapotranspiration | AK11: Source: Meteo Rwanda
C12: =(C9*10000*C11)/1000 -> 1.3360451e+10 | D12: m3 | M12: =+M9*10000*M11/1000 -> 1.2801176e+10 | N12: m3 | W12: =+W9*10000*W11/1000 -> 1.328795e+10 | X12: m3 | AG12: =+AG9*10000*AG11/1000 -> 1.3619321e+10 | AH12: m3
C13: =+C12/1000 -> 13360451 | D13: ' 000 m3 | G13: =C11/C10 -> 0.67503925 | M13: =+M12/1000 -> 12801176 | N13: ' 000 m3 | W13: =+W12/1000 -> 13287950 | X13: ' 000 m3 | AG13: =+AG12/1000 -> 13619321 | AH13: ' 000 m3 | AN13: =AG10*0.69 -> 869.676
B14: % | C14: =+C13/1000 -> 13360.451 | D14: MCM of ET | L14: % | M14: =+M13/1000 -> 12801.176 | N14: MCM of ET | Q14: From Land Use table we have: | V14: % | W14: =+W13/1000 -> 13287.95 | X14: MCM of ET | AF14: % | AG14: =+AG13/1000 -> 13619.321 | AH14: MCM of ET
A15: =B15*C$13 -> 10684321 | B15: =C15/C$9 -> 0.79969767 | C15: =B31 -> 1242362.9 | D15: Agriculture (crop/irrigation) | K15: =L15*M$13 -> 10237071 | L15: =M15/M$9 -> 0.79969767 | M15: =L31 -> 1242362.9 | N15: Agriculture (crop/irrigation) | U15: =V15*W$13 -> 10635036 | V15: =W15/W$9 -> 0.80035194 | W15: =V31 -> 1251180.8 | X15: Agriculture (crop/irrigation) | AE15: =AF15*AG$13 -> 10903752 | AF15: =AG15/AG$9 -> 0.80060911 | AG15: =AF31 -> 1253304.9 | AH15: Agriculture (crop/irrigation)
A16: =B16*C$13 -> 1035825.1 | B16: =C16/C$9 -> 0.077529206 | C16: =B37 -> 120444.78 | D16: Livestock | K16: =L16*M$13 -> 992465.01 | L16: =M16/M$9 -> 0.077529206 | M16: =L37 -> 120444.78 | N16: Livestock | U16: =V16*W$13 -> 1007952.5 | V16: =W16/W$9 -> 0.075854631 | W16: =V37 -> 118582.65 | X16: Livestock | AD16: =W10*0.7 -> 849.59 | AE16: =AF16*AG$13 -> 1031634.9 | AF16: =AG16/AG$9 -> 0.075747897 | AG16: =AF37 -> 118578.73 | AH16: Livestock
A17: =B17*C$13 -> 1639261.6 | B17: =C17/C$9 -> 0.12269508 | C17: =B35 -> 190611.82 | D17: Forest | K17: =L17*M$13 -> 1570641.4 | L17: =M17/M$9 -> 0.12269508 | M17: =L35 -> 190611.82 | N17: Forest | U17: =V17*W$13 -> 1643948 | V17: =W17/W$9 -> 0.1237172 | W17: =V35 -> 193405.64 | X17: Forest | AE17: =AF17*AG$13 -> 1682829.5 | AF17: =AG17/AG$9 -> 0.12356192 | AG17: =AF35 -> 193428.68 | AH17: Forest
A18: =B18*C$13 -> 1042.6277 | B18: =C18/C$9 -> 7.803836e-05 | C18: =B34 -> 121.23578 | D18: Fishing | K18: =L18*M$13 -> 998.98279 | L18: =M18/M$9 -> 7.803836e-05 | M18: =L34 -> 121.23578 | N18: Fishing | U18: =V18*W$13 -> 1012.888 | V18: =W18/W$9 -> 7.6226054e-05 | W18: =V34 -> 119.16329 | X18: Fishing | AE18: =AF18*AG$13 -> 1104.1485 | AF18: =AG18/AG$9 -> 8.1072216e-05 | AG18: =AF34 -> 126.91362 | AH18: Fishing
A20: However, Soil water for 2012 is | B20: =A15+A17+A16 -> 13359408 | C20: 000'm3 | K20: However, Soil water for 2013 is | L20: =K15+K17+K16 -> 12800177 | M20: 000'm3 | U20: However, Soil water for 2014 is | V20: =U15+U17+U16 -> 13286937 | W20: 000'm3 | AE20: However, Soil water for 2015 is | AF20: =AE15+AE17+AE16 -> 13618217 | AG20: 000'm3
A22: Areas (ha) for 2012 | C22: Actual ET (mm/y) | D22: ET per sector | E22: Actual ET (m3/y) | F22: Actual ET ("000"m3/y) | K22: Areas (ha) for 2013 | M22: Actual ET (mm/y) | N22: ET per sector | O22: Actual ET (m3/y) | P22: Actual ET ("000"m3/y) | U22: Areas (ha) for 2014 | W22: Actual ET (mm/y) | X22: ET per sector | Y22: Actual ET (m3/y) | Z22: Actual ET ("000"m3/y) | AE22: Areas (ha) for 2012 | AG22: Actual ET (mm/y) | AH22: ET per sector | AI22: Actual ET (m3/y) | AJ22: Actual ET ("000"m3/y)
A23: =C15 -> 1242362.9 | B23: Agriculture (crop/irrigation) | C23: 860 | D23: =A23*C23 -> 1.0684321e+09 | E23: =D23*10000/1000 -> 1.0684321e+10 | F23: =E23/1000 -> 10684321 | K23: 1242362.9 | L23: Agriculture (crop/irrigation) | M23: 824 | N23: =K23*M23 -> 1.0237071e+09 | O23: =N23*10000/1000 -> 1.0237071e+10 | P23: =O23/1000 -> 10237071 | U23: =V31 -> 1251180.8 | V23: Agriculture (crop/irrigation) | W23: 850 | X23: =U23*W23 -> 1.0635036e+09 | Y23: =X23*10000/1000 -> 1.0635036e+10 | Z23: =Y23/1000 -> 10635036 | AE23: =AF31 -> 1253304.9 | AF23: Agriculture (crop/irrigation) | AG23: 870 | AH23: =AE23*AG23 -> 1.0903752e+09 | AI23: =AH23*10000/1000 -> 1.0903752e+10 | AJ23: =AI23/1000 -> 10903752
A24: =C16 -> 120444.78 | B24: Livestock | C24: 860 | D24: =A24*C24 -> 1.0358251e+08 | E24: =D24*10000/1000 -> 1.0358251e+09 | F24: =E24/1000 -> 1035825.1 | K24: 120444.78 | L24: Livestock | M24: 824 | N24: =K24*M24 -> 99246499 | O24: =N24*10000/1000 -> 9.9246499e+08 | P24: =O24/1000 -> 992464.99 | U24: =V37 -> 118582.65 | V24: Livestock | W24: 850 | X24: =U24*W24 -> 1.0079525e+08 | Y24: =X24*10000/1000 -> 1.0079525e+09 | Z24: =Y24/1000 -> 1007952.5 | AE24: =AF37 -> 118578.73 | AF24: Livestock | AG24: 870 | AH24: =AE24*AG24 -> 1.0316349e+08 | AI24: =AH24*10000/1000 -> 1.0316349e+09 | AJ24: =AI24/1000 -> 1031634.9
A25: =C17 -> 190611.82 | B25: Forest | C25: 860 | D25: =A25*C25 -> 1.6392616e+08 | E25: =D25*10000/1000 -> 1.6392616e+09 | F25: =E25/1000 -> 1639261.6 | K25: 190611.82 | L25: Forest | M25: 824 | N25: =K25*M25 -> 1.5706414e+08 | O25: =N25*10000/1000 -> 1.5706414e+09 | P25: =O25/1000 -> 1570641.4 | U25: =V35 -> 193405.64 | V25: Forest | W25: 850 | X25: =U25*W25 -> 1.643948e+08 | Y25: =X25*10000/1000 -> 1.643948e+09 | Z25: =Y25/1000 -> 1643948 | AE25: =AF35 -> 193428.68 | AF25: Forest | AG25: 870 | AH25: =AE25*AG25 -> 1.6828295e+08 | AI25: =AH25*10000/1000 -> 1.6828295e+09 | AJ25: =AI25/1000 -> 1682829.5
A26: =C18 -> 121.23578 | B26: Fishing | C26: 860 | D26: =A26*C26 -> 104262.77 | E26: =D26*10000/1000 -> 1042627.7 | F26: =E26/1000 -> 1042.6277 | K26: 121.24 | L26: Fishing | M26: 824 | N26: =K26*M26 -> 99901.76 | O26: =N26*10000/1000 -> 999017.6 | P26: =O26/1000 -> 999.0176 | U26: =V34 -> 119.16329 | V26: Fishing | W26: 850 | X26: =U26*W26 -> 101288.8 | Y26: =X26*10000/1000 -> 1012888 | Z26: =Y26/1000 -> 1012.888 | AE26: =AF34 -> 126.91362 | AF26: Fishing | AG26: 870 | AH26: =AE26*AG26 -> 110414.85 | AI26: =AH26*10000/1000 -> 1104148.5 | AJ26: =AI26/1000 -> 1104.1485
U27: Source: Land Use Matrix (Land Accounts results) Cfr: Ngabirame Gabriel Land data analyst | AE27: Source: Land Use Matrix (Land Accounts results) Cfr: Ngabirame Gabriel Land data analyst
A28: Source: Land Use Matrix (Land Accounts results) Cfr: Ngabirame Gabriel Land data analyst | K28: Source: Land Use Matrix (Land Accounts results) Cfr: Ngabirame Gabriel Land data analyst
A29: total_parcels | B29: size_in_Ha | C29: land_use | K29: total_parcels | L29: size_in_Ha | M29: land_use | U29: total_parcels | V29: size_in_Ha | W29: land_use | AE29: total_parcels | AF29: size_in_Ha | AG29: land_use
K30: 1918 | L30: 6713.8837 | M30: Administrative | U30: 1973 | V30: 6908.085 | W30: Administrative | AE30: 1784 | AF30: 6519.6726 | AG30: Administrative
A31: 7107286 | B31: 1242362.9 | C31: Agriculture | K31: 7107286 | L31: 1242362.9 | M31: Agriculture | U31: 7251589 | V31: 1251180.8 | W31: Agriculture | AE31: 7300822 | AF31: 1253304.9 | AG31: Agriculture
A32: 59629 | B32: 8311.5019 | C32: Commercial | K32: 59629 | L32: 8311.5019 | M32: Commercial | U32: 60007 | V32: 8340.4227 | W32: Commercial | AE32: 59890 | AF32: 8364.3323 | AG32: Commercial
A33: 89737 | B33: 10754.163 | C33: Economic | K33: 89737 | L33: 10754.163 | M33: Economic | U33: 90118 | V33: 10615.161 | W33: Economic | AE33: 89913 | AF33: 10547.513 | AG33: Economic
A34: 161 | B34: 121.23578 | C34: Fishing | K34: 161 | L34: 121.23578 | M34: Fishing | U34: 180 | V34: 119.16329 | W34: Fishing | AE34: 188 | AF34: 126.91362 | AG34: Fishing
A35: 883327 | B35: 190611.82 | C35: Forestry | K35: 883327 | L35: 190611.82 | M35: Forestry | U35: 909044 | V35: 193405.64 | W35: Forestry | AE35: 916305 | AF35: 193428.68 | AG35: Forestry
A36: 19305 | B36: 3490.4319 | C36: Industrial | K36: 19305 | L36: 3490.4319 | M36: Industrial | U36: 19578 | V36: 3370.2322 | W36: Industrial | AE36: 19846 | AF36: 3217.827 | AG36: Industrial
A37: 40273 | B37: 120444.78 | C37: Livestock | K37: 40273 | L37: 120444.78 | M37: Livestock | U37: 40807 | V37: 118582.65 | W37: Livestock | AE37: 43848 | AF37: 118578.73 | AG37: Livestock
A38: 2474 | B38: 10689.797 | C38: Research/Scientific | K38: 2474 | L38: 10689.797 | M38: Research/Scientific | U38: 2552 | V38: 10412.553 | W38: Research/Scientific | AE38: 2650 | AF38: 10351.006 | AG38: Research/Scientific
A39: 1189279 | B39: 157741.69 | C39: Residential | K39: 1189279 | L39: 157741.69 | M39: Residential | U39: 1223911 | V39: 159816.74 | W39: Residential | AE39: 1340067 | AF39: 176012.64 | AG39: Residential
A40: 20270 | B40: 8190.7458 | C40: Social and culture | K40: 20270 | L40: 8190.7458 | M40: Social and culture | U40: 20829 | V40: 8360.5774 | W40: Social and culture | AE40: 21263 | AF40: 8805.6108 | AG40: Social and culture
A41: 3908 | B41: 852.46117 | C41: Tourism | K41: 3908 | L41: 852.46117 | M41: Tourism | U41: 3998 | V41: 926.59715 | W41: Tourism | AE41: 4021 | AF41: 1004.7989 | AG41: Tourism
A42: =SUM(A30:A41) -> 9415649 | B42: =SUM(B30:B41) -> 1753571.6 | K42: =SUM(K30:K41) -> 9417567 | L42: =SUM(L30:L41) -> 1760285.5 | U42: =SUM(U30:U41) -> 9624586 | V42: =SUM(V30:V41) -> 1772038.6 | AE42: =SUM(AE30:AE41) -> 9800597 | AF42: =SUM(AF30:AF41) -> 1790262.6
A45: Soil Water Stock calculation (1st of January for opening stock) & For closing stock 31 december of closing stock or simply 1st of January next year.
A46: =SUM(B31,B34,B35,B37,B41) -> 1554393.2 | B46: ha | C46: Selected area
A47: =SUM(B42) -> 1753571.6 | B47: ha | C47: Total area (LAIS 2013 figure, after that has been further improved)
A48: =+(2633800)-(217500) -> 2416300 | B48: ha | C48: Total land area of Rwanda (= total area Rwanda -/- wet surface area of water like lakes, rivers, streams, artificial reservoirs), exclude wetlands. Source: REMA publication 2008 figure & MSc Thesis Dr. Omar & 2014 article …).
A49: =+(A48*10000) -> 24163000000 | B49: m2 | C49: ??
A50: 1.39 | B50: soil layer (m), consits of unsaturate zone (soil water) and saturated zone (groundwater). Underneath, there is impermeable zone of rock. Check with Innocent: Soil layer and saturation etc. Further treatment of aquifer (confined) …
A51: 0.5 | B51: Distance between land surface & groundwater table, on average. soil layer (m) unsaturated with water (the layer with soil water), same as above in different terms
A52: 0.55 | B52: Pore volume (%)
A53: 0.51 | B53: Saturation of the pores with water (%) (i.e. compare with soil moisture (%) from either Rwanda Meteo on this data 1st of January
A54: =+A52*A53 -> 0.2805 | B54: VOLUME METRIC WATER CONTENT, (NOT Soil Moisture (%), as percentage of the volume in (m3 water /m3 soil) (i.e. compare with soil moisture (%) from either Rwanda Meteo or MINAGRI & RAB on this data 1st of January
A55: =+(A49)*A51*A52*A53 -> 3.3888608e+09 | B55: m3
A56: =+(A49)*A51*A54 -> 3.3888608e+09 | B56: m3 | C56: Combine with actual soil moisture at this data from Rwanda Meteo or MINAGRI & RAB on this data 1st of January
A57: =+A55/1000000000 -> 3.3888608 | B57: 10^9 m3
A58: =+A55/1000000 -> 3388.8608 | B58: 10^6 m3
A61: Ground Water Stock calculation (1st of January for opening stock) & For closing stock 31 december of closing stock or simply 1st of January next year.
A62: =SUM(B31,B34,B35,B37,B41) -> 1554393.2 | B62: ha | C62: Selected area
A63: =SUM(B42) -> 1753571.6 | B63: ha | C63: Total area (LAIS 2013 figure, after that has been further improved)
A64: =+(2633800)-(217500) -> 2416300 | B64: ha | C64: Total land area of Rwanda (= total area Rwanda -/- wet surface area of water like lakes, rivers, streams, artificial reservoirs), exclude wetlands. Source: REMA publication 2008 figure & MSc Thesis Dr. Omar & 2014 article …).
A65: =+(2633800) -> 2633800 | B65: ha | C65: Total area of Rwanda
A66: =+(A65*10000) -> 26338000000 | B66: m2 | C66: ??
A67: 1.39 | B67: Soil layer (m), consists of unsaturated zone (soil water) and saturated zone (groundwater). Underneath, there is impermeable zone of rock. Check with Innocent: Soil layer and saturation etc. Further treatment of aquifer (confined) …
A68: =+(A67-A51) -> 0.89 | B68: Distance between groundwater table and impermeable rock underneath, on average for country. Soil layer (m) saturated with water (the layer with shallow ground water (not yet deep groundwater)), put in different terms
A69: 0.45 | B69: Pore volume (%), discussion on this figure may change this figure slightly.
A70: 1 | B70: Saturation of the pores with water (%) (i.e. compare with soil moisture (%) from either Rwanda Meteo on this data 1st of January
A71: =+(A66)*(A68)*A69*A70 -> 1.0548369e+10 | B71: m3
A72: =+A71/1000000000 -> 10.548369 | B72: 10^9 m3
A73: =+A71/1000000 -> 10548.369 | B73: 10^6 m3 | C73: Shallow ground water
A74: =62127-(10548.369) -> 51578.631 | B74: 10^6 m3 | C74: Volume of 'deep' groundwater in 'confined aquifers'. Start from 2012NWRMP, check how this is assessed and compare with other sources. Like from global assessments of groundwater in aquifers, i.e. from IGRAC: International Groundwater Resources Assessment Centre (at IHE - Delft).
A75: =SUM(A73:A74) -> 62127 | B75: 10^6 m3 | C75: Total volume of groundwater for Rwanda.
A78: Total surface of water bodies
A79: According to Land Cover 2015
A80: 152002.94 | B80: ha | C80: Total area of surface water bodies from Land cover 2015; smaller than area of natural lakes from report water storage per capita!!??
A81: 88651.369 | B81: ha | C81: Total wetland area from Land cover 2015; probably includes wet buffer zones (swampy) around lakes; ask Eric
A82: =A80+A81 -> 240654.31 | B82: ha | C82: Total area wet surface water bodies plus wetlands
A83: According to Report Water storage per capita
A84: =A108 -> 162183.21 | B84: ha | C84: Area natural lakes. This surface is already higher then total water body surface from landcover map. Gilbert: there are usually large buffer zones/swampy areas around lakes. Maybe these areas are included.
A86: 6462 | B86: km | C86: Area Rivers: 861 rivers totalling 6462 km in length. Source of length of rivers: http://www.rema.gov.rw/soe/chap7.pdf. Average width??
A87: 10 | B87: m | C87: First estimate of average width of rivers: 10 m: needs to be checked by the team!!
A88: =A86*1000*A87/10000 -> 6462 | B88: ha | C88: Estimated area of rivers
A90: 1942.4934 | B90: ha | C90: Area Artificial reservoirs and dams: see Water storage per capita final report.pdf__Map2__II.xlsx and report table 6: combine volume and dam height for first estimate of area.
A91: 4.19975 | B91: ha | C91: Area Ponds, see Water storage per capita final report.pdf__Map2__II.xlsx. Preliminary estimate with average depth of 4 m. Ask Minagri for average depth of ponds
A92: =A90+A91 -> 1946.6932 | B92: ha | C92: Total Area of Ponds and Artificial reservoirs
A94: =A84+A88+A92 -> 170591.9 | B94: ha | C94: Total area of water bodies
A96: Total Surface of Rwanda lakes. | C96: Source: Report water storage per capita
A97: m2 | C97: Adapted by Cor: see
A98: 2.2805975e+08 | B98: Sum of Eastern valley lakes
A99: 80238900 | B99: Burera
A100: 88172100 | B100: Ihema
A101: 26064900 | B101: Ruhondo
A102: 3960200 | B102: Rumira
A103: 2642200 | B103: Mirayi
A104: 1.0105957e+09 | B104: Kivu | C104: Only the area of Rwanda! | E104: Total including DRC is 2700 km2
A105: 55939619 | B105: Cyohoha South | C105: Only the area of Rwanda? Check!
A106: 1.2615871e+08 | B106: Rweru | C106: Only the area of Rwanda? Check!
A107: =SUM(A98:A106) -> 1.6218321e+09 | B107: Total lakes
A108: =A107/10000 -> 162183.21 | B108: ha
A114: Total Surface of Rivers

Sheet Prec&ET2012
A1: 2012
A2: Rwanda size
A3: Total area of Agriculture sector
A4: Precipitation | B4: SEE worksheet: 'GW&SOILW_2012'
A5: Evapotranspiration
A7: Source: Meteo Rwanda from 85 rain gauge stations countrywide
A8: Source: NWRMP, 2015 and Meteo Rwanda
A9: Calculated rainfall for year 2012 as collected from Rwanda Meteo
A10: 1274.2 | B10: mm/yr | C10: 26338 | D10: km2
A11: 1.2742 | B11: m/yr | C11: 26338000000 | D11: m2
D12: =A11*C11 -> 33559879600 | E12: m3
D13: =+D12/1000000 -> 33559.88 | E13: Million m3/yr | F13: Total rainfall volume for yr 2012
B15: P on watersurface itself | C15: m2 | D15: m3 | E15: Sum P on water surface itself + Surroundings (m3)
A16: =A11 -> 1.2742 | B16: Lakes | C16: =(A$52)*10000 -> 1.6218321e+09 | D16: =(A$11)*C16 -> 2.0665384e+09 | E16: =SUM(D16,D25) -> 2.2048333e+09
B17: Rivers and streams | C17: =(A$56)*10000 -> 64620000 | D17: =(A$11)*C17 -> 82338804 | E17: =SUM(D17,D26) -> 2.6269654e+09
B18: Artificial reservoirs | C18: =(A$63)*10000 -> 19466932 | D18: =(A$11)*C18 -> 24804764 | E18: =SUM(D18,D27) -> 1.0778172e+08
E19: =SUM(E16:E18) -> 4.9395804e+09
E21: P on Surrounding areas to water surfaces (m3)
D22: =SUM(Asset_2012_Table!C9:E9)*1000000 -> 4.9395804e+09 | E22: Lakes, Rivers and streams, Artificial reservoirs
D23: =SUM(D12)-SUM(E16:E18) -> 2.8620299e+10 | E23: Soil water (Remainder)
D24: =(Runoff!K21) -> 2.7658985e+09 | E24: Of Which: To 'Runoff'
D25: =+(D$24)*5% -> 1.3829492e+08 | E25: Of Which: To 'Runoff' Lakes
D26: =+(D$24)*92% -> 2.5446266e+09 | E26: Of Which: To 'Runoff' rivers and streams
D27: =+(D$24)*3% -> 82976954 | E27: Of Which: To 'Runoff' 'Artificial Reservoirs'
A31: Source: Meteo Rwanda from 85 rain gauge stations countrywide
A32: Source: NWRMP, 2015 and Meteo Rwanda
A33: Calculated ET for year 2012 as collected from Rwanda Meteo
A34: 863.8 | B34: mm/yr | C34: 26338 | D34: km2
A35: 0.8638 | B35: m/yr | C35: 26338000000 | D35: m2
D36: =A35*C35 -> 22750764400 | E36: m3
D37: =+D36/1000000 -> 22750.764 | E37: Million m3/yr | F37: Total rainfall volume for yr 2012
B39: ET on watersurface itself | C39: m2 | D39: m3 | E39: Sum ET on water surface itself (m3)
A40: =A35 -> 0.8638 | B40: Lakes | C40: =(A$52)*10000 -> 1.6218321e+09 | D40: =(A$35)*C40 -> 1.4009385e+09 | E40: =SUM(D40) -> 1.4009385e+09
B41: Rivers and streams | C41: =(A$56)*10000 -> 64620000 | D41: =(A$35)*C41 -> 55818756 | E41: =SUM(D41) -> 55818756
B42: Artificial reservoirs | C42: =(A$63)*10000 -> 19466932 | D42: =(A$35)*C42 -> 16815536 | E42: =SUM(D42) -> 16815536
E43: =SUM(E40:E42) -> 1.4735728e+09
E44: =SUM(D36)-SUM(E40:E42) -> 2.1277192e+10 | F44: Soil water (Remainder)
A46: Total surface of water bodies
A47: According to Land Cover 2015
A48: 152002.94 | B48: ha | C48: Total area of surface water bodies from Land cover 2015; smaller than area of natural lakes from report water storage per capita!!??
A49: 88651.369 | B49: ha | C49: Total wetland area from Land cover 2015; probably includes wet buffer zones (swampy) around lakes; ask Eric
A50: =A48+A49 -> 240654.31 | B50: ha | C50: Total area wet surface water bodies plus wetlands
A51: According to Report Water storage per capita
A52: =A79 -> 162183.21 | B52: ha | C52: Area natural lakes. This surface is already higher then total water body surface from landcover map. Gilbert: there are usually large buffer zones/swampy areas around lakes. Maybe these areas are included.
A54: 6462 | B54: km | C54: Area Rivers: 861 rivers totalling 6462 km in length. Source of length of rivers: http://www.rema.gov.rw/soe/chap7.pdf. Average width??
A55: 10 | B55: m | C55: First estimate of average width of rivers: 10 m: needs to be checked by the team!!
A56: =A54*1000*A55/10000 -> 6462 | B56: ha | C56: Estimated area of rivers
A57: =+A56*10000 -> 64620000 | B57: m2
A58: 2 | B58: m | C58: Av. Depth
A59: =+A57*A58 -> 129240000 | B59: m3 | C59: Content
A61: 1942.4934 | B61: ha | C61: Area Artificial reservoirs and dams: see Water storage per capita final report.pdf__Map2__II.xlsx and report table 6: combine volume and dam height for first estimate of area.
A62: 4.19975 | B62: ha | C62: Area Ponds, see Water storage per capita final report.pdf__Map2__II.xlsx. Preliminary estimate with average depth of 4 m. Ask Minagri for average depth of ponds
A63: =A61+A62 -> 1946.6932 | B63: ha | C63: Total Area of Ponds and Artificial reservoirs
A65: =A52+A56+A63 -> 170591.9 | B65: ha | C65: Total area of water bodies
A67: Total Surface of Rwanda lakes. | C67: Source: Report water storage per capita
A68: m2 | C68: Adapted by Cor: see
A69: 2.2805975e+08 | B69: Sum of Eastern valley lakes
A70: 80238900 | B70: Burera
A71: 88172100 | B71: Ihema
A72: 26064900 | B72: Ruhondo
A73: 3960200 | B73: Rumira
A74: 2642200 | B74: Mirayi
A75: 1.0105957e+09 | B75: Kivu | C75: Only the area of Rwanda! | E75: Total including DRC is 2700 km2
A76: 55939619 | B76: Cyohoha South | C76: Only the area of Rwanda? Check!
A77: 1.2615871e+08 | B77: Rweru | C77: Only the area of Rwanda? Check!
A78: =SUM(A69:A77) -> 1.6218321e+09 | B78: Total lakes
A79: =A78/10000 -> 162183.21 | B79: ha
A82: Total Surface of Rivers
A85: 2013
A86: Rwanda size
A87: Total area of Agriculture sector
A88: Precipitation
A89: Evapotranspiration
A91: Source: Meteo Rwanda from 85 rain gauge stations countrywide
A92: Source: NWRMP, 2015 and Meteo Rwanda
A93: Calculated rainfall for year 2013 as collected from Rwanda Meteo
A94: 1212.5 | B94: mm/yr | C94: 26338 | D94: km2
A95: 1.2125 | B95: m/yr | C95: 26338000000 | D95: m2
D96: =A95*C95 -> 3.1934825e+10 | E96: m3
D97: =+D96/1000000 -> 31934.825 | E97: Million m3/yr | F97: Total rainfall volume for yr 2012
B99: P on watersurface itself | C99: m2 | D99: m3 | E99: Sum P on water surface itself + Surroundings (m3)
A100: =A95 -> 1.2125 | B100: Lakes | C100: =(A$52)*10000 -> 1.6218321e+09 | D100: =(A$95)*C100 -> 1.9664714e+09 | E100: =SUM(D100,D109) -> 2.1047663e+09
B101: Rivers and streams | C101: =(A$56)*10000 -> 64620000 | D101: =(A$95)*C101 -> 78351750 | E101: =SUM(D101,D110) -> 2.6229783e+09
B102: Artificial reservoirs | C102: =(A$63)*10000 -> 19466932 | D102: =(A$95)*C102 -> 23603655 | E102: =SUM(D102,D111) -> 1.0658061e+08
E103: =SUM(E100:E102) -> 4.8343252e+09
E105: P on Surrounding areas to water surfaces (m3)
D106: =SUM(Asset_2013_Table!C9:E9)*1000000 -> 4.8343252e+09 | E106: Lakes, Rivers and streams, Artificial reservoirs
D107: =SUM(D96)-SUM(E100:E102) -> 2.71005e+10 | E107: Soil water (Remainder)
D108: =(Runoff!K21) -> 2.7658985e+09 | E108: Of Which: To 'Runoff'
D109: =+(D$108)*5% -> 1.3829492e+08 | E109: Of Which: To 'Runoff' Lakes
D110: =+(D$108)*92% -> 2.5446266e+09 | E110: Of Which: To 'Runoff' rivers and streams
D111: =+(D$108)*3% -> 82976954 | E111: Of Which: To 'Runoff' 'Artificial Reservoirs'
A115: Source: Meteo Rwanda from 85 rain gauge stations countrywide
A116: Source: NWRMP, 2015 and Meteo Rwanda
A117: Calculated ET for year 2013 as collected from Rwanda Meteo
A118: 852.6 | B118: mm/yr | C118: 26338 | D118: km2
A119: 0.8526 | B119: m/yr | C119: 26338000000 | D119: m2
D120: =A119*C119 -> 22455778800 | E120: m3
D121: =+D120/1000000 -> 22455.779 | E121: Million m3/yr | F121: Total rainfall volume for yr 2012
B123: ET on watersurface itself | C123: m2 | D123: m3 | E123: Sum ET on water surface itself (m3)
...

Sheet Runoff
A1: NWRMP2012
A2: Assets Accounts
A4: Consumptive Water demand | B4: Agriculture
A5: Year 2012 | B5: Rainfall | D5: Evaporation loss | F5: R-NWRMP: Surface water runoff = SEEA-W 'Internal Flow' | H5: Of Which: To Groundwater recharge | J5: Of Which: To 'Runoff' | L5: Groundwater volume storage | M5: Surface-water volume storage | O5: Renewable resource | P5: Catch. Area (km2) | Q5: Population
B6: (mm/yr) | C6: (MCM) | D6: (mm/yr) | E6: (MCM) | F6: (mm/yr) | G6: (MCM) | H6: (mm/yr) | I6: (MCM) | J6: (mm/yr) | K6: (MCM) | L6: (MCM) | M6: (MCM) | N6: (MCM) | O6: ['000 m³] | S6: Runoff | T6: Renewable water
A7: CKIV (Lake Kivu, 2,425 km²) | B7: 1240 | C7: =B7*P7*1000000/1000/1000000 -> 3007 | D7: 870 | E7: =D7*P7*1000000/1000/1000000 -> 2109.75 | F7: =SUM(B7,-D7) -> 370 | G7: =+(F7*$P7)/1000 -> 897.25 | H7: 250 | I7: =+(H7*$P7)/1000 -> 606.25 | J7: =F7-H7 -> 120 | K7: =+(J7*$P7)/1000 -> 291 | L7: 2400 | M7: 550000 | N7: =L7+I7+M7+G7+E7+C7 -> 559020.25 | O7: 898000 | P7: 2425 | Q7: 1415418 | S7: =B7-D7 -> 370 | T7: =+F7*P7 -> 897250
A8: CRUS (Rusizi, 1.005 km²) | B8: 1295 | C8: =B8*P8*1000000/1000/1000000 -> 1301.475 | D8: 865 | E8: =D8*P8*1000000/1000/1000000 -> 869.325 | F8: =SUM(B8,-D8) -> 430 | G8: =+(F8*$P8)/1000 -> 432.15 | H8: 268 | I8: =+(H8*$P8)/1000 -> 269.34 | J8: =F8-H8 -> 162 | K8: =+(J8*$P8)/1000 -> 162.81 | L8: 5000 | N8: =L8+I8+M8+G8+E8+C8 -> 7872.29 | O8: 432000 | P8: 1005 | Q8: 318048 | S8: =B8-D8 -> 430 | T8: =+F8*P8 -> 432150
A9: NNYU (Upper Nyabarongo, 3,348 km²) | B9: 1365 | C9: =B9*P9*1000000/1000/1000000 -> 4570.02 | D9: 980 | E9: =D9*P9*1000000/1000/1000000 -> 3281.04 | F9: =SUM(B9,-D9) -> 385 | G9: =+(F9*$P9)/1000 -> 1288.98 | H9: 292 | I9: =+(H9*$P9)/1000 -> 977.616 | J9: =F9-H9 -> 93 | K9: =+(J9*$P9)/1000 -> 311.364 | L9: 25110 | N9: =L9+I9+M9+G9+E9+C9 -> 35227.656 | O9: 1290000 | P9: 3348 | Q9: 1425492 | S9: =B9-D9 -> 385 | T9: =+F9*P9 -> 1288980
A10: NMUK (Mukungwa, 1,949 km²) | B10: 1315 | C10: =B10*P10*1000000/1000/1000000 -> 2562.935 | D10: 851 | E10: =D10*P10*1000000/1000/1000000 -> 1658.599 | F10: =SUM(B10,-D10) -> 464 | G10: =+(F10*$P10)/1000 -> 904.336 | H10: 322 | I10: =+(H10*$P10)/1000 -> 627.578 | J10: =F10-H10 -> 142 | K10: =+(J10*$P10)/1000 -> 276.758 | L10: 4872 | M10: 3508 | N10: =L10+I10+M10+G10+E10+C10 -> 14133.448 | O10: 905000 | P10: 1949 | Q10: 1048631 | S10: =B10-D10 -> 464 | T10: =+F10*P10 -> 904336
A11: NNYL (Lower Nyabarongo, 3.304 km²) | B11: 1191 | C11: =B11*P11*1000000/1000/1000000 -> 3935.064 | D11: 919 | E11: =D11*P11*1000000/1000/1000000 -> 3036.376 | F11: =SUM(B11,-D11) -> 272 | G11: =+(F11*$P11)/1000 -> 898.688 | H11: 165 | I11: =+(H11*$P11)/1000 -> 545.16 | J11: =F11-H11 -> 107 | K11: =+(J11*$P11)/1000 -> 353.528 | L11: 8673 | M11: 330 | N11: =L11+I11+M11+G11+E11+C11 -> 17418.288 | O11: 899000 | P11: 3304 | Q11: 2181940 | S11: =B11-D11 -> 272 | T11: =+F11*P11 -> 898688
A12: NAKN (Akanyaru, 3,402 km²) | B12: 1225 | C12: =B12*P12*1000000/1000/1000000 -> 4167.45 | D12: 990 | E12: =D12*P12*1000000/1000/1000000 -> 3367.98 | F12: =SUM(B12,-D12) -> 235 | G12: =+(F12*$P12)/1000 -> 799.47 | H12: 156 | I12: =+(H12*$P12)/1000 -> 530.712 | J12: =F12-H12 -> 79 | K12: =+(J12*$P12)/1000 -> 268.758 | L12: 5103 | N12: =L12+I12+M12+G12+E12+C12 -> 13968.612 | O12: 798000 | P12: 3402 | Q12: 1447480 | S12: =B12-D12 -> 235 | T12: =+F12*P12 -> 799470
A13: NAKU (Upper Akagera, 3.053 km²) | B13: 925 | C13: =B13*P13*1000000/1000/1000000 -> 2824.025 | D13: 760 | E13: =D13*P13*1000000/1000/1000000 -> 2320.28 | F13: =SUM(B13,-D13) -> 165 | G13: =+(F13*$P13)/1000 -> 503.745 | H13: 115 | I13: =+(H13*$P13)/1000 -> 351.095 | J13: =F13-H13 -> 50 | K13: =+(J13*$P13)/1000 -> 152.65 | L13: 4580 | N13: =L13+I13+M13+G13+E13+C13 -> 10579.145 | O13: 504000 | P13: 3053 | Q13: 1318379 | S13: =B13-D13 -> 165 | T13: =+F13*P13 -> 503745
A14: NAKL (Lower Akagera, 4.288 km²) | B14: 835 | C14: =B14*P14*1000000/1000/1000000 -> 3580.48 | D14: 624 | E14: =D14*P14*1000000/1000/1000000 -> 2675.712 | F14: =SUM(B14,-D14) -> 211 | G14: =+(F14*$P14)/1000 -> 904.768 | H14: 125 | I14: =+(H14*$P14)/1000 -> 536 | J14: =F14-H14 -> 86 | K14: =+(J14*$P14)/1000 -> 368.768 | L14: 4824 | N14: =L14+I14+M14+G14+E14+C14 -> 12520.96 | O14: 907000 | P14: 4288 | Q14: 725068 | S14: =B14-D14 -> 211 | T14: =+F14*P14 -> 904768
A15: NMUV (Muvumba, 1,568 km²) | B15: 995 | C15: =B15*P15*1000000/1000/1000000 -> 1560.16 | D15: 872 | E15: =D15*P15*1000000/1000/1000000 -> 1367.296 | F15: =SUM(B15,-D15) -> 123 | G15: =+(F15*$P15)/1000 -> 192.864 | H15: 71 | I15: =+(H15*$P15)/1000 -> 111.328 | J15: =F15-H15 -> 52 | K15: =+(J15*$P15)/1000 -> 81.536 | L15: 1565 | N15: =L15+I15+M15+G15+E15+C15 -> 4796.648 | O15: 193000 | P15: 1568 | Q15: 725068 | S15: =B15-D15 -> 123 | T15: =+F15*P15 -> 192864
T17: =SUM(T7:T16) -> 6822251
A18: TOTAL FOR RWANDA (000m3/yr) | B18: =AVERAGE(B7:B15) -> 1154 | C18: =SUM(C7:C17) -> 27508.609 | D18: =AVERAGE(D7:D15) -> 859 | E18: =SUM(E7:E17) -> 20686.358 | F18: =AVERAGE(F7:F15) -> 295 | G18: =SUM(G7:G17) -> 6822.251 | H18: =AVERAGE(H7:H15) -> 196 | I18: =SUM(I7:I17) -> 4555.079 | J18: =AVERAGE(J7:J15) -> 99 | K18: =SUM(K7:K17) -> 2267.172 | L18: =SUM(L7:L17) -> 62127 | M18: =SUM(M7:M17) -> 553838 | N18: =SUM(N7:N17) -> 675537.3 | O18: =SUM(O7:O17) -> 6826000 | P18: =SUM(P7:P17) -> 24342 | Q18: =SUM(Q7:Q17) -> 10605524 | R18: 10192072 | S18: from water storage report
A19: Actual P for 2012 as per Meteo | C19: 33559.88 | F19: =SUM(B18,-D18) -> 295 | G19: =+G18*1000000 -> 6822251000 | K19: =(K18*C20) -> 2765.8985 | O19: =+O18*1000 -> 6826000000
A20: Difference RATIO to LTAA (20 yrs up to 2000) | C20: =(C19/C18) -> 1.2199773
K21: =K19*(1000000) -> 2.7658985e+09
A22: Index (P=100): | C22: =100*(C18/$C18) -> 100 | E22: =100*(E18/$C18) -> 75.199578 | G22: =100*(G18/$C18) -> 24.800422 | I22: =100*(I18/$C18) -> 16.55874 | K22: =100*(K18/$C18) -> 8.2416817
G23: =G19/R18 -> 669.36841 | O23: =O19/R18 -> 669.73624 | R23: m3/ca/yr
O24: =+O23/365 -> 1.8348938 | R24: m3/ca/day
A25: Year 2012 | B25: Renewable % of Prec. | O25: =+O23*1000/365 -> 1834.8938 | R25: l/ca/day
B26: (mm/yr) | D26: (MCM) | J26: Water Available for recharge | N26: =(H18/1000)*P18 -> 4771.032 | O26: m3/ca/yr
A27: CKIV (Lake Kivu, 2,425 km²) | B27: =+B7-D7 -> 370 | C27: =+B27/B7 -> 0.2983871 | D27: =+C7-E7 -> 897.25 | E27: =+H7/F7 -> 0.67567568 | J27: Water Available for recharge | N27: =(K23*1000000)/Q18 -> 0 | O27: m3/ca/yr
A28: CRUS (Rusizi, 1.005 km²) | B28: =+B8-D8 -> 430 | C28: =+B28/B8 -> 0.33204633 | D28: =+C8-E8 -> 432.15 | E28: =+H8/F8 -> 0.62325581 | J28: Water Available for recharge | N28: =(K23*1000000)/(P18*100) -> 0 | O28: m3/ha/yr
A29: NNYU (Upper Nyabarongo, 3,348 km²) | B29: =+B9-D9 -> 385 | C29: =+B29/B9 -> 0.28205128 | D29: =+C9-E9 -> 1288.98 | E29: =+H9/F9 -> 0.75844156
A30: NMUK (Mukungwa, 1,949 km²) | B30: =+B10-D10 -> 464 | C30: =+B30/B10 -> 0.35285171 | D30: =+C10-E10 -> 904.336 | E30: =+H10/F10 -> 0.69396552 | J30: =(H12/1000)*(P12) -> 530.712
A31: NNYL (Lower Nyabarongo, 3.304 km²) | B31: =+B11-D11 -> 272 | C31: =+B31/B11 -> 0.22837951 | D31: =+C11-E11 -> 898.688 | E31: =+H11/F11 -> 0.60661765
A32: NAKN (Akanyaru, 3,402 km²) | B32: =+B12-D12 -> 235 | C32: =+B32/B12 -> 0.19183673 | D32: =+C12-E12 -> 799.47 | E32: =+H12/F12 -> 0.66382979
A33: NAKU (Upper Akagera, 3.053 km²) | B33: =+B13-D13 -> 165 | C33: =+B33/B13 -> 0.17837838 | D33: =+C13-E13 -> 503.745 | E33: =+H13/F13 -> 0.6969697
A34: NAKL (Lower Akagera, 4.288 km²) | B34: =+B14-D14 -> 211 | C34: =+B34/B14 -> 0.25269461 | D34: =+C14-E14 -> 904.768 | E34: =+H14/F14 -> 0.59241706
A35: NMUV (Muvumba, 1,568 km²) | B35: =+B15-D15 -> 123 | C35: =+B35/B15 -> 0.12361809 | D35: =+C15-E15 -> 192.864 | E35: =+H15/F15 -> 0.57723577

Sheet Inflow
B1: INflows from other territories
B2: Inflows from other territory coming in (only) via the Rw rivers
B4: Data from RNRA as measured at 3 rivers, mainly:
B5: Ruvubu river from Burundi. It is a shared river, therfore we take 50% of this Ruvubu river! | C5: =+(25.7087*50%) -> 12.85435 | D5: m3/s
B6: Muvumba river from Uganda, data from WEAP model. | C6: 7.65 | D6: m3/s
B7: Akanyaru river partially from Burundi. It is river at the border, BUT ends fully in Rwanda. Measuring station is in Rwanda, far from the border. That is why TWG take 30% of the Akanyaru river as 'Inflow from Burundi'. | C7: =(21.518)*30% -> 6.4554 | F7: See Calculation in Excel: 'From water levels to Discharge'. File: 'Water_Level_to_Discharge_Calc__ RWANDA_RWAFA_2017-09-21__I'.
B8: Total inflows: | C8: =SUM(C5:C7) -> 26.95975
C9: =+C8*(3600*24*365) -> 8.5020268e+08 | D9: m3/yr (365days)
C10: =C9/1000000 -> 850.20268 | D10: Million m3/yr
B12: Kinyababa river at Burera data to be added ... and gauging station to be installed to measure and collect the data in future ...
B17: 2012
B18: Lake Kivu | C18: 10^9 * m3
B19: Net Inflow (or net outflow) to Rwanda from other territory via Lake KIVU:
B21: Inflows from incoming rivers in Rwanda to KIVU (draining to lake KIVU) (+):
B22: Known:
B24: From WEAP Uganda inflow …
B28: Gisenyi-Sebeya
B29: ..
B30: ..
B32: Unknown
B33: ..
B34: ..
B35: ..
B37: Outflow via Rwandan rivers draining lake KIVU (-/-):
... B42: Internal flow: Precipitation -/- EvapoTranspiration (ET):
C43: m | E43: km2 | F43: m2 | G43: m3
B44: P | C44: =+G44/1000000000 -> 1.359 | D44: 1.359 | E44: 1000 | F44: =+E44*1000000 -> 1000000000 | G44: =+D44*F44 -> 1359000000
B45: ET | C45: =+G45/1000000000 -> 1.582 | D45: 1.582 | E45: 1000 | F45: =+E45*1000000 -> 1000000000 | G45: =+D45*F45 -> 1582000000
B46: P -/- ET | C46: =+G46/1000000000 -> -0.223 | D46: =+D44-D45 -> -0.223 | E46: 1000 | F46: =+E46*1000000 -> 1000000000 | G46: =+D46*F46 -> -2.23e+08

Sheet Outflow
B1: Outflows to other territories
B2: Outflows to other from Rw rivers
D4: Outflow (m3/sec) | H4: Outflow (MCM/Year)
B6: Ruhwa river | C6: Previously we used: 17.8561570547727 from whatever source (?). Now we considered a recent study (2018) by REMA, TNC - Third National Communication on Climate Change for Water Resources Sector (including autors: Omar & Tetero) with a more recent estimate for the volume at the outlet: 256 m3/sec. We take 50% as this is Shared River (50/50 share on water volume) with Burundi. | D6: =(2.7)*50% -> 1.35 | H6: =D6*(3600*24*365)/1000000 -> 42.5736
B7: Rusizi river at KIVU Outlet | C7: At KIVU outlet. We take 50% as this is Shared River (50/50 share on water volume) with Congo. | D7: =(101.509099266037)*50% -> 50.75455 | H7: =D7*(3600*24*365)/1000000 -> 1600.5955 | I7: File: water levels and discharges from Alsaad__I
B8: Rubyiro at Bugarama | H8: 198.75564 | I8: File: water levels and discharges from Alsaad__I
B9: Umurindi river at Gatuna | C9: NO DATA (Recommendation to install Station) | D9: =(1.4) -> 1.4 | E9: m3/sec | H9: =D9*(3600*24*365)/1000000 -> 44.1504 | I9: WEAP-Model outcome, analaysed by Alsaad with technical 'Expert judgement'.
B10: Muvumba River at Kagitumba. | C10: Average dicharge 1970-1988: was 16.3814093390006 | D10: =(16.3814093390006) -> 16.381409 | E10: m3/sec | H10: =D10*(3600*24*365)/1000000 -> 516.60412
B11: Akagera river at Rusumo Station, this discharge of Akagera river at Rusumo Station is taken as an estimate for the Akagera Outlet (at Kagitumba). | C11: Average dicharge 1955-2000: 335.804765625 m3/sec. Now we considered a recent study (2018) by REMA, TNC - Third National Communication on Climate Change for Water Resources Sector (including autors: Omar & Tetero) with a more recent estimate for the volume at the outlet: 256 m3/sec. We take 50% as this is Shared River (50/50 share on water volume) with Tanzania. | D11: =(256)*50% -> 128 | E11: m3/sec | F11: =D11-150 -> -22 | H11: =D11*(3600*24*365)/1000000 -> 4036.608 | I11: Recommendation to install 2 main stations: 1.at the Outlet of Akagera at Kagitumba and; 2.at point in Akagera River just before Rweru Lake.
B14: Total Outflows | D14: =SUM(D6:D12) -> 197.88596 | E14: m3/sec | H14: =SUM(H6:H12) -> 6439.2872
D16: =D14*(3600*24*365) -> 6.2405316e+09 | E16: m3/yr | F16: =365 -> 365 | G16: days
D17: =D16/1000000 -> 6240.5316 | E17: Million m3/yr
D18: =D17/1000 -> 6.2405316 | E18: Billion m3/yr
B21: Rusizi river at Kamanyola | C21: TBD either KIVU outlet or at the border with Kamanyola | H21: 3040.0704 | I21: File: water levels and discharges from Alsaad__I

Sheet Closing_stocks
A2: Closing stock water resources
A3: Units in Million Cubic Meters | B3: Surface water | E3: Soil water | F3: Groundwater | G3: Total
B4: Lakes | C4: Rivers and streams | D4: Artificial reservoirs
A5: Closing stock water resources 2012 | B5: =+Asset_2012_Table!C24 -> 257690 | C5: =+Asset_2012_Table!D24 -> 1264 | D5: =+Asset_2012_Table!E24 -> 62.61347 | E5: =+Asset_2012_Table!F24 -> 3388.8608 | F5: =+Asset_2012_Table!G24 -> 62127 | G5: =+Asset_2012_Table!H24 -> 324532.47
A6: Closing stock water resources 2013 | B6: =+Asset_2013_Table!C24 -> 257248.31 | C6: =+Asset_2013_Table!D24 -> 1264 | D6: =+Asset_2013_Table!E24 -> 68.059209 | E6: =+Asset_2013_Table!F24 -> 3388.8608 | F6: =+Asset_2013_Table!G24 -> 62127 | G6: =+Asset_2013_Table!H24 -> 324096.23
A7: Closing stock water resources 2014 | B7: =+Asset_2014_Table!C24 -> 256806.61 | C7: =+Asset_2014_Table!D24 -> 1264 | D7: =+Asset_2014_Table!E24 -> 77.397325 | E7: =+Asset_2014_Table!F24 -> 3388.8608 | F7: =+Asset_2014_Table!G24 -> 62127 | G7: =+Asset_2014_Table!H24 -> 323663.87
A8: Closing stock water resources 2015 | B8: =+Asset_2015_Table!C24 -> 256364.92 | C8: =+Asset_2015_Table!D24 -> 1264 | D8: =+Asset_2015_Table!E24 -> 102.15047 | E8: =+Asset_2015_Table!F24 -> 3388.8608 | F8: =+Asset_2015_Table!G24 -> 62127 | G8: =+Asset_2015_Table!H24 -> 323246.93
A9: Trends (2012-2015) | B9: =(B8/B5)-1 -> -0.0051421432 | C9: =(C8/C5)-1 -> 0 | D9: =(D8/D5)-1 -> 0.63144557 | E9: =(E8/E5)-1 -> 0 | F9: =(F8/F5)-1 -> 0 | G9: =(G8/G5)-1 -> -0.0039612118
A12: Checks:
A13: Units in Million Cubic Meters | B13: Surface water | E13: Soil water | F13: Groundwater | G13: Total
B14: Lakes | C14: Rivers and streams | D14: Artificial reservoirs
A15: Closing stock water resources2012 | B15: =+Asset_2012_Table!C26 -> 257690 | C15: =+Asset_2012_Table!D26 -> 818.64426 | D15: =+Asset_2012_Table!E26 -> -19.184503 | E15: =+Asset_2012_Table!F26 -> 3551.6687 | F15: =+Asset_2012_Table!G26 -> 62309.29 | G15: =+Asset_2012_Table!H26 -> 324350.42
A16: Closing stock water resources2013 | B16: =+Asset_2013_Table!C26 -> 257248.31 | C16: =+Asset_2013_Table!D26 -> 815.49449 | D16: =+Asset_2013_Table!E26 -> -26.28868 | E16: =+Asset_2013_Table!F26 -> 2942.8046 | F16: =+Asset_2013_Table!G26 -> 62308.897 | G16: =+Asset_2013_Table!H26 -> 323289.21
A17: Closing stock water resources2014 | B17: =+Asset_2014_Table!C26 -> 256806.61 | C17: =+Asset_2014_Table!D26 -> 822.76328 | D17: =+Asset_2014_Table!E26 -> -32.372366 | E17: =+Asset_2014_Table!F26 -> 3684.1796 | F17: =+Asset_2014_Table!G26 -> 62308.507 | G17: =+Asset_2014_Table!H26 -> 323589.69
A18: Closing stock water resources2015 | B18: =+Asset_2015_Table!C26 -> 256364.92 | C18: =+Asset_2015_Table!D26 -> 823.00854 | D18: =+Asset_2015_Table!E26 -> -34.972385 | E18: =+Asset_2015_Table!F26 -> 3375.6355 | F18: =+Asset_2015_Table!G26 -> 62308.111 | G18: =+Asset_2015_Table!H26 -> 322836.7
A19: Closing stock water resources2016
A22: Closing stock water resources (after balancing)
A23: Units in Million Cubic Meters | B23: Surface water | E23: Soil water | F23: Groundwater | G23: Total
B24: Lakes | C24: Rivers and streams | D24: Artificial reservoirs
A25: Closing stock water resources2012 | B25: =+Asset_Tbl_Balance_2012!C24 -> 257690 | C25: =+Asset_Tbl_Balance_2012!D24 -> 1264 | D25: =+Asset_Tbl_Balance_2012!E24 -> 62.61347 | E25: =+Asset_Tbl_Balance_2012!F24 -> 3388.8608 | F25: =+Asset_Tbl_Balance_2012!G24 -> 62127 | G25: =+Asset_Tbl_Balance_2012!H24 -> 324532.47
A26: Closing stock water resources2013 | B26: =+Asset_Tbl_Balance_2013!C24 -> 257248.31 | C26: =+Asset_Tbl_Balance_2013!D24 -> 1264 | D26: =+Asset_Tbl_Balance_2013!E24 -> 68.059209 | E26: =+Asset_Tbl_Balance_2013!F24 -> 3388.8608 | F26: =+Asset_Tbl_Balance_2013!G24 -> 62127 | G26: =+Asset_Tbl_Balance_2013!H24 -> 324096.23
A27: Closing stock water resources2014 | B27: =+Asset_Tbl_Balance_2014!C24 -> 256806.61 | C27: =+Asset_Tbl_Balance_2014!D24 -> 1264 | D27: =+Asset_Tbl_Balance_2014!E24 -> 77.397325 | E27: =+Asset_Tbl_Balance_2014!F24 -> 3388.8608 | F27: =+Asset_Tbl_Balance_2014!G24 -> 62127 | G27: =+Asset_Tbl_Balance_2014!H24 -> 323663.87
A28: Closing stock water resources2015 | B28: =+Asset_Tbl_Balance_2015!C24 -> 256364.92 | C28: =+Asset_Tbl_Balance_2015!D24 -> 1264 | D28: =+Asset_Tbl_Balance_2015!E24 -> 102.15047 | E28: =+Asset_Tbl_Balance_2015!F24 -> 3388.8608 | F28: =+Asset_Tbl_Balance_2015!G24 -> 62127 | G28: =+Asset_Tbl_Balance_2015!H24 -> 323246.93
A29: Closing stock water resources2016

Sheet Asset_2012_Table
B1: SEEA Physical Asset Account for water resources, Year 2012 (Million m3)
B3: Units in Million Cubic Meters | C3: Surface water | F3: Soil water | G3: Groundwater | H3: Total | J3: Internal Renewable water resources | K3: Total Renewable water resources
C4: Lakes | D4: Rivers and streams | E4: Artificial reservoirs
B5: Opening stock water resources | C5: ='W-Assets_Data&Method_2012'!F3 -> 258131.69 | D5: ='W-Assets_Data&Method_2012'!F4 -> 1264 | E5: ='W-Assets_Data&Method_2012'!F5 -> 60.391466 | F5: ='W-Assets_Data&Method_2012'!F6 -> 3388.8608 | G5: ='W-Assets_Data&Method_2012'!F7 -> 62127 | H5: =SUM(C5:G5) -> 324971.95
B7: Additions to stock
B8: Returns of water | C8: ='W-Assets_Data&Method_2012'!F8 -> 0.91867446 | D8: ='W-Assets_Data&Method_2012'!F9 -> 321.53606 | E8: ='W-Assets_Data&Method_2012'!F10 -> 0 | F8: ='W-Assets_Data&Method_2012'!F11 -> 135.73415 | G8: ='W-Assets_Data&Method_2012'!F12 -> 1.1483431 | H8: =SUM(C8:G8) -> 459.33723
B9: Precipitation | C9: ='W-Assets_Data&Method_2012'!F13 -> 2204.8333 | D9: ='W-Assets_Data&Method_2012'!F14 -> 2626.9654 | E9: ='W-Assets_Data&Method_2012'!F15 -> 107.78172 | F9: ='W-Assets_Data&Method_2012'!F16 -> 28620.299 | H9: =SUM(C9:G9) -> 33559.88 | J9: =+(H9) -> 33559.88 | K9: =+(H9) -> 33559.88
B10: Inflows from other territories | C10: ='W-Assets_Data&Method_2012'!F18 -> 0 | D10: ='W-Assets_Data&Method_2012'!F19 -> 850.20268 | E10: ='W-Assets_Data&Method_2012'!F20 -> 0 | G10: ='W-Assets_Data&Method_2012'!F22 -> 0 | H10: =SUM(C10:G10) -> 850.20268 | K10: =+(H10) -> 850.20268 | M10: =+K10/K9 -> 0.025333901 | N10: =+H17/H10 -> 7.5738261
B11: Inflows from other inland water resources | C11: ='W-Assets_Data&Method_2012'!F23 -> 1636 | D11: ='W-Assets_Data&Method_2012'!F24 -> 4422.52 | E11: ='W-Assets_Data&Method_2012'!F25 -> 221.126 | F11: ='W-Assets_Data&Method_2012'!F26 -> 911.12 | G11: ='W-Assets_Data&Method_2012'!F27 -> 3644.48 | H11: =SUM(C11:G11) -> 10835.246
B12: Total additions to stock | C12: =SUM(C8:C11) -> 3841.752 | D12: =SUM(D8:D11) -> 8221.2241 | E12: =SUM(E8:E11) -> 328.90772 | F12: =SUM(F8:F11) -> 29667.153 | G12: =SUM(G8:G11) -> 3645.6283 | H12: =SUM(C12:G12) -> 45704.666 | J12: =SUM(J8:J11) -> 33559.88 | K12: =SUM(K8:K11) -> 34410.082
B14: Reductions in stock
B15: Abstraction of water | C15: ='W-Assets_Data&Method_2012'!F28 -> 18.292297 | D15: ='W-Assets_Data&Method_2012'!F29 -> 314.34787 | E15: ='W-Assets_Data&Method_2012'!F30 -> 260.10506 | F15: ='W-Assets_Data&Method_2012'!F31 -> 0 | G15: ='W-Assets_Data&Method_2012'!F32 -> 63.450817 | H15: =SUM(C15:G15) -> 656.19604 | M15: SEEA-W "USE": | O15: =H15 -> 656.19604 | P15: =+(O15*1000000)/J29 -> 62.598351 | Q15: Per Capita Abstraction per annum
B16: Actual Evaporation and transpiration | C16: ='W-Assets_Data&Method_2012'!F33 -> 1400.9385 | D16: ='W-Assets_Data&Method_2012'!F34 -> 55.818756 | E16: ='W-Assets_Data&Method_2012'!F35 -> 16.815536 | F16: ='W-Assets_Data&Method_2012'!F36 -> 21277.192 | H16: =SUM(C16:G16) -> 22750.764 | J16: =+(H16) -> 22750.764 | K16: =+(H16) -> 22750.764 | M16: Demand (IWRM): | O16: 500 | P16: =+(O16*1000000)/J29 -> 47.697904 | Q16: Per Capita Abstraction per annum
B17: Outflows to other territories | D17: ='W-Assets_Data&Method_2012'!F39 -> 6439.2872 | E17: ='W-Assets_Data&Method_2012'!F40 -> 0 | G17: ='W-Assets_Data&Method_2012'!F42 -> 0 | H17: =SUM(C17:G17) -> 6439.2872
B18: Outflow to the sea | D18: ='W-Assets_Data&Method_2012'!F44 -> 0 | E18: ='W-Assets_Data&Method_2012'!F45 -> 0 | G18: ='W-Assets_Data&Method_2012'!F47 -> 0 | H18: =SUM(C18:G18) -> 0 | N18: Calculated rainfall for year 2012 as collected from Rwanda Meteo
B19: Outflow to other inland water resources | C19: ='W-Assets_Data&Method_2012'!F48 -> 2864.2141 | D19: ='W-Assets_Data&Method_2012'!F49 -> 1857.126 | E19: ='W-Assets_Data&Method_2012'!F50 -> 131.56309 | F19: ='W-Assets_Data&Method_2012'!F51 -> 8227.1538 | G19: ='W-Assets_Data&Method_2012'!F52 -> 3399.8874 | H19: =SUM(C19:G19) -> 16479.944 | N19: 1274.2mm/yr | O19: 26338km2 | P19: =12742*26338 -> 335598796 | Q19: 863.8mm/yr | R19: ET for 2012
B20: Total reductions in stock | C20: =SUM(C15:C19) -> 4283.445 | D20: =SUM(D15:D19) -> 8666.5799 | E20: =SUM(E15:E19) -> 408.48369 | F20: =SUM(F15:F19) -> 29504.345 | G20: =SUM(G15:G19) -> 3463.3382 | H20: =SUM(C20:G20) -> 46326.192 | J20: =SUM(J15:J19) -> 22750.764 | K20: =SUM(K15:K19) -> 22750.764 | N20: 1.2742m/yr | O20: 26338000000m2 | Q20: 0.8638m/yr
B22: Balancing item: | C22: =-SUM(C5,C12,-C20,-C24) -> 0 | D22: =-SUM(D5,D12,-D20,-D24) -> 445.35574 | E22: =-SUM(E5,E12,-E20,-E24) -> 81.797973 | F22: =-SUM(F5,F12,-F20,-F24) -> -162.80794 | G22: =-SUM(G5,G12,-G20,-G24) -> -182.29015 | H22: =SUM(C22:G22) -> 182.05562 | N22: 1.2742 | O22: 26338000000 | P22: =N22*O22 -> 33559879600 | Q22: 0.8638 | R22: =Q22*O22 -> 22750764400
B24: Closing stock water resources | C24: =C5+(Lakes!F68/1000000) -> 257690 | D24: =D5+(0) -> 1264 | E24: ='W-Assets_Data&Method_2012'!F55 -> 62.61347 | F24: =F5*(100%) -> 3388.8608 | G24: =G5+(0) -> 62127 | H24: =SUM(C24:G24) -> 324532.47 | N24: =+P22/1000000 -> 33559.88 | O24: Total rainfall volume for yr 2012 | Q24: =R22/1000000 -> 22750.764
N25: =N24/1000 -> 33.55988 | O25: Billion m3/yr | P25: Lakes
B26: Checks: | C26: =(C5+C12)-C20 -> 257690 | D26: =(D5+D12)-D20 -> 818.64426 | E26: =(E5+E12)-E20 -> -19.184503 | F26: =(F5+F12)-F20 -> 3551.6687 | G26: =(G5+G12)-G20 -> 62309.29 | H26: =(H5+H12)-H20 -> 324350.42 | J26: IRWR | K26: TRWR | M26: Cell E58 and E59 seem to be double counted | P26: Rivers and streams
J27: =SUM(J12,-J20) -> 10809.115 | P27: Artificial reservoirs
K28: =SUM(K12,-K20) -> 11659.318 | P28: Soil water
J29: 10482641 | K29: population in 2012 (NISR, Census 2012) | P29: Groundwater
J30: 10.482641 | K30: population in mln 2012
J31: =+(J27/J30) -> 1031.1443 | L31: IRWR (m3) / capita
K32: =+(K28/J30) -> 1112.25 | L32: TRWR (m3) / capita
K33: =H38 -> 151.61675 | L33: TWW
K34: =+(K33/K28) -> 0.013003912 | L34: Water Stress %
F36: 499468512 | G36: TWW from Water users study done in 2017 for year 2016
L37: Ratio from TWW in 2012 as per NCA to TWW in 2016 as per Water User survey
G38: 2012 | H38: 151.61675 | L38: =H38/(F$36/1000000) -> 0.30355617
G39: 2013 | H39: 197.10177 | L39: =H39/(F$36/1000000) -> 0.39462302
G40: 2014 | H40: 256.23231 | L40: =H40/(F$36/1000000) -> 0.51300993
G41: 2015 | H41: 333.102 | L41: =H41/(F$36/1000000) -> 0.66691291
G42: 2016 | H42: 499.46851 | I42: 2016 | L42: =H42/(F$36/1000000) -> 1

Sheet W-Assets_Data&Method_2012
B2: Asset Account | D2: No | E2: Description | F2: Volume in Million M3 (Hardcopy) | G2: Source / Institution | H2: Period of collected Data | I2: Method / Explanations / Assumptions
B3: Opening Stock | D3: 1 | E3: Opening Stock_Surface water _Lakes | F3: =Lakes!N61/1000000 -> 258131.69 | G3: RNRA | H3: 2012 | I3: For details: worksheet: 'Lakes' Splitted the Rwanda part from lake Kivu. Which is about 1000 km2 out of 2700 km2. Average depth for Rwanda part may be less than 240 m, as it is the smaller part of the lake in contrast to DRC. 1000 * 1000,000 m2 * 240 m = 240,000 mln m3. We found a source that says: 249,000 mln m3 (Munyaneza Omar MSc thesis, 2007, NUR) The report: 'Water storage per capita final report', shows the capacity i Table 4: 247,595,940,457.6 m3, or 247.6 bln m3. The average depth may be overestimate a bit. I.e. compare to the volume of 500,000 mln m3, less than half may be less than 250,000 mln m3! First we had: 553,838 mln m3. But this included the whole lake Kivu. We thus tried to limit to the lake Kivu area which is part of Rwanda territory. Kivu Lake Lake in Afrika Wikipedia Area: 2.700 km² Hightof water surface : 1.460 m Length: 89 km Average depth: 240 m Maximum depth: 480 m Volume: 500 km³ = 500 mln m3. Cities: Goma, Bukavu, Kibuye, Gisenyi, Cyangugu All transboundary lakes have been considered. Including Cyohoha South and Rweru. Small lakes were also considered. Table 4: Sampled Lakes Area Volume estimations. For the rest of the eastern valley lakes, an approximation was adopted based on the average depth obtained from the Ihema, Rumira and Mirayi Lakes. The estimated average depth used to estimate the storage capacities of the remaining valley lakes was 4.14 meters depth. Table 5 provides the results of this estimation. The majority of the existing lakes are located in the Akagera Upstream and Akagara Downstream catchments.
D4: 2 | E4: Opening Stock_Surface water _Rivers and streams | F4: =Rivers!D4 -> 1264 | G4: RNRA | H4: 2012 | I4: 1, First start from stocks in rivers from Rwanda Resources Masterplan 2012 (RWRMP2012) add pages
D5: 3 | E5: Opening Stock_Surface water _Artificial reservoirs | F5: =Artificial_reserv!Q112 -> 60.391466 | G5: RNRA | H5: 2016 | I5: From Eng. Alsaad of RWFA who extracted data from RNRA report on water storage per capita, 2016. This is design capacity! Next step is to get to real water contained by these reservoirs. Two options to come from capacity to real volume at 01-01-20JJ (Any year): METHOD 1. To consider the 'YEAR of coming in OPERATION' and trace back from 2016 Reporting Year Information towards previous year up from 2012 !! To estimate: A. a percentage from the DESIGN storage capacity to get to 'MAXIMUM ACTUAL CAPACITY' (NOT actual capacity) reduced each year, depending on sedimentation; Percentage will depend on the lifetime of the reservoir, due to SEDIMENTATION, Affected dykes and quality of the dam etc. To estimate: B. a percentage from the 'MAXIMUM ACTUAL CAPACITY' to get to the 'ACTUAL STORAGE for each single YEAR', largely determined by the water level in the reservoir, which is determined by the actual storage depending of the weather in previous months and from the volume used in economic activity, evaporation and percolation in Rwandan dams); METHOD 2. See also METHOD 1. But information like size and orientation of reservoir and water levels, using EO / remote sensing (ESA - Data from SENTINEL - I, from YEAR X onwards) assess average 'water depth' in each reservoir at 01-01-20JJ (Any year); Together area * average depth = real volume of water in the reservoir; From EO / remote sensing assess area of the reservoirs combined with depth wit classification model, being a digital elevation model (via Benji). We need the volume at certain date: 01-01-2012.
D6: 4 | E6: Opening Stock_Soil water | F6: ='GW&SOILW_2012'!A58 -> 3388.8608 | G6: Land accounts, RNRA | H6: 2012 | I6: Calculated based on Land use change matrix and considering ET and Rainfall of 2012 as collected from Rwanda Meteo Soil Water & Ground Water assessment: Combine the land area with for each region (or catchment) relevant soil characteristics Relevant soil characteristics: - Soil depth (average & distribution) over the country - At what depth start the impermeable layer deep subsoil (with no or hardly groundwater flows)? - Soil depth, relative to the surface / ground level - Option: visualise a representative cross-section over the country - porevolume of this soil layer over the country (differences depending on type of soil and region?) - Distribute porevolumes over groundwater (saturated) and soil water (unsaturated), relate to regions / catchments - Distribution of porevolumes over groundwater vs soil water may (will) depend on soil moisture, eventually relate to soil moisture date for regions / catchments (?)
D7: 5 | E7: Opening Stock_Groundwater | F7: ='GW&SOILW_2012'!A75 -> 62127 | G7: RNRA | H7: 2012 | I7: See worksheet 'G&SW2012', with developed method and results for Groundwater and for Soil Water: Update parts of these data, with data from soil data base, like with soil layer or soil depth from soil database incl horizons. Roughly starting from these data: 0.60 soil layer (m), consits of unsaturated zone (soil water) and saturated zone (groundwater). Underneath, there is impermeable zone of rock. Check with Innocent: Soil layer and saturation etc. Further treatment of aquifer (confined) … 0.30 Distance between land surface & groundwater table, on average 0.30 soil layer (m) unsaturated with water (the layer with soil water), same as above in different terms 0.50 Pore volume (%) 0.50 Saturation of the pores with water (%) (i.e. compare with soil moisture (%) from either Rwanda Meteo on this data 1st of January 0.25 Soil Moisture (%) (i.e. compare with soil moisture (%) from either Rwanda Meteo or MINAGRI & RAB on this data 1st of January. Previously: Deep Groundwater, say from aquifers are taken From Master Plan, 2015. Expected to bekind of constant. Only shallow GRW is changing each year a bit.
B8: Additions to Stock | D8: 6 | E8: Returns_Surface water _Lakes | F8: =(SUM(PSUT_2012!AA12:'PSUT_2012'!AA16)/1000)*(70%*0.2%) -> 0.91867446 | H8: 2012 | I8: Returns of water after abstraction flows to inland water resources, we assumed that the total water abstracted only 0.2% goes back to lakes. it was linked with PSUT table data on this category
D9: 7 | E9: Returns_Surface water _Rivers and streams | F9: =(SUM(PSUT_2012!AA12:'PSUT_2012'!AA16)/1000)*(70%*70%) -> 321.53606 | H9: 2012 | I9: Returns of water after abstraction flows to inland water resources, we assumed that the total water abstracted only 70% goes back to rivers and streams . it was linked with PSUT table data on this category: This assumption of 70% was due on urban areas and irrigation schemes much water goes back to rivers and while in rural areas much water return to soil
D10: 8 | E10: Returns_Surface water _Artificial reservoirs | F10: =((SUM(PSUT_2012!AA12:'PSUT_2012'!AA16)+(PSUT_2012!AA21)/1000))*(70%*0%) -> 0 | H10: 2012 | I10: Returns of water after abstraction flows to inland water resources, we assumed that the total water abstracted only 0% goes back to reservoirs . it was linked with PSUT table data on this category
D11: 9 | E11: Returns_Soil water | F11: =(SUM(PSUT_2012!AA12:'PSUT_2012'!AA16)/1000)*(70%*29.55%) -> 135.73415 | H11: 2012 | I11: Returns of water after abstraction flows to inland water resources, we assumed that the total water abstracted only 29.55% goes back to soils . it was linked with PSUT table data on this category. This assumption of 29.55% was due on urban areas and irrigation schemes much water goes back to rivers and while in rural areas much water return to soil
D12: 10 | E12: Returns_Groundwater | F12: =(SUM(PSUT_2012!AA12:'PSUT_2012'!AA16)/1000)*(70%*0.25%) -> 1.1483431 | H12: 2012 | I12: Returns of water after abstraction flows to inland water resources, we assumed that the total water abstracted only 0.25% goes back to Groundwater . it was linked with PSUT table data on this category
D13: 11 | E13: Precipitation_Surface water _Lakes | F13: =+('Prec&ET2012'!E16/1000000) -> 2204.8333 | I13: Calculated based on rainfall data collected from Rwanda Meteo and considering surface area of rwanda lakes Surface area is taken from landcoverdata 2015 (RCMRD). Also consider the RUNOFF from the area directly connected to the differet lakes (NOT the full catchment). Here to be added the RUNOFF for a small area surrounding the 'Lakes' 5% share from all catchments of the country (direct RUNOFF). Later the 'Lakes' will get the water collected by the rivers (and similar for the artificial reservoirs), this to be done In line 11: 'Inflows from other inland water resources' and Line 19 'outflows from other inland water resources'. Eventually For this purpse all "Water Balances" of all lakes??
D14: 12 | E14: Precipitation_Surface water _Rivers and streams | F14: =+('Prec&ET2012'!E17/1000000) -> 2626.9654 | I14: Calculated based on rainfall data collected from Rwanda Meteo and considering surface area of rwanda rivers Surface area is taken from landcoverdata 2015 (RCMRD). Here to be added the RUNOFF of all catchments for the total area of the country, 92%. MINUS a small area surrounding the 'Lakes' 5% and the area surrounding the 'Artificial Reservoirs' 3% (direct RUNOFF). Later on this will end up in the lakes and artificial reservoirs. In line 11: 'Inflows from other inland water resources'.
D15: 13 | E15: Precipitation_Surface water _Artificial reservoirs | F15: =+('Prec&ET2012'!E18/1000000) -> 107.78172 | I15: Inflow to inland water resources, Rwanda Meteo and considering surface area of Artificial Reservoir. Also consider the RUNOFF from the area directly connected to the differet lakes (NOT the full catchment). Here to be added the RUNOFF for a small area surrounding the 'Artificial Reservoirs' 3% share from all catchments of the country (direct RUNOFF). Later the 'artificial reservoirs' will get the water collected by the rivers (similar to the lakes), this to be done In line 11: 'Inflows from other inland water resources' and Line 19 'outflows from other inland water resources'.
D16: 14 | E16: Precipitation_Soil water | F16: =('Prec&ET2012'!D23/1000000) -> 28620.299 | I16: Inflow of water to inland water resources, Rwanda Meteo and considering surface area of agricultural land adding to Soil Water. Alternative calculation: Total P minus P on Lakes + Rivers + Reservoirs? But autonomous calculation using area is better. Here the precipitation entering the land require redistribution in: 1. INFILTRATION to the land itself and 2. into SURFACE RUNOFF away from the land into waterbodies. Derive a RUNOFF coëfficient. Start from the infiltration rates from the R-NWRMP2012, being different at catchment level. In meantime we use the R-NWRMP figure 'Surface water runoff' to reduce the volume of precipitation entering the soil via infiltration. This 'Surface water runoff' will be redistributed over lakes, rivers and artificial reservoirs according the capture (shares depending on their relevance in the catchment) of this RUNOFF. From the infiltration, big part goes into ET, the remainder goes into groundwater recharge (or depletion).
D17: 15 | E17: Precipitation_Groundwater | I17: Inflow of water to inland water resources, Rwanda Meteo and considering surface area of agricultural land to GW,but empty following SEEA-W (in first instance all allocated to soilwater)
D18: 16 | E18: Inflows from other territories_Surface water _Lakes | I18: See also worksheet 'inflow' How to treat inflow to lake Kivu? --> Solved by using the river(s) to Rwanda that drains the lake, Rusizi (its inflow flow is not yet measured, so no data yet ...Possible FOLLOW UP WITH EXPERT FROM IWRM TO MAKE FIRST ASSESSMENT for 2012 etc.). This ends up in item 'Outflows to other territories'. If there is a net flow from Congo than it is covered in the outflow. But also in the inflow?? If too many unkwown variables remain, than leave this value at 0. Also because the net inflow or outflow leaves Rwanda quite quickly. Look with experts LAKE KIVU Monitorings program, Including the estimates made fro the contribution via groundwater flows. See also SHARE Report, to get data (Estimates) for all rivers entering Lake KIVU from Rwanda. I.e. consultants working on it. See Report: 'Lake Kivu Monitoring Prgramme'. The water from Congo Basin to Lake Kivu is 1.3 km3 / year. It contains even a 'Water Balance'. --> Known.
D19: 17 | E19: Inflows from other territories_Surface water _Rivers and streams | F19: =(Inflow!C10) -> 850.20268 | H19: 2012 | I19: Data from RNRA as measured at 3 rivers: mainly Ruvubu river from Burundi; Muvumba river from Uganda; and Kinyababa river from Uganda at Burera. Ruvubu river at Rusumo. For Rivers that enter from neighboring countries, BUT enter one of the 'SHARED RIVERS' with one of the neigboring countries Tanzania, Burundi, these becone shared rivers, and THUS this INFLOW is shared with this neighboring country! Therefor TWG takes 50% of the Inflow from such rivers! This is relevant for Ruvubu River (at Rusumo) at border with Burundi entering the shared river at border. Kinyababa river at Burera data to be added ... and gauging station to be installed to measure and collect the data in future ...
D20: 18 | E20: Inflows from other territories_Surface water _Artificial reservoirs
D21: 19 | E21: Inflows from other territories_Soil water
D22: 20 | E22: Inflows from other territories_Groundwater
D23: 21 | E23: Inflows from other inland water resources_Surface water_Lakes | F23: 1636 | I23: This ROW is about net EXCHANGE of water between the inland water resources (5 categrories) within the year. This Item in Total (5 categories) should balance with 'Outflows to other inland water resources'). This has been filled at the country level using data from Lake Kivu Monitoring Programme report which shows contribution of all rivers from congo to Lake Kivu (936 MCM) as reported by (ABAKIR). in addition we added the contribution of Sebeya River to lake Kivu (76.4 MCM) AND Rusumo Rugezi river to lake Burera (42.9 MCM). contribution of other rivers to lakes are not available but for lake kivu we have estimated them using water balance equation where by the evaporation of lake kivu is 3600 MCM: SOURCE(Muvunja et al, 2009) and using the outflow from Kivu to RUSIZI river which is about 3200MCM (Source: RWAFA) and precipitation 1240 mm/y=1.24m/yr (master Plan, 2015)= 1.24*2,400,000,000 m2 = 2,976 MCM, hence other rivers to lake kivu are equal to = (2,976 + 936 + 76.4)-3600-3200= 2,811.6 MCM. To get Inflows from other inland water resources for Kivu Lake, we considered half (50%) of inflows from Congo plus Sebeya river, plus other rivers contributing to Lake Kivu: (936 + 76.4 + 2811.6)/2.4 = 1593 MCM However, for the whole Inflows from other inland water resources for Lakes, we get 1593 MCM plus Rusumo-Rugezi river 42.9 MCM means 1636 MCM, Will be improved after the information at the catchment (9*) is processed. -->> From the flow 'lake to the rivers', and then add to it 'WATER BALANCE', With 1. Discharge + 2. P, 3. -ET, 4. change in water balance, in order to derive inflow to the lake or 'artificial Reservoir'. We follow the approach of the 'Water Balance'.
D24: 22 | E24: Inflows from other inland water resources_Surface water _Rivers and streams | F24: =(('2012NWRMP'!J34)*70%)+(F23*70%)+(221*40%) -> 4422.52 | I24: First: 4,556 million m3 is the water from GW to rivers and streams as per Master plan and 30% of it is flowing to the soil water layer due to capilary rise. Secondly: we have considered 70% of Inflows from other inland water resources to lakes back to rivers and streams and. In this second Inflow category there may be a bit of double counting with first category here. Lastly: 40% of Inflows from other inland water resources to Artificial Reservoirs goes back to rivers and streams (see next cell).
D25: 23 | E25: Inflows from other inland water resources_Surface water _Artificial reservoirs | F25: =F24*5% -> 221.126 | I25: Some data are availlable on infows from Rivers to the artificial reservoirs (AR). Let consider that 80% of water in AR comes from rivers. Hence take 5% of water within rivers (as per Inflows from other inland water resourcesas) contribute to AR.
D26: 24 | E26: Inflows from other inland water resources_Soil water | F26: =('2012NWRMP'!J34)*20% -> 911.12 | I26: Groundwater recharge from water resources master plan 2015. which is the combination of recharge of 'Ground- & soil water'or contribution to the water under the groundwater table. It is an estimate of the flow on a dayly basis for the 365 days of a year. Let's take 80% for GW and 20% for Soil water Here the 'Capilary Rise' of water is relevant that thus flows from the 'shallow groundwater' underneath, UP to the Soil Water above. Which is a gain or addition of groundwater to the exisitng volume of Soil water. We assume that 2% of the SHALLOW GW is contributing to soil water. --> Source: Water Experts judgement but there is another methodology which can be used to estimate the soil water via capillary rise On contribution from capillairy rise: Handbook on dairy farming 2013 says: Water suply from Capillary Rise to rooted zone In addition to the amount of easily absorbable moisture in the root zone, the extent to which capillary water delivery occurs from the subsurface is important. The amount (volume) of capillary supply strongly depends on the groundwater level and the soil texture. Sometimes the maximum distance is exceeded for which sufficient capillary supply to the bottom of the effective root zone is still possible (critical ascending distance z). This leads to crop growth reduction. A capillary supply to the root zone of 1.0 to 2.0 mm/day is generally considered sufficient. Table 1.14 gives an approximation of the permissible distance between the bottom of the effective root zone and the groundwater level and the groundwater level (cm) for rising speeds of 3, 2, 1, 0.8 and 0.4 mm./day. Other sources on contribution from capillary rise to soil water (rooted zone) in Rwanda ...? Example calculation: From Groundwater to Soil Water via capillary Rise: Say 2 million ha is 20 billion m2 Times 200 days of 1 mm / day = 200 mm - 20cm = 0.20 m 20 bln times 0.20 is 4 billlion = 2,000 million m3 / year --> Please REDO with actual Rwanda information !
D27: 25 | E27: Inflows from other inland water resources_Groundwater | F27: =('2012NWRMP'!J34)*80% -> 3644.48 | I27: Groundwater recharge from water resources master plan 2015. which is the combination of recharge of 'Ground- & soil water'or contribution to the water under the groundwater table. It is an estimate of the flow on a dayly basis for the 365 days of a year. Let's take 80% for GW and 20% for Soil water
B28: Reductions to Stock | D28: 26 | E28: Abstraction of water_Surface water _Lakes | F28: =SUM(PSUT_2012!AA12)/1000 -> 18.292297 | H28: 2012 | I28: Data from the PSUT, linked from the TOTAL column (possibly column V). Method: straightforward use the values from the PSUT ! OLD: Without information, first 'expert judgement': 30% of surface water are abstracted from lakes and 70% from rivers. Better information on these shares is desired.
D29: 27 | E29: Abstraction of water_Surface water _Rivers and streams | F29: =SUM(PSUT_2012!AA13)/1000 -> 314.34787 | H29: 2012 | I29: Method: straightforward use the values from the PSUT ! Water use in Hydro - Electric is IN-Stream Use ! Don't confuse 'Use' versus 'Consumption'. From other study the 'water consumption' as a consequence of the hydro power is considered 5%, leidng to a reduction of 5% lower Return flow from the Hydro Power Stations. OLD: 30% of surface water are abstracted from lakes and 70% from rivers
D30: 28 | E30: Abstraction of water_Surface water _Artificial reservoirs | F30: =SUM(PSUT_2012!AA14,PSUT_2012!AA15)/1000 -> 260.10506 | H30: 2012 | I30: We considered here water harvested
D31: 29 | E31: Abstraction of water_Soil water | I31: from green water
D32: 30 | E32: Abstraction of water_Groundwater | F32: =SUM(PSUT_2012!AA16)/1000 -> 63.450817 | H32: 2012 | I32: As abstracted from GW. What about abstraction of groundwater (i.e. springwater)?
D33: 31 | E33: Evaporation and transpiration_Surface water _Lakes | F33: =+('Prec&ET2012'!E40)/1000000 -> 1400.9385 | H33: 2012 | I33: Use total area of all lakes in Rwanda * average Evaporation (ET) value for lakes from FAO WaPOR database data extracted (in Excels Benji). For area lakes, use consistent data from calculation of the stocks. Old: Master plan shows ET of 2012 yr is 860 mm and rainfall is 1274 mm meaning 67.5% of abstracted water are evaporated
D34: 32 | E34: Evaporation and transpiration_Surface water _Rivers and streams | F34: =+('Prec&ET2012'!E41)/1000000 -> 55.818756 | H34: 2012 | I34: based on total area rivers in Rwanda times average ET in m. Area calculation: i.e. see calculation for lakes ET value take E value from open water bodies (similar to values of lakes) also from FAO WaPOR database.
D35: 33 | E35: Evaporation and transpiration_Surface water _Artificial reservoirs | F35: =+('Prec&ET2012'!E42)/1000000 -> 16.815536 | H35: 2012 | I35: Same method as for Rivers and streams. But here use the total surface area of the artificial reservoirs including the ponds.
D36: 34 | E36: Actual Evaporation and transpiration_Soil water | F36: =+('Prec&ET2012'!E44)/1000000 -> 21277.192 | H36: 2012 | I36: New calculation: A. from FAO WaPOR database Actual ET data (both E as T in mm / yr) is extracted and is gridcell based (raster). From the Excels (Benji), these Actual ET values, can be combined with the areas of the gridcells and the results derived for both country wide and at (9*) catchment level. Via an overlay, thsi s even more convenient. B. Average Evaporation (ET) value for land area (Rwanda area without the lakes) from FAO WaPOR database data extracted (in Excels Benji). Combine with area of land (eventuall just for agricultural land, grassland and forest). Use consistent area from calculation of the stocks. Existing Calculation: 1.Area (m2) * average layer of water of ET (m) = m3; 2.Area (from Landcover maps): of the 1.lakes, vs 2.Rivers&streams vs 3.artificial Reservoirs; 3. Sources used. The REMAINDER can get allocated to SOIL Water. Or take Soil Water and/or compare with the ET data in the PSUT (Confront the Data Sources). Around 67% of soil water evapotranspirated through different types of crops.
D37: 35 | E37: Evaporation and transpiration_Groundwater
D38: 36 | E38: Outflows to other territories_Surface water _Lakes | F38: 0 | I38: This ROW is about het EXCHANGE of water between the inland water resources (5 categrories) within the year. This Item in Total (5 categories) should balance with 'Outflows to other inland water resources'). Has been filled at the country level. Will be improved after the information at the catchment (9*) is processed. -->> From the flow 'lake to the rivers', and then add to it 'WATER BALANCE', With 1. Discharge + 2. P, 3. -ET, 4. change in water balance, in order to derive inflow to the lake or 'artificial Reservoir'. We follow the approach of the 'Water Balance', For inflows from Lakes to Rivers, we have only considered 3 lakes (Kivu, Muhazi and Ruhondo). For lake Muhazi, only 2 discharge measurements have been taken and available, that's why we took their average.
D39: 37 | E39: Outflows to other territories_Surface water _Rivers and streams | F39: =+(Outflow!H14) -> 6439.2872 | H39: 2012 | I39: Data from RNRA as measured at 4 rivers (Akagera river at Rusumo, Rusizi river at Kamanyora and Ruhwa and Muvumba river before entering to Akagera river. Ruhwa river: 17.86m3/s; Kagitumba river at Bugaragara: 16.38m3/s; Akagera river at Rusumo: 335.80m3/s. Total Outflows: 370.04m3/s = 11,669,654,982.54 m3/yr for 365days = 11,669.65Million m3/yr. For Rivers that enter from neighboring countries, BUT enter one of the 'SHARED RIVERS' with one of the neigboring countries Tanzania, Burundi, these becone shared rivers, and THUS this INFLOW is shared with this neighboring country! Therefor TWG takes 50% of the Inflow from such rivers! This is relevant for Ruvubu River (at Rusumo) at border with Burundi entering the shared river at border. At the Outlet of Akagera, currently there is no station. In the past (eighties) there may have been a station, TWG hope to obtain these as a first estimate (2012 data??). So far we use the discharge of Akagera river at Rusumo Station as an estimate for the Akagera Outlet (Kagitumba). This because the experts explained after station at Rusumo there is both inflow, but clearly also outflow (i.e. to feed the lakes in Rwanda, while the precipitation is limited in Eastern Province, thus probably little addtion to akagera from the catchment there.
D40: 38 | E40: Outflows to other territories_Surface water _Artificial reservoirs
D41: 39 | E41: Outflows to other territories_Soil water
D42: 40 | E42: Outflows to other territories_Groundwater
D43: 41 | E43: Outflow to the sea_Surface water _Lakes
D44: 42 | E44: Outflow to the sea_Surface water _Rivers and streams | I44: There is no sea near by Rwanda
D45: 43 | E45: Outflow to the sea_Surface water _Artificial reservoirs | I45: There is no sea near by Rwanda
D46: 44 | E46: Outflow to the sea_Soil water
D47: 45 | E47: Outflow to the sea_Groundwater | I47: There is no sea near by Rwanda
D48: 46 | E48: Outflow to other inland water resources_Surface water _Lakes | F48: =SUM(Asset_2012_Table!C5,Asset_2012_Table!C12)-SUM(Asset_2012_Table!C24,Asset_2012_Table!C15,Asset_2012_Table!C16) -> 2864.2141 | I48: I.e. Flow from Lake Kivu to Risizi River. Well, this need to balance the total volume availlable for lakes, say opening stock lakes + additions of water to stock lakes -/- closing stock lakes is sort of reductions of water to stock lakes .. Isn't it?! Is it needed 'to balance with items under Total from 'Outflow to other inland water resources'. We had now considered 70% of Inflows from other inland water resources to lakes back to rivers and streams. --> Before we had formulas: =(F23)*70% = 1,145 mln m3 =(F13+F23)*70% = 2689 mln m3 OR: Take the remaining difference. In order to derived the only cell that is unknown. ... Although this last step can also be done in the "Asset_Tbl_Balance_2012' Worksheet Now we use Formula: =SUM(Asset_2012_Table!C5;Asset_2012_Table!C12)-SUM(Asset_2012_Table!C24;Asset_2012_Table!C15;Asset_2012_Table!C16) --> It might that, as lake Kivu is cross-border, even here an outflow from the lake to abroad DRC could be observed.
D49: 47 | E49: Outflow to other inland water resources_Surface water _Rivers and streams | F49: =F23+F25 -> 1857.126 | I49: I.e The River discharges to the Lakes, like to lake Kivu. However, as per inflows from other inland water resources for Lakes which is equal to 1636 MCM came from rivers. In addition, 5% of water within rivers (as per inflows from other inland water resources) contribute to AR.
D50: 48 | E50: Outflow to other inland water resources_Surface water _Artificial reservoirs | F50: =(F25+F15)*40% -> 131.56309 | I50: I.e. The discharges from the 'Artificial Reservoirs' to the Rivers downstream. This need 'to balance with items under Total from 'Outflow to other inland water resources'. We considered 40% of Inflows from other inland water resources to Artificial Reservoirs back to rivers and streams, as the biggest part of the outflow of the reservoir goes to irrigation in agriculture and will NOT return to the Inland Water System as it for big part goes to the atmosphere due to ET after irrigation. This need to balance to some extent with the water tht is lost by evaporation from the reservoirs (which is known in assrt table) and presumably little (?) will percolate to groundwater and the rest remains available for outflow to use in hydro and irrigation.For Rwanda this is a fair share. In contrast to for example countries with very flat reservoirs (haing higher losses from evaporation. But here also used the same percentage from the precipitation water that entered the Artificial reservoirs throughout the year.
D51: 49 | E51: Outflow to other inland water resources_Soil water | F51: =('2012NWRMP'!J34)+((Asset_2012_Table!F9-Asset_2012_Table!F16)*50%) -> 8227.1538 | I51: First: Part of the 'Excess' Soil water will flow to other inland water bodies, partially this Soil Water flows to the shallow groundwater underneath, but probably also partly to the DEEP groundwater bodies. This flow is the so-called 'Percolation' from Soil water to the grounwater underneath. Here put is a first 'rough' estimate. However, we took GW recharge as given by Master plan 2015. Further, a second category of water that may flow out of soil water: as we treat Soil Water and groundwater separately, this is in contrast with the NWRMP_2012, that only considered 'Groundwater', that is fine in itself. But therefore, in order to make it balancing we need to considerer all flows leaving the soil water after it has been 'loaded' with a large inflow of water from precipitation. This large inflow somewhere need to flow out again, either to groundwater, but clearly also to one of the other 'inland water resources' like rivers, lakes, reservoirs and so on. We now start from taking precipitation -/- ET = remaining water that is available in the soil for whatever purpose, but ready to flow out to one of the other categories. The exact parametrisation (50%) ofcourse can be discussed within TWG.
D52: 50 | E52: Outflow to other inland water resources_Groundwater | F52: =(('2012NWRMP'!J34))*70%+'GW&SOILW_2012'!A73*2% -> 3399.8874 | I52: Here the 'Capilary Rise' of water is relevant, which flows from the 'shallow groundwater' underneath UP to the soilwater above. Which is a loss or reduction of groundwater as it is taken from the exisitng groundwater in the soil, let's say 2% of the SHALLOW GW is contributing to soil water. Also we took 70% of GW recharge of 4556 MCM flow to rivers and streams as per Master plan.
B53: Closing Stock | D53: 51 | E53: Closing Stock_Surface water _Lakes | F53: =F3+(Lakes!F68/1000000) -> 257690 | I53: Method: Openingstock and change with the changing volume in the lake, based upon the data water level changes in the Lakes. Data from Alsaad (downloaded from IWRM website (database als possible with more actual data in future?).
D54: 52 | E54: Closing Stock_Surface water _Rivers and streams | F54: =Asset_2012_Table!D24 -> 1264
D55: 53 | E55: Closing Stock_Surface water _Artificial reservoirs | F55: =Artificial_reserv!R112 -> 62.61347 | I55: From Eng. Alsaad of RWFA who extracted data from RNRA report on water storage per capita, 2016. This is design capacity! Next step is to get to real water contained by these reservoirs. Two options to come from capacity to real volume at 01-01-20JJ (Any year): METHOD 1. To consider the 'YEAR of coming in OPERATION' and trace back from 2016 Reporting Year Information towards previous year up from 2012 !! To estimate: A. a percentage from the DESIGN storage capacity to get to 'MAXIMUM ACTUAL CAPACITY' (NOT actual capacity) reduced each year, depending on sedimentation; Percentage will depend on the lifetime of the reservoir, due to SEDIMENTATION, Affected dykes and quality of the dam etc. To estimate: B. a percentage from the 'MAXIMUM ACTUAL CAPACITY' to get to the 'ACTUAL STORAGE for each single YEAR', largely determined by the water level in the reservoir, which is determined by the actual storage depending of the weather in previous months and from the volume used in economic activity, evaporation and percolation in Rwandan dams); METHOD 2. See also METHOD 1. But information like size and orientation of reservoir and water levels, using EO / remote sensing (ESA - Data from SENTINEL - I, from YEAR X onwards) assess average 'water depth' in each reservoir at 01-01-20JJ (Any year); Together area * average depth = real volume of water in the reservoir; From EO / remote sensing assess area of the reservoirs combined with depth wit classification model, being a digital elevation model (via Benji). We need the volume at certain date: 01-01-2012.
D56: 54 | E56: Closing Stock_Soil water | F56: =Asset_2012_Table!F24 -> 3388.8608 | I56: Here the team need to find 'soil water content' or better apply the CHANGE in 'volume percentage' data over the 1st of the subsequent year following the current reporting year from Rwanda Meteo (m3/m3) and update the table accordingly. Can also be derived from soil water content sampling results for this particular reporting year (Weight percentage). Check in the end whether the outcome do look plausible volume change, starting from opening stock! Can also indirectly be derived from 'Soil water content' (Weight percentage).
D57: 55 | E57: Closing Stock_Groundwater | F57: ='GW&SOILW_2012'!A75 -> 62127 | I57: For the SHALLOW groundwater, the NCA-team need to try to find a number of boreholes with measured/monitored groundwater tables. The change in groundtables can be used to correct the volume of (shallow) ground water content from beginning to closing stock of (shallow) ground water. Maybe extract data from few boreholes (about ... out of 12 boreholes monitored permanently which data can be downloaded from the RWFA - WaterDataPORTAL !) that have this data on groundwatertable and use it to correct the closing stock. The range in here van be used to make countrywide assessment. Look in the end to plausible volume change, starting from opening stock !
D58: 56 | E58: Internal Renewable Water Resources (IRWR): Precipitation | F58: =Asset_2012_Table!J9 -> 33559.88 | I58: Indicator compilation: straight taken from Asset Table. Data used are rainfall from Rwanda Meteo
D59: 57 | E59: Internal Renewable Water Resources (IRWR): ET | F59: =Asset_2012_Table!J16 -> 22750.764 | I59: Indicator compilation: straight taken from Asset Table. Data used are evaporation from Rwanda Meteo
D60: 58 | E60: IRWR: Internal Flow: P - ET | F60: =Asset_2012_Table!J27 -> 10809.115 | I60: Indicator compilation: straight taken from Asset Table. Look to plausible volume change, by checking stock change, starting from opening stock!
D61: 59 | E61: ERWR: External Inflows from other territories | F61: =Asset_2012_Table!K10 -> 850.20268 | I61: Indicator compilation: straight taken from Asset Table.
D62: 60 | E62: TRWR: Total Renewable Water Resources: | F62: =Asset_2012_Table!K28 -> 11659.318 | I62: Indicator compilation: straight taken from Asset Table.

Sheet Asset_Tbl_Balance_2012_Doc
B1: Physical asset account for water resources Year 2012 in Million m3 (BALANCED !)
B3: Units in Million Cubic Meters | C3: Surface water | F3: Soil water | G3: Groundwater | H3: Total | I3: Internal Renewable water resources | J3: Total Renewable water resources
C4: Lakes | D4: Rivers and streams | E4: Artificial reservoirs
B5: Opening stock water resources | C5: =SUM(Asset_2012_Table!C5) -> 258131.69 | D5: =SUM(Asset_2012_Table!D5) -> 1264 | E5: =SUM(Asset_2012_Table!E5) -> 60.391466 | F5: =SUM(Asset_2012_Table!F5) -> 3388.8608 | G5: =SUM(Asset_2012_Table!G5) -> 62127 | H5: =SUM(C5:G5) -> 324971.95
B6: Additions to stock
B7: Returns of water | C7: =SUM(Asset_2012_Table!C8,+(0)) -> 0.91867446 | D7: =SUM(Asset_2012_Table!D8,+(0)) -> 321.53606 | E7: =SUM(Asset_2012_Table!E8,+(0)) -> 0 | F7: =SUM(Asset_2012_Table!F8,+(0)) -> 135.73415 | G7: =SUM(Asset_2012_Table!G8,+(0)) -> 1.1483431 | H7: =SUM(C7:G7) -> 459.33723
B8: Precipitation | C8: =SUM(Asset_2012_Table!C9,+(0)) -> 2204.8333 | D8: =SUM(Asset_2012_Table!D9,+(0)) -> 2626.9654 | E8: =SUM(Asset_2012_Table!E9,+(0)) -> 107.78172 | F8: =SUM(Asset_2012_Table!F9,+(0)) -> 28620.299 | H8: =SUM(C8:G8) -> 33559.88 | I8: =+(H8) -> 33559.88 | J8: =+(H8) -> 33559.88
B9: Inflows from other territories | C9: =SUM(Asset_2012_Table!C10,+(0)) -> 0 | D9: =SUM(Asset_2012_Table!D10,+(0)) -> 850.20268 | E9: =SUM(Asset_2012_Table!E10,+(0)) -> 0 | G9: =SUM(Asset_2012_Table!G10,+(0)) -> 0 | H9: =SUM(C9:G9) -> 850.20268 | J9: =+(H9) -> 850.20268
B10: Inflows from other inland water resources | C10: =SUM(Asset_2012_Table!C11,+(0)) -> 1636 | D10: =SUM(Asset_2012_Table!D11,+(503)) -> 4925.52 | E10: =SUM(Asset_2012_Table!E11,+(47)) -> 268.126 | F10: =SUM(Asset_2012_Table!F11,+(0)) -> 911.12 | G10: =SUM(Asset_2012_Table!G11,+(0)) -> 3644.48 | H10: =SUM(C10:G10) -> 11385.246
B11: Total additions to stock | C11: =SUM(C7:C10) -> 3841.752 | D11: =SUM(D7:D10) -> 8724.2241 | E11: =SUM(E7:E10) -> 375.90772 | F11: =SUM(F7:F10) -> 29667.153 | G11: =SUM(G7:G10) -> 3645.6283 | H11: =SUM(C11:G11) -> 46254.666 | I11: =SUM(I7:I10) -> 33559.88 | J11: =SUM(J7:J10) -> 34410.082
B12: Reductions in stock
B13: Abstraction of water | C13: =SUM(Asset_2012_Table!C15,+(0)) -> 18.292297 | D13: =SUM(Asset_2012_Table!D15,+(0)) -> 314.34787 | E13: =SUM(Asset_2012_Table!E15,+(0)) -> 260.10506 | F13: =SUM(Asset_2012_Table!F15,+(0)) -> 0 | G13: =SUM(Asset_2012_Table!G15,+(0)) -> 63.450817 | H13: =SUM(C13:G13) -> 656.19604
B14: Actual Evaporation and transpiration | C14: =SUM(Asset_2012_Table!C16,+(0)) -> 1400.9385 | D14: =SUM(Asset_2012_Table!D16,+(0)) -> 55.818756 | E14: =SUM(Asset_2012_Table!E16,+(0)) -> 16.815536 | F14: =SUM(Asset_2012_Table!F16,+(0)) -> 21277.192 | H14: =SUM(C14:G14) -> 22750.764 | I14: =+(H14) -> 22750.764 | J14: =+(H14) -> 22750.764
B15: Outflows to other territories | D15: =SUM(Asset_2012_Table!D17,+(0)) -> 6439.2872 | E15: =SUM(Asset_2012_Table!E17,+(0)) -> 0 | G15: =SUM(Asset_2012_Table!G17,+(0)) -> 0 | H15: =SUM(C15:G15) -> 6439.2872
B16: Outflow to the sea | D16: =SUM(Asset_2012_Table!D18,+(0)) -> 0 | E16: =SUM(Asset_2012_Table!E18,+(0)) -> 0 | G16: =SUM(Asset_2012_Table!G18,+(0)) -> 0 | H16: =SUM(C16:G16) -> 0
B17: Outflow to other inland water resources | C17: =SUM(Asset_2012_Table!C19,+(0)) -> 2864.2141 | D17: =SUM(Asset_2012_Table!D19,+(0)) -> 1857.126 | E17: =SUM(Asset_2012_Table!E19,+(0)) -> 131.56309 | F17: =SUM(Asset_2012_Table!F19,+(173)) -> 8400.1538 | G17: =SUM(Asset_2012_Table!G19,+(182)) -> 3581.8874 | H17: =SUM(C17:G17) -> 16834.944
B18: Total reductions in stock | C18: =SUM(C13:C17) -> 4283.445 | D18: =SUM(D13:D17) -> 8666.5799 | E18: =SUM(E13:E17) -> 408.48369 | F18: =SUM(F13:F17) -> 29677.345 | G18: =SUM(G13:G17) -> 3645.3382 | H18: =SUM(C18:G18) -> 46681.192 | I18: =SUM(I13:I17) -> 22750.764 | J18: =SUM(J13:J17) -> 22750.764
B19: Closing stock water resources | C19: =SUM(Asset_2012_Table!C24) -> 257690 | D19: =SUM(Asset_2012_Table!D24) -> 1264 | E19: =SUM(Asset_2012_Table!E24) -> 62.61347 | F19: =SUM(Asset_2012_Table!F24) -> 3388.8608 | G19: =SUM(Asset_2012_Table!G24) -> 62127 | H19: =SUM(C19:G19) -> 324532.47 | I19: 108099.1 | J19: 11659.3
I21: IRWR | J21: TRWR
I22: =SUM(I11,-I18) -> 10809.115
J23: =SUM(J11,-J18) -> 11659.318
B25: Resulting Adjustments due to balancing procedure:
B26: Units in Million Cubic Meters | C26: Surface water | F26: Soil water | G26: Groundwater | H26: Total | I26: Internal Renewable water resources | J26: Total Renewable water resources
C27: Lakes | D27: Rivers and streams | E27: Artificial reservoirs
B28: Opening stock water resources | C28: =SUM(C5,-Asset_2012_Table!C5) -> 0 | D28: =SUM(D5,-Asset_2012_Table!D5) -> 0 | E28: =SUM(E5,-Asset_2012_Table!E5) -> 0 | F28: =SUM(F5,-Asset_2012_Table!F5) -> 0 | G28: =SUM(G5,-Asset_2012_Table!G5) -> 0 | H28: =SUM(H5,-Asset_2012_Table!H5) -> 0 | I28: =SUM(I5,-Asset_2012_Table!J5) -> 0 | J28: =SUM(J5,-Asset_2012_Table!K5) -> 0
B30: Additions to stock
B31: Returns of water | C31: =SUM(C7,-Asset_2012_Table!C8) -> 0 | D31: =SUM(D7,-Asset_2012_Table!D8) -> 0 | E31: =SUM(E7,-Asset_2012_Table!E8) -> 0 | F31: =SUM(F7,-Asset_2012_Table!F8) -> 0 | G31: =SUM(G7,-Asset_2012_Table!G8) -> 0 | H31: =SUM(H7,-Asset_2012_Table!H8) -> 0
B32: Precipitation | C32: =SUM(C8,-Asset_2012_Table!C9) -> 0 | D32: =SUM(D8,-Asset_2012_Table!D9) -> 0 | E32: =SUM(E8,-Asset_2012_Table!E9) -> 0 | F32: =SUM(F8,-Asset_2012_Table!F9) -> 0 | H32: =SUM(H8,-Asset_2012_Table!H9) -> 0 | I32: =SUM(I8,-Asset_2012_Table!J9) -> 0 | J32: =SUM(J8,-Asset_2012_Table!K9) -> 0
B33: Inflows from other territories | C33: =SUM(C9,-Asset_2012_Table!C10) -> 0 | D33: =SUM(D9,-Asset_2012_Table!D10) -> 0 | E33: =SUM(E9,-Asset_2012_Table!E10) -> 0 | G33: =SUM(G9,-Asset_2012_Table!G10) -> 0 | H33: =SUM(H9,-Asset_2012_Table!H10) -> 0 | J33: =SUM(J9,-Asset_2012_Table!K10) -> 0
B34: Inflows from other inland water resources | C34: =SUM(C10,-Asset_2012_Table!C11) -> 0 | D34: =SUM(D10,-Asset_2012_Table!D11) -> 503 | E34: =SUM(E10,-Asset_2012_Table!E11) -> 47 | F34: =SUM(F10,-Asset_2012_Table!F11) -> 0 | G34: =SUM(G10,-Asset_2012_Table!G11) -> 0 | H34: =SUM(H10,-Asset_2012_Table!H11) -> 550
B35: Total additions to stock | C35: =SUM(C11,-Asset_2012_Table!C12) -> 0 | D35: =SUM(D11,-Asset_2012_Table!D12) -> 503 | E35: =SUM(E11,-Asset_2012_Table!E12) -> 47 | F35: =SUM(F11,-Asset_2012_Table!F12) -> 0 | G35: =SUM(G11,-Asset_2012_Table!G12) -> 0 | H35: =SUM(H11,-Asset_2012_Table!H12) -> 550 | I35: =SUM(I11,-Asset_2012_Table!J12) -> 0 | J35: =SUM(J11,-Asset_2012_Table!K12) -> 0
B37: Reductions in stock
B38: Abstraction of water | C38: =SUM(C13,-Asset_2012_Table!C15) -> 0 | D38: =SUM(D13,-Asset_2012_Table!D15) -> 0 | E38: =SUM(E13,-Asset_2012_Table!E15) -> 0 | F38: =SUM(F13,-Asset_2012_Table!F15) -> 0 | G38: =SUM(G13,-Asset_2012_Table!G15) -> 0 | H38: =SUM(H13,-Asset_2012_Table!H15) -> 0
B39: Evaporation and transpiration | C39: =SUM(C14,-Asset_2012_Table!C16) -> 0 | D39: =SUM(D14,-Asset_2012_Table!D16) -> 0 | E39: =SUM(E14,-Asset_2012_Table!E16) -> 0 | F39: =SUM(F14,-Asset_2012_Table!F16) -> 0 | H39: =SUM(H14,-Asset_2012_Table!H16) -> 0 | I39: =SUM(I14,-Asset_2012_Table!J16) -> 0 | J39: =SUM(J14,-Asset_2012_Table!K16) -> 0
B40: Outflows to other territories | D40: =SUM(D15,-Asset_2012_Table!D17) -> 0 | E40: =SUM(E15,-Asset_2012_Table!E17) -> 0 | G40: =SUM(G15,-Asset_2012_Table!G17) -> 0 | H40: =SUM(H15,-Asset_2012_Table!H17) -> 0
B41: Outflow to the sea | D41: =SUM(D16,-Asset_2012_Table!D18) -> 0 | E41: =SUM(E16,-Asset_2012_Table!E18) -> 0 | G41: =SUM(G16,-Asset_2012_Table!G18) -> 0 | H41: =SUM(H16,-Asset_2012_Table!H18) -> 0
B42: Outflow to other inland water resources | C42: =SUM(C17,-Asset_2012_Table!C19) -> 0 | D42: =SUM(D17,-Asset_2012_Table!D19) -> 0 | E42: =SUM(E17,-Asset_2012_Table!E19) -> 0 | F42: =SUM(F17,-Asset_2012_Table!F19) -> 173 | G42: =SUM(G17,-Asset_2012_Table!G19) -> 182 | H42: =SUM(H17,-Asset_2012_Table!H19) -> 355
B43: Total reductions in stock | C43: =SUM(C18,-Asset_2012_Table!C20) -> 0 | D43: =SUM(D18,-Asset_2012_Table!D20) -> 0 | E43: =SUM(E18,-Asset_2012_Table!E20) -> 0 | F43: =SUM(F18,-Asset_2012_Table!F20) -> 173 | G43: =SUM(G18,-Asset_2012_Table!G20) -> 182 | H43: =SUM(H18,-Asset_2012_Table!H20) -> 355 | I43: =SUM(I18,-Asset_2012_Table!J20) -> 0 | J43: =SUM(J18,-Asset_2012_Table!K20) -> 0
B45: Balancing item: | C45: =-SUM(C28,C35,-C43,-C47) -> 0 | D45: =SUM(#REF!,-Asset_2012_Table!D22) -> #REF! | E45: =SUM(#REF!,-Asset_2012_Table!E22) -> #REF! | F45: =SUM(#REF!,-Asset_2012_Table!F22) -> #REF! | G45: =SUM(#REF!,-Asset_2012_Table!G22) -> #REF! | H45: =SUM(#REF!,-Asset_2012_Table!H22) -> #REF!
B47: Closing stock water resources | C47: =SUM(Asset_2012_Table!C49) -> 0 | D47: =SUM(Asset_2012_Table!D49) -> 0 | E47: =SUM(Asset_2012_Table!E49) -> 0 | F47: =SUM(Asset_2012_Table!F49) -> 0 | G47: =SUM(Asset_2012_Table!G49) -> 0 | H47: =SUM(C47:G47) -> 0

Sheet Asset_Tbl_Balance_2012
B1: Physical asset account for water resources Year 2012 in Million m3 (BALANCED !)
B3: Units in Million Cubic Meters | C3: Surface water | F3: Soil water | G3: Groundwater | H3: Total | J3: Internal Renewable water resources | K3: Total Renewable water resources
C4: Lakes | D4: Rivers and streams | E4: Artificial reservoirs
B5: Opening stock water resources | C5: =SUM(Asset_2012_Table!C5) -> 258131.69 | D5: =SUM(Asset_2012_Table!D5) -> 1264 | E5: =SUM(Asset_2012_Table!E5) -> 60.391466 | F5: =SUM(Asset_2012_Table!F5) -> 3388.8608 | G5: =SUM(Asset_2012_Table!G5) -> 62127 | H5: =SUM(C5:G5) -> 324971.95
B7: Additions to stock
B8: Returns of water | C8: =SUM(Asset_2012_Table!C8,+(0)) -> 0.91867446 | D8: =SUM(Asset_2012_Table!D8,+(0)) -> 321.53606 | E8: =SUM(Asset_2012_Table!E8,+(0)) -> 0 | F8: =SUM(Asset_2012_Table!F8,+(0)) -> 135.73415 | G8: =SUM(Asset_2012_Table!G8,+(0)) -> 1.1483431 | H8: =SUM(C8:G8) -> 459.33723
B9: Precipitation | C9: =SUM(Asset_2012_Table!C9,+(0)) -> 2204.8333 | D9: =SUM(Asset_2012_Table!D9,+(0)) -> 2626.9654 | E9: =SUM(Asset_2012_Table!E9,+(0)) -> 107.78172 | F9: =SUM(Asset_2012_Table!F9,+(0)) -> 28620.299 | H9: =SUM(C9:G9) -> 33559.88 | J9: =+(H9) -> 33559.88 | K9: =+(H9) -> 33559.88
B10: Inflows from other territories | C10: =SUM(Asset_2012_Table!C10,+(0)) -> 0 | D10: =SUM(Asset_2012_Table!D10,+(0)) -> 850.20268 | E10: =SUM(Asset_2012_Table!E10,+(0)) -> 0 | G10: =SUM(Asset_2012_Table!G10,+(0)) -> 0 | H10: =SUM(C10:G10) -> 850.20268 | K10: =+(H10) -> 850.20268 | M10: =+H10/H17 -> 0.13221846 | N10: =+H17/H10 -> 7.5632404
B11: Inflows from other inland water resources | C11: =SUM(Asset_2012_Table!C11,+(0)) -> 1636 | D11: =SUM(Asset_2012_Table!D11,+(436)) -> 4858.52 | E11: =SUM(Asset_2012_Table!E11,+(67.2)) -> 288.326 | F11: =SUM(Asset_2012_Table!F11,+(0)) -> 911.12 | G11: =SUM(Asset_2012_Table!G11,+(0)) -> 3644.48 | H11: =SUM(C11:G11) -> 11338.446
B12: Total additions to stock | C12: =SUM(C8:C11) -> 3841.752 | D12: =SUM(D8:D11) -> 8657.2241 | E12: =SUM(E8:E11) -> 396.10772 | F12: =SUM(F8:F11) -> 29667.153 | G12: =SUM(G8:G11) -> 3645.6283 | H12: =SUM(C12:G12) -> 46207.866 | J12: =SUM(J8:J11) -> 33559.88 | K12: =SUM(K8:K11) -> 34410.082
B14: Reductions in stock
B15: Abstraction of water | C15: =SUM(Asset_2012_Table!C15,+(0)) -> 18.292297 | D15: =SUM(Asset_2012_Table!D15,+(0)) -> 314.34787 | E15: =SUM(Asset_2012_Table!E15,+(0)) -> 260.10506 | F15: =SUM(Asset_2012_Table!F15,+(0)) -> 0 | G15: =SUM(Asset_2012_Table!G15,+(0)) -> 63.450817 | H15: =SUM(C15:G15) -> 656.19604
B16: Actual Evaporation and transpiration | C16: =SUM(Asset_2012_Table!C16,+(0)) -> 1400.9385 | D16: =SUM(Asset_2012_Table!D16,+(0)) -> 55.818756 | E16: =SUM(Asset_2012_Table!E16,+(0)) -> 16.815536 | F16: =SUM(Asset_2012_Table!F16,+(0)) -> 21277.192 | H16: =SUM(C16:G16) -> 22750.764 | J16: =+(H16) -> 22750.764 | K16: =+(H16) -> 22750.764
B17: Outflows to other territories | D17: =SUM(Asset_2012_Table!D17,+(-9)) -> 6430.2872 | E17: =SUM(Asset_2012_Table!E17,+(0)) -> 0 | G17: =SUM(Asset_2012_Table!G17,+(0)) -> 0 | H17: =SUM(C17:G17) -> 6430.2872 | N17: =+H17-H10 -> 5580.0846 | O17: =+N17/H5 -> 0.017170973 | P17: =+N17/K9 -> 0.16627248
B18: Outflow to the sea | D18: =SUM(Asset_2012_Table!D18,+(0)) -> 0 | E18: =SUM(Asset_2012_Table!E18,+(0)) -> 0 | G18: =SUM(Asset_2012_Table!G18,+(0)) -> 0 | H18: =SUM(C18:G18) -> 0 | P18: =+N17/K28 -> 0.47859443
B19: Outflow to other inland water resources | C19: =SUM(Asset_2012_Table!C19,+(0)) -> 2864.2141 | D19: =SUM(Asset_2012_Table!D19,+(0)) -> 1857.126 | E19: =SUM(Asset_2012_Table!E19,+(-15)) -> 116.56309 | F19: =SUM(Asset_2012_Table!F19,+(163)) -> 8390.1538 | G19: =SUM(Asset_2012_Table!G19,+(182)) -> 3581.8874 | H19: =SUM(C19:G19) -> 16809.944
B20: Total reductions in stock | C20: =SUM(C15:C19) -> 4283.445 | D20: =SUM(D15:D19) -> 8657.5799 | E20: =SUM(E15:E19) -> 393.48369 | F20: =SUM(F15:F19) -> 29667.345 | G20: =SUM(G15:G19) -> 3645.3382 | H20: =SUM(C20:G20) -> 46647.192 | J20: =SUM(J15:J19) -> 22750.764 | K20: =SUM(K15:K19) -> 22750.764
B22: Balancing item: | C22: =-SUM(C5,C12,-C20,-C24) -> 0 | D22: =-SUM(D5,D12,-D20,-D24) -> 0.35573589 | E22: =-SUM(E5,E12,-E20,-E24) -> -0.40202736 | F22: =-SUM(F5,F12,-F20,-F24) -> 0.19205687 | G22: =-SUM(G5,G12,-G20,-G24) -> -0.29014606 | H22: =SUM(C22:G22) -> -0.14438065
B24: Closing stock water resources | C24: =SUM(Asset_2012_Table!C24) -> 257690 | D24: =SUM(Asset_2012_Table!D24) -> 1264 | E24: =SUM(Asset_2012_Table!E24) -> 62.61347 | F24: =SUM(Asset_2012_Table!F24) -> 3388.8608 | G24: =SUM(Asset_2012_Table!G24) -> 62127 | H24: =SUM(C24:G24) -> 324532.47 | M24: =+H24-H5 -> -439.47096 | N24: =+M24/H5 -> -0.0013523351
J26: IRWR | K26: TRWR
J27: =SUM(J12,-J20) -> 10809.115
K28: =SUM(K12,-K20) -> 11659.318
B30: Resulting Adjustments due to balancing procedure:
B31: Units in Million Cubic Meters | C31: Surface water | F31: Soil water | G31: Groundwater | H31: Total | J31: Internal Renewable water resources | K31: Total Renewable water resources
C32: Lakes | D32: Rivers and streams | E32: Artificial reservoirs
B33: Opening stock water resources | C33: =SUM(C5,-Asset_2012_Table!C5) -> 0 | D33: =SUM(D5,-Asset_2012_Table!D5) -> 0 | E33: =SUM(E5,-Asset_2012_Table!E5) -> 0 | F33: =SUM(F5,-Asset_2012_Table!F5) -> 0 | G33: =SUM(G5,-Asset_2012_Table!G5) -> 0 | H33: =SUM(H5,-Asset_2012_Table!H5) -> 0 | J33: =SUM(J5,-Asset_2012_Table!J5) -> 0 | K33: =SUM(K5,-Asset_2012_Table!K5) -> 0
B35: Additions to stock
B36: Returns of water | C36: =SUM(C8,-Asset_2012_Table!C8) -> 0 | D36: =SUM(D8,-Asset_2012_Table!D8) -> 0 | E36: =SUM(E8,-Asset_2012_Table!E8) -> 0 | F36: =SUM(F8,-Asset_2012_Table!F8) -> 0 | G36: =SUM(G8,-Asset_2012_Table!G8) -> 0 | H36: =SUM(H8,-Asset_2012_Table!H8) -> 0
B37: Precipitation | C37: =SUM(C9,-Asset_2012_Table!C9) -> 0 | D37: =SUM(D9,-Asset_2012_Table!D9) -> 0 | E37: =SUM(E9,-Asset_2012_Table!E9) -> 0 | F37: =SUM(F9,-Asset_2012_Table!F9) -> 0 | H37: =SUM(H9,-Asset_2012_Table!H9) -> 0 | J37: =SUM(J9,-Asset_2012_Table!J9) -> 0 | K37: =SUM(K9,-Asset_2012_Table!K9) -> 0
B38: Inflows from other territories | C38: =SUM(C10,-Asset_2012_Table!C10) -> 0 | D38: =SUM(D10,-Asset_2012_Table!D10) -> 0 | E38: =SUM(E10,-Asset_2012_Table!E10) -> 0 | G38: =SUM(G10,-Asset_2012_Table!G10) -> 0 | H38: =SUM(H10,-Asset_2012_Table!H10) -> 0 | K38: =SUM(K10,-Asset_2012_Table!K10) -> 0
B39: Inflows from other inland water resources | C39: =SUM(C11,-Asset_2012_Table!C11) -> 0 | D39: =SUM(D11,-Asset_2012_Table!D11) -> 436 | E39: =SUM(E11,-Asset_2012_Table!E11) -> 67.2 | F39: =SUM(F11,-Asset_2012_Table!F11) -> 0 | G39: =SUM(G11,-Asset_2012_Table!G11) -> 0 | H39: =SUM(H11,-Asset_2012_Table!H11) -> 503.2
B40: Total additions to stock | C40: =SUM(C12,-Asset_2012_Table!C12) -> 0 | D40: =SUM(D12,-Asset_2012_Table!D12) -> 436 | E40: =SUM(E12,-Asset_2012_Table!E12) -> 67.2 | F40: =SUM(F12,-Asset_2012_Table!F12) -> 0 | G40: =SUM(G12,-Asset_2012_Table!G12) -> 0 | H40: =SUM(H12,-Asset_2012_Table!H12) -> 503.2 | J40: =SUM(J12,-Asset_2012_Table!J12) -> 0 | K40: =SUM(K12,-Asset_2012_Table!K12) -> 0
B42: Reductions in stock
B43: Abstraction of water | C43: =SUM(C15,-Asset_2012_Table!C15) -> 0 | D43: =SUM(D15,-Asset_2012_Table!D15) -> 0 | E43: =SUM(E15,-Asset_2012_Table!E15) -> 0 | F43: =SUM(F15,-Asset_2012_Table!F15) -> 0 | G43: =SUM(G15,-Asset_2012_Table!G15) -> 0 | H43: =SUM(H15,-Asset_2012_Table!H15) -> 0
B44: Evaporation and transpiration | C44: =SUM(C16,-Asset_2012_Table!C16) -> 0 | D44: =SUM(D16,-Asset_2012_Table!D16) -> 0 | E44: =SUM(E16,-Asset_2012_Table!E16) -> 0 | F44: =SUM(F16,-Asset_2012_Table!F16) -> 0 | H44: =SUM(H16,-Asset_2012_Table!H16) -> 0 | J44: =SUM(J16,-Asset_2012_Table!J16) -> 0 | K44: =SUM(K16,-Asset_2012_Table!K16) -> 0
B45: Outflows to other territories | D45: =SUM(D17,-Asset_2012_Table!D17) -> -9 | E45: =SUM(E17,-Asset_2012_Table!E17) -> 0 | G45: =SUM(G17,-Asset_2012_Table!G17) -> 0 | H45: =SUM(H17,-Asset_2012_Table!H17) -> -9
B46: Outflow to the sea | D46: =SUM(D18,-Asset_2012_Table!D18) -> 0 | E46: =SUM(E18,-Asset_2012_Table!E18) -> 0 | G46: =SUM(G18,-Asset_2012_Table!G18) -> 0 | H46: =SUM(H18,-Asset_2012_Table!H18) -> 0
B47: Outflow to other inland water resources | C47: =SUM(C19,-Asset_2012_Table!C19) -> 0 | D47: =SUM(D19,-Asset_2012_Table!D19) -> 0 | E47: =SUM(E19,-Asset_2012_Table!E19) -> -15 | F47: =SUM(F19,-Asset_2012_Table!F19) -> 163 | G47: =SUM(G19,-Asset_2012_Table!G19) -> 182 | H47: =SUM(H19,-Asset_2012_Table!H19) -> 330
B48: Total reductions in stock | C48: =SUM(C20,-Asset_2012_Table!C20) -> 0 | D48: =SUM(D20,-Asset_2012_Table!D20) -> -9 | E48: =SUM(E20,-Asset_2012_Table!E20) -> -15 | F48: =SUM(F20,-Asset_2012_Table!F20) -> 163 | G48: =SUM(G20,-Asset_2012_Table!G20) -> 182 | H48: =SUM(H20,-Asset_2012_Table!H20) -> 321 | J48: =SUM(J20,-Asset_2012_Table!J20) -> 0 | K48: =SUM(K20,-Asset_2012_Table!K20) -> 0
B50: Balancing item: | C50: =-SUM(C33,C40,-C48,-C52) -> 0 | D50: =SUM(D22,-Asset_2012_Table!D22) -> -445 | E50: =SUM(E22,-Asset_2012_Table!E22) -> -82.2 | F50: =SUM(F22,-Asset_2012_Table!F22) -> 163 | G50: =SUM(G22,-Asset_2012_Table!G22) -> 182 | H50: =SUM(H22,-Asset_2012_Table!H22) -> -182.2
B52: Closing stock water resources | C52: =SUM(Asset_2012_Table!C49) -> 0 | D52: =SUM(Asset_2012_Table!D49) -> 0 | E52: =SUM(Asset_2012_Table!E49) -> 0 | F52: =SUM(Asset_2012_Table!F49) -> 0 | G52: =SUM(Asset_2012_Table!G49) -> 0 | H52: =SUM(C52:G52) -> 0

Sheet PSUT_Data&Method_2012
D1: ISIC Code | E1: Industries (by ISIC categories) | G1: Description | H1: Volume in 1000 m3 | I1: Source / Institution | J1: Period of collected Data | K1: Explanations / Assumptions
B2: SEEAW Standard Table I: Physical use table | D2: 1-3 | E2: A. Agriculture, forestry and fishing | G2: 1 - Total abstraction (=1.a+1.b = 1.i+1.ii) | H2: =SUM(H3:H4) -> 13563381
G3: 1.a Abstraction for own use | H3: =+(H5) -> 13563381 | K3: 807m3 from Master Plan and other from our own survey
G4: 1.b Abstraction for distribution | H4: 0
G5: 1 - Total abstraction (1.i+1.ii) | H5: =SUM(H6+H16) -> 13563381
G6: 1.i From water resources: | H6: =SUM(H7,H12,H15) -> 13562574
G7: 1.i.1 Surface water | H7: =SUM(H8:H11) -> 189335.69
G8: 1.i.1.a Lakes | H8: =+('RBM&E-2017_S'!T$30*7%) -> 13252.297 | K8: NCA-Team: Looking after RBM&E_2017 study on reporting year 2016, what can we learn from the different categories of 'water use' in this study that can be allocated to stemming from the Rwanda Lakes for this year?
G9: 1.i.1.b Rivers | H9: =+('RBM&E-2017_S'!T$30*58%) -> 109804.75 | K9: See: line 11, posibly abstraction from Surface Water from Rivers is covered by that line already!? Prevent from double counting.
G10: 1.i.1.c Reservoirs (Dams, ponds, ..) | H10: =+('RBM&E-2017_S'!T$30*25%)+('RBM&E-2017_S'!T$34*60%) -> 47346.795 | K10: NCA-Team: Start from figure of RBM&E_2017 study on reporting year 2016 and do kind of 'backasting', in order to arrive at 2012 reporting year. And use expert knowledge on the development of irrigation levels over time from 2012 - 2016. The 2016 figure is 157,982,745.60 mln m3 for hydro power and for irrigation: 222,328,965.00 mln m3. From PPT for 2012 we have 162 mln m3 / yr (for 40.5 kha and 4000/ha/yr) and 35 mln m3 / yr for hillside irrigation (for 5kha and 7000 m3/ha/yr). together is 197 mln m3 for 2012. Distribute the volume of RBM&E_2017 study over 1.lakes (7%?), 2.Rivers (58%?) and 3.Artificial Reservoirs (25%?) and 4. Combined River & Reservoirs (Dams, ponds, ..) (10%). See also: 2012NWRMP', 2012 figure on irrigation (?). And come up with solution. Was: 197,000.0
G11: 1.i.1.d Combined River & Reservoirs (Dams, ponds, ..) | H11: =+('RBM&E-2017_S'!T$30*10%) -> 18931.853 | K11: ? Team check please: Small-scale irrigation: Possibly this represents the water taken from rivers transported via the small canals (Weirs) to the fields. Was: 31,537.0.
G12: 1.i.2 Groundwater | H12: =SUM(H13:H14) -> 13829.735
G13: 1.i.2.a From Boreholes | H13: =(5657.79959)*(75%*100%) -> 4243.3497 | K13: NCA-Team: Start from figure of RBM&E_2017 study, including BOREHOLES on reporting year 2016 and do kind of 'backasting', in order to arrive at water volume for 2012 reporting year. Possibly use expert knowledge (from NCA-Water & IWRM) on the development of water use volumes from Boreholes over time from 2012 - 2016. The 2016 figure for Boreholes is 5,657,799.59 mln m3. We need to discover which part goes to agriculture (75% ?), and which part goes to the other industries (ISIC - categories) !? And: We need to correct and trace back ('backcast') the volume in previous years all back to reportingyear 2012 and find the right volume (mln m3). As a proposal start as a share with 2012 being 90% of 2016. Please check this on plausibility. See also: 2012NWRMP', has this 2012 figure on water obtained from boreholes .. (?). And come up with final bid for 2012. Source: ... & Link ? Correct??
G14: 1.i.2.b From Springs | H14: =+('RBM&E-2017_S'!T$33*25%) -> 9586.3855 | K14: NCA-Team: Start from figure of RBM&E_2017 study on reporting year 2016 and do kind of 'backasting', in order to arrive at 2012 reporting year. And use expert knowledge on the development of Water Use levels from Spring irrigation by Households and maybe agriculture over time from 2012 - 2016. Distribute the volume of RBM&E_2017 study over 1.households (70%?) and 2.agriculture (30%?) and 3. ... (any other?) (X %?). See also: 2012NWRMP', 2012 figure on irrigation (?). And come up with solution. Was: =(39118.22402)*(75%*90%) = 26.405. As a proposal Was: We need to discover (or judge) which part goes to agriculture (75% ?), and which part goes to the other industries (ISIC - categories). And further need to choose a trend for reporting year 2012 as a trend comparing to 90% of 2016. Please check on plausibility.
G15: 1.i.3 Soil water (green water) | H15: =+('GW&SOILW_2012'!B20) -> 13359408
G16: 1.ii From other sources | H16: =SUM(H17:H18) -> 807
G17: 1.ii.1 Collection of precipitation (rainwater harvesting; ..) | H17: 807 | K17: Source:
G18: 1.ii.2 Abstraction from the sea | H18: 0
G19: 2. Use of water received from other economic units | H19: 90250 | K19: Source:
D20: 6-8 | E20: B. Mining and Quarrying | G20: 1 - Total abstraction (=1.a+1.b = 1.i+1.ii) | H20: =SUM(H21:H22) -> 22390.659
G21: 1.a Abstraction for own use | H21: =SUM(H23,-H22) -> 22390.659 | K21: Was: 1,309,600.65 Source was: from previous data collection NCA - team water. Now prefer to rely upon RBM&E2017 study, also needed to obtain consistency!
G22: 1.b Abstraction for distribution | H22: 0 | K22: Please check if correct?!
G23: 1 - Total abstraction (1.i+1.ii) | H23: =SUM(H24+H34) -> 22390.659 | K23: Please check if correct?!
G24: 1.i From water resources: | H24: =SUM(H25,H30,H33) -> 1030.8589
G25: 1.i.1 Surface water | H25: =SUM(H26:H29) -> 967.07073
G26: 1.i.1.a Lakes | H26: 0
G27: 1.i.1.b Rivers | H27: =+('RBM&E-2017_S'!T$32*100%) -> 967.07073 | K27: NWRMP - Mining - 2012 - Country wide: This was 4,007,000 m3. Now: Use the values from the RBM&E - Report 2017 directly, on the water used by Mining sector.
G28: 1.i.1.c Reservoirs (Dams, ponds, ..) | H28: 0
G29: 1.i.1.d Combined River & Reservoirs (Dams, ponds, ..) | H29: 0
G30: 1.i.2 Groundwater | H30: 63.78813 | K30: Was: 63,78813. Source: … ? Can this get further breakdown underneath for distribution over Boreholes and Springs ? In H85 to: 1.i.2.a From Boreholes and In H86 to: 1.i.2.b From Springs
G31: 1.i.2.a From Boreholes
G32: 1.i.2.b From Springs | H32: =SUM(H30,-H31) -> 63.78813
G33: 1.i.3 Soil water (green water) | H33: 0
G34: 1.ii From other sources | H34: =SUM(H35:H36) -> 21359.8
G35: 1.ii.1 Collection of precipitation (rainwater harvesting; ..) | H35: 21359.8 | K35: Source: was from previous data collection NCA - team water (?)
G36: 1.ii.2 Abstraction from the sea | H36: 0
G37: 2. Use of water received from other economic units | H37: 0
D38: 10-13; 22, 32 | E38: C. Manufacturing | G38: 1 - Total abstraction (=1.a+1.b = 1.i+1.ii) | H38: =SUM(H39:H40) -> 23638.125
G39: 1.a Abstraction for own use | H39: =SUM(H41,-H40) -> 23552.35 | K39: Was 684.521 Source: ?? Figure must align with: '1 - Total abstraction (1.i+1.ii)'. Adjusted.
G40: 1.b Abstraction for distribution | H40: 85.775 | K40: Source: ??
G41: 1 - Total abstraction (1.i+1.ii) | H41: =SUM(H42+H52) -> 23638.125
G42: 1.i From water resources: | H42: =SUM(H43,H48,H51) -> 23609.925 | K42: Sum: all from RBM&E study
G43: 1.i.1 Surface water | H43: =SUM(H44:H47) -> 14844.848
G44: 1.i.1.a Lakes | H44: 0
G45: 1.i.1.b Rivers | H45: =+('RBM&E-2017_S'!T$28*100%)+(0) -> 11482.405 | K45: Was Hardcopy: 8,078,000 m3 Now Linked to RBM&E: 11,482,000 m3 (just covering the 'Coffee Washing Stations') … / (what about use from rivers by other industries manufacturing (ISIC - C) ??
G46: 1.i.1.c Reservoirs (Dams, ponds, ..) | H46: 0
G47: 1.i.1.d Combined River & Reservoirs (Dams, ponds, ..) | H47: =+('RBM&E-2017_S'!T$31*50%) -> 3362.443 | K47: 50% Ok?
G48: 1.i.2 Groundwater | H48: =SUM(H49:H50) -> 8765.0769 | K48: Was: 741,096
G49: 1.i.2.a From Boreholes | H49: =+('RBM&E-2017_S'!T$27*30%)+('RBM&E-2017_S'!T$31*25%) -> 3249.3012 | K49: NCA-Team: Start from figure of RBM&E_2017 study, including BOREHOLES on reporting year 2016 and do kind of 'backasting', in order to arrive at water volume for 2012 reporting year. Possibly use expert knowledge (from NCA-Water & IWRM) on the development of water use volumes from Boreholes over time from 2012 - 2016. The 2016 figure for Boreholes is 5,657,799.59 mln m3. We need to discover which part goes to agriculture (75% ?), and which part goes to the other industries (ISIC - categories) !? And: We need to correct and trace back ('backcast') the volume in previous years all back to reportingyear 2012 and find the right volume (mln m3). As a proposal start as a share with 2012 being 90% of 2016. Please check this on plausibility. See also: 2012NWRMP', has this 2012 figure on water obtained from boreholes .. (?). And come up with final bid for 2012. 30% Ok? & 25% Ok?
G50: 1.i.2.b From Springs | H50: =+('RBM&E-2017_S'!T$33*10%)+('RBM&E-2017_S'!T$31*25%) -> 5515.7757 | K50: NCA-Team: Start from figure of RBM&E_2017 study on reporting year 2016 and do kind of 'backasting', in order to arrive at 2012 reporting year. And use expert knowledge on the development of Water Use levels from Spring irrigation by Households and maybe agriculture over time from 2012 - 2016. Distribute the volume of RBM&E_2017 study over 1.households (70%?) and 2.agriculture (30%?) and 3. ... (any other?) (X %?). See also: 2012NWRMP', 2012 figure on irrigation (?). And come up with solution. Was: ... . As a proposal Was: We need to discover (or judge) which part goes to agriculture (25% ?), and which part goes to the other industries (ISIC - categories), 10 percent to manufacturing (10%) and households (65%). And see again the trend (in timeseries) for reporting year 2012 as a trend comparing to 90% or else compared to 2016. Please check on plausibility.
G51: 1.i.3 Soil water (green water) | H51: 0
G52: 1.ii From other sources | H52: =SUM(H53:H54) -> 28.2
G53: 1.ii.1 Collection of precipitation (rainwater harvesting; ..) | H53: 28.2 | K53: Source: …
G54: 1.ii.2 Abstraction from the sea | H54: 0
G55: 2. Use of water received from other economic units | H55: 642763.79 | K55: Source:
D56: 35 | E56: D. Electricity, gas, steam and air conditioning supply | G56: 1 - Total abstraction (=1.a+1.b = 1.i+1.ii) | H56: =SUM(H57:H58) -> 335270.17
G57: 1.a Abstraction for own use | H57: =SUM(H59,-H58) -> 335270.17
G58: 1.b Abstraction for distribution | H58: 0
G59: 1 - Total abstraction (1.i+1.ii) | H59: =SUM(H60+H70) -> 335270.17
G60: 1.i From water resources: | H60: =SUM(H61,H66,H69) -> 335270.17
G61: 1.i.1 Surface water | H61: =SUM(H62:H65) -> 335270.17
G62: 1.i.1.a Lakes | H62: 0
G63: 1.i.1.b Rivers | H63: =+(('RBM&E-2017_S'!T29)*100%) -> 145951.64 | K63: From rivers: October 2017: From 15.6 Mln m3 To: January 2018: 2,215.0 Mln m3 ??? --> A factor of about 150 difference ! To: March 2018: RBM&E 2012: 213 mln m3 from just Rivers !!
G64: 1.i.1.c Reservoirs (Dams, ponds, ..) | H64: =+(('RBM&E-2017_S'!T30)*100%) -> 189318.53 | K64: What is the water volume (m3) from Artificial Reservoirs used for hydro generation? This is In-stream use, meaning it largely remains in the Inland Water System. --> This means: - Is 'Water use' - But is NOT perse 'Water consumption' !
G65: 1.i.1.d Combined River & Reservoirs (Dams, ponds, ..) | H65: 0
G66: 1.i.2 Groundwater | H66: =SUM(H67:H68) -> 0
G67: 1.i.2.a From Boreholes
G68: 1.i.2.b From Springs
G69: 1.i.3 Soil water (green water) | H69: 0
G70: 1.ii From other sources | H70: =SUM(H71:H72) -> 0
G71: 1.ii.1 Collection of precipitation (rainwater harvesting; ..) | H71: 0
G72: 1.ii.2 Abstraction from the sea | H72: 0
G73: 2. Use of water received from other economic units | H73: 0
D74: 36-38 | E74: E. Water supply (WASAC & AquaVirunga) | G74: 1 - Total abstraction (=1.a+1.b = 1.i+1.ii) | H74: =SUM(H75:H76) -> 53008.786
G75: 1.a Abstraction for own use | H75: 3212.9128 | K75: Source: … ?
G76: 1.b Abstraction for distribution | H76: =+('RBM&E-2017_S'!T$35*100%)-(3212.9128) -> 49795.874 | K76: Was: 36,963,000 m3. Source: … ? Now 2018: NCA-Team: Start from figure of RBM&E_2017 study, including the water used by: 'Section E: Water supply; sewerage, waste management etc - 36 (Division) - Water collection, treatment and supply' on reporting year 2016 and via kind of 'backasting' in order to arrive at water volume for 2012 reporting year. Here also apply expert knowledge (from NCA-Water & IWRM) on the development, the trend of water use volumes from Boreholes over time from 2012 - 2016 by implmenting indexes. The 2016 figure for Section E water use is 53,008,,790 mln m3. We need to discover which part goes to ... (75% ?), and which part comes from surface water (ricvers) and which part comes from groundwater ... ( %) !?. Apply distribution, following previous data (based upon WASAC distribution). See evt. also: 2012NWRMP', has this 2012 figure on water for Public Water Supply. And confront after growth with 2012 figure.
G77: 1 - Total abstraction (1.i+1.ii) | H77: =SUM(H78+H88) -> 53008.786 | K77: Was: 40,176,000 m3. Source: … ? Now 2018: NCA-Team: Start from figure of RBM&E_2017 study, including the water used by: 'Section E: Water supply; sewerage, waste management etc - 36 (Division) - Water collection, treatment and supply' on reporting year 2016 and via kind of 'backasting' in order to arrive at water volume for 2012 reporting year. Here also apply expert knowledge (from NCA-Water & IWRM) on the development, the trend of water use volumes from Boreholes over time from 2012 - 2016 by implmenting indexes. The 2016 figure for Section E water use is 53,008,,790 mln m3. We need to discover which part goes to ... (75% ?), and which part comes from surface water (ricvers) and which part comes from groundwater ... ( %) !?. Apply distribution, following previous data (based upon WASAC distribution). See evt. also: 2012NWRMP', has this 2012 figure on water for Public Water Supply. And confront after growth with 2012 figure.
G78: 1.i From water resources: | H78: =SUM(H79,H84,H87) -> 53008.786
G79: 1.i.1 Surface water | H79: =SUM(H80:H83) -> 41023.931
G80: 1.i.1.a Lakes | H80: 0 | K80: At lake Muhazi, Mugesera, Cyohoha - South, there is abstraction for water treatment plants. Data from RBM&E project data.
G81: 1.i.1.b Rivers | H81: =+('RBM&E-2017_S'!T$35*(31092229.6/40175607.8)) -> 41023.931 | K81: Was: 31,092,000 m3. Source: … ? Now 2018: NCA-Team: Start from figure of RBM&E_2017 study, including the water used by: 'Section E: Water supply; sewerage, waste management etc - 36 (Division) - Water collection, treatment and supply' on reporting year 2016 and via kind of 'backasting' in order to arrive at water volume for 2012 reporting year. Apply Ratio old: 31,092,229.6 / (31,092,229.6 + 9,083,378.2) = 31,092,229.6 / 40,175,607.8
G82: 1.i.1.c Reservoirs (Dams, ponds, ..) | H82: 0
G83: 1.i.1.d Combined River & Reservoirs (Dams, ponds, ..) | H83: 0
G84: 1.i.2 Groundwater | H84: =+('RBM&E-2017_S'!T$35*(9083378.2/40175607.8)) -> 11984.856 | K84: Was: 9,083,000 m3. Source: … ? Now 2018: NCA-Team: Start from figure of RBM&E_2017 study, including the water used by: 'Section E: Water supply; sewerage, waste management etc - 36 (Division) - Water collection, treatment and supply' on reporting year 2016 and via kind of 'backasting' in order to arrive at water volume for 2012 reporting year. Apply Ratio old: 31,092,229.6 / (31,092,229.6 + 9,083,378.2) = 9,083,378.2 / 40,175,607.8 --> Can this get further breakdown underneath over Boreholes and Springs: In H85 to: 1.i.2.a From Boreholes and In H86 to: 1.i.2.b From Springs
G85: 1.i.2.a From Boreholes | K85: Share of cell L85: 1.i.2 Groundwater …?
G86: 1.i.2.b From Springs | H86: =SUM(H84,-H85) -> 11984.856 | K86: Share of cell L85: 1.i.2 Groundwater …?
G87: 1.i.3 Soil water (green water) | H87: 0
G88: 1.ii From other sources | H88: =SUM(H89:H90) -> 0
G89: 1.ii.1 Collection of precipitation (rainwater harvesting; ..) | H89: 0
G90: 1.ii.2 Abstraction from the sea | H90: 0
G91: 2. Use of water received from other economic units | H91: 0
E92: F. Construction | G92: 1 - Total abstraction (=1.a+1.b = 1.i+1.ii) | H92: =SUM(H93:H94) -> 0
G93: 1.a Abstraction for own use
G94: 1.b Abstraction for distribution
G95: 1 - Total abstraction (1.i+1.ii) | H95: =SUM(H96+H106) -> 0
G96: 1.i From water resources: | H96: =SUM(H97,H102,H105) -> 0
G97: 1.i.1 Surface water | H97: =SUM(H98:H101) -> 0
G98: 1.i.1.a Lakes
G99: 1.i.1.b Rivers
G100: 1.i.1.c Reservoirs (Dams, ponds, ..)
...

Sheet PSUT_2012
B1: SEEA Physical Account for water | C1: SEEA-W Physical Supply - Use Table Year 2012 (1000 m3)
B2: 2012 | C2: Physical units: 1000 m3
A3: '000 m3 | C3: Industries (by ISIC categories) | W3: Total Production activities | Y3: U. Activities of extraterritorial organizations and bodies | Z3: Rest of the world | AA3: Total
C4: A. Agriculture, forestry and fishing | D4: B. Mining and Quarrying | E4: C. Manufacturing | F4: D. Electricity, gas, steam and air conditioning supply | G4: E. Water supply (WASAC & AquaVirunga) | H4: F. Construction | I4: G. Wholesale and retail trade; repair of motor vehicles and motorcycles | J4: H. Transportation and storage | K4: I. Accommodation and food service activities | L4: J. Information and communication | M4: K. Banking and insurance activities | N4: L. Real estate activities | O4: M. Professional, scientific and technical activities | P4: N. Administrative and support service activities | Q4: O. Public administration and defence; compulsory social security | R4: P. Education | S4: Q. Human health and social work activities | T4: R. Arts, entertainment and recreation | U4: S. Other service activities (Religious & Burial) | V4: T. Activities of households as employers; undifferentiated goods- and services-producing activities of households for own use | X4: Households
B5: ISIC-Rev.4 Code: | C5: 1-3 | D5: 6-8 | E5: 10-13. 22, 32 | F5: 35 | G5: 36-38 | K5: 55-56 | M5: 64-66, 71-72, 75 | R5: 85 | S5: 86, 88 | U5: 94, 96 | W5: Total | X5: 98 | Y5: 99
A6: From the environment | B6: 1 - Total abstraction (=1.a+1.b = 1.i+1.ii) | C6: ='PSUT_Data&Method_2012'!H2 -> 13563381 | D6: ='PSUT_Data&Method_2012'!H20 -> 22390.659 | E6: ='PSUT_Data&Method_2012'!H38 -> 23638.125 | F6: ='PSUT_Data&Method_2012'!H56 -> 335270.17 | G6: ='PSUT_Data&Method_2012'!H74 -> 53008.786 | H6: ='PSUT_Data&Method_2012'!H92 -> 0 | I6: ='PSUT_Data&Method_2012'!H110 -> 0 | J6: ='PSUT_Data&Method_2012'!H128 -> 0 | K6: ='PSUT_Data&Method_2012'!H146 -> 0 | L6: ='PSUT_Data&Method_2012'!H164 -> 0 | M6: ='PSUT_Data&Method_2012'!H182 -> 0.06 | N6: ='PSUT_Data&Method_2012'!H200 -> 0 | O6: ='PSUT_Data&Method_2012'!H218 -> 0 | P6: ='PSUT_Data&Method_2012'!H236 -> 0 | Q6: ='PSUT_Data&Method_2012'!H254 -> 0 | R6: ='PSUT_Data&Method_2012'!H272 -> 133.1154 | S6: ='PSUT_Data&Method_2012'!H290 -> 588.77952 | T6: ='PSUT_Data&Method_2012'!H308 -> 0 | U6: ='PSUT_Data&Method_2012'!H326 -> 11.7096 | V6: ='PSUT_Data&Method_2012'!H344 -> 0 | W6: =SUM(C6:V6) -> 13998422 | X6: ='PSUT_Data&Method_2012'!H365 -> 40434.896 | Y6: ='PSUT_Data&Method_2012'!H383 -> 0 | AA6: =W6+X6+Y6 -> 14038857
B7: 1.a Abstraction for own use | C7: ='PSUT_Data&Method_2012'!H3 -> 13563381 | D7: ='PSUT_Data&Method_2012'!H21 -> 22390.659 | E7: ='PSUT_Data&Method_2012'!H39 -> 23552.35 | F7: ='PSUT_Data&Method_2012'!H57 -> 335270.17 | G7: ='PSUT_Data&Method_2012'!H75 -> 3212.9128 | H7: ='PSUT_Data&Method_2012'!H93 -> 0 | I7: ='PSUT_Data&Method_2012'!H111 -> 0 | J7: ='PSUT_Data&Method_2012'!H129 -> 0 | K7: ='PSUT_Data&Method_2012'!H147 -> 0 | L7: ='PSUT_Data&Method_2012'!H165 -> 0 | M7: ='PSUT_Data&Method_2012'!H183 -> 0.06 | N7: ='PSUT_Data&Method_2012'!H201 -> 0 | O7: ='PSUT_Data&Method_2012'!H219 -> 0 | P7: ='PSUT_Data&Method_2012'!H237 -> 0 | Q7: ='PSUT_Data&Method_2012'!H255 -> 0 | R7: ='PSUT_Data&Method_2012'!H273 -> 133.1154 | S7: ='PSUT_Data&Method_2012'!H291 -> 588.77952 | T7: ='PSUT_Data&Method_2012'!H309 -> 0 | U7: ='PSUT_Data&Method_2012'!H327 -> 11.7096 | V7: ='PSUT_Data&Method_2012'!H345 -> 0 | W7: =SUM(C7:V7) -> 13948540 | X7: ='PSUT_Data&Method_2012'!H366 -> 40434.896 | Y7: ='PSUT_Data&Method_2012'!H384 -> 0 | AA7: =W7+X7+Y7 -> 13988975
B8: 1.b Abstraction for distribution | C8: ='PSUT_Data&Method_2012'!H4 -> 0 | D8: ='PSUT_Data&Method_2012'!H22 -> 0 | E8: ='PSUT_Data&Method_2012'!H40 -> 85.775 | F8: ='PSUT_Data&Method_2012'!H58 -> 0 | G8: ='PSUT_Data&Method_2012'!H76 -> 49795.874 | H8: ='PSUT_Data&Method_2012'!H94 -> 0 | I8: ='PSUT_Data&Method_2012'!H112 -> 0 | J8: ='PSUT_Data&Method_2012'!H130 -> 0 | K8: ='PSUT_Data&Method_2012'!H148 -> 0 | L8: ='PSUT_Data&Method_2012'!H166 -> 0 | M8: ='PSUT_Data&Method_2012'!H184 -> 0 | N8: ='PSUT_Data&Method_2012'!H202 -> 0 | O8: ='PSUT_Data&Method_2012'!H220 -> 0 | P8: ='PSUT_Data&Method_2012'!H238 -> 0 | Q8: ='PSUT_Data&Method_2012'!H256 -> 0 | R8: ='PSUT_Data&Method_2012'!H274 -> 0 | S8: ='PSUT_Data&Method_2012'!H292 -> 0 | T8: ='PSUT_Data&Method_2012'!H310 -> 0 | U8: ='PSUT_Data&Method_2012'!H328 -> 0 | V8: ='PSUT_Data&Method_2012'!H346 -> 0 | W8: =SUM(C8:V8) -> 49881.649 | X8: ='PSUT_Data&Method_2012'!H367 -> 0 | Y8: ='PSUT_Data&Method_2012'!H385 -> 0 | AA8: =W8+X8+Y8 -> 49881.649
B9: 1 - Total abstraction (1.i+1.ii) | C9: ='PSUT_Data&Method_2012'!H5 -> 13563381 | D9: ='PSUT_Data&Method_2012'!H23 -> 22390.659 | E9: ='PSUT_Data&Method_2012'!H41 -> 23638.125 | F9: ='PSUT_Data&Method_2012'!H59 -> 335270.17 | G9: ='PSUT_Data&Method_2012'!H77 -> 53008.786 | H9: ='PSUT_Data&Method_2012'!H95 -> 0 | I9: ='PSUT_Data&Method_2012'!H113 -> 0 | J9: ='PSUT_Data&Method_2012'!H131 -> 0 | K9: ='PSUT_Data&Method_2012'!H149 -> 0 | L9: ='PSUT_Data&Method_2012'!H167 -> 0 | M9: ='PSUT_Data&Method_2012'!H185 -> 0.06 | N9: ='PSUT_Data&Method_2012'!H203 -> 0 | O9: ='PSUT_Data&Method_2012'!H221 -> 0 | P9: ='PSUT_Data&Method_2012'!H239 -> 0 | Q9: ='PSUT_Data&Method_2012'!H257 -> 0 | R9: ='PSUT_Data&Method_2012'!H275 -> 133.1154 | S9: ='PSUT_Data&Method_2012'!H293 -> 588.77952 | T9: ='PSUT_Data&Method_2012'!H311 -> 0 | U9: ='PSUT_Data&Method_2012'!H329 -> 11.7096 | V9: ='PSUT_Data&Method_2012'!H347 -> 0 | W9: =SUM(C9:V9) -> 13998422 | X9: ='PSUT_Data&Method_2012'!H368 -> 40434.896 | Y9: ='PSUT_Data&Method_2012'!H386 -> 0 | AA9: =W9+X9+Y9 -> 14038857
B10: 1.i From water resources: | C10: ='PSUT_Data&Method_2012'!H6 -> 13562574 | D10: ='PSUT_Data&Method_2012'!H24 -> 1030.8589 | E10: ='PSUT_Data&Method_2012'!H42 -> 23609.925 | F10: ='PSUT_Data&Method_2012'!H60 -> 335270.17 | G10: ='PSUT_Data&Method_2012'!H78 -> 53008.786 | H10: ='PSUT_Data&Method_2012'!H96 -> 0 | I10: ='PSUT_Data&Method_2012'!H114 -> 0 | J10: ='PSUT_Data&Method_2012'!H132 -> 0 | K10: ='PSUT_Data&Method_2012'!H150 -> 0 | L10: ='PSUT_Data&Method_2012'!H168 -> 0 | M10: ='PSUT_Data&Method_2012'!H186 -> 0 | N10: ='PSUT_Data&Method_2012'!H204 -> 0 | O10: ='PSUT_Data&Method_2012'!H222 -> 0 | P10: ='PSUT_Data&Method_2012'!H240 -> 0 | Q10: ='PSUT_Data&Method_2012'!H258 -> 0 | R10: ='PSUT_Data&Method_2012'!H276 -> 133.1154 | S10: ='PSUT_Data&Method_2012'!H294 -> 90.790816 | T10: ='PSUT_Data&Method_2012'!H312 -> 0 | U10: ='PSUT_Data&Method_2012'!H330 -> 2.0736 | V10: ='PSUT_Data&Method_2012'!H348 -> 0 | W10: =SUM(C10:V10) -> 13975719 | X10: ='PSUT_Data&Method_2012'!H369 -> 39884.896 | Y10: ='PSUT_Data&Method_2012'!H387 -> 0 | AA10: =W10+X10+Y10 -> 14015604
B11: 1.i.1 Surface water | C11: ='PSUT_Data&Method_2012'!H7 -> 189335.69 | D11: ='PSUT_Data&Method_2012'!H25 -> 967.07073 | E11: ='PSUT_Data&Method_2012'!H43 -> 14844.848 | F11: ='PSUT_Data&Method_2012'!H61 -> 335270.17 | G11: ='PSUT_Data&Method_2012'!H79 -> 41023.931 | H11: ='PSUT_Data&Method_2012'!H97 -> 0 | I11: ='PSUT_Data&Method_2012'!H115 -> 0 | J11: ='PSUT_Data&Method_2012'!H133 -> 0 | K11: ='PSUT_Data&Method_2012'!H151 -> 0 | L11: ='PSUT_Data&Method_2012'!H169 -> 0 | M11: ='PSUT_Data&Method_2012'!H187 -> 0 | N11: ='PSUT_Data&Method_2012'!H205 -> 0 | O11: ='PSUT_Data&Method_2012'!H223 -> 0 | P11: ='PSUT_Data&Method_2012'!H241 -> 0 | Q11: ='PSUT_Data&Method_2012'!H259 -> 0 | R11: ='PSUT_Data&Method_2012'!H277 -> 0 | S11: ='PSUT_Data&Method_2012'!H295 -> 0 | T11: ='PSUT_Data&Method_2012'!H313 -> 0 | U11: ='PSUT_Data&Method_2012'!H331 -> 2.0736 | V11: ='PSUT_Data&Method_2012'!H349 -> 0 | W11: =SUM(C11:V11) -> 581443.79 | X11: ='PSUT_Data&Method_2012'!H370 -> 11301.441 | Y11: ='PSUT_Data&Method_2012'!H388 -> 0 | AA11: =W11+X11+Y11 -> 592745.23
B12: 1.i.1.a Lakes | C12: ='PSUT_Data&Method_2012'!H8 -> 13252.297 | D12: ='PSUT_Data&Method_2012'!H26 -> 0 | E12: ='PSUT_Data&Method_2012'!H44 -> 0 | F12: ='PSUT_Data&Method_2012'!H62 -> 0 | G12: ='PSUT_Data&Method_2012'!H80 -> 0 | H12: ='PSUT_Data&Method_2012'!H98 -> 0 | I12: ='PSUT_Data&Method_2012'!H116 -> 0 | J12: ='PSUT_Data&Method_2012'!H134 -> 0 | K12: ='PSUT_Data&Method_2012'!H152 -> 0 | L12: ='PSUT_Data&Method_2012'!H170 -> 0 | M12: ='PSUT_Data&Method_2012'!H188 -> 0 | N12: ='PSUT_Data&Method_2012'!H206 -> 0 | O12: ='PSUT_Data&Method_2012'!H224 -> 0 | P12: ='PSUT_Data&Method_2012'!H242 -> 0 | Q12: ='PSUT_Data&Method_2012'!H260 -> 0 | R12: ='PSUT_Data&Method_2012'!H278 -> 0 | S12: ='PSUT_Data&Method_2012'!H296 -> 0 | T12: ='PSUT_Data&Method_2012'!H314 -> 0 | U12: ='PSUT_Data&Method_2012'!H332 -> 0 | V12: ='PSUT_Data&Method_2012'!H350 -> 0 | W12: =SUM(C12:V12) -> 13252.297 | X12: ='PSUT_Data&Method_2012'!H371 -> 5040 | Y12: ='PSUT_Data&Method_2012'!H389 -> 0 | AA12: =W12+X12+Y12 -> 18292.297
B13: 1.i.1.b Rivers | C13: ='PSUT_Data&Method_2012'!H9 -> 109804.75 | D13: ='PSUT_Data&Method_2012'!H27 -> 967.07073 | E13: ='PSUT_Data&Method_2012'!H45 -> 11482.405 | F13: ='PSUT_Data&Method_2012'!H63 -> 145951.64 | G13: ='PSUT_Data&Method_2012'!H81 -> 41023.931 | H13: ='PSUT_Data&Method_2012'!H99 -> 0 | I13: ='PSUT_Data&Method_2012'!H117 -> 0 | J13: ='PSUT_Data&Method_2012'!H135 -> 0 | K13: ='PSUT_Data&Method_2012'!H153 -> 0 | L13: ='PSUT_Data&Method_2012'!H171 -> 0 | M13: ='PSUT_Data&Method_2012'!H189 -> 0 | N13: ='PSUT_Data&Method_2012'!H207 -> 0 | O13: ='PSUT_Data&Method_2012'!H225 -> 0 | P13: ='PSUT_Data&Method_2012'!H243 -> 0 | Q13: ='PSUT_Data&Method_2012'!H261 -> 0 | R13: ='PSUT_Data&Method_2012'!H279 -> 0 | S13: ='PSUT_Data&Method_2012'!H297 -> 0 | T13: ='PSUT_Data&Method_2012'!H315 -> 0 | U13: ='PSUT_Data&Method_2012'!H333 -> 2.0736 | V13: ='PSUT_Data&Method_2012'!H351 -> 0 | W13: =SUM(C13:V13) -> 309231.87 | X13: ='PSUT_Data&Method_2012'!H372 -> 5116 | Y13: ='PSUT_Data&Method_2012'!H390 -> 0 | AA13: =W13+X13+Y13 -> 314347.87
B14: 1.i.1.c Reservoirs (Dams, ponds, ..) | C14: ='PSUT_Data&Method_2012'!H10 -> 47346.795 | D14: ='PSUT_Data&Method_2012'!H28 -> 0 | E14: ='PSUT_Data&Method_2012'!H46 -> 0 | F14: ='PSUT_Data&Method_2012'!H64 -> 189318.53 | G14: ='PSUT_Data&Method_2012'!H82 -> 0 | H14: ='PSUT_Data&Method_2012'!H100 -> 0 | I14: ='PSUT_Data&Method_2012'!H118 -> 0 | J14: ='PSUT_Data&Method_2012'!H136 -> 0 | K14: ='PSUT_Data&Method_2012'!H154 -> 0 | L14: ='PSUT_Data&Method_2012'!H172 -> 0 | M14: ='PSUT_Data&Method_2012'!H190 -> 0 | N14: ='PSUT_Data&Method_2012'!H208 -> 0 | O14: ='PSUT_Data&Method_2012'!H226 -> 0 | P14: ='PSUT_Data&Method_2012'!H244 -> 0 | Q14: ='PSUT_Data&Method_2012'!H262 -> 0 | R14: ='PSUT_Data&Method_2012'!H280 -> 0 | S14: ='PSUT_Data&Method_2012'!H298 -> 0 | T14: ='PSUT_Data&Method_2012'!H316 -> 0 | U14: ='PSUT_Data&Method_2012'!H334 -> 0 | V14: ='PSUT_Data&Method_2012'!H352 -> 0 | W14: =SUM(C14:V14) -> 236665.33 | X14: ='PSUT_Data&Method_2012'!H373 -> 11.441449 | Y14: ='PSUT_Data&Method_2012'!H391 -> 0 | AA14: =W14+X14+Y14 -> 236676.77
B15: 1.i.1.d Combined River & Reservoirs (Dams, ponds, ..) | C15: ='PSUT_Data&Method_2012'!H11 -> 18931.853 | D15: ='PSUT_Data&Method_2012'!H29 -> 0 | E15: ='PSUT_Data&Method_2012'!H47 -> 3362.443 | F15: ='PSUT_Data&Method_2012'!H65 -> 0 | G15: ='PSUT_Data&Method_2012'!H83 -> 0 | H15: ='PSUT_Data&Method_2012'!H101 -> 0 | I15: ='PSUT_Data&Method_2012'!H119 -> 0 | J15: ='PSUT_Data&Method_2012'!H137 -> 0 | K15: ='PSUT_Data&Method_2012'!H155 -> 0 | L15: ='PSUT_Data&Method_2012'!H173 -> 0 | M15: ='PSUT_Data&Method_2012'!H191 -> 0 | N15: ='PSUT_Data&Method_2012'!H209 -> 0 | O15: ='PSUT_Data&Method_2012'!H227 -> 0 | P15: ='PSUT_Data&Method_2012'!H245 -> 0 | Q15: ='PSUT_Data&Method_2012'!H263 -> 0 | R15: ='PSUT_Data&Method_2012'!H281 -> 0 | S15: ='PSUT_Data&Method_2012'!H299 -> 0 | T15: ='PSUT_Data&Method_2012'!H317 -> 0 | U15: ='PSUT_Data&Method_2012'!H335 -> 0 | V15: ='PSUT_Data&Method_2012'!H353 -> 0 | W15: =SUM(C15:V15) -> 22294.296 | X15: ='PSUT_Data&Method_2012'!H374 -> 1134 | Y15: ='PSUT_Data&Method_2012'!H392 -> 0 | AA15: =W15+X15+Y15 -> 23428.296
B16: 1.i.2 Groundwater | C16: ='PSUT_Data&Method_2012'!H12 -> 13829.735 | D16: ='PSUT_Data&Method_2012'!H30 -> 63.78813 | E16: ='PSUT_Data&Method_2012'!H48 -> 8765.0769 | F16: ='PSUT_Data&Method_2012'!H66 -> 0 | G16: ='PSUT_Data&Method_2012'!H84 -> 11984.856 | H16: ='PSUT_Data&Method_2012'!H102 -> 0 | I16: ='PSUT_Data&Method_2012'!H120 -> 0 | J16: ='PSUT_Data&Method_2012'!H138 -> 0 | K16: ='PSUT_Data&Method_2012'!H156 -> 0 | L16: ='PSUT_Data&Method_2012'!H174 -> 0 | M16: ='PSUT_Data&Method_2012'!H192 -> 0 | N16: ='PSUT_Data&Method_2012'!H210 -> 0 | O16: ='PSUT_Data&Method_2012'!H228 -> 0 | P16: ='PSUT_Data&Method_2012'!H246 -> 0 | Q16: ='PSUT_Data&Method_2012'!H264 -> 0 | R16: ='PSUT_Data&Method_2012'!H282 -> 133.1154 | S16: ='PSUT_Data&Method_2012'!H300 -> 90.790816 | T16: ='PSUT_Data&Method_2012'!H318 -> 0 | U16: ='PSUT_Data&Method_2012'!H336 -> 0 | V16: ='PSUT_Data&Method_2012'!H354 -> 0 | W16: =SUM(C16:V16) -> 34867.362 | X16: ='PSUT_Data&Method_2012'!H375 -> 28583.455 | Y16: ='PSUT_Data&Method_2012'!H393 -> 0 | AA16: =W16+X16+Y16 -> 63450.817
B17: 1.i.2a From Boreholes | C17: ='PSUT_Data&Method_2012'!H13 -> 4243.3497 | D17: ='PSUT_Data&Method_2012'!H31 -> 0 | E17: ='PSUT_Data&Method_2012'!H49 -> 3249.3012 | F17: ='PSUT_Data&Method_2012'!H67 -> 0 | G17: ='PSUT_Data&Method_2012'!H85 -> 0 | H17: ='PSUT_Data&Method_2012'!H103 -> 0 | I17: ='PSUT_Data&Method_2012'!H121 -> 0 | J17: ='PSUT_Data&Method_2012'!H139 -> 0 | K17: ='PSUT_Data&Method_2012'!H157 -> 0 | L17: ='PSUT_Data&Method_2012'!H175 -> 0 | M17: ='PSUT_Data&Method_2012'!H193 -> 0 | N17: ='PSUT_Data&Method_2012'!H211 -> 0 | O17: ='PSUT_Data&Method_2012'!H229 -> 0 | P17: ='PSUT_Data&Method_2012'!H247 -> 0 | Q17: ='PSUT_Data&Method_2012'!H265 -> 0 | R17: ='PSUT_Data&Method_2012'!H283 -> 126.45963 | S17: ='PSUT_Data&Method_2012'!H301 -> 18.158163 | T17: ='PSUT_Data&Method_2012'!H319 -> 0 | U17: ='PSUT_Data&Method_2012'!H337 -> 0 | V17: ='PSUT_Data&Method_2012'!H355 -> 0 | W17: =SUM(C17:V17) -> 7637.2687 | X17: ='PSUT_Data&Method_2012'!H376 -> 3658.8526 | Y17: ='PSUT_Data&Method_2012'!H394 -> 0 | AA17: =W17+X17+Y17 -> 11296.121
B18: 1.i.2b From Springs | C18: ='PSUT_Data&Method_2012'!H14 -> 9586.3855 | D18: ='PSUT_Data&Method_2012'!H32 -> 63.78813 | E18: ='PSUT_Data&Method_2012'!H50 -> 5515.7757 | F18: ='PSUT_Data&Method_2012'!H68 -> 0 | G18: ='PSUT_Data&Method_2012'!H86 -> 11984.856 | H18: ='PSUT_Data&Method_2012'!H104 -> 0 | I18: ='PSUT_Data&Method_2012'!H122 -> 0 | J18: ='PSUT_Data&Method_2012'!H140 -> 0 | K18: ='PSUT_Data&Method_2012'!H158 -> 0 | L18: ='PSUT_Data&Method_2012'!H176 -> 0 | M18: ='PSUT_Data&Method_2012'!H194 -> 0 | N18: ='PSUT_Data&Method_2012'!H212 -> 0 | O18: ='PSUT_Data&Method_2012'!H230 -> 0 | P18: ='PSUT_Data&Method_2012'!H248 -> 0 | Q18: ='PSUT_Data&Method_2012'!H266 -> 0 | R18: ='PSUT_Data&Method_2012'!H284 -> 6.65577 | S18: ='PSUT_Data&Method_2012'!H302 -> 72.632652 | T18: ='PSUT_Data&Method_2012'!H320 -> 0 | U18: ='PSUT_Data&Method_2012'!H338 -> 0 | V18: ='PSUT_Data&Method_2012'!H356 -> 0 | W18: =SUM(C18:V18) -> 27230.093 | X18: ='PSUT_Data&Method_2012'!H377 -> 24924.602 | Y18: ='PSUT_Data&Method_2012'!H395 -> 0 | AA18: =W18+X18+Y18 -> 52154.696
... B22: 1.ii.2 Abstraction from the sea | C22: ='PSUT_Data&Method_2012'!H18 -> 0 | D22: ='PSUT_Data&Method_2012'!H36 -> 0 | E22: ='PSUT_Data&Method_2012'!H54 -> 0 | F22: ='PSUT_Data&Method_2012'!H72 -> 0 | G22: ='PSUT_Data&Method_2012'!H90 -> 0 | H22: ='PSUT_Data&Method_2012'!H108 -> 0 | I22: ='PSUT_Data&Method_2012'!H126 -> 0 | J22: ='PSUT_Data&Method_2012'!H144 -> 0 | K22: ='PSUT_Data&Method_2012'!H162 -> 0 | L22: ='PSUT_Data&Method_2012'!H180 -> 0 | M22: ='PSUT_Data&Method_2012'!H198 -> 0 | N22: ='PSUT_Data&Method_2012'!H216 -> 0 | O22: ='PSUT_Data&Method_2012'!H234 -> 0 | P22: ='PSUT_Data&Method_2012'!H252 -> 0 | Q22: ='PSUT_Data&Method_2012'!H270 -> 0 | R22: ='PSUT_Data&Method_2012'!H288 -> 0 | S22: ='PSUT_Data&Method_2012'!H306 -> 0 | T22: ='PSUT_Data&Method_2012'!H324 -> 0 | U22: ='PSUT_Data&Method_2012'!H342 -> 0 | V22: ='PSUT_Data&Method_2012'!H360 -> 0 | W22: =SUM(C22:V22) -> 0 | X22: ='PSUT_Data&Method_2012'!H381 -> 0 | Y22: ='PSUT_Data&Method_2012'!H399 -> 0 | AA22: =W22+X22+Y22 -> 0
A23: Within the economy | B23: 2. Use of water received from other economic units | C23: ='PSUT_Data&Method_2012'!H19 -> 90250 | D23: ='PSUT_Data&Method_2012'!H37 -> 0 | E23: ='PSUT_Data&Method_2012'!H55 -> 642763.79 | F23: ='PSUT_Data&Method_2012'!H73 -> 0 | G23: ='PSUT_Data&Method_2012'!H91 -> 0 | H23: ='PSUT_Data&Method_2012'!H109 -> 0 | I23: ='PSUT_Data&Method_2012'!H127 -> 0 | J23: ='PSUT_Data&Method_2012'!H145 -> 0 | K23: ='PSUT_Data&Method_2012'!H163 -> 16672.61 | L23: ='PSUT_Data&Method_2012'!H181 -> 0 | M23: ='PSUT_Data&Method_2012'!H199 -> 76.030545 | N23: ='PSUT_Data&Method_2012'!H217 -> 0 | O23: ='PSUT_Data&Method_2012'!H235 -> 0 | P23: ='PSUT_Data&Method_2012'!H253 -> 0 | Q23: ='PSUT_Data&Method_2012'!H271 -> 0 | R23: ='PSUT_Data&Method_2012'!H289 -> 224372.33 | S23: ='PSUT_Data&Method_2012'!H307 -> 3720.9428 | T23: ='PSUT_Data&Method_2012'!H325 -> 0 | U23: ='PSUT_Data&Method_2012'!H343 -> 131.69367 | V23: ='PSUT_Data&Method_2012'!H361 -> 0 | W23: =SUM(C23:V23) -> 977987.39 | X23: ='PSUT_Data&Method_2012'!H382 -> 176061 | Y23: ='PSUT_Data&Method_2012'!H400 -> 6514.5681 | AA23: =W23+X23+Y23 -> 1160563
A24: 3. Total use of water (=1+2) | C24: =SUM(C6,C23) -> 13653631 | D24: =SUM(D6,D23) -> 22390.659 | E24: =SUM(E6,E23) -> 666401.91 | F24: =SUM(F6,F23) -> 335270.17 | G24: =SUM(G6,G23) -> 53008.786 | H24: =SUM(H6,H23) -> 0 | I24: =SUM(I6,I23) -> 0 | J24: =SUM(J6,J23) -> 0 | ... V24: =SUM(V6,V23) -> 0 | W24: =SUM(C24:V24) -> 14976409 | X24: =SUM(X6,X23) -> 216495.9 | Y24: =SUM(Y6,Y23) -> 6514.5681 | AA24: =W24+X24+Y24 -> 15199420
A26: Note: grey cells indicate zero entries by definition. | X26: Water Demand in 2012 | AA26: =AA24-(C24+F24) -> 1210519.1
A27: Note: The cels contain a formular, are not fillled (exception possible). | X27: with no consideration of rainfed agriculture and electricity demand
A28: Note: Where we have zero do not mean zero, just we did not get data but maybe should be available in different agencies except sea water.
A30: SEEAW Standard Table II: Physical supply table
A31: Physical units: 1000 m3
A32: '000 m3 | C32: Industries (by ISIC categories) | X32: Households | Y32: U. Activities of extraterritorial organizations and bodies | Z32: Rest of the world | AA32: Total
C33: A. Agriculture, forestry and fishing | D33: B. Mining and Quarrying | E33: C. Manufacturing | F33: D. Electricity, gas, steam and air conditioning supply | G33: E. Water supply (WASAC & AquaVirunga) | H33: F. Construction | I33: G. Wholesale and retail trade; repair of motor vehicles and motorcycles | J33: H. Transportation and storage | K33: I. Accommodation and food service activities | L33: J. Information and communication | M33: K. Banking and insurance activities | N33: L. Real estate activities | O33: M. Professional, scientific and technical activities | P33: N. Administrative and support service activities | Q33: O. Public administration and defence; compulsory social security | R33: P. Education | S33: Q. Human health and social work activities | T33: R. Arts, entertainment and recreation | U33: S. Other service activities (Religious & Burial) | V33: T. Activities of households as employers; undifferentiated goods- and services-producing activities of households for own use
C34: 1-3 | D34: 6-8 | E34: 10-13. 22, 32 | F34: 35 | G34: 36-38 | K34: 55-56 | M34: 64-66, 71-72, 75 | R34: 85 | S34: 86, 88 | U34: 94, 96 | W34: Total | X34: 98 | Y34: 99
A35: Within the economy | B35: 4. Supply of water to other economic units | C35: ='PSUT_Data&Method_2012'!H405 -> 0 | D35: ='PSUT_Data&Method_2012'!H414 -> 21271.126 | E35: ='PSUT_Data&Method_2012'!H423 -> 816.87563 | F35: ='PSUT_Data&Method_2012'!H432 -> 0 | G35: ='PSUT_Data&Method_2012'!H441 -> 0 | H35: ='PSUT_Data&Method_2012'!H450 -> 0 | I35: ='PSUT_Data&Method_2012'!H459 -> 0 | J35: ='PSUT_Data&Method_2012'!H468 -> 0 | K35: ='PSUT_Data&Method_2012'!H477 -> 12671.184 | L35: ='PSUT_Data&Method_2012'!H486 -> 0 | M35: ='PSUT_Data&Method_2012'!H495 -> 5.6106036 | N35: ='PSUT_Data&Method_2012'!H504 -> 0 | O35: ='PSUT_Data&Method_2012'!H513 -> 0 | P35: ='PSUT_Data&Method_2012'!H522 -> 0 | Q35: ='PSUT_Data&Method_2012'!H531 -> 0 | R35: ='PSUT_Data&Method_2012'!H540 -> 0 | S35: ='PSUT_Data&Method_2012'!H549 -> 0 | T35: ='PSUT_Data&Method_2012'!H558 -> 0 | U35: ='PSUT_Data&Method_2012'!H567 -> 0 | V35: ='PSUT_Data&Method_2012'!H576 -> 0 | W35: =SUM(C35:V35) -> 34764.796 | X35: ='PSUT_Data&Method_2012'!H588 -> 0 | Y35: ='PSUT_Data&Method_2012'!H597 -> 0 | AA35: =W35+X35+Y35 -> 34764.796
B36: 4.a Reused water | C36: ='PSUT_Data&Method_2012'!H406 -> 0 | D36: ='PSUT_Data&Method_2012'!H415 -> 21271.126 | E36: ='PSUT_Data&Method_2012'!H424 -> 346.29059 | F36: ='PSUT_Data&Method_2012'!H433 -> 0 | G36: ='PSUT_Data&Method_2012'!H442 -> 0 | H36: ='PSUT_Data&Method_2012'!H451 -> 0 | I36: ='PSUT_Data&Method_2012'!H460 -> 0 | J36: ='PSUT_Data&Method_2012'!H469 -> 0 | K36: ='PSUT_Data&Method_2012'!H478 -> 12671.184 | L36: ='PSUT_Data&Method_2012'!H487 -> 0 | M36: ='PSUT_Data&Method_2012'!H496 -> 2.3110417 | N36: ='PSUT_Data&Method_2012'!H505 -> 0 | O36: ='PSUT_Data&Method_2012'!H514 -> 0 | P36: ='PSUT_Data&Method_2012'!H523 -> 0 | Q36: ='PSUT_Data&Method_2012'!H532 -> 0 | R36: ='PSUT_Data&Method_2012'!H541 -> 0 | S36: ='PSUT_Data&Method_2012'!H550 -> 0 | T36: ='PSUT_Data&Method_2012'!H559 -> 0 | U36: ='PSUT_Data&Method_2012'!H568 -> 0 | V36: ='PSUT_Data&Method_2012'!H577 -> 0 | W36: =SUM(C36:V36) -> 34290.911 | X36: ='PSUT_Data&Method_2012'!H589 -> 0 | Y36: ='PSUT_Data&Method_2012'!H598 -> 0 | AA36: =W36+X36+Y36 -> 34290.911
B37: 4.b Wastewater to sewerage | C37: ='PSUT_Data&Method_2012'!H407 -> 0 | D37: ='PSUT_Data&Method_2012'!H416 -> 0 | E37: ='PSUT_Data&Method_2012'!H425 -> 470.58504 | F37: ='PSUT_Data&Method_2012'!H434 -> 0 | G37: ='PSUT_Data&Method_2012'!H443 -> 0 | H37: ='PSUT_Data&Method_2012'!H452 -> 0 | I37: ='PSUT_Data&Method_2012'!H461 -> 0 | J37: ='PSUT_Data&Method_2012'!H470 -> 0 | K37: ='PSUT_Data&Method_2012'!H479 -> 0 | L37: ='PSUT_Data&Method_2012'!H488 -> 0 | M37: ='PSUT_Data&Method_2012'!H497 -> 3.2995619 | N37: ='PSUT_Data&Method_2012'!H506 -> 0 | O37: ='PSUT_Data&Method_2012'!H515 -> 0 | P37: ='PSUT_Data&Method_2012'!H524 -> 0 | Q37: ='PSUT_Data&Method_2012'!H533 -> 0 | R37: ='PSUT_Data&Method_2012'!H542 -> 0 | S37: ='PSUT_Data&Method_2012'!H551 -> 0 | T37: ='PSUT_Data&Method_2012'!H560 -> 0 | U37: ='PSUT_Data&Method_2012'!H569 -> 0 | V37: ='PSUT_Data&Method_2012'!H578 -> 0 | W37: =SUM(C37:V37) -> 473.8846 | X37: ='PSUT_Data&Method_2012'!H590 -> 0 | Y37: ='PSUT_Data&Method_2012'!H599 -> 0 | AA37: =W37+X37+Y37 -> 473.8846
A38: To the environment | B38: 5. Total returns (= 5.a+5.b) | C38: ='PSUT_Data&Method_2012'!H408 -> 1529661.7 | D38: ='PSUT_Data&Method_2012'!H417 -> 54.21991 | E38: ='PSUT_Data&Method_2012'!H426 -> 514699.26 | F38: ='PSUT_Data&Method_2012'!H435 -> 318506.66 | G38: ='PSUT_Data&Method_2012'!H444 -> 2570.3302 | H38: ='PSUT_Data&Method_2012'!H453 -> 0 | I38: ='PSUT_Data&Method_2012'!H462 -> 0 | J38: ='PSUT_Data&Method_2012'!H471 -> 0 | K38: ='PSUT_Data&Method_2012'!H480 -> 301.01142 | L38: ='PSUT_Data&Method_2012'!H489 -> 0 | M38: ='PSUT_Data&Method_2012'!H498 -> 56.86862 | N38: ='PSUT_Data&Method_2012'!H507 -> 0 | O38: ='PSUT_Data&Method_2012'!H516 -> 0 | P38: ='PSUT_Data&Method_2012'!H525 -> 0 | Q38: ='PSUT_Data&Method_2012'!H534 -> 0 | R38: ='PSUT_Data&Method_2012'!H543 -> 179497.86 | S38: ='PSUT_Data&Method_2012'!H552 -> 3447.7778 | T38: ='PSUT_Data&Method_2012'!H561 -> 0 | U38: ='PSUT_Data&Method_2012'!H570 -> 10.714873 | V38: ='PSUT_Data&Method_2012'!H579 -> 0 | W38: =SUM(C38:V38) -> 2548806.4 | X38: ='PSUT_Data&Method_2012'!H591 -> 82781 | Y38: ='PSUT_Data&Method_2012'!H600 -> 5211.6545 | AA38: =W38+X38+Y38 -> 2636799.1
B39: 5.a To water resources | C39: ='PSUT_Data&Method_2012'!H409 -> 1529661.7 | D39: ='PSUT_Data&Method_2012'!H418 -> 54.21991 | E39: ='PSUT_Data&Method_2012'!H427 -> 514699.26 | F39: ='PSUT_Data&Method_2012'!H436 -> 318506.66 | G39: ='PSUT_Data&Method_2012'!H445 -> 2570.3302 | H39: ='PSUT_Data&Method_2012'!H454 -> 0 | I39: ='PSUT_Data&Method_2012'!H463 -> 0 | J39: ='PSUT_Data&Method_2012'!H472 -> 0 | K39: ='PSUT_Data&Method_2012'!H481 -> 301.01142 | L39: ='PSUT_Data&Method_2012'!H490 -> 0 | M39: ='PSUT_Data&Method_2012'!H499 -> 56.86862 | N39: ='PSUT_Data&Method_2012'!H508 -> 0 | O39: ='PSUT_Data&Method_2012'!H517 -> 0 | P39: ='PSUT_Data&Method_2012'!H526 -> 0 | Q39: ='PSUT_Data&Method_2012'!H535 -> 0 | R39: ='PSUT_Data&Method_2012'!H544 -> 179497.86 | S39: ='PSUT_Data&Method_2012'!H553 -> 3447.7778 | T39: ='PSUT_Data&Method_2012'!H562 -> 0 | U39: ='PSUT_Data&Method_2012'!H571 -> 10.714873 | V39: ='PSUT_Data&Method_2012'!H580 -> 0 | W39: =SUM(C39:V39) -> 2548806.4 | X39: ='PSUT_Data&Method_2012'!H592 -> 72433 | Y39: ='PSUT_Data&Method_2012'!H601 -> 5211.6545 | AA39: =W39+X39+Y39 -> 2626451.1
B40: 5.a.1 Surface water | C40: ='PSUT_Data&Method_2012'!H410 -> 769541.4 | D40: ='PSUT_Data&Method_2012'!H419 -> 1.2757626 | E40: ='PSUT_Data&Method_2012'!H428 -> 514526.07 | F40: ='PSUT_Data&Method_2012'!H437 -> 318506.66 | G40: ='PSUT_Data&Method_2012'!H446 -> 2570.3302 | H40: ='PSUT_Data&Method_2012'!H455 -> 0 | I40: ='PSUT_Data&Method_2012'!H464 -> 0 | J40: ='PSUT_Data&Method_2012'!H473 -> 0 | K40: ='PSUT_Data&Method_2012'!H482 -> 159.0913 | L40: ='PSUT_Data&Method_2012'!H491 -> 0 | M40: ='PSUT_Data&Method_2012'!H500 -> 46.976259 | N40: ='PSUT_Data&Method_2012'!H509 -> 0 | O40: ='PSUT_Data&Method_2012'!H518 -> 0 | P40: ='PSUT_Data&Method_2012'!H527 -> 0 | Q40: ='PSUT_Data&Method_2012'!H536 -> 0 | R40: ='PSUT_Data&Method_2012'!H545 -> 44209.77 | S40: ='PSUT_Data&Method_2012'!H554 -> 0 | T40: ='PSUT_Data&Method_2012'!H563 -> 0 | U40: ='PSUT_Data&Method_2012'!H572 -> 1.1818737 | V40: ='PSUT_Data&Method_2012'!H581 -> 0 | W40: =SUM(C40:V40) -> 1649562.8 | X40: ='PSUT_Data&Method_2012'!H593 -> 41390 | Y40: ='PSUT_Data&Method_2012'!H602 -> 4688.7653 | AA40: =W40+X40+Y40 -> 1695641.5
B41: 5.a.2 Groundwater | C41: ='PSUT_Data&Method_2012'!H411 -> 81951.3 | D41: ='PSUT_Data&Method_2012'!H420 -> 1.9136439 | E41: ='PSUT_Data&Method_2012'!H429 -> 166.95464 | F41: ='PSUT_Data&Method_2012'!H438 -> 0 | G41: ='PSUT_Data&Method_2012'!H447 -> 0 | H41: ='PSUT_Data&Method_2012'!H456 -> 0 | I41: ='PSUT_Data&Method_2012'!H465 -> 0 | J41: ='PSUT_Data&Method_2012'!H474 -> 0 | K41: ='PSUT_Data&Method_2012'!H483 -> 0 | L41: ='PSUT_Data&Method_2012'!H492 -> 0 | M41: ='PSUT_Data&Method_2012'!H501 -> 4.7351203 | N41: ='PSUT_Data&Method_2012'!H510 -> 0 | O41: ='PSUT_Data&Method_2012'!H519 -> 0 | P41: ='PSUT_Data&Method_2012'!H528 -> 0 | Q41: ='PSUT_Data&Method_2012'!H537 -> 0 | R41: ='PSUT_Data&Method_2012'!H546 -> 135288.09 | S41: ='PSUT_Data&Method_2012'!H555 -> 3201.048 | T41: ='PSUT_Data&Method_2012'!H564 -> 0 | U41: ='PSUT_Data&Method_2012'!H573 -> 9.3718229 | V41: ='PSUT_Data&Method_2012'!H582 -> 0 | W41: =SUM(C41:V41) -> 220623.42 | X41: ='PSUT_Data&Method_2012'!H594 -> 20695 | Y41: ='PSUT_Data&Method_2012'!H603 -> 522.8892 | AA41: =W41+X41+Y41 -> 241841.31
B42: 5.a.3 Soil water | C42: ='PSUT_Data&Method_2012'!H412 -> 678169.03 | D42: ='PSUT_Data&Method_2012'!H421 -> 51.030504 | E42: ='PSUT_Data&Method_2012'!H430 -> 6.2332307 | F42: ='PSUT_Data&Method_2012'!H439 -> 0 | G42: ='PSUT_Data&Method_2012'!H448 -> 0 | H42: ='PSUT_Data&Method_2012'!H457 -> 0 | I42: ='PSUT_Data&Method_2012'!H466 -> 0 | J42: ='PSUT_Data&Method_2012'!H475 -> 0 | K42: ='PSUT_Data&Method_2012'!H484 -> 141.92012 | L42: ='PSUT_Data&Method_2012'!H493 -> 0 | M42: ='PSUT_Data&Method_2012'!H502 -> 5.1572408 | N42: ='PSUT_Data&Method_2012'!H511 -> 0 | O42: ='PSUT_Data&Method_2012'!H520 -> 0 | P42: ='PSUT_Data&Method_2012'!H529 -> 0 | Q42: ='PSUT_Data&Method_2012'!H538 -> 0 | R42: ='PSUT_Data&Method_2012'!H547 -> 0 | S42: ='PSUT_Data&Method_2012'!H556 -> 246.72984 | T42: ='PSUT_Data&Method_2012'!H565 -> 0 | U42: ='PSUT_Data&Method_2012'!H574 -> 0.16117641 | V42: ='PSUT_Data&Method_2012'!H583 -> 0 | W42: =SUM(C42:V42) -> 678620.26 | X42: ='PSUT_Data&Method_2012'!H595 -> 10348 | Y42: ='PSUT_Data&Method_2012'!H604 -> 0 | AA42: =W42+X42+Y42 -> 688968.26
B43: 5.b To other sources (e.g. sea water) | C43: ='PSUT_Data&Method_2012'!H413 -> 0 | D43: ='PSUT_Data&Method_2012'!H422 -> 0 | E43: ='PSUT_Data&Method_2012'!H431 -> 0 | F43: ='PSUT_Data&Method_2012'!H440 -> 0 | G43: ='PSUT_Data&Method_2012'!H449 -> 0 | H43: ='PSUT_Data&Method_2012'!H458 -> 0 | I43: ='PSUT_Data&Method_2012'!H467 -> 0 | J43: ='PSUT_Data&Method_2012'!H476 -> 0 | K43: ='PSUT_Data&Method_2012'!H485 -> 0 | L43: ='PSUT_Data&Method_2012'!H494 -> 0 | M43: ='PSUT_Data&Method_2012'!H503 -> 0 | N43: ='PSUT_Data&Method_2012'!H512 -> 0 | O43: ='PSUT_Data&Method_2012'!H521 -> 0 | P43: ='PSUT_Data&Method_2012'!H530 -> 0 | Q43: ='PSUT_Data&Method_2012'!H539 -> 0 | R43: ='PSUT_Data&Method_2012'!H548 -> 0 | S43: ='PSUT_Data&Method_2012'!H557 -> 0 | T43: ='PSUT_Data&Method_2012'!H566 -> 0 | U43: ='PSUT_Data&Method_2012'!H575 -> 0 | V43: ='PSUT_Data&Method_2012'!H584 -> 0 | W43: =SUM(C43:V43) -> 0 | X43: ='PSUT_Data&Method_2012'!H596 -> 10348 | Y43: ='PSUT_Data&Method_2012'!H605 -> 0 | AA43: =W43+X43+Y43 -> 10348
A44: 6. Total supply of water (= 4+5) | C44: =SUM(C35,C38) -> 1529661.7 | D44: =SUM(D35,D38) -> 21325.346 | E44: =SUM(E35,E38) -> 515516.14 | F44: =SUM(F35,F38) -> 318506.66 | G44: =SUM(G35,G38) -> 2570.3302 | H44: =SUM(H35,H38) -> 0 | I44: =SUM(I35,I38) -> 0 | J44: =SUM(J35,J38) -> 0 | ... V44: =SUM(V35,V38) -> 0 | W44: =SUM(C44:V44) -> 2583571.2 | X44: =SUM(X35,X38) -> 82781 | Y44: =SUM(Y35,Y38) -> 5211.6545 | AA44: =W44+X44+Y44 -> 2671563.9
A45: 7. Consumption (3-6) | C45: =SUM(C24-C44) -> 12123969 | D45: =SUM(D24-D44) -> 1065.313 | E45: =SUM(E24-E44) -> 150885.77 | F45: =SUM(F24-F44) -> 16763.508 | G45: =SUM(G24-G44) -> 50438.456 | H45: =SUM(H24-H44) -> 0 | I45: =SUM(I24-I44) -> 0 | J45: =SUM(J24-J44) -> 0 | ... V45: =SUM(V24-V44) -> 0 | W45: =SUM(C45:V45) -> 12392838 | X45: =SUM(X24-X44) -> 133714.9 | Y45: =SUM(Y24-Y44) -> 1302.9136 | AA45: =W45+X45+Y45 -> 12527856
A47: Note: grey cells indicate zero entries by definition.
A48: Note: The cels contain a formular, are not fillled (exception possible).
A49: Note: Where we have zero do not mean zero, just we did not get data but maybe should be available in different agencies except sea water.

Sheet RBM&E-2017_S
H1: RBM&E Project
H2: Survey applied to a sample in order to verify the existing data available from on Springs WASAC and boreholes from IWRM.
H3: Available water' is taken from Rwanda - R-NWRMP2012.
H4: After these data are used to feed the model (SVR - Regression) in order to extrapolate to the entire population.
H6: IR: Small Scale Based upon list of irrigators from RAB
H8: See also Report: RBM&E_Final Report_Water Users and Uses_31.07.2017-1
R10: RBM&E 2017 Study Results
E11: usertype | F11: Usertype_FullName | H11: Sum of wateruse(m3) | I11: Province | R11: Reporting year is 2016
B12: Approach Taken | H12: usertype | I12: City of Kigali | J12: Eastern Province | K12: Northern Province | L12: Southern Province | M12: Western Province | N12: (blank) | O12: Grand Total | R12: Grand Total (m3) | S12: Grand Total (MCM) | V12: ISIC-Rev.4 ? | W12: Water type
B13: Population from MINIRENA. Full set (capacity of discharge from company installing) * (operation hours) | C13: 500* | E13: BH | F13: Borehole | H13: BH | N13: 5657799.6 | O13: 5657799.6 | R13: 5657799.6 | S13: =+R13/1000000 -> 5.6577996 | T13: Borehole | V13: … Various (mainly households) | W13: Groundwater
B14: Model (depending on volume washed) | E14: CWS | F14: Coffee Washing Station | H14: CWS | N14: 11948637 | O14: 11948637 | R14: 11948637 | S14: =+R14/1000000 -> 11.948637 | T14: Coffee Washing Station | V14: 1079 - Manufacture of other food products n.e.c. | W14: Surface water (rivers)
B15: Full set (5% of water taken) | E15: HP | F15: Hydropower | H15: HP | N15: 1.5798275e+08 | O15: 1.5798275e+08 | R15: 1.5798275e+08 | S15: =+R15/1000000 -> 157.98275 | T15: Hydropower | V15: 3510 - Electric power generation, transmission and distribution | W15: Surface water (rivers)
A16: Full set | B16: Full set (large scale) & Modal (small scale) | E16: IR | F16: Irrigation | H16: IR | I16: 10096950 | J16: 84665830 | K16: 5401490 | L16: 70793300 | M16: 26910390 | N16: 24461005 | O16: 222328965 | R16: 222328965 | S16: =+R16/1000000 -> 222.32897 | T16: Irrigation | U16: ?? | V16: 01 (Division) - Crop and animal production, hunting and related service activities | W16: Surface water (rivers & lakes & AR)
B17: MINECOM (Commerce) list 300 for Industry. 30 were surveyed that use water. | E17: MF | F17: Manufacturing | H17: MF | I17: 819470.36 | J17: 3114144.6 | K17: 207001 | L17: 1488632 | M17: 1649985 | O17: 7279233 | R17: 7279233 | S17: =+R17/1000000 -> 7.279233 | T17: Manufacturing | V17: Section C - Manufacturing (Division 10 - 33) | W17: Groundwater & Surface water
B18: Model (operational time) | E18: MG | F18: Mining | H18: MG | N18: 1046788.5 | O18: 1046788.5 | R18: 1046788.5 | S18: =+R18/1000000 -> 1.0467885 | T18: Mining | V18: Section B - Mining and quarrying (Division 05 - 09) | W18: Surface water (rivers)
B19: Start from WASAC List of > 10.000 (9000 in operation). (capacity of discharge from company installing) * (operation hours) | E19: Spring | F19: Spring | H19: Spring | N19: 39118224 | O19: 39118224 | R19: 39118224 | S19: =+R19/1000000 -> 39.118224 | T19: Spring | V19: … Various (mainly agriculture) | W19: Groundwater
E20: WP | F20: Waterpond | H20: WP | N20: 29180 | O20: 29180 | R20: 29180 | S20: =+R20/1000000 -> 0.02918 | T20: Waterpond | V20: … Various | W20: Surface water (Artificial reservoir)
E21: WTP | F21: Water Treatment Plant for Public Water Supply | H21: WTP | N21: 54076940 | O21: 54076940 | R21: 54076940 | S21: =+R21/1000000 -> 54.07694 | T21: Water Treatment Plant for Public Water Supply | U21: ?? | V21: 36 (Division) - Water collection, treatment and supply | W21: Groundwater & Surface water
H22: Grand Total | I22: 10916420 | J22: 87779975 | K22: 5608491 | L22: 72281932 | M22: 28560375 | N22: 2.9432132e+08 | O22: 4.9946851e+08 | R22: 4.9946851e+08 | S22: =+R22/1000000 -> 499.46851 | T22: TOTAL
T24: As per RBM&E - study & Trend | U24: As per RBM&E - study & Trend | V24: As per RBM&E - study & Trend | W24: As per RBM&E - study & Trend | X24: As per RBM&E - study & Trend
Q25: Reporting year is 2016
Q26: Grand Total (*1000 m3) | R26: ISIC-Rev.4 ? | S26: Water type | T26: 2012 | U26: 2013 | V26: 2014 | W26: 2015 | X26: 2016
Q27: Borehole | R27: =R45 -> … Various (mainly households) | S27: Groundwater | T27: =+T45*1000 -> 5226.9323 | U27: =+U45*1000 -> 5331.4709 | V27: =+V45*1000 -> 5438.1003 | W27: =+W45*1000 -> 5546.8623 | X27: =+X45*1000 -> 5657.7996
Q28: Coffee Washing Station | R28: =R46 -> Section C - Manufacturing - 1079 - Manufacture of other food products n.e.c. | S28: Surface water (rivers) | T28: =+T46*1000 -> 11482.405 | U28: =+U46*1000 -> 11597.229 | V28: =+V46*1000 -> 11713.201 | W28: =+W46*1000 -> 11830.333 | X28: =+X46*1000 -> 11948.637
